Workbook
Name ACQ_AMORTIZATION: Financing!$D$19
Name ACQ_FEE: Assumptions!$I$9
Name ACQ_LOAN_FEE: Financing!$D$16
Name ACQ_LOAN_TERM: Financing!$D$20
Name ACQ_PREPAY_PENALTY: Financing!$D$18
Name ACQ_PREPAY_WINDOW: Financing!$D$17
Name AM_FEE: Assumptions!$F$13
Name CAP_RESERVES: Assumptions!$D$34
Name CLOSE_DATE: Assumptions!$I$13
Name CLOSING_COSTS: Assumptions!$I$10
Name CM_FEE: Assumptions!$F$14
Name COSTS_OF_SALE: Assumptions!$L$7
Name CURR_ASSESSED_VAL: Assumptions!$B$52
Name DISTRIBUTION_FREQ: Assumptions!$L$12
Name EXIT_CAP: Assumptions!$L$9
Name EXP_GROWTH: Assumptions!$E$32
Name FIXED_CHARGES: Assumptions!$B$51
Name HOLD_PERIOD: Assumptions!$M$8
Name IO_ACQ: Financing!$D$15
Name IO_MEZZ: Financing!$E$15
Name IO_REFI: Financing!$F$15
Name MEZZ_AMORTIZATION: Financing!$E$19
Name MEZZ_LOAN_FEE: Financing!$E$16
Name MEZZ_PREPAY_PENALTY: Financing!$E$18
Name MEZZ_PREPAY_WINDOW: Financing!$E$17
Name MGMT_FEE: Assumptions!$E$33
Name MGMT_FEEs: Assumptions!$E$33
Name NLA: Assumptions!$C$5
Name PROPERTY_TAX_RATE: Assumptions!$B$50
Name PURCH_PRICE: Assumptions!$I$7
Name REASSESSED_UPON_SALE: Assumptions!$B$55
Name REFI_AMORTIZATION: Financing!$F$19
Name REFI_LOAN_FEE: Financing!$F$16
Name REFI_LOAN_TERM: Financing!$F$20
Name REFI_PREPAY_PENALTY: Financing!$F$18
Name REFI_PREPAY_WINDOW: Financing!$F$17
Name TOTAL_COST: Summary!$E$7
Name units: [3]Rents!$C$51
Name Units: Rent!$D$67
Name VALUE_ASSESSED: Assumptions!$B$54
Name WORKING_CAP: Assumptions!$I$11
Name YEAR_REASSESSED: Assumptions!$B$53

Sheet Checks
A1: Checks
A2: Monthly CF Equal Annual CF | B2: =ABS(SUM('Combined CF'!$O$6:$O$60)-SUM('Combined CF'!$A$6:$A$60))<0.01 -> TRUE
A3: Equity Investment = Sum of All Negative Cash Flows | B3: =ABS(Summary!E22+SUMIF('Combined CF'!Q60:ES60,"<"&0))<0.01 -> TRUE
A4: Expenses Sheet Row 26,27 Formula(Property Tax+Mngt Fee) = Row 21,22 Value(Property Tax+Mngt Fee) | B4: =ABS(SUM(Expenses!B20:NI21)-SUM(Expenses!B15:NI16))<0.01 -> TRUE
A5: Net Working Capital Equals Working Capital Distributed | B5: =ABS(WORKING_CAP-'Combined CF'!A48)<0.01 -> TRUE
B6: =SUMIF(Expenses!$B$12:$NI$12,1,Expenses!$B$20:$NI$20)+'CFS-Main Page'!G39-Assumptions!B45<0.01 -> TRUE
A9: Underwriting Notes & Assumptions
A11: General Modeling Notes
A12: 1. We have used the Rent comps from Hello Data and added the screenshot for the rent comps as well.
A13: 2. We made a change on Rent page to choose from either of Comps or RR market rent in Col L. Also you can compare the rents of Classic vs renovated in the Rows F5 to O6.
A14: 3. We have added a switch for the Taxes in the Pro Forma Assumptions to choose between T12 taxes and taxes on Reassessed value.
A15: 4. Broker numbers are not added as there was no Broker OM available.
A16: Our Assumptions
A17: General Assumptions
A18: 1. General assumptions (including market rent growth, expense growth, tax growth, and property management fees) are consistent with those applied in the prior model.
A19: 2. For financing, we have a 3 year I/O period and all in rate of 5.41% (5 year Treasury Yield of 4.007% + 1.40% spread).
A20: 3. Market Rents (For new and renewal leases) have been taken as $34.27 as per Colliers' 2025 Q4 Retail Report for the Downtown submarket (Over 10K Sqft).
A21: Asking Price and Exit Assumptions
... A32: Question to the team Catalyst

Sheet Summary
D1: Summary Details | G1: Levered Return Metrics | R1: Retail/Office Rent Roll (Consolidated) | Y1: Sensitivity Intervals | AB1: Tenant | AC1: Percentage of Base Rent
D2: Purchase Price | E2: =Assumptions!I7 -> 180000000 | G2: IRR | H2: =XIRR('Combined CF'!$Q$60:$ES$60,'Combined CF'!$Q$4:$ES$4) -> 0.14881178 | R2: Suite | S2: Tenant | T2: SF | U2: In-Place Rent/SF | V2: Reimbursement | W2: Expiration | Y2: Hold Period | Z2: 12 | AB2: =S3 -> Health PC Reserve | AC2: =U3*T3/($T$13*$U$13) -> 0.20427929
D3: Purchase Price Per SF | E3: =Assumptions!I8 -> 13447.889 | G3: Equity Multiple | H3: =SUMIF('Combined CF'!$Q$60:$ES$60,">"&0)/-SUMIF('Combined CF'!$Q$60:$ES$60,"<"&0) -> 1.926724 | R3: =Leases!A5 -> 1 | S3: =Leases!C5 -> Health PC Reserve | T3: =Leases!B5 -> 2583 | U3: =IFERROR(Leases!$D$170/T3,0) -> 2.639375 | V3: =Leases!G5 -> NNN | W3: =Leases!E5 -> 47330 | Y3: Exit Cap | Z3: 0.005 | AB3: =S4 -> Uptown Veterinary Hospital | AC3: =U4*T4/($T$13*$U$13) -> 0.21943263
D4: Going-In Cap Rate | E4: =Assumptions!I12 -> 0.028285466 | G4: Average Cash-on-Cash Return | H4: =AVERAGEIF('Combined CF'!$D$2:$M$2,"<="&HOLD_PERIOD/12,'Combined CF'!$D$63:$M$63) -> 0.039588165 | R4: =Leases!A21 -> 2 | S4: =Leases!C21 -> Uptown Veterinary Hospital | T4: =Leases!B21 -> 3367 | U4: =IFERROR(Leases!$D$186/Summary!T4,0) -> 2.175 | V4: =Leases!G21 -> NNN | W4: =Leases!E21 -> 46265 | AB4: =S5 -> Indigo Tea and Coffee Co. Grounds, LLC | AC4: =U5*T5/($T$13*$U$13) -> 0.19271751
D5: Going-In DSCR | E5: ='Combined CF'!R14/-'Combined CF'!R41 -> 0.77802392 | R5: =Leases!$A$37 -> 3 | S5: =Leases!$C$37 -> Indigo Tea and Coffee Co. Grounds, LLC | T5: =Leases!$B$37 -> 2437 | U5: =IFERROR(Leases!$D$202/Summary!T5,0) -> 2.6391667 | V5: =Leases!$G$37 -> NNN | W5: =Leases!$E$37 -> 46721 | Y5: Chart Metrics | AB5: =S6 -> Raghav Sundaresh | AC5: =U6*T6/($T$13*$U$13) -> 0.19140661
D6: Going-In Debt Yield | E6: ='Combined CF'!D14/'Combined CF'!C39 -> 0.040407809 | G6: Unlevered Return Metrics | R6: =Leases!$A$53 -> 4 | S6: =Leases!$C$53 -> Raghav Sundaresh | T6: =Leases!$B$53 -> 2568 | U6: =IFERROR(Leases!$D$218/Summary!T6,0) -> 2.4875 | V6: =Leases!$G$53 -> NNN | W6: =Leases!$E$53 -> 47330 | Y6: Metric | Z6: Net Operating Income | AB6: =S7 -> Pizzeria Sapienza CLT, LLC | AC6: =U7*T7/($T$13*$U$13) -> 0.19216395
D7: Total Cost | E7: =Assumptions!F27 -> 1.8509946e+08 | G7: IRR | H7: =XIRR('Combined CF'!$Q$36:$ES$36,'Combined CF'!$Q$4:$ES$4) -> 0.093561557 | R7: =Leases!$A$69 -> 5 | S7: =Leases!$C$69 -> Pizzeria Sapienza CLT, LLC | T7: =Leases!$B$69 -> 2430 | U7: =IFERROR(Leases!$D$234/Summary!T7,0) -> 2.6391667 | V7: =Leases!$G$69 -> NNN | W7: =Leases!$E$69 -> 46873 | AB7: =S8 -> 0 | AC7: =U8*T8/($T$13*$U$13) -> 0
D8: All-In Basis Per SF | E8: =E7/Assumptions!C5 -> 13828.873 | G8: Equity Multiple | H8: =SUMIF('Combined CF'!$Q$36:$ES$36,">"&0)/-SUMIF('Combined CF'!$Q$36:$ES$36,"<"&0) -> 1.5042331 | R8: =Leases!$A$85 -> 0 | S8: =Leases!$C$85 -> 0 | T8: =Leases!$B$85 -> 0 | U8: =IFERROR(Leases!$D$250/Summary!T8,0) -> 0 | V8: =Leases!$G$85 -> 0 | W8: =Leases!$E$85 -> 0 | AB8: =S9 -> 0 | AC8: =U9*T9/($T$13*$U$13) -> 0
G9: Average Cash-on-Cash Return | H9: =AVERAGEIF(CF!D2:M2,"<="&HOLD_PERIOD/12,'Combined CF'!$D$62:$M$62) -> 0.055575425 | R9: =Leases!$A$101 -> 0 | S9: =Leases!$C$101 -> 0 | T9: =Leases!$B$101 -> 0 | U9: =IFERROR(Leases!$D$266/Summary!T9,0) -> 0 | V9: =Leases!$G$101 -> 0 | W9: =Leases!$E$101 -> 0 | AB9: =S10 -> 0 | AC9: =U10*T10/($T$13*$U$13) -> 0
D10: Capital Budget Breakdown | R10: =Leases!$A$117 -> 0 | S10: =Leases!$C$117 -> 0 | T10: =Leases!$B$117 -> 0 | U10: =IFERROR(Leases!$D$282/Summary!T10,0) -> 0 | V10: =Leases!$G$117 -> 0 | W10: =Leases!$E$117 -> 0 | AB10: =S11 -> 0 | AC10: =U11*T11/($T$13*$U$13) -> 0
D11: Common Area Capital Budget | E11: ='Construction Budget'!C19 -> 0 | G11: Sale Details | R11: =Leases!$A$133 -> 0 | S11: =Leases!$C$133 -> 0 | T11: =Leases!$B$133 -> 0 | U11: =IFERROR(Leases!$D$298/Summary!T11,0) -> 0 | V11: =Leases!$G$133 -> 0 | W11: =Leases!$E$133 -> 0 | AB11: =S12 -> 0 | AC11: =U12*T12/($T$13*$U$13) -> 0
D12: Common Area Capital Budget Per SF | E12: =+E11/Assumptions!C5 -> 0 | G12: Sale Date | H12: =HLOOKUP(HOLD_PERIOD,CF!R4:ET5,2,0) -> 47968 | R12: =Leases!$A$149 -> 0 | S12: =Leases!$C$149 -> 0 | T12: =Leases!$B$149 -> 0 | U12: =IFERROR(Leases!$D$314/Summary!T12,0) -> 0 | V12: =Leases!$G$149 -> 0 | W12: =Leases!$E$149 -> 0
D13: TI/LC Costs | E13: =-SUM(CF!P31:P32) -> 457082.1 | G13: Exit Cap Rate | H13: =EXIT_CAP -> 0.0575 | S13: Total/Weighted Average | T13: =SUM(T3:T12) -> 13385 | U13: =SUMPRODUCT($T$3:$T$12,U3:U12)/T13 -> 2.4933474 | W13: =SUMPRODUCT($T$3:$T$12,W3:W12)/T13 -> 46868.252
D14: TI/LC Costs Per SF | E14: =E13/Assumptions!C5 -> 34.148831 | G14: Cap Rate Expansion Per Year | H14: =(H13-Assumptions!I12)/(Assumptions!M8/12) -> 0.0058429068
D15: Total Capital Costs | E15: =SUM(E11,E13) -> 457082.1 | G15: Sale Price | H15: ='Combined CF'!A33 -> 2.2520356e+08
D16: Total Capital Costs Per SF | E16: =E15/Assumptions!C5 -> 34.148831 | G16: Sale Price Per SF | H16: =H15/Assumptions!C5 -> 16825.069
D17: Month Construction Starts | E17: ='Construction Budget'!E19 -> 0 | G17: Costs of Sale | H17: =-'Combined CF'!A34 -> 2252035.6
D18: Month Construction Ends | E18: ='Construction Budget'!F19 -> 0 | G18: Value CAGR | H18: =RATE(Assumptions!M8/12,,-Assumptions!I7,H15,0,) -> 0.04582868
D20: Total Sources | G20: IRR Partitioning
D21: Acquisition/Mezzanine Loan Proceeds | E21: ='Combined CF'!O39+'Combined CF'!O40 -> 1.26e+08 | G21: From Sale/Financing | H21: =MAX(MIN('Combined CF'!O66/SUM('Combined CF'!O65:O66),1),0) -> 0.86772518
D22: Equity | E22: =E24-E21 -> 59099459 | G22: From Operating CF | H22: =MAX(MIN('Combined CF'!O65/SUM('Combined CF'!O65:O66),1),0) -> 0.13227482
D24: Total Sources | E24: =E36 -> 1.8509946e+08
D26: Total Uses
D27: Purchase Price | E27: =Assumptions!I7 -> 180000000
D28: Acquisition Fee | E28: =Assumptions!I9 -> 1800000
D29: Other Costs | E29: =SUM(Assumptions!F26,Assumptions!F22,Assumptions!F20) -> 0
D30: Construction Management Fee | E30: =-SUM('Combined CF'!R25:ES25) -> 0
D31: TI / LC Costs | E31: =SUM('Combined CF'!R57:ES57) -> 457082.1
D32: Construction Expenses | E32: =Assumptions!$F$25 -> 0
D33: Operating Shortfalls | E33: =SUM('Combined CF'!R56:ES56) -> 1582377
D34: Working Capital | E34: =+Assumptions!I11 -> 0
D35: Loan Fees | E35: =-'Combined CF'!Q43 -> 1260000
D36: Total Uses | E36: =SUM(E27:E35) -> 1.8509946e+08
D39: Month | E39: 1 | F39: =E39+1 -> 2 | G39: =F39+1 -> 3 | H39: =G39+1 -> 4 | I39: =H39+1 -> 5 | J39: =I39+1 -> 6 | K39: =J39+1 -> 7 | L39: =K39+1 -> 8 | M39: =L39+1 -> 9 | ... DT39: =DS39+1 -> 120
D40: Month Ending | E40: =IF(CF!S5<=Summary!$H$12,CF!S5,"") -> 46173 | F40: =IF(CF!T5<=Summary!$H$12,CF!T5,"") -> 46203 | G40: =IF(CF!U5<=Summary!$H$12,CF!U5,"") -> 46234 | H40: =IF(CF!V5<=Summary!$H$12,CF!V5,"") -> 46265 | I40: =IF(CF!W5<=Summary!$H$12,CF!W5,"") -> 46295 | J40: =IF(CF!X5<=Summary!$H$12,CF!X5,"") -> 46326 | K40: =IF(CF!Y5<=Summary!$H$12,CF!Y5,"") -> 46356 | L40: =IF(CF!Z5<=Summary!$H$12,CF!Z5,"") -> 46387 | ... DT40: =IF(CF!EH5<=Summary!$H$12,CF!EH5,"")
D41: =Z6 -> Net Operating Income | E41: =IF(AND(E40<=$H$12,VLOOKUP($D$41,$E$44:$F$56,2,0)="Positive"),VLOOKUP($D$41,'Combined CF'!$P$6:$ES$50,Summary!E39+2,0),IF(AND(E40<=$H$12,VLOOKUP($D$41,$E$44:$F$56,2,0)="Negative"),ABS(VLOOKUP($D$41,'Combined CF'!$P$6:$ES$50,Summary!E39+2,0)),"")) -> 425744.61 | F41: =IF(AND(F40<=$H$12,VLOOKUP($D$41,$E$44:$F$56,2,0)="Positive"),VLOOKUP($D$41,'Combined CF'!$P$6:$ES$50,Summary!F39+2,0),IF(AND(F40<=$H$12,VLOOKUP($D$41,$E$44:$F$56,2,0)="Negative"),ABS(VLOOKUP($D$41,'Combined CF'!$P$6:$ES$50,Summary!F39+2,0)),"")) -> 425744.61 | G41: =IF(AND(G40<=$H$12,VLOOKUP($D$41,$E$44:$F$56,2,0)="Positive"),VLOOKUP($D$41,'Combined CF'!$P$6:$ES$50,Summary!G39+2,0),IF(AND(G40<=$H$12,VLOOKUP($D$41,$E$44:$F$56,2,0)="Negative"),ABS(VLOOKUP($D$41,'Combined CF'!$P$6:$ES$50,Summary!G39+2,0)),"")) -> 425937.54 | H41: =IF(AND(H40<=$H$12,VLOOKUP($D$41,$E$44:$F$56,2,0)="Positive"),VLOOKUP($D$41,'Combined CF'!$P$6:$ES$50,Summary!H39+2,0),IF(AND(H40<=$H$12,VLOOKUP($D$41,$E$44:$F$56,2,0)="Negative"),ABS(VLOOKUP($D$41,'Combined CF'!$P$6:$ES$50,Summary!H39+2,0)),"")) -> 426333.7 | I41: =IF(AND(I40<=$H$12,VLOOKUP($D$41,$E$44:$F$56,2,0)="Positive"),VLOOKUP($D$41,'Combined CF'!$P$6:$ES$50,Summary!I39+2,0),IF(AND(I40<=$H$12,VLOOKUP($D$41,$E$44:$F$56,2,0)="Negative"),ABS(VLOOKUP($D$41,'Combined CF'!$P$6:$ES$50,Summary!I39+2,0)),"")) -> 417550.78 | J41: =IF(AND(J40<=$H$12,VLOOKUP($D$41,$E$44:$F$56,2,0)="Positive"),VLOOKUP($D$41,'Combined CF'!$P$6:$ES$50,Summary!J39+2,0),IF(AND(J40<=$H$12,VLOOKUP($D$41,$E$44:$F$56,2,0)="Negative"),ABS(VLOOKUP($D$41,'Combined CF'!$P$6:$ES$50,Summary!J39+2,0)),"")) -> 417547.47 | K41: =IF(AND(K40<=$H$12,VLOOKUP($D$41,$E$44:$F$56,2,0)="Positive"),VLOOKUP($D$41,'Combined CF'!$P$6:$ES$50,Summary!K39+2,0),IF(AND(K40<=$H$12,VLOOKUP($D$41,$E$44:$F$56,2,0)="Negative"),ABS(VLOOKUP($D$41,'Combined CF'!$P$6:$ES$50,Summary!K39+2,0)),"")) -> 419010.48 | L41: =IF(AND(L40<=$H$12,VLOOKUP($D$41,$E$44:$F$56,2,0)="Positive"),VLOOKUP($D$41,'Combined CF'!$P$6:$ES$50,Summary!L39+2,0),IF(AND(L40<=$H$12,VLOOKUP($D$41,$E$44:$F$56,2,0)="Negative"),ABS(VLOOKUP($D$41,'Combined CF'!$P$6:$ES$50,Summary!L39+2,0)),"")) -> 419010.48 | ... DT41: =IF(AND(DT40<=$H$12,VLOOKUP($D$41,$E$44:$F$56,2,0)="Positive"),VLOOKUP($D$41,'Combined CF'!$P$6:$ES$50,Summary!DT39+2,0),IF(AND(DT40<=$H$12,VLOOKUP($D$41,$E$44:$F$56,2,0)="Negative"),ABS(VLOOKUP($D$41,'Combined CF'!$P$6:$ES$50,Summary!DT39+2,0)),""))
E44: Net Rental Income | F44: Positive
E45: CAM Reimbursements | F45: Positive
E46: Percentage Rent | F46: Positive
E47: Effective Gross Revenue | F47: Positive
E48: Property Taxes | F48: Negative
E49: Net Operating Income | F49: Positive
D50: Monthly | E50: Construction Expenses | F50: Negative
D51: Quarterly | E51: Tenant Improvements | F51: Negative
D52: Annually | E52: Leasing Commissions | F52: Negative
E53: Additional Loan Proceeds | F53: Positive
E54: Debt Service | F54: Negative
E55: Working Capital Distributed | F55: Positive
E56: Total Levered Cash Flow | F56: Positive
D58: Year Ending | E58: =IF(CF!D2*12<=HOLD_PERIOD,CF!D5,"") -> 46507 | F58: =IF(CF!E2*12<=HOLD_PERIOD,CF!E5,"") -> 46873 | G58: =IF(CF!F2*12<=HOLD_PERIOD,CF!F5,"") -> 47238 | H58: =IF(CF!G2*12<=HOLD_PERIOD,CF!G5,"") -> 47603 | I58: =IF(CF!H2*12<=HOLD_PERIOD,CF!H5,"") -> 47968 | J58: =IF(CF!I2*12<=HOLD_PERIOD,CF!I5,"") | K58: =IF(CF!J2*12<=HOLD_PERIOD,CF!J5,"") | L58: =IF(CF!K2*12<=HOLD_PERIOD,CF!K5,"") | ... N58: =IF(CF!M2*12<=HOLD_PERIOD,CF!M5,"")
D59: DSCR | E59: =IF('Combined CF'!D2*12<=HOLD_PERIOD,'Combined CF'!D14/-'Combined CF'!D41,"") -> 0.76366156 | F59: =IF('Combined CF'!E2*12<=HOLD_PERIOD,'Combined CF'!E14/-'Combined CF'!E41,"") -> 1.4267531 | G59: =IF('Combined CF'!F2*12<=HOLD_PERIOD,'Combined CF'!F14/-'Combined CF'!F41,"") -> 1.5628743 | H59: =IF('Combined CF'!G2*12<=HOLD_PERIOD,'Combined CF'!G14/-'Combined CF'!G41,"") -> 1.3686343 | I59: =IF('Combined CF'!H2*12<=HOLD_PERIOD,'Combined CF'!H14/-'Combined CF'!H41,"") -> 1.3790594 | J59: =IF('Combined CF'!I2*12<=HOLD_PERIOD,'Combined CF'!I14/-'Combined CF'!I41,"") | K59: =IF('Combined CF'!J2*12<=HOLD_PERIOD,'Combined CF'!J14/-'Combined CF'!J41,"") | L59: =IF('Combined CF'!K2*12<=HOLD_PERIOD,'Combined CF'!K14/-'Combined CF'!K41,"") | ... N59: =IF('Combined CF'!M2*12<=HOLD_PERIOD,'Combined CF'!M14/-'Combined CF'!M41,"")

Sheet Combined CF
B1: =Assumptions!A1 -> Levered Return Metrics | C1: =Assumptions!B1 -> IRR | D1: =Assumptions!C1 -> 0.14881178 | E1: =Assumptions!D1 -> Equity Multiple | F1: =Assumptions!E1 -> 1.926724 | G1: =Assumptions!F1 -> Unlevered Return Metrics | H1: =Assumptions!G1 -> IRR | I1: =Assumptions!H1 -> 0.093561557 | ... K1: =Assumptions!J1 -> 1.5042331
B2: Year | C2: 0 | D2: 1 | E2: =D2+1 -> 2 | F2: =E2+1 -> 3 | G2: =F2+1 -> 4 | H2: =G2+1 -> 5 | I2: =H2+1 -> 6 | J2: =I2+1 -> 7 | K2: =J2+1 -> 8 | L2: =K2+1 -> 9 | M2: =L2+1 -> 10 | P2: Year | Q2: 0 | R2: 1 | S2: 1 | T2: 1 | U2: 1 | V2: 1 | W2: 1 | X2: 1 | Y2: 1 | Z2: 1 | AA2: 1 | AB2: 1 | AC2: 1 | AD2: =R2+1 -> 2 | AE2: =S2+1 -> 2 | AF2: =T2+1 -> 2 | AG2: =U2+1 -> 2 | AH2: =V2+1 -> 2 | AI2: =W2+1 -> 2 | AJ2: =X2+1 -> 2 | AK2: =Y2+1 -> 2 | ... ES2: =EG2+1 -> 11
P3: Month | Q3: 0 | R3: 1 | S3: =R3+1 -> 2 | T3: =S3+1 -> 3 | U3: =T3+1 -> 4 | V3: =U3+1 -> 5 | W3: =V3+1 -> 6 | X3: =W3+1 -> 7 | Y3: =X3+1 -> 8 | Z3: =Y3+1 -> 9 | ... ES3: =ER3+1 -> 132
B4: Month Ending | C4: =CLOSE_DATE -> 46142 | D4: =EOMONTH(C4,12) -> 46507 | E4: =EOMONTH(D4,12) -> 46873 | F4: =EOMONTH(E4,12) -> 47238 | G4: =EOMONTH(F4,12) -> 47603 | H4: =EOMONTH(G4,12) -> 47968 | I4: =EOMONTH(H4,12) -> 48334 | J4: =EOMONTH(I4,12) -> 48699 | K4: =EOMONTH(J4,12) -> 49064 | ... M4: =EOMONTH(L4,12) -> 49795 | P4: Month Ending | Q4: =CLOSE_DATE -> 46142 | R4: =Leases!D167 -> 46173 | S4: =EOMONTH(R4,1) -> 46203 | T4: =EOMONTH(S4,1) -> 46234 | U4: =EOMONTH(T4,1) -> 46265 | V4: =EOMONTH(U4,1) -> 46295 | W4: =EOMONTH(V4,1) -> 46326 | X4: =EOMONTH(W4,1) -> 46356 | Y4: =EOMONTH(X4,1) -> 46387 | Z4: =EOMONTH(Y4,1) -> 46418 | ... ES4: =EOMONTH(ER4,1) -> 50160
A6: =SUM(C6:M6) -> 97882425 | B6: Net Rental Income | D6: =SUMIF($R$2:$ES$2,D$2,$R6:$ES6) -> 10248853 | E6: =SUMIF($R$2:$ES$2,E$2,$R6:$ES6) -> 15260922 | F6: =SUMIF($R$2:$ES$2,F$2,$R6:$ES6) -> 16748297 | G6: =SUMIF($R$2:$ES$2,G$2,$R6:$ES6) -> 17970973 | H6: =SUMIF($R$2:$ES$2,H$2,$R6:$ES6) -> 18581410 | I6: =SUMIF($R$2:$ES$2,I$2,$R6:$ES6) -> 19071970 | J6: =SUMIF($R$2:$ES$2,J$2,$R6:$ES6) -> 0 | K6: =SUMIF($R$2:$ES$2,K$2,$R6:$ES6) -> 0 | ... M6: =SUMIF($R$2:$ES$2,M$2,$R6:$ES6) -> 0 | O6: =SUM(Q6:ES6) -> 97882425 | P6: Net Rental Income | R6: =INDEX(CF!$Q$11:$ET$35,MATCH($P6,CF!$Q$11:$Q$35,0),MATCH(R$4,CF!$Q$5:$ET$5,0))+SUMIF('CFS-Main Page'!$G$15:$AA$15,R$2,'CFS-Main Page'!$G$25:$AA$25)/12 -> 855290.12 | S6: =INDEX(CF!$Q$11:$ET$35,MATCH($P6,CF!$Q$11:$Q$35,0),MATCH(S$4,CF!$Q$5:$ET$5,0))+SUMIF('CFS-Main Page'!$G$15:$AA$15,S$2,'CFS-Main Page'!$G$25:$AA$25)/12 -> 855290.12 | T6: =INDEX(CF!$Q$11:$ET$35,MATCH($P6,CF!$Q$11:$Q$35,0),MATCH(T$4,CF!$Q$5:$ET$5,0))+SUMIF('CFS-Main Page'!$G$15:$AA$15,T$2,'CFS-Main Page'!$G$25:$AA$25)/12 -> 855483.05 | U6: =INDEX(CF!$Q$11:$ET$35,MATCH($P6,CF!$Q$11:$Q$35,0),MATCH(U$4,CF!$Q$5:$ET$5,0))+SUMIF('CFS-Main Page'!$G$15:$AA$15,U$2,'CFS-Main Page'!$G$25:$AA$25)/12 -> 855879.21 | V6: =INDEX(CF!$Q$11:$ET$35,MATCH($P6,CF!$Q$11:$Q$35,0),MATCH(V$4,CF!$Q$5:$ET$5,0))+SUMIF('CFS-Main Page'!$G$15:$AA$15,V$2,'CFS-Main Page'!$G$25:$AA$25)/12 -> 848555.99 | W6: =INDEX(CF!$Q$11:$ET$35,MATCH($P6,CF!$Q$11:$Q$35,0),MATCH(W$4,CF!$Q$5:$ET$5,0))+SUMIF('CFS-Main Page'!$G$15:$AA$15,W$2,'CFS-Main Page'!$G$25:$AA$25)/12 -> 848555.99 | X6: =INDEX(CF!$Q$11:$ET$35,MATCH($P6,CF!$Q$11:$Q$35,0),MATCH(X$4,CF!$Q$5:$ET$5,0))+SUMIF('CFS-Main Page'!$G$15:$AA$15,X$2,'CFS-Main Page'!$G$25:$AA$25)/12 -> 848555.99 | Y6: =INDEX(CF!$Q$11:$ET$35,MATCH($P6,CF!$Q$11:$Q$35,0),MATCH(Y$4,CF!$Q$5:$ET$5,0))+SUMIF('CFS-Main Page'!$G$15:$AA$15,Y$2,'CFS-Main Page'!$G$25:$AA$25)/12 -> 848555.99 | ... ES6: =INDEX(CF!$Q$11:$ET$35,MATCH($P6,CF!$Q$11:$Q$35,0),MATCH(ES$4,CF!$Q$5:$ET$5,0))+SUMIF('CFS-Main Page'!$G$15:$AA$15,ES$2,'CFS-Main Page'!$G$25:$AA$25)/12 -> 0
A8: =SUM(C8:M8) -> 6587768.1 | B8: Total Other Income | D8: =SUMIF($R$2:$ES$2,D$2,$R8:$ES8) -> 1025953.7 | E8: =SUMIF($R$2:$ES$2,E$2,$R8:$ES8) -> 1054982.1 | F8: =SUMIF($R$2:$ES$2,F$2,$R8:$ES8) -> 1083864.5 | G8: =SUMIF($R$2:$ES$2,G$2,$R8:$ES8) -> 1110756.3 | H8: =SUMIF($R$2:$ES$2,H$2,$R8:$ES8) -> 1145760.7 | I8: =SUMIF($R$2:$ES$2,I$2,$R8:$ES8) -> 1166450.7 | J8: =SUMIF($R$2:$ES$2,J$2,$R8:$ES8) -> 0 | K8: =SUMIF($R$2:$ES$2,K$2,$R8:$ES8) -> 0 | ... M8: =SUMIF($R$2:$ES$2,M$2,$R8:$ES8) -> 0 | O8: =SUM(Q8:ES8) -> 6587768.1 | P8: Total Other Income | R8: =INDEX(CF!$Q$11:$ET$35,MATCH($P8,CF!$Q$11:$Q$35,0),MATCH(R$4,CF!$Q$5:$ET$5,0))+SUMIF('CFS-Main Page'!$G$15:$AA$15,R$2,'CFS-Main Page'!$G$29:$AA$29)/12 -> 85667.576 | S8: =INDEX(CF!$Q$11:$ET$35,MATCH($P8,CF!$Q$11:$Q$35,0),MATCH(S$4,CF!$Q$5:$ET$5,0))+SUMIF('CFS-Main Page'!$G$15:$AA$15,S$2,'CFS-Main Page'!$G$29:$AA$29)/12 -> 85680.591 | T8: =INDEX(CF!$Q$11:$ET$35,MATCH($P8,CF!$Q$11:$Q$35,0),MATCH(T$4,CF!$Q$5:$ET$5,0))+SUMIF('CFS-Main Page'!$G$15:$AA$15,T$2,'CFS-Main Page'!$G$29:$AA$29)/12 -> 85693.636 | U8: =INDEX(CF!$Q$11:$ET$35,MATCH($P8,CF!$Q$11:$Q$35,0),MATCH(U$4,CF!$Q$5:$ET$5,0))+SUMIF('CFS-Main Page'!$G$15:$AA$15,U$2,'CFS-Main Page'!$G$29:$AA$29)/12 -> 85706.71 | V8: =INDEX(CF!$Q$11:$ET$35,MATCH($P8,CF!$Q$11:$Q$35,0),MATCH(V$4,CF!$Q$5:$ET$5,0))+SUMIF('CFS-Main Page'!$G$15:$AA$15,V$2,'CFS-Main Page'!$G$29:$AA$29)/12 -> 84260.115 | W8: =INDEX(CF!$Q$11:$ET$35,MATCH($P8,CF!$Q$11:$Q$35,0),MATCH(W$4,CF!$Q$5:$ET$5,0))+SUMIF('CFS-Main Page'!$G$15:$AA$15,W$2,'CFS-Main Page'!$G$29:$AA$29)/12 -> 84269.944 | X8: =INDEX(CF!$Q$11:$ET$35,MATCH($P8,CF!$Q$11:$Q$35,0),MATCH(X$4,CF!$Q$5:$ET$5,0))+SUMIF('CFS-Main Page'!$G$15:$AA$15,X$2,'CFS-Main Page'!$G$29:$AA$29)/12 -> 85746.11 | Y8: =INDEX(CF!$Q$11:$ET$35,MATCH($P8,CF!$Q$11:$Q$35,0),MATCH(Y$4,CF!$Q$5:$ET$5,0))+SUMIF('CFS-Main Page'!$G$15:$AA$15,Y$2,'CFS-Main Page'!$G$29:$AA$29)/12 -> 85759.303 | ... ES8: =INDEX(CF!$Q$11:$ET$35,MATCH($P8,CF!$Q$11:$Q$35,0),MATCH(ES$4,CF!$Q$5:$ET$5,0))+SUMIF('CFS-Main Page'!$G$15:$AA$15,ES$2,'CFS-Main Page'!$G$29:$AA$29)/12 -> 0
A10: =SUM(C10:M10) -> 1.0447019e+08 | B10: Effective Gross Revenue | D10: =SUMIF($R$2:$ES$2,D$2,$R10:$ES10) -> 11274806 | E10: =SUMIF($R$2:$ES$2,E$2,$R10:$ES10) -> 16315904 | F10: =SUMIF($R$2:$ES$2,F$2,$R10:$ES10) -> 17832162 | G10: =SUMIF($R$2:$ES$2,G$2,$R10:$ES10) -> 19081729 | H10: =SUMIF($R$2:$ES$2,H$2,$R10:$ES10) -> 19727171 | I10: =SUMIF($R$2:$ES$2,I$2,$R10:$ES10) -> 20238421 | J10: =SUMIF($R$2:$ES$2,J$2,$R10:$ES10) -> 0 | K10: =SUMIF($R$2:$ES$2,K$2,$R10:$ES10) -> 0 | ... M10: =SUMIF($R$2:$ES$2,M$2,$R10:$ES10) -> 0 | O10: =SUM(Q10:ES10) -> 1.0447019e+08 | P10: Effective Gross Revenue | R10: =SUM(R6,R8) -> 940957.7 | S10: =SUM(S6,S8) -> 940970.71 | T10: =SUM(T6,T8) -> 941176.68 | U10: =SUM(U6,U8) -> 941585.92 | V10: =SUM(V6,V8) -> 932816.1 | W10: =SUM(W6,W8) -> 932825.93 | X10: =SUM(X6,X8) -> 934302.1 | Y10: =SUM(Y6,Y8) -> 934315.29 | ... ES10: =SUM(ES6,ES8) -> 0
A12: =SUM(C12:M12) -> -40512383 | B12: Total Operating Expenses | D12: =SUMIF($R$2:$ES$2,D$2,$R12:$ES12) -> -6183422.6 | E12: =SUMIF($R$2:$ES$2,E$2,$R12:$ES12) -> -6458691.4 | F12: =SUMIF($R$2:$ES$2,F$2,$R12:$ES12) -> -6640903.2 | G12: =SUMIF($R$2:$ES$2,G$2,$R12:$ES12) -> -6820371.4 | H12: =SUMIF($R$2:$ES$2,H$2,$R12:$ES12) -> -7119777.9 | I12: =SUMIF($R$2:$ES$2,I$2,$R12:$ES12) -> -7289216.5 | J12: =SUMIF($R$2:$ES$2,J$2,$R12:$ES12) -> 0 | K12: =SUMIF($R$2:$ES$2,K$2,$R12:$ES12) -> 0 | ... M12: =SUMIF($R$2:$ES$2,M$2,$R12:$ES12) -> 0 | O12: =SUM(Q12:ES12) -> -40512383 | P12: Total Operating Expenses | R12: =INDEX(CF!$Q$11:$ET$35,MATCH($P12,CF!$Q$11:$Q$35,0),MATCH(R$4,CF!$Q$5:$ET$5,0))-SUMIF('CFS-Main Page'!$G$15:$AA$15,R$2,'CFS-Main Page'!$G$46:$AA$46)/12 -> -515213.09 | S12: =INDEX(CF!$Q$11:$ET$35,MATCH($P12,CF!$Q$11:$Q$35,0),MATCH(S$4,CF!$Q$5:$ET$5,0))-SUMIF('CFS-Main Page'!$G$15:$AA$15,S$2,'CFS-Main Page'!$G$46:$AA$46)/12 -> -515226.1 | T12: =INDEX(CF!$Q$11:$ET$35,MATCH($P12,CF!$Q$11:$Q$35,0),MATCH(T$4,CF!$Q$5:$ET$5,0))-SUMIF('CFS-Main Page'!$G$15:$AA$15,T$2,'CFS-Main Page'!$G$46:$AA$46)/12 -> -515239.15 | U12: =INDEX(CF!$Q$11:$ET$35,MATCH($P12,CF!$Q$11:$Q$35,0),MATCH(U$4,CF!$Q$5:$ET$5,0))-SUMIF('CFS-Main Page'!$G$15:$AA$15,U$2,'CFS-Main Page'!$G$46:$AA$46)/12 -> -515252.22 | V12: =INDEX(CF!$Q$11:$ET$35,MATCH($P12,CF!$Q$11:$Q$35,0),MATCH(V$4,CF!$Q$5:$ET$5,0))-SUMIF('CFS-Main Page'!$G$15:$AA$15,V$2,'CFS-Main Page'!$G$46:$AA$46)/12 -> -515265.32 | W12: =INDEX(CF!$Q$11:$ET$35,MATCH($P12,CF!$Q$11:$Q$35,0),MATCH(W$4,CF!$Q$5:$ET$5,0))-SUMIF('CFS-Main Page'!$G$15:$AA$15,W$2,'CFS-Main Page'!$G$46:$AA$46)/12 -> -515278.46 | X12: =INDEX(CF!$Q$11:$ET$35,MATCH($P12,CF!$Q$11:$Q$35,0),MATCH(X$4,CF!$Q$5:$ET$5,0))-SUMIF('CFS-Main Page'!$G$15:$AA$15,X$2,'CFS-Main Page'!$G$46:$AA$46)/12 -> -515291.62 | Y12: =INDEX(CF!$Q$11:$ET$35,MATCH($P12,CF!$Q$11:$Q$35,0),MATCH(Y$4,CF!$Q$5:$ET$5,0))-SUMIF('CFS-Main Page'!$G$15:$AA$15,Y$2,'CFS-Main Page'!$G$46:$AA$46)/12 -> -515304.81 | ... ES12: =INDEX(CF!$Q$11:$ET$35,MATCH($P12,CF!$Q$11:$Q$35,0),MATCH(ES$4,CF!$Q$5:$ET$5,0))-SUMIF('CFS-Main Page'!$G$15:$AA$15,ES$2,'CFS-Main Page'!$G$46:$AA$46)/12 -> 0
A14: =SUM(C14:M14) -> 63957810 | B14: Net Operating Income | D14: =SUMIF($R$2:$ES$2,D$2,$R14:$ES14) -> 5091383.9 | E14: =SUMIF($R$2:$ES$2,E$2,$R14:$ES14) -> 9857212.3 | F14: =SUMIF($R$2:$ES$2,F$2,$R14:$ES14) -> 11191259 | G14: =SUMIF($R$2:$ES$2,G$2,$R14:$ES14) -> 12261358 | H14: =SUMIF($R$2:$ES$2,H$2,$R14:$ES14) -> 12607393 | I14: =SUMIF($R$2:$ES$2,I$2,$R14:$ES14) -> 12949204 | J14: =SUMIF($R$2:$ES$2,J$2,$R14:$ES14) -> 0 | K14: =SUMIF($R$2:$ES$2,K$2,$R14:$ES14) -> 0 | ... M14: =SUMIF($R$2:$ES$2,M$2,$R14:$ES14) -> 0 | O14: =SUM(Q14:ES14) -> 63957810 | P14: Net Operating Income | R14: =SUM(R10,R12) -> 425744.61 | S14: =SUM(S10,S12) -> 425744.61 | T14: =SUM(T10,T12) -> 425937.54 | U14: =SUM(U10,U12) -> 426333.7 | V14: =SUM(V10,V12) -> 417550.78 | W14: =SUM(W10,W12) -> 417547.47 | X14: =SUM(X10,X12) -> 419010.48 | Y14: =SUM(Y10,Y12) -> 419010.48 | ... ES14: =SUM(ES10,ES12) -> 0
A16: =SUM(C16:M16) -> -457082.1 | B16: Total TI/LC Expenses | D16: =SUMIF($R$2:$ES$2,D$2,$R16:$ES16) -> -113576.43 | E16: =SUMIF($R$2:$ES$2,E$2,$R16:$ES16) -> -82964.871 | F16: =SUMIF($R$2:$ES$2,F$2,$R16:$ES16) -> -82971.826 | G16: =SUMIF($R$2:$ES$2,G$2,$R16:$ES16) -> -177568.98 | H16: =SUMIF($R$2:$ES$2,H$2,$R16:$ES16) -> 0 | I16: =SUMIF($R$2:$ES$2,I$2,$R16:$ES16) -> 0 | J16: =SUMIF($R$2:$ES$2,J$2,$R16:$ES16) -> 0 | K16: =SUMIF($R$2:$ES$2,K$2,$R16:$ES16) -> 0 | ... M16: =SUMIF($R$2:$ES$2,M$2,$R16:$ES16) -> 0 | O16: =SUM(Q16:ES16) -> -457082.1 | P16: Total TI/LC Expenses | R16: =INDEX(CF!$Q$11:$ET$35,MATCH($P16,CF!$Q$11:$Q$35,0),MATCH(R$4,CF!$Q$5:$ET$5,0)) -> 0 | S16: =INDEX(CF!$Q$11:$ET$35,MATCH($P16,CF!$Q$11:$Q$35,0),MATCH(S$4,CF!$Q$5:$ET$5,0)) -> 0 | T16: =INDEX(CF!$Q$11:$ET$35,MATCH($P16,CF!$Q$11:$Q$35,0),MATCH(T$4,CF!$Q$5:$ET$5,0)) -> 0 | U16: =INDEX(CF!$Q$11:$ET$35,MATCH($P16,CF!$Q$11:$Q$35,0),MATCH(U$4,CF!$Q$5:$ET$5,0)) -> 0 | V16: =INDEX(CF!$Q$11:$ET$35,MATCH($P16,CF!$Q$11:$Q$35,0),MATCH(V$4,CF!$Q$5:$ET$5,0)) -> 0 | W16: =INDEX(CF!$Q$11:$ET$35,MATCH($P16,CF!$Q$11:$Q$35,0),MATCH(W$4,CF!$Q$5:$ET$5,0)) -> -113576.43 | X16: =INDEX(CF!$Q$11:$ET$35,MATCH($P16,CF!$Q$11:$Q$35,0),MATCH(X$4,CF!$Q$5:$ET$5,0)) -> 0 | Y16: =INDEX(CF!$Q$11:$ET$35,MATCH($P16,CF!$Q$11:$Q$35,0),MATCH(Y$4,CF!$Q$5:$ET$5,0)) -> 0 | ... ES16: =INDEX(CF!$Q$11:$ET$35,MATCH($P16,CF!$Q$11:$Q$35,0),MATCH(ES$4,CF!$Q$5:$ET$5,0)) -> 0
A18: =SUM(C18:M18) -> 50551524 | B18: Total Cash Flow Before Debt Service | D18: =SUMIF($R$2:$ES$2,D$2,$R18:$ES18) -> 4977807.5 | E18: =SUMIF($R$2:$ES$2,E$2,$R18:$ES18) -> 9774247.5 | F18: =SUMIF($R$2:$ES$2,F$2,$R18:$ES18) -> 11108287 | G18: =SUMIF($R$2:$ES$2,G$2,$R18:$ES18) -> 12083789 | H18: =SUMIF($R$2:$ES$2,H$2,$R18:$ES18) -> 12607393 | I18: =SUMIF($R$2:$ES$2,I$2,$R18:$ES18) -> 0 | J18: =SUMIF($R$2:$ES$2,J$2,$R18:$ES18) -> 0 | K18: =SUMIF($R$2:$ES$2,K$2,$R18:$ES18) -> 0 | ... M18: =SUMIF($R$2:$ES$2,M$2,$R18:$ES18) -> 0 | O18: =SUM(Q18:ES18) -> 50551524 | P18: Total Cash Flow Before Debt Service | R18: =IF(R$3<=HOLD_PERIOD,SUM(R14,R16),0) -> 425744.61 | S18: =IF(S$3<=HOLD_PERIOD,SUM(S14,S16),0) -> 425744.61 | T18: =IF(T$3<=HOLD_PERIOD,SUM(T14,T16),0) -> 425937.54 | U18: =IF(U$3<=HOLD_PERIOD,SUM(U14,U16),0) -> 426333.7 | V18: =IF(V$3<=HOLD_PERIOD,SUM(V14,V16),0) -> 417550.78 | W18: =IF(W$3<=HOLD_PERIOD,SUM(W14,W16),0) -> 303971.05 | X18: =IF(X$3<=HOLD_PERIOD,SUM(X14,X16),0) -> 419010.48 | Y18: =IF(Y$3<=HOLD_PERIOD,SUM(Y14,Y16),0) -> 419010.48 | ... ES18: =IF(ES$3<=HOLD_PERIOD,SUM(ES14,ES16),0) -> 0
A20: =SUM(C20:M20) -> -33462.5 | B20: Capital Reserves | D20: =SUMIF($R$2:$ES$2,D$2,$R20:$ES20) -> -6692.5 | E20: =SUMIF($R$2:$ES$2,E$2,$R20:$ES20) -> -6692.5 | F20: =SUMIF($R$2:$ES$2,F$2,$R20:$ES20) -> -6692.5 | G20: =SUMIF($R$2:$ES$2,G$2,$R20:$ES20) -> -6692.5 | H20: =SUMIF($R$2:$ES$2,H$2,$R20:$ES20) -> -6692.5 | I20: =SUMIF($R$2:$ES$2,I$2,$R20:$ES20) -> 0 | J20: =SUMIF($R$2:$ES$2,J$2,$R20:$ES20) -> 0 | K20: =SUMIF($R$2:$ES$2,K$2,$R20:$ES20) -> 0 | ... M20: =SUMIF($R$2:$ES$2,M$2,$R20:$ES20) -> 0 | O20: =SUM(Q20:ES20) -> -33462.5 | P20: Capital Reserves | R20: =IF(R$3<=HOLD_PERIOD,-CAP_RESERVES*NLA/12,0) -> -557.70833 | S20: =IF(S$3<=HOLD_PERIOD,-CAP_RESERVES*NLA/12,0) -> -557.70833 | T20: =IF(T$3<=HOLD_PERIOD,-CAP_RESERVES*NLA/12,0) -> -557.70833 | U20: =IF(U$3<=HOLD_PERIOD,-CAP_RESERVES*NLA/12,0) -> -557.70833 | V20: =IF(V$3<=HOLD_PERIOD,-CAP_RESERVES*NLA/12,0) -> -557.70833 | W20: =IF(W$3<=HOLD_PERIOD,-CAP_RESERVES*NLA/12,0) -> -557.70833 | X20: =IF(X$3<=HOLD_PERIOD,-CAP_RESERVES*NLA/12,0) -> -557.70833 | Y20: =IF(Y$3<=HOLD_PERIOD,-CAP_RESERVES*NLA/12,0) -> -557.70833 | ... ES20: =IF(ES$3<=HOLD_PERIOD,-CAP_RESERVES*NLA/12,0) -> 0
A21: =SUM(C21:M21) -> 0 | B21: Construction Expenses | D21: =SUMIF($R$2:$ES$2,D$2,$R21:$ES21) -> 0 | E21: =SUMIF($R$2:$ES$2,E$2,$R21:$ES21) -> 0 | F21: =SUMIF($R$2:$ES$2,F$2,$R21:$ES21) -> 0 | G21: =SUMIF($R$2:$ES$2,G$2,$R21:$ES21) -> 0 | H21: =SUMIF($R$2:$ES$2,H$2,$R21:$ES21) -> 0 | I21: =SUMIF($R$2:$ES$2,I$2,$R21:$ES21) -> 0 | J21: =SUMIF($R$2:$ES$2,J$2,$R21:$ES21) -> 0 | K21: =SUMIF($R$2:$ES$2,K$2,$R21:$ES21) -> 0 | ... M21: =SUMIF($R$2:$ES$2,M$2,$R21:$ES21) -> 0 | O21: =SUM(Q21:ES21) -> 0 | P21: Construction Expenses | R21: =-'Construction Budget'!W8 -> 0 | S21: =-'Construction Budget'!X8 -> 0 | T21: =-'Construction Budget'!Y8 -> 0 | U21: =-'Construction Budget'!Z8 -> 0 | V21: =-'Construction Budget'!AA8 -> 0 | W21: =-'Construction Budget'!AB8 -> 0 | X21: =-'Construction Budget'!AC8 -> 0 | Y21: =-'Construction Budget'!AD8 -> 0 | ... ES21: =-'Construction Budget'!EX8 -> 0
B23: Partnership Expenses | P23: Partnership Expenses
A24: =SUM(C24:M24) -> 0 | B24: Asset Management Fee | D24: =SUMIF($R$2:$ES$2,D$2,$R24:$ES24) -> 0 | E24: =SUMIF($R$2:$ES$2,E$2,$R24:$ES24) -> 0 | F24: =SUMIF($R$2:$ES$2,F$2,$R24:$ES24) -> 0 | G24: =SUMIF($R$2:$ES$2,G$2,$R24:$ES24) -> 0 | H24: =SUMIF($R$2:$ES$2,H$2,$R24:$ES24) -> 0 | I24: =SUMIF($R$2:$ES$2,I$2,$R24:$ES24) -> 0 | J24: =SUMIF($R$2:$ES$2,J$2,$R24:$ES24) -> 0 | K24: =SUMIF($R$2:$ES$2,K$2,$R24:$ES24) -> 0 | ... M24: =SUMIF($R$2:$ES$2,M$2,$R24:$ES24) -> 0 | O24: =SUM(Q24:ES24) -> 0 | P24: Asset Management Fee | R24: =IF(OR(Summary!$E$22*AM_FEE/12>(R18+R41),R$3>HOLD_PERIOD),0,-Summary!$E$22*AM_FEE/12) -> 0 | S24: =IF(OR(Summary!$E$22*AM_FEE/12>(S18+S41),S$3>HOLD_PERIOD),0,-Summary!$E$22*AM_FEE/12) -> 0 | T24: =IF(OR(Summary!$E$22*AM_FEE/12>(T18+T41),T$3>HOLD_PERIOD),0,-Summary!$E$22*AM_FEE/12) -> 0 | U24: =IF(OR(Summary!$E$22*AM_FEE/12>(U18+U41),U$3>HOLD_PERIOD),0,-Summary!$E$22*AM_FEE/12) -> 0 | V24: =IF(OR(Summary!$E$22*AM_FEE/12>(V18+V41),V$3>HOLD_PERIOD),0,-Summary!$E$22*AM_FEE/12) -> 0 | W24: =IF(OR(Summary!$E$22*AM_FEE/12>(W18+W41),W$3>HOLD_PERIOD),0,-Summary!$E$22*AM_FEE/12) -> 0 | X24: =IF(OR(Summary!$E$22*AM_FEE/12>(X18+X41),X$3>HOLD_PERIOD),0,-Summary!$E$22*AM_FEE/12) -> 0 | Y24: =IF(OR(Summary!$E$22*AM_FEE/12>(Y18+Y41),Y$3>HOLD_PERIOD),0,-Summary!$E$22*AM_FEE/12) -> 0 | ... ES24: =IF(OR(Summary!$E$22*AM_FEE/12>(ES18+ES41),ES$3>HOLD_PERIOD),0,-Summary!$E$22*AM_FEE/12) -> 0
A25: =SUM(C25:M25) -> 0 | B25: Construction Management Fee | D25: =SUMIF($R$2:$ES$2,D$2,$R25:$ES25) -> 0 | E25: =SUMIF($R$2:$ES$2,E$2,$R25:$ES25) -> 0 | F25: =SUMIF($R$2:$ES$2,F$2,$R25:$ES25) -> 0 | G25: =SUMIF($R$2:$ES$2,G$2,$R25:$ES25) -> 0 | H25: =SUMIF($R$2:$ES$2,H$2,$R25:$ES25) -> 0 | I25: =SUMIF($R$2:$ES$2,I$2,$R25:$ES25) -> 0 | J25: =SUMIF($R$2:$ES$2,J$2,$R25:$ES25) -> 0 | K25: =SUMIF($R$2:$ES$2,K$2,$R25:$ES25) -> 0 | ... M25: =SUMIF($R$2:$ES$2,M$2,$R25:$ES25) -> 0 | O25: =SUM(Q25:ES25) -> 0 | P25: Construction Management Fee | R25: =R21*CM_FEE -> 0 | S25: =S21*CM_FEE -> 0 | T25: =T21*CM_FEE -> 0 | U25: =U21*CM_FEE -> 0 | V25: =V21*CM_FEE -> 0 | W25: =W21*CM_FEE -> 0 | X25: =X21*CM_FEE -> 0 | Y25: =Y21*CM_FEE -> 0 | ... ES25: =ES21*CM_FEE -> 0
B27: Acquisition Information | P27: Acquisition Information
A28: =SUM(C28:M28) -> -180000000 | B28: Purchase Price | C28: =SUMIF($Q$2:$ES$2,C$2,$Q28:$ES28) -> -180000000 | O28: =SUM(Q28:ES28) -> -180000000 | P28: Purchase Price | Q28: =-PURCH_PRICE -> -180000000
A29: =SUM(C29:M29) -> -1800000 | B29: Acquisition Fee | C29: =SUMIF($Q$2:$ES$2,C$2,$Q29:$ES29) -> -1800000 | O29: =SUM(Q29:ES29) -> -1800000 | P29: Acquisition Fee | Q29: =-ACQ_FEE -> -1800000
A30: =SUM(C30:M30) -> 0 | B30: Closing Costs | C30: =SUMIF($Q$2:$ES$2,C$2,$Q30:$ES30) -> 0 | O30: =SUM(Q30:ES30) -> 0 | P30: Closing Costs | Q30: =-CLOSING_COSTS -> 0
B32: Sale Information | P32: Sale Information
A33: =SUM(C33:M33) -> 2.2520356e+08 | B33: Sale Proceeds | D33: =SUMIF($R$2:$ES$2,D$2,$R33:$ES33) -> 0 | E33: =SUMIF($R$2:$ES$2,E$2,$R33:$ES33) -> 0 | F33: =SUMIF($R$2:$ES$2,F$2,$R33:$ES33) -> 0 | G33: =SUMIF($R$2:$ES$2,G$2,$R33:$ES33) -> 0 | H33: =SUMIF($R$2:$ES$2,H$2,$R33:$ES33) -> 2.2520356e+08 | I33: =SUMIF($R$2:$ES$2,I$2,$R33:$ES33) -> 0 | J33: =SUMIF($R$2:$ES$2,J$2,$R33:$ES33) -> 0 | K33: =SUMIF($R$2:$ES$2,K$2,$R33:$ES33) -> 0 | ... M33: =SUMIF($R$2:$ES$2,M$2,$R33:$ES33) -> 0 | O33: =SUM(Q33:ES33) -> 2.2520356e+08 | P33: Sale Proceeds | R33: =IF(R$3=HOLD_PERIOD,SUM(S14:AD14)/EXIT_CAP,0) -> 0 | S33: =IF(S$3=HOLD_PERIOD,SUM(T14:AE14)/EXIT_CAP,0) -> 0 | T33: =IF(T$3=HOLD_PERIOD,SUM(U14:AF14)/EXIT_CAP,0) -> 0 | U33: =IF(U$3=HOLD_PERIOD,SUM(V14:AG14)/EXIT_CAP,0) -> 0 | V33: =IF(V$3=HOLD_PERIOD,SUM(W14:AH14)/EXIT_CAP,0) -> 0 | W33: =IF(W$3=HOLD_PERIOD,SUM(X14:AI14)/EXIT_CAP,0) -> 0 | X33: =IF(X$3=HOLD_PERIOD,SUM(Y14:AJ14)/EXIT_CAP,0) -> 0 | Y33: =IF(Y$3=HOLD_PERIOD,SUM(Z14:AK14)/EXIT_CAP,0) -> 0 | ... ES33: =IF(ES$3=HOLD_PERIOD,SUM(ET14:FE14)/EXIT_CAP,0) -> 0
A34: =SUM(C34:M34) -> -2252035.6 | B34: Costs of Sale | D34: =SUMIF($R$2:$ES$2,D$2,$R34:$ES34) -> 0 | E34: =SUMIF($R$2:$ES$2,E$2,$R34:$ES34) -> 0 | F34: =SUMIF($R$2:$ES$2,F$2,$R34:$ES34) -> 0 | G34: =SUMIF($R$2:$ES$2,G$2,$R34:$ES34) -> 0 | H34: =SUMIF($R$2:$ES$2,H$2,$R34:$ES34) -> -2252035.6 | I34: =SUMIF($R$2:$ES$2,I$2,$R34:$ES34) -> 0 | J34: =SUMIF($R$2:$ES$2,J$2,$R34:$ES34) -> 0 | K34: =SUMIF($R$2:$ES$2,K$2,$R34:$ES34) -> 0 | ... M34: =SUMIF($R$2:$ES$2,M$2,$R34:$ES34) -> 0 | O34: =SUM(Q34:ES34) -> -2252035.6 | P34: Costs of Sale | R34: =R33*-COSTS_OF_SALE -> 0 | S34: =S33*-COSTS_OF_SALE -> 0 | T34: =T33*-COSTS_OF_SALE -> 0 | U34: =U33*-COSTS_OF_SALE -> 0 | V34: =V33*-COSTS_OF_SALE -> 0 | W34: =W33*-COSTS_OF_SALE -> 0 | X34: =X33*-COSTS_OF_SALE -> 0 | Y34: =Y33*-COSTS_OF_SALE -> 0 | ... ES34: =ES33*-COSTS_OF_SALE -> 0
A36: =SUM(C36:M36) -> 91669581 | B36: Total Unlevered Cash Flow | C36: =SUMIF($Q$2:$ES$2,C$2,$Q36:$ES36) -> -181800000 | D36: =SUMIF($R$2:$ES$2,D$2,$R36:$ES36) -> 4971115 | E36: =SUMIF($R$2:$ES$2,E$2,$R36:$ES36) -> 9767555 | F36: =SUMIF($R$2:$ES$2,F$2,$R36:$ES36) -> 11101594 | G36: =SUMIF($R$2:$ES$2,G$2,$R36:$ES36) -> 12077096 | H36: =SUMIF($R$2:$ES$2,H$2,$R36:$ES36) -> 2.3555222e+08 | I36: =SUMIF($R$2:$ES$2,I$2,$R36:$ES36) -> 0 | J36: =SUMIF($R$2:$ES$2,J$2,$R36:$ES36) -> 0 | K36: =SUMIF($R$2:$ES$2,K$2,$R36:$ES36) -> 0 | ... M36: =SUMIF($R$2:$ES$2,M$2,$R36:$ES36) -> 0 | O36: =SUM(Q36:ES36) -> 91669581 | P36: Total Unlevered Cash Flow | Q36: =SUM(Q18:Q34) -> -181800000 | R36: =SUM(R18:R34) -> 425186.9 | S36: =SUM(S18:S34) -> 425186.9 | T36: =SUM(T18:T34) -> 425379.83 | U36: =SUM(U18:U34) -> 425775.99 | V36: =SUM(V18:V34) -> 416993.07 | W36: =SUM(W18:W34) -> 303413.34 | X36: =SUM(X18:X34) -> 418452.77 | ... ES36: =SUM(ES18:ES34) -> 0
B38: Loan Information | P38: Loan Information
A39: =SUM(C39:M39) -> 1.26e+08 | B39: Acquisition Loan/Refinance Proceeds | C39: =SUMIF($Q$2:$ES$2,C$2,$Q39:$ES39) -> 1.26e+08 | D39: =SUMIF($R$2:$ES$2,D$2,$R39:$ES39) -> 0 | E39: =SUMIF($R$2:$ES$2,E$2,$R39:$ES39) -> 0 | F39: =SUMIF($R$2:$ES$2,F$2,$R39:$ES39) -> 0 | G39: =SUMIF($R$2:$ES$2,G$2,$R39:$ES39) -> 0 | H39: =SUMIF($R$2:$ES$2,H$2,$R39:$ES39) -> 0 | I39: =SUMIF($R$2:$ES$2,I$2,$R39:$ES39) -> 0 | J39: =SUMIF($R$2:$ES$2,J$2,$R39:$ES39) -> 0 | K39: =SUMIF($R$2:$ES$2,K$2,$R39:$ES39) -> 0 | ... M39: =SUMIF($R$2:$ES$2,M$2,$R39:$ES39) -> 0 | O39: =SUM(Q39:ES39) -> 1.26e+08 | P39: Acquisition Loan/Refinance Proceeds | Q39: =Financing!D3+Financing!E3 -> 1.26e+08 | R39: =IF(R$3>=HOLD_PERIOD,0,IF(R$3=ACQ_LOAN_TERM,Financing!$F$3,0)) -> 0 | S39: =IF(S$3>=HOLD_PERIOD,0,IF(S$3=ACQ_LOAN_TERM,Financing!$F$3,0)) -> 0 | T39: =IF(T$3>=HOLD_PERIOD,0,IF(T$3=ACQ_LOAN_TERM,Financing!$F$3,0)) -> 0 | U39: =IF(U$3>=HOLD_PERIOD,0,IF(U$3=ACQ_LOAN_TERM,Financing!$F$3,0)) -> 0 | V39: =IF(V$3>=HOLD_PERIOD,0,IF(V$3=ACQ_LOAN_TERM,Financing!$F$3,0)) -> 0 | W39: =IF(W$3>=HOLD_PERIOD,0,IF(W$3=ACQ_LOAN_TERM,Financing!$F$3,0)) -> 0 | X39: =IF(X$3>=HOLD_PERIOD,0,IF(X$3=ACQ_LOAN_TERM,Financing!$F$3,0)) -> 0 | Y39: =IF(Y$3>=HOLD_PERIOD,0,IF(Y$3=ACQ_LOAN_TERM,Financing!$F$3,0)) -> 0 | ... ES39: =IF(ES$3>=HOLD_PERIOD,0,IF(ES$3=ACQ_LOAN_TERM,Financing!$F$3,0)) -> 0
A40: =SUM(C40:M40) -> 0 | B40: Additional Loan Proceeds | D40: =SUMIF($R$2:$ES$2,D$2,$R40:$ES40) -> 0 | E40: =SUMIF($R$2:$ES$2,E$2,$R40:$ES40) -> 0 | F40: =SUMIF($R$2:$ES$2,F$2,$R40:$ES40) -> 0 | G40: =SUMIF($R$2:$ES$2,G$2,$R40:$ES40) -> 0 | H40: =SUMIF($R$2:$ES$2,H$2,$R40:$ES40) -> 0 | I40: =SUMIF($R$2:$ES$2,I$2,$R40:$ES40) -> 0 | J40: =SUMIF($R$2:$ES$2,J$2,$R40:$ES40) -> 0 | K40: =SUMIF($R$2:$ES$2,K$2,$R40:$ES40) -> 0 | ... M40: =SUMIF($R$2:$ES$2,M$2,$R40:$ES40) -> 0 | O40: =SUM(Q40:ES40) -> 0 | P40: Additional Loan Proceeds | R40: =SUMIF(Financing!$A:$A,"ALP",Financing!D:D) -> 0 | S40: =SUMIF(Financing!$A:$A,"ALP",Financing!E:E) -> 0 | T40: =SUMIF(Financing!$A:$A,"ALP",Financing!F:F) -> 0 | U40: =SUMIF(Financing!$A:$A,"ALP",Financing!G:G) -> 0 | V40: =SUMIF(Financing!$A:$A,"ALP",Financing!H:H) -> 0 | W40: =SUMIF(Financing!$A:$A,"ALP",Financing!I:I) -> 0 | X40: =SUMIF(Financing!$A:$A,"ALP",Financing!J:J) -> 0 | Y40: =SUMIF(Financing!$A:$A,"ALP",Financing!K:K) -> 0 | Z40: =SUMIF(Financing!$A:$A,"ALP",Financing!L:L) -> 0 | AA40: =SUMIF(Financing!$A:$A,"ALP",Financing!M:M) -> 0 | AB40: =SUMIF(Financing!$A:$A,"ALP",Financing!N:N) -> 0 | AC40: =SUMIF(Financing!$A:$A,"ALP",Financing!O:O) -> 0 | AD40: =SUMIF(Financing!$A:$A,"ALP",Financing!P:P) -> 0 | AE40: =SUMIF(Financing!$A:$A,"ALP",Financing!Q:Q) -> 0 | AF40: =SUMIF(Financing!$A:$A,"ALP",Financing!R:R) -> 0 | AG40: =SUMIF(Financing!$A:$A,"ALP",Financing!S:S) -> 0 | AH40: =SUMIF(Financing!$A:$A,"ALP",Financing!T:T) -> 0 | AI40: =SUMIF(Financing!$A:$A,"ALP",Financing!U:U) -> 0 | AJ40: =SUMIF(Financing!$A:$A,"ALP",Financing!V:V) -> 0 | AK40: =SUMIF(Financing!$A:$A,"ALP",Financing!W:W) -> 0 | AL40: =SUMIF(Financing!$A:$A,"ALP",Financing!X:X) -> 0 | AM40: =SUMIF(Financing!$A:$A,"ALP",Financing!Y:Y) -> 0 | AN40: =SUMIF(Financing!$A:$A,"ALP",Financing!Z:Z) -> 0 | AO40: =SUMIF(Financing!$A:$A,"ALP",Financing!AA:AA) -> 0 | AP40: =SUMIF(Financing!$A:$A,"ALP",Financing!AB:AB) -> 0 | AQ40: =SUMIF(Financing!$A:$A,"ALP",Financing!AC:AC) -> 0 | AR40: =SUMIF(Financing!$A:$A,"ALP",Financing!AD:AD) -> 0 | AS40: =SUMIF(Financing!$A:$A,"ALP",Financing!AE:AE) -> 0 | AT40: =SUMIF(Financing!$A:$A,"ALP",Financing!AF:AF) -> 0 | AU40: =SUMIF(Financing!$A:$A,"ALP",Financing!AG:AG) -> 0 | AV40: =SUMIF(Financing!$A:$A,"ALP",Financing!AH:AH) -> 0 | AW40: =SUMIF(Financing!$A:$A,"ALP",Financing!AI:AI) -> 0 | AX40: =SUMIF(Financing!$A:$A,"ALP",Financing!AJ:AJ) -> 0 | AY40: =SUMIF(Financing!$A:$A,"ALP",Financing!AK:AK) -> 0 | AZ40: =SUMIF(Financing!$A:$A,"ALP",Financing!AL:AL) -> 0 | BA40: =SUMIF(Financing!$A:$A,"ALP",Financing!AM:AM) -> 0 | BB40: =SUMIF(Financing!$A:$A,"ALP",Financing!AN:AN) -> 0 | BC40: =SUMIF(Financing!$A:$A,"ALP",Financing!AO:AO) -> 0 | BD40: =SUMIF(Financing!$A:$A,"ALP",Financing!AP:AP) -> 0 | BE40: =SUMIF(Financing!$A:$A,"ALP",Financing!AQ:AQ) -> 0 | BF40: =SUMIF(Financing!$A:$A,"ALP",Financing!AR:AR) -> 0 | BG40: =SUMIF(Financing!$A:$A,"ALP",Financing!AS:AS) -> 0 | BH40: =SUMIF(Financing!$A:$A,"ALP",Financing!AT:AT) -> 0 | BI40: =SUMIF(Financing!$A:$A,"ALP",Financing!AU:AU) -> 0 | BJ40: =SUMIF(Financing!$A:$A,"ALP",Financing!AV:AV) -> 0 | BK40: =SUMIF(Financing!$A:$A,"ALP",Financing!AW:AW) -> 0 | BL40: =SUMIF(Financing!$A:$A,"ALP",Financing!AX:AX) -> 0 | BM40: =SUMIF(Financing!$A:$A,"ALP",Financing!AY:AY) -> 0 | BN40: =SUMIF(Financing!$A:$A,"ALP",Financing!AZ:AZ) -> 0 | BO40: =SUMIF(Financing!$A:$A,"ALP",Financing!BA:BA) -> 0 | BP40: =SUMIF(Financing!$A:$A,"ALP",Financing!BB:BB) -> 0 | BQ40: =SUMIF(Financing!$A:$A,"ALP",Financing!BC:BC) -> 0 | BR40: =SUMIF(Financing!$A:$A,"ALP",Financing!BD:BD) -> 0 | BS40: =SUMIF(Financing!$A:$A,"ALP",Financing!BE:BE) -> 0 | BT40: =SUMIF(Financing!$A:$A,"ALP",Financing!BF:BF) -> 0 | BU40: =SUMIF(Financing!$A:$A,"ALP",Financing!BG:BG) -> 0 | BV40: =SUMIF(Financing!$A:$A,"ALP",Financing!BH:BH) -> 0 | BW40: =SUMIF(Financing!$A:$A,"ALP",Financing!BI:BI) -> 0 | BX40: =SUMIF(Financing!$A:$A,"ALP",Financing!BJ:BJ) -> 0 | BY40: =SUMIF(Financing!$A:$A,"ALP",Financing!BK:BK) -> 0 | BZ40: =SUMIF(Financing!$A:$A,"ALP",Financing!BL:BL) -> 0 | CA40: =SUMIF(Financing!$A:$A,"ALP",Financing!BM:BM) -> 0 | CB40: =SUMIF(Financing!$A:$A,"ALP",Financing!BN:BN) -> 0 | CC40: =SUMIF(Financing!$A:$A,"ALP",Financing!BO:BO) -> 0 | CD40: =SUMIF(Financing!$A:$A,"ALP",Financing!BP:BP) -> 0 | CE40: =SUMIF(Financing!$A:$A,"ALP",Financing!BQ:BQ) -> 0 | CF40: =SUMIF(Financing!$A:$A,"ALP",Financing!BR:BR) -> 0 | CG40: =SUMIF(Financing!$A:$A,"ALP",Financing!BS:BS) -> 0 | CH40: =SUMIF(Financing!$A:$A,"ALP",Financing!BT:BT) -> 0 | CI40: =SUMIF(Financing!$A:$A,"ALP",Financing!BU:BU) -> 0 | CJ40: =SUMIF(Financing!$A:$A,"ALP",Financing!BV:BV) -> 0 | CK40: =SUMIF(Financing!$A:$A,"ALP",Financing!BW:BW) -> 0 | CL40: =SUMIF(Financing!$A:$A,"ALP",Financing!BX:BX) -> 0 | CM40: =SUMIF(Financing!$A:$A,"ALP",Financing!BY:BY) -> 0 | CN40: =SUMIF(Financing!$A:$A,"ALP",Financing!BZ:BZ) -> 0 | CO40: =SUMIF(Financing!$A:$A,"ALP",Financing!CA:CA) -> 0 | CP40: =SUMIF(Financing!$A:$A,"ALP",Financing!CB:CB) -> 0 | CQ40: =SUMIF(Financing!$A:$A,"ALP",Financing!CC:CC) -> 0 | CR40: =SUMIF(Financing!$A:$A,"ALP",Financing!CD:CD) -> 0 | CS40: =SUMIF(Financing!$A:$A,"ALP",Financing!CE:CE) -> 0 | CT40: =SUMIF(Financing!$A:$A,"ALP",Financing!CF:CF) -> 0 | CU40: =SUMIF(Financing!$A:$A,"ALP",Financing!CG:CG) -> 0 | CV40: =SUMIF(Financing!$A:$A,"ALP",Financing!CH:CH) -> 0 | CW40: =SUMIF(Financing!$A:$A,"ALP",Financing!CI:CI) -> 0 | CX40: =SUMIF(Financing!$A:$A,"ALP",Financing!CJ:CJ) -> 0 | CY40: =SUMIF(Financing!$A:$A,"ALP",Financing!CK:CK) -> 0 | CZ40: =SUMIF(Financing!$A:$A,"ALP",Financing!CL:CL) -> 0 | DA40: =SUMIF(Financing!$A:$A,"ALP",Financing!CM:CM) -> 0 | DB40: =SUMIF(Financing!$A:$A,"ALP",Financing!CN:CN) -> 0 | DC40: =SUMIF(Financing!$A:$A,"ALP",Financing!CO:CO) -> 0 | DD40: =SUMIF(Financing!$A:$A,"ALP",Financing!CP:CP) -> 0 | DE40: =SUMIF(Financing!$A:$A,"ALP",Financing!CQ:CQ) -> 0 | DF40: =SUMIF(Financing!$A:$A,"ALP",Financing!CR:CR) -> 0 | DG40: =SUMIF(Financing!$A:$A,"ALP",Financing!CS:CS) -> 0 | DH40: =SUMIF(Financing!$A:$A,"ALP",Financing!CT:CT) -> 0 | DI40: =SUMIF(Financing!$A:$A,"ALP",Financing!CU:CU) -> 0 | DJ40: =SUMIF(Financing!$A:$A,"ALP",Financing!CV:CV) -> 0 | DK40: =SUMIF(Financing!$A:$A,"ALP",Financing!CW:CW) -> 0 | DL40: =SUMIF(Financing!$A:$A,"ALP",Financing!CX:CX) -> 0 | DM40: =SUMIF(Financing!$A:$A,"ALP",Financing!CY:CY) -> 0 | DN40: =SUMIF(Financing!$A:$A,"ALP",Financing!CZ:CZ) -> 0 | DO40: =SUMIF(Financing!$A:$A,"ALP",Financing!DA:DA) -> 0 | DP40: =SUMIF(Financing!$A:$A,"ALP",Financing!DB:DB) -> 0 | DQ40: =SUMIF(Financing!$A:$A,"ALP",Financing!DC:DC) -> 0 | DR40: =SUMIF(Financing!$A:$A,"ALP",Financing!DD:DD) -> 0 | DS40: =SUMIF(Financing!$A:$A,"ALP",Financing!DE:DE) -> 0 | DT40: =SUMIF(Financing!$A:$A,"ALP",Financing!DF:DF) -> 0 | DU40: =SUMIF(Financing!$A:$A,"ALP",Financing!DG:DG) -> 0 | DV40: =SUMIF(Financing!$A:$A,"ALP",Financing!DH:DH) -> 0 | DW40: =SUMIF(Financing!$A:$A,"ALP",Financing!DI:DI) -> 0 | DX40: =SUMIF(Financing!$A:$A,"ALP",Financing!DJ:DJ) -> 0 | DY40: =SUMIF(Financing!$A:$A,"ALP",Financing!DK:DK) -> 0 | DZ40: =SUMIF(Financing!$A:$A,"ALP",Financing!DL:DL) -> 0 | EA40: =SUMIF(Financing!$A:$A,"ALP",Financing!DM:DM) -> 0 | EB40: =SUMIF(Financing!$A:$A,"ALP",Financing!DN:DN) -> 0 | EC40: =SUMIF(Financing!$A:$A,"ALP",Financing!DO:DO) -> 0 | ED40: =SUMIF(Financing!$A:$A,"ALP",Financing!DP:DP) -> 0 | EE40: =SUMIF(Financing!$A:$A,"ALP",Financing!DQ:DQ) -> 0 | EF40: =SUMIF(Financing!$A:$A,"ALP",Financing!DR:DR) -> 0 | EG40: =SUMIF(Financing!$A:$A,"ALP",Financing!DS:DS) -> 0 | EH40: =SUMIF(Financing!$A:$A,"ALP",Financing!DT:DT) -> 0 | EI40: =SUMIF(Financing!$A:$A,"ALP",Financing!DU:DU) -> 0 | EJ40: =SUMIF(Financing!$A:$A,"ALP",Financing!DV:DV) -> 0 | EK40: =SUMIF(Financing!$A:$A,"ALP",Financing!DW:DW) -> 0 | EL40: =SUMIF(Financing!$A:$A,"ALP",Financing!DX:DX) -> 0 | EM40: =SUMIF(Financing!$A:$A,"ALP",Financing!DY:DY) -> 0 | EN40: =SUMIF(Financing!$A:$A,"ALP",Financing!DZ:DZ) -> 0 | EO40: =SUMIF(Financing!$A:$A,"ALP",Financing!EA:EA) -> 0 | EP40: =SUMIF(Financing!$A:$A,"ALP",Financing!EB:EB) -> 0 | EQ40: =SUMIF(Financing!$A:$A,"ALP",Financing!EC:EC) -> 0 | ER40: =SUMIF(Financing!$A:$A,"ALP",Financing!ED:ED) -> 0 | ES40: =SUMIF(Financing!$A:$A,"ALP",Financing!EE:EE) -> 0
A41: =SUM(C41:M41) -> -38837452 | B41: Debt Service | D41: =SUMIF($R$2:$ES$2,D$2,$R41:$ES41) -> -6667068.5 | E41: =SUMIF($R$2:$ES$2,E$2,$R41:$ES41) -> -6908842.5 | F41: =SUMIF($R$2:$ES$2,F$2,$R41:$ES41) -> -7160690.2 | G41: =SUMIF($R$2:$ES$2,G$2,$R41:$ES41) -> -8958827.1 | H41: =SUMIF($R$2:$ES$2,H$2,$R41:$ES41) -> -9142023.5 | I41: =SUMIF($R$2:$ES$2,I$2,$R41:$ES41) -> 0 | J41: =SUMIF($R$2:$ES$2,J$2,$R41:$ES41) -> 0 | K41: =SUMIF($R$2:$ES$2,K$2,$R41:$ES41) -> 0 | ... M41: =SUMIF($R$2:$ES$2,M$2,$R41:$ES41) -> 0 | O41: =SUM(Q41:ES41) -> -38837452 | P41: Debt Service | R41: =-SUMIF(Financing!$A:$A,"TLP",Financing!D:D) -> -547212.75 | S41: =-SUMIF(Financing!$A:$A,"TLP",Financing!E:E) -> -548530.5 | T41: =-SUMIF(Financing!$A:$A,"TLP",Financing!F:F) -> -549777.9 | U41: =-SUMIF(Financing!$A:$A,"TLP",Financing!G:G) -> -551220.6 | V41: =-SUMIF(Financing!$A:$A,"TLP",Financing!H:H) -> -552754.65 | W41: =-SUMIF(Financing!$A:$A,"TLP",Financing!I:I) -> -554317.05 | X41: =-SUMIF(Financing!$A:$A,"TLP",Financing!J:J) -> -556021.2 | Y41: =-SUMIF(Financing!$A:$A,"TLP",Financing!K:K) -> -557821.95 | Z41: =-SUMIF(Financing!$A:$A,"TLP",Financing!L:L) -> -559545 | AA41: =-SUMIF(Financing!$A:$A,"TLP",Financing!M:M) -> -561516.9 | AB41: =-SUMIF(Financing!$A:$A,"TLP",Financing!N:N) -> -563372.25 | AC41: =-SUMIF(Financing!$A:$A,"TLP",Financing!O:O) -> -564977.7 | AD41: =-SUMIF(Financing!$A:$A,"TLP",Financing!P:P) -> -566658.75 | AE41: =-SUMIF(Financing!$A:$A,"TLP",Financing!Q:Q) -> -568383.9 | AF41: =-SUMIF(Financing!$A:$A,"TLP",Financing!R:R) -> -569975.7 | AG41: =-SUMIF(Financing!$A:$A,"TLP",Financing!S:S) -> -571643.1 | AH41: =-SUMIF(Financing!$A:$A,"TLP",Financing!T:T) -> -573243.3 | AI41: =-SUMIF(Financing!$A:$A,"TLP",Financing!U:U) -> -574877.1 | AJ41: =-SUMIF(Financing!$A:$A,"TLP",Financing!V:V) -> -576630.6 | AK41: =-SUMIF(Financing!$A:$A,"TLP",Financing!W:W) -> -578175.15 | AL41: =-SUMIF(Financing!$A:$A,"TLP",Financing!X:X) -> -579852 | AM41: =-SUMIF(Financing!$A:$A,"TLP",Financing!Y:Y) -> -581632.8 | AN41: =-SUMIF(Financing!$A:$A,"TLP",Financing!Z:Z) -> -583005.15 | AO41: =-SUMIF(Financing!$A:$A,"TLP",Financing!AA:AA) -> -584764.95 | AP41: =-SUMIF(Financing!$A:$A,"TLP",Financing!AB:AB) -> -586662.3 | AQ41: =-SUMIF(Financing!$A:$A,"TLP",Financing!AC:AC) -> -588354.9 | AR41: =-SUMIF(Financing!$A:$A,"TLP",Financing!AD:AD) -> -590177.7 | AS41: =-SUMIF(Financing!$A:$A,"TLP",Financing!AE:AE) -> -592111.8 | AT41: =-SUMIF(Financing!$A:$A,"TLP",Financing!AF:AF) -> -593865.3 | AU41: =-SUMIF(Financing!$A:$A,"TLP",Financing!AG:AG) -> -595726.95 | AV41: =-SUMIF(Financing!$A:$A,"TLP",Financing!AH:AH) -> -597603.3 | AW41: =-SUMIF(Financing!$A:$A,"TLP",Financing!AI:AI) -> -599473.35 | AX41: =-SUMIF(Financing!$A:$A,"TLP",Financing!AJ:AJ) -> -601533.45 | AY41: =-SUMIF(Financing!$A:$A,"TLP",Financing!AK:AK) -> -603247.05 | AZ41: =-SUMIF(Financing!$A:$A,"TLP",Financing!AL:AL) -> -605041.5 | BA41: =-SUMIF(Financing!$A:$A,"TLP",Financing!AM:AM) -> -606892.65 | BB41: =-SUMIF(Financing!$A:$A,"TLP",Financing!AN:AN) -> -739145.95 | BC41: =-SUMIF(Financing!$A:$A,"TLP",Financing!AO:AO) -> -740493.52 | BD41: =-SUMIF(Financing!$A:$A,"TLP",Financing!AP:AP) -> -741873.37 | BE41: =-SUMIF(Financing!$A:$A,"TLP",Financing!AQ:AQ) -> -743265.44 | BF41: =-SUMIF(Financing!$A:$A,"TLP",Financing!AR:AR) -> -744586.61 | BG41: =-SUMIF(Financing!$A:$A,"TLP",Financing!AS:AS) -> -746022.95 | BH41: =-SUMIF(Financing!$A:$A,"TLP",Financing!AT:AT) -> -747272.07 | BI41: =-SUMIF(Financing!$A:$A,"TLP",Financing!AU:AU) -> -748599.48 | BJ41: =-SUMIF(Financing!$A:$A,"TLP",Financing!AV:AV) -> -749957.31 | BK41: =-SUMIF(Financing!$A:$A,"TLP",Financing!AW:AW) -> -751240.6 | BL41: =-SUMIF(Financing!$A:$A,"TLP",Financing!AX:AX) -> -752501.82 | BM41: =-SUMIF(Financing!$A:$A,"TLP",Financing!AY:AY) -> -753867.93 | BN41: =-SUMIF(Financing!$A:$A,"TLP",Financing!AZ:AZ) -> -755059.06 | BO41: =-SUMIF(Financing!$A:$A,"TLP",Financing!BA:BA) -> -756319.23 | BP41: =-SUMIF(Financing!$A:$A,"TLP",Financing!BB:BB) -> -757655.44 | BQ41: =-SUMIF(Financing!$A:$A,"TLP",Financing!BC:BC) -> -758833.83 | BR41: =-SUMIF(Financing!$A:$A,"TLP",Financing!BD:BD) -> -760017.91 | BS41: =-SUMIF(Financing!$A:$A,"TLP",Financing!BE:BE) -> -761318.72 | BT41: =-SUMIF(Financing!$A:$A,"TLP",Financing!BF:BF) -> -762441.8 | BU41: =-SUMIF(Financing!$A:$A,"TLP",Financing!BG:BG) -> -763641.27 | BV41: =-SUMIF(Financing!$A:$A,"TLP",Financing!BH:BH) -> -764821.23 | BW41: =-SUMIF(Financing!$A:$A,"TLP",Financing!BI:BI) -> -766012.27 | BX41: =-SUMIF(Financing!$A:$A,"TLP",Financing!BJ:BJ) -> -767359.21 | BY41: =-SUMIF(Financing!$A:$A,"TLP",Financing!BK:BK) -> -768543.51 | BZ41: =-SUMIF(Financing!$A:$A,"TLP",Financing!BL:BL) -> 0 | CA41: =-SUMIF(Financing!$A:$A,"TLP",Financing!BM:BM) -> 0 | CB41: =-SUMIF(Financing!$A:$A,"TLP",Financing!BN:BN) -> 0 | CC41: =-SUMIF(Financing!$A:$A,"TLP",Financing!BO:BO) -> 0 | CD41: =-SUMIF(Financing!$A:$A,"TLP",Financing!BP:BP) -> 0 | CE41: =-SUMIF(Financing!$A:$A,"TLP",Financing!BQ:BQ) -> 0 | CF41: =-SUMIF(Financing!$A:$A,"TLP",Financing!BR:BR) -> 0 | CG41: =-SUMIF(Financing!$A:$A,"TLP",Financing!BS:BS) -> 0 | CH41: =-SUMIF(Financing!$A:$A,"TLP",Financing!BT:BT) -> 0 | CI41: =-SUMIF(Financing!$A:$A,"TLP",Financing!BU:BU) -> 0 | CJ41: =-SUMIF(Financing!$A:$A,"TLP",Financing!BV:BV) -> 0 | CK41: =-SUMIF(Financing!$A:$A,"TLP",Financing!BW:BW) -> 0 | CL41: =-SUMIF(Financing!$A:$A,"TLP",Financing!BX:BX) -> 0 | CM41: =-SUMIF(Financing!$A:$A,"TLP",Financing!BY:BY) -> 0 | CN41: =-SUMIF(Financing!$A:$A,"TLP",Financing!BZ:BZ) -> 0 | CO41: =-SUMIF(Financing!$A:$A,"TLP",Financing!CA:CA) -> 0 | CP41: =-SUMIF(Financing!$A:$A,"TLP",Financing!CB:CB) -> 0 | CQ41: =-SUMIF(Financing!$A:$A,"TLP",Financing!CC:CC) -> 0 | CR41: =-SUMIF(Financing!$A:$A,"TLP",Financing!CD:CD) -> 0 | CS41: =-SUMIF(Financing!$A:$A,"TLP",Financing!CE:CE) -> 0 | CT41: =-SUMIF(Financing!$A:$A,"TLP",Financing!CF:CF) -> 0 | CU41: =-SUMIF(Financing!$A:$A,"TLP",Financing!CG:CG) -> 0 | CV41: =-SUMIF(Financing!$A:$A,"TLP",Financing!CH:CH) -> 0 | CW41: =-SUMIF(Financing!$A:$A,"TLP",Financing!CI:CI) -> 0 | CX41: =-SUMIF(Financing!$A:$A,"TLP",Financing!CJ:CJ) -> 0 | CY41: =-SUMIF(Financing!$A:$A,"TLP",Financing!CK:CK) -> 0 | CZ41: =-SUMIF(Financing!$A:$A,"TLP",Financing!CL:CL) -> 0 | DA41: =-SUMIF(Financing!$A:$A,"TLP",Financing!CM:CM) -> 0 | DB41: =-SUMIF(Financing!$A:$A,"TLP",Financing!CN:CN) -> 0 | DC41: =-SUMIF(Financing!$A:$A,"TLP",Financing!CO:CO) -> 0 | DD41: =-SUMIF(Financing!$A:$A,"TLP",Financing!CP:CP) -> 0 | DE41: =-SUMIF(Financing!$A:$A,"TLP",Financing!CQ:CQ) -> 0 | DF41: =-SUMIF(Financing!$A:$A,"TLP",Financing!CR:CR) -> 0 | DG41: =-SUMIF(Financing!$A:$A,"TLP",Financing!CS:CS) -> 0 | DH41: =-SUMIF(Financing!$A:$A,"TLP",Financing!CT:CT) -> 0 | DI41: =-SUMIF(Financing!$A:$A,"TLP",Financing!CU:CU) -> 0 | DJ41: =-SUMIF(Financing!$A:$A,"TLP",Financing!CV:CV) -> 0 | DK41: =-SUMIF(Financing!$A:$A,"TLP",Financing!CW:CW) -> 0 | DL41: =-SUMIF(Financing!$A:$A,"TLP",Financing!CX:CX) -> 0 | DM41: =-SUMIF(Financing!$A:$A,"TLP",Financing!CY:CY) -> 0 | DN41: =-SUMIF(Financing!$A:$A,"TLP",Financing!CZ:CZ) -> 0 | DO41: =-SUMIF(Financing!$A:$A,"TLP",Financing!DA:DA) -> 0 | DP41: =-SUMIF(Financing!$A:$A,"TLP",Financing!DB:DB) -> 0 | DQ41: =-SUMIF(Financing!$A:$A,"TLP",Financing!DC:DC) -> 0 | DR41: =-SUMIF(Financing!$A:$A,"TLP",Financing!DD:DD) -> 0 | DS41: =-SUMIF(Financing!$A:$A,"TLP",Financing!DE:DE) -> 0 | DT41: =-SUMIF(Financing!$A:$A,"TLP",Financing!DF:DF) -> 0 | DU41: =-SUMIF(Financing!$A:$A,"TLP",Financing!DG:DG) -> 0 | DV41: =-SUMIF(Financing!$A:$A,"TLP",Financing!DH:DH) -> 0 | DW41: =-SUMIF(Financing!$A:$A,"TLP",Financing!DI:DI) -> 0 | DX41: =-SUMIF(Financing!$A:$A,"TLP",Financing!DJ:DJ) -> 0 | DY41: =-SUMIF(Financing!$A:$A,"TLP",Financing!DK:DK) -> 0 | DZ41: =-SUMIF(Financing!$A:$A,"TLP",Financing!DL:DL) -> 0 | EA41: =-SUMIF(Financing!$A:$A,"TLP",Financing!DM:DM) -> 0 | EB41: =-SUMIF(Financing!$A:$A,"TLP",Financing!DN:DN) -> 0 | EC41: =-SUMIF(Financing!$A:$A,"TLP",Financing!DO:DO) -> 0 | ED41: =-SUMIF(Financing!$A:$A,"TLP",Financing!DP:DP) -> 0 | EE41: =-SUMIF(Financing!$A:$A,"TLP",Financing!DQ:DQ) -> 0 | EF41: =-SUMIF(Financing!$A:$A,"TLP",Financing!DR:DR) -> 0 | EG41: =-SUMIF(Financing!$A:$A,"TLP",Financing!DS:DS) -> 0 | EH41: =-SUMIF(Financing!$A:$A,"TLP",Financing!DT:DT) -> 0 | EI41: =-SUMIF(Financing!$A:$A,"TLP",Financing!DU:DU) -> 0 | EJ41: =-SUMIF(Financing!$A:$A,"TLP",Financing!DV:DV) -> 0 | EK41: =-SUMIF(Financing!$A:$A,"TLP",Financing!DW:DW) -> 0 | EL41: =-SUMIF(Financing!$A:$A,"TLP",Financing!DX:DX) -> 0 | EM41: =-SUMIF(Financing!$A:$A,"TLP",Financing!DY:DY) -> 0 | EN41: =-SUMIF(Financing!$A:$A,"TLP",Financing!DZ:DZ) -> 0 | EO41: =-SUMIF(Financing!$A:$A,"TLP",Financing!EA:EA) -> 0 | EP41: =-SUMIF(Financing!$A:$A,"TLP",Financing!EB:EB) -> 0 | EQ41: =-SUMIF(Financing!$A:$A,"TLP",Financing!EC:EC) -> 0 | ER41: =-SUMIF(Financing!$A:$A,"TLP",Financing!ED:ED) -> 0 | ES41: =-SUMIF(Financing!$A:$A,"TLP",Financing!EE:EE) -> 0
A42: =SUM(C42:M42) -> -1.2280324e+08 | B42: Loan Payoff | D42: =SUMIF($R$2:$ES$2,D$2,$R42:$ES42) -> 0 | E42: =SUMIF($R$2:$ES$2,E$2,$R42:$ES42) -> 0 | F42: =SUMIF($R$2:$ES$2,F$2,$R42:$ES42) -> 0 | G42: =SUMIF($R$2:$ES$2,G$2,$R42:$ES42) -> 0 | H42: =SUMIF($R$2:$ES$2,H$2,$R42:$ES42) -> -1.2280324e+08 | I42: =SUMIF($R$2:$ES$2,I$2,$R42:$ES42) -> 0 | J42: =SUMIF($R$2:$ES$2,J$2,$R42:$ES42) -> 0 | K42: =SUMIF($R$2:$ES$2,K$2,$R42:$ES42) -> 0 | ... M42: =SUMIF($R$2:$ES$2,M$2,$R42:$ES42) -> 0 | O42: =SUM(Q42:ES42) -> -1.2280324e+08 | P42: Loan Payoff | R42: =SUMIF(Financing!$A:$A,"LP",Financing!D:D) -> 0 | S42: =SUMIF(Financing!$A:$A,"LP",Financing!E:E) -> 0 | T42: =SUMIF(Financing!$A:$A,"LP",Financing!F:F) -> 0 | U42: =SUMIF(Financing!$A:$A,"LP",Financing!G:G) -> 0 | V42: =SUMIF(Financing!$A:$A,"LP",Financing!H:H) -> 0 | W42: =SUMIF(Financing!$A:$A,"LP",Financing!I:I) -> 0 | X42: =SUMIF(Financing!$A:$A,"LP",Financing!J:J) -> 0 | Y42: =SUMIF(Financing!$A:$A,"LP",Financing!K:K) -> 0 | Z42: =SUMIF(Financing!$A:$A,"LP",Financing!L:L) -> 0 | AA42: =SUMIF(Financing!$A:$A,"LP",Financing!M:M) -> 0 | AB42: =SUMIF(Financing!$A:$A,"LP",Financing!N:N) -> 0 | AC42: =SUMIF(Financing!$A:$A,"LP",Financing!O:O) -> 0 | AD42: =SUMIF(Financing!$A:$A,"LP",Financing!P:P) -> 0 | AE42: =SUMIF(Financing!$A:$A,"LP",Financing!Q:Q) -> 0 | AF42: =SUMIF(Financing!$A:$A,"LP",Financing!R:R) -> 0 | AG42: =SUMIF(Financing!$A:$A,"LP",Financing!S:S) -> 0 | AH42: =SUMIF(Financing!$A:$A,"LP",Financing!T:T) -> 0 | AI42: =SUMIF(Financing!$A:$A,"LP",Financing!U:U) -> 0 | AJ42: =SUMIF(Financing!$A:$A,"LP",Financing!V:V) -> 0 | AK42: =SUMIF(Financing!$A:$A,"LP",Financing!W:W) -> 0 | AL42: =SUMIF(Financing!$A:$A,"LP",Financing!X:X) -> 0 | AM42: =SUMIF(Financing!$A:$A,"LP",Financing!Y:Y) -> 0 | AN42: =SUMIF(Financing!$A:$A,"LP",Financing!Z:Z) -> 0 | AO42: =SUMIF(Financing!$A:$A,"LP",Financing!AA:AA) -> 0 | AP42: =SUMIF(Financing!$A:$A,"LP",Financing!AB:AB) -> 0 | AQ42: =SUMIF(Financing!$A:$A,"LP",Financing!AC:AC) -> 0 | AR42: =SUMIF(Financing!$A:$A,"LP",Financing!AD:AD) -> 0 | AS42: =SUMIF(Financing!$A:$A,"LP",Financing!AE:AE) -> 0 | AT42: =SUMIF(Financing!$A:$A,"LP",Financing!AF:AF) -> 0 | AU42: =SUMIF(Financing!$A:$A,"LP",Financing!AG:AG) -> 0 | AV42: =SUMIF(Financing!$A:$A,"LP",Financing!AH:AH) -> 0 | AW42: =SUMIF(Financing!$A:$A,"LP",Financing!AI:AI) -> 0 | AX42: =SUMIF(Financing!$A:$A,"LP",Financing!AJ:AJ) -> 0 | AY42: =SUMIF(Financing!$A:$A,"LP",Financing!AK:AK) -> 0 | AZ42: =SUMIF(Financing!$A:$A,"LP",Financing!AL:AL) -> 0 | BA42: =SUMIF(Financing!$A:$A,"LP",Financing!AM:AM) -> 0 | BB42: =SUMIF(Financing!$A:$A,"LP",Financing!AN:AN) -> 0 | BC42: =SUMIF(Financing!$A:$A,"LP",Financing!AO:AO) -> 0 | BD42: =SUMIF(Financing!$A:$A,"LP",Financing!AP:AP) -> 0 | BE42: =SUMIF(Financing!$A:$A,"LP",Financing!AQ:AQ) -> 0 | BF42: =SUMIF(Financing!$A:$A,"LP",Financing!AR:AR) -> 0 | BG42: =SUMIF(Financing!$A:$A,"LP",Financing!AS:AS) -> 0 | BH42: =SUMIF(Financing!$A:$A,"LP",Financing!AT:AT) -> 0 | BI42: =SUMIF(Financing!$A:$A,"LP",Financing!AU:AU) -> 0 | BJ42: =SUMIF(Financing!$A:$A,"LP",Financing!AV:AV) -> 0 | BK42: =SUMIF(Financing!$A:$A,"LP",Financing!AW:AW) -> 0 | BL42: =SUMIF(Financing!$A:$A,"LP",Financing!AX:AX) -> 0 | BM42: =SUMIF(Financing!$A:$A,"LP",Financing!AY:AY) -> 0 | BN42: =SUMIF(Financing!$A:$A,"LP",Financing!AZ:AZ) -> 0 | BO42: =SUMIF(Financing!$A:$A,"LP",Financing!BA:BA) -> 0 | BP42: =SUMIF(Financing!$A:$A,"LP",Financing!BB:BB) -> 0 | BQ42: =SUMIF(Financing!$A:$A,"LP",Financing!BC:BC) -> 0 | BR42: =SUMIF(Financing!$A:$A,"LP",Financing!BD:BD) -> 0 | BS42: =SUMIF(Financing!$A:$A,"LP",Financing!BE:BE) -> 0 | BT42: =SUMIF(Financing!$A:$A,"LP",Financing!BF:BF) -> 0 | BU42: =SUMIF(Financing!$A:$A,"LP",Financing!BG:BG) -> 0 | BV42: =SUMIF(Financing!$A:$A,"LP",Financing!BH:BH) -> 0 | BW42: =SUMIF(Financing!$A:$A,"LP",Financing!BI:BI) -> 0 | BX42: =SUMIF(Financing!$A:$A,"LP",Financing!BJ:BJ) -> 0 | BY42: =SUMIF(Financing!$A:$A,"LP",Financing!BK:BK) -> -1.2280324e+08 | BZ42: =SUMIF(Financing!$A:$A,"LP",Financing!BL:BL) -> 0 | CA42: =SUMIF(Financing!$A:$A,"LP",Financing!BM:BM) -> 0 | CB42: =SUMIF(Financing!$A:$A,"LP",Financing!BN:BN) -> 0 | CC42: =SUMIF(Financing!$A:$A,"LP",Financing!BO:BO) -> 0 | CD42: =SUMIF(Financing!$A:$A,"LP",Financing!BP:BP) -> 0 | CE42: =SUMIF(Financing!$A:$A,"LP",Financing!BQ:BQ) -> 0 | CF42: =SUMIF(Financing!$A:$A,"LP",Financing!BR:BR) -> 0 | CG42: =SUMIF(Financing!$A:$A,"LP",Financing!BS:BS) -> 0 | CH42: =SUMIF(Financing!$A:$A,"LP",Financing!BT:BT) -> 0 | CI42: =SUMIF(Financing!$A:$A,"LP",Financing!BU:BU) -> 0 | CJ42: =SUMIF(Financing!$A:$A,"LP",Financing!BV:BV) -> 0 | CK42: =SUMIF(Financing!$A:$A,"LP",Financing!BW:BW) -> 0 | CL42: =SUMIF(Financing!$A:$A,"LP",Financing!BX:BX) -> 0 | CM42: =SUMIF(Financing!$A:$A,"LP",Financing!BY:BY) -> 0 | CN42: =SUMIF(Financing!$A:$A,"LP",Financing!BZ:BZ) -> 0 | CO42: =SUMIF(Financing!$A:$A,"LP",Financing!CA:CA) -> 0 | CP42: =SUMIF(Financing!$A:$A,"LP",Financing!CB:CB) -> 0 | CQ42: =SUMIF(Financing!$A:$A,"LP",Financing!CC:CC) -> 0 | CR42: =SUMIF(Financing!$A:$A,"LP",Financing!CD:CD) -> 0 | CS42: =SUMIF(Financing!$A:$A,"LP",Financing!CE:CE) -> 0 | CT42: =SUMIF(Financing!$A:$A,"LP",Financing!CF:CF) -> 0 | CU42: =SUMIF(Financing!$A:$A,"LP",Financing!CG:CG) -> 0 | CV42: =SUMIF(Financing!$A:$A,"LP",Financing!CH:CH) -> 0 | CW42: =SUMIF(Financing!$A:$A,"LP",Financing!CI:CI) -> 0 | CX42: =SUMIF(Financing!$A:$A,"LP",Financing!CJ:CJ) -> 0 | CY42: =SUMIF(Financing!$A:$A,"LP",Financing!CK:CK) -> 0 | CZ42: =SUMIF(Financing!$A:$A,"LP",Financing!CL:CL) -> 0 | DA42: =SUMIF(Financing!$A:$A,"LP",Financing!CM:CM) -> 0 | DB42: =SUMIF(Financing!$A:$A,"LP",Financing!CN:CN) -> 0 | DC42: =SUMIF(Financing!$A:$A,"LP",Financing!CO:CO) -> 0 | DD42: =SUMIF(Financing!$A:$A,"LP",Financing!CP:CP) -> 0 | DE42: =SUMIF(Financing!$A:$A,"LP",Financing!CQ:CQ) -> 0 | DF42: =SUMIF(Financing!$A:$A,"LP",Financing!CR:CR) -> 0 | DG42: =SUMIF(Financing!$A:$A,"LP",Financing!CS:CS) -> 0 | DH42: =SUMIF(Financing!$A:$A,"LP",Financing!CT:CT) -> 0 | DI42: =SUMIF(Financing!$A:$A,"LP",Financing!CU:CU) -> 0 | DJ42: =SUMIF(Financing!$A:$A,"LP",Financing!CV:CV) -> 0 | DK42: =SUMIF(Financing!$A:$A,"LP",Financing!CW:CW) -> 0 | DL42: =SUMIF(Financing!$A:$A,"LP",Financing!CX:CX) -> 0 | DM42: =SUMIF(Financing!$A:$A,"LP",Financing!CY:CY) -> 0 | DN42: =SUMIF(Financing!$A:$A,"LP",Financing!CZ:CZ) -> 0 | DO42: =SUMIF(Financing!$A:$A,"LP",Financing!DA:DA) -> 0 | DP42: =SUMIF(Financing!$A:$A,"LP",Financing!DB:DB) -> 0 | DQ42: =SUMIF(Financing!$A:$A,"LP",Financing!DC:DC) -> 0 | DR42: =SUMIF(Financing!$A:$A,"LP",Financing!DD:DD) -> 0 | DS42: =SUMIF(Financing!$A:$A,"LP",Financing!DE:DE) -> 0 | DT42: =SUMIF(Financing!$A:$A,"LP",Financing!DF:DF) -> 0 | DU42: =SUMIF(Financing!$A:$A,"LP",Financing!DG:DG) -> 0 | DV42: =SUMIF(Financing!$A:$A,"LP",Financing!DH:DH) -> 0 | DW42: =SUMIF(Financing!$A:$A,"LP",Financing!DI:DI) -> 0 | DX42: =SUMIF(Financing!$A:$A,"LP",Financing!DJ:DJ) -> 0 | DY42: =SUMIF(Financing!$A:$A,"LP",Financing!DK:DK) -> 0 | DZ42: =SUMIF(Financing!$A:$A,"LP",Financing!DL:DL) -> 0 | EA42: =SUMIF(Financing!$A:$A,"LP",Financing!DM:DM) -> 0 | EB42: =SUMIF(Financing!$A:$A,"LP",Financing!DN:DN) -> 0 | EC42: =SUMIF(Financing!$A:$A,"LP",Financing!DO:DO) -> 0 | ED42: =SUMIF(Financing!$A:$A,"LP",Financing!DP:DP) -> 0 | EE42: =SUMIF(Financing!$A:$A,"LP",Financing!DQ:DQ) -> 0 | EF42: =SUMIF(Financing!$A:$A,"LP",Financing!DR:DR) -> 0 | EG42: =SUMIF(Financing!$A:$A,"LP",Financing!DS:DS) -> 0 | EH42: =SUMIF(Financing!$A:$A,"LP",Financing!DT:DT) -> 0 | EI42: =SUMIF(Financing!$A:$A,"LP",Financing!DU:DU) -> 0 | EJ42: =SUMIF(Financing!$A:$A,"LP",Financing!DV:DV) -> 0 | EK42: =SUMIF(Financing!$A:$A,"LP",Financing!DW:DW) -> 0 | EL42: =SUMIF(Financing!$A:$A,"LP",Financing!DX:DX) -> 0 | EM42: =SUMIF(Financing!$A:$A,"LP",Financing!DY:DY) -> 0 | EN42: =SUMIF(Financing!$A:$A,"LP",Financing!DZ:DZ) -> 0 | EO42: =SUMIF(Financing!$A:$A,"LP",Financing!EA:EA) -> 0 | EP42: =SUMIF(Financing!$A:$A,"LP",Financing!EB:EB) -> 0 | EQ42: =SUMIF(Financing!$A:$A,"LP",Financing!EC:EC) -> 0 | ER42: =SUMIF(Financing!$A:$A,"LP",Financing!ED:ED) -> 0 | ES42: =SUMIF(Financing!$A:$A,"LP",Financing!EE:EE) -> 0
A43: =SUM(C43:M43) -> -1260000 | B43: Loan Fees | C43: =SUMIF($Q$2:$ES$2,C$2,$Q43:$ES43) -> -1260000 | D43: =SUMIF($R$2:$ES$2,D$2,$R43:$ES43) -> 0 | E43: =SUMIF($R$2:$ES$2,E$2,$R43:$ES43) -> 0 | F43: =SUMIF($R$2:$ES$2,F$2,$R43:$ES43) -> 0 | G43: =SUMIF($R$2:$ES$2,G$2,$R43:$ES43) -> 0 | H43: =SUMIF($R$2:$ES$2,H$2,$R43:$ES43) -> 0 | I43: =SUMIF($R$2:$ES$2,I$2,$R43:$ES43) -> 0 | J43: =SUMIF($R$2:$ES$2,J$2,$R43:$ES43) -> 0 | K43: =SUMIF($R$2:$ES$2,K$2,$R43:$ES43) -> 0 | ... M43: =SUMIF($R$2:$ES$2,M$2,$R43:$ES43) -> 0 | O43: =SUM(Q43:ES43) -> -1260000 | P43: Loan Fees | Q43: =-Financing!D3*ACQ_LOAN_FEE-Financing!E3*MEZZ_LOAN_FEE -> -1260000 | R43: =-R39*REFI_LOAN_FEE-(Financing!D26*ACQ_LOAN_FEE+Financing!D39*MEZZ_LOAN_FEE+Financing!D52*REFI_LOAN_FEE) -> 0 | S43: =-S39*REFI_LOAN_FEE-(Financing!E26*ACQ_LOAN_FEE+Financing!E39*MEZZ_LOAN_FEE+Financing!E52*REFI_LOAN_FEE) -> 0 | T43: =-T39*REFI_LOAN_FEE-(Financing!F26*ACQ_LOAN_FEE+Financing!F39*MEZZ_LOAN_FEE+Financing!F52*REFI_LOAN_FEE) -> 0 | U43: =-U39*REFI_LOAN_FEE-(Financing!G26*ACQ_LOAN_FEE+Financing!G39*MEZZ_LOAN_FEE+Financing!G52*REFI_LOAN_FEE) -> 0 | V43: =-V39*REFI_LOAN_FEE-(Financing!H26*ACQ_LOAN_FEE+Financing!H39*MEZZ_LOAN_FEE+Financing!H52*REFI_LOAN_FEE) -> 0 | W43: =-W39*REFI_LOAN_FEE-(Financing!I26*ACQ_LOAN_FEE+Financing!I39*MEZZ_LOAN_FEE+Financing!I52*REFI_LOAN_FEE) -> 0 | X43: =-X39*REFI_LOAN_FEE-(Financing!J26*ACQ_LOAN_FEE+Financing!J39*MEZZ_LOAN_FEE+Financing!J52*REFI_LOAN_FEE) -> 0 | Y43: =-Y39*REFI_LOAN_FEE-(Financing!K26*ACQ_LOAN_FEE+Financing!K39*MEZZ_LOAN_FEE+Financing!K52*REFI_LOAN_FEE) -> 0 | ... ES43: =-ES39*REFI_LOAN_FEE-(Financing!EE26*ACQ_LOAN_FEE+Financing!EE39*MEZZ_LOAN_FEE+Financing!EE52*REFI_LOAN_FEE) -> 0
A44: =SUM(C44:M44) -> 0 | B44: Prepayment Penalties | D44: =SUMIF($R$2:$ES$2,D$2,$R44:$ES44) -> 0 | E44: =SUMIF($R$2:$ES$2,E$2,$R44:$ES44) -> 0 | F44: =SUMIF($R$2:$ES$2,F$2,$R44:$ES44) -> 0 | G44: =SUMIF($R$2:$ES$2,G$2,$R44:$ES44) -> 0 | H44: =SUMIF($R$2:$ES$2,H$2,$R44:$ES44) -> 0 | I44: =SUMIF($R$2:$ES$2,I$2,$R44:$ES44) -> 0 | J44: =SUMIF($R$2:$ES$2,J$2,$R44:$ES44) -> 0 | K44: =SUMIF($R$2:$ES$2,K$2,$R44:$ES44) -> 0 | ... M44: =SUMIF($R$2:$ES$2,M$2,$R44:$ES44) -> 0 | O44: =SUM(Q44:ES44) -> 0 | P44: Prepayment Penalties | R44: =SUMIF(Financing!$A:$A,"PRP",Financing!D:D) -> 0 | S44: =SUMIF(Financing!$A:$A,"PRP",Financing!E:E) -> 0 | T44: =SUMIF(Financing!$A:$A,"PRP",Financing!F:F) -> 0 | U44: =SUMIF(Financing!$A:$A,"PRP",Financing!G:G) -> 0 | V44: =SUMIF(Financing!$A:$A,"PRP",Financing!H:H) -> 0 | W44: =SUMIF(Financing!$A:$A,"PRP",Financing!I:I) -> 0 | X44: =SUMIF(Financing!$A:$A,"PRP",Financing!J:J) -> 0 | Y44: =SUMIF(Financing!$A:$A,"PRP",Financing!K:K) -> 0 | Z44: =SUMIF(Financing!$A:$A,"PRP",Financing!L:L) -> 0 | AA44: =SUMIF(Financing!$A:$A,"PRP",Financing!M:M) -> 0 | AB44: =SUMIF(Financing!$A:$A,"PRP",Financing!N:N) -> 0 | AC44: =SUMIF(Financing!$A:$A,"PRP",Financing!O:O) -> 0 | AD44: =SUMIF(Financing!$A:$A,"PRP",Financing!P:P) -> 0 | AE44: =SUMIF(Financing!$A:$A,"PRP",Financing!Q:Q) -> 0 | AF44: =SUMIF(Financing!$A:$A,"PRP",Financing!R:R) -> 0 | AG44: =SUMIF(Financing!$A:$A,"PRP",Financing!S:S) -> 0 | AH44: =SUMIF(Financing!$A:$A,"PRP",Financing!T:T) -> 0 | AI44: =SUMIF(Financing!$A:$A,"PRP",Financing!U:U) -> 0 | AJ44: =SUMIF(Financing!$A:$A,"PRP",Financing!V:V) -> 0 | AK44: =SUMIF(Financing!$A:$A,"PRP",Financing!W:W) -> 0 | AL44: =SUMIF(Financing!$A:$A,"PRP",Financing!X:X) -> 0 | AM44: =SUMIF(Financing!$A:$A,"PRP",Financing!Y:Y) -> 0 | AN44: =SUMIF(Financing!$A:$A,"PRP",Financing!Z:Z) -> 0 | AO44: =SUMIF(Financing!$A:$A,"PRP",Financing!AA:AA) -> 0 | AP44: =SUMIF(Financing!$A:$A,"PRP",Financing!AB:AB) -> 0 | AQ44: =SUMIF(Financing!$A:$A,"PRP",Financing!AC:AC) -> 0 | AR44: =SUMIF(Financing!$A:$A,"PRP",Financing!AD:AD) -> 0 | AS44: =SUMIF(Financing!$A:$A,"PRP",Financing!AE:AE) -> 0 | AT44: =SUMIF(Financing!$A:$A,"PRP",Financing!AF:AF) -> 0 | AU44: =SUMIF(Financing!$A:$A,"PRP",Financing!AG:AG) -> 0 | AV44: =SUMIF(Financing!$A:$A,"PRP",Financing!AH:AH) -> 0 | AW44: =SUMIF(Financing!$A:$A,"PRP",Financing!AI:AI) -> 0 | AX44: =SUMIF(Financing!$A:$A,"PRP",Financing!AJ:AJ) -> 0 | AY44: =SUMIF(Financing!$A:$A,"PRP",Financing!AK:AK) -> 0 | AZ44: =SUMIF(Financing!$A:$A,"PRP",Financing!AL:AL) -> 0 | BA44: =SUMIF(Financing!$A:$A,"PRP",Financing!AM:AM) -> 0 | BB44: =SUMIF(Financing!$A:$A,"PRP",Financing!AN:AN) -> 0 | BC44: =SUMIF(Financing!$A:$A,"PRP",Financing!AO:AO) -> 0 | BD44: =SUMIF(Financing!$A:$A,"PRP",Financing!AP:AP) -> 0 | BE44: =SUMIF(Financing!$A:$A,"PRP",Financing!AQ:AQ) -> 0 | BF44: =SUMIF(Financing!$A:$A,"PRP",Financing!AR:AR) -> 0 | BG44: =SUMIF(Financing!$A:$A,"PRP",Financing!AS:AS) -> 0 | BH44: =SUMIF(Financing!$A:$A,"PRP",Financing!AT:AT) -> 0 | BI44: =SUMIF(Financing!$A:$A,"PRP",Financing!AU:AU) -> 0 | BJ44: =SUMIF(Financing!$A:$A,"PRP",Financing!AV:AV) -> 0 | BK44: =SUMIF(Financing!$A:$A,"PRP",Financing!AW:AW) -> 0 | BL44: =SUMIF(Financing!$A:$A,"PRP",Financing!AX:AX) -> 0 | BM44: =SUMIF(Financing!$A:$A,"PRP",Financing!AY:AY) -> 0 | BN44: =SUMIF(Financing!$A:$A,"PRP",Financing!AZ:AZ) -> 0 | BO44: =SUMIF(Financing!$A:$A,"PRP",Financing!BA:BA) -> 0 | BP44: =SUMIF(Financing!$A:$A,"PRP",Financing!BB:BB) -> 0 | BQ44: =SUMIF(Financing!$A:$A,"PRP",Financing!BC:BC) -> 0 | BR44: =SUMIF(Financing!$A:$A,"PRP",Financing!BD:BD) -> 0 | BS44: =SUMIF(Financing!$A:$A,"PRP",Financing!BE:BE) -> 0 | BT44: =SUMIF(Financing!$A:$A,"PRP",Financing!BF:BF) -> 0 | BU44: =SUMIF(Financing!$A:$A,"PRP",Financing!BG:BG) -> 0 | BV44: =SUMIF(Financing!$A:$A,"PRP",Financing!BH:BH) -> 0 | BW44: =SUMIF(Financing!$A:$A,"PRP",Financing!BI:BI) -> 0 | BX44: =SUMIF(Financing!$A:$A,"PRP",Financing!BJ:BJ) -> 0 | BY44: =SUMIF(Financing!$A:$A,"PRP",Financing!BK:BK) -> 0 | BZ44: =SUMIF(Financing!$A:$A,"PRP",Financing!BL:BL) -> 0 | CA44: =SUMIF(Financing!$A:$A,"PRP",Financing!BM:BM) -> 0 | CB44: =SUMIF(Financing!$A:$A,"PRP",Financing!BN:BN) -> 0 | CC44: =SUMIF(Financing!$A:$A,"PRP",Financing!BO:BO) -> 0 | CD44: =SUMIF(Financing!$A:$A,"PRP",Financing!BP:BP) -> 0 | CE44: =SUMIF(Financing!$A:$A,"PRP",Financing!BQ:BQ) -> 0 | CF44: =SUMIF(Financing!$A:$A,"PRP",Financing!BR:BR) -> 0 | CG44: =SUMIF(Financing!$A:$A,"PRP",Financing!BS:BS) -> 0 | CH44: =SUMIF(Financing!$A:$A,"PRP",Financing!BT:BT) -> 0 | CI44: =SUMIF(Financing!$A:$A,"PRP",Financing!BU:BU) -> 0 | CJ44: =SUMIF(Financing!$A:$A,"PRP",Financing!BV:BV) -> 0 | CK44: =SUMIF(Financing!$A:$A,"PRP",Financing!BW:BW) -> 0 | CL44: =SUMIF(Financing!$A:$A,"PRP",Financing!BX:BX) -> 0 | CM44: =SUMIF(Financing!$A:$A,"PRP",Financing!BY:BY) -> 0 | CN44: =SUMIF(Financing!$A:$A,"PRP",Financing!BZ:BZ) -> 0 | CO44: =SUMIF(Financing!$A:$A,"PRP",Financing!CA:CA) -> 0 | CP44: =SUMIF(Financing!$A:$A,"PRP",Financing!CB:CB) -> 0 | CQ44: =SUMIF(Financing!$A:$A,"PRP",Financing!CC:CC) -> 0 | CR44: =SUMIF(Financing!$A:$A,"PRP",Financing!CD:CD) -> 0 | CS44: =SUMIF(Financing!$A:$A,"PRP",Financing!CE:CE) -> 0 | CT44: =SUMIF(Financing!$A:$A,"PRP",Financing!CF:CF) -> 0 | CU44: =SUMIF(Financing!$A:$A,"PRP",Financing!CG:CG) -> 0 | CV44: =SUMIF(Financing!$A:$A,"PRP",Financing!CH:CH) -> 0 | CW44: =SUMIF(Financing!$A:$A,"PRP",Financing!CI:CI) -> 0 | CX44: =SUMIF(Financing!$A:$A,"PRP",Financing!CJ:CJ) -> 0 | CY44: =SUMIF(Financing!$A:$A,"PRP",Financing!CK:CK) -> 0 | CZ44: =SUMIF(Financing!$A:$A,"PRP",Financing!CL:CL) -> 0 | DA44: =SUMIF(Financing!$A:$A,"PRP",Financing!CM:CM) -> 0 | DB44: =SUMIF(Financing!$A:$A,"PRP",Financing!CN:CN) -> 0 | DC44: =SUMIF(Financing!$A:$A,"PRP",Financing!CO:CO) -> 0 | DD44: =SUMIF(Financing!$A:$A,"PRP",Financing!CP:CP) -> 0 | DE44: =SUMIF(Financing!$A:$A,"PRP",Financing!CQ:CQ) -> 0 | DF44: =SUMIF(Financing!$A:$A,"PRP",Financing!CR:CR) -> 0 | DG44: =SUMIF(Financing!$A:$A,"PRP",Financing!CS:CS) -> 0 | DH44: =SUMIF(Financing!$A:$A,"PRP",Financing!CT:CT) -> 0 | DI44: =SUMIF(Financing!$A:$A,"PRP",Financing!CU:CU) -> 0 | DJ44: =SUMIF(Financing!$A:$A,"PRP",Financing!CV:CV) -> 0 | DK44: =SUMIF(Financing!$A:$A,"PRP",Financing!CW:CW) -> 0 | DL44: =SUMIF(Financing!$A:$A,"PRP",Financing!CX:CX) -> 0 | DM44: =SUMIF(Financing!$A:$A,"PRP",Financing!CY:CY) -> 0 | DN44: =SUMIF(Financing!$A:$A,"PRP",Financing!CZ:CZ) -> 0 | DO44: =SUMIF(Financing!$A:$A,"PRP",Financing!DA:DA) -> 0 | DP44: =SUMIF(Financing!$A:$A,"PRP",Financing!DB:DB) -> 0 | DQ44: =SUMIF(Financing!$A:$A,"PRP",Financing!DC:DC) -> 0 | DR44: =SUMIF(Financing!$A:$A,"PRP",Financing!DD:DD) -> 0 | DS44: =SUMIF(Financing!$A:$A,"PRP",Financing!DE:DE) -> 0 | DT44: =SUMIF(Financing!$A:$A,"PRP",Financing!DF:DF) -> 0 | DU44: =SUMIF(Financing!$A:$A,"PRP",Financing!DG:DG) -> 0 | DV44: =SUMIF(Financing!$A:$A,"PRP",Financing!DH:DH) -> 0 | DW44: =SUMIF(Financing!$A:$A,"PRP",Financing!DI:DI) -> 0 | DX44: =SUMIF(Financing!$A:$A,"PRP",Financing!DJ:DJ) -> 0 | DY44: =SUMIF(Financing!$A:$A,"PRP",Financing!DK:DK) -> 0 | DZ44: =SUMIF(Financing!$A:$A,"PRP",Financing!DL:DL) -> 0 | EA44: =SUMIF(Financing!$A:$A,"PRP",Financing!DM:DM) -> 0 | EB44: =SUMIF(Financing!$A:$A,"PRP",Financing!DN:DN) -> 0 | EC44: =SUMIF(Financing!$A:$A,"PRP",Financing!DO:DO) -> 0 | ED44: =SUMIF(Financing!$A:$A,"PRP",Financing!DP:DP) -> 0 | EE44: =SUMIF(Financing!$A:$A,"PRP",Financing!DQ:DQ) -> 0 | EF44: =SUMIF(Financing!$A:$A,"PRP",Financing!DR:DR) -> 0 | EG44: =SUMIF(Financing!$A:$A,"PRP",Financing!DS:DS) -> 0 | EH44: =SUMIF(Financing!$A:$A,"PRP",Financing!DT:DT) -> 0 | EI44: =SUMIF(Financing!$A:$A,"PRP",Financing!DU:DU) -> 0 | EJ44: =SUMIF(Financing!$A:$A,"PRP",Financing!DV:DV) -> 0 | EK44: =SUMIF(Financing!$A:$A,"PRP",Financing!DW:DW) -> 0 | EL44: =SUMIF(Financing!$A:$A,"PRP",Financing!DX:DX) -> 0 | EM44: =SUMIF(Financing!$A:$A,"PRP",Financing!DY:DY) -> 0 | EN44: =SUMIF(Financing!$A:$A,"PRP",Financing!DZ:DZ) -> 0 | EO44: =SUMIF(Financing!$A:$A,"PRP",Financing!EA:EA) -> 0 | EP44: =SUMIF(Financing!$A:$A,"PRP",Financing!EB:EB) -> 0 | EQ44: =SUMIF(Financing!$A:$A,"PRP",Financing!EC:EC) -> 0 | ER44: =SUMIF(Financing!$A:$A,"PRP",Financing!ED:ED) -> 0 | ES44: =SUMIF(Financing!$A:$A,"PRP",Financing!EE:EE) -> 0
B46: Working Capital | P46: Working Capital
A47: =SUM(C47:M47) -> 0 | B47: Working Capital Contributed | C47: =SUMIF($Q$2:$ES$2,C$2,$Q47:$ES47) -> 0 | O47: =SUM(Q47:ES47) -> 0 | P47: Working Capital Contributed | Q47: =-WORKING_CAP -> 0
A48: =SUM(C48:M48) -> 0 | B48: Working Capital Distributed | D48: =SUMIF($R$2:$ES$2,D$2,$R48:$ES48) -> 0 | E48: =SUMIF($R$2:$ES$2,E$2,$R48:$ES48) -> 0 | F48: =SUMIF($R$2:$ES$2,F$2,$R48:$ES48) -> 0 | G48: =SUMIF($R$2:$ES$2,G$2,$R48:$ES48) -> 0 | H48: =SUMIF($R$2:$ES$2,H$2,$R48:$ES48) -> 0 | I48: =SUMIF($R$2:$ES$2,I$2,$R48:$ES48) -> 0 | J48: =SUMIF($R$2:$ES$2,J$2,$R48:$ES48) -> 0 | K48: =SUMIF($R$2:$ES$2,K$2,$R48:$ES48) -> 0 | ... M48: =SUMIF($R$2:$ES$2,M$2,$R48:$ES48) -> 0 | O48: =SUM(Q48:ES48) -> 0 | P48: Working Capital Distributed | R48: =IF(R$3=HOLD_PERIOD,Q62,IF(SUM(R18,R39:R44)<0,MIN(-SUM(R18,R39:R44),Q62),0)) -> 0 | S48: =IF(S$3=HOLD_PERIOD,R62,IF(SUM(S18,S39:S44)<0,MIN(-SUM(S18,S39:S44),R62),0)) -> 0 | T48: =IF(T$3=HOLD_PERIOD,S62,IF(SUM(T18,T39:T44)<0,MIN(-SUM(T18,T39:T44),S62),0)) -> 0 | U48: =IF(U$3=HOLD_PERIOD,T62,IF(SUM(U18,U39:U44)<0,MIN(-SUM(U18,U39:U44),T62),0)) -> 0 | V48: =IF(V$3=HOLD_PERIOD,U62,IF(SUM(V18,V39:V44)<0,MIN(-SUM(V18,V39:V44),U62),0)) -> 0 | W48: =IF(W$3=HOLD_PERIOD,V62,IF(SUM(W18,W39:W44)<0,MIN(-SUM(W18,W39:W44),V62),0)) -> 0 | X48: =IF(X$3=HOLD_PERIOD,W62,IF(SUM(X18,X39:X44)<0,MIN(-SUM(X18,X39:X44),W62),0)) -> 0 | Y48: =IF(Y$3=HOLD_PERIOD,X62,IF(SUM(Y18,Y39:Y44)<0,MIN(-SUM(Y18,Y39:Y44),X62),0)) -> 0 | ... ES48: =IF(ES$3=HOLD_PERIOD,ER62,IF(SUM(ES18,ES39:ES44)<0,MIN(-SUM(ES18,ES39:ES44),ER62),0)) -> 0
A50: =SUM(C50:M50) -> 54768889 | B50: Total Levered Cash Flow | C50: =SUMIF($Q$2:$ES$2,C$2,$Q50:$ES50) -> -57060000 | D50: =SUMIF($R$2:$ES$2,D$2,$R50:$ES50) -> -1695953.5 | E50: =SUMIF($R$2:$ES$2,E$2,$R50:$ES50) -> 2858712.5 | F50: =SUMIF($R$2:$ES$2,F$2,$R50:$ES50) -> 3940904.2 | G50: =SUMIF($R$2:$ES$2,G$2,$R50:$ES50) -> 3118269.3 | H50: =SUMIF($R$2:$ES$2,H$2,$R50:$ES50) -> 1.0360696e+08 | I50: =SUMIF($R$2:$ES$2,I$2,$R50:$ES50) -> 0 | J50: =SUMIF($R$2:$ES$2,J$2,$R50:$ES50) -> 0 | K50: =SUMIF($R$2:$ES$2,K$2,$R50:$ES50) -> 0 | ... M50: =SUMIF($R$2:$ES$2,M$2,$R50:$ES50) -> 0 | O50: =SUM(Q50:ES50) -> 54768889 | P50: Total Levered Cash Flow | Q50: =SUM(Q36:Q48) -> -57060000 | R50: =SUM(R36:R48) -> -122025.85 | S50: =SUM(S36:S48) -> -123343.6 | T50: =SUM(T36:T48) -> -124398.07 | U50: =SUM(U36:U48) -> -125444.61 | V50: =SUM(V36:V48) -> -135761.58 | W50: =SUM(W36:W48) -> -250903.71 | X50: =SUM(X36:X48) -> -137568.43 | ... ES50: =SUM(ES36:ES48) -> 0
B52: Investor Distributions | P52: Investor Distributions
A53: =SUM(C53:M53) -> 0 | B53: Beginning Cash Balance | C53: =Q53 -> 0 | D53: =C59 -> 0 | E53: =D59 -> 0 | F53: =E59 -> 0 | G53: =F59 -> 0 | H53: =G59 -> 0 | I53: =H59 -> 0 | J53: =I59 -> 0 | K53: =J59 -> 0 | ... M53: =L59 -> 0 | O53: =SUM(Q53:ES53) -> 0 | P53: Beginning Cash Balance | Q53: 0 | R53: =Q59 -> 0 | S53: =R59 -> 0 | T53: =S59 -> 0 | U53: =T59 -> 0 | V53: =U59 -> 0 | W53: =V59 -> 0 | X53: =W59 -> 0 | Y53: =X59 -> 0 | ... ES53: =ER59 -> 0
A54: =SUM(C54:M54) -> 1.1182889e+08 | B54: Positive Cash Flow | C54: =Q54 -> 0 | D54: =SUMIF($R$2:$ES$2,D$2,$R54:$ES54) -> -1695953.5 | E54: =SUMIF($R$2:$ES$2,E$2,$R54:$ES54) -> 2858712.5 | F54: =SUMIF($R$2:$ES$2,F$2,$R54:$ES54) -> 3940904.2 | G54: =SUMIF($R$2:$ES$2,G$2,$R54:$ES54) -> 3118269.3 | H54: =SUMIF($R$2:$ES$2,H$2,$R54:$ES54) -> 1.0360696e+08 | I54: =SUMIF($R$2:$ES$2,I$2,$R54:$ES54) -> 0 | J54: =SUMIF($R$2:$ES$2,J$2,$R54:$ES54) -> 0 | K54: =SUMIF($R$2:$ES$2,K$2,$R54:$ES54) -> 0 | ... M54: =SUMIF($R$2:$ES$2,M$2,$R54:$ES54) -> 0 | O54: =SUM(Q54:ES54) -> 1.1182889e+08 | P54: Project-Level Cash Flow | Q54: 0 | R54: =R50 -> -122025.85 | S54: =S50 -> -123343.6 | T54: =T50 -> -124398.07 | U54: =U50 -> -125444.61 | V54: =V50 -> -135761.58 | W54: =W50 -> -250903.71 | X54: =X50 -> -137568.43 | Y54: =Y50 -> -139369.18 | ... ES54: =ES50 -> 0
A55: =SUM(C55:M55) -> -58755953 | B55: Capital Contributions | C55: =Q55 -> -57060000 | D55: =SUMIF($R$2:$ES$2,D$2,$R55:$ES55) -> -1695953.5 | E55: =SUMIF($R$2:$ES$2,E$2,$R55:$ES55) -> 0 | F55: =SUMIF($R$2:$ES$2,F$2,$R55:$ES55) -> 0 | G55: =SUMIF($R$2:$ES$2,G$2,$R55:$ES55) -> 0 | H55: =SUMIF($R$2:$ES$2,H$2,$R55:$ES55) -> 0 | I55: =SUMIF($R$2:$ES$2,I$2,$R55:$ES55) -> 0 | J55: =SUMIF($R$2:$ES$2,J$2,$R55:$ES55) -> 0 | K55: =SUMIF($R$2:$ES$2,K$2,$R55:$ES55) -> 0 | ... M55: =SUMIF($R$2:$ES$2,M$2,$R55:$ES55) -> 0 | O55: =SUM(Q55:ES55) -> -58755953 | P55: Capital Contributions | Q55: =IF(Q50<0,Q50,0) -> -57060000 | R55: =MIN(R54+R53,0) -> -122025.85 | S55: =MIN(S54+S53,0) -> -123343.6 | T55: =MIN(T54+T53,0) -> -124398.07 | U55: =MIN(U54+U53,0) -> -125444.61 | V55: =MIN(V54+V53,0) -> -135761.58 | W55: =MIN(W54+W53,0) -> -250903.71 | X55: =MIN(X54+X53,0) -> -137568.43 | Y55: =MIN(Y54+Y53,0) -> -139369.18 | ... ES55: =MIN(ES54+ES53,0) -> 0
A56: =SUM(C56:M56) -> 0 | B56: Operating Shortfall Reserve | C56: =Q56 -> -1582377 | D56: =SUMIF($R$2:$ES$2,D$2,$R56:$ES56) -> 1582377 | E56: =SUMIF($R$2:$ES$2,E$2,$R56:$ES56) -> 0 | F56: =SUMIF($R$2:$ES$2,F$2,$R56:$ES56) -> 0 | G56: =SUMIF($R$2:$ES$2,G$2,$R56:$ES56) -> 0 | H56: =SUMIF($R$2:$ES$2,H$2,$R56:$ES56) -> 0 | I56: =SUMIF($R$2:$ES$2,I$2,$R56:$ES56) -> 0 | J56: =SUMIF($R$2:$ES$2,J$2,$R56:$ES56) -> 0 | K56: =SUMIF($R$2:$ES$2,K$2,$R56:$ES56) -> 0 | ... M56: =SUMIF($R$2:$ES$2,M$2,$R56:$ES56) -> 0 | O56: =SUM(Q56:ES56) -> -2.3283064e-10 | P56: Operating Shortfall Reserve | Q56: =-Summary!E33 -> -1582377 | R56: =-IF(AND(R$3<=HOLD_PERIOD,SUM(R14,R20,R41,R48)<0),SUM(R14,R20,R41,R48),0) -> 122025.85 | S56: =-IF(AND(S$3<=HOLD_PERIOD,SUM(S14,S20,S41,S48)<0),SUM(S14,S20,S41,S48),0) -> 123343.6 | T56: =-IF(AND(T$3<=HOLD_PERIOD,SUM(T14,T20,T41,T48)<0),SUM(T14,T20,T41,T48),0) -> 124398.07 | U56: =-IF(AND(U$3<=HOLD_PERIOD,SUM(U14,U20,U41,U48)<0),SUM(U14,U20,U41,U48),0) -> 125444.61 | V56: =-IF(AND(V$3<=HOLD_PERIOD,SUM(V14,V20,V41,V48)<0),SUM(V14,V20,V41,V48),0) -> 135761.58 | W56: =-IF(AND(W$3<=HOLD_PERIOD,SUM(W14,W20,W41,W48)<0),SUM(W14,W20,W41,W48),0) -> 137327.29 | X56: =-IF(AND(X$3<=HOLD_PERIOD,SUM(X14,X20,X41,X48)<0),SUM(X14,X20,X41,X48),0) -> 137568.43 | Y56: =-IF(AND(Y$3<=HOLD_PERIOD,SUM(Y14,Y20,Y41,Y48)<0),SUM(Y14,Y20,Y41,Y48),0) -> 139369.18 | ... ES56: =-IF(AND(ES$3<=HOLD_PERIOD,SUM(ES14,ES20,ES41,ES48)<0),SUM(ES14,ES20,ES41,ES48),0) -> 0
A57: =SUM(C57:M57) -> 2.910383e-11 | B57: TI/LC Reserve | C57: =Q57 -> -457082.1 | D57: =SUMIF($R$2:$ES$2,D$2,$R57:$ES57) -> 113576.43 | E57: =SUMIF($R$2:$ES$2,E$2,$R57:$ES57) -> 82964.871 | F57: =SUMIF($R$2:$ES$2,F$2,$R57:$ES57) -> 82971.826 | G57: =SUMIF($R$2:$ES$2,G$2,$R57:$ES57) -> 177568.98 | H57: =SUMIF($R$2:$ES$2,H$2,$R57:$ES57) -> 0 | I57: =SUMIF($R$2:$ES$2,I$2,$R57:$ES57) -> 0 | J57: =SUMIF($R$2:$ES$2,J$2,$R57:$ES57) -> 0 | K57: =SUMIF($R$2:$ES$2,K$2,$R57:$ES57) -> 0 | ... M57: =SUMIF($R$2:$ES$2,M$2,$R57:$ES57) -> 0 | O57: =SUM(Q57:ES57) -> 2.910383e-11 | P57: TI/LC Reserve | Q57: =-Summary!E31 -> -457082.1 | R57: =-IF(R$3<=HOLD_PERIOD,SUMIF(Leases!$B170:$B955,"TI",Leases!D170:D955),0)-IF(R$3<=HOLD_PERIOD,SUMIF(Leases!$B170:$B955,"LC",Leases!D170:D955)+IF(AND(R$56=0,R$16<0,(R14+R20+R41)<0),R14+R20+R41,0),0) -> 0 | S57: =-IF(S$3<=HOLD_PERIOD,SUMIF(Leases!$B170:$B955,"TI",Leases!E170:E955),0)-IF(S$3<=HOLD_PERIOD,SUMIF(Leases!$B170:$B955,"LC",Leases!E170:E955)+IF(AND(S$56=0,S$16<0,(S14+S20+S41)<0),S14+S20+S41,0),0) -> 0 | T57: =-IF(T$3<=HOLD_PERIOD,SUMIF(Leases!$B170:$B955,"TI",Leases!F170:F955),0)-IF(T$3<=HOLD_PERIOD,SUMIF(Leases!$B170:$B955,"LC",Leases!F170:F955)+IF(AND(T$56=0,T$16<0,(T14+T20+T41)<0),T14+T20+T41,0),0) -> 0 | U57: =-IF(U$3<=HOLD_PERIOD,SUMIF(Leases!$B170:$B955,"TI",Leases!G170:G955),0)-IF(U$3<=HOLD_PERIOD,SUMIF(Leases!$B170:$B955,"LC",Leases!G170:G955)+IF(AND(U$56=0,U$16<0,(U14+U20+U41)<0),U14+U20+U41,0),0) -> 0 | V57: =-IF(V$3<=HOLD_PERIOD,SUMIF(Leases!$B170:$B955,"TI",Leases!H170:H955),0)-IF(V$3<=HOLD_PERIOD,SUMIF(Leases!$B170:$B955,"LC",Leases!H170:H955)+IF(AND(V$56=0,V$16<0,(V14+V20+V41)<0),V14+V20+V41,0),0) -> 0 | W57: =-IF(W$3<=HOLD_PERIOD,SUMIF(Leases!$B170:$B955,"TI",Leases!I170:I955),0)-IF(W$3<=HOLD_PERIOD,SUMIF(Leases!$B170:$B955,"LC",Leases!I170:I955)+IF(AND(W$56=0,W$16<0,(W14+W20+W41)<0),W14+W20+W41,0),0) -> 113576.43 | X57: =-IF(X$3<=HOLD_PERIOD,SUMIF(Leases!$B170:$B955,"TI",Leases!J170:J955),0)-IF(X$3<=HOLD_PERIOD,SUMIF(Leases!$B170:$B955,"LC",Leases!J170:J955)+IF(AND(X$56=0,X$16<0,(X14+X20+X41)<0),X14+X20+X41,0),0) -> 0 | Y57: =-IF(Y$3<=HOLD_PERIOD,SUMIF(Leases!$B170:$B955,"TI",Leases!K170:K955),0)-IF(Y$3<=HOLD_PERIOD,SUMIF(Leases!$B170:$B955,"LC",Leases!K170:K955)+IF(AND(Y$56=0,Y$16<0,(Y14+Y20+Y41)<0),Y14+Y20+Y41,0),0) -> 0 | ... ES57: =-IF(ES$3<=HOLD_PERIOD,SUMIF(Leases!$B170:$B955,"TI",Leases!EE170:EE955),0)-IF(ES$3<=HOLD_PERIOD,SUMIF(Leases!$B170:$B955,"LC",Leases!EE170:EE955)+IF(AND(ES$56=0,ES$16<0,(ES14+ES20+ES41)<0),ES14+ES20+ES41,0),0) -> 0
A58: =SUM(C58:M58) -> 1.1352484e+08 | B58: Capital Distributions | C58: =Q58 -> 0 | D58: =SUMIF($R$2:$ES$2,D$2,$R58:$ES58) -> 0 | E58: =SUMIF($R$2:$ES$2,E$2,$R58:$ES58) -> 2858712.5 | F58: =SUMIF($R$2:$ES$2,F$2,$R58:$ES58) -> 3940904.2 | G58: =SUMIF($R$2:$ES$2,G$2,$R58:$ES58) -> 3118269.3 | H58: =SUMIF($R$2:$ES$2,H$2,$R58:$ES58) -> 1.0360696e+08 | I58: =SUMIF($R$2:$ES$2,I$2,$R58:$ES58) -> 0 | J58: =SUMIF($R$2:$ES$2,J$2,$R58:$ES58) -> 0 | K58: =SUMIF($R$2:$ES$2,K$2,$R58:$ES58) -> 0 | ... M58: =SUMIF($R$2:$ES$2,M$2,$R58:$ES58) -> 0 | O58: =SUM(Q58:ES58) -> 1.1352484e+08 | P58: Capital Distributions | Q58: 0 | R58: =IF(R$3=HOLD_PERIOD,R53+R54,IF(SUM(R53:R55)<=0,0,IF(DISTRIBUTION_FREQ="Monthly",SUM(R53:R54),IF(DISTRIBUTION_FREQ="Quarterly",IF(MOD(R3,3)=0,SUM(R53:R54),0),IF(DISTRIBUTION_FREQ="Annually",IF(S2-R2=1,SUM(R53:R54),0)))))) -> 0 | S58: =IF(S$3=HOLD_PERIOD,S53+S54,IF(SUM(S53:S55)<=0,0,IF(DISTRIBUTION_FREQ="Monthly",SUM(S53:S54),IF(DISTRIBUTION_FREQ="Quarterly",IF(MOD(S3,3)=0,SUM(S53:S54),0),IF(DISTRIBUTION_FREQ="Annually",IF(T2-S2=1,SUM(S53:S54),0)))))) -> 0 | T58: =IF(T$3=HOLD_PERIOD,T53+T54,IF(SUM(T53:T55)<=0,0,IF(DISTRIBUTION_FREQ="Monthly",SUM(T53:T54),IF(DISTRIBUTION_FREQ="Quarterly",IF(MOD(T3,3)=0,SUM(T53:T54),0),IF(DISTRIBUTION_FREQ="Annually",IF(U2-T2=1,SUM(T53:T54),0)))))) -> 0 | U58: =IF(U$3=HOLD_PERIOD,U53+U54,IF(SUM(U53:U55)<=0,0,IF(DISTRIBUTION_FREQ="Monthly",SUM(U53:U54),IF(DISTRIBUTION_FREQ="Quarterly",IF(MOD(U3,3)=0,SUM(U53:U54),0),IF(DISTRIBUTION_FREQ="Annually",IF(V2-U2=1,SUM(U53:U54),0)))))) -> 0 | V58: =IF(V$3=HOLD_PERIOD,V53+V54,IF(SUM(V53:V55)<=0,0,IF(DISTRIBUTION_FREQ="Monthly",SUM(V53:V54),IF(DISTRIBUTION_FREQ="Quarterly",IF(MOD(V3,3)=0,SUM(V53:V54),0),IF(DISTRIBUTION_FREQ="Annually",IF(W2-V2=1,SUM(V53:V54),0)))))) -> 0 | W58: =IF(W$3=HOLD_PERIOD,W53+W54,IF(SUM(W53:W55)<=0,0,IF(DISTRIBUTION_FREQ="Monthly",SUM(W53:W54),IF(DISTRIBUTION_FREQ="Quarterly",IF(MOD(W3,3)=0,SUM(W53:W54),0),IF(DISTRIBUTION_FREQ="Annually",IF(X2-W2=1,SUM(W53:W54),0)))))) -> 0 | X58: =IF(X$3=HOLD_PERIOD,X53+X54,IF(SUM(X53:X55)<=0,0,IF(DISTRIBUTION_FREQ="Monthly",SUM(X53:X54),IF(DISTRIBUTION_FREQ="Quarterly",IF(MOD(X3,3)=0,SUM(X53:X54),0),IF(DISTRIBUTION_FREQ="Annually",IF(Y2-X2=1,SUM(X53:X54),0)))))) -> 0 | Y58: =IF(Y$3=HOLD_PERIOD,Y53+Y54,IF(SUM(Y53:Y55)<=0,0,IF(DISTRIBUTION_FREQ="Monthly",SUM(Y53:Y54),IF(DISTRIBUTION_FREQ="Quarterly",IF(MOD(Y3,3)=0,SUM(Y53:Y54),0),IF(DISTRIBUTION_FREQ="Annually",IF(Z2-Y2=1,SUM(Y53:Y54),0)))))) -> 0 | ... ES58: =IF(ES$3=HOLD_PERIOD,ES53+ES54,IF(SUM(ES53:ES55)<=0,0,IF(DISTRIBUTION_FREQ="Monthly",SUM(ES53:ES54),IF(DISTRIBUTION_FREQ="Quarterly",IF(MOD(ES3,3)=0,SUM(ES53:ES54),0),IF(DISTRIBUTION_FREQ="Annually",IF(ET2-ES2=1,SUM(ES53:ES54),0)))))) -> 0
A59: =SUM(C59:M59) -> 0 | B59: Ending Cash Balance | C59: =HLOOKUP(C$2,$Q$2:$ES$59,MATCH($B59,$P$2:$P$59,0)) -> 0 | D59: =HLOOKUP(D$2,$Q$2:$ES$59,MATCH($B59,$P$2:$P$59,0)) -> 0 | E59: =HLOOKUP(E$2,$Q$2:$ES$59,MATCH($B59,$P$2:$P$59,0)) -> 0 | F59: =HLOOKUP(F$2,$Q$2:$ES$59,MATCH($B59,$P$2:$P$59,0)) -> 0 | G59: =HLOOKUP(G$2,$Q$2:$ES$59,MATCH($B59,$P$2:$P$59,0)) -> 0 | H59: =HLOOKUP(H$2,$Q$2:$ES$59,MATCH($B59,$P$2:$P$59,0)) -> 0 | I59: =HLOOKUP(I$2,$Q$2:$ES$59,MATCH($B59,$P$2:$P$59,0)) -> 0 | J59: =HLOOKUP(J$2,$Q$2:$ES$59,MATCH($B59,$P$2:$P$59,0)) -> 0 | ... M59: =HLOOKUP(M$2,$Q$2:$ES$59,MATCH($B59,$P$2:$P$59,0)) -> 0 | O59: =SUM(Q59:ES59) -> 0 | P59: Ending Cash Balance | Q59: =Q53+Q54-Q58 -> 0 | R59: =MAX(R53+R54-R58,0) -> 0 | S59: =MAX(S53+S54-S58,0) -> 0 | T59: =MAX(T53+T54-T58,0) -> 0 | U59: =MAX(U53+U54-U58,0) -> 0 | V59: =MAX(V53+V54-V58,0) -> 0 | W59: =MAX(W53+W54-W58,0) -> 0 | X59: =MAX(X53+X54-X58,0) -> 0 | Y59: =MAX(Y53+Y54-Y58,0) -> 0 | ... ES59: =MAX(ES53+ES54-ES58,0) -> 0
A60: =SUM(C60:M60) -> 54768889 | B60: Total Investor Cash Flow | C60: =Q60 -> -59099459 | D60: =SUMIF($R$2:$ES$2,D$2,$R60:$ES60) -> 1.4551915e-11 | E60: =SUMIF($R$2:$ES$2,E$2,$R60:$ES60) -> 2941677.3 | F60: =SUMIF($R$2:$ES$2,F$2,$R60:$ES60) -> 4023876 | G60: =SUMIF($R$2:$ES$2,G$2,$R60:$ES60) -> 3295838.2 | H60: =SUMIF($R$2:$ES$2,H$2,$R60:$ES60) -> 1.0360696e+08 | I60: =SUMIF($R$2:$ES$2,I$2,$R60:$ES60) -> 0 | J60: =SUMIF($R$2:$ES$2,J$2,$R60:$ES60) -> 0 | K60: =SUMIF($R$2:$ES$2,K$2,$R60:$ES60) -> 0 | ... M60: =SUMIF($R$2:$ES$2,M$2,$R60:$ES60) -> 0 | O60: =SUM(Q60:ES60) -> 54768889 | P60: Total Investor Cash Flow | Q60: =SUM(Q55:Q58) -> -59099459 | R60: =SUM(R55:R58) -> 0 | S60: =SUM(S55:S58) -> 0 | T60: =SUM(T55:T58) -> 0 | U60: =SUM(U55:U58) -> 0 | V60: =SUM(V55:V58) -> 0 | W60: =SUM(W55:W58) -> 1.4551915e-11 | X60: =SUM(X55:X58) -> 0 | ... ES60: =SUM(ES55:ES58) -> 0
B62: Unlevered Cash-on-Cash Return | D62: =SUM(D18,D20:D21,D24:D25)/ABS(SUMIF($C36:C36,"<"&0,$C36:C36)) -> 0.027343867 | E62: =SUM(E18,E20:E21,E24:E25)/ABS(SUMIF($C36:D36,"<"&0,$C36:D36)) -> 0.053726925 | F62: =SUM(F18,F20:F21,F24:F25)/ABS(SUMIF($C36:E36,"<"&0,$C36:E36)) -> 0.061064876 | G62: =SUM(G18,G20:G21,G24:G25)/ABS(SUMIF($C36:F36,"<"&0,$C36:F36)) -> 0.066430673 | H62: =SUM(H18,H20:H21,H24:H25)/ABS(SUMIF($C36:G36,"<"&0,$C36:G36)) -> 0.069310785 | I62: =SUM(I18,I20:I21,I24:I25)/ABS(SUMIF($C36:H36,"<"&0,$C36:H36)) -> 0 | J62: =SUM(J18,J20:J21,J24:J25)/ABS(SUMIF($C36:I36,"<"&0,$C36:I36)) -> 0 | K62: =SUM(K18,K20:K21,K24:K25)/ABS(SUMIF($C36:J36,"<"&0,$C36:J36)) -> 0 | ... M62: =SUM(M18,M20:M21,M24:M25)/ABS(SUMIF($C36:L36,"<"&0,$C36:L36)) -> 0 | P62: Working Capital Ending Balance | Q62: =-Q47 -> 0 | R62: =Q62-R48 -> 0 | S62: =R62-S48 -> 0 | T62: =S62-T48 -> 0 | U62: =T62-U48 -> 0 | V62: =U62-V48 -> 0 | W62: =V62-W48 -> 0 | X62: =W62-X48 -> 0 | Y62: =X62-Y48 -> 0 | ... ES62: =ER62-ES48 -> 0
B63: Levered Cash-on-Cash Return | D63: =IFERROR(SUM(D18,D20:D21,D24:D25,D40:D41,D47:D48,IF(D2<>ROUNDUP(ACQ_LOAN_TERM/12,0),D43,0))/MAX(-SUMIF($C50:C50,"<"&0,$C50:C50)-SUM(IF(D2>ACQ_LOAN_TERM/12,HLOOKUP(ROUNDUP(ACQ_LOAN_TERM/12,0),$D$2:$M$44,38,0),0),IF(D2>ACQ_LOAN_TERM/12,HLOOKUP(ROUNDUP(ACQ_LOAN_TERM/12,0),$D$2:$M$44,41),0),IF(D2>ACQ_LOAN_TERM/12,HLOOKUP(ROUNDUP(ACQ_LOAN_TERM/12,0),$D$2:$M$44,42,0),0),IF(D2>ACQ_LOAN_TERM/12,HLOOKUP(ROUNDUP(ACQ_LOAN_TERM/12,0),$D$2:$M$44,43,0),0)),0),"N/A") -> -0.029722283 | E63: =IFERROR(SUM(E18,E20:E21,E24:E25,E40:E41,E47:E48,IF(E2<>ROUNDUP(ACQ_LOAN_TERM/12,0),E43,0))/MAX(-SUMIF($C50:D50,"<"&0,$C50:D50)-SUM(IF(E2>ACQ_LOAN_TERM/12,HLOOKUP(ROUNDUP(ACQ_LOAN_TERM/12,0),$D$2:$M$44,38,0),0),IF(E2>ACQ_LOAN_TERM/12,HLOOKUP(ROUNDUP(ACQ_LOAN_TERM/12,0),$D$2:$M$44,41),0),IF(E2>ACQ_LOAN_TERM/12,HLOOKUP(ROUNDUP(ACQ_LOAN_TERM/12,0),$D$2:$M$44,42,0),0),IF(E2>ACQ_LOAN_TERM/12,HLOOKUP(ROUNDUP(ACQ_LOAN_TERM/12,0),$D$2:$M$44,43,0),0)),0),"N/A") -> 0.048654005 | F63: =IFERROR(SUM(F18,F20:F21,F24:F25,F40:F41,F47:F48,IF(F2<>ROUNDUP(ACQ_LOAN_TERM/12,0),F43,0))/MAX(-SUMIF($C50:E50,"<"&0,$C50:E50)-SUM(IF(F2>ACQ_LOAN_TERM/12,HLOOKUP(ROUNDUP(ACQ_LOAN_TERM/12,0),$D$2:$M$44,38,0),0),IF(F2>ACQ_LOAN_TERM/12,HLOOKUP(ROUNDUP(ACQ_LOAN_TERM/12,0),$D$2:$M$44,41),0),IF(F2>ACQ_LOAN_TERM/12,HLOOKUP(ROUNDUP(ACQ_LOAN_TERM/12,0),$D$2:$M$44,42,0),0),IF(F2>ACQ_LOAN_TERM/12,HLOOKUP(ROUNDUP(ACQ_LOAN_TERM/12,0),$D$2:$M$44,43,0),0)),0),"N/A") -> 0.067072423 | G63: =IFERROR(SUM(G18,G20:G21,G24:G25,G40:G41,G47:G48,IF(G2<>ROUNDUP(ACQ_LOAN_TERM/12,0),G43,0))/MAX(-SUMIF($C50:F50,"<"&0,$C50:F50)-SUM(IF(G2>ACQ_LOAN_TERM/12,HLOOKUP(ROUNDUP(ACQ_LOAN_TERM/12,0),$D$2:$M$44,38,0),0),IF(G2>ACQ_LOAN_TERM/12,HLOOKUP(ROUNDUP(ACQ_LOAN_TERM/12,0),$D$2:$M$44,41),0),IF(G2>ACQ_LOAN_TERM/12,HLOOKUP(ROUNDUP(ACQ_LOAN_TERM/12,0),$D$2:$M$44,42,0),0),IF(G2>ACQ_LOAN_TERM/12,HLOOKUP(ROUNDUP(ACQ_LOAN_TERM/12,0),$D$2:$M$44,43,0),0)),0),"N/A") -> 0.053071546 | H63: =IFERROR(SUM(H18,H20:H21,H24:H25,H40:H41,H47:H48,IF(H2<>ROUNDUP(ACQ_LOAN_TERM/12,0),H43,0))/MAX(-SUMIF($C50:G50,"<"&0,$C50:G50)-SUM(IF(H2>ACQ_LOAN_TERM/12,HLOOKUP(ROUNDUP(ACQ_LOAN_TERM/12,0),$D$2:$M$44,38,0),0),IF(H2>ACQ_LOAN_TERM/12,HLOOKUP(ROUNDUP(ACQ_LOAN_TERM/12,0),$D$2:$M$44,41),0),IF(H2>ACQ_LOAN_TERM/12,HLOOKUP(ROUNDUP(ACQ_LOAN_TERM/12,0),$D$2:$M$44,42,0),0),IF(H2>ACQ_LOAN_TERM/12,HLOOKUP(ROUNDUP(ACQ_LOAN_TERM/12,0),$D$2:$M$44,43,0),0)),0),"N/A") -> 0.058865137 | I63: =IFERROR(SUM(I18,I20:I21,I24:I25,I40:I41,I47:I48,IF(I2<>ROUNDUP(ACQ_LOAN_TERM/12,0),I43,0))/MAX(-SUMIF($C50:H50,"<"&0,$C50:H50)-SUM(IF(I2>ACQ_LOAN_TERM/12,HLOOKUP(ROUNDUP(ACQ_LOAN_TERM/12,0),$D$2:$M$44,38,0),0),IF(I2>ACQ_LOAN_TERM/12,HLOOKUP(ROUNDUP(ACQ_LOAN_TERM/12,0),$D$2:$M$44,41),0),IF(I2>ACQ_LOAN_TERM/12,HLOOKUP(ROUNDUP(ACQ_LOAN_TERM/12,0),$D$2:$M$44,42,0),0),IF(I2>ACQ_LOAN_TERM/12,HLOOKUP(ROUNDUP(ACQ_LOAN_TERM/12,0),$D$2:$M$44,43,0),0)),0),"N/A") -> 0 | J63: =IFERROR(SUM(J18,J20:J21,J24:J25,J40:J41,J47:J48,IF(J2<>ROUNDUP(ACQ_LOAN_TERM/12,0),J43,0))/MAX(-SUMIF($C50:I50,"<"&0,$C50:I50)-SUM(IF(J2>ACQ_LOAN_TERM/12,HLOOKUP(ROUNDUP(ACQ_LOAN_TERM/12,0),$D$2:$M$44,38,0),0),IF(J2>ACQ_LOAN_TERM/12,HLOOKUP(ROUNDUP(ACQ_LOAN_TERM/12,0),$D$2:$M$44,41),0),IF(J2>ACQ_LOAN_TERM/12,HLOOKUP(ROUNDUP(ACQ_LOAN_TERM/12,0),$D$2:$M$44,42,0),0),IF(J2>ACQ_LOAN_TERM/12,HLOOKUP(ROUNDUP(ACQ_LOAN_TERM/12,0),$D$2:$M$44,43,0),0)),0),"N/A") -> 0 | K63: =IFERROR(SUM(K18,K20:K21,K24:K25,K40:K41,K47:K48,IF(K2<>ROUNDUP(ACQ_LOAN_TERM/12,0),K43,0))/MAX(-SUMIF($C50:J50,"<"&0,$C50:J50)-SUM(IF(K2>ACQ_LOAN_TERM/12,HLOOKUP(ROUNDUP(ACQ_LOAN_TERM/12,0),$D$2:$M$44,38,0),0),IF(K2>ACQ_LOAN_TERM/12,HLOOKUP(ROUNDUP(ACQ_LOAN_TERM/12,0),$D$2:$M$44,41),0),IF(K2>ACQ_LOAN_TERM/12,HLOOKUP(ROUNDUP(ACQ_LOAN_TERM/12,0),$D$2:$M$44,42,0),0),IF(K2>ACQ_LOAN_TERM/12,HLOOKUP(ROUNDUP(ACQ_LOAN_TERM/12,0),$D$2:$M$44,43,0),0)),0),"N/A") -> 0 | ... M63: =IFERROR(SUM(M18,M20:M21,M24:M25,M40:M41,M47:M48,IF(M2<>ROUNDUP(ACQ_LOAN_TERM/12,0),M43,0))/MAX(-SUMIF($C50:L50,"<"&0,$C50:L50)-SUM(IF(M2>ACQ_LOAN_TERM/12,HLOOKUP(ROUNDUP(ACQ_LOAN_TERM/12,0),$D$2:$M$44,38,0),0),IF(M2>ACQ_LOAN_TERM/12,HLOOKUP(ROUNDUP(ACQ_LOAN_TERM/12,0),$D$2:$M$44,41),0),IF(M2>ACQ_LOAN_TERM/12,HLOOKUP(ROUNDUP(ACQ_LOAN_TERM/12,0),$D$2:$M$44,42,0),0),IF(M2>ACQ_LOAN_TERM/12,HLOOKUP(ROUNDUP(ACQ_LOAN_TERM/12,0),$D$2:$M$44,43,0),0)),0),"N/A") -> 0
P64: IRR Partitioning
O65: =XNPV(Summary!$H$2,'Combined CF'!Q65:ES65,$Q$4:$ES$4) -> 7626565.5 | P65: CF From Operations | Q65: 0 | R65: =SUM(R18,R24:R25,R41,R57,R47:R48) -> -121468.14 | S65: =SUM(S18,S24:S25,S41,S57,S47:S48) -> -122785.89 | T65: =SUM(T18,T24:T25,T41,T57,T47:T48) -> -123840.36 | U65: =SUM(U18,U24:U25,U41,U57,U47:U48) -> -124886.9 | V65: =SUM(V18,V24:V25,V41,V57,V47:V48) -> -135203.87 | W65: =SUM(W18,W24:W25,W41,W57,W47:W48) -> -136769.58 | X65: =SUM(X18,X24:X25,X41,X57,X47:X48) -> -137010.72 | Y65: =SUM(Y18,Y24:Y25,Y41,Y57,Y47:Y48) -> -138811.47 | ... ES65: =SUM(ES18,ES24:ES25,ES41,ES57,ES47:ES48) -> 0
O66: =XNPV(Summary!$H$2,'Combined CF'!Q66:ES66,$Q$4:$ES$4) -> 50030407 | P66: CF From Sale/Financing | Q66: 0 | R66: =SUM(R33:R34,R39:R40,R42:R44) -> 0 | S66: =SUM(S33:S34,S39:S40,S42:S44) -> 0 | T66: =SUM(T33:T34,T39:T40,T42:T44) -> 0 | U66: =SUM(U33:U34,U39:U40,U42:U44) -> 0 | V66: =SUM(V33:V34,V39:V40,V42:V44) -> 0 | W66: =SUM(W33:W34,W39:W40,W42:W44) -> 0 | X66: =SUM(X33:X34,X39:X40,X42:X44) -> 0 | Y66: =SUM(Y33:Y34,Y39:Y40,Y42:Y44) -> 0 | ... ES66: =SUM(ES33:ES34,ES39:ES40,ES42:ES44) -> 0

Sheet Assumptions
A1: =Summary!G1 -> Levered Return Metrics | B1: =Summary!G2 -> IRR | C1: =Summary!H2 -> 0.14881178 | D1: =Summary!G3 -> Equity Multiple | E1: =Summary!H3 -> 1.926724 | F1: =Summary!G6 -> Unlevered Return Metrics | G1: =Summary!G7 -> IRR | H1: =Summary!H7 -> 0.093561557 | I1: =Summary!G8 -> Equity Multiple | J1: =Summary!H8 -> 1.5042331
A3: The Ascher | B3: MF - Office - Retail | C3: Net Leasable Area | D3: Units/Suites
B4: Multifamily | C4: =Rent!I67 -> 533096 | D4: =Units -> 672
B5: Retail/Office | C5: =Leases!C347 -> 13385 | D5: =COUNTIF(Leases!A5:A149,"<>") -> 5
A6: Property Details | E6: Parking Information | H6: Acquisition Information | K6: Sale Information
A7: Year Built | C7: 2015/2017 | E7: Uncovered Spaces | F7: 0 | H7: Purchase Price | I7: 180000000 | K7: Cost of Exit (Brokerage) | L7: 0.01
A8: Land Square Footage | C8: 25264.8 | E8: Covered Spaces | F8: 0 | H8: Purchase Price Per SF | I8: =I7/C5 -> 13447.889 | K8: Exit Year / Month | L8: 5 | M8: =L8*12 -> 60
A9: Number of Stories | C9: 24 | E9: Total Spaces | F9: =SUM(F7:F8) -> 0 | H9: Acquisition Fee | I9: =PURCH_PRICE*H19 -> 1800000 | K9: Exit Cap Rate | L9: 0.0575
A10: FAR | C10: =+C5/C8 -> 0.52978848 | E10: Total Spaces Per 1,000 SF | F10: =F9/(C5/1000) -> 0 | H10: Closing Costs | I10: =SUM(F26,F20) -> 0
A11: Street Address | C11: 620 & 640 N. Church St | H11: Working Capital | I11: 0 | K11: Investor Distributions
A12: City/State/Zip | C12: Charlotte, NC 28202 | E12: Project-Level Fees | H12: Going-In Cap Rate | I12: ='Combined CF'!D14/PURCH_PRICE -> 0.028285466 | K12: Frequency | L12: Monthly
E13: Asset Management Fee | F13: 0 | H13: Escrow Closing Date | I13: 46142
E14: Construction Management Fee | F14: 0.01
A16: Source of Fund | B16: Amount | E16: Usage of Fund | F16: Amount
A17: Debt | B17: =Financing!$D$3+Financing!E3 -> 1.26e+08 | C17: =B17/$B$27 -> 0.68071512 | E17: Purchase Price | F17: =PURCH_PRICE -> 180000000 | G17: =F17/$F$27 -> 0.97245017
A18: Equity | B18: =F27-B17 -> 59099459 | C18: =B18/$B$27 -> 0.31928488 | E18: Loan Processing Fees | F18: =B17*H18 -> 1260000 | G18: =F18/$F$27 -> 0.0068071512 | H18: 0.01
E19: Acquisition Fees | F19: =H19*F17 -> 1800000 | G19: =F19/$F$27 -> 0.0097245017 | H19: 0.01
E20: Other Closing Cost | F20: =F17*H20 -> 0 | G20: =F20/$F$27 -> 0 | H20: 0
E21: Working Capital | F21: =WORKING_CAP -> 0 | G21: =F21/$F$27 -> 0
E22: Construction Management Fees | F22: =Summary!E30 -> 0 | G22: =F22/$F$27 -> 0
E23: TI/LC Reserve | F23: =Summary!E31 -> 457082.1 | G23: =F23/$F$27 -> 0.0024693865
E24: Operating Shortfall Reserve | F24: =Summary!E33 -> 1582377 | G24: =F24/$F$27 -> 0.0085487934
E25: Construction Expenses | F25: ='Construction Budget'!$C$19 -> 0 | G25: =F25/$F$27 -> 0
E26: Other Closing Cost | F26: =F17*H26 -> 0 | G26: =F26/$F$27 -> 0 | H26: 0
A27: Total | B27: =SUM(B17:B18) -> 1.8509946e+08 | C27: =SUM(C17:C26) -> 1 | E27: Total | F27: =SUM(F17:F26) -> 1.8509946e+08 | G27: =SUM(G17:G26) -> 1
A29: Pro forma Assumptions | D29: Multifamily | E29: Retail / Office
A30: Rent Increase (Y2 Onwards) | D30: 0.03
A31: Other Income Increase (Y2) | D31: =D30 -> 0.03
A32: Expense Increase (Year 2 Onwards) | D32: 0.0275 | E32: 0.0275
A33: Property Management Fee | D33: 0.0275 | E33: 0
A34: Replacement Reserve (Per Unit) | D34: 0.5
A35: RE Taxes Distribution | D35: =1-E35 -> 1 | E35: 0
B39: ='Combined CF'!D4 -> 46507 | C39: =EOMONTH(B39,12) -> 46873 | D39: =EOMONTH(C39,12) -> 47238 | E39: =EOMONTH(D39,12) -> 47603 | F39: =EOMONTH(E39,12) -> 47968 | G39: =EOMONTH(F39,12) -> 48334 | H39: =EOMONTH(G39,12) -> 48699 | I39: =EOMONTH(H39,12) -> 49064 | J39: =EOMONTH(I39,12) -> 49429 | ... L39: =EOMONTH(K39,12) -> 50160
B40: 1 | C40: =B40+1 -> 2 | D40: =C40+1 -> 3 | E40: =D40+1 -> 4 | F40: =E40+1 -> 5 | G40: =F40+1 -> 6 | H40: =G40+1 -> 7 | I40: =H40+1 -> 8 | J40: =I40+1 -> 9 | ... L40: =K40+1 -> 11
A41: Property Tax Rate | B41: =Assumptions!$B$50 -> 0.00821 | C41: =Assumptions!$B$50 -> 0.00821 | D41: =Assumptions!$B$50 -> 0.00821 | E41: =Assumptions!$B$50 -> 0.00821 | F41: =Assumptions!$B$50 -> 0.00821 | G41: =Assumptions!$B$50 -> 0.00821 | H41: =Assumptions!$B$50 -> 0.00821 | I41: =Assumptions!$B$50 -> 0.00821 | ... L41: =Assumptions!$B$50 -> 0.00821
A42: Assessed Value | B42: =IF(AND(B40>HOLD_PERIOD/12,REASSESSED_UPON_SALE=1),'Combined CF'!$A$33*VALUE_ASSESSED,IF(Assumptions!B40<YEAR_REASSESSED,CURR_ASSESSED_VAL*((1+Assumptions!B46)^(B40-1)),PURCH_PRICE*VALUE_ASSESSED*((1+Assumptions!B46)^(B40-1)))) -> 164126800 | C42: =IF(AND(C40>HOLD_PERIOD/12,REASSESSED_UPON_SALE=1),'Combined CF'!$A$33*VALUE_ASSESSED,IF(Assumptions!C40<YEAR_REASSESSED,CURR_ASSESSED_VAL*((1+Assumptions!C46)^(C40-1)),PURCH_PRICE*VALUE_ASSESSED*((1+Assumptions!C46)^(C40-1)))) -> 165768068 | D42: =IF(AND(D40>HOLD_PERIOD/12,REASSESSED_UPON_SALE=1),'Combined CF'!$A$33*VALUE_ASSESSED,IF(Assumptions!D40<YEAR_REASSESSED,CURR_ASSESSED_VAL*((1+Assumptions!D46)^(D40-1)),PURCH_PRICE*VALUE_ASSESSED*((1+Assumptions!D46)^(D40-1)))) -> 1.6742575e+08 | E42: =IF(AND(E40>HOLD_PERIOD/12,REASSESSED_UPON_SALE=1),'Combined CF'!$A$33*VALUE_ASSESSED,IF(Assumptions!E40<YEAR_REASSESSED,CURR_ASSESSED_VAL*((1+Assumptions!E46)^(E40-1)),PURCH_PRICE*VALUE_ASSESSED*((1+Assumptions!E46)^(E40-1)))) -> 1.6910001e+08 | F42: =IF(AND(F40>HOLD_PERIOD/12,REASSESSED_UPON_SALE=1),'Combined CF'!$A$33*VALUE_ASSESSED,IF(Assumptions!F40<YEAR_REASSESSED,CURR_ASSESSED_VAL*((1+Assumptions!F46)^(F40-1)),PURCH_PRICE*VALUE_ASSESSED*((1+Assumptions!F46)^(F40-1)))) -> 1.8730872e+08 | G42: =IF(AND(G40>HOLD_PERIOD/12,REASSESSED_UPON_SALE=1),'Combined CF'!$A$33*VALUE_ASSESSED,IF(Assumptions!G40<YEAR_REASSESSED,CURR_ASSESSED_VAL*((1+Assumptions!G46)^(G40-1)),PURCH_PRICE*VALUE_ASSESSED*((1+Assumptions!G46)^(G40-1)))) -> 1.8918181e+08 | H42: =IF(AND(H40>HOLD_PERIOD/12,REASSESSED_UPON_SALE=1),'Combined CF'!$A$33*VALUE_ASSESSED,IF(Assumptions!H40<YEAR_REASSESSED,CURR_ASSESSED_VAL*((1+Assumptions!H46)^(H40-1)),PURCH_PRICE*VALUE_ASSESSED*((1+Assumptions!H46)^(H40-1)))) -> 1.9107363e+08 | I42: =IF(AND(I40>HOLD_PERIOD/12,REASSESSED_UPON_SALE=1),'Combined CF'!$A$33*VALUE_ASSESSED,IF(Assumptions!I40<YEAR_REASSESSED,CURR_ASSESSED_VAL*((1+Assumptions!I46)^(I40-1)),PURCH_PRICE*VALUE_ASSESSED*((1+Assumptions!I46)^(I40-1)))) -> 1.9298436e+08 | ... L42: =IF(AND(L40>HOLD_PERIOD/12,REASSESSED_UPON_SALE=1),'Combined CF'!$A$33*VALUE_ASSESSED,IF(Assumptions!L40<YEAR_REASSESSED,CURR_ASSESSED_VAL*((1+Assumptions!L46)^(L40-1)),PURCH_PRICE*VALUE_ASSESSED*((1+Assumptions!L46)^(L40-1)))) -> 1.9883198e+08
A43: Fixed Charge Assessments | B43: =Assumptions!B51 -> 36624 | C43: =B43*(1+Assumptions!B46) -> 36990.24 | D43: =C43*(1+Assumptions!C46) -> 37360.142 | E43: =D43*(1+Assumptions!D46) -> 37733.744 | F43: =E43*(1+Assumptions!E46) -> 38111.081 | G43: =F43*(1+Assumptions!F46) -> 38492.192 | H43: =G43*(1+Assumptions!G46) -> 38877.114 | I43: =H43*(1+Assumptions!H46) -> 39265.885 | J43: =I43*(1+Assumptions!I46) -> 39658.544 | ... L43: =K43*(1+Assumptions!K46) -> 40455.681
A44: Less Credits | B44: 0 | C44: 0 | D44: 0 | E44: 0 | F44: 0 | G44: 0 | H44: 0 | I44: 0 | J44: 0 | K44: 0 | L44: 0
A45: Total Property Taxes | B45: =IF($B$57>0,$B$57*(1+B$46)^B$40,B41*B42+B43+B44) -> 1384105 | C45: =IF($B$57>0,$B$57*(1+C$46)^C$40,C41*C42+C43+C44) -> 1397946.1 | D45: =IF($B$57>0,$B$57*(1+D$46)^D$40,D41*D42+D43+D44) -> 1411925.5 | E45: =IF($B$57>0,$B$57*(1+E$46)^E$40,E41*E42+E43+E44) -> 1426044.8 | F45: =IF($B$57>0,$B$57*(1+F$46)^F$40,F41*F42+F43+F44) -> 1575915.7 | G45: =IF($B$57>0,$B$57*(1+G$46)^G$40,G41*G42+G43+G44) -> 1591674.8 | H45: =IF($B$57>0,$B$57*(1+H$46)^H$40,H41*H42+H43+H44) -> 1607591.6 | I45: =IF($B$57>0,$B$57*(1+I$46)^I$40,I41*I42+I43+I44) -> 1623667.5 | ... L45: =IF($B$57>0,$B$57*(1+L$46)^L$40,L41*L42+L43+L44) -> 1672866.3
A46: Property Tax Growth Rates | B46: 0.01 | C46: 0.01 | D46: 0.01 | E46: 0.01 | F46: 0.01 | G46: 0.01 | H46: 0.01 | I46: 0.01 | J46: 0.01 | K46: 0.01 | L46: 0.01
A49: Property Tax Information
A50: Property Tax Rate | B50: =0.004927+0.002741+0.000414+0.000128 -> 0.00821
A51: Fixed Charge Assessments | B51: =18312+18312 -> 36624
A52: Current Assessed Value | B52: =82849200+81277600 -> 164126800
A53: Year of Reassessment | B53: 5 | C53: *Reassessment takes place every 4 years in Mecklenberg county with the last assessment in 2023.
A54: Percentage of Value Assessed | B54: 1 | C54: Tax Links: | D54: Link | E54: Link
A55: Reassessed Upon Sale | B55: 0
A57: Tax Amount (Mannual override) | B57: 0

Sheet Construction Budget
A1: =Summary!G1 -> Levered Return Metrics | B1: =Summary!G2 -> IRR | C1: =Summary!H2 -> 0.14881178 | D1: =Summary!G3 -> Equity Multiple | E1: =Summary!H3 -> 1.926724 | F1: =Summary!G6 -> Unlevered Return Metrics | G1: =Summary!G7 -> IRR | H1: =Summary!H7 -> 0.093561557 | I1: =Summary!G8 -> Equity Multiple | J1: =Summary!H8 -> 1.5042331
H2: Month | I2: 1 | J2: =I2+1 -> 2 | K2: =J2+1 -> 3 | L2: =K2+1 -> 4 | M2: =L2+1 -> 5 | N2: =M2+1 -> 6 | O2: =N2+1 -> 7 | P2: =O2+1 -> 8 | Q2: =P2+1 -> 9 | ... EJ2: =EI2+1 -> 132
B3: Capital Budget | H3: Year | I3: =ROUNDUP(I2/12,0) -> 1 | J3: =ROUNDUP(J2/12,0) -> 1 | K3: =ROUNDUP(K2/12,0) -> 1 | L3: =ROUNDUP(L2/12,0) -> 1 | M3: =ROUNDUP(M2/12,0) -> 1 | N3: =ROUNDUP(N2/12,0) -> 1 | O3: =ROUNDUP(O2/12,0) -> 1 | P3: =ROUNDUP(P2/12,0) -> 1 | ... EJ3: =ROUNDUP(EJ2/12,0) -> 11
A4: Checks | B4: Item | C4: Total | D4: Per SF | E4: Month Start | F4: Month End | G4: Total Months | H4: Month Ending | I4: =CF!S5 -> 46173 | J4: =CF!T5 -> 46203 | K4: =CF!U5 -> 46234 | L4: =CF!V5 -> 46265 | M4: =CF!W5 -> 46295 | N4: =CF!X5 -> 46326 | O4: =CF!Y5 -> 46356 | P4: =CF!Z5 -> 46387 | ... EJ4: =CF!ET5 -> 50160
A5: =C5=SUM(I5:EJ5) -> TRUE | B5: Roofing | C5: 0 | D5: =C5/NLA -> 0 | E5: 3 | F5: 5 | G5: =F5-E5+1 -> 3 | I5: =IF(AND(I$2>=$E5,I$2<=$F5),$C5/$G5,0) -> 0 | J5: =IF(AND(J$2>=$E5,J$2<=$F5),$C5/$G5,0) -> 0 | K5: =IF(AND(K$2>=$E5,K$2<=$F5),$C5/$G5,0) -> 0 | L5: =IF(AND(L$2>=$E5,L$2<=$F5),$C5/$G5,0) -> 0 | M5: =IF(AND(M$2>=$E5,M$2<=$F5),$C5/$G5,0) -> 0 | N5: =IF(AND(N$2>=$E5,N$2<=$F5),$C5/$G5,0) -> 0 | O5: =IF(AND(O$2>=$E5,O$2<=$F5),$C5/$G5,0) -> 0 | P5: =IF(AND(P$2>=$E5,P$2<=$F5),$C5/$G5,0) -> 0 | ... EJ5: =IF(AND(EJ$2>=$E5,EJ$2<=$F5),$C5/$G5,0) -> 0
A6: =C6=SUM(I6:EJ6) -> TRUE | B6: Exterior Painting | C6: 0 | D6: =C6/NLA -> 0 | E6: 9 | F6: 10 | G6: =F6-E6+1 -> 2 | I6: =IF(AND(I$2>=$E6,I$2<=$F6),$C6/$G6,0) -> 0 | J6: =IF(AND(J$2>=$E6,J$2<=$F6),$C6/$G6,0) -> 0 | K6: =IF(AND(K$2>=$E6,K$2<=$F6),$C6/$G6,0) -> 0 | L6: =IF(AND(L$2>=$E6,L$2<=$F6),$C6/$G6,0) -> 0 | M6: =IF(AND(M$2>=$E6,M$2<=$F6),$C6/$G6,0) -> 0 | N6: =IF(AND(N$2>=$E6,N$2<=$F6),$C6/$G6,0) -> 0 | O6: =IF(AND(O$2>=$E6,O$2<=$F6),$C6/$G6,0) -> 0 | P6: =IF(AND(P$2>=$E6,P$2<=$F6),$C6/$G6,0) -> 0 | ... EJ6: =IF(AND(EJ$2>=$E6,EJ$2<=$F6),$C6/$G6,0) -> 0
A7: =C7=SUM(I7:EJ7) -> TRUE | B7: Landscaping | C7: 0 | D7: =C7/NLA -> 0 | E7: 3 | F7: 5 | G7: =F7-E7+1 -> 3 | I7: =IF(AND(I$2>=$E7,I$2<=$F7),$C7/$G7,0) -> 0 | J7: =IF(AND(J$2>=$E7,J$2<=$F7),$C7/$G7,0) -> 0 | K7: =IF(AND(K$2>=$E7,K$2<=$F7),$C7/$G7,0) -> 0 | L7: =IF(AND(L$2>=$E7,L$2<=$F7),$C7/$G7,0) -> 0 | M7: =IF(AND(M$2>=$E7,M$2<=$F7),$C7/$G7,0) -> 0 | N7: =IF(AND(N$2>=$E7,N$2<=$F7),$C7/$G7,0) -> 0 | O7: =IF(AND(O$2>=$E7,O$2<=$F7),$C7/$G7,0) -> 0 | P7: =IF(AND(P$2>=$E7,P$2<=$F7),$C7/$G7,0) -> 0 | ... EJ7: =IF(AND(EJ$2>=$E7,EJ$2<=$F7),$C7/$G7,0) -> 0
A8: =C8=SUM(I8:EJ8) -> TRUE | B8: Parking Lots | C8: 0 | D8: =C8/NLA -> 0 | E8: 3 | F8: 3 | G8: =F8-E8+1 -> 1 | I8: =IF(AND(I$2>=$E8,I$2<=$F8),$C8/$G8,0) -> 0 | J8: =IF(AND(J$2>=$E8,J$2<=$F8),$C8/$G8,0) -> 0 | K8: =IF(AND(K$2>=$E8,K$2<=$F8),$C8/$G8,0) -> 0 | L8: =IF(AND(L$2>=$E8,L$2<=$F8),$C8/$G8,0) -> 0 | M8: =IF(AND(M$2>=$E8,M$2<=$F8),$C8/$G8,0) -> 0 | N8: =IF(AND(N$2>=$E8,N$2<=$F8),$C8/$G8,0) -> 0 | O8: =IF(AND(O$2>=$E8,O$2<=$F8),$C8/$G8,0) -> 0 | P8: =IF(AND(P$2>=$E8,P$2<=$F8),$C8/$G8,0) -> 0 | ... EJ8: =IF(AND(EJ$2>=$E8,EJ$2<=$F8),$C8/$G8,0) -> 0
A9: =C9=SUM(I9:EJ9) -> TRUE | B9: Sidewalks | C9: 0 | D9: =C9/NLA -> 0 | E9: 3 | F9: 3 | G9: =F9-E9+1 -> 1 | I9: =IF(AND(I$2>=$E9,I$2<=$F9),$C9/$G9,0) -> 0 | J9: =IF(AND(J$2>=$E9,J$2<=$F9),$C9/$G9,0) -> 0 | K9: =IF(AND(K$2>=$E9,K$2<=$F9),$C9/$G9,0) -> 0 | L9: =IF(AND(L$2>=$E9,L$2<=$F9),$C9/$G9,0) -> 0 | M9: =IF(AND(M$2>=$E9,M$2<=$F9),$C9/$G9,0) -> 0 | N9: =IF(AND(N$2>=$E9,N$2<=$F9),$C9/$G9,0) -> 0 | O9: =IF(AND(O$2>=$E9,O$2<=$F9),$C9/$G9,0) -> 0 | P9: =IF(AND(P$2>=$E9,P$2<=$F9),$C9/$G9,0) -> 0 | ... EJ9: =IF(AND(EJ$2>=$E9,EJ$2<=$F9),$C9/$G9,0) -> 0
A10: =C10=SUM(I10:EJ10) -> TRUE | B10: Trash Enclosures | C10: 0 | D10: =C10/NLA -> 0 | E10: 3 | F10: 3 | G10: =F10-E10+1 -> 1 | I10: =IF(AND(I$2>=$E10,I$2<=$F10),$C10/$G10,0) -> 0 | J10: =IF(AND(J$2>=$E10,J$2<=$F10),$C10/$G10,0) -> 0 | K10: =IF(AND(K$2>=$E10,K$2<=$F10),$C10/$G10,0) -> 0 | L10: =IF(AND(L$2>=$E10,L$2<=$F10),$C10/$G10,0) -> 0 | M10: =IF(AND(M$2>=$E10,M$2<=$F10),$C10/$G10,0) -> 0 | N10: =IF(AND(N$2>=$E10,N$2<=$F10),$C10/$G10,0) -> 0 | O10: =IF(AND(O$2>=$E10,O$2<=$F10),$C10/$G10,0) -> 0 | P10: =IF(AND(P$2>=$E10,P$2<=$F10),$C10/$G10,0) -> 0 | ... EJ10: =IF(AND(EJ$2>=$E10,EJ$2<=$F10),$C10/$G10,0) -> 0
A11: =C11=SUM(I11:EJ11) -> TRUE | B11: Fences | C11: 0 | D11: =C11/NLA -> 0 | E11: 3 | F11: 3 | G11: =F11-E11+1 -> 1 | I11: =IF(AND(I$2>=$E11,I$2<=$F11),$C11/$G11,0) -> 0 | J11: =IF(AND(J$2>=$E11,J$2<=$F11),$C11/$G11,0) -> 0 | K11: =IF(AND(K$2>=$E11,K$2<=$F11),$C11/$G11,0) -> 0 | L11: =IF(AND(L$2>=$E11,L$2<=$F11),$C11/$G11,0) -> 0 | M11: =IF(AND(M$2>=$E11,M$2<=$F11),$C11/$G11,0) -> 0 | N11: =IF(AND(N$2>=$E11,N$2<=$F11),$C11/$G11,0) -> 0 | O11: =IF(AND(O$2>=$E11,O$2<=$F11),$C11/$G11,0) -> 0 | P11: =IF(AND(P$2>=$E11,P$2<=$F11),$C11/$G11,0) -> 0 | ... EJ11: =IF(AND(EJ$2>=$E11,EJ$2<=$F11),$C11/$G11,0) -> 0
A12: =C12=SUM(I12:EJ12) -> TRUE | B12: Plumbing | C12: 0 | D12: =C12/NLA -> 0 | E12: 1 | F12: 3 | G12: =F12-E12+1 -> 3 | I12: =IF(AND(I$2>=$E12,I$2<=$F12),$C12/$G12,0) -> 0 | J12: =IF(AND(J$2>=$E12,J$2<=$F12),$C12/$G12,0) -> 0 | K12: =IF(AND(K$2>=$E12,K$2<=$F12),$C12/$G12,0) -> 0 | L12: =IF(AND(L$2>=$E12,L$2<=$F12),$C12/$G12,0) -> 0 | M12: =IF(AND(M$2>=$E12,M$2<=$F12),$C12/$G12,0) -> 0 | N12: =IF(AND(N$2>=$E12,N$2<=$F12),$C12/$G12,0) -> 0 | O12: =IF(AND(O$2>=$E12,O$2<=$F12),$C12/$G12,0) -> 0 | P12: =IF(AND(P$2>=$E12,P$2<=$F12),$C12/$G12,0) -> 0 | ... EJ12: =IF(AND(EJ$2>=$E12,EJ$2<=$F12),$C12/$G12,0) -> 0
A13: =C13=SUM(I13:EJ13) -> TRUE | B13: HVAC | C13: 0 | D13: =C13/NLA -> 0 | E13: 3 | F13: 3 | G13: =F13-E13+1 -> 1 | I13: =IF(AND(I$2>=$E13,I$2<=$F13),$C13/$G13,0) -> 0 | J13: =IF(AND(J$2>=$E13,J$2<=$F13),$C13/$G13,0) -> 0 | K13: =IF(AND(K$2>=$E13,K$2<=$F13),$C13/$G13,0) -> 0 | L13: =IF(AND(L$2>=$E13,L$2<=$F13),$C13/$G13,0) -> 0 | M13: =IF(AND(M$2>=$E13,M$2<=$F13),$C13/$G13,0) -> 0 | N13: =IF(AND(N$2>=$E13,N$2<=$F13),$C13/$G13,0) -> 0 | O13: =IF(AND(O$2>=$E13,O$2<=$F13),$C13/$G13,0) -> 0 | P13: =IF(AND(P$2>=$E13,P$2<=$F13),$C13/$G13,0) -> 0 | ... EJ13: =IF(AND(EJ$2>=$E13,EJ$2<=$F13),$C13/$G13,0) -> 0
A14: =C14=SUM(I14:EJ14) -> TRUE | B14: Signage | C14: 0 | D14: =C14/NLA -> 0 | E14: 4 | F14: 7 | G14: =F14-E14+1 -> 4 | I14: =IF(AND(I$2>=$E14,I$2<=$F14),$C14/$G14,0) -> 0 | J14: =IF(AND(J$2>=$E14,J$2<=$F14),$C14/$G14,0) -> 0 | K14: =IF(AND(K$2>=$E14,K$2<=$F14),$C14/$G14,0) -> 0 | L14: =IF(AND(L$2>=$E14,L$2<=$F14),$C14/$G14,0) -> 0 | M14: =IF(AND(M$2>=$E14,M$2<=$F14),$C14/$G14,0) -> 0 | N14: =IF(AND(N$2>=$E14,N$2<=$F14),$C14/$G14,0) -> 0 | O14: =IF(AND(O$2>=$E14,O$2<=$F14),$C14/$G14,0) -> 0 | P14: =IF(AND(P$2>=$E14,P$2<=$F14),$C14/$G14,0) -> 0 | ... EJ14: =IF(AND(EJ$2>=$E14,EJ$2<=$F14),$C14/$G14,0) -> 0
A15: =C15=SUM(I15:EJ15) -> TRUE | B15: Electrical | C15: 0 | D15: =C15/NLA -> 0 | E15: 4 | F15: 7 | G15: =F15-E15+1 -> 4 | I15: =IF(AND(I$2>=$E15,I$2<=$F15),$C15/$G15,0) -> 0 | J15: =IF(AND(J$2>=$E15,J$2<=$F15),$C15/$G15,0) -> 0 | K15: =IF(AND(K$2>=$E15,K$2<=$F15),$C15/$G15,0) -> 0 | L15: =IF(AND(L$2>=$E15,L$2<=$F15),$C15/$G15,0) -> 0 | M15: =IF(AND(M$2>=$E15,M$2<=$F15),$C15/$G15,0) -> 0 | N15: =IF(AND(N$2>=$E15,N$2<=$F15),$C15/$G15,0) -> 0 | O15: =IF(AND(O$2>=$E15,O$2<=$F15),$C15/$G15,0) -> 0 | P15: =IF(AND(P$2>=$E15,P$2<=$F15),$C15/$G15,0) -> 0 | ... EJ15: =IF(AND(EJ$2>=$E15,EJ$2<=$F15),$C15/$G15,0) -> 0
A16: =C16=SUM(I16:EJ16) -> TRUE | B16: Lighting | C16: 0 | D16: =C16/NLA -> 0 | E16: 4 | F16: 7 | G16: =F16-E16+1 -> 4 | I16: =IF(AND(I$2>=$E16,I$2<=$F16),$C16/$G16,0) -> 0 | J16: =IF(AND(J$2>=$E16,J$2<=$F16),$C16/$G16,0) -> 0 | K16: =IF(AND(K$2>=$E16,K$2<=$F16),$C16/$G16,0) -> 0 | L16: =IF(AND(L$2>=$E16,L$2<=$F16),$C16/$G16,0) -> 0 | M16: =IF(AND(M$2>=$E16,M$2<=$F16),$C16/$G16,0) -> 0 | N16: =IF(AND(N$2>=$E16,N$2<=$F16),$C16/$G16,0) -> 0 | O16: =IF(AND(O$2>=$E16,O$2<=$F16),$C16/$G16,0) -> 0 | P16: =IF(AND(P$2>=$E16,P$2<=$F16),$C16/$G16,0) -> 0 | ... EJ16: =IF(AND(EJ$2>=$E16,EJ$2<=$F16),$C16/$G16,0) -> 0
A17: =C17=SUM(I17:EJ17) -> TRUE | B17: Subtotal | C17: =SUM(C5:C16) -> 0 | D17: =SUM(D5:D16) -> 0 | E17: {=MIN(IF($C$5:$C$16>0,$E$5:$E$16))} -> 0 | F17: {=MAX(IF($C$5:$C$16>0,$F$5:$F$16))} -> 0 | G17: =F17-E17+1 -> 1 | I17: =SUM(I5:I16) -> 0 | J17: =SUM(J5:J16) -> 0 | K17: =SUM(K5:K16) -> 0 | L17: =SUM(L5:L16) -> 0 | M17: =SUM(M5:M16) -> 0 | N17: =SUM(N5:N16) -> 0 | O17: =SUM(O5:O16) -> 0 | P17: =SUM(P5:P16) -> 0 | ... EJ17: =SUM(EJ5:EJ16) -> 0
B18: Contingency | C18: =SUM(I18:EJ18) -> 0 | D18: =C18/NLA -> 0 | H18: 0.1 | I18: =$H$18*I17 -> 0 | J18: =$H$18*J17 -> 0 | K18: =$H$18*K17 -> 0 | L18: =$H$18*L17 -> 0 | M18: =$H$18*M17 -> 0 | N18: =$H$18*N17 -> 0 | O18: =$H$18*O17 -> 0 | P18: =$H$18*P17 -> 0 | ... EJ18: =$H$18*EJ17 -> 0
A19: =C19=SUM(I19:EJ19) -> TRUE | B19: Total | C19: =SUM(C17:C18) -> 0 | D19: =SUM(D17:D18) -> 0 | E19: =E17 -> 0 | F19: =F17 -> 0 | G19: =G17 -> 1 | I19: =SUM(I17:I18) -> 0 | J19: =SUM(J17:J18) -> 0 | K19: =SUM(K17:K18) -> 0 | L19: =SUM(L17:L18) -> 0 | M19: =SUM(M17:M18) -> 0 | N19: =SUM(N17:N18) -> 0 | O19: =SUM(O17:O18) -> 0 | P19: =SUM(P17:P18) -> 0 | ... EJ19: =SUM(EJ17:EJ18) -> 0

Sheet Financing
A1: =Summary!G1 -> Levered Return Metrics | B1: =Summary!G2 -> IRR | C1: =Summary!H2 -> 0.14881178 | D1: =Summary!G3 -> Equity Multiple | E1: =Summary!H3 -> 1.926724 | F1: =Summary!G6 -> Unlevered Return Metrics | G1: =Summary!G7 -> IRR | H1: =Summary!H7 -> 0.093561557 | I1: =Summary!G8 -> Equity Multiple | J1: =Summary!H8 -> 1.5042331
C2: Loan Information | D2: Acquisition | E2: Mezzanine | F2: Refinancing | H2: Max Proceeds | I2: Acquisition | J2: Mezzanine | K2: Refinancing
C3: Loan Amount | D3: =INDEX($I$3:$K$6,MATCH(D4,$H$3:$H$6,0),MATCH(D2,$I$2:$K$2,0)) -> 1.26e+08 | E3: =INDEX($I$3:$K$6,MATCH(E4,$H$3:$H$6,0),MATCH(E2,$I$2:$K$2,0)) -> 0 | F3: =INDEX($I$3:$K$6,MATCH(F4,$H$3:$H$6,0),MATCH(F2,$I$2:$K$2,0)) -> 1.500632e+08 | H3: LTV | I3: =D5*PURCH_PRICE -> 1.26e+08 | J3: =MAX(E5*PURCH_PRICE-I3,0) -> 0 | K3: =SUMIFS('Combined CF'!$R$14:$ES$14,'Combined CF'!$R$3:$ES$3,">"&Financing!D20,'Combined CF'!$R$3:$ES$3,"<="&Financing!D20+12)/F13*F5 -> 0
C4: Size By | D4: LTV | E4: LTV | F4: DSCR | H4: LTC | I4: =D6*Summary!$E$7 -> 1.2586763e+08 | J4: =MAX(E6*Summary!$E$7-Financing!I4,0) -> 0 | K4: =F6*TOTAL_COST -> 1.2586763e+08
C5: Max LTV | D5: 0.7 | E5: 0 | F5: 0 | H5: DSCR | I5: =IFERROR(PV(D12/12,D19*12,-SUM('Combined CF'!R14:AC14)/Financing!D7/12,0,0),0) -> 1.0388615e+08 | J5: =IFERROR(MAX(PV(E12/12,E19*12,-SUM('Combined CF'!R14:AC14)/Financing!E7/12,0,0)-I5,0),0) -> 0 | K5: =IFERROR(PV(F12/12,F19*12,-SUMIFS('Combined CF'!$R$14:$ES$14,'Combined CF'!$R$3:$ES$3,">"&Financing!D20,'Combined CF'!$R$3:$ES$3,"<="&Financing!D20+12)/Financing!F7/12,0,0),0) -> 1.500632e+08
C6: Max LTC | D6: 0.68 | E6: 0.68 | F6: 0.68 | H6: Debt Yield | I6: =IFERROR(SUM('Combined CF'!R14:AC14)/Financing!D8,0) -> 1.0390579e+08 | J6: =IFERROR(MAX(SUM('Combined CF'!R14:AC14)/Financing!E8-I6,0),0) -> 0 | K6: =IFERROR(SUMIFS('Combined CF'!$R$14:$ES$14,'Combined CF'!$R$3:$ES$3,">"&Financing!D20,'Combined CF'!$R$3:$ES$3,"<="&Financing!D20+12)/F8,0) -> 2.6426948e+08
C7: Minimum DSCR | D7: 1.2 | E7: 1.2 | F7: 1.2
C8: Minimum Debt Yield | D8: 0.049 | E8: 0.049 | F8: 0.049
C9: Fixed/Floating | D9: Floating | E9: Fixed | F9: Fixed | H9: Fixed
C10: Fixed Interest Rate Index | D10: 0 | E10: 0.025 | F10: 0.03 | H10: Floating
C11: Interest Rate Spread | D11: 0.014 | E11: 0.045 | F11: 0.0225
C12: All-In Interest Rate | D12: =SUM(D10:D11) -> 0.014 | E12: =SUM(E10:E11) -> 0.07 | F12: =SUM(F10:F11) -> 0.0525
C13: Cap Rate Used For Valuation | F13: 0.0625
C14: % of Construction/TI/LC Costs Funded By Loan | D14: 0 | E14: 0 | F14: 0 | G14: *Acq/Mezz must be equal to or less than 100%
C15: Interest Only Period | D15: 36 | E15: 24 | F15: 36
C16: Loan Fee (as % of Proceeds) | D16: 0.01 | E16: 0.02 | F16: 0.01
C17: Prepayment Window | D17: 9 | E17: 9 | F17: 9
C18: Prepayment Penalty (% of Outstanding Balance) | D18: 0.01 | E18: 0.01 | F18: 0.01
C19: Amortization | D19: 30 | E19: 25 | F19: 25
C20: Term | D20: =HOLD_PERIOD -> 60 | E20: =D20 -> 60 | F20: 84
A22: CF Code | B22: Check | C22: Acquisition Financing
B23: =ABS(D3+B26-B28+B30)<0.01 -> TRUE | C23: Month | D23: 1 | E23: =D23+1 -> 2 | F23: =E23+1 -> 3 | G23: =F23+1 -> 4 | H23: =G23+1 -> 5 | I23: =H23+1 -> 6 | J23: =I23+1 -> 7 | K23: =J23+1 -> 8 | L23: =K23+1 -> 9 | ... EE23: =ED23+1 -> 132
C24: Date | D24: =CF!S5 -> 46173 | E24: =CF!T5 -> 46203 | F24: =CF!U5 -> 46234 | G24: =CF!V5 -> 46265 | H24: =CF!W5 -> 46295 | I24: =CF!X5 -> 46326 | J24: =CF!Y5 -> 46356 | K24: =CF!Z5 -> 46387 | ... EE24: =CF!ET5 -> 50160
B25: =MAX(D25:EE25) -> 1.26e+08 | C25: Starting Loan Balance | D25: =D3 -> 1.26e+08 | E25: =D32 -> 1.26e+08 | F25: =E32 -> 1.26e+08 | G25: =F32 -> 1.26e+08 | H25: =G32 -> 1.26e+08 | I25: =H32 -> 1.26e+08 | J25: =I32 -> 1.26e+08 | K25: =J32 -> 1.26e+08 | L25: =K32 -> 1.26e+08 | ... EE25: =ED32 -> 0
A26: ALP | B26: =SUM(D26:EE26) -> 0 | C26: Additional Loan Proceeds | D26: =IF(AND(D23<=$D$20,D23<=HOLD_PERIOD),-SUM(CF!S31:S32)*Financing!$D$14,0) -> 0 | E26: =IF(AND(E23<=$D$20,E23<=HOLD_PERIOD),-SUM(CF!T31:T32)*Financing!$D$14,0) -> 0 | F26: =IF(AND(F23<=$D$20,F23<=HOLD_PERIOD),-SUM(CF!U31:U32)*Financing!$D$14,0) -> 0 | G26: =IF(AND(G23<=$D$20,G23<=HOLD_PERIOD),-SUM(CF!V31:V32)*Financing!$D$14,0) -> 0 | H26: =IF(AND(H23<=$D$20,H23<=HOLD_PERIOD),-SUM(CF!W31:W32)*Financing!$D$14,0) -> 0 | I26: =IF(AND(I23<=$D$20,I23<=HOLD_PERIOD),-SUM(CF!X31:X32)*Financing!$D$14,0) -> 0 | J26: =IF(AND(J23<=$D$20,J23<=HOLD_PERIOD),-SUM(CF!Y31:Y32)*Financing!$D$14,0) -> 0 | K26: =IF(AND(K23<=$D$20,K23<=HOLD_PERIOD),-SUM(CF!Z31:Z32)*Financing!$D$14,0) -> 0 | ... EE26: =IF(AND(EE23<=$D$20,EE23<=HOLD_PERIOD),-SUM(CF!ET31:ET32)*Financing!$D$14,0) -> 0
A27: TLP | B27: =SUM(D27:EE27) -> 38837452 | C27: Total Loan Payment | D27: =IF(D23>MIN(ACQ_LOAN_TERM,HOLD_PERIOD),0,IF(D23<=IO_ACQ,SUM(D25:D26)*D33/12,PMT(D33/12,ACQ_AMORTIZATION*12-D23+IO_ACQ+1,-D25-D26,0,0))) -> 547212.75 | E27: =IF(E23>MIN(ACQ_LOAN_TERM,HOLD_PERIOD),0,IF(E23<=IO_ACQ,SUM(E25:E26)*E33/12,PMT(E33/12,ACQ_AMORTIZATION*12-E23+IO_ACQ+1,-E25-E26,0,0))) -> 548530.5 | F27: =IF(F23>MIN(ACQ_LOAN_TERM,HOLD_PERIOD),0,IF(F23<=IO_ACQ,SUM(F25:F26)*F33/12,PMT(F33/12,ACQ_AMORTIZATION*12-F23+IO_ACQ+1,-F25-F26,0,0))) -> 549777.9 | G27: =IF(G23>MIN(ACQ_LOAN_TERM,HOLD_PERIOD),0,IF(G23<=IO_ACQ,SUM(G25:G26)*G33/12,PMT(G33/12,ACQ_AMORTIZATION*12-G23+IO_ACQ+1,-G25-G26,0,0))) -> 551220.6 | H27: =IF(H23>MIN(ACQ_LOAN_TERM,HOLD_PERIOD),0,IF(H23<=IO_ACQ,SUM(H25:H26)*H33/12,PMT(H33/12,ACQ_AMORTIZATION*12-H23+IO_ACQ+1,-H25-H26,0,0))) -> 552754.65 | I27: =IF(I23>MIN(ACQ_LOAN_TERM,HOLD_PERIOD),0,IF(I23<=IO_ACQ,SUM(I25:I26)*I33/12,PMT(I33/12,ACQ_AMORTIZATION*12-I23+IO_ACQ+1,-I25-I26,0,0))) -> 554317.05 | J27: =IF(J23>MIN(ACQ_LOAN_TERM,HOLD_PERIOD),0,IF(J23<=IO_ACQ,SUM(J25:J26)*J33/12,PMT(J33/12,ACQ_AMORTIZATION*12-J23+IO_ACQ+1,-J25-J26,0,0))) -> 556021.2 | K27: =IF(K23>MIN(ACQ_LOAN_TERM,HOLD_PERIOD),0,IF(K23<=IO_ACQ,SUM(K25:K26)*K33/12,PMT(K33/12,ACQ_AMORTIZATION*12-K23+IO_ACQ+1,-K25-K26,0,0))) -> 557821.95 | ... EE27: =IF(EE23>MIN(ACQ_LOAN_TERM,HOLD_PERIOD),0,IF(EE23<=IO_ACQ,SUM(EE25:EE26)*EE33/12,PMT(EE33/12,ACQ_AMORTIZATION*12-EE23+IO_ACQ+1,-EE25-EE26,0,0))) -> 0
A28: PP | B28: =SUM(D28:EE28) -> 3196759.9 | C28: Principal Payment | D28: =IF(D23>MIN(ACQ_LOAN_TERM,HOLD_PERIOD),0,IF(D23<=IO_ACQ,0,D27-D29)) -> 0 | E28: =IF(E23>MIN(ACQ_LOAN_TERM,HOLD_PERIOD),0,IF(E23<=IO_ACQ,0,E27-E29)) -> 0 | F28: =IF(F23>MIN(ACQ_LOAN_TERM,HOLD_PERIOD),0,IF(F23<=IO_ACQ,0,F27-F29)) -> 0 | G28: =IF(G23>MIN(ACQ_LOAN_TERM,HOLD_PERIOD),0,IF(G23<=IO_ACQ,0,G27-G29)) -> 0 | H28: =IF(H23>MIN(ACQ_LOAN_TERM,HOLD_PERIOD),0,IF(H23<=IO_ACQ,0,H27-H29)) -> 0 | I28: =IF(I23>MIN(ACQ_LOAN_TERM,HOLD_PERIOD),0,IF(I23<=IO_ACQ,0,I27-I29)) -> 0 | J28: =IF(J23>MIN(ACQ_LOAN_TERM,HOLD_PERIOD),0,IF(J23<=IO_ACQ,0,J27-J29)) -> 0 | K28: =IF(K23>MIN(ACQ_LOAN_TERM,HOLD_PERIOD),0,IF(K23<=IO_ACQ,0,K27-K29)) -> 0 | ... EE28: =IF(EE23>MIN(ACQ_LOAN_TERM,HOLD_PERIOD),0,IF(EE23<=IO_ACQ,0,EE27-EE29)) -> 0
A29: IP | B29: =SUM(D29:EE29) -> 35640692 | C29: Interest Payment | D29: =IF(D23>MIN(ACQ_LOAN_TERM,HOLD_PERIOD),0,SUM(D25:D26)*D33/12) -> 547212.75 | E29: =IF(E23>MIN(ACQ_LOAN_TERM,HOLD_PERIOD),0,SUM(E25:E26)*E33/12) -> 548530.5 | F29: =IF(F23>MIN(ACQ_LOAN_TERM,HOLD_PERIOD),0,SUM(F25:F26)*F33/12) -> 549777.9 | G29: =IF(G23>MIN(ACQ_LOAN_TERM,HOLD_PERIOD),0,SUM(G25:G26)*G33/12) -> 551220.6 | H29: =IF(H23>MIN(ACQ_LOAN_TERM,HOLD_PERIOD),0,SUM(H25:H26)*H33/12) -> 552754.65 | I29: =IF(I23>MIN(ACQ_LOAN_TERM,HOLD_PERIOD),0,SUM(I25:I26)*I33/12) -> 554317.05 | J29: =IF(J23>MIN(ACQ_LOAN_TERM,HOLD_PERIOD),0,SUM(J25:J26)*J33/12) -> 556021.2 | K29: =IF(K23>MIN(ACQ_LOAN_TERM,HOLD_PERIOD),0,SUM(K25:K26)*K33/12) -> 557821.95 | ... EE29: =IF(EE23>MIN(ACQ_LOAN_TERM,HOLD_PERIOD),0,SUM(EE25:EE26)*EE33/12) -> 0
A30: LP | B30: =SUM(D30:EE30) -> -1.2280324e+08 | C30: Loan Payoff | D30: =IF(D23=MIN(ACQ_LOAN_TERM,HOLD_PERIOD),-D25-D26+D28,0) -> 0 | E30: =IF(E23=MIN(ACQ_LOAN_TERM,HOLD_PERIOD),-E25-E26+E28,0) -> 0 | F30: =IF(F23=MIN(ACQ_LOAN_TERM,HOLD_PERIOD),-F25-F26+F28,0) -> 0 | G30: =IF(G23=MIN(ACQ_LOAN_TERM,HOLD_PERIOD),-G25-G26+G28,0) -> 0 | H30: =IF(H23=MIN(ACQ_LOAN_TERM,HOLD_PERIOD),-H25-H26+H28,0) -> 0 | I30: =IF(I23=MIN(ACQ_LOAN_TERM,HOLD_PERIOD),-I25-I26+I28,0) -> 0 | J30: =IF(J23=MIN(ACQ_LOAN_TERM,HOLD_PERIOD),-J25-J26+J28,0) -> 0 | K30: =IF(K23=MIN(ACQ_LOAN_TERM,HOLD_PERIOD),-K25-K26+K28,0) -> 0 | ... EE30: =IF(EE23=MIN(ACQ_LOAN_TERM,HOLD_PERIOD),-EE25-EE26+EE28,0) -> 0
A31: PRP | B31: =SUM(D31:EE31) -> 0 | C31: Prepayment Penalty | D31: =IF(ACQ_LOAN_TERM-D23<=ACQ_PREPAY_WINDOW,0,D30*ACQ_PREPAY_PENALTY) -> 0 | E31: =IF(ACQ_LOAN_TERM-E23<=ACQ_PREPAY_WINDOW,0,E30*ACQ_PREPAY_PENALTY) -> 0 | F31: =IF(ACQ_LOAN_TERM-F23<=ACQ_PREPAY_WINDOW,0,F30*ACQ_PREPAY_PENALTY) -> 0 | G31: =IF(ACQ_LOAN_TERM-G23<=ACQ_PREPAY_WINDOW,0,G30*ACQ_PREPAY_PENALTY) -> 0 | H31: =IF(ACQ_LOAN_TERM-H23<=ACQ_PREPAY_WINDOW,0,H30*ACQ_PREPAY_PENALTY) -> 0 | I31: =IF(ACQ_LOAN_TERM-I23<=ACQ_PREPAY_WINDOW,0,I30*ACQ_PREPAY_PENALTY) -> 0 | J31: =IF(ACQ_LOAN_TERM-J23<=ACQ_PREPAY_WINDOW,0,J30*ACQ_PREPAY_PENALTY) -> 0 | K31: =IF(ACQ_LOAN_TERM-K23<=ACQ_PREPAY_WINDOW,0,K30*ACQ_PREPAY_PENALTY) -> 0 | ... EE31: =IF(ACQ_LOAN_TERM-EE23<=ACQ_PREPAY_WINDOW,0,EE30*ACQ_PREPAY_PENALTY) -> 0
C32: Ending Balance | D32: =D25+D26-D28+D30 -> 1.26e+08 | E32: =E25+E26-E28+E30 -> 1.26e+08 | F32: =F25+F26-F28+F30 -> 1.26e+08 | G32: =G25+G26-G28+G30 -> 1.26e+08 | H32: =H25+H26-H28+H30 -> 1.26e+08 | I32: =I25+I26-I28+I30 -> 1.26e+08 | J32: =J25+J26-J28+J30 -> 1.26e+08 | K32: =K25+K26-K28+K30 -> 1.26e+08 | ... EE32: =EE25+EE26-EE28+EE30 -> 0
C33: Interest Rate | D33: =IFERROR(IF($D$9="Fixed",$D$12,HLOOKUP(D24,$D$62:$EE$63,2,0)+$D$11),C33) -> 0.0521155 | E33: =IFERROR(IF($D$9="Fixed",$D$12,HLOOKUP(E24,$D$62:$EE$63,2,0)+$D$11),D33) -> 0.052241 | F33: =IFERROR(IF($D$9="Fixed",$D$12,HLOOKUP(F24,$D$62:$EE$63,2,0)+$D$11),E33) -> 0.0523598 | G33: =IFERROR(IF($D$9="Fixed",$D$12,HLOOKUP(G24,$D$62:$EE$63,2,0)+$D$11),F33) -> 0.0524972 | H33: =IFERROR(IF($D$9="Fixed",$D$12,HLOOKUP(H24,$D$62:$EE$63,2,0)+$D$11),G33) -> 0.0526433 | I33: =IFERROR(IF($D$9="Fixed",$D$12,HLOOKUP(I24,$D$62:$EE$63,2,0)+$D$11),H33) -> 0.0527921 | J33: =IFERROR(IF($D$9="Fixed",$D$12,HLOOKUP(J24,$D$62:$EE$63,2,0)+$D$11),I33) -> 0.0529544 | K33: =IFERROR(IF($D$9="Fixed",$D$12,HLOOKUP(K24,$D$62:$EE$63,2,0)+$D$11),J33) -> 0.0531259 | ... EE33: =IFERROR(IF($D$9="Fixed",$D$12,HLOOKUP(EE24,$D$62:$EE$63,2,0)+$D$11),ED33) -> 0.0712339
A35: CF Code | B35: Check | C35: Mezzanine Financing
B36: =ABS(E3+B39-B41+B43)<0.01 -> TRUE | C36: Month | D36: 1 | E36: =D36+1 -> 2 | F36: =E36+1 -> 3 | G36: =F36+1 -> 4 | H36: =G36+1 -> 5 | I36: =H36+1 -> 6 | J36: =I36+1 -> 7 | K36: =J36+1 -> 8 | L36: =K36+1 -> 9 | ... EE36: =ED36+1 -> 132
C37: Date | D37: =D24 -> 46173 | E37: =E24 -> 46203 | F37: =F24 -> 46234 | G37: =G24 -> 46265 | H37: =H24 -> 46295 | I37: =I24 -> 46326 | J37: =J24 -> 46356 | K37: =K24 -> 46387 | ... EE37: =EE24 -> 50160
B38: =MAX(D38:EE38) -> 0 | C38: Starting Loan Balance | D38: =E3 -> 0 | E38: =D45 -> 0 | F38: =E45 -> 0 | G38: =F45 -> 0 | H38: =G45 -> 0 | I38: =H45 -> 0 | J38: =I45 -> 0 | K38: =J45 -> 0 | L38: =K45 -> 0 | ... EE38: =ED45 -> 0
A39: ALP | B39: =SUM(D39:EE39) -> 0 | C39: Additional Loan Proceeds | D39: =IF(AND(D36<=$D$20,D36<=HOLD_PERIOD),-SUM(CF!S$31:S$32)*Financing!$E$14,0) -> 0 | E39: =IF(AND(E36<=$D$20,E36<=HOLD_PERIOD),-SUM(CF!T$31:T$32)*Financing!$E$14,0) -> 0 | F39: =IF(AND(F36<=$D$20,F36<=HOLD_PERIOD),-SUM(CF!U$31:U$32)*Financing!$E$14,0) -> 0 | G39: =IF(AND(G36<=$D$20,G36<=HOLD_PERIOD),-SUM(CF!V$31:V$32)*Financing!$E$14,0) -> 0 | H39: =IF(AND(H36<=$D$20,H36<=HOLD_PERIOD),-SUM(CF!W$31:W$32)*Financing!$E$14,0) -> 0 | I39: =IF(AND(I36<=$D$20,I36<=HOLD_PERIOD),-SUM(CF!X$31:X$32)*Financing!$E$14,0) -> 0 | J39: =IF(AND(J36<=$D$20,J36<=HOLD_PERIOD),-SUM(CF!Y$31:Y$32)*Financing!$E$14,0) -> 0 | K39: =IF(AND(K36<=$D$20,K36<=HOLD_PERIOD),-SUM(CF!Z$31:Z$32)*Financing!$E$14,0) -> 0 | ... EE39: =IF(AND(EE36<=$D$20,EE36<=HOLD_PERIOD),-SUM(CF!ET$31:ET$32)*Financing!$E$14,0) -> 0
A40: TLP | B40: =SUM(D40:EE40) -> 0 | C40: Total Loan Payment | D40: =IF(D36>MIN(ACQ_LOAN_TERM,HOLD_PERIOD),0,IF(D36<=IO_MEZZ,SUM(D38:D39)*D46/12,PMT(D46/12,MEZZ_AMORTIZATION*12-D36+IO_MEZZ+1,-D38-D39,0,0))) -> 0 | E40: =IF(E36>MIN(ACQ_LOAN_TERM,HOLD_PERIOD),0,IF(E36<=IO_MEZZ,SUM(E38:E39)*E46/12,PMT(E46/12,MEZZ_AMORTIZATION*12-E36+IO_MEZZ+1,-E38-E39,0,0))) -> 0 | F40: =IF(F36>MIN(ACQ_LOAN_TERM,HOLD_PERIOD),0,IF(F36<=IO_MEZZ,SUM(F38:F39)*F46/12,PMT(F46/12,MEZZ_AMORTIZATION*12-F36+IO_MEZZ+1,-F38-F39,0,0))) -> 0 | G40: =IF(G36>MIN(ACQ_LOAN_TERM,HOLD_PERIOD),0,IF(G36<=IO_MEZZ,SUM(G38:G39)*G46/12,PMT(G46/12,MEZZ_AMORTIZATION*12-G36+IO_MEZZ+1,-G38-G39,0,0))) -> 0 | H40: =IF(H36>MIN(ACQ_LOAN_TERM,HOLD_PERIOD),0,IF(H36<=IO_MEZZ,SUM(H38:H39)*H46/12,PMT(H46/12,MEZZ_AMORTIZATION*12-H36+IO_MEZZ+1,-H38-H39,0,0))) -> 0 | I40: =IF(I36>MIN(ACQ_LOAN_TERM,HOLD_PERIOD),0,IF(I36<=IO_MEZZ,SUM(I38:I39)*I46/12,PMT(I46/12,MEZZ_AMORTIZATION*12-I36+IO_MEZZ+1,-I38-I39,0,0))) -> 0 | J40: =IF(J36>MIN(ACQ_LOAN_TERM,HOLD_PERIOD),0,IF(J36<=IO_MEZZ,SUM(J38:J39)*J46/12,PMT(J46/12,MEZZ_AMORTIZATION*12-J36+IO_MEZZ+1,-J38-J39,0,0))) -> 0 | K40: =IF(K36>MIN(ACQ_LOAN_TERM,HOLD_PERIOD),0,IF(K36<=IO_MEZZ,SUM(K38:K39)*K46/12,PMT(K46/12,MEZZ_AMORTIZATION*12-K36+IO_MEZZ+1,-K38-K39,0,0))) -> 0 | ... EE40: =IF(EE36>MIN(ACQ_LOAN_TERM,HOLD_PERIOD),0,IF(EE36<=IO_MEZZ,SUM(EE38:EE39)*EE46/12,PMT(EE46/12,MEZZ_AMORTIZATION*12-EE36+IO_MEZZ+1,-EE38-EE39,0,0))) -> 0
A41: PP | B41: =SUM(D41:EE41) -> 0 | C41: Principal Payment | D41: =IF(D36>MIN(ACQ_LOAN_TERM,HOLD_PERIOD),0,IF(D36<=IO_MEZZ,0,D40-D42)) -> 0 | E41: =IF(E36>MIN(ACQ_LOAN_TERM,HOLD_PERIOD),0,IF(E36<=IO_MEZZ,0,E40-E42)) -> 0 | F41: =IF(F36>MIN(ACQ_LOAN_TERM,HOLD_PERIOD),0,IF(F36<=IO_MEZZ,0,F40-F42)) -> 0 | G41: =IF(G36>MIN(ACQ_LOAN_TERM,HOLD_PERIOD),0,IF(G36<=IO_MEZZ,0,G40-G42)) -> 0 | H41: =IF(H36>MIN(ACQ_LOAN_TERM,HOLD_PERIOD),0,IF(H36<=IO_MEZZ,0,H40-H42)) -> 0 | I41: =IF(I36>MIN(ACQ_LOAN_TERM,HOLD_PERIOD),0,IF(I36<=IO_MEZZ,0,I40-I42)) -> 0 | J41: =IF(J36>MIN(ACQ_LOAN_TERM,HOLD_PERIOD),0,IF(J36<=IO_MEZZ,0,J40-J42)) -> 0 | K41: =IF(K36>MIN(ACQ_LOAN_TERM,HOLD_PERIOD),0,IF(K36<=IO_MEZZ,0,K40-K42)) -> 0 | ... EE41: =IF(EE36>MIN(ACQ_LOAN_TERM,HOLD_PERIOD),0,IF(EE36<=IO_MEZZ,0,EE40-EE42)) -> 0
A42: IP | B42: =SUM(D42:EE42) -> 0 | C42: Interest Payment | D42: =IF(D36>MIN(ACQ_LOAN_TERM,HOLD_PERIOD),0,SUM(D38:D39)*D46/12) -> 0 | E42: =IF(E36>MIN(ACQ_LOAN_TERM,HOLD_PERIOD),0,SUM(E38:E39)*E46/12) -> 0 | F42: =IF(F36>MIN(ACQ_LOAN_TERM,HOLD_PERIOD),0,SUM(F38:F39)*F46/12) -> 0 | G42: =IF(G36>MIN(ACQ_LOAN_TERM,HOLD_PERIOD),0,SUM(G38:G39)*G46/12) -> 0 | H42: =IF(H36>MIN(ACQ_LOAN_TERM,HOLD_PERIOD),0,SUM(H38:H39)*H46/12) -> 0 | I42: =IF(I36>MIN(ACQ_LOAN_TERM,HOLD_PERIOD),0,SUM(I38:I39)*I46/12) -> 0 | J42: =IF(J36>MIN(ACQ_LOAN_TERM,HOLD_PERIOD),0,SUM(J38:J39)*J46/12) -> 0 | K42: =IF(K36>MIN(ACQ_LOAN_TERM,HOLD_PERIOD),0,SUM(K38:K39)*K46/12) -> 0 | ... EE42: =IF(EE36>MIN(ACQ_LOAN_TERM,HOLD_PERIOD),0,SUM(EE38:EE39)*EE46/12) -> 0
A43: LP | B43: =SUM(D43:EE43) -> 0 | C43: Loan Payoff | D43: =IF(D36=MIN(ACQ_LOAN_TERM,HOLD_PERIOD),-D38-D39+D41,0) -> 0 | E43: =IF(E36=MIN(ACQ_LOAN_TERM,HOLD_PERIOD),-E38-E39+E41,0) -> 0 | F43: =IF(F36=MIN(ACQ_LOAN_TERM,HOLD_PERIOD),-F38-F39+F41,0) -> 0 | G43: =IF(G36=MIN(ACQ_LOAN_TERM,HOLD_PERIOD),-G38-G39+G41,0) -> 0 | H43: =IF(H36=MIN(ACQ_LOAN_TERM,HOLD_PERIOD),-H38-H39+H41,0) -> 0 | I43: =IF(I36=MIN(ACQ_LOAN_TERM,HOLD_PERIOD),-I38-I39+I41,0) -> 0 | J43: =IF(J36=MIN(ACQ_LOAN_TERM,HOLD_PERIOD),-J38-J39+J41,0) -> 0 | K43: =IF(K36=MIN(ACQ_LOAN_TERM,HOLD_PERIOD),-K38-K39+K41,0) -> 0 | ... EE43: =IF(EE36=MIN(ACQ_LOAN_TERM,HOLD_PERIOD),-EE38-EE39+EE41,0) -> 0
A44: PRP | B44: =SUM(D44:EE44) -> 0 | C44: Prepayment Penalty | D44: =IF(ACQ_LOAN_TERM-D36<=MEZZ_PREPAY_WINDOW,0,D43*MEZZ_PREPAY_PENALTY) -> 0 | E44: =IF(ACQ_LOAN_TERM-E36<=MEZZ_PREPAY_WINDOW,0,E43*MEZZ_PREPAY_PENALTY) -> 0 | F44: =IF(ACQ_LOAN_TERM-F36<=MEZZ_PREPAY_WINDOW,0,F43*MEZZ_PREPAY_PENALTY) -> 0 | G44: =IF(ACQ_LOAN_TERM-G36<=MEZZ_PREPAY_WINDOW,0,G43*MEZZ_PREPAY_PENALTY) -> 0 | H44: =IF(ACQ_LOAN_TERM-H36<=MEZZ_PREPAY_WINDOW,0,H43*MEZZ_PREPAY_PENALTY) -> 0 | I44: =IF(ACQ_LOAN_TERM-I36<=MEZZ_PREPAY_WINDOW,0,I43*MEZZ_PREPAY_PENALTY) -> 0 | J44: =IF(ACQ_LOAN_TERM-J36<=MEZZ_PREPAY_WINDOW,0,J43*MEZZ_PREPAY_PENALTY) -> 0 | K44: =IF(ACQ_LOAN_TERM-K36<=MEZZ_PREPAY_WINDOW,0,K43*MEZZ_PREPAY_PENALTY) -> 0 | ... EE44: =IF(ACQ_LOAN_TERM-EE36<=MEZZ_PREPAY_WINDOW,0,EE43*MEZZ_PREPAY_PENALTY) -> 0
C45: Ending Balance | D45: =D38+D39-D41+D43 -> 0 | E45: =E38+E39-E41+E43 -> 0 | F45: =F38+F39-F41+F43 -> 0 | G45: =G38+G39-G41+G43 -> 0 | H45: =H38+H39-H41+H43 -> 0 | I45: =I38+I39-I41+I43 -> 0 | J45: =J38+J39-J41+J43 -> 0 | K45: =K38+K39-K41+K43 -> 0 | ... EE45: =EE38+EE39-EE41+EE43 -> 0
C46: Interest Rate | D46: =IFERROR(IF($E$9="Fixed",$E$12,HLOOKUP(D37,$D$62:$EE$63,2,0)+$E$11),C46) -> 0.07 | E46: =IFERROR(IF($E$9="Fixed",$E$12,HLOOKUP(E37,$D$62:$EE$63,2,0)+$E$11),D46) -> 0.07 | F46: =IFERROR(IF($E$9="Fixed",$E$12,HLOOKUP(F37,$D$62:$EE$63,2,0)+$E$11),E46) -> 0.07 | G46: =IFERROR(IF($E$9="Fixed",$E$12,HLOOKUP(G37,$D$62:$EE$63,2,0)+$E$11),F46) -> 0.07 | H46: =IFERROR(IF($E$9="Fixed",$E$12,HLOOKUP(H37,$D$62:$EE$63,2,0)+$E$11),G46) -> 0.07 | I46: =IFERROR(IF($E$9="Fixed",$E$12,HLOOKUP(I37,$D$62:$EE$63,2,0)+$E$11),H46) -> 0.07 | J46: =IFERROR(IF($E$9="Fixed",$E$12,HLOOKUP(J37,$D$62:$EE$63,2,0)+$E$11),I46) -> 0.07 | K46: =IFERROR(IF($E$9="Fixed",$E$12,HLOOKUP(K37,$D$62:$EE$63,2,0)+$E$11),J46) -> 0.07 | ... EE46: =IFERROR(IF($E$9="Fixed",$E$12,HLOOKUP(EE37,$D$62:$EE$63,2,0)+$E$11),ED46) -> 0.07
A48: CF Code | B48: Check | C48: Refinancing
B49: =ABS(F3+B52-B54+B56)<0.01 -> FALSE | C49: Month | D49: 1 | E49: =D49+1 -> 2 | F49: =E49+1 -> 3 | G49: =F49+1 -> 4 | H49: =G49+1 -> 5 | I49: =H49+1 -> 6 | J49: =I49+1 -> 7 | K49: =J49+1 -> 8 | L49: =K49+1 -> 9 | ... EE49: =ED49+1 -> 132
C50: Date | D50: =D37 -> 46173 | E50: =E37 -> 46203 | F50: =F37 -> 46234 | G50: =G37 -> 46265 | H50: =H37 -> 46295 | I50: =I37 -> 46326 | J50: =J37 -> 46356 | K50: =K37 -> 46387 | ... EE50: =EE37 -> 50160
B51: =MAX(D51:EE51) -> 0 | C51: Starting Loan Balance | D51: =IF(AND(ACQ_LOAN_TERM=HOLD_PERIOD,ACQ_LOAN_TERM=D49),0,IF(OR(D49>HOLD_PERIOD,D49<ACQ_LOAN_TERM),0,IF(D49=ACQ_LOAN_TERM,$F$3,C58))) -> 0 | E51: =IF(AND(ACQ_LOAN_TERM=HOLD_PERIOD,ACQ_LOAN_TERM=E49),0,IF(OR(E49>HOLD_PERIOD,E49<ACQ_LOAN_TERM),0,IF(E49=ACQ_LOAN_TERM,$F$3,D58))) -> 0 | F51: =IF(AND(ACQ_LOAN_TERM=HOLD_PERIOD,ACQ_LOAN_TERM=F49),0,IF(OR(F49>HOLD_PERIOD,F49<ACQ_LOAN_TERM),0,IF(F49=ACQ_LOAN_TERM,$F$3,E58))) -> 0 | G51: =IF(AND(ACQ_LOAN_TERM=HOLD_PERIOD,ACQ_LOAN_TERM=G49),0,IF(OR(G49>HOLD_PERIOD,G49<ACQ_LOAN_TERM),0,IF(G49=ACQ_LOAN_TERM,$F$3,F58))) -> 0 | H51: =IF(AND(ACQ_LOAN_TERM=HOLD_PERIOD,ACQ_LOAN_TERM=H49),0,IF(OR(H49>HOLD_PERIOD,H49<ACQ_LOAN_TERM),0,IF(H49=ACQ_LOAN_TERM,$F$3,G58))) -> 0 | I51: =IF(AND(ACQ_LOAN_TERM=HOLD_PERIOD,ACQ_LOAN_TERM=I49),0,IF(OR(I49>HOLD_PERIOD,I49<ACQ_LOAN_TERM),0,IF(I49=ACQ_LOAN_TERM,$F$3,H58))) -> 0 | J51: =IF(AND(ACQ_LOAN_TERM=HOLD_PERIOD,ACQ_LOAN_TERM=J49),0,IF(OR(J49>HOLD_PERIOD,J49<ACQ_LOAN_TERM),0,IF(J49=ACQ_LOAN_TERM,$F$3,I58))) -> 0 | K51: =IF(AND(ACQ_LOAN_TERM=HOLD_PERIOD,ACQ_LOAN_TERM=K49),0,IF(OR(K49>HOLD_PERIOD,K49<ACQ_LOAN_TERM),0,IF(K49=ACQ_LOAN_TERM,$F$3,J58))) -> 0 | ... EE51: =IF(AND(ACQ_LOAN_TERM=HOLD_PERIOD,ACQ_LOAN_TERM=EE49),0,IF(OR(EE49>HOLD_PERIOD,EE49<ACQ_LOAN_TERM),0,IF(EE49=ACQ_LOAN_TERM,$F$3,ED58))) -> 0
A52: ALP | B52: =SUM(D52:EE52) -> 0 | C52: Additional Loan Proceeds | D52: =IF(AND(D49>ACQ_LOAN_TERM,D49<=HOLD_PERIOD),-SUM(CF!S$31:S$32)*Financing!$F$14,0) -> 0 | E52: =IF(AND(E49>ACQ_LOAN_TERM,E49<=HOLD_PERIOD),-SUM(CF!T$31:T$32)*Financing!$F$14,0) -> 0 | F52: =IF(AND(F49>ACQ_LOAN_TERM,F49<=HOLD_PERIOD),-SUM(CF!U$31:U$32)*Financing!$F$14,0) -> 0 | G52: =IF(AND(G49>ACQ_LOAN_TERM,G49<=HOLD_PERIOD),-SUM(CF!V$31:V$32)*Financing!$F$14,0) -> 0 | H52: =IF(AND(H49>ACQ_LOAN_TERM,H49<=HOLD_PERIOD),-SUM(CF!W$31:W$32)*Financing!$F$14,0) -> 0 | I52: =IF(AND(I49>ACQ_LOAN_TERM,I49<=HOLD_PERIOD),-SUM(CF!X$31:X$32)*Financing!$F$14,0) -> 0 | J52: =IF(AND(J49>ACQ_LOAN_TERM,J49<=HOLD_PERIOD),-SUM(CF!Y$31:Y$32)*Financing!$F$14,0) -> 0 | K52: =IF(AND(K49>ACQ_LOAN_TERM,K49<=HOLD_PERIOD),-SUM(CF!Z$31:Z$32)*Financing!$F$14,0) -> 0 | ... EE52: =IF(AND(EE49>ACQ_LOAN_TERM,EE49<=HOLD_PERIOD),-SUM(CF!ET$31:ET$32)*Financing!$F$14,0) -> 0
A53: TLP | B53: =SUM(D53:EE53) -> 0 | C53: Total Loan Payment | D53: =IF(OR(D49>HOLD_PERIOD,D49<=ACQ_LOAN_TERM),0,IF(D49<=ACQ_LOAN_TERM+IO_REFI,SUM(D51:D52)*D59/12,PMT(D59/12,REFI_AMORTIZATION*12-D49+ACQ_LOAN_TERM+IO_REFI+1,-D51-D52,0,0))) -> 0 | E53: =IF(OR(E49>HOLD_PERIOD,E49<=ACQ_LOAN_TERM),0,IF(E49<=ACQ_LOAN_TERM+IO_REFI,SUM(E51:E52)*E59/12,PMT(E59/12,REFI_AMORTIZATION*12-E49+ACQ_LOAN_TERM+IO_REFI+1,-E51-E52,0,0))) -> 0 | F53: =IF(OR(F49>HOLD_PERIOD,F49<=ACQ_LOAN_TERM),0,IF(F49<=ACQ_LOAN_TERM+IO_REFI,SUM(F51:F52)*F59/12,PMT(F59/12,REFI_AMORTIZATION*12-F49+ACQ_LOAN_TERM+IO_REFI+1,-F51-F52,0,0))) -> 0 | G53: =IF(OR(G49>HOLD_PERIOD,G49<=ACQ_LOAN_TERM),0,IF(G49<=ACQ_LOAN_TERM+IO_REFI,SUM(G51:G52)*G59/12,PMT(G59/12,REFI_AMORTIZATION*12-G49+ACQ_LOAN_TERM+IO_REFI+1,-G51-G52,0,0))) -> 0 | H53: =IF(OR(H49>HOLD_PERIOD,H49<=ACQ_LOAN_TERM),0,IF(H49<=ACQ_LOAN_TERM+IO_REFI,SUM(H51:H52)*H59/12,PMT(H59/12,REFI_AMORTIZATION*12-H49+ACQ_LOAN_TERM+IO_REFI+1,-H51-H52,0,0))) -> 0 | I53: =IF(OR(I49>HOLD_PERIOD,I49<=ACQ_LOAN_TERM),0,IF(I49<=ACQ_LOAN_TERM+IO_REFI,SUM(I51:I52)*I59/12,PMT(I59/12,REFI_AMORTIZATION*12-I49+ACQ_LOAN_TERM+IO_REFI+1,-I51-I52,0,0))) -> 0 | J53: =IF(OR(J49>HOLD_PERIOD,J49<=ACQ_LOAN_TERM),0,IF(J49<=ACQ_LOAN_TERM+IO_REFI,SUM(J51:J52)*J59/12,PMT(J59/12,REFI_AMORTIZATION*12-J49+ACQ_LOAN_TERM+IO_REFI+1,-J51-J52,0,0))) -> 0 | K53: =IF(OR(K49>HOLD_PERIOD,K49<=ACQ_LOAN_TERM),0,IF(K49<=ACQ_LOAN_TERM+IO_REFI,SUM(K51:K52)*K59/12,PMT(K59/12,REFI_AMORTIZATION*12-K49+ACQ_LOAN_TERM+IO_REFI+1,-K51-K52,0,0))) -> 0 | ... EE53: =IF(OR(EE49>HOLD_PERIOD,EE49<=ACQ_LOAN_TERM),0,IF(EE49<=ACQ_LOAN_TERM+IO_REFI,SUM(EE51:EE52)*EE59/12,PMT(EE59/12,REFI_AMORTIZATION*12-EE49+ACQ_LOAN_TERM+IO_REFI+1,-EE51-EE52,0,0))) -> 0
A54: PP | B54: =SUM(D54:EE54) -> 0 | C54: Principal Payment | D54: =IF(D49<=ACQ_LOAN_TERM+IO_REFI,0,D53-D55) -> 0 | E54: =IF(E49<=ACQ_LOAN_TERM+IO_REFI,0,E53-E55) -> 0 | F54: =IF(F49<=ACQ_LOAN_TERM+IO_REFI,0,F53-F55) -> 0 | G54: =IF(G49<=ACQ_LOAN_TERM+IO_REFI,0,G53-G55) -> 0 | H54: =IF(H49<=ACQ_LOAN_TERM+IO_REFI,0,H53-H55) -> 0 | I54: =IF(I49<=ACQ_LOAN_TERM+IO_REFI,0,I53-I55) -> 0 | J54: =IF(J49<=ACQ_LOAN_TERM+IO_REFI,0,J53-J55) -> 0 | K54: =IF(K49<=ACQ_LOAN_TERM+IO_REFI,0,K53-K55) -> 0 | ... EE54: =IF(EE49<=ACQ_LOAN_TERM+IO_REFI,0,EE53-EE55) -> 0
A55: IP | B55: =SUM(D55:EE55) -> 0 | C55: Interest Payment | D55: =IF(D49<=ACQ_LOAN_TERM,0,SUM(D51:D52)*D59/12) -> 0 | E55: =IF(E49<=ACQ_LOAN_TERM,0,SUM(E51:E52)*E59/12) -> 0 | F55: =IF(F49<=ACQ_LOAN_TERM,0,SUM(F51:F52)*F59/12) -> 0 | G55: =IF(G49<=ACQ_LOAN_TERM,0,SUM(G51:G52)*G59/12) -> 0 | H55: =IF(H49<=ACQ_LOAN_TERM,0,SUM(H51:H52)*H59/12) -> 0 | I55: =IF(I49<=ACQ_LOAN_TERM,0,SUM(I51:I52)*I59/12) -> 0 | J55: =IF(J49<=ACQ_LOAN_TERM,0,SUM(J51:J52)*J59/12) -> 0 | K55: =IF(K49<=ACQ_LOAN_TERM,0,SUM(K51:K52)*K59/12) -> 0 | ... EE55: =IF(EE49<=ACQ_LOAN_TERM,0,SUM(EE51:EE52)*EE59/12) -> 0
A56: LP | B56: =SUM(D56:EE56) -> 0 | C56: Loan Payoff | D56: =IF(D49=HOLD_PERIOD,-D51-D52+D54,0) -> 0 | E56: =IF(E49=HOLD_PERIOD,-E51-E52+E54,0) -> 0 | F56: =IF(F49=HOLD_PERIOD,-F51-F52+F54,0) -> 0 | G56: =IF(G49=HOLD_PERIOD,-G51-G52+G54,0) -> 0 | H56: =IF(H49=HOLD_PERIOD,-H51-H52+H54,0) -> 0 | I56: =IF(I49=HOLD_PERIOD,-I51-I52+I54,0) -> 0 | J56: =IF(J49=HOLD_PERIOD,-J51-J52+J54,0) -> 0 | K56: =IF(K49=HOLD_PERIOD,-K51-K52+K54,0) -> 0 | ... EE56: =IF(EE49=HOLD_PERIOD,-EE51-EE52+EE54,0) -> 0
A57: PRP | B57: =SUM(D57:EE57) -> 0 | C57: Prepayment Penalty | D57: =IF(REFI_LOAN_TERM+ACQ_LOAN_TERM-D49<=REFI_PREPAY_WINDOW,0,REFI_PREPAY_PENALTY*D56) -> 0 | E57: =IF(REFI_LOAN_TERM+ACQ_LOAN_TERM-E49<=REFI_PREPAY_WINDOW,0,REFI_PREPAY_PENALTY*E56) -> 0 | F57: =IF(REFI_LOAN_TERM+ACQ_LOAN_TERM-F49<=REFI_PREPAY_WINDOW,0,REFI_PREPAY_PENALTY*F56) -> 0 | G57: =IF(REFI_LOAN_TERM+ACQ_LOAN_TERM-G49<=REFI_PREPAY_WINDOW,0,REFI_PREPAY_PENALTY*G56) -> 0 | H57: =IF(REFI_LOAN_TERM+ACQ_LOAN_TERM-H49<=REFI_PREPAY_WINDOW,0,REFI_PREPAY_PENALTY*H56) -> 0 | I57: =IF(REFI_LOAN_TERM+ACQ_LOAN_TERM-I49<=REFI_PREPAY_WINDOW,0,REFI_PREPAY_PENALTY*I56) -> 0 | J57: =IF(REFI_LOAN_TERM+ACQ_LOAN_TERM-J49<=REFI_PREPAY_WINDOW,0,REFI_PREPAY_PENALTY*J56) -> 0 | K57: =IF(REFI_LOAN_TERM+ACQ_LOAN_TERM-K49<=REFI_PREPAY_WINDOW,0,REFI_PREPAY_PENALTY*K56) -> 0 | ... EE57: =IF(REFI_LOAN_TERM+ACQ_LOAN_TERM-EE49<=REFI_PREPAY_WINDOW,0,REFI_PREPAY_PENALTY*EE56) -> 0
C58: Ending Balance | D58: =D51+D52-D54+D56 -> 0 | E58: =E51+E52-E54+E56 -> 0 | F58: =F51+F52-F54+F56 -> 0 | G58: =G51+G52-G54+G56 -> 0 | H58: =H51+H52-H54+H56 -> 0 | I58: =I51+I52-I54+I56 -> 0 | J58: =J51+J52-J54+J56 -> 0 | K58: =K51+K52-K54+K56 -> 0 | ... EE58: =EE51+EE52-EE54+EE56 -> 0
C59: Interest Rate | D59: =IFERROR(IF($F$9="Fixed",$F$12,HLOOKUP(D50,$D$62:$EE$63,2,0)+$F$11),C59) -> 0.0525 | E59: =IFERROR(IF($F$9="Fixed",$F$12,HLOOKUP(E50,$D$62:$EE$63,2,0)+$F$11),D59) -> 0.0525 | F59: =IFERROR(IF($F$9="Fixed",$F$12,HLOOKUP(F50,$D$62:$EE$63,2,0)+$F$11),E59) -> 0.0525 | G59: =IFERROR(IF($F$9="Fixed",$F$12,HLOOKUP(G50,$D$62:$EE$63,2,0)+$F$11),F59) -> 0.0525 | H59: =IFERROR(IF($F$9="Fixed",$F$12,HLOOKUP(H50,$D$62:$EE$63,2,0)+$F$11),G59) -> 0.0525 | I59: =IFERROR(IF($F$9="Fixed",$F$12,HLOOKUP(I50,$D$62:$EE$63,2,0)+$F$11),H59) -> 0.0525 | J59: =IFERROR(IF($F$9="Fixed",$F$12,HLOOKUP(J50,$D$62:$EE$63,2,0)+$F$11),I59) -> 0.0525 | K59: =IFERROR(IF($F$9="Fixed",$F$12,HLOOKUP(K50,$D$62:$EE$63,2,0)+$F$11),J59) -> 0.0525 | ... EE59: =IFERROR(IF($F$9="Fixed",$F$12,HLOOKUP(EE50,$D$62:$EE$63,2,0)+$F$11),ED59) -> 0.0525
C61: Date | D61: {=TRANSPOSE(C69:C189)} -> 46094 | E61: 46125 | F61: 46155 | G61: 46188 | H61: 46216 | I61: 46247 | J61: 46279 | K61: 46308 | L61: 46339 | M61: 46370 | N61: 46400 | O61: 46434 | P61: 46461 | Q61: 46490 | R61: 46520 | S61: 46552 | T61: 46581 | U61: 46612 | V61: 46643 | W61: 46673 | X61: 46706 | Y61: 46734 | Z61: 46765 | AA61: 46797 | AB61: 46825 | AC61: 46856 | AD61: 46888 | AE61: 46917 | AF61: 46947 | AG61: 46979 | AH61: 47009 | AI61: 47039 | AJ61: 47070 | AK61: 47100 | AL61: 47134 | AM61: 47162 | AN61: 47190 | AO61: 47221 | AP61: 47252 | AQ61: 47282 | AR61: 47312 | AS61: 47343 | AT61: 47374 | AU61: 47406 | AV61: 47435 | AW61: 47465 | AX61: 47497 | AY61: 47527 | AZ61: 47555 | BA61: 47588 | BB61: 47616 | BC61: 47647 | BD61: 47679 | BE61: 47708 | BF61: 47739 | BG61: 47771 | BH61: 47800 | BI61: 47830 | BJ61: 47861 | BK61: 47892 | BL61: 47920 | BM61: 47952 | BN61: 47981 | BO61: 48012 | BP61: 48043 | BQ61: 48073 | BR61: 48106 | BS61: 48135 | BT61: 48165 | BU61: 48197 | BV61: 48226 | BW61: 48257 | BX61: 48288 | BY61: 48317 | BZ61: 48347 | CA61: 48379 | CB61: 48408 | CC61: 48439 | CD61: 48470 | CE61: 48500 | CF61: 48533 | CG61: 48561 | CH61: 48592 | CI61: 48624 | CJ61: 48652 | CK61: 48682 | CL61: 48712 | CM61: 48743 | CN61: 48773 | CO61: 48806 | CP61: 48835 | CQ61: 48865 | CR61: 48897 | CS61: 48926 | CT61: 48957 | CU61: 48988 | CV61: 49016 | CW61: 49047 | CX61: 49079 | CY61: 49108 | CZ61: 49138 | DA61: 49170 | DB61: 49200 | DC61: 49230 | DD61: 49261 | DE61: 49291 | DF61: 49325 | DG61: 49353 | DH61: 49381 | DI61: 49412 | DJ61: 49443 | DK61: 49473 | DL61: 49503 | DM61: 49534 | DN61: 49565 | DO61: 49597 | DP61: 49626 | DQ61: 49656 | DR61: 49688 | DS61: 49718 | DT61: 49747 | DU61: #N/A | DV61: #N/A | DW61: #N/A | DX61: #N/A | DY61: #N/A | DZ61: #N/A | EA61: #N/A | EB61: #N/A | EC61: #N/A | ED61: #N/A | EE61: #N/A
C62: Month Ending | D62: =EOMONTH(D61,0) -> 46112 | E62: =EOMONTH(D62,1) -> 46142 | F62: =EOMONTH(E62,1) -> 46173 | G62: =EOMONTH(F62,1) -> 46203 | H62: =EOMONTH(G62,1) -> 46234 | I62: =EOMONTH(H62,1) -> 46265 | J62: =EOMONTH(I62,1) -> 46295 | K62: =EOMONTH(J62,1) -> 46326 | L62: =EOMONTH(K62,1) -> 46356 | ... EE62: =EOMONTH(ED62,1) -> 50099
C63: U.S. Treasury Yields Forward Curves | D63: =IFERROR(VLOOKUP(D61,$C$69:$D$189,2,0),C63) -> 0.0379124 | E63: =IFERROR(VLOOKUP(E61,$C$69:$D$189,2,0),D63) -> 0.0380082 | F63: =IFERROR(VLOOKUP(F61,$C$69:$D$189,2,0),E63) -> 0.0381155 | G63: =IFERROR(VLOOKUP(G61,$C$69:$D$189,2,0),F63) -> 0.038241 | H63: =IFERROR(VLOOKUP(H61,$C$69:$D$189,2,0),G63) -> 0.0383598 | I63: =IFERROR(VLOOKUP(I61,$C$69:$D$189,2,0),H63) -> 0.0384972 | J63: =IFERROR(VLOOKUP(J61,$C$69:$D$189,2,0),I63) -> 0.0386433 | K63: =IFERROR(VLOOKUP(K61,$C$69:$D$189,2,0),J63) -> 0.0387921 | ... EE63: =IFERROR(VLOOKUP(EE61,$C$69:$D$189,2,0),ED63) -> 0.0572339
C68: Date | D68: 5 Year
C69: 46094 | D69: 0.0379124
C70: 46125 | D70: 0.0380082
C71: 46155 | D71: 0.0381155
C72: 46188 | D72: 0.038241
C73: 46216 | D73: 0.0383598
C74: 46247 | D74: 0.0384972
C75: 46279 | D75: 0.0386433
C76: 46308 | D76: 0.0387921
C77: 46339 | D77: 0.0389544
C78: 46370 | D78: 0.0391259
C79: 46400 | D79: 0.03929
C80: 46434 | D80: 0.0394778
... C189: 49747 | D189: 0.0572339

Sheet Retail

Sheet CF
B1: =Summary!G1 -> Levered Return Metrics | C1: =Summary!G2 -> IRR | D1: =Summary!H2 -> 0.14881178 | E1: =Summary!G3 -> Equity Multiple | F1: =Summary!H3 -> 1.926724 | G1: =Summary!G6 -> Unlevered Return Metrics | H1: =Summary!G7 -> IRR | I1: =Summary!H7 -> 0.093561557 | J1: =Summary!G8 -> Equity Multiple | K1: =Summary!H8 -> 1.5042331
B2: Year | C2: 0 | D2: 1 | E2: =D2+1 -> 2 | F2: =E2+1 -> 3 | G2: =F2+1 -> 4 | H2: =G2+1 -> 5 | I2: =H2+1 -> 6 | J2: =I2+1 -> 7 | K2: =J2+1 -> 8 | L2: =K2+1 -> 9 | M2: =L2+1 -> 10 | Q2: Year | R2: 0 | S2: =ROUNDUP(S4/12,0) -> 1 | T2: =ROUNDUP(T4/12,0) -> 1 | U2: =ROUNDUP(U4/12,0) -> 1 | V2: =ROUNDUP(V4/12,0) -> 1 | W2: =ROUNDUP(W4/12,0) -> 1 | X2: =ROUNDUP(X4/12,0) -> 1 | Y2: =ROUNDUP(Y4/12,0) -> 1 | Z2: =ROUNDUP(Z4/12,0) -> 1 | ... ET2: =ROUNDUP(ET4/12,0) -> 11
Q3: Quarter | R3: 0 | S3: =ROUNDUP(S4/3,0) -> 1 | T3: =ROUNDUP(T4/3,0) -> 1 | U3: =ROUNDUP(U4/3,0) -> 1 | V3: =ROUNDUP(V4/3,0) -> 2 | W3: =ROUNDUP(W4/3,0) -> 2 | X3: =ROUNDUP(X4/3,0) -> 2 | Y3: =ROUNDUP(Y4/3,0) -> 3 | Z3: =ROUNDUP(Z4/3,0) -> 3 | ... ET3: =ROUNDUP(ET4/3,0) -> 44
Q4: Month | R4: 0 | S4: 1 | T4: =S4+1 -> 2 | U4: =T4+1 -> 3 | V4: =U4+1 -> 4 | W4: =V4+1 -> 5 | X4: =W4+1 -> 6 | Y4: =X4+1 -> 7 | Z4: =Y4+1 -> 8 | AA4: =Z4+1 -> 9 | ... ET4: =ES4+1 -> 132
B5: Month Ending | C5: =CLOSE_DATE -> 46142 | D5: =EOMONTH(C5,12) -> 46507 | E5: =EOMONTH(D5,12) -> 46873 | F5: =EOMONTH(E5,12) -> 47238 | G5: =EOMONTH(F5,12) -> 47603 | H5: =EOMONTH(G5,12) -> 47968 | I5: =EOMONTH(H5,12) -> 48334 | J5: =EOMONTH(I5,12) -> 48699 | K5: =EOMONTH(J5,12) -> 49064 | ... M5: =EOMONTH(L5,12) -> 49795 | Q5: Month Ending | R5: =CLOSE_DATE -> 46142 | S5: =Leases!D167 -> 46173 | T5: =EOMONTH(S5,1) -> 46203 | U5: =EOMONTH(T5,1) -> 46234 | V5: =EOMONTH(U5,1) -> 46265 | W5: =EOMONTH(V5,1) -> 46295 | X5: =EOMONTH(W5,1) -> 46326 | Y5: =EOMONTH(X5,1) -> 46356 | Z5: =EOMONTH(Y5,1) -> 46387 | AA5: =EOMONTH(Z5,1) -> 46418 | ... ET5: =EOMONTH(ES5,1) -> 50160
B7: Revenue | Q7: Revenue
A8: =SUM(C8:M8) -> 2740812.2 | B8: Base Rental Revenue | D8: =SUMIFS(CF!$R8:$ET8,CF!$R$2:$ET$2,CF!D$2,CF!$R$4:$ET$4,"<="&HOLD_PERIOD+12) -> 405083.95 | E8: =SUMIFS(CF!$R8:$ET8,CF!$R$2:$ET$2,CF!E$2,CF!$R$4:$ET$4,"<="&HOLD_PERIOD+12) -> 433879.06 | F8: =SUMIFS(CF!$R8:$ET8,CF!$R$2:$ET$2,CF!F$2,CF!$R$4:$ET$4,"<="&HOLD_PERIOD+12) -> 456537.26 | G8: =SUMIFS(CF!$R8:$ET8,CF!$R$2:$ET$2,CF!G$2,CF!$R$4:$ET$4,"<="&HOLD_PERIOD+12) -> 464155.66 | H8: =SUMIFS(CF!$R8:$ET8,CF!$R$2:$ET$2,CF!H$2,CF!$R$4:$ET$4,"<="&HOLD_PERIOD+12) -> 516275.34 | I8: =SUMIFS(CF!$R8:$ET8,CF!$R$2:$ET$2,CF!I$2,CF!$R$4:$ET$4,"<="&HOLD_PERIOD+12) -> 464880.97 | J8: =SUMIFS(CF!$R8:$ET8,CF!$R$2:$ET$2,CF!J$2,CF!$R$4:$ET$4,"<="&HOLD_PERIOD+12) -> 0 | K8: =SUMIFS(CF!$R8:$ET8,CF!$R$2:$ET$2,CF!K$2,CF!$R$4:$ET$4,"<="&HOLD_PERIOD+12) -> 0 | ... M8: =SUMIFS(CF!$R8:$ET8,CF!$R$2:$ET$2,CF!M$2,CF!$R$4:$ET$4,"<="&HOLD_PERIOD+12) -> 0 | P8: =SUMIF($R$4:$ET$4,"<="&HOLD_PERIOD,R8:ET8) -> 2275931.3 | Q8: Base Rental Revenue | S8: =IF(S4>HOLD_PERIOD+12,0,SUMIF(Leases!$B$170:$B$955,"BRR",Leases!D$170:D$955)) -> 33373.455 | T8: =IF(T4>HOLD_PERIOD+12,0,SUMIF(Leases!$B$170:$B$955,"BRR",Leases!E$170:E$955)) -> 33373.455 | U8: =IF(U4>HOLD_PERIOD+12,0,SUMIF(Leases!$B$170:$B$955,"BRR",Leases!F$170:F$955)) -> 33566.384 | V8: =IF(V4>HOLD_PERIOD+12,0,SUMIF(Leases!$B$170:$B$955,"BRR",Leases!G$170:G$955)) -> 33962.546 | W8: =IF(W4>HOLD_PERIOD+12,0,SUMIF(Leases!$B$170:$B$955,"BRR",Leases!H$170:H$955)) -> 26639.321 | X8: =IF(X4>HOLD_PERIOD+12,0,SUMIF(Leases!$B$170:$B$955,"BRR",Leases!I$170:I$955)) -> 26639.321 | Y8: =IF(Y4>HOLD_PERIOD+12,0,SUMIF(Leases!$B$170:$B$955,"BRR",Leases!J$170:J$955)) -> 36254.912 | Z8: =IF(Z4>HOLD_PERIOD+12,0,SUMIF(Leases!$B$170:$B$955,"BRR",Leases!K$170:K$955)) -> 36254.912 | ... ET8: =IF(ET4>HOLD_PERIOD+12,0,SUMIF(Leases!$B$170:$B$955,"BRR",Leases!EE$170:EE$955)) -> 0
A9: =SUM(C9:M9) -> -80441.593 | B9: Free Rent | D9: =SUMIFS(CF!$R9:$ET9,CF!$R$2:$ET$2,CF!D$2,CF!$R$4:$ET$4,"<="&HOLD_PERIOD+12) -> -19231.182 | E9: =SUMIFS(CF!$R9:$ET9,CF!$R$2:$ET$2,CF!E$2,CF!$R$4:$ET$4,"<="&HOLD_PERIOD+12) -> -14336.912 | F9: =SUMIFS(CF!$R9:$ET9,CF!$R$2:$ET$2,CF!F$2,CF!$R$4:$ET$4,"<="&HOLD_PERIOD+12) -> -14724.602 | G9: =SUMIFS(CF!$R9:$ET9,CF!$R$2:$ET$2,CF!G$2,CF!$R$4:$ET$4,"<="&HOLD_PERIOD+12) -> -32148.897 | H9: =SUMIFS(CF!$R9:$ET9,CF!$R$2:$ET$2,CF!H$2,CF!$R$4:$ET$4,"<="&HOLD_PERIOD+12) -> 0 | I9: =SUMIFS(CF!$R9:$ET9,CF!$R$2:$ET$2,CF!I$2,CF!$R$4:$ET$4,"<="&HOLD_PERIOD+12) -> 0 | J9: =SUMIFS(CF!$R9:$ET9,CF!$R$2:$ET$2,CF!J$2,CF!$R$4:$ET$4,"<="&HOLD_PERIOD+12) -> 0 | K9: =SUMIFS(CF!$R9:$ET9,CF!$R$2:$ET$2,CF!K$2,CF!$R$4:$ET$4,"<="&HOLD_PERIOD+12) -> 0 | ... M9: =SUMIFS(CF!$R9:$ET9,CF!$R$2:$ET$2,CF!M$2,CF!$R$4:$ET$4,"<="&HOLD_PERIOD+12) -> 0 | P9: =SUMIF($R$4:$ET$4,"<="&HOLD_PERIOD,R9:ET9) -> -80441.593 | Q9: Free Rent | S9: =IF(S4>HOLD_PERIOD+12,0,SUMIF(Leases!$B$170:$B$955,"FR",Leases!D$170:D$955)) -> 0 | T9: =IF(T4>HOLD_PERIOD+12,0,SUMIF(Leases!$B$170:$B$955,"FR",Leases!E$170:E$955)) -> 0 | U9: =IF(U4>HOLD_PERIOD+12,0,SUMIF(Leases!$B$170:$B$955,"FR",Leases!F$170:F$955)) -> 0 | V9: =IF(V4>HOLD_PERIOD+12,0,SUMIF(Leases!$B$170:$B$955,"FR",Leases!G$170:G$955)) -> 0 | W9: =IF(W4>HOLD_PERIOD+12,0,SUMIF(Leases!$B$170:$B$955,"FR",Leases!H$170:H$955)) -> 0 | X9: =IF(X4>HOLD_PERIOD+12,0,SUMIF(Leases!$B$170:$B$955,"FR",Leases!I$170:I$955)) -> 0 | Y9: =IF(Y4>HOLD_PERIOD+12,0,SUMIF(Leases!$B$170:$B$955,"FR",Leases!J$170:J$955)) -> -9615.5908 | Z9: =IF(Z4>HOLD_PERIOD+12,0,SUMIF(Leases!$B$170:$B$955,"FR",Leases!K$170:K$955)) -> -9615.5908 | ... ET9: =IF(ET4>HOLD_PERIOD+12,0,SUMIF(Leases!$B$170:$B$955,"FR",Leases!EE$170:EE$955)) -> 0
A10: =SUM(C10:M10) -> 0 | B10: Credit Loss | D10: =SUMIFS(CF!$R10:$ET10,CF!$R$2:$ET$2,CF!D$2,CF!$R$4:$ET$4,"<="&HOLD_PERIOD+12) -> 0 | E10: =SUMIFS(CF!$R10:$ET10,CF!$R$2:$ET$2,CF!E$2,CF!$R$4:$ET$4,"<="&HOLD_PERIOD+12) -> 0 | F10: =SUMIFS(CF!$R10:$ET10,CF!$R$2:$ET$2,CF!F$2,CF!$R$4:$ET$4,"<="&HOLD_PERIOD+12) -> 0 | G10: =SUMIFS(CF!$R10:$ET10,CF!$R$2:$ET$2,CF!G$2,CF!$R$4:$ET$4,"<="&HOLD_PERIOD+12) -> 0 | H10: =SUMIFS(CF!$R10:$ET10,CF!$R$2:$ET$2,CF!H$2,CF!$R$4:$ET$4,"<="&HOLD_PERIOD+12) -> 0 | I10: =SUMIFS(CF!$R10:$ET10,CF!$R$2:$ET$2,CF!I$2,CF!$R$4:$ET$4,"<="&HOLD_PERIOD+12) -> 0 | J10: =SUMIFS(CF!$R10:$ET10,CF!$R$2:$ET$2,CF!J$2,CF!$R$4:$ET$4,"<="&HOLD_PERIOD+12) -> 0 | K10: =SUMIFS(CF!$R10:$ET10,CF!$R$2:$ET$2,CF!K$2,CF!$R$4:$ET$4,"<="&HOLD_PERIOD+12) -> 0 | ... M10: =SUMIFS(CF!$R10:$ET10,CF!$R$2:$ET$2,CF!M$2,CF!$R$4:$ET$4,"<="&HOLD_PERIOD+12) -> 0 | P10: =SUMIF($R$4:$ET$4,"<="&HOLD_PERIOD,R10:ET10) -> 0 | Q10: Credit Loss | S10: =-HLOOKUP(S2,Expenses!$J$2:$T$3,2,0)*SUM(S8:S9) -> 0 | T10: =-HLOOKUP(T2,Expenses!$J$2:$T$3,2,0)*SUM(T8:T9) -> 0 | U10: =-HLOOKUP(U2,Expenses!$J$2:$T$3,2,0)*SUM(U8:U9) -> 0 | V10: =-HLOOKUP(V2,Expenses!$J$2:$T$3,2,0)*SUM(V8:V9) -> 0 | W10: =-HLOOKUP(W2,Expenses!$J$2:$T$3,2,0)*SUM(W8:W9) -> 0 | X10: =-HLOOKUP(X2,Expenses!$J$2:$T$3,2,0)*SUM(X8:X9) -> 0 | Y10: =-HLOOKUP(Y2,Expenses!$J$2:$T$3,2,0)*SUM(Y8:Y9) -> 0 | Z10: =-HLOOKUP(Z2,Expenses!$J$2:$T$3,2,0)*SUM(Z8:Z9) -> 0 | ... ET10: =-HLOOKUP(ET2,Expenses!$J$2:$T$3,2,0)*SUM(ET8:ET9) -> 0
A11: =SUM(C11:M11) -> 2660370.6 | B11: Net Rental Income | D11: =SUMIFS(CF!$R11:$ET11,CF!$R$2:$ET$2,CF!D$2,CF!$R$4:$ET$4,"<="&HOLD_PERIOD+12) -> 385852.77 | E11: =SUMIFS(CF!$R11:$ET11,CF!$R$2:$ET$2,CF!E$2,CF!$R$4:$ET$4,"<="&HOLD_PERIOD+12) -> 419542.15 | F11: =SUMIFS(CF!$R11:$ET11,CF!$R$2:$ET$2,CF!F$2,CF!$R$4:$ET$4,"<="&HOLD_PERIOD+12) -> 441812.66 | G11: =SUMIFS(CF!$R11:$ET11,CF!$R$2:$ET$2,CF!G$2,CF!$R$4:$ET$4,"<="&HOLD_PERIOD+12) -> 432006.76 | H11: =SUMIFS(CF!$R11:$ET11,CF!$R$2:$ET$2,CF!H$2,CF!$R$4:$ET$4,"<="&HOLD_PERIOD+12) -> 516275.34 | I11: =SUMIFS(CF!$R11:$ET11,CF!$R$2:$ET$2,CF!I$2,CF!$R$4:$ET$4,"<="&HOLD_PERIOD+12) -> 464880.97 | J11: =SUMIFS(CF!$R11:$ET11,CF!$R$2:$ET$2,CF!J$2,CF!$R$4:$ET$4,"<="&HOLD_PERIOD+12) -> 0 | K11: =SUMIFS(CF!$R11:$ET11,CF!$R$2:$ET$2,CF!K$2,CF!$R$4:$ET$4,"<="&HOLD_PERIOD+12) -> 0 | ... M11: =SUMIFS(CF!$R11:$ET11,CF!$R$2:$ET$2,CF!M$2,CF!$R$4:$ET$4,"<="&HOLD_PERIOD+12) -> 0 | P11: =SUMIF($R$4:$ET$4,"<="&HOLD_PERIOD,R11:ET11) -> 2195489.7 | Q11: Net Rental Income | S11: =SUM(S8:S10) -> 33373.455 | T11: =SUM(T8:T10) -> 33373.455 | U11: =SUM(U8:U10) -> 33566.384 | V11: =SUM(V8:V10) -> 33962.546 | W11: =SUM(W8:W10) -> 26639.321 | X11: =SUM(X8:X10) -> 26639.321 | Y11: =SUM(Y8:Y10) -> 26639.321 | Z11: =SUM(Z8:Z10) -> 26639.321 | ... ET11: =SUM(ET8:ET10) -> 0
B13: Other Income | Q13: Other Income
A14: =SUM(C14:M14) -> 426845.1 | B14: CAM Reimbursements | D14: =SUMIFS(CF!$R14:$ET14,CF!$R$2:$ET$2,CF!D$2,CF!$R$4:$ET$4,"<="&HOLD_PERIOD+12) -> 66949.713 | E14: =SUMIFS(CF!$R14:$ET14,CF!$R$2:$ET$2,CF!E$2,CF!$R$4:$ET$4,"<="&HOLD_PERIOD+12) -> 69605.518 | F14: =SUMIFS(CF!$R14:$ET14,CF!$R$2:$ET$2,CF!F$2,CF!$R$4:$ET$4,"<="&HOLD_PERIOD+12) -> 71561.331 | G14: =SUMIFS(CF!$R14:$ET14,CF!$R$2:$ET$2,CF!G$2,CF!$R$4:$ET$4,"<="&HOLD_PERIOD+12) -> 70957.408 | H14: =SUMIFS(CF!$R14:$ET14,CF!$R$2:$ET$2,CF!H$2,CF!$R$4:$ET$4,"<="&HOLD_PERIOD+12) -> 77881.278 | I14: =SUMIFS(CF!$R14:$ET14,CF!$R$2:$ET$2,CF!I$2,CF!$R$4:$ET$4,"<="&HOLD_PERIOD+12) -> 69889.848 | J14: =SUMIFS(CF!$R14:$ET14,CF!$R$2:$ET$2,CF!J$2,CF!$R$4:$ET$4,"<="&HOLD_PERIOD+12) -> 0 | K14: =SUMIFS(CF!$R14:$ET14,CF!$R$2:$ET$2,CF!K$2,CF!$R$4:$ET$4,"<="&HOLD_PERIOD+12) -> 0 | ... M14: =SUMIFS(CF!$R14:$ET14,CF!$R$2:$ET$2,CF!M$2,CF!$R$4:$ET$4,"<="&HOLD_PERIOD+12) -> 0 | P14: =SUMIF($R$4:$ET$4,"<="&HOLD_PERIOD,R14:ET14) -> 356955.25 | Q14: CAM Reimbursements | S14: =IF(S4>HOLD_PERIOD+12,0,SUMIF(Leases!$B$170:$B$955,"CAM",Leases!D$170:D$955)) -> 5750.575 | T14: =IF(T4>HOLD_PERIOD+12,0,SUMIF(Leases!$B$170:$B$955,"CAM",Leases!E$170:E$955)) -> 5763.5902 | U14: =IF(U4>HOLD_PERIOD+12,0,SUMIF(Leases!$B$170:$B$955,"CAM",Leases!F$170:F$955)) -> 5776.6348 | V14: =IF(V4>HOLD_PERIOD+12,0,SUMIF(Leases!$B$170:$B$955,"CAM",Leases!G$170:G$955)) -> 5789.7089 | W14: =IF(W4>HOLD_PERIOD+12,0,SUMIF(Leases!$B$170:$B$955,"CAM",Leases!H$170:H$955)) -> 4343.1137 | X14: =IF(X4>HOLD_PERIOD+12,0,SUMIF(Leases!$B$170:$B$955,"CAM",Leases!I$170:I$955)) -> 4352.9434 | Y14: =IF(Y4>HOLD_PERIOD+12,0,SUMIF(Leases!$B$170:$B$955,"CAM",Leases!J$170:J$955)) -> 5829.1091 | Z14: =IF(Z4>HOLD_PERIOD+12,0,SUMIF(Leases!$B$170:$B$955,"CAM",Leases!K$170:K$955)) -> 5842.302 | ... ET14: =IF(ET4>HOLD_PERIOD+12,0,SUMIF(Leases!$B$170:$B$955,"CAM",Leases!EE$170:EE$955)) -> 0
A15: =SUM(C15:M15) -> 0 | B15: Percentage Rent | D15: =SUMIFS(CF!$R15:$ET15,CF!$R$2:$ET$2,CF!D$2,CF!$R$4:$ET$4,"<="&HOLD_PERIOD+12) -> 0 | E15: =SUMIFS(CF!$R15:$ET15,CF!$R$2:$ET$2,CF!E$2,CF!$R$4:$ET$4,"<="&HOLD_PERIOD+12) -> 0 | F15: =SUMIFS(CF!$R15:$ET15,CF!$R$2:$ET$2,CF!F$2,CF!$R$4:$ET$4,"<="&HOLD_PERIOD+12) -> 0 | G15: =SUMIFS(CF!$R15:$ET15,CF!$R$2:$ET$2,CF!G$2,CF!$R$4:$ET$4,"<="&HOLD_PERIOD+12) -> 0 | H15: =SUMIFS(CF!$R15:$ET15,CF!$R$2:$ET$2,CF!H$2,CF!$R$4:$ET$4,"<="&HOLD_PERIOD+12) -> 0 | I15: =SUMIFS(CF!$R15:$ET15,CF!$R$2:$ET$2,CF!I$2,CF!$R$4:$ET$4,"<="&HOLD_PERIOD+12) -> 0 | J15: =SUMIFS(CF!$R15:$ET15,CF!$R$2:$ET$2,CF!J$2,CF!$R$4:$ET$4,"<="&HOLD_PERIOD+12) -> 0 | K15: =SUMIFS(CF!$R15:$ET15,CF!$R$2:$ET$2,CF!K$2,CF!$R$4:$ET$4,"<="&HOLD_PERIOD+12) -> 0 | ... M15: =SUMIFS(CF!$R15:$ET15,CF!$R$2:$ET$2,CF!M$2,CF!$R$4:$ET$4,"<="&HOLD_PERIOD+12) -> 0 | P15: =SUMIF($R$4:$ET$4,"<="&HOLD_PERIOD,R15:ET15) -> 0 | Q15: Percentage Rent | S15: =IF(S4>HOLD_PERIOD+12,0,SUMIF(Leases!$B$170:$B$955,"PR",Leases!D$170:D$955)) -> 0 | T15: =IF(T4>HOLD_PERIOD+12,0,SUMIF(Leases!$B$170:$B$955,"PR",Leases!E$170:E$955)) -> 0 | U15: =IF(U4>HOLD_PERIOD+12,0,SUMIF(Leases!$B$170:$B$955,"PR",Leases!F$170:F$955)) -> 0 | V15: =IF(V4>HOLD_PERIOD+12,0,SUMIF(Leases!$B$170:$B$955,"PR",Leases!G$170:G$955)) -> 0 | W15: =IF(W4>HOLD_PERIOD+12,0,SUMIF(Leases!$B$170:$B$955,"PR",Leases!H$170:H$955)) -> 0 | X15: =IF(X4>HOLD_PERIOD+12,0,SUMIF(Leases!$B$170:$B$955,"PR",Leases!I$170:I$955)) -> 0 | Y15: =IF(Y4>HOLD_PERIOD+12,0,SUMIF(Leases!$B$170:$B$955,"PR",Leases!J$170:J$955)) -> 0 | Z15: =IF(Z4>HOLD_PERIOD+12,0,SUMIF(Leases!$B$170:$B$955,"PR",Leases!K$170:K$955)) -> 0 | ... ET15: =IF(ET4>HOLD_PERIOD+12,0,SUMIF(Leases!$B$170:$B$955,"PR",Leases!EE$170:EE$955)) -> 0
A16: =SUM(C16:M16) -> 426845.1 | B16: Total Other Income | D16: =SUMIFS(CF!$R16:$ET16,CF!$R$2:$ET$2,CF!D$2,CF!$R$4:$ET$4,"<="&HOLD_PERIOD+12) -> 66949.713 | E16: =SUMIFS(CF!$R16:$ET16,CF!$R$2:$ET$2,CF!E$2,CF!$R$4:$ET$4,"<="&HOLD_PERIOD+12) -> 69605.518 | F16: =SUMIFS(CF!$R16:$ET16,CF!$R$2:$ET$2,CF!F$2,CF!$R$4:$ET$4,"<="&HOLD_PERIOD+12) -> 71561.331 | G16: =SUMIFS(CF!$R16:$ET16,CF!$R$2:$ET$2,CF!G$2,CF!$R$4:$ET$4,"<="&HOLD_PERIOD+12) -> 70957.408 | H16: =SUMIFS(CF!$R16:$ET16,CF!$R$2:$ET$2,CF!H$2,CF!$R$4:$ET$4,"<="&HOLD_PERIOD+12) -> 77881.278 | I16: =SUMIFS(CF!$R16:$ET16,CF!$R$2:$ET$2,CF!I$2,CF!$R$4:$ET$4,"<="&HOLD_PERIOD+12) -> 69889.848 | J16: =SUMIFS(CF!$R16:$ET16,CF!$R$2:$ET$2,CF!J$2,CF!$R$4:$ET$4,"<="&HOLD_PERIOD+12) -> 0 | K16: =SUMIFS(CF!$R16:$ET16,CF!$R$2:$ET$2,CF!K$2,CF!$R$4:$ET$4,"<="&HOLD_PERIOD+12) -> 0 | ... M16: =SUMIFS(CF!$R16:$ET16,CF!$R$2:$ET$2,CF!M$2,CF!$R$4:$ET$4,"<="&HOLD_PERIOD+12) -> 0 | P16: =SUMIF($R$4:$ET$4,"<="&HOLD_PERIOD,R16:ET16) -> 356955.25 | Q16: Total Other Income | S16: =SUM(S14:S15) -> 5750.575 | T16: =SUM(T14:T15) -> 5763.5902 | U16: =SUM(U14:U15) -> 5776.6348 | V16: =SUM(V14:V15) -> 5789.7089 | W16: =SUM(W14:W15) -> 4343.1137 | X16: =SUM(X14:X15) -> 4352.9434 | Y16: =SUM(Y14:Y15) -> 5829.1091 | Z16: =SUM(Z14:Z15) -> 5842.302 | ... ET16: =SUM(ET14:ET15) -> 0
A18: =SUM(C18:M18) -> 3087215.7 | B18: Effective Gross Revenue | D18: =SUMIFS(CF!$R18:$ET18,CF!$R$2:$ET$2,CF!D$2,CF!$R$4:$ET$4,"<="&HOLD_PERIOD+12) -> 452802.48 | E18: =SUMIFS(CF!$R18:$ET18,CF!$R$2:$ET$2,CF!E$2,CF!$R$4:$ET$4,"<="&HOLD_PERIOD+12) -> 489147.67 | F18: =SUMIFS(CF!$R18:$ET18,CF!$R$2:$ET$2,CF!F$2,CF!$R$4:$ET$4,"<="&HOLD_PERIOD+12) -> 513373.99 | G18: =SUMIFS(CF!$R18:$ET18,CF!$R$2:$ET$2,CF!G$2,CF!$R$4:$ET$4,"<="&HOLD_PERIOD+12) -> 502964.17 | H18: =SUMIFS(CF!$R18:$ET18,CF!$R$2:$ET$2,CF!H$2,CF!$R$4:$ET$4,"<="&HOLD_PERIOD+12) -> 594156.62 | I18: =SUMIFS(CF!$R18:$ET18,CF!$R$2:$ET$2,CF!I$2,CF!$R$4:$ET$4,"<="&HOLD_PERIOD+12) -> 534770.81 | J18: =SUMIFS(CF!$R18:$ET18,CF!$R$2:$ET$2,CF!J$2,CF!$R$4:$ET$4,"<="&HOLD_PERIOD+12) -> 0 | K18: =SUMIFS(CF!$R18:$ET18,CF!$R$2:$ET$2,CF!K$2,CF!$R$4:$ET$4,"<="&HOLD_PERIOD+12) -> 0 | ... M18: =SUMIFS(CF!$R18:$ET18,CF!$R$2:$ET$2,CF!M$2,CF!$R$4:$ET$4,"<="&HOLD_PERIOD+12) -> 0 | P18: =SUMIF($R$4:$ET$4,"<="&HOLD_PERIOD,R18:ET18) -> 2552444.9 | Q18: Effective Gross Revenue | S18: =SUM(S11,S16) -> 39124.03 | T18: =SUM(T11,T16) -> 39137.045 | U18: =SUM(U11,U16) -> 39343.019 | V18: =SUM(V11,V16) -> 39752.255 | W18: =SUM(W11,W16) -> 30982.435 | X18: =SUM(X11,X16) -> 30992.265 | Y18: =SUM(Y11,Y16) -> 32468.43 | Z18: =SUM(Z11,Z16) -> 32481.623 | ... ET18: =SUM(ET11,ET16) -> 0
B20: Operating Expenses | Q20: Operating Expenses
A21: =SUM(C21:M21) -> 0 | B21: =Expenses!E5 -> Insurance | D21: =SUMIFS(CF!$R21:$ET21,CF!$R$2:$ET$2,CF!D$2,CF!$R$4:$ET$4,"<="&HOLD_PERIOD+12) -> 0 | E21: =SUMIFS(CF!$R21:$ET21,CF!$R$2:$ET$2,CF!E$2,CF!$R$4:$ET$4,"<="&HOLD_PERIOD+12) -> 0 | F21: =SUMIFS(CF!$R21:$ET21,CF!$R$2:$ET$2,CF!F$2,CF!$R$4:$ET$4,"<="&HOLD_PERIOD+12) -> 0 | G21: =SUMIFS(CF!$R21:$ET21,CF!$R$2:$ET$2,CF!G$2,CF!$R$4:$ET$4,"<="&HOLD_PERIOD+12) -> 0 | H21: =SUMIFS(CF!$R21:$ET21,CF!$R$2:$ET$2,CF!H$2,CF!$R$4:$ET$4,"<="&HOLD_PERIOD+12) -> 0 | I21: =SUMIFS(CF!$R21:$ET21,CF!$R$2:$ET$2,CF!I$2,CF!$R$4:$ET$4,"<="&HOLD_PERIOD+12) -> 0 | J21: =SUMIFS(CF!$R21:$ET21,CF!$R$2:$ET$2,CF!J$2,CF!$R$4:$ET$4,"<="&HOLD_PERIOD+12) -> 0 | K21: =SUMIFS(CF!$R21:$ET21,CF!$R$2:$ET$2,CF!K$2,CF!$R$4:$ET$4,"<="&HOLD_PERIOD+12) -> 0 | ... M21: =SUMIFS(CF!$R21:$ET21,CF!$R$2:$ET$2,CF!M$2,CF!$R$4:$ET$4,"<="&HOLD_PERIOD+12) -> 0 | P21: =SUMIF($R$4:$ET$4,"<="&HOLD_PERIOD,R21:ET21) -> 0 | Q21: =Expenses!E5 -> Insurance | S21: =IF(S$4>HOLD_PERIOD+12,0,-Expenses!B14) -> 0 | T21: =IF(T$4>HOLD_PERIOD+12,0,-Expenses!C14) -> 0 | U21: =IF(U$4>HOLD_PERIOD+12,0,-Expenses!D14) -> 0 | V21: =IF(V$4>HOLD_PERIOD+12,0,-Expenses!E14) -> 0 | W21: =IF(W$4>HOLD_PERIOD+12,0,-Expenses!F14) -> 0 | X21: =IF(X$4>HOLD_PERIOD+12,0,-Expenses!G14) -> 0 | Y21: =IF(Y$4>HOLD_PERIOD+12,0,-Expenses!H14) -> 0 | Z21: =IF(Z$4>HOLD_PERIOD+12,0,-Expenses!I14) -> 0 | ... ET21: =IF(ET$4>HOLD_PERIOD+12,0,-Expenses!EC14) -> 0
A22: =SUM(C22:M22) -> 0 | B22: =Expenses!E4 -> Other | D22: =SUMIFS(CF!$R22:$ET22,CF!$R$2:$ET$2,CF!D$2,CF!$R$4:$ET$4,"<="&HOLD_PERIOD+12) -> 0 | E22: =SUMIFS(CF!$R22:$ET22,CF!$R$2:$ET$2,CF!E$2,CF!$R$4:$ET$4,"<="&HOLD_PERIOD+12) -> 0 | F22: =SUMIFS(CF!$R22:$ET22,CF!$R$2:$ET$2,CF!F$2,CF!$R$4:$ET$4,"<="&HOLD_PERIOD+12) -> 0 | G22: =SUMIFS(CF!$R22:$ET22,CF!$R$2:$ET$2,CF!G$2,CF!$R$4:$ET$4,"<="&HOLD_PERIOD+12) -> 0 | H22: =SUMIFS(CF!$R22:$ET22,CF!$R$2:$ET$2,CF!H$2,CF!$R$4:$ET$4,"<="&HOLD_PERIOD+12) -> 0 | I22: =SUMIFS(CF!$R22:$ET22,CF!$R$2:$ET$2,CF!I$2,CF!$R$4:$ET$4,"<="&HOLD_PERIOD+12) -> 0 | J22: =SUMIFS(CF!$R22:$ET22,CF!$R$2:$ET$2,CF!J$2,CF!$R$4:$ET$4,"<="&HOLD_PERIOD+12) -> 0 | K22: =SUMIFS(CF!$R22:$ET22,CF!$R$2:$ET$2,CF!K$2,CF!$R$4:$ET$4,"<="&HOLD_PERIOD+12) -> 0 | ... M22: =SUMIFS(CF!$R22:$ET22,CF!$R$2:$ET$2,CF!M$2,CF!$R$4:$ET$4,"<="&HOLD_PERIOD+12) -> 0 | P22: =SUMIF($R$4:$ET$4,"<="&HOLD_PERIOD,R22:ET22) -> 0 | Q22: =Expenses!E4 -> Other | S22: =IF(S$4>HOLD_PERIOD+12,0,-Expenses!B15) -> 0 | T22: =IF(T$4>HOLD_PERIOD+12,0,-Expenses!C15) -> 0 | U22: =IF(U$4>HOLD_PERIOD+12,0,-Expenses!D15) -> 0 | V22: =IF(V$4>HOLD_PERIOD+12,0,-Expenses!E15) -> 0 | W22: =IF(W$4>HOLD_PERIOD+12,0,-Expenses!F15) -> 0 | X22: =IF(X$4>HOLD_PERIOD+12,0,-Expenses!G15) -> 0 | Y22: =IF(Y$4>HOLD_PERIOD+12,0,-Expenses!H15) -> 0 | Z22: =IF(Z$4>HOLD_PERIOD+12,0,-Expenses!I15) -> 0 | ... ET22: =IF(ET$4>HOLD_PERIOD+12,0,-Expenses!EC15) -> 0
A23: =SUM(C23:M23) -> 0 | B23: =Expenses!E7 -> Other | D23: =SUMIFS(CF!$R23:$ET23,CF!$R$2:$ET$2,CF!D$2,CF!$R$4:$ET$4,"<="&HOLD_PERIOD+12) -> 0 | E23: =SUMIFS(CF!$R23:$ET23,CF!$R$2:$ET$2,CF!E$2,CF!$R$4:$ET$4,"<="&HOLD_PERIOD+12) -> 0 | F23: =SUMIFS(CF!$R23:$ET23,CF!$R$2:$ET$2,CF!F$2,CF!$R$4:$ET$4,"<="&HOLD_PERIOD+12) -> 0 | G23: =SUMIFS(CF!$R23:$ET23,CF!$R$2:$ET$2,CF!G$2,CF!$R$4:$ET$4,"<="&HOLD_PERIOD+12) -> 0 | H23: =SUMIFS(CF!$R23:$ET23,CF!$R$2:$ET$2,CF!H$2,CF!$R$4:$ET$4,"<="&HOLD_PERIOD+12) -> 0 | I23: =SUMIFS(CF!$R23:$ET23,CF!$R$2:$ET$2,CF!I$2,CF!$R$4:$ET$4,"<="&HOLD_PERIOD+12) -> 0 | J23: =SUMIFS(CF!$R23:$ET23,CF!$R$2:$ET$2,CF!J$2,CF!$R$4:$ET$4,"<="&HOLD_PERIOD+12) -> 0 | K23: =SUMIFS(CF!$R23:$ET23,CF!$R$2:$ET$2,CF!K$2,CF!$R$4:$ET$4,"<="&HOLD_PERIOD+12) -> 0 | ... M23: =SUMIFS(CF!$R23:$ET23,CF!$R$2:$ET$2,CF!M$2,CF!$R$4:$ET$4,"<="&HOLD_PERIOD+12) -> 0 | P23: =SUMIF($R$4:$ET$4,"<="&HOLD_PERIOD,R23:ET23) -> 0 | Q23: =Expenses!E7 -> Other | S23: =IF(S$4>HOLD_PERIOD+12,0,-Expenses!B16) -> 0 | T23: =IF(T$4>HOLD_PERIOD+12,0,-Expenses!C16) -> 0 | U23: =IF(U$4>HOLD_PERIOD+12,0,-Expenses!D16) -> 0 | V23: =IF(V$4>HOLD_PERIOD+12,0,-Expenses!E16) -> 0 | W23: =IF(W$4>HOLD_PERIOD+12,0,-Expenses!F16) -> 0 | X23: =IF(X$4>HOLD_PERIOD+12,0,-Expenses!G16) -> 0 | Y23: =IF(Y$4>HOLD_PERIOD+12,0,-Expenses!H16) -> 0 | Z23: =IF(Z$4>HOLD_PERIOD+12,0,-Expenses!I16) -> 0 | ... ET23: =IF(ET$4>HOLD_PERIOD+12,0,-Expenses!EC16) -> 0
A24: =SUM(C24:M24) -> -449135.71 | B24: =Expenses!E6 -> CAM | D24: =SUMIFS(CF!$R24:$ET24,CF!$R$2:$ET$2,CF!D$2,CF!$R$4:$ET$4,"<="&HOLD_PERIOD+12) -> -69872.414 | E24: =SUMIFS(CF!$R24:$ET24,CF!$R$2:$ET$2,CF!E$2,CF!$R$4:$ET$4,"<="&HOLD_PERIOD+12) -> -71793.906 | F24: =SUMIFS(CF!$R24:$ET24,CF!$R$2:$ET$2,CF!F$2,CF!$R$4:$ET$4,"<="&HOLD_PERIOD+12) -> -73768.238 | G24: =SUMIFS(CF!$R24:$ET24,CF!$R$2:$ET$2,CF!G$2,CF!$R$4:$ET$4,"<="&HOLD_PERIOD+12) -> -75796.865 | H24: =SUMIFS(CF!$R24:$ET24,CF!$R$2:$ET$2,CF!H$2,CF!$R$4:$ET$4,"<="&HOLD_PERIOD+12) -> -77881.278 | I24: =SUMIFS(CF!$R24:$ET24,CF!$R$2:$ET$2,CF!I$2,CF!$R$4:$ET$4,"<="&HOLD_PERIOD+12) -> -80023.013 | J24: =SUMIFS(CF!$R24:$ET24,CF!$R$2:$ET$2,CF!J$2,CF!$R$4:$ET$4,"<="&HOLD_PERIOD+12) -> 0 | K24: =SUMIFS(CF!$R24:$ET24,CF!$R$2:$ET$2,CF!K$2,CF!$R$4:$ET$4,"<="&HOLD_PERIOD+12) -> 0 | ... M24: =SUMIFS(CF!$R24:$ET24,CF!$R$2:$ET$2,CF!M$2,CF!$R$4:$ET$4,"<="&HOLD_PERIOD+12) -> 0 | P24: =SUMIF($R$4:$ET$4,"<="&HOLD_PERIOD,R24:ET24) -> -369112.7 | Q24: =Expenses!E6 -> CAM | S24: =IF(S$4>HOLD_PERIOD+12,0,-Expenses!B17) -> -5750.575 | T24: =IF(T$4>HOLD_PERIOD+12,0,-Expenses!C17) -> -5763.5902 | U24: =IF(U$4>HOLD_PERIOD+12,0,-Expenses!D17) -> -5776.6348 | V24: =IF(V$4>HOLD_PERIOD+12,0,-Expenses!E17) -> -5789.7089 | W24: =IF(W$4>HOLD_PERIOD+12,0,-Expenses!F17) -> -5802.8126 | X24: =IF(X$4>HOLD_PERIOD+12,0,-Expenses!G17) -> -5815.946 | Y24: =IF(Y$4>HOLD_PERIOD+12,0,-Expenses!H17) -> -5829.1091 | Z24: =IF(Z$4>HOLD_PERIOD+12,0,-Expenses!I17) -> -5842.302 | ... ET24: =IF(ET$4>HOLD_PERIOD+12,0,-Expenses!EC17) -> 0
A25: =SUM(C25:M25) -> 0 | B25: =Expenses!E8 -> Other | D25: =SUMIFS(CF!$R25:$ET25,CF!$R$2:$ET$2,CF!D$2,CF!$R$4:$ET$4,"<="&HOLD_PERIOD+12) -> 0 | E25: =SUMIFS(CF!$R25:$ET25,CF!$R$2:$ET$2,CF!E$2,CF!$R$4:$ET$4,"<="&HOLD_PERIOD+12) -> 0 | F25: =SUMIFS(CF!$R25:$ET25,CF!$R$2:$ET$2,CF!F$2,CF!$R$4:$ET$4,"<="&HOLD_PERIOD+12) -> 0 | G25: =SUMIFS(CF!$R25:$ET25,CF!$R$2:$ET$2,CF!G$2,CF!$R$4:$ET$4,"<="&HOLD_PERIOD+12) -> 0 | H25: =SUMIFS(CF!$R25:$ET25,CF!$R$2:$ET$2,CF!H$2,CF!$R$4:$ET$4,"<="&HOLD_PERIOD+12) -> 0 | I25: =SUMIFS(CF!$R25:$ET25,CF!$R$2:$ET$2,CF!I$2,CF!$R$4:$ET$4,"<="&HOLD_PERIOD+12) -> 0 | J25: =SUMIFS(CF!$R25:$ET25,CF!$R$2:$ET$2,CF!J$2,CF!$R$4:$ET$4,"<="&HOLD_PERIOD+12) -> 0 | K25: =SUMIFS(CF!$R25:$ET25,CF!$R$2:$ET$2,CF!K$2,CF!$R$4:$ET$4,"<="&HOLD_PERIOD+12) -> 0 | ... M25: =SUMIFS(CF!$R25:$ET25,CF!$R$2:$ET$2,CF!M$2,CF!$R$4:$ET$4,"<="&HOLD_PERIOD+12) -> 0 | P25: =SUMIF($R$4:$ET$4,"<="&HOLD_PERIOD,R25:ET25) -> 0 | Q25: =Expenses!E8 -> Other | S25: =IF(S$4>HOLD_PERIOD+12,0,-Expenses!B18) -> 0 | T25: =IF(T$4>HOLD_PERIOD+12,0,-Expenses!C18) -> 0 | U25: =IF(U$4>HOLD_PERIOD+12,0,-Expenses!D18) -> 0 | V25: =IF(V$4>HOLD_PERIOD+12,0,-Expenses!E18) -> 0 | W25: =IF(W$4>HOLD_PERIOD+12,0,-Expenses!F18) -> 0 | X25: =IF(X$4>HOLD_PERIOD+12,0,-Expenses!G18) -> 0 | Y25: =IF(Y$4>HOLD_PERIOD+12,0,-Expenses!H18) -> 0 | Z25: =IF(Z$4>HOLD_PERIOD+12,0,-Expenses!I18) -> 0 | ... ET25: =IF(ET$4>HOLD_PERIOD+12,0,-Expenses!EC18) -> 0
A26: =SUM(C26:M26) -> -449135.71 | B26: Total Operating Expenses | D26: =SUMIFS(CF!$R26:$ET26,CF!$R$2:$ET$2,CF!D$2,CF!$R$4:$ET$4,"<="&HOLD_PERIOD+12) -> -69872.414 | E26: =SUMIFS(CF!$R26:$ET26,CF!$R$2:$ET$2,CF!E$2,CF!$R$4:$ET$4,"<="&HOLD_PERIOD+12) -> -71793.906 | F26: =SUMIFS(CF!$R26:$ET26,CF!$R$2:$ET$2,CF!F$2,CF!$R$4:$ET$4,"<="&HOLD_PERIOD+12) -> -73768.238 | G26: =SUMIFS(CF!$R26:$ET26,CF!$R$2:$ET$2,CF!G$2,CF!$R$4:$ET$4,"<="&HOLD_PERIOD+12) -> -75796.865 | H26: =SUMIFS(CF!$R26:$ET26,CF!$R$2:$ET$2,CF!H$2,CF!$R$4:$ET$4,"<="&HOLD_PERIOD+12) -> -77881.278 | I26: =SUMIFS(CF!$R26:$ET26,CF!$R$2:$ET$2,CF!I$2,CF!$R$4:$ET$4,"<="&HOLD_PERIOD+12) -> -80023.013 | J26: =SUMIFS(CF!$R26:$ET26,CF!$R$2:$ET$2,CF!J$2,CF!$R$4:$ET$4,"<="&HOLD_PERIOD+12) -> 0 | K26: =SUMIFS(CF!$R26:$ET26,CF!$R$2:$ET$2,CF!K$2,CF!$R$4:$ET$4,"<="&HOLD_PERIOD+12) -> 0 | ... M26: =SUMIFS(CF!$R26:$ET26,CF!$R$2:$ET$2,CF!M$2,CF!$R$4:$ET$4,"<="&HOLD_PERIOD+12) -> 0 | P26: =SUMIF($R$4:$ET$4,"<="&HOLD_PERIOD,R26:ET26) -> -369112.7 | Q26: Total Operating Expenses | S26: =SUM(S22:S25) -> -5750.575 | T26: =SUM(T22:T25) -> -5763.5902 | U26: =SUM(U22:U25) -> -5776.6348 | V26: =SUM(V22:V25) -> -5789.7089 | W26: =SUM(W22:W25) -> -5802.8126 | X26: =SUM(X22:X25) -> -5815.946 | Y26: =SUM(Y22:Y25) -> -5829.1091 | Z26: =SUM(Z22:Z25) -> -5842.302 | ... ET26: =SUM(ET22:ET25) -> 0
A28: =SUM(C28:M28) -> 2638080 | B28: Net Operating Income | D28: =SUMIFS(CF!$R28:$ET28,CF!$R$2:$ET$2,CF!D$2,CF!$R$4:$ET$4,"<="&HOLD_PERIOD+12) -> 382930.07 | E28: =SUMIFS(CF!$R28:$ET28,CF!$R$2:$ET$2,CF!E$2,CF!$R$4:$ET$4,"<="&HOLD_PERIOD+12) -> 417353.76 | F28: =SUMIFS(CF!$R28:$ET28,CF!$R$2:$ET$2,CF!F$2,CF!$R$4:$ET$4,"<="&HOLD_PERIOD+12) -> 439605.75 | G28: =SUMIFS(CF!$R28:$ET28,CF!$R$2:$ET$2,CF!G$2,CF!$R$4:$ET$4,"<="&HOLD_PERIOD+12) -> 427167.3 | H28: =SUMIFS(CF!$R28:$ET28,CF!$R$2:$ET$2,CF!H$2,CF!$R$4:$ET$4,"<="&HOLD_PERIOD+12) -> 516275.34 | I28: =SUMIFS(CF!$R28:$ET28,CF!$R$2:$ET$2,CF!I$2,CF!$R$4:$ET$4,"<="&HOLD_PERIOD+12) -> 454747.8 | J28: =SUMIFS(CF!$R28:$ET28,CF!$R$2:$ET$2,CF!J$2,CF!$R$4:$ET$4,"<="&HOLD_PERIOD+12) -> 0 | K28: =SUMIFS(CF!$R28:$ET28,CF!$R$2:$ET$2,CF!K$2,CF!$R$4:$ET$4,"<="&HOLD_PERIOD+12) -> 0 | ... M28: =SUMIFS(CF!$R28:$ET28,CF!$R$2:$ET$2,CF!M$2,CF!$R$4:$ET$4,"<="&HOLD_PERIOD+12) -> 0 | P28: =SUMIF($R$4:$ET$4,"<="&HOLD_PERIOD,R28:ET28) -> 2183332.2 | Q28: Net Operating Income | S28: =SUM(S18,S26) -> 33373.455 | T28: =SUM(T18,T26) -> 33373.455 | U28: =SUM(U18,U26) -> 33566.384 | V28: =SUM(V18,V26) -> 33962.546 | W28: =SUM(W18,W26) -> 25179.622 | X28: =SUM(X18,X26) -> 25176.318 | Y28: =SUM(Y18,Y26) -> 26639.321 | Z28: =SUM(Z18,Z26) -> 26639.321 | ... ET28: =SUM(ET18,ET26) -> 0
B30: TI/LC Expenses | Q30: TI/LC Expenses
A31: =SUM(C31:M31) -> -341317.5 | B31: Tenant Improvements | D31: =SUMIFS(CF!$R31:$ET31,CF!$R$2:$ET$2,CF!D$2,CF!$R$4:$ET$4,"<="&HOLD_PERIOD) -> -85858.5 | E31: =SUMIFS(CF!$R31:$ET31,CF!$R$2:$ET$2,CF!E$2,CF!$R$4:$ET$4,"<="&HOLD_PERIOD) -> -62143.5 | F31: =SUMIFS(CF!$R31:$ET31,CF!$R$2:$ET$2,CF!F$2,CF!$R$4:$ET$4,"<="&HOLD_PERIOD) -> -61965 | G31: =SUMIFS(CF!$R31:$ET31,CF!$R$2:$ET$2,CF!G$2,CF!$R$4:$ET$4,"<="&HOLD_PERIOD) -> -131350.5 | H31: =SUMIFS(CF!$R31:$ET31,CF!$R$2:$ET$2,CF!H$2,CF!$R$4:$ET$4,"<="&HOLD_PERIOD) -> 0 | I31: =SUMIFS(CF!$R31:$ET31,CF!$R$2:$ET$2,CF!I$2,CF!$R$4:$ET$4,"<="&HOLD_PERIOD) -> 0 | J31: =SUMIFS(CF!$R31:$ET31,CF!$R$2:$ET$2,CF!J$2,CF!$R$4:$ET$4,"<="&HOLD_PERIOD) -> 0 | K31: =SUMIFS(CF!$R31:$ET31,CF!$R$2:$ET$2,CF!K$2,CF!$R$4:$ET$4,"<="&HOLD_PERIOD) -> 0 | ... M31: =SUMIFS(CF!$R31:$ET31,CF!$R$2:$ET$2,CF!M$2,CF!$R$4:$ET$4,"<="&HOLD_PERIOD) -> 0 | P31: =SUMIF($R$4:$ET$4,"<="&HOLD_PERIOD,R31:ET31) -> -341317.5 | Q31: Tenant Improvements | S31: =IF(S4<=HOLD_PERIOD,SUMIF(Leases!$B$170:$B$955,"TI",Leases!D$170:D$955),0) -> 0 | T31: =IF(T4<=HOLD_PERIOD,SUMIF(Leases!$B$170:$B$955,"TI",Leases!E$170:E$955),0) -> 0 | U31: =IF(U4<=HOLD_PERIOD,SUMIF(Leases!$B$170:$B$955,"TI",Leases!F$170:F$955),0) -> 0 | V31: =IF(V4<=HOLD_PERIOD,SUMIF(Leases!$B$170:$B$955,"TI",Leases!G$170:G$955),0) -> 0 | W31: =IF(W4<=HOLD_PERIOD,SUMIF(Leases!$B$170:$B$955,"TI",Leases!H$170:H$955),0) -> 0 | X31: =IF(X4<=HOLD_PERIOD,SUMIF(Leases!$B$170:$B$955,"TI",Leases!I$170:I$955),0) -> -85858.5 | Y31: =IF(Y4<=HOLD_PERIOD,SUMIF(Leases!$B$170:$B$955,"TI",Leases!J$170:J$955),0) -> 0 | Z31: =IF(Z4<=HOLD_PERIOD,SUMIF(Leases!$B$170:$B$955,"TI",Leases!K$170:K$955),0) -> 0 | ... ET31: =IF(ET4<=HOLD_PERIOD,SUMIF(Leases!$B$170:$B$955,"TI",Leases!EE$170:EE$955),0) -> 0
A32: =SUM(C32:M32) -> -115764.6 | B32: Leasing Commissions | D32: =SUMIFS(CF!$R32:$ET32,CF!$R$2:$ET$2,CF!D$2,CF!$R$4:$ET$4,"<="&HOLD_PERIOD) -> -27717.927 | E32: =SUMIFS(CF!$R32:$ET32,CF!$R$2:$ET$2,CF!E$2,CF!$R$4:$ET$4,"<="&HOLD_PERIOD) -> -20821.371 | F32: =SUMIFS(CF!$R32:$ET32,CF!$R$2:$ET$2,CF!F$2,CF!$R$4:$ET$4,"<="&HOLD_PERIOD) -> -21006.826 | G32: =SUMIFS(CF!$R32:$ET32,CF!$R$2:$ET$2,CF!G$2,CF!$R$4:$ET$4,"<="&HOLD_PERIOD) -> -46218.476 | H32: =SUMIFS(CF!$R32:$ET32,CF!$R$2:$ET$2,CF!H$2,CF!$R$4:$ET$4,"<="&HOLD_PERIOD) -> 0 | I32: =SUMIFS(CF!$R32:$ET32,CF!$R$2:$ET$2,CF!I$2,CF!$R$4:$ET$4,"<="&HOLD_PERIOD) -> 0 | J32: =SUMIFS(CF!$R32:$ET32,CF!$R$2:$ET$2,CF!J$2,CF!$R$4:$ET$4,"<="&HOLD_PERIOD) -> 0 | K32: =SUMIFS(CF!$R32:$ET32,CF!$R$2:$ET$2,CF!K$2,CF!$R$4:$ET$4,"<="&HOLD_PERIOD) -> 0 | ... M32: =SUMIFS(CF!$R32:$ET32,CF!$R$2:$ET$2,CF!M$2,CF!$R$4:$ET$4,"<="&HOLD_PERIOD) -> 0 | P32: =SUMIF($R$4:$ET$4,"<="&HOLD_PERIOD,R32:ET32) -> -115764.6 | Q32: Leasing Commissions | S32: =IF(S4<=HOLD_PERIOD,SUMIF(Leases!$B$170:$B$955,"LC",Leases!D$170:D$955),0) -> 0 | T32: =IF(T4<=HOLD_PERIOD,SUMIF(Leases!$B$170:$B$955,"LC",Leases!E$170:E$955),0) -> 0 | U32: =IF(U4<=HOLD_PERIOD,SUMIF(Leases!$B$170:$B$955,"LC",Leases!F$170:F$955),0) -> 0 | V32: =IF(V4<=HOLD_PERIOD,SUMIF(Leases!$B$170:$B$955,"LC",Leases!G$170:G$955),0) -> 0 | W32: =IF(W4<=HOLD_PERIOD,SUMIF(Leases!$B$170:$B$955,"LC",Leases!H$170:H$955),0) -> 0 | X32: =IF(X4<=HOLD_PERIOD,SUMIF(Leases!$B$170:$B$955,"LC",Leases!I$170:I$955),0) -> -27717.927 | Y32: =IF(Y4<=HOLD_PERIOD,SUMIF(Leases!$B$170:$B$955,"LC",Leases!J$170:J$955),0) -> 0 | Z32: =IF(Z4<=HOLD_PERIOD,SUMIF(Leases!$B$170:$B$955,"LC",Leases!K$170:K$955),0) -> 0 | ... ET32: =IF(ET4<=HOLD_PERIOD,SUMIF(Leases!$B$170:$B$955,"LC",Leases!EE$170:EE$955),0) -> 0
A33: =SUM(C33:M33) -> -457082.1 | B33: Total TI/LC Expenses | D33: =SUMIFS(CF!$R33:$ET33,CF!$R$2:$ET$2,CF!D$2,CF!$R$4:$ET$4,"<="&HOLD_PERIOD) -> -113576.43 | E33: =SUMIFS(CF!$R33:$ET33,CF!$R$2:$ET$2,CF!E$2,CF!$R$4:$ET$4,"<="&HOLD_PERIOD) -> -82964.871 | F33: =SUMIFS(CF!$R33:$ET33,CF!$R$2:$ET$2,CF!F$2,CF!$R$4:$ET$4,"<="&HOLD_PERIOD) -> -82971.826 | G33: =SUMIFS(CF!$R33:$ET33,CF!$R$2:$ET$2,CF!G$2,CF!$R$4:$ET$4,"<="&HOLD_PERIOD) -> -177568.98 | H33: =SUMIFS(CF!$R33:$ET33,CF!$R$2:$ET$2,CF!H$2,CF!$R$4:$ET$4,"<="&HOLD_PERIOD) -> 0 | I33: =SUMIFS(CF!$R33:$ET33,CF!$R$2:$ET$2,CF!I$2,CF!$R$4:$ET$4,"<="&HOLD_PERIOD) -> 0 | J33: =SUMIFS(CF!$R33:$ET33,CF!$R$2:$ET$2,CF!J$2,CF!$R$4:$ET$4,"<="&HOLD_PERIOD) -> 0 | K33: =SUMIFS(CF!$R33:$ET33,CF!$R$2:$ET$2,CF!K$2,CF!$R$4:$ET$4,"<="&HOLD_PERIOD) -> 0 | ... M33: =SUMIFS(CF!$R33:$ET33,CF!$R$2:$ET$2,CF!M$2,CF!$R$4:$ET$4,"<="&HOLD_PERIOD) -> 0 | P33: =SUMIF($R$4:$ET$4,"<="&HOLD_PERIOD,R33:ET33) -> -457082.1 | Q33: Total TI/LC Expenses | S33: =SUM(S31:S32) -> 0 | T33: =SUM(T31:T32) -> 0 | U33: =SUM(U31:U32) -> 0 | V33: =SUM(V31:V32) -> 0 | W33: =SUM(W31:W32) -> 0 | X33: =SUM(X31:X32) -> -113576.43 | Y33: =SUM(Y31:Y32) -> 0 | Z33: =SUM(Z31:Z32) -> 0 | ... ET33: =SUM(ET31:ET32) -> 0
A35: =SUM(C35:M35) -> 1726250.1 | B35: Total Cash Flow Before Debt Service | D35: =SUMIFS(CF!$R35:$ET35,CF!$R$2:$ET$2,CF!D$2,CF!$R$4:$ET$4,"<="&HOLD_PERIOD) -> 269353.64 | E35: =SUMIFS(CF!$R35:$ET35,CF!$R$2:$ET$2,CF!E$2,CF!$R$4:$ET$4,"<="&HOLD_PERIOD) -> 334388.89 | F35: =SUMIFS(CF!$R35:$ET35,CF!$R$2:$ET$2,CF!F$2,CF!$R$4:$ET$4,"<="&HOLD_PERIOD) -> 356633.93 | G35: =SUMIFS(CF!$R35:$ET35,CF!$R$2:$ET$2,CF!G$2,CF!$R$4:$ET$4,"<="&HOLD_PERIOD) -> 249598.33 | H35: =SUMIFS(CF!$R35:$ET35,CF!$R$2:$ET$2,CF!H$2,CF!$R$4:$ET$4,"<="&HOLD_PERIOD) -> 516275.34 | I35: =SUMIFS(CF!$R35:$ET35,CF!$R$2:$ET$2,CF!I$2,CF!$R$4:$ET$4,"<="&HOLD_PERIOD) -> 0 | J35: =SUMIFS(CF!$R35:$ET35,CF!$R$2:$ET$2,CF!J$2,CF!$R$4:$ET$4,"<="&HOLD_PERIOD) -> 0 | K35: =SUMIFS(CF!$R35:$ET35,CF!$R$2:$ET$2,CF!K$2,CF!$R$4:$ET$4,"<="&HOLD_PERIOD) -> 0 | ... M35: =SUMIFS(CF!$R35:$ET35,CF!$R$2:$ET$2,CF!M$2,CF!$R$4:$ET$4,"<="&HOLD_PERIOD) -> 0 | P35: =SUMIF($R$4:$ET$4,"<="&HOLD_PERIOD,R35:ET35) -> 1726250.1 | Q35: Total Cash Flow Before Debt Service | S35: =IF(S4<=HOLD_PERIOD,SUM(S28,S33),0) -> 33373.455 | T35: =IF(T4<=HOLD_PERIOD,SUM(T28,T33),0) -> 33373.455 | U35: =IF(U4<=HOLD_PERIOD,SUM(U28,U33),0) -> 33566.384 | V35: =IF(V4<=HOLD_PERIOD,SUM(V28,V33),0) -> 33962.546 | W35: =IF(W4<=HOLD_PERIOD,SUM(W28,W33),0) -> 25179.622 | X35: =IF(X4<=HOLD_PERIOD,SUM(X28,X33),0) -> -88400.109 | Y35: =IF(Y4<=HOLD_PERIOD,SUM(Y28,Y33),0) -> 26639.321 | Z35: =IF(Z4<=HOLD_PERIOD,SUM(Z28,Z33),0) -> 26639.321 | ... ET35: =IF(ET4<=HOLD_PERIOD,SUM(ET28,ET33),0) -> 0

Sheet Leases
A1: =Summary!G1 -> Levered Return Metrics | B1: =Summary!G2 -> IRR | C1: =Summary!H2 -> 0.14881178 | D1: =Summary!G3 -> Equity Multiple | E1: =Summary!H3 -> 1.926724 | F1: =Summary!G6 -> Unlevered Return Metrics | G1: =Summary!G7 -> IRR | H1: =Summary!H7 -> 0.093561557 | I1: =Summary!G8 -> Equity Multiple | J1: =Summary!H8 -> 1.5042331
A2: Commercial Current Lease / Assumptions
A3: In-Place Tenant Details | H3: Reimbursement Structure | L3: Rent Escalation Schedule | O3: Re-Leasing Assumptions | Y3: Re-Leasing Reimbursement Structure | AC3: Re-Leasing Costs | AJ3: Percentage Rent
A4: Suite Number | B4: SF | C4: Tenant Name | D4: Start Date | E4: End Date | F4: Pro Rata Share | G4: Reimbursements | H4: Expense | I4: Reimburse For MG | J4: Reimburse For BYS | K4: BYS Amount | L4: Start Date | M4: End Date | N4: Amount/SF/Year | O4: Renewal Probability | P4: Lease Term (New) | Q4: Lease Term (Renewal) | R4: Downtime | S4: Free Rent (New) | T4: Free Rent (Renewal) | U4: Market Rent (New) | V4: Market Rent (Renewal) | W4: Market Rent Growth/Year | X4: Reimbursement Structure | Y4: Expense | Z4: Reimburse For MG | AA4: Reimburse For BYS | AB4: BYS Amount | AC4: TI/SF (New) | AD4: TI/SF (Renewal) | AE4: Annual TI Growth | AF4: New LCs (Years 1-5) | AG4: New LCs (Years 6+) | AH4: Renewal LCs (Years 1-5) | AI4: Renewal LCs (Years 6+) | AJ4: Annual Sales | AK4: Health Ratio | AL4: % Rent | AM4: Breakpoint | AN4: Sales Growth/Year
A5: 1 | B5: 2583 | C5: Health PC Reserve | D5: =MIN(L5:L19) -> 45870 | E5: =MAX(M5:M19) -> 47330 | F5: =B5/$C$347 -> 0.19297721 | G5: NNN | H5: Property Taxes | I5: 1 | J5: 1 | K5: 0 | L5: 45870 | M5: =EOMONTH(L5,11) -> 46234 | N5: 31.6725 | O5: 0.7 | P5: 5 | Q5: 5 | R5: 9 | S5: 2 | T5: 2 | U5: 34.27 | V5: 34.27 | W5: 0.03 | X5: NNN | Y5: Property Taxes | Z5: 1 | AA5: 1 | AB5: 0 | AC5: 50 | AD5: 15 | AE5: 0 | AF5: 0.06 | AG5: 0.03 | AH5: 0.04 | AI5: 0.02 | AJ5: 3000000 | AK5: =SUM(D170:O171)/AJ5 -> 0.032378193 | AL5: 0 | AM5: 0.06 | AN5: 0.03
D6: =MIN(L6:L20) -> 46235 | E6: =MAX(M6:M20) -> 47330 | H6: Insurance | I6: 1 | J6: 1 | K6: 0 | L6: =M5+1 -> 46235 | M6: =EOMONTH(L6,11) -> 46599 | N6: 32.622675 | O6: =N5*$B$5 -> 81810.068 | Y6: Insurance | Z6: 1 | AA6: 1 | AB6: 0
D7: =MIN(L7:L21) -> 45901 | E7: =MAX(M7:M21) -> 47330 | H7: CAM | I7: 1 | J7: 1 | K7: 0 | L7: =M6+1 -> 46600 | M7: =EOMONTH(L7,11) -> 46965 | N7: 33.601355 | O7: =N6*$B$5 -> 84264.37 | Y7: CAM | Z7: 1 | AA7: 1 | AB7: 0
H8: Management Fee | I8: 1 | J8: 1 | K8: 0 | L8: =M7+1 -> 46966 | M8: =EOMONTH(L8,11) -> 47330 | N8: 34.609396 | O8: =N7*$B$5 -> 86792.301 | Y8: Management Fee | Z8: 1 | AA8: 1 | AB8: 0
H9: Other | I9: 1 | J9: 1 | K9: 0 | O9: =N8*$B$5 -> 89396.07 | Y9: Other | Z9: 1 | AA9: 1 | AB9: 0
GA20: x
A21: 2 | B21: 3367 | C21: Uptown Veterinary Hospital | D21: =MIN(L21:L35) -> 45901 | E21: =MAX(M21:M35) -> 46265 | F21: =B21/$C$347 -> 0.25155024 | G21: NNN | H21: Property Taxes | I21: 1 | J21: 1 | K21: 0 | L21: 45901 | M21: =EOMONTH(L21,11) -> 46265 | N21: 26.1 | O21: 0.7 | P21: 5 | Q21: 5 | R21: 9 | S21: 2 | T21: 2 | U21: 34.27 | V21: 34.27 | W21: 0.03 | X21: NNN | Y21: Property Taxes | Z21: 1 | AA21: 1 | AB21: 0 | AC21: 50 | AD21: 15 | AE21: 0 | AF21: 0.06 | AG21: 0.03 | AH21: 0.04 | AI21: 0.02 | AJ21: 3000000 | AK21: =SUM(D186:O187)/AJ21 -> 0.011699603 | AL21: 0 | AM21: 0.06 | AN21: 0.03
H22: Insurance | I22: 1 | J22: 1 | K22: 0 | O22: =N21*$B$21 -> 87878.7 | Y22: Insurance | Z22: 1 | AA22: 1 | AB22: 0 | AC22: TI Alocation Start Month | AD22: TI Alocation End Month
H23: CAM | I23: 1 | J23: 1 | K23: 0 | Y23: CAM | Z23: 1 | AA23: 1 | AB23: 0 | AC23: 1 | AD23: 4
H24: Management Fee | I24: 1 | J24: 1 | K24: 0 | Y24: Management Fee | Z24: 1 | AA24: 1 | AB24: 0
H25: Other | I25: 1 | J25: 1 | K25: 0 | Y25: Other | Z25: 1 | AA25: 1 | AB25: 0
GA36: x
A37: 3 | B37: 2437 | C37: Indigo Tea and Coffee Co. Grounds, LLC | D37: =MIN(L37:L51) -> 45849 | E37: =MAX(M37:M51) -> 46721 | F37: =B37/$C$347 -> 0.18206948 | G37: NNN | H37: Property Taxes | I37: 1 | J37: 1 | K37: 0 | L37: 45849 | M37: =EOMONTH(L37,11) -> 46203 | N37: 31.67 | O37: 0.7 | P37: 5 | Q37: 5 | R37: 9 | S37: 2 | T37: 2 | U37: 34.27 | V37: 34.27 | W37: 0.03 | X37: NNN | Y37: Property Taxes | Z37: 1 | AA37: 1 | AB37: 0 | AC37: 50 | AD37: 15 | AE37: 0 | AF37: 0.06 | AG37: 0.03 | AH37: 0.04 | AI37: 0.02 | AJ37: 3000000 | AK37: =SUM(D202:O203)/AJ37 -> 0.030610239 | AL37: 0 | AM37: 0.06 | AN37: 0.03
H38: Insurance | I38: 1 | J38: 1 | K38: 0 | L38: =M37+1 -> 46204 | M38: =EOMONTH(L38,11) -> 46568 | N38: 32.62 | O38: =N37*$B$37 -> 77179.79 | Y38: Insurance | Z38: 1 | AA38: 1 | AB38: 0
H39: CAM | I39: 1 | J39: 1 | K39: 0 | L39: =M38+1 -> 46569 | M39: =EOMONTH(L39,4) -> 46721 | N39: 33.6 | O39: =N38*$B$37 -> 79494.94 | Y39: CAM | Z39: 1 | AA39: 1 | AB39: 0
H40: Management Fee | I40: 1 | J40: 1 | K40: 0 | O40: =N39*$B$37 -> 81883.2 | Y40: Management Fee | Z40: 1 | AA40: 1 | AB40: 0
H41: Other | I41: 1 | J41: 1 | K41: 0 | Y41: Other | Z41: 1 | AA41: 1 | AB41: 0
GA52: x
A53: 4 | B53: 2568 | C53: Raghav Sundaresh | D53: =MIN(L53:L67) -> 45870 | E53: =MAX(M53:M67) -> 47330 | F53: =B53/$C$347 -> 0.19185656 | G53: NNN | H53: Property Taxes | I53: 1 | J53: 1 | K53: 0 | L53: 45870 | M53: =EOMONTH(L53,11) -> 46234 | N53: 29.85 | O53: 0.7 | P53: 5 | Q53: 5 | R53: 9 | S53: 2 | T53: 2 | U53: 34.27 | V53: 34.27 | W53: 0.03 | X53: NNN | Y53: Property Taxes | Z53: 1 | AA53: 1 | AB53: 0 | AC53: 50 | AD53: 15 | AE53: 0 | AF53: 0.06 | AG53: 0.03 | AH53: 0.04 | AI53: 0.02 | AJ53: 3000000 | AK53: =SUM(D218:O219)/AJ53 -> 0.030595005 | AL53: 0 | AM53: 0.05 | AN53: 0.03
H54: Insurance | I54: 1 | J54: 1 | K54: 0 | L54: =M53+1 -> 46235 | M54: =EOMONTH(L54,11) -> 46599 | N54: =N53*(1+0.03) -> 30.7455 | O54: =N53*$B$53 -> 76654.8 | Y54: Insurance | Z54: 1 | AA54: 1 | AB54: 0
H55: CAM | I55: 1 | J55: 1 | K55: 0 | L55: =M54+1 -> 46600 | M55: =EOMONTH(L55,11) -> 46965 | N55: =N54*(1+0.03) -> 31.667865 | O55: =N54*$B$53 -> 78954.444 | Y55: CAM | Z55: 1 | AA55: 1 | AB55: 0
H56: Management Fee | I56: 1 | J56: 1 | K56: 0 | L56: =M55+1 -> 46966 | M56: =EOMONTH(L56,11) -> 47330 | N56: =N55*(1+0.03) -> 32.617901 | O56: =N55*$B$53 -> 81323.077 | Y56: Management Fee | Z56: 1 | AA56: 1 | AB56: 0
H57: Other | I57: 1 | J57: 1 | K57: 0 | O57: =N56*$B$53 -> 83762.77 | Y57: Other | Z57: 1 | AA57: 1 | AB57: 0
GA68: x
A69: 5 | B69: 2430 | C69: Pizzeria Sapienza CLT, LLC | D69: =MIN(L69:L83) -> 45778 | E69: =MAX(M69:M83) -> 46873 | F69: =B69/$C$347 -> 0.18154651 | G69: NNN | H69: Property Taxes | I69: 1 | J69: 1 | K69: 0 | L69: 45778 | M69: =EOMONTH(L69,11) -> 46142 | N69: 30.75 | O69: 0.7 | P69: 5 | Q69: 5 | R69: 9 | S69: 2 | T69: 2 | U69: 34.27 | V69: 34.27 | W69: 0.03 | X69: NNN | Y69: Property Taxes | Z69: 1 | AA69: 1 | AB69: 0 | AC69: 50 | AD69: 15 | AE69: 0 | AF69: 0.06 | AG69: 0.03 | AH69: 0.04 | AI69: 0.02 | AJ69: 3000000 | AK69: =SUM(D234:O235)/AJ69 -> 0.029881064 | AL69: 0 | AM69: 0.06 | AN69: 0.03
H70: Insurance | I70: 1 | J70: 1 | K70: 0 | L70: =M69+1 -> 46143 | M70: =EOMONTH(L70,11) -> 46507 | N70: 31.67 | O70: =N69*$B$69 -> 74722.5 | Y70: Insurance | Z70: 1 | AA70: 1 | AB70: 0
H71: CAM | I71: 1 | J71: 1 | K71: 0 | L71: =M70+1 -> 46508 | M71: =EOMONTH(L71,11) -> 46873 | N71: 32.62 | O71: =N70*$B$69 -> 76958.1 | Y71: CAM | Z71: 1 | AA71: 1 | AB71: 0
H72: Management Fee | I72: 1 | J72: 1 | K72: 0 | O72: =N71*$B$69 -> 79266.6 | Y72: Management Fee | Z72: 1 | AA72: 1 | AB72: 0
H73: Other | I73: 1 | J73: 1 | K73: 0 | Y73: Other | Z73: 1 | AA73: 1 | AB73: 0
GA84: x
D85: =MIN(L85:L99) -> 46142 | E85: =MAX(M85:M99) -> 0 | L85: =CLOSE_DATE -> 46142
GA100: x
D101: =MIN(L101:L115) -> 46142 | E101: =MAX(M101:M115) -> 0 | L101: =CLOSE_DATE -> 46142
GA116: x
D117: =MIN(L117:L131) -> 46142 | E117: =MAX(M117:M131) -> 0 | L117: =CLOSE_DATE -> 46142
GA132: x
D133: =MIN(L133:L147) -> 46142 | E133: =MAX(M133:M147) -> 0 | L133: =CLOSE_DATE -> 46142
H134: Insurance | I134: 1 | J134: 1 | K134: 0 | Y134: Insurance | Z134: 1 | AA134: 1 | AB134: 0 | AD134: =A308 -> 0 | AF134: =A307 -> 0 | AG134: =A309 -> 0
H135: CAM | I135: 1 | J135: 1 | K135: 0 | Y135: CAM | Z135: 1 | AA135: 1 | AB135: 0 | AD135: TI Alocation End Month
H136: Management Fee | I136: 1 | J136: 1 | K136: 0 | Y136: Management Fee | Z136: 1 | AA136: 1 | AB136: 0 | AD136: 4
H137: Other | I137: 1 | J137: 1 | K137: 0 | Y137: Other | Z137: 1 | AA137: 1 | AB137: 0
GA148: x
D149: =MIN(L149:L163) -> 46142 | E149: =MAX(M149:M163) -> 0 | L149: =CLOSE_DATE -> 46142
H150: Insurance | I150: 1 | J150: 1 | K150: 0 | Y150: Insurance | Z150: 1 | AA150: 1 | AB150: 0
H151: CAM | I151: 1 | J151: 1 | K151: 0 | Y151: CAM | Z151: 1 | AA151: 1 | AB151: 0
H152: Management Fee | I152: 1 | J152: 1 | K152: 0 | Y152: Management Fee | Z152: 1 | AA152: 1 | AB152: 0
H153: Other | I153: 1 | J153: 1 | K153: 0 | Y153: Other | Z153: 1 | AA153: 1 | AB153: 0
GA164: x
C165: Year | D165: =ROUNDUP(D166/12,0) -> 1 | E165: =ROUNDUP(E166/12,0) -> 1 | F165: =ROUNDUP(F166/12,0) -> 1 | G165: =ROUNDUP(G166/12,0) -> 1 | H165: =ROUNDUP(H166/12,0) -> 1 | I165: =ROUNDUP(I166/12,0) -> 1 | J165: =ROUNDUP(J166/12,0) -> 1 | K165: =ROUNDUP(K166/12,0) -> 1 | ... NK165: =ROUNDUP(NK166/12,0) -> 31
C166: Month | D166: 1 | E166: =D166+1 -> 2 | F166: =E166+1 -> 3 | G166: =F166+1 -> 4 | H166: =G166+1 -> 5 | I166: =H166+1 -> 6 | J166: =I166+1 -> 7 | K166: =J166+1 -> 8 | L166: =K166+1 -> 9 | ... NK166: =NJ166+1 -> 372
C167: Month Ending | D167: =EOMONTH(Assumptions!I13,1) -> 46173 | E167: =EOMONTH(D167,1) -> 46203 | F167: =EOMONTH(E167,1) -> 46234 | G167: =EOMONTH(F167,1) -> 46265 | H167: =EOMONTH(G167,1) -> 46295 | I167: =EOMONTH(H167,1) -> 46326 | J167: =EOMONTH(I167,1) -> 46356 | K167: =EOMONTH(J167,1) -> 46387 | L167: =EOMONTH(K167,1) -> 46418 | ... NK167: =EOMONTH(NJ167,1) -> 57465
C168: Suite / Tenant
C169: =A5&" / "&C5 -> 1 / Health PC Reserve
A170: =SUM(D170:NK170) -> 280905.26 | B170: BRR | C170: In-Place Base Rent | D170: {=IFERROR(INDEX($N5:$N19,MATCH(1,IF($L5:$L19<=D$167,IF($M5:$M19>=D$167,1)),0))*$B5/12,0)} -> 6817.5056 | E170: {=IFERROR(INDEX($N5:$N19,MATCH(1,IF($L5:$L19<=E$167,IF($M5:$M19>=E$167,1)),0))*$B5/12,0)} -> 6817.5056 | F170: {=IFERROR(INDEX($N5:$N19,MATCH(1,IF($L5:$L19<=F$167,IF($M5:$M19>=F$167,1)),0))*$B5/12,0)} -> 6817.5056 | G170: {=IFERROR(INDEX($N5:$N19,MATCH(1,IF($L5:$L19<=G$167,IF($M5:$M19>=G$167,1)),0))*$B5/12,0)} -> 7022.0308 | H170: {=IFERROR(INDEX($N5:$N19,MATCH(1,IF($L5:$L19<=H$167,IF($M5:$M19>=H$167,1)),0))*$B5/12,0)} -> 7022.0308 | I170: {=IFERROR(INDEX($N5:$N19,MATCH(1,IF($L5:$L19<=I$167,IF($M5:$M19>=I$167,1)),0))*$B5/12,0)} -> 7022.0308 | J170: {=IFERROR(INDEX($N5:$N19,MATCH(1,IF($L5:$L19<=J$167,IF($M5:$M19>=J$167,1)),0))*$B5/12,0)} -> 7022.0308 | K170: {=IFERROR(INDEX($N5:$N19,MATCH(1,IF($L5:$L19<=K$167,IF($M5:$M19>=K$167,1)),0))*$B5/12,0)} -> 7022.0308 | ... NK170: {=IFERROR(INDEX($N5:$N19,MATCH(1,IF($L5:$L19<=NK$167,IF($M5:$M19>=NK$167,1)),0))*$B5/12,0)} -> 0
A171: =SUM(D171:NK171) -> 45193.611 | B171: CAM | C171: In-Place Reimbursements | D171: =IF(AND(D$167<=$E5,D$167>=EOMONTH($D5,0)),IF($G5="NNN",SUM(Expenses!B$14:B$18)*$F5,IF($G5="FSG",0,IF($G5="MG",SUMPRODUCT(Expenses!B$14:B$18,$I5:$I9)*$F5,MAX((Expenses!B$15-$K5/12)*$J5*$F5,0)+MAX((Expenses!B$14-$K6/12)*$J6*$F5,0)+MAX((Expenses!B$17-$K7/12)*$J7*$F5,0)+MAX((Expenses!B$16-$K8/12)*$J8*$F5,0)+MAX((Expenses!B$18-$K9/12)*$J9*$F5,0)))),0) -> 1109.7299 | E171: =IF(AND(E$167<=$E5,E$167>=EOMONTH($D5,0)),IF($G5="NNN",SUM(Expenses!C$14:C$18)*$F5,IF($G5="FSG",0,IF($G5="MG",SUMPRODUCT(Expenses!C$14:C$18,$I5:$I9)*$F5,MAX((Expenses!C$15-$K5/12)*$J5*$F5,0)+MAX((Expenses!C$14-$K6/12)*$J6*$F5,0)+MAX((Expenses!C$17-$K7/12)*$J7*$F5,0)+MAX((Expenses!C$16-$K8/12)*$J8*$F5,0)+MAX((Expenses!C$18-$K9/12)*$J9*$F5,0)))),0) -> 1112.2416 | F171: =IF(AND(F$167<=$E5,F$167>=EOMONTH($D5,0)),IF($G5="NNN",SUM(Expenses!D$14:D$18)*$F5,IF($G5="FSG",0,IF($G5="MG",SUMPRODUCT(Expenses!D$14:D$18,$I5:$I9)*$F5,MAX((Expenses!D$15-$K5/12)*$J5*$F5,0)+MAX((Expenses!D$14-$K6/12)*$J6*$F5,0)+MAX((Expenses!D$17-$K7/12)*$J7*$F5,0)+MAX((Expenses!D$16-$K8/12)*$J8*$F5,0)+MAX((Expenses!D$18-$K9/12)*$J9*$F5,0)))),0) -> 1114.7589 | G171: =IF(AND(G$167<=$E5,G$167>=EOMONTH($D5,0)),IF($G5="NNN",SUM(Expenses!E$14:E$18)*$F5,IF($G5="FSG",0,IF($G5="MG",SUMPRODUCT(Expenses!E$14:E$18,$I5:$I9)*$F5,MAX((Expenses!E$15-$K5/12)*$J5*$F5,0)+MAX((Expenses!E$14-$K6/12)*$J6*$F5,0)+MAX((Expenses!E$17-$K7/12)*$J7*$F5,0)+MAX((Expenses!E$16-$K8/12)*$J8*$F5,0)+MAX((Expenses!E$18-$K9/12)*$J9*$F5,0)))),0) -> 1117.2819 | H171: =IF(AND(H$167<=$E5,H$167>=EOMONTH($D5,0)),IF($G5="NNN",SUM(Expenses!F$14:F$18)*$F5,IF($G5="FSG",0,IF($G5="MG",SUMPRODUCT(Expenses!F$14:F$18,$I5:$I9)*$F5,MAX((Expenses!F$15-$K5/12)*$J5*$F5,0)+MAX((Expenses!F$14-$K6/12)*$J6*$F5,0)+MAX((Expenses!F$17-$K7/12)*$J7*$F5,0)+MAX((Expenses!F$16-$K8/12)*$J8*$F5,0)+MAX((Expenses!F$18-$K9/12)*$J9*$F5,0)))),0) -> 1119.8106 | I171: =IF(AND(I$167<=$E5,I$167>=EOMONTH($D5,0)),IF($G5="NNN",SUM(Expenses!G$14:G$18)*$F5,IF($G5="FSG",0,IF($G5="MG",SUMPRODUCT(Expenses!G$14:G$18,$I5:$I9)*$F5,MAX((Expenses!G$15-$K5/12)*$J5*$F5,0)+MAX((Expenses!G$14-$K6/12)*$J6*$F5,0)+MAX((Expenses!G$17-$K7/12)*$J7*$F5,0)+MAX((Expenses!G$16-$K8/12)*$J8*$F5,0)+MAX((Expenses!G$18-$K9/12)*$J9*$F5,0)))),0) -> 1122.3451 | J171: =IF(AND(J$167<=$E5,J$167>=EOMONTH($D5,0)),IF($G5="NNN",SUM(Expenses!H$14:H$18)*$F5,IF($G5="FSG",0,IF($G5="MG",SUMPRODUCT(Expenses!H$14:H$18,$I5:$I9)*$F5,MAX((Expenses!H$15-$K5/12)*$J5*$F5,0)+MAX((Expenses!H$14-$K6/12)*$J6*$F5,0)+MAX((Expenses!H$17-$K7/12)*$J7*$F5,0)+MAX((Expenses!H$16-$K8/12)*$J8*$F5,0)+MAX((Expenses!H$18-$K9/12)*$J9*$F5,0)))),0) -> 1124.8852 | K171: =IF(AND(K$167<=$E5,K$167>=EOMONTH($D5,0)),IF($G5="NNN",SUM(Expenses!I$14:I$18)*$F5,IF($G5="FSG",0,IF($G5="MG",SUMPRODUCT(Expenses!I$14:I$18,$I5:$I9)*$F5,MAX((Expenses!I$15-$K5/12)*$J5*$F5,0)+MAX((Expenses!I$14-$K6/12)*$J6*$F5,0)+MAX((Expenses!I$17-$K7/12)*$J7*$F5,0)+MAX((Expenses!I$16-$K8/12)*$J8*$F5,0)+MAX((Expenses!I$18-$K9/12)*$J9*$F5,0)))),0) -> 1127.4312 | ... NK171: =IF(AND(NK$167<=$E5,NK$167>=EOMONTH($D5,0)),IF($G5="NNN",SUM(Expenses!NI$14:NI$18)*$F5,IF($G5="FSG",0,IF($G5="MG",SUMPRODUCT(Expenses!NI$14:NI$18,$I5:$I9)*$F5,MAX((Expenses!NI$15-$K5/12)*$J5*$F5,0)+MAX((Expenses!NI$14-$K6/12)*$J6*$F5,0)+MAX((Expenses!NI$17-$K7/12)*$J7*$F5,0)+MAX((Expenses!NI$16-$K8/12)*$J8*$F5,0)+MAX((Expenses!NI$18-$K9/12)*$J9*$F5,0)))),0) -> 0
A172: =SUM(D172:NK172) -> 0 | B172: PR | C172: Total Percentage Rent | D172: =IF(OR($AL5=0,D$167>$E5,D$167<EOMONTH($D5,0)),0,IF(((($AJ5*((1+$AN5)^(D$165-1))/12))-(D170/$AM5))*$AM5<0,0,((($AJ5*((1+$AN5)^(D$165-1))/12))-(D170/$AM5))*$AM5)) -> 0 | E172: =IF(OR($AL5=0,E$167>$E5,E$167<EOMONTH($D5,0)),0,IF(((($AJ5*((1+$AN5)^(E$165-1))/12))-(E170/$AM5))*$AM5<0,0,((($AJ5*((1+$AN5)^(E$165-1))/12))-(E170/$AM5))*$AM5)) -> 0 | F172: =IF(OR($AL5=0,F$167>$E5,F$167<EOMONTH($D5,0)),0,IF(((($AJ5*((1+$AN5)^(F$165-1))/12))-(F170/$AM5))*$AM5<0,0,((($AJ5*((1+$AN5)^(F$165-1))/12))-(F170/$AM5))*$AM5)) -> 0 | G172: =IF(OR($AL5=0,G$167>$E5,G$167<EOMONTH($D5,0)),0,IF(((($AJ5*((1+$AN5)^(G$165-1))/12))-(G170/$AM5))*$AM5<0,0,((($AJ5*((1+$AN5)^(G$165-1))/12))-(G170/$AM5))*$AM5)) -> 0 | H172: =IF(OR($AL5=0,H$167>$E5,H$167<EOMONTH($D5,0)),0,IF(((($AJ5*((1+$AN5)^(H$165-1))/12))-(H170/$AM5))*$AM5<0,0,((($AJ5*((1+$AN5)^(H$165-1))/12))-(H170/$AM5))*$AM5)) -> 0 | I172: =IF(OR($AL5=0,I$167>$E5,I$167<EOMONTH($D5,0)),0,IF(((($AJ5*((1+$AN5)^(I$165-1))/12))-(I170/$AM5))*$AM5<0,0,((($AJ5*((1+$AN5)^(I$165-1))/12))-(I170/$AM5))*$AM5)) -> 0 | J172: =IF(OR($AL5=0,J$167>$E5,J$167<EOMONTH($D5,0)),0,IF(((($AJ5*((1+$AN5)^(J$165-1))/12))-(J170/$AM5))*$AM5<0,0,((($AJ5*((1+$AN5)^(J$165-1))/12))-(J170/$AM5))*$AM5)) -> 0 | K172: =IF(OR($AL5=0,K$167>$E5,K$167<EOMONTH($D5,0)),0,IF(((($AJ5*((1+$AN5)^(K$165-1))/12))-(K170/$AM5))*$AM5<0,0,((($AJ5*((1+$AN5)^(K$165-1))/12))-(K170/$AM5))*$AM5)) -> 0 | ... NK172: =IF(OR($AL5=0,NK$167>$E5,NK$167<EOMONTH($D5,0)),0,IF(((($AJ5*((1+$AN5)^(NK$165-1))/12))-(NK170/$AM5))*$AM5<0,0,((($AJ5*((1+$AN5)^(NK$165-1))/12))-(NK170/$AM5))*$AM5)) -> 0
A173: =SUM(D173:NK173) -> 0 | B173: FR | C173: Up-Front Free Rent | D173: =IF(AND(D$167>=EOMONTH($D5,0),D$167<EOMONTH($D5,$S5)),-D170,0) -> 0 | E173: =IF(AND(E$167>=EOMONTH($D5,0),E$167<EOMONTH($D5,$S5)),-E170,0) -> 0 | F173: =IF(AND(F$167>=EOMONTH($D5,0),F$167<EOMONTH($D5,$S5)),-F170,0) -> 0 | G173: =IF(AND(G$167>=EOMONTH($D5,0),G$167<EOMONTH($D5,$S5)),-G170,0) -> 0 | H173: =IF(AND(H$167>=EOMONTH($D5,0),H$167<EOMONTH($D5,$S5)),-H170,0) -> 0 | I173: =IF(AND(I$167>=EOMONTH($D5,0),I$167<EOMONTH($D5,$S5)),-I170,0) -> 0 | J173: =IF(AND(J$167>=EOMONTH($D5,0),J$167<EOMONTH($D5,$S5)),-J170,0) -> 0 | K173: =IF(AND(K$167>=EOMONTH($D5,0),K$167<EOMONTH($D5,$S5)),-K170,0) -> 0 | ... NK173: =IF(AND(NK$167>=EOMONTH($D5,0),NK$167<EOMONTH($D5,$S5)),-NK170,0) -> 0
A174: =SUM(D174:NK174) -> 519958.94 | B174: BRR | C174: Re-Leasing Base Rent | D174: =IF(OR(D$167<=EOMONTH($E5,$R5*(1-$O5)),D$167>EOMONTH($E5,$P5*12*(1-$O5)+$Q5*12*$O5+$R5*(1-$O5))),0,FV($W5,ROUNDDOWN(YEARFRAC($D$167,D$167,1),0),,-($U5*(1-$O5)+$V5*$O5)*$B5/12,0)) -> 0 | E174: =IF(OR(E$167<=EOMONTH($E5,$R5*(1-$O5)),E$167>EOMONTH($E5,$P5*12*(1-$O5)+$Q5*12*$O5+$R5*(1-$O5))),0,FV($W5,ROUNDDOWN(YEARFRAC($D$167,E$167,1),0),,-($U5*(1-$O5)+$V5*$O5)*$B5/12,0)) -> 0 | F174: =IF(OR(F$167<=EOMONTH($E5,$R5*(1-$O5)),F$167>EOMONTH($E5,$P5*12*(1-$O5)+$Q5*12*$O5+$R5*(1-$O5))),0,FV($W5,ROUNDDOWN(YEARFRAC($D$167,F$167,1),0),,-($U5*(1-$O5)+$V5*$O5)*$B5/12,0)) -> 0 | G174: =IF(OR(G$167<=EOMONTH($E5,$R5*(1-$O5)),G$167>EOMONTH($E5,$P5*12*(1-$O5)+$Q5*12*$O5+$R5*(1-$O5))),0,FV($W5,ROUNDDOWN(YEARFRAC($D$167,G$167,1),0),,-($U5*(1-$O5)+$V5*$O5)*$B5/12,0)) -> 0 | H174: =IF(OR(H$167<=EOMONTH($E5,$R5*(1-$O5)),H$167>EOMONTH($E5,$P5*12*(1-$O5)+$Q5*12*$O5+$R5*(1-$O5))),0,FV($W5,ROUNDDOWN(YEARFRAC($D$167,H$167,1),0),,-($U5*(1-$O5)+$V5*$O5)*$B5/12,0)) -> 0 | I174: =IF(OR(I$167<=EOMONTH($E5,$R5*(1-$O5)),I$167>EOMONTH($E5,$P5*12*(1-$O5)+$Q5*12*$O5+$R5*(1-$O5))),0,FV($W5,ROUNDDOWN(YEARFRAC($D$167,I$167,1),0),,-($U5*(1-$O5)+$V5*$O5)*$B5/12,0)) -> 0 | J174: =IF(OR(J$167<=EOMONTH($E5,$R5*(1-$O5)),J$167>EOMONTH($E5,$P5*12*(1-$O5)+$Q5*12*$O5+$R5*(1-$O5))),0,FV($W5,ROUNDDOWN(YEARFRAC($D$167,J$167,1),0),,-($U5*(1-$O5)+$V5*$O5)*$B5/12,0)) -> 0 | K174: =IF(OR(K$167<=EOMONTH($E5,$R5*(1-$O5)),K$167>EOMONTH($E5,$P5*12*(1-$O5)+$Q5*12*$O5+$R5*(1-$O5))),0,FV($W5,ROUNDDOWN(YEARFRAC($D$167,K$167,1),0),,-($U5*(1-$O5)+$V5*$O5)*$B5/12,0)) -> 0 | ... NK174: =IF(OR(NK$167<=EOMONTH($E5,$R5*(1-$O5)),NK$167>EOMONTH($E5,$P5*12*(1-$O5)+$Q5*12*$O5+$R5*(1-$O5))),0,FV($W5,ROUNDDOWN(YEARFRAC($D$167,NK$167,1),0),,-($U5*(1-$O5)+$V5*$O5)*$B5/12,0)) -> 0
A175: =SUM(D175:NK175) -> -16121.258 | B175: FR | C175: Re-Leasing Free Rent | D175: =IF(AND(D$167>EOMONTH($E5,$R5*(1-$O5)),D$167<=EOMONTH($E5,$R5*(1-$O5)+$S5*(1-$O5)+$T5*$O5)),-D174,0) -> 0 | E175: =IF(AND(E$167>EOMONTH($E5,$R5*(1-$O5)),E$167<=EOMONTH($E5,$R5*(1-$O5)+$S5*(1-$O5)+$T5*$O5)),-E174,0) -> 0 | F175: =IF(AND(F$167>EOMONTH($E5,$R5*(1-$O5)),F$167<=EOMONTH($E5,$R5*(1-$O5)+$S5*(1-$O5)+$T5*$O5)),-F174,0) -> 0 | G175: =IF(AND(G$167>EOMONTH($E5,$R5*(1-$O5)),G$167<=EOMONTH($E5,$R5*(1-$O5)+$S5*(1-$O5)+$T5*$O5)),-G174,0) -> 0 | H175: =IF(AND(H$167>EOMONTH($E5,$R5*(1-$O5)),H$167<=EOMONTH($E5,$R5*(1-$O5)+$S5*(1-$O5)+$T5*$O5)),-H174,0) -> 0 | I175: =IF(AND(I$167>EOMONTH($E5,$R5*(1-$O5)),I$167<=EOMONTH($E5,$R5*(1-$O5)+$S5*(1-$O5)+$T5*$O5)),-I174,0) -> 0 | J175: =IF(AND(J$167>EOMONTH($E5,$R5*(1-$O5)),J$167<=EOMONTH($E5,$R5*(1-$O5)+$S5*(1-$O5)+$T5*$O5)),-J174,0) -> 0 | K175: =IF(AND(K$167>EOMONTH($E5,$R5*(1-$O5)),K$167<=EOMONTH($E5,$R5*(1-$O5)+$S5*(1-$O5)+$T5*$O5)),-K174,0) -> 0 | ... NK175: =IF(AND(NK$167>EOMONTH($E5,$R5*(1-$O5)),NK$167<=EOMONTH($E5,$R5*(1-$O5)+$S5*(1-$O5)+$T5*$O5)),-NK174,0) -> 0
A176: =SUM(D176:NK176) -> 78148.313 | B176: CAM | C176: Re-Leasing Reimbursements | D176: =IF(OR(D$167<=EOMONTH($E5,$R5*(1-$O5)),D$167>EOMONTH($E5,$P5*12*(1-$O5)+$Q5*12*$O5+$R5*(1-$O5))),0,IF($X5="NNN",SUM(Expenses!B$14:B$18)*$F5,IF($X5="FSG",0,IF($X5="MG",SUMPRODUCT(Expenses!B$14:B$18,$Z5:$Z9)*$F5,MAX((Expenses!B$15-$AB5/12)*$AA5*$F5,0)+MAX((Expenses!B$14-$AB6/12)*$AA6*$F5,0)+MAX((Expenses!B$17-$AB7/12)*$AA7*$F5,0)+MAX((Expenses!B$16-$AB8/12)*$AA8*$F5,0)+MAX((Expenses!B$18-$AB9/12)*$AA9*$F5,0))))) -> 0 | E176: =IF(OR(E$167<=EOMONTH($E5,$R5*(1-$O5)),E$167>EOMONTH($E5,$P5*12*(1-$O5)+$Q5*12*$O5+$R5*(1-$O5))),0,IF($X5="NNN",SUM(Expenses!C$14:C$18)*$F5,IF($X5="FSG",0,IF($X5="MG",SUMPRODUCT(Expenses!C$14:C$18,$Z5:$Z9)*$F5,MAX((Expenses!C$15-$AB5/12)*$AA5*$F5,0)+MAX((Expenses!C$14-$AB6/12)*$AA6*$F5,0)+MAX((Expenses!C$17-$AB7/12)*$AA7*$F5,0)+MAX((Expenses!C$16-$AB8/12)*$AA8*$F5,0)+MAX((Expenses!C$18-$AB9/12)*$AA9*$F5,0))))) -> 0 | F176: =IF(OR(F$167<=EOMONTH($E5,$R5*(1-$O5)),F$167>EOMONTH($E5,$P5*12*(1-$O5)+$Q5*12*$O5+$R5*(1-$O5))),0,IF($X5="NNN",SUM(Expenses!D$14:D$18)*$F5,IF($X5="FSG",0,IF($X5="MG",SUMPRODUCT(Expenses!D$14:D$18,$Z5:$Z9)*$F5,MAX((Expenses!D$15-$AB5/12)*$AA5*$F5,0)+MAX((Expenses!D$14-$AB6/12)*$AA6*$F5,0)+MAX((Expenses!D$17-$AB7/12)*$AA7*$F5,0)+MAX((Expenses!D$16-$AB8/12)*$AA8*$F5,0)+MAX((Expenses!D$18-$AB9/12)*$AA9*$F5,0))))) -> 0 | G176: =IF(OR(G$167<=EOMONTH($E5,$R5*(1-$O5)),G$167>EOMONTH($E5,$P5*12*(1-$O5)+$Q5*12*$O5+$R5*(1-$O5))),0,IF($X5="NNN",SUM(Expenses!E$14:E$18)*$F5,IF($X5="FSG",0,IF($X5="MG",SUMPRODUCT(Expenses!E$14:E$18,$Z5:$Z9)*$F5,MAX((Expenses!E$15-$AB5/12)*$AA5*$F5,0)+MAX((Expenses!E$14-$AB6/12)*$AA6*$F5,0)+MAX((Expenses!E$17-$AB7/12)*$AA7*$F5,0)+MAX((Expenses!E$16-$AB8/12)*$AA8*$F5,0)+MAX((Expenses!E$18-$AB9/12)*$AA9*$F5,0))))) -> 0 | H176: =IF(OR(H$167<=EOMONTH($E5,$R5*(1-$O5)),H$167>EOMONTH($E5,$P5*12*(1-$O5)+$Q5*12*$O5+$R5*(1-$O5))),0,IF($X5="NNN",SUM(Expenses!F$14:F$18)*$F5,IF($X5="FSG",0,IF($X5="MG",SUMPRODUCT(Expenses!F$14:F$18,$Z5:$Z9)*$F5,MAX((Expenses!F$15-$AB5/12)*$AA5*$F5,0)+MAX((Expenses!F$14-$AB6/12)*$AA6*$F5,0)+MAX((Expenses!F$17-$AB7/12)*$AA7*$F5,0)+MAX((Expenses!F$16-$AB8/12)*$AA8*$F5,0)+MAX((Expenses!F$18-$AB9/12)*$AA9*$F5,0))))) -> 0 | I176: =IF(OR(I$167<=EOMONTH($E5,$R5*(1-$O5)),I$167>EOMONTH($E5,$P5*12*(1-$O5)+$Q5*12*$O5+$R5*(1-$O5))),0,IF($X5="NNN",SUM(Expenses!G$14:G$18)*$F5,IF($X5="FSG",0,IF($X5="MG",SUMPRODUCT(Expenses!G$14:G$18,$Z5:$Z9)*$F5,MAX((Expenses!G$15-$AB5/12)*$AA5*$F5,0)+MAX((Expenses!G$14-$AB6/12)*$AA6*$F5,0)+MAX((Expenses!G$17-$AB7/12)*$AA7*$F5,0)+MAX((Expenses!G$16-$AB8/12)*$AA8*$F5,0)+MAX((Expenses!G$18-$AB9/12)*$AA9*$F5,0))))) -> 0 | J176: =IF(OR(J$167<=EOMONTH($E5,$R5*(1-$O5)),J$167>EOMONTH($E5,$P5*12*(1-$O5)+$Q5*12*$O5+$R5*(1-$O5))),0,IF($X5="NNN",SUM(Expenses!H$14:H$18)*$F5,IF($X5="FSG",0,IF($X5="MG",SUMPRODUCT(Expenses!H$14:H$18,$Z5:$Z9)*$F5,MAX((Expenses!H$15-$AB5/12)*$AA5*$F5,0)+MAX((Expenses!H$14-$AB6/12)*$AA6*$F5,0)+MAX((Expenses!H$17-$AB7/12)*$AA7*$F5,0)+MAX((Expenses!H$16-$AB8/12)*$AA8*$F5,0)+MAX((Expenses!H$18-$AB9/12)*$AA9*$F5,0))))) -> 0 | K176: =IF(OR(K$167<=EOMONTH($E5,$R5*(1-$O5)),K$167>EOMONTH($E5,$P5*12*(1-$O5)+$Q5*12*$O5+$R5*(1-$O5))),0,IF($X5="NNN",SUM(Expenses!I$14:I$18)*$F5,IF($X5="FSG",0,IF($X5="MG",SUMPRODUCT(Expenses!I$14:I$18,$Z5:$Z9)*$F5,MAX((Expenses!I$15-$AB5/12)*$AA5*$F5,0)+MAX((Expenses!I$14-$AB6/12)*$AA6*$F5,0)+MAX((Expenses!I$17-$AB7/12)*$AA7*$F5,0)+MAX((Expenses!I$16-$AB8/12)*$AA8*$F5,0)+MAX((Expenses!I$18-$AB9/12)*$AA9*$F5,0))))) -> 0 | ... NK176: =IF(OR(NK$167<=EOMONTH($E5,$R5*(1-$O5)),NK$167>EOMONTH($E5,$P5*12*(1-$O5)+$Q5*12*$O5+$R5*(1-$O5))),0,IF($X5="NNN",SUM(Expenses!NI$14:NI$18)*$F5,IF($X5="FSG",0,IF($X5="MG",SUMPRODUCT(Expenses!NI$14:NI$18,$Z5:$Z9)*$F5,MAX((Expenses!NI$15-$AB5/12)*$AA5*$F5,0)+MAX((Expenses!NI$14-$AB6/12)*$AA6*$F5,0)+MAX((Expenses!NI$17-$AB7/12)*$AA7*$F5,0)+MAX((Expenses!NI$16-$AB8/12)*$AA8*$F5,0)+MAX((Expenses!NI$18-$AB9/12)*$AA9*$F5,0))))) -> 0
A177: =SUM(D177:NK177) -> 908084.86 | C177: Total Suite Operating Cash Flow | D177: =SUM(D170:D176) -> 7927.2356 | E177: =SUM(E170:E176) -> 7929.7472 | F177: =SUM(F170:F176) -> 7932.2645 | G177: =SUM(G170:G176) -> 8139.3127 | H177: =SUM(H170:H176) -> 8141.8414 | I177: =SUM(I170:I176) -> 8144.3759 | J177: =SUM(J170:J176) -> 8146.916 | K177: =SUM(K170:K176) -> 8149.462 | ... NK177: =SUM(NK170:NK176) -> 0
A178: =SUM(D178:NK178) -> 0 | B178: TI | C178: Up-Front Tenant Improvements | D178: =IF(D$167=EOMONTH($D5,-1),-FV($AE5,ROUNDDOWN(YEARFRAC($D$167,D$167,1),0),,-$AC5*$B5,0),0) -> 0 | E178: =IF(E$167=EOMONTH($D5,-1),-FV($AE5,ROUNDDOWN(YEARFRAC($D$167,E$167,1),0),,-$AC5*$B5,0),0) -> 0 | F178: =IF(F$167=EOMONTH($D5,-1),-FV($AE5,ROUNDDOWN(YEARFRAC($D$167,F$167,1),0),,-$AC5*$B5,0),0) -> 0 | G178: =IF(G$167=EOMONTH($D5,-1),-FV($AE5,ROUNDDOWN(YEARFRAC($D$167,G$167,1),0),,-$AC5*$B5,0),0) -> 0 | H178: =IF(H$167=EOMONTH($D5,-1),-FV($AE5,ROUNDDOWN(YEARFRAC($D$167,H$167,1),0),,-$AC5*$B5,0),0) -> 0 | I178: =IF(I$167=EOMONTH($D5,-1),-FV($AE5,ROUNDDOWN(YEARFRAC($D$167,I$167,1),0),,-$AC5*$B5,0),0) -> 0 | J178: =IF(J$167=EOMONTH($D5,-1),-FV($AE5,ROUNDDOWN(YEARFRAC($D$167,J$167,1),0),,-$AC5*$B5,0),0) -> 0 | K178: =IF(K$167=EOMONTH($D5,-1),-FV($AE5,ROUNDDOWN(YEARFRAC($D$167,K$167,1),0),,-$AC5*$B5,0),0) -> 0 | ... NK178: =IF(NK$167=EOMONTH($D5,-1),-FV($AE5,ROUNDDOWN(YEARFRAC($D$167,NK$167,1),0),,-$AC5*$B5,0),0) -> 0
A179: =SUM(D179:NK179) -> 0 | B179: LC | C179: Up-Front Leasing Commissions | D179: =IF(D$167=EOMONTH($D5,-1),SUMIFS($D170:$NK170,$D$167:$NK$167,">="&EOMONTH($D5,$S5),$D$167:$NK$167,"<"&EOMONTH($D5,60))*-$AF5+SUMIFS($D170:$NK170,$D$167:$NK$167,">="&EOMONTH($D5,60),$D$167:$NK$167,"<"&EOMONTH($D5,300))*-$AG5,0) -> 0 | E179: =IF(E$167=EOMONTH($D5,-1),SUMIFS($D170:$NK170,$D$167:$NK$167,">="&EOMONTH($D5,$S5),$D$167:$NK$167,"<"&EOMONTH($D5,60))*-$AF5+SUMIFS($D170:$NK170,$D$167:$NK$167,">="&EOMONTH($D5,60),$D$167:$NK$167,"<"&EOMONTH($D5,300))*-$AG5,0) -> 0 | F179: =IF(F$167=EOMONTH($D5,-1),SUMIFS($D170:$NK170,$D$167:$NK$167,">="&EOMONTH($D5,$S5),$D$167:$NK$167,"<"&EOMONTH($D5,60))*-$AF5+SUMIFS($D170:$NK170,$D$167:$NK$167,">="&EOMONTH($D5,60),$D$167:$NK$167,"<"&EOMONTH($D5,300))*-$AG5,0) -> 0 | G179: =IF(G$167=EOMONTH($D5,-1),SUMIFS($D170:$NK170,$D$167:$NK$167,">="&EOMONTH($D5,$S5),$D$167:$NK$167,"<"&EOMONTH($D5,60))*-$AF5+SUMIFS($D170:$NK170,$D$167:$NK$167,">="&EOMONTH($D5,60),$D$167:$NK$167,"<"&EOMONTH($D5,300))*-$AG5,0) -> 0 | H179: =IF(H$167=EOMONTH($D5,-1),SUMIFS($D170:$NK170,$D$167:$NK$167,">="&EOMONTH($D5,$S5),$D$167:$NK$167,"<"&EOMONTH($D5,60))*-$AF5+SUMIFS($D170:$NK170,$D$167:$NK$167,">="&EOMONTH($D5,60),$D$167:$NK$167,"<"&EOMONTH($D5,300))*-$AG5,0) -> 0 | I179: =IF(I$167=EOMONTH($D5,-1),SUMIFS($D170:$NK170,$D$167:$NK$167,">="&EOMONTH($D5,$S5),$D$167:$NK$167,"<"&EOMONTH($D5,60))*-$AF5+SUMIFS($D170:$NK170,$D$167:$NK$167,">="&EOMONTH($D5,60),$D$167:$NK$167,"<"&EOMONTH($D5,300))*-$AG5,0) -> 0 | J179: =IF(J$167=EOMONTH($D5,-1),SUMIFS($D170:$NK170,$D$167:$NK$167,">="&EOMONTH($D5,$S5),$D$167:$NK$167,"<"&EOMONTH($D5,60))*-$AF5+SUMIFS($D170:$NK170,$D$167:$NK$167,">="&EOMONTH($D5,60),$D$167:$NK$167,"<"&EOMONTH($D5,300))*-$AG5,0) -> 0 | K179: =IF(K$167=EOMONTH($D5,-1),SUMIFS($D170:$NK170,$D$167:$NK$167,">="&EOMONTH($D5,$S5),$D$167:$NK$167,"<"&EOMONTH($D5,60))*-$AF5+SUMIFS($D170:$NK170,$D$167:$NK$167,">="&EOMONTH($D5,60),$D$167:$NK$167,"<"&EOMONTH($D5,300))*-$AG5,0) -> 0 | ... NK179: =IF(NK$167=EOMONTH($D5,-1),SUMIFS($D170:$NK170,$D$167:$NK$167,">="&EOMONTH($D5,$S5),$D$167:$NK$167,"<"&EOMONTH($D5,60))*-$AF5+SUMIFS($D170:$NK170,$D$167:$NK$167,">="&EOMONTH($D5,60),$D$167:$NK$167,"<"&EOMONTH($D5,300))*-$AG5,0) -> 0
A180: =SUM(D180:NK180) -> -65866.5 | B180: TI | C180: Re-Leasing Tenant Improvements | D180: =IF(D$167=EOMONTH($E5,$R5*(1-$O5)),-FV($AE5,ROUNDDOWN(YEARFRAC($D$167,D$167,1),0),,-($AC5*(1-$O5)+$AD5*$O5)*$B5,0),0) -> 0 | E180: =IF(E$167=EOMONTH($E5,$R5*(1-$O5)),-FV($AE5,ROUNDDOWN(YEARFRAC($D$167,E$167,1),0),,-($AC5*(1-$O5)+$AD5*$O5)*$B5,0),0) -> 0 | F180: =IF(F$167=EOMONTH($E5,$R5*(1-$O5)),-FV($AE5,ROUNDDOWN(YEARFRAC($D$167,F$167,1),0),,-($AC5*(1-$O5)+$AD5*$O5)*$B5,0),0) -> 0 | G180: =IF(G$167=EOMONTH($E5,$R5*(1-$O5)),-FV($AE5,ROUNDDOWN(YEARFRAC($D$167,G$167,1),0),,-($AC5*(1-$O5)+$AD5*$O5)*$B5,0),0) -> 0 | H180: =IF(H$167=EOMONTH($E5,$R5*(1-$O5)),-FV($AE5,ROUNDDOWN(YEARFRAC($D$167,H$167,1),0),,-($AC5*(1-$O5)+$AD5*$O5)*$B5,0),0) -> 0 | I180: =IF(I$167=EOMONTH($E5,$R5*(1-$O5)),-FV($AE5,ROUNDDOWN(YEARFRAC($D$167,I$167,1),0),,-($AC5*(1-$O5)+$AD5*$O5)*$B5,0),0) -> 0 | J180: =IF(J$167=EOMONTH($E5,$R5*(1-$O5)),-FV($AE5,ROUNDDOWN(YEARFRAC($D$167,J$167,1),0),,-($AC5*(1-$O5)+$AD5*$O5)*$B5,0),0) -> 0 | K180: =IF(K$167=EOMONTH($E5,$R5*(1-$O5)),-FV($AE5,ROUNDDOWN(YEARFRAC($D$167,K$167,1),0),,-($AC5*(1-$O5)+$AD5*$O5)*$B5,0),0) -> 0 | ... NK180: =IF(NK$167=EOMONTH($E5,$R5*(1-$O5)),-FV($AE5,ROUNDDOWN(YEARFRAC($D$167,NK$167,1),0),,-($AC5*(1-$O5)+$AD5*$O5)*$B5,0),0) -> 0
