Workbook
Name units: [1]Rents!$C$51
Name Units: Rent!$D$29

Sheet CFS-Main Page
B2: The Grove on Southlake | C2: Address: | D2: 7290 Southlake Parkway Morrow, GA, 30260
B3: Cashflow Statement - Main Page | C3: Units | D3: =Units -> 260
C4: Year Built/Reno | D4: 2001 | F4: Scenario | G4: 2 | M4: Tax rate info. | P4: County Link:
B5: Analysis Start Date | C5: 46173 | G5: =10925000 -> 10925000 | M5: Districts | N5: Jurisdictions | Q5: 2025 Rate
B6: Investment Assumptions/Summary | D6: Per Unit | F6: Pro forma Assumptions | I6: Key Metrics | M6: Clayton County | P6: Link | Q6: 3.8298
B7: Purchase Price | C7: =IF(OR(G4=0,G4=1),J8,K8)*1000000 -> 42700000 | D7: =C7/$D$3 -> 164230.77 | F7: Rent Increase (Y2 Onwards) | H7: 0.03 | I7: =B2 -> The Grove on Southlake | J7: 1 | K7: 2 | L7: Broker's Numbers
B8: NOI After Reserve | C8: =I66 -> 2133450.4 | D8: =C8/$D$3 -> 8205.5784 | F8: Other Income Increase (Y2) | H8: =H7 -> 0.03 | I8: Asking Price | J8: =IF(G4=2,"",L8) | K8: 42.7 | L8: 0
B9: All in Cost | C9: ='Sources & Usage'!C9 -> 43425900 | D9: =C9/$D$3 -> 167022.69 | F9: Expense Increase (Year 2 Onwards) | H9: 0.0275 | I9: Y1 NOI | J9: =IF(G4=2,"",I63) | K9: =IF(G4=1,"",I63) -> 2133450.4 | L9: =H63 -> 0
B10: PP Cap Rate | C10: =C8/C7 -> 0.04996371 | F10: Property Management Fee | H10: 0.0275 | I10: Cap rate | J10: =IF(G4=2,"",J9/(J8*1000000)) | K10: =IF(G4=1,"",K9/(K8*1000000)) -> 0.04996371 | L10: 0
B11: Total Rentable Square Feet | C11: =Rent!I29 -> 270332 | D11: =C11/$D$3 -> 1039.7385 | F11: Asset Management Fee | H11: 0 | I11: Levered COC | J11: =IF(G4=2,"",G76) | K11: =IF(G4=1,"",G76) -> 0.043197118 | L11: -
B12: Cash on Cash Return | C12: =I76 -> 0.038216749 | F12: Cost of Exit (Brokerage) | H12: 0.01 | I12: Levered IRR | J12: =IF(G4=2,"",G78) | K12: =IF(G4=1,"",G78) -> 0.049579896 | L12: -
B13: Exit Year | C13: 5 | F13: Replacement Reserve (Per Unit) | H13: 0 | I13: Y1 Yield on Cost | J13: =IF(G4=2,"",$I$63/(J8*1000000)) | K13: =IF(G4=1,"",$I$63/'Sources & Usage'!$C$23) -> 0.049128525 | L13: -
B14: Exit Cap Rate | C14: 0.06 | F14: Assesment Ratio | G14: 0.4 | H14: =G14*C7 -> 17080000 | I14: Appraisal happens every year and reflects the sale price on the next year of sale in Georgia.
B15: Exit NOI (After Reserve) | C15: =HLOOKUP($C$13+1,$I$46:$S$66,ROWS($I$46:$I$66)) -> 2610262.9 | D15: =C15/$D$3 -> 10039.473 | F15: Y1 Tax Reassessed | G15: =Q16 -> 0.038298 | H15: =G15*H14 -> 654129.84
B16: Exit Price | C16: =HLOOKUP($C$13,$I$46:$S$67,ROWS($I$46:$I$67)) -> 43069339 | D16: =C16/$D$3 -> 165651.3 | F16: Tax growth (Y2 Onwards) | H16: 0.03 | I16: Direct tax in last tax bill was $0. | N16: Millage Rate | Q16: =SUM(Q6:Q15)/100 -> 0.038298
B18: Rental Assumptions | D18: =Rent!D5 -> 46104 | F18: T3 | G18: T12 | H18: Broker Numbers | I18: 1 | J18: =IF(I18<$C$13+1,I18+1,"") -> 2 | K18: =IF(J18<$C$13+1,J18+1,"") -> 3 | L18: =IF(K18<$C$13+1,K18+1,"") -> 4 | M18: =IF(L18<$C$13+1,L18+1,"") -> 5 | N18: =IF(M18<$C$13+1,M18+1,"") -> 6 | O18: =IF(N18<$C$13+1,N18+1,"") | P18: =IF(O18<$C$13+1,O18+1,"") | Q18: =IF(P18<$C$13+1,P18+1,"") | ... AC18: =IF(AB18<$C$13+1,AB18+1,"")
B19: Loss to Lease | D19: =Rent!H32/Rent!H30 -> 0.019496639 | F19: =-F34/F33 -> 0.022239821 | G19: =-G34/G33 -> 0.013078285 | H19: =-H34/H33 -> #DIV/0! | I19: =-I34/I33 -> 0.019496639 | J19: 0.01 | K19: 0.01 | L19: 0.01 | M19: 0.01 | N19: =M19 -> 0.01 | O19: =N19 -> 0.01 | P19: =O19 -> 0.01 | Q19: =P19 -> 0.01 | R19: =Q19 -> 0.01 | S19: =R19 -> 0.01 | T19: =S19 -> 0.01 | U19: =T19 -> 0.01 | ... AB19: =AA19 -> 0.01
B20: Vacancy | D20: =1-Rent!H29 -> 0.080769231 | F20: =-F36/$G$35 -> 0.076333088 | G20: =-G36/$G$35 -> 0.065317102 | H20: =-H36/$H$35 -> #DIV/0! | I20: 0.05 | J20: 0.05 | K20: 0.05 | L20: 0.05 | M20: =L20 -> 0.05 | N20: =M20 -> 0.05 | O20: =N20 -> 0.05 | P20: =O20 -> 0.05 | Q20: =P20 -> 0.05 | R20: =Q20 -> 0.05 | S20: =R20 -> 0.05 | T20: =S20 -> 0.05 | ... AB20: =AA20 -> 0.05
B21: Concession/Discount | F21: =-F37/$G$35 -> 0.018401291 | G21: =-G37/$G$35 -> 0.011438724 | H21: =-H37/$H$35 -> #DIV/0! | I21: 0.01 | J21: 0.01 | K21: 0.01 | L21: 0.01 | M21: =L21 -> 0.01 | N21: =M21 -> 0.01 | O21: =N21 -> 0.01 | P21: =O21 -> 0.01 | Q21: =P21 -> 0.01 | R21: =Q21 -> 0.01 | S21: =R21 -> 0.01 | T21: =S21 -> 0.01 | ... AB21: =AA21 -> 0.01
B22: Bad Debt | F22: =-F38/$G$35 -> 0.041047311 | G22: =-G38/$G$35 -> 0.034963814 | H22: =-H38/$H$35 -> #DIV/0! | I22: 0.035 | J22: 0.02 | K22: =J22 -> 0.02 | L22: =K22 -> 0.02 | M22: =L22 -> 0.02 | N22: =M22 -> 0.02 | O22: =N22 -> 0.02 | P22: =O22 -> 0.02 | Q22: =P22 -> 0.02 | R22: =Q22 -> 0.02 | ... AB22: =AA22 -> 0.02
B23: Non Revenue Units | F23: =-F39/$G$35 -> 0.0053015073 | G23: =-G39/$G$35 -> 0.0061691074 | H23: =-H39/$H$35 -> #DIV/0! | I23: =G23 -> 0.0061691074 | J23: =I23 -> 0.0061691074 | K23: =J23 -> 0.0061691074 | L23: =K23 -> 0.0061691074 | M23: =L23 -> 0.0061691074 | N23: =M23 -> 0.0061691074 | O23: =N23 -> 0.0061691074 | P23: =O23 -> 0.0061691074 | Q23: =P23 -> 0.0061691074 | ... AB23: =AA23 -> 0.0061691074
D24: =Rent!H29 -> 0.91923077
B25: Average Rent (GRP) | F25: =F35/Units/12 -> 1407.0696 | G25: =G35/Units/12 -> 1396.9902 | H25: =H35/Units/12 -> 0 | I25: =I35/Units/12 -> 1419.6784 | J25: =IF(J$18="","",J35/Units/12) -> 1476.4315 | K25: =IF(K$18="","",K35/Units/12) -> 1520.7244 | L25: =IF(L$18="","",L35/Units/12) -> 1566.3462 | M25: =IF(M$18="","",M35/Units/12) -> 1613.3365 | N25: =IF(N$18="","",N35/Units/12) -> 1661.7366 | O25: =IF(O$18="","",O35/Units/12) | P25: =IF(P$18="","",P35/Units/12) | Q25: =IF(Q$18="","",Q35/Units/12) | ... AC25: =IF(AC$18="","",AC35/Units/12)
B26: GRP Increases | I26: =IF(I$18="","",I35/G35-1) -> 0.01624073 | J26: =IF(J$18="","",J35/I35-1) -> 0.039976037 | K26: =IF(K$18="","",K35/J35-1) -> 0.03 | L26: =IF(L$18="","",L35/K35-1) -> 0.03 | M26: =IF(M$18="","",M35/L35-1) -> 0.03 | N26: =IF(N$18="","",N35/M35-1) -> 0.03 | O26: =IF(O$18="","",O35/N35-1) | P26: =IF(P$18="","",P35/O35-1) | Q26: =IF(Q$18="","",Q35/P35-1) | ... AC26: =IF(AC$18="","",AC35/AB35-1)
B27: Economic Occupancy | F27: =IF(F$18="","",F40/F35) -> 0.85992744 | G27: =IF(G$18="","",G40/G35) -> 0.88211125 | H27: =IF(H$18="","",H40/H35) -> #DIV/0! | I27: =IF(I$18="","",I40/I35) -> 0.89883089 | J27: =IF(J$18="","",J40/J35) -> 0.91383089 | K27: =IF(K$18="","",K40/K35) -> 0.91383089 | L27: =IF(L$18="","",L40/L35) -> 0.91383089 | M27: =IF(M$18="","",M40/M35) -> 0.91383089 | ... AC27: =IF(AC$18="","",AC40/AC35)
B28: GEI Increases | I28: =IF(I$18="","",I40/G40-1) -> 0.035502676 | J28: =IF(J$18="","",J40/I40-1) -> 0.057331516 | K28: =IF(K$18="","",K40/J40-1) -> 0.03 | L28: =IF(L$18="","",L40/K40-1) -> 0.03 | M28: =IF(M$18="","",M40/L40-1) -> 0.03 | N28: =IF(N$18="","",N40/M40-1) -> 0.03 | O28: =IF(O$18="","",O40/N40-1) | P28: =IF(P$18="","",P40/O40-1) | Q28: =IF(Q$18="","",Q40/P40-1) | ... AC28: =IF(AC$18="","",AC40/AB40-1)
B30: Income | D30: Per Unit (T12) | E30: Per Unit Y1 | F30: =F18 -> T3 | G30: T12 | H30: Broker's Numbers | I30: 1 | J30: =IF(I30<$C$13+1,I30+1,"") -> 2 | K30: =IF(J30<$C$13+1,J30+1,"") -> 3 | L30: =IF(K30<$C$13+1,K30+1,"") -> 4 | M30: =IF(L30<$C$13+1,L30+1,"") -> 5 | N30: =IF(M30<$C$13+1,M30+1,"") -> 6 | O30: =IF(N30<$C$13+1,N30+1,"") | P30: =IF(O30<$C$13+1,O30+1,"") | Q30: =IF(P30<$C$13+1,P30+1,"") | ... AC30: =IF(AB30<$C$13+1,AB30+1,"")
B31: Market Rent Potential | D31: =G31/Units -> 15336.954 | E31: =I31/Units -> 17374.892 | F31: ='Historical Analysis'!X9 -> 4061152 | G31: ='Historical Analysis'!W9 -> 3987608 | H31: 0 | I31: {=(SUMPRODUCT(Rent!$K$9:$K$28*(Rent!$L$9:$L$28=Rent!$K$8),Rent!$D$9:$D$28)+SUMPRODUCT(Rent!$J$9:$J$28*(Rent!$L$9:$L$28=Rent!$J$8),Rent!$D$9:$D$28))*12} -> 4517472 | J31: =IF(J$30>$C$13+1,"",I$31*(1+$H$7)) -> 4652996.2 | K31: =IF(K$30>$C$13+1,"",J$31*(1+$H$7)) -> 4792586 | L31: =IF(L$30>$C$13+1,"",K$31*(1+$H$7)) -> 4936363.6 | M31: =IF(M$30>$C$13+1,"",L$31*(1+$H$7)) -> 5084454.5 | N31: =IF(N$30>$C$13+1,"",M$31*(1+$H$7)) -> 5236988.2 | O31: =IF(O$30>$C$13+1,"",N$31*(1+$H$7)) | P31: =IF(P$30>$C$13+1,"",O$31*(1+$H$7)) | Q31: =IF(Q$30>$C$13+1,"",P$31*(1+$H$7)) | ... AC31: =IF(AC$30>$C$13+1,"",AB$31*(1+$H$7))
B32: Renovation Premium | D32: =G32/Units -> 1649.0769 | E32: =I32/Units -> 0 | F32: ='Historical Analysis'!X10 -> 428760 | G32: ='Historical Analysis'!W10 -> 428760 | H32: 0 | I32: =Rent!I57*12/3 -> 0 | J32: =IF(J30<=$C$13+1,(Rent!I57*12/3)+I32*(1+$H$7),"") -> 0 | K32: =IF(K30<=$C$13+1,(Rent!I57*12/3)+J32*(1+$H$7),"") -> 0 | L32: =IF(L30<=$C$13+1,K32*(1+$H$7),"") -> 0 | M32: =IF(M30<=$C$13+1,L32*(1+$H$7),"") -> 0 | N32: =IF(N30<=$C$13+1,M32*(1+$H$7),"") -> 0 | O32: =IF(O30<=$C$13+1,N32*(1+$H$7),"") | P32: =IF(P30<=$C$13+1,O32*(1+$H$7),"") | Q32: =IF(Q30<=$C$13+1,P32*(1+$H$7),"") | R32: =IF(R30<=$C$13+1,Q32*(1+$H$7),"") | S32: =IF(S30<=$C$13+1,R32*(1+$H$7),"") | ... AC32: =IF(AC30<=$C$13+1,AB32*(1+$H$7),"")
B33: Total Market Rent Potential | D33: =G33/Units -> 16986.031 | E33: =I33/Units -> 17374.892 | F33: =F31+F32 -> 4489912 | G33: =G31+G32 -> 4416368 | H33: =SUM(H31:H32) -> 0 | I33: =IF(I$30<=$C$13+1,I31+I32,"") -> 4517472 | J33: =IF(J$30<=$C$13+1,J31+J32,"") -> 4652996.2 | K33: =IF(K$30<=$C$13+1,K31+K32,"") -> 4792586 | L33: =IF(L$30<=$C$13+1,L31+L32,"") -> 4936363.6 | M33: =IF(M$30<=$C$13+1,M31+M32,"") -> 5084454.5 | N33: =IF(N$30<=$C$13+1,N31+N32,"") -> 5236988.2 | O33: =IF(O$30<=$C$13+1,O31+O32,"") | P33: =IF(P$30<=$C$13+1,P31+P32,"") | ... AC33: =IF(AC$30<=$C$13+1,AC31+AC32,"")
B34: Loss to Lease | D34: =G34/Units -> -222.14815 | E34: =I34/Units -> -338.752 | F34: ='Historical Analysis'!X12 -> -99854.84 | G34: ='Historical Analysis'!W12 -> -57758.52 | H34: 0 | I34: =IF(I$30<=$C$13+1,I35-I33,"") -> -88075.519 | J34: =IF(J$30<=$C$13+1,-J19*J33,"") -> -46529.962 | K34: =IF(K$30<=$C$13+1,-K19*K33,"") -> -47925.86 | L34: =IF(L$30<=$C$13+1,-L19*L33,"") -> -49363.636 | M34: =IF(M$30<=$C$13+1,-M19*M33,"") -> -50844.545 | N34: =IF(N$30<=$C$13+1,-N19*N33,"") -> -52369.882 | O34: =IF(O$30<=$C$13+1,-O19*O33,"") | P34: =IF(P$30<=$C$13+1,-P19*P33,"") | Q34: =IF(Q$30<=$C$13+1,-Q19*Q33,"") | ... AC34: =IF(AC$30<=$C$13+1,-AC19*AC33,"")
B35: Scheduled Rental Income | D35: =G35/Units -> 16763.883 | E35: =I35/Units -> 17036.14 | F35: =F33+F34 -> 4390057.2 | G35: =G33+G34 -> 4358609.5 | H35: =SUM(H33:H34) -> 0 | I35: =IF(I$30<=$C$13+1,Rent!N29*12,"") -> 4429396.5 | J35: =IF(J$30<=$C$13+1,J33+J34,"") -> 4606466.2 | K35: =IF(K$30<=$C$13+1,K33+K34,"") -> 4744660.2 | L35: =IF(L$30<=$C$13+1,L33+L34,"") -> 4887000 | M35: =IF(M$30<=$C$13+1,M33+M34,"") -> 5033610 | N35: =IF(N$30<=$C$13+1,N33+N34,"") -> 5184618.3 | O35: =IF(O$30<=$C$13+1,O33+O34,"") | P35: =IF(P$30<=$C$13+1,P33+P34,"") | Q35: =IF(Q$30<=$C$13+1,Q33+Q34,"") | ... AC35: =IF(AC$30<=$C$13+1,AC33+AC34,"")
B36: Vacancy | D36: =G36/Units -> -1094.9682 | E36: =I36/Units -> -851.80702 | F36: ='Historical Analysis'!X14 -> -332706.12 | G36: ='Historical Analysis'!W14 -> -284691.74 | H36: 0 | I36: =IF(I$30<=$C$13+1,-I$35*I20,"") -> -221469.82 | J36: =IF(J$30<=$C$13+1,-J$35*J20,"") -> -230323.31 | K36: =IF(K$30<=$C$13+1,-K$35*K20,"") -> -237233.01 | L36: =IF(L$30<=$C$13+1,-L$35*L20,"") -> -244350 | M36: =IF(M$30<=$C$13+1,-M$35*M20,"") -> -251680.5 | N36: =IF(N$30<=$C$13+1,-N$35*N20,"") -> -259230.91 | O36: =IF(O$30<=$C$13+1,-O$35*O20,"") | P36: =IF(P$30<=$C$13+1,-P$35*P20,"") | ... AC36: =IF(AC$30<=$C$13+1,-AC$35*AC20,"")
B37: Concession/Discount | D37: =G37/Units -> -191.75742 | E37: =I37/Units -> -170.3614 | F37: ='Historical Analysis'!X15 -> -80204.04 | G37: ='Historical Analysis'!W15 -> -49856.93 | H37: 0 | I37: =IF(I$30<=$C$13+1,-I$35*I21,"") -> -44293.965 | J37: =IF(J$30<=$C$13+1,-J$35*J21,"") -> -46064.662 | K37: =IF(K$30<=$C$13+1,-K$35*K21,"") -> -47446.602 | L37: =IF(L$30<=$C$13+1,-L$35*L21,"") -> -48870 | M37: =IF(M$30<=$C$13+1,-M$35*M21,"") -> -50336.1 | N37: =IF(N$30<=$C$13+1,-N$35*N21,"") -> -51846.183 | O37: =IF(O$30<=$C$13+1,-O$35*O21,"") | P37: =IF(P$30<=$C$13+1,-P$35*P21,"") | ... AC37: =IF(AC$30<=$C$13+1,-AC$35*AC21,"")
B38: Bad Debt | D38: =G38/Units -> -586.12927 | E38: =I38/Units -> -596.26491 | F38: ='Historical Analysis'!X16 -> -178909.2 | G38: ='Historical Analysis'!W16 -> -152393.61 | H38: 0 | I38: =IF(I$30<=$C$13+1,-I$35*I22,"") -> -155028.88 | J38: =IF(J$30<=$C$13+1,-J$35*J22,"") -> -92129.324 | K38: =IF(K$30<=$C$13+1,-K$35*K22,"") -> -94893.204 | L38: =IF(L$30<=$C$13+1,-L$35*L22,"") -> -97740 | M38: =IF(M$30<=$C$13+1,-M$35*M22,"") -> -100672.2 | N38: =IF(N$30<=$C$13+1,-N$35*N22,"") -> -103692.37 | O38: =IF(O$30<=$C$13+1,-O$35*O22,"") | P38: =IF(P$30<=$C$13+1,-P$35*P22,"") | ... AC38: =IF(AC$30<=$C$13+1,-AC$35*AC22,"")
B39: Non Revenue Units | D39: =G39/Units -> -103.41819 | E39: =I39/Units -> -105.09778 | F39: ='Historical Analysis'!X17 -> -23107.2 | G39: ='Historical Analysis'!W17 -> -26888.73 | H39: 0 | I39: =IF(I$30<=$C$13+1,-I$35*I23,"") -> -27325.423 | J39: =IF(J$30<=$C$13+1,-J$35*J23,"") -> -28417.785 | K39: =IF(K$30<=$C$13+1,-K$35*K23,"") -> -29270.318 | L39: =IF(L$30<=$C$13+1,-L$35*L23,"") -> -30148.428 | M39: =IF(M$30<=$C$13+1,-M$35*M23,"") -> -31052.881 | N39: =IF(N$30<=$C$13+1,-N$35*N23,"") -> -31984.467 | O39: =IF(O$30<=$C$13+1,-O$35*O23,"") | P39: =IF(P$30<=$C$13+1,-P$35*P23,"") | ... Z39: =IF(Z$30<=$C$13+1,-Z$35*Z23,"") | AA39: =IF(AA$30<=$C$13+1,Z39*(1+$H$7),"") | AB39: =IF(AB$30<=$C$13+1,AA39*(1+$H$7),"") | AC39: =IF(AC$30<=$C$13+1,AB39*(1+$H$7),"")
B40: Gross Effective Income | D40: =G40/Units -> 14787.61 | E40: =I40/Units -> 15312.609 | F40: =F35+SUM(F36:F39) -> 3775130.6 | G40: =G35+SUM(G36:G39) -> 3844778.5 | H40: =SUM(H35:H39) -> 0 | I40: =IF(I$30<=$C$13+1,SUM(I35:I39),"") -> 3981278.4 | J40: =IF(J$30<=$C$13+1,SUM(J35:J39),"") -> 4209531.1 | K40: =IF(K$30<=$C$13+1,SUM(K35:K39),"") -> 4335817.1 | L40: =IF(L$30<=$C$13+1,SUM(L35:L39),"") -> 4465891.6 | M40: =IF(M$30<=$C$13+1,SUM(M35:M39),"") -> 4599868.3 | N40: =IF(N$30<=$C$13+1,SUM(N35:N39),"") -> 4737864.4 | O40: =IF(O$30<=$C$13+1,SUM(O35:O39),"") | P40: =IF(P$30<=$C$13+1,SUM(P35:P39),"") | ... AC40: =IF(AC$30<=$C$13+1,SUM(AC35:AC39),"")
B41: Utility Reimbursements | D41: =G41/Units -> 661.22465 | E41: 660 | F41: ='Historical Analysis'!X19 -> 178771.76 | G41: ='Historical Analysis'!W19 -> 171918.41 | H41: 0 | I41: =IF(I$46="","",E41*Units) -> 171600 | J41: =IF(J$46="","",I41*(1+$H$9)) -> 176319 | K41: =IF(K$46="","",J41*(1+$H$9)) -> 181167.77 | L41: =IF(L$46="","",K41*(1+$H$9)) -> 186149.89 | M41: =IF(M$46="","",L41*(1+$H$9)) -> 191269.01 | N41: =IF(N$46="","",M41*(1+$H$9)) -> 196528.91 | O41: =IF(O$46="","",N41*(1+$H$9)) | P41: =IF(P$46="","",O41*(1+$H$9)) | Q41: =IF(Q$46="","",P41*(1+$H$9)) | ... AC41: =IF(AC$46="","",AB41*(1+$H$9))
B42: Other Reimbursements | D42: =G42/Units -> 386.01715 | E42: 390 | F42: ='Historical Analysis'!X20 -> 106408.96 | G42: ='Historical Analysis'!W20 -> 100364.46 | H42: 0 | I42: =IF(I$46="","",E42*Units) -> 101400 | J42: =IF(J$30="","",(I42*(1+$H$9))) -> 104188.5 | K42: =IF(K$46="","",J42*(1+$H$9)) -> 107053.68 | L42: =IF(L$46="","",K42*(1+$H$9)) -> 109997.66 | M42: =IF(M$46="","",L42*(1+$H$9)) -> 113022.6 | N42: =IF(N$46="","",M42*(1+$H$9)) -> 116130.72 | O42: =IF(O$46="","",N42*(1+$H$9)) | P42: =IF(P$46="","",O42*(1+$H$9)) | Q42: =IF(Q$46="","",P42*(1+$H$9)) | R42: =IF(R$46="","",Q42*(1+$H$9)) | ... AC42: =IF(AC$46="","",AB42*(1+$H$9))
B43: Other Income | D43: =G43/Units -> 765.68281 | E43: 770 | F43: ='Historical Analysis'!X21 -> 240180.48 | G43: ='Historical Analysis'!W21 -> 199077.53 | H43: 0 | I43: =IF(I$46="","",E43*Units) -> 200200 | J43: =IF(J$46="","",I43*(1+$H$8)) -> 206206 | K43: =IF(K$46="","",J43*(1+$H$8)) -> 212392.18 | L43: =IF(L$46="","",K43*(1+$H$8)) -> 218763.95 | M43: =IF(M$46="","",L43*(1+$H$8)) -> 225326.86 | N43: =IF(N$46="","",M43*(1+$H$8)) -> 232086.67 | O43: =IF(O$46="","",N43*(1+$H$8)) | P43: =IF(P$46="","",O43*(1+$H$8)) | Q43: =IF(Q$46="","",P43*(1+$H$8)) | ... AC43: =IF(AC$46="","",AB43*(1+$H$8))
B44: Total Operating Revenue | D44: =G44/Units -> 16600.534 | E44: =J44/Units -> 18062.479 | F44: =SUM(F40:F43) -> 4300491.8 | G44: =SUM(G40:G43) -> 4316138.9 | H44: =SUM(H40:H43) -> 0 | I44: =IF(I$30="","",SUM(I40:I43)) -> 4454478.4 | J44: =IF(J$30="","",SUM(J40:J43)) -> 4696244.6 | K44: =IF(K$30="","",SUM(K40:K43)) -> 4836430.7 | L44: =IF(L$30="","",SUM(L40:L43)) -> 4980803.1 | M44: =IF(M$30="","",SUM(M40:M43)) -> 5129486.8 | N44: =IF(N$30="","",SUM(N40:N43)) -> 5282610.7 | O44: =IF(O$30="","",SUM(O40:O43)) | P44: =IF(P$30="","",SUM(P40:P43)) | ... AC44: =IF(AC$30="","",SUM(AC40:AC43))
R45: =IF(R30<=$C$13+1,R44-Q44,"") | S45: =IF(S30<=$C$13+1,S44-R44,"") | T45: =IF(T30<=$C$13+1,T44-S44,"") | U45: =IF(U30<=$C$13+1,U44-T44,"") | V45: =IF(V30<=$C$13+1,V44-U44,"") | W45: =IF(W30<=$C$13+1,W44-V44,"") | X45: =IF(X30<=$C$13+1,X44-W44,"") | Y45: =IF(Y30<=$C$13+1,Y44-X44,"") | ... AC45: =IF(AC30<=$C$13+1,AC44-AB44,"")
B46: Operating Expenses | D46: Per Unit (T12) | E46: Per Unit Y1 | F46: =F30 -> T3 | G46: T12 | H46: Broker's Numbers | I46: 1 | J46: =IF(I46<$C$13+1,I46+1,"") -> 2 | K46: =IF(J46<$C$13+1,J46+1,"") -> 3 | L46: =IF(K46<$C$13+1,K46+1,"") -> 4 | M46: =IF(L46<$C$13+1,L46+1,"") -> 5 | N46: =IF(M46<$C$13+1,M46+1,"") -> 6 | O46: =IF(N46<$C$13+1,N46+1,"") | P46: =IF(O46<$C$13+1,O46+1,"") | Q46: =IF(P46<$C$13+1,P46+1,"") | ... AC46: =IF(AB46<$C$13+1,AB46+1,"")
B47: Repair & Maintenance | D47: =G47/Units -> 408.53188 | E47: 410 | F47: ='Historical Analysis'!X25 -> 121923.72 | G47: ='Historical Analysis'!W25 -> 106218.29 | H47: 0 | I47: =IF(I$46="","",E47*Units) -> 106600 | J47: =IF(J$46="","",I47*(1+$H$9)) -> 109531.5 | K47: =IF(K$46="","",J47*(1+$H$9)) -> 112543.62 | L47: =IF(L$46="","",K47*(1+$H$9)) -> 115638.57 | M47: =IF(M$46="","",L47*(1+$H$9)) -> 118818.63 | N47: =IF(N$46="","",M47*(1+$H$9)) -> 122086.14 | O47: =IF(O$46="","",N47*(1+$H$9)) | P47: =IF(P$46="","",O47*(1+$H$9)) | Q47: =IF(Q$46="","",P47*(1+$H$9)) | ... AC47: =IF(AC$46="","",AB47*(1+$H$9))
B48: Cleaning & Decorating | D48: =G48/Units -> 261.84112 | E48: 260 | F48: ='Historical Analysis'!X26 -> 47325.28 | G48: ='Historical Analysis'!W26 -> 68078.69 | H48: 0 | I48: =IF(I$46="","",E48*Units) -> 67600 | J48: =IF(J$46="","",I48*(1+$H$9)) -> 69459 | K48: =IF(K$46="","",J48*(1+$H$9)) -> 71369.123 | L48: =IF(L$46="","",K48*(1+$H$9)) -> 73331.773 | M48: =IF(M$46="","",L48*(1+$H$9)) -> 75348.397 | N48: =IF(N$46="","",M48*(1+$H$9)) -> 77420.478 | O48: =IF(O$46="","",N48*(1+$H$9)) | P48: =IF(P$46="","",O48*(1+$H$9)) | Q48: =IF(Q$46="","",P48*(1+$H$9)) | ... AC48: =IF(AC$46="","",AB48*(1+$H$9))
B49: Contract & Services | D49: =G49/Units -> 1249.0985 | E49: 1355 | F49: ='Historical Analysis'!X27 -> 344526.68 | G49: ='Historical Analysis'!W27 -> 324765.62 | H49: 0 | I49: =IF(I$46="","",E49*Units) -> 352300 | J49: =IF(J$46="","",I49*(1+$H$9)) -> 361988.25 | K49: =IF(K$46="","",J49*(1+$H$9)) -> 371942.93 | L49: =IF(L$46="","",K49*(1+$H$9)) -> 382171.36 | M49: =IF(M$46="","",L49*(1+$H$9)) -> 392681.07 | N49: =IF(N$46="","",M49*(1+$H$9)) -> 403479.8 | O49: =IF(O$46="","",N49*(1+$H$9)) | P49: =IF(P$46="","",O49*(1+$H$9)) | Q49: =IF(Q$46="","",P49*(1+$H$9)) | ... AC49: =IF(AC$46="","",AB49*(1+$H$9))
B50: Utility | D50: =G50/Units -> 213.12438 | E50: 215 | F50: ='Historical Analysis'!X28 -> 64601.52 | G50: ='Historical Analysis'!W28 -> 55412.34 | H50: 0 | I50: =IF(I$46="","",E50*Units) -> 55900 | J50: =IF(J$46="","",I50*(1+$H$9)) -> 57437.25 | K50: =IF(K$46="","",J50*(1+$H$9)) -> 59016.774 | L50: =IF(L$46="","",K50*(1+$H$9)) -> 60639.736 | M50: =IF(M$46="","",L50*(1+$H$9)) -> 62307.328 | N50: =IF(N$46="","",M50*(1+$H$9)) -> 64020.78 | O50: =IF(O$46="","",N50*(1+$H$9)) | P50: =IF(P$46="","",O50*(1+$H$9)) | Q50: =IF(Q$46="","",P50*(1+$H$9)) | ... AC50: =IF(AC$46="","",AB50*(1+$H$9))
B51: Utility- Water/Sewage | D51: =G51/Units -> 601.58808 | E51: 600 | F51: ='Historical Analysis'!X29 -> 177613.48 | G51: ='Historical Analysis'!W29 -> 156412.9 | H51: 0 | I51: =IF(I$46="","",E51*Units) -> 156000 | J51: =IF(J$46="","",I51*(1+$H$9)) -> 160290 | K51: =IF(K$46="","",J51*(1+$H$9)) -> 164697.98 | L51: =IF(L$46="","",K51*(1+$H$9)) -> 169227.17 | M51: =IF(M$46="","",L51*(1+$H$9)) -> 173880.92 | N51: =IF(N$46="","",M51*(1+$H$9)) -> 178662.64 | O51: =IF(O$46="","",N51*(1+$H$9)) | P51: =IF(P$46="","",O51*(1+$H$9)) | Q51: =IF(Q$46="","",P51*(1+$H$9)) | ... AC51: =IF(AC$46="","",AB51*(1+$H$9))
B52: Utility- Gas, Telephone & Others | D52: =G52/Units -> 57.708231 | E52: 60 | F52: ='Historical Analysis'!X30 -> 14451.04 | G52: ='Historical Analysis'!W30 -> 15004.14 | H52: 0 | I52: =IF(I$46="","",E52*Units) -> 15600 | J52: =IF(J$46="","",I52*(1+$H$9)) -> 16029 | K52: =IF(K$46="","",J52*(1+$H$9)) -> 16469.798 | L52: =IF(L$46="","",K52*(1+$H$9)) -> 16922.717 | M52: =IF(M$46="","",L52*(1+$H$9)) -> 17388.092 | N52: =IF(N$46="","",M52*(1+$H$9)) -> 17866.264 | O52: =IF(O$46="","",N52*(1+$H$9)) | P52: =IF(P$46="","",O52*(1+$H$9)) | Q52: =IF(Q$46="","",P52*(1+$H$9)) | ... AC52: =IF(AC$46="","",AB52*(1+$H$9))
B53: RE Taxes | D53: =G53/Units -> 1990.0805 | E53: =I53/Units -> 2515.884 | F53: ='Historical Analysis'!X33 -> 515612.56 | G53: ='Historical Analysis'!W33 -> 517420.94 | H53: 0 | I53: =IF(I$46="","",IF($F$15="Y1 Tax T12 Based",$G$53,$H$15)) -> 654129.84 | J53: =IF(J$46="","",I53*(1+$H$16)) -> 673753.74 | K53: =IF(K$46="","",J53*(1+$H$16)) -> 693966.35 | L53: =IF(L$46="","",K53*(1+$H$16)) -> 714785.34 | M53: =IF(M$46="","",L53*(1+$H$16)) -> 736228.9 | N53: =IF(N$46="","",M53*(1+$H$16)) -> 758315.76 | O53: =IF(O$46="","",N53*(1+$H$16)) | P53: =IF(P$46="","",O53*(1+$H$16)) | Q53: =IF(Q$46="","",P53*(1+$H$16)) | ... AC53: =IF(AC$46="","",AB53*(1+$H$16))
B54: Property Mangement fees | D54: =G54/Units -> 415.54704 | E54: =I54/Units -> 471.14675 | F54: ='Historical Analysis'!X35 -> 107512.8 | G54: ='Historical Analysis'!W35 -> 108042.23 | H54: 0 | I54: =IF(I$46="","",I44*$H$10) -> 122498.16 | J54: =IF(J$46="","",J44*$H$10) -> 129146.73 | K54: =IF(K$46="","",K44*$H$10) -> 133001.84 | L54: =IF(L$46="","",L44*$H$10) -> 136972.08 | M54: =IF(M$46="","",M44*$H$10) -> 141060.89 | N54: =IF(N$46="","",N44*$H$10) -> 145271.79 | O54: =IF(O$46="","",O44*$H$10) | P54: =IF(P$46="","",P44*$H$10) | ... AC54: =IF(AC$46="","",AC44*$H$10)
B55: Marketing | D55: =G55/Units -> 382.50381 | E55: 390 | F55: ='Historical Analysis'!X31 -> 110734.28 | G55: ='Historical Analysis'!W31 -> 99450.99 | H55: 0 | I55: =IF(I$46="","",E55*Units) -> 101400 | J55: =IF(J$46="","",I55*(1+$H$9)) -> 104188.5 | K55: =IF(K$46="","",J55*(1+$H$9)) -> 107053.68 | L55: =IF(L$46="","",K55*(1+$H$9)) -> 109997.66 | M55: =IF(M$46="","",L55*(1+$H$9)) -> 113022.6 | N55: =IF(N$46="","",M55*(1+$H$9)) -> 116130.72 | O55: =IF(O$46="","",N55*(1+$H$9)) | P55: =IF(P$46="","",O55*(1+$H$9)) | Q55: =IF(Q$46="","",P55*(1+$H$9)) | ... AC55: =IF(AC$46="","",AB55*(1+$H$9))
B56: Payroll | D56: =G56/Units -> 1739.7502 | E56: 1750 | F56: ='Historical Analysis'!X32 -> 478699.88 | G56: ='Historical Analysis'!W32 -> 452335.06 | H56: 0 | I56: =IF(I$46="","",E56*Units) -> 455000 | J56: =IF(J$46="","",I56*(1+$H$9)) -> 467512.5 | K56: =IF(K$46="","",J56*(1+$H$9)) -> 480369.09 | L56: =IF(L$46="","",K56*(1+$H$9)) -> 493579.24 | M56: =IF(M$46="","",L56*(1+$H$9)) -> 507152.67 | N56: =IF(N$46="","",M56*(1+$H$9)) -> 521099.37 | O56: =IF(O$46="","",N56*(1+$H$9)) | P56: =IF(P$46="","",O56*(1+$H$9)) | Q56: =IF(Q$46="","",P56*(1+$H$9)) | ... AC56: =IF(AC$46="","",AB56*(1+$H$9))
B57: Insurance | D57: =G57/Units -> 1105.2378 | E57: 550 | F57: ='Historical Analysis'!X34 -> 285043.88 | G57: ='Historical Analysis'!W34 -> 287361.82 | H57: 0 | I57: =IF(I$46="","",E57*Units) -> 143000 | J57: =IF(J$46="","",I57*(1+$H$9)) -> 146932.5 | K57: =IF(K$46="","",J57*(1+$H$9)) -> 150973.14 | L57: =IF(L$46="","",K57*(1+$H$9)) -> 155124.91 | M57: =IF(M$46="","",L57*(1+$H$9)) -> 159390.84 | N57: =IF(N$46="","",M57*(1+$H$9)) -> 163774.09 | O57: =IF(O$46="","",N57*(1+$H$9)) | P57: =IF(P$46="","",O57*(1+$H$9)) | Q57: =IF(Q$46="","",P57*(1+$H$9)) | ... AC57: =IF(AC$46="","",AB57*(1+$H$9))
B58: General & Administrative | D58: =G58/Units -> 367.02162 | E58: 350 | F58: ='Historical Analysis'!X36 -> 120435.84 | G58: ='Historical Analysis'!W36 -> 95425.62 | H58: 0 | I58: =IF(I$46="","",E58*Units) -> 91000 | J58: =IF(J$46="","",I58*(1+$H$9)) -> 93502.5 | K58: =IF(K$46="","",J58*(1+$H$9)) -> 96073.819 | L58: =IF(L$46="","",K58*(1+$H$9)) -> 98715.849 | M58: =IF(M$46="","",L58*(1+$H$9)) -> 101430.53 | N58: =IF(N$46="","",M58*(1+$H$9)) -> 104219.87 | O58: =IF(O$46="","",N58*(1+$H$9)) | P58: =IF(P$46="","",O58*(1+$H$9)) | Q58: =IF(Q$46="","",P58*(1+$H$9)) | ... AC58: =IF(AC$46="","",AB58*(1+$H$9))
B59: Other taxes/Permit license | D59: =G59/Units -> 77.000769 | E59: 0 | F59: ='Historical Analysis'!X37 -> 36049.12 | G59: ='Historical Analysis'!W37 -> 20020.2 | H59: 0 | I59: =IF(I$46="","",E59*Units) -> 0 | J59: =IF(J$46="","",I59*(1+$H$9)) -> 0 | K59: =IF(K$46="","",J59*(1+$H$9)) -> 0 | L59: =IF(L$46="","",K59*(1+$H$9)) -> 0 | M59: =IF(M$46="","",L59*(1+$H$9)) -> 0 | N59: =IF(N$46="","",M59*(1+$H$9)) -> 0 | O59: =IF(O$46="","",N59*(1+$H$9)) | P59: =IF(P$46="","",O59*(1+$H$9)) | Q59: =IF(Q$46="","",P59*(1+$H$9)) | ... AC59: =IF(AC$46="","",AB59*(1+$H$9))
B60: Total Operating Expenses | D60: =SUM(D47:D59) -> 8869.034 | E60: =SUM(E47:E59) -> 8927.0308 | F60: =SUM(F47:F59) -> 2424530.1 | G60: =SUM(G47:G59) -> 2305948.8 | H60: =SUM(H47:H59) -> 0 | I60: =SUM(I47:I59) -> 2321028 | J60: =SUM(J47:J59) -> 2389771.5 | K60: =SUM(K47:K59) -> 2457478.1 | ... N60: =SUM(N47:N59) -> 2672347.7 | O60: =IF(O$46="","",SUM(O47:O59)) | P60: =IF(P$46="","",SUM(P47:P59)) | Q60: =IF(Q$46="","",SUM(Q47:Q59)) | R60: =IF(R$46="","",SUM(R47:R59)) | S60: =IF(S$46="","",SUM(S47:S59)) | T60: =IF(T$46="","",SUM(T47:T59)) | U60: =IF(U$46="","",SUM(U47:U59)) | V60: =IF(V$46="","",SUM(V47:V59)) | ... AC60: =IF(AC$46="","",SUM(AC47:AC59))
B61: Expense Ratio | F61: =IF(F$46="","",F60/F44) -> 0.56377972 | G61: =IF(G$46="","",G60/G44) -> 0.53426197 | H61: =IF(H$46="","",H60/H44) -> #DIV/0! | I61: =IF(I$46="","",I60/I44) -> 0.52105495 | J61: =IF(J$46="","",J60/J44) -> 0.50886861 | K61: =IF(K$46="","",K60/K44) -> 0.50811814 | L61: =IF(L$46="","",L60/L44) -> 0.50736927 | M61: =IF(M$46="","",M60/M44) -> 0.506622 | ... AC61: =IF(AC$46="","",AC60/AC44)
B63: Net Operating Income (NOI) before reserve | F63: =F44-F60 -> 1875961.7 | G63: =G44-G60 -> 2010190 | H63: =H44-H60 -> 0 | I63: =IF(I$46="","",I44-I60) -> 2133450.4 | J63: =IF(J$46="","",J44-J60) -> 2306473.2 | K63: =IF(K$46="","",K44-K60) -> 2378952.5 | L63: =IF(L$46="","",L44-L60) -> 2453696.7 | M63: =IF(M$46="","",M44-M60) -> 2530775.9 | N63: =IF(N$46="","",N44-N60) -> 2610262.9 | O63: =IF(O$46="","",O44-O60) | P63: =IF(P$46="","",P44-P60) | ... V63: =IF(V$46="","",V44-V60) | W63: =IF(W$46="","",W44+W60) | X63: =IF(X$46="","",X44+X60) | Y63: =IF(Y$46="","",Y44+Y60) | Z63: =IF(Z$46="","",Z44+Z60) | AA63: =IF(AA$46="","",AA44+AA60) | AB63: =IF(AB$46="","",AB44+AB60) | AC63: =IF(AC$46="","",AC44+AC60)
B64: % Increase in NOI | I64: =IF(I$46="","",I63/G63-1) -> 0.061317769 | J64: =IF(J$46="","",J63/I63-1) -> 0.081099968 | K64: =IF(K$46="","",K63/J63-1) -> 0.031424336 | L64: =IF(L$46="","",L63/K63-1) -> 0.031418917 | M64: =IF(M$46="","",M63/L63-1) -> 0.031413526 | N64: =IF(N$46="","",N63/M63-1) -> 0.031408162 | O64: =IF(O$46="","",O63/N63-1) | P64: =IF(P$46="","",P63/O63-1) | Q64: =IF(Q$46="","",Q63/P63-1) | ... AC64: =IF(AC$46="","",AC63/AB63-1)
B65: Replacement Reserves | D65: =G65/Units -> 0 | E65: =I65/Units -> 0 | F65: ='Historical Analysis'!X41 -> 0 | G65: ='Historical Analysis'!W41 -> 0 | H65: 0 | I65: =IF(I46="","",-$H$13*Units) -> 0 | J65: =IF(J46="","",I65*(1+$H$9)) -> 0 | K65: =IF(K46="","",J65*(1+$H$9)) -> 0 | L65: =IF(L46="","",K65*(1+$H$9)) -> 0 | M65: =IF(M46="","",L65*(1+$H$9)) -> 0 | N65: =IF(N46="","",M65*(1+$H$9)) -> 0 | O65: =IF(O46="","",N65*(1+$H$9)) | P65: =IF(P46="","",O65*(1+$H$9)) | Q65: =IF(Q46="","",-$H$13*Units) | R65: =IF(R46="","",-$H$13*Units) | S65: =IF(S46="","",-$H$13*Units) | T65: =IF(T46="","",-$H$13*Units) | U65: =IF(U46="","",-$H$13*Units) | V65: =IF(V46="","",-$H$13*Units) | W65: =IF(W46="","",-$H$13*Units) | X65: =IF(X46="","",-$H$13*Units) | ... AC65: =IF(AC46="","",-$H$13*Units)
B66: Net Operating Cash Flow | G66: =G63+G65 -> 2010190 | H66: =H63+H65 -> 0 | I66: =IF(I46="","",I63+I65) -> 2133450.4 | J66: =IF(J46="","",J63+J65) -> 2306473.2 | K66: =IF(K46="","",K63+K65) -> 2378952.5 | L66: =IF(L46="","",L63+L65) -> 2453696.7 | M66: =IF(M46="","",M63+M65) -> 2530775.9 | N66: =IF(N46="","",N63+N65) -> 2610262.9 | O66: =IF(O46="","",O63+O65) | P66: =IF(P46="","",P63+P65) | ... AC66: =IF(AC46="","",AC63+AC65)
B67: Sale Proceed | I67: =IF(I46="","",IF(I46=$C$13,(J66/$C$14*(1-$H$12)),0)) -> 0 | J67: =IF(J46="","",IF(J46=$C$13,(K66/$C$14*(1-$H$12)),0)) -> 0 | K67: =IF(K46="","",IF(K46=$C$13,(L66/$C$14*(1-$H$12)),0)) -> 0 | L67: =IF(L46="","",IF(L46=$C$13,(M66/$C$14*(1-$H$12)),0)) -> 0 | M67: =IF(M46="","",IF(M46=$C$13,(N66/$C$14*(1-$H$12)),0)) -> 43069339 | N67: =IF(N46="","",IF(N46=$C$13,(O66/$C$14*(1-$H$12)),0)) -> 0 | O67: =IF(O46="","",IF(O46=$C$13,(P66/$C$14*(1-$H$12)),0)) | P67: =IF(P46="","",IF(P46=$C$13,(Q66/$C$14*(1-$H$12)),0)) | ... AC67: =IF(AC46="","",IF(AC46=$C$13,(AD66/$C$14*(1-$H$12)),0))
B68: Debt Service | I68: =-Loan!E46 -> -1616152.3 | J68: =-Loan!F46 -> -1616152.3 | K68: =-Loan!G46 -> -1616152.3 | L68: =-Loan!H46 -> -2015666.2 | M68: =-Loan!I46 -> -2015666.2 | N68: =-Loan!J46 -> 0 | O68: =-Loan!K46 -> 0 | P68: =-Loan!L46 -> 0 | ... AC68: =-Loan!Y46 -> 0
B69: DSCR | I69: =IF(I46<=$C$13,-(I67+I66)/(I70+I68),"") -> 1.32008 | J69: =IF(J46<=$C$13,-(J67+J66)/(J70+J68),"") -> 1.4271385 | K69: =IF(K46<=$C$13,-(K67+K66)/(K70+K68),"") -> 1.4719854 | L69: =IF(L46<=$C$13,-(L67+L66)/(L70+L68),"") -> 1.217313 | M69: =IF(M46<=$C$13,-(M67+M66)/(M70+M68),"") -> 1.4669474 | N69: =IF(N46<=$C$13,-(N67+N66)/(N70+N68),"") | O69: =IF(O46<=$C$13,-(O67+O66)/(O70+O68),"") | P69: =IF(P46<=$C$13,-(P67+P66)/(P70+P68),"") | ... AC69: =IF(AC46<=$C$13,-(AC67+AC66)/(AC70+AC68),"")
B70: Loan Payoff | I70: =-Loan!E44 -> 0 | J70: =-Loan!F44 -> 0 | K70: =-Loan!G44 -> 0 | L70: =-Loan!H44 -> 0 | M70: =-Loan!I44 -> -29069370 | N70: =-Loan!J44 -> 0 | O70: =-Loan!K44 -> 0 | P70: =-Loan!L44 -> 0 | ... AC70: =-Loan!Y44 -> 0
B71: Asset Management Fee | I71: =-IF(I46="",0,IF(I46>$C$13,0,('Sources & Usage'!$C$8*$H$11))) -> 0 | J71: =-IF(J46="",0,IF(J46>$C$13,0,('Sources & Usage'!$C$8*$H$11))) -> 0 | K71: =-IF(K46="",0,IF(K46>$C$13,0,('Sources & Usage'!$C$8*$H$11))) -> 0 | L71: =-IF(L46="",0,IF(L46>$C$13,0,('Sources & Usage'!$C$8*$H$11))) -> 0 | M71: =-IF(M46="",0,IF(M46>$C$13,0,('Sources & Usage'!$C$8*$H$11))) -> 0 | N71: =-IF(N46="",0,IF(N46>$C$13,0,('Sources & Usage'!$C$8*$H$11))) -> 0 | O71: =-IF(O46="",0,IF(O46>$C$13,0,('Sources & Usage'!$C$8*$H$11))) -> 0 | P71: =-IF(P46="",0,IF(P46>$C$13,0,('Sources & Usage'!$C$8*$H$11))) -> 0 | ... AC71: =-IF(AC46="",0,IF(AC46>$C$13,0,('Sources & Usage'!$C$8*$H$11))) -> 0
B72: Levered Cash Flow | I72: =IF(I46>$C$13,0,I66+I67+I68+I70+I71) -> 517298.1 | J72: =IF(J46>$C$13,0,J66+J67+J68+J70+J71) -> 690320.86 | K72: =IF(K46>$C$13,0,K66+K67+K68+K70+K71) -> 762800.24 | L72: =IF(L46>$C$13,0,L66+L67+L68+L70+L71) -> 438030.46 | M72: =IF(M46>$C$13,0,M66+M67+M68+M70+M71) -> 14515078 | N72: =IF(N46>$C$13,0,N66+N67+N68+N70+N71) -> 0 | O72: =IF(O46>$C$13,0,O66+O67+O68+O70+O71) -> 0 | P72: =IF(P46>$C$13,0,P66+P67+P68+P70+P71) -> 0 | ... AC72: =IF(AC46>$C$13,0,AC66+AC67+AC68+AC70+AC71) -> 0
B74: Return Metrics | G74: Avg return | H74: 0 | I74: =IF(H74<$C$13,H74+1,"") -> 1 | J74: =IF(I74<$C$13,I74+1,"") -> 2 | K74: =IF(J74<$C$13,J74+1,"") -> 3 | L74: =IF(K74<$C$13,K74+1,"") -> 4 | M74: =IF(L74<$C$13,L74+1,"") -> 5 | N74: =IF(M74<$C$13,M74+1,"") | O74: =IF(N74<$C$13,N74+1,"") | P74: =IF(O74<$C$13,O74+1,"") | ... AC74: =IF(AB74<$C$13,AB74+1,"")
B75: Cash on Cash Return (Unlevered) | G75: =AVERAGE(I75:AC75) -> 0.054360871 | I75: =IF(I46>$C$13,"",I66/'Sources & Usage'!$C$23) -> 0.049128525 | J75: =IF(J46>$C$13,"",J66/'Sources & Usage'!$C$23) -> 0.053112846 | K75: =IF(K46>$C$13,"",K66/'Sources & Usage'!$C$23) -> 0.054781882 | L75: =IF(L46>$C$13,"",L66/'Sources & Usage'!$C$23) -> 0.05650307 | M75: =IF(M46>$C$13,"",M66/'Sources & Usage'!$C$23) -> 0.05827803 | N75: =IF(N46>$C$13,"",N66/'Sources & Usage'!$C$23) | O75: =IF(O46>$C$13,"",O66/'Sources & Usage'!$C$23) | P75: =IF(P46>$C$13,"",P66/'Sources & Usage'!$C$23) | ... R75: =IF(R46>$C$13,"",R66/'Sources & Usage'!$C$23)
B76: Cash on Cash Return (levered) | G76: =AVERAGE(I76:AC76) -> 0.043197118 | I76: =IF(I46>$C$13,"",SUM(I66,I68,I71)/'Sources & Usage'!$C$8) -> 0.038216749 | J76: =IF(J46>$C$13,"",SUM(J66,J68,J71)/'Sources & Usage'!$C$8) -> 0.050999258 | K76: =IF(K46>$C$13,"",SUM(K66,K68,K71)/'Sources & Usage'!$C$8) -> 0.056353862 | L76: =IF(L46>$C$13,"",SUM(L66,L68,L71)/'Sources & Usage'!$C$8) -> 0.032360645 | M76: =IF(M46>$C$13,"",SUM(M66,M68,M71)/'Sources & Usage'!$C$8) -> 0.038055077 | N76: =IF(N46>$C$13,"",SUM(N66,N68,N71)/'Sources & Usage'!$C$8) | O76: =IF(O46>$C$13,"",SUM(O66,O68,O71)/'Sources & Usage'!$C$8) | P76: =IF(P46>$C$13,"",SUM(P66,P68,P71)/'Sources & Usage'!$C$8) | ... R76: =IF(R46>$C$13,"",SUM(R66,R68,R71)/'Sources & Usage'!$C$8)
B77: IRR-Unlevered | G77: =IRR(H79:AC79) -> 0.052659271
B78: IRR-levered | G78: =IRR(H80:AC80) -> 0.049579896
B79: Cashflow -Unlevered | H79: =IF(H74="","",-'Sources & Usage'!C9) -> -43425900 | I79: =IF(I74="","",I66+I67+I71) -> 2133450.4 | J79: =IF(J74="","",J66+J67+J71) -> 2306473.2 | K79: =IF(K74="","",K66+K67+K71) -> 2378952.5 | L79: =IF(L74="","",L66+L67+L71) -> 2453696.7 | M79: =IF(M74="","",M66+M67+M71) -> 45600114 | N79: =IF(N74="","",N66+N67+N71) | O79: =IF(O74="","",O66+O67+O71) | P79: =IF(P74="","",P66+P67+P71) | ... AC79: =IF(AC74="","",AC66+AC67+AC71)
B80: Cashflow -levered | H80: =-'Sources & Usage'!C8 -> -13535900 | I80: =I72 -> 517298.1 | J80: =J72 -> 690320.86 | K80: =K72 -> 762800.24 | L80: =L72 -> 438030.46 | M80: =M72 -> 14515078 | N80: =N72 -> 0 | O80: =O72 -> 0 | P80: =P72 -> 0 | ... AC80: =AC72 -> 0
B81: Equity Required | H81: ='Sources & Usage'!C8 -> 13535900
B86: Underwriting Notes & Assumptions
B88: General Modeling Notes
B89: 1. We have used the Rent comps from Hello Data and added the screenshot for the rent comps as well.
B90: 2. We made a change on Rent page to choose from either of Comps or RR market rent in Col L. Also you can compare the rents of Classic vs renovated in the Rows F5 to O6.
B91: 3. We have added a switch for the Taxes in the Pro Forma Assumptions to choose between T12 taxes and taxes on Reassessed value.
B92: 4. Broker numbers are not added as there was no Broker OM available.
B93: Our Assumptions
B94: General Assumptions
B95: 1. General assumptions (including market rent growth, expense growth, tax growth, and property management fees) are consistent with those applied in the prior model.
B96: 2. For financing, we have a 3 year I/O period and all in rate of 5.41% (5 year Treasury Yield of 4.007% + 1.40% spread).
B97: Asking Price and Exit Assumptions
B98: 1. The asking price is not provided on Landlinq or Broker OM. A valuation has been inferred using an assumed cap rate of approximately 5%.
... B109: Question to the team Catalyst

Sheet Rent
B2: ='CFS-Main Page'!B2 -> The Grove on Southlake | D2: ='CFS-Main Page'!C2 -> Address: | E2: ='CFS-Main Page'!D2 -> 7290 Southlake Parkway Morrow, GA, 30260
B3: Rent Roll Analysis | D3: ='CFS-Main Page'!C3 -> Units | E3: ='CFS-Main Page'!D3 -> 260
B4: ='CFS-Main Page'!B4 -> 0 | D4: ='CFS-Main Page'!C4 -> Year Built/Reno | E4: ='CFS-Main Page'!D4 -> 2001
C5: Rent Roll as on | D5: 46104 | E5: Avg Rent | F5: 1x1 | G5: {=-SUMPRODUCT(-($B$9:$B$28=F5),$E$9:$E$28,$J$9:$J$28)/SUMIF($B$9:$B$28,"="&F5,$E$9:$E$28)} -> 1292.2824 | H5: 2x2 | I5: {=-SUMPRODUCT(-($B$9:$B$28=H5),$E$9:$E$28,$J$9:$J$28)/SUMIF($B$9:$B$28,"="&H5,$E$9:$E$28)} -> 1487.558 | J5: 3x3 | K5: {=-SUMPRODUCT(-($B$9:$B$28=J5),$E$9:$E$28,$J$9:$J$28)/SUMIF($B$9:$B$28,"="&J5,$E$9:$E$28)} -> 1643.8853
C6: Rent Schedule
B8: Beds X Baths | C8: Type | D8: Units | E8: Occupied | F8: Vacant/Model | G8: Unit Mix % | H8: Occupancy % | I8: Square Feet | J8: MR - Based on RR | K8: MR - Based on Comps | L8: RR/Comps | M8: Effective Rent | N8: GRP | O8: GRP/unit
B9: 1x1 | C9: E1 | D9: =IF(C9="","",COUNTIF($D$62:$D$997,"="&C9)) -> 29 | E9: =IF(C9="","",COUNTIF($I$62:$I$997,"="&C9)) -> 26 | F9: =IFERROR(D9-E9,0) -> 3 | G9: =IFERROR(D9/$D$29,0) -> 0.11153846 | H9: =IFERROR(E9/D9,0) -> 0.89655172 | I9: =IFERROR(SUMIF($D$62:$D$997,"="&C9,$E$62:$E$997)/D9,0) -> 583 | J9: =IFERROR(SUMIF($D$62:$D$997,"="&C9,$G$62:$G$997)/D9,0) -> 1128.7241 | K9: 1454 | L9: MR - Based on RR | M9: =IFERROR(SUMIF($D$62:$D$997,"="&C9,$H$62:$H$997)/E9,0) -> 1082.9231 | N9: =IFERROR((M9*E9)+(F9*J9),0) -> 31542.172 | O9: =IFERROR(N9/D9,0) -> 1087.6611
B10: 1x1 | C10: E1-L2 | D10: =IF(C10="","",COUNTIF($D$62:$D$997,"="&C10)) -> 1 | E10: =IF(C10="","",COUNTIF($I$62:$I$997,"="&C10)) -> 1 | F10: =IFERROR(D10-E10,0) -> 0 | G10: =IFERROR(D10/$D$29,0) -> 0.0038461538 | H10: =IFERROR(E10/D10,0) -> 1 | I10: =IFERROR(SUMIF($D$62:$D$997,"="&C10,$E$62:$E$997)/D10,0) -> 583 | J10: =IFERROR(SUMIF($D$62:$D$997,"="&C10,$G$62:$G$997)/D10,0) -> 1134 | K10: 1454 | L10: MR - Based on RR | M10: =IFERROR(SUMIF($D$62:$D$997,"="&C10,$H$62:$H$997)/E10,0) -> 1242 | N10: =IFERROR((M10*E10)+(F10*J10),0) -> 1242 | O10: =IFERROR(N10/D10,0) -> 1242
B11: 1x1 | C11: A1 | D11: =IF(C11="","",COUNTIF($D$62:$D$997,"="&C11)) -> 26 | E11: =IF(C11="","",COUNTIF($I$62:$I$997,"="&C11)) -> 23 | F11: =IFERROR(D11-E11,0) -> 3 | G11: =IFERROR(D11/$D$29,0) -> 0.1 | H11: =IFERROR(E11/D11,0) -> 0.88461538 | I11: =IFERROR(SUMIF($D$62:$D$997,"="&C11,$E$62:$E$997)/D11,0) -> 825 | J11: =IFERROR(SUMIF($D$62:$D$997,"="&C11,$G$62:$G$997)/D11,0) -> 1201.8462 | K11: 1744 | L11: MR - Based on RR | M11: =IFERROR(SUMIF($D$62:$D$997,"="&C11,$H$62:$H$997)/E11,0) -> 1195.913 | N11: =IFERROR((M11*E11)+(F11*J11),0) -> 31111.538 | O11: =IFERROR(N11/D11,0) -> 1196.5976
B12: 1x1 | C12: A1-L2 | D12: =IF(C12="","",COUNTIF($D$62:$D$997,"="&C12)) -> 42 | E12: =IF(C12="","",COUNTIF($I$62:$I$997,"="&C12)) -> 41 | F12: =IFERROR(D12-E12,0) -> 1 | G12: =IFERROR(D12/$D$29,0) -> 0.16153846 | H12: =IFERROR(E12/D12,0) -> 0.97619048 | I12: =IFERROR(SUMIF($D$62:$D$997,"="&C12,$E$62:$E$997)/D12,0) -> 825 | J12: =IFERROR(SUMIF($D$62:$D$997,"="&C12,$G$62:$G$997)/D12,0) -> 1450.5952 | K12: 1744 | L12: MR - Based on RR | M12: =IFERROR(SUMIF($D$62:$D$997,"="&C12,$H$62:$H$997)/E12,0) -> 1374.122 | N12: =IFERROR((M12*E12)+(F12*J12),0) -> 57789.595 | O12: =IFERROR(N12/D12,0) -> 1375.9427
B13: 2x2 | C13: B1 | D13: =IF(C13="","",COUNTIF($D$62:$D$997,"="&C13)) -> 26 | E13: =IF(C13="","",COUNTIF($I$62:$I$997,"="&C13)) -> 25 | F13: =IFERROR(D13-E13,0) -> 1 | G13: =IFERROR(D13/$D$29,0) -> 0.1 | H13: =IFERROR(E13/D13,0) -> 0.96153846 | I13: =IFERROR(SUMIF($D$62:$D$997,"="&C13,$E$62:$E$997)/D13,0) -> 1127 | J13: =IFERROR(SUMIF($D$62:$D$997,"="&C13,$G$62:$G$997)/D13,0) -> 1309.1154 | K13: 2045 | L13: MR - Based on RR | M13: =IFERROR(SUMIF($D$62:$D$997,"="&C13,$H$62:$H$997)/E13,0) -> 1335.44 | N13: =IFERROR((M13*E13)+(F13*J13),0) -> 34695.115 | O13: =IFERROR(N13/D13,0) -> 1334.4275
B14: 2x2 | C14: B1-L2 | D14: =IF(C14="","",COUNTIF($D$62:$D$997,"="&C14)) -> 80 | E14: =IF(C14="","",COUNTIF($I$62:$I$997,"="&C14)) -> 70 | F14: =IFERROR(D14-E14,0) -> 10 | G14: =IFERROR(D14/$D$29,0) -> 0.30769231 | H14: =IFERROR(E14/D14,0) -> 0.875 | I14: =IFERROR(SUMIF($D$62:$D$997,"="&C14,$E$62:$E$997)/D14,0) -> 1127 | J14: =IFERROR(SUMIF($D$62:$D$997,"="&C14,$G$62:$G$997)/D14,0) -> 1551.2875 | K14: 2045 | L14: MR - Based on RR | M14: =IFERROR(SUMIF($D$62:$D$997,"="&C14,$H$62:$H$997)/E14,0) -> 1474.6429 | N14: =IFERROR((M14*E14)+(F14*J14),0) -> 118737.88 | O14: =IFERROR(N14/D14,0) -> 1484.2234
B15: 3x3 | C15: C1 | D15: =IF(C15="","",COUNTIF($D$62:$D$997,"="&C15)) -> 17 | E15: =IF(C15="","",COUNTIF($I$62:$I$997,"="&C15)) -> 17 | F15: =IFERROR(D15-E15,0) -> 0 | G15: =IFERROR(D15/$D$29,0) -> 0.065384615 | H15: =IFERROR(E15/D15,0) -> 1 | I15: =IFERROR(SUMIF($D$62:$D$997,"="&C15,$E$62:$E$997)/D15,0) -> 1380 | J15: =IFERROR(SUMIF($D$62:$D$997,"="&C15,$G$62:$G$997)/D15,0) -> 1489.7059 | K15: 1454 | L15: MR - Based on RR | M15: =IFERROR(SUMIF($D$62:$D$997,"="&C15,$H$62:$H$997)/E15,0) -> 1529.8824 | N15: =IFERROR((M15*E15)+(F15*J15),0) -> 26008 | O15: =IFERROR(N15/D15,0) -> 1529.8824
B16: 3x3 | C16: C1-L2 | D16: =IF(C16="","",COUNTIF($D$62:$D$997,"="&C16)) -> 39 | E16: =IF(C16="","",COUNTIF($I$62:$I$997,"="&C16)) -> 36 | F16: =IFERROR(D16-E16,0) -> 3 | G16: =IFERROR(D16/$D$29,0) -> 0.15 | H16: =IFERROR(E16/D16,0) -> 0.92307692 | I16: =IFERROR(SUMIF($D$62:$D$997,"="&C16,$E$62:$E$997)/D16,0) -> 1380 | J16: =IFERROR(SUMIF($D$62:$D$997,"="&C16,$G$62:$G$997)/D16,0) -> 1716.6923 | K16: 1454 | L16: MR - Based on RR | M16: =IFERROR(SUMIF($D$62:$D$997,"="&C16,$H$62:$H$997)/E16,0) -> 1745.5556 | N16: =IFERROR((M16*E16)+(F16*J16),0) -> 67990.077 | O16: =IFERROR(N16/D16,0) -> 1743.3353
D17: =IF(C17="","",COUNTIF($D$62:$D$997,"="&C17)) | E17: =IF(C17="","",COUNTIF($I$62:$I$997,"="&C17)) | F17: =IFERROR(D17-E17,0) -> 0 | G17: =IFERROR(D17/$D$29,0) -> 0 | H17: =IFERROR(E17/D17,0) -> 0 | I17: =IFERROR(SUMIF($D$62:$D$997,"="&C17,$E$62:$E$997)/D17,0) -> 0 | J17: =IFERROR(SUMIF($D$62:$D$997,"="&C17,$G$62:$G$997)/D17,0) -> 0 | K17: 0 | M17: =IFERROR(SUMIF($D$62:$D$997,"="&C17,$H$62:$H$997)/E17,0) -> 0 | N17: =IFERROR((M17*E17)+(F17*J17),0) -> 0 | O17: =IFERROR(N17/D17,0) -> 0
D18: =IF(C18="","",COUNTIF($D$62:$D$997,"="&C18)) | E18: =IF(C18="","",COUNTIF($I$62:$I$997,"="&C18)) | F18: =IFERROR(D18-E18,0) -> 0 | G18: =IFERROR(D18/$D$29,0) -> 0 | H18: =IFERROR(E18/D18,0) -> 0 | I18: =IFERROR(SUMIF($D$62:$D$997,"="&C18,$E$62:$E$997)/D18,0) -> 0 | J18: =IFERROR(SUMIF($D$62:$D$997,"="&C18,$G$62:$G$997)/D18,0) -> 0 | K18: 0 | M18: =IFERROR(SUMIF($D$62:$D$997,"="&C18,$H$62:$H$997)/E18,0) -> 0 | N18: =IFERROR((M18*E18)+(F18*J18),0) -> 0 | O18: =IFERROR(N18/D18,0) -> 0
D19: =IF(C19="","",COUNTIF($D$62:$D$997,"="&C19)) | E19: =IF(C19="","",COUNTIF($I$62:$I$997,"="&C19)) | F19: =IFERROR(D19-E19,0) -> 0 | G19: =IFERROR(D19/$D$29,0) -> 0 | H19: =IFERROR(E19/D19,0) -> 0 | I19: =IFERROR(SUMIF($D$62:$D$997,"="&C19,$E$62:$E$997)/D19,0) -> 0 | J19: =IFERROR(SUMIF($D$62:$D$997,"="&C19,$G$62:$G$997)/D19,0) -> 0 | K19: 0 | M19: =IFERROR(SUMIF($D$62:$D$997,"="&C19,$H$62:$H$997)/E19,0) -> 0 | N19: =IFERROR((M19*E19)+(F19*J19),0) -> 0 | O19: =IFERROR(N19/D19,0) -> 0
D20: =IF(C20="","",COUNTIF($D$62:$D$997,"="&C20)) | E20: =IF(C20="","",COUNTIF($I$62:$I$997,"="&C20)) | F20: =IFERROR(D20-E20,0) -> 0 | G20: =IFERROR(D20/$D$29,0) -> 0 | H20: =IFERROR(E20/D20,0) -> 0 | I20: =IFERROR(SUMIF($D$62:$D$997,"="&C20,$E$62:$E$997)/D20,0) -> 0 | J20: =IFERROR(SUMIF($D$62:$D$997,"="&C20,$G$62:$G$997)/D20,0) -> 0 | K20: 0 | M20: =IFERROR(SUMIF($D$62:$D$997,"="&C20,$H$62:$H$997)/E20,0) -> 0 | N20: =IFERROR((M20*E20)+(F20*J20),0) -> 0 | O20: =IFERROR(N20/D20,0) -> 0
D21: =IF(C21="","",COUNTIF($D$62:$D$997,"="&C21)) | E21: =IF(C21="","",COUNTIF($I$62:$I$997,"="&C21)) | F21: =IFERROR(D21-E21,0) -> 0 | G21: =IFERROR(D21/$D$29,0) -> 0 | H21: =IFERROR(E21/D21,0) -> 0 | I21: =IFERROR(SUMIF($D$62:$D$997,"="&C21,$E$62:$E$997)/D21,0) -> 0 | J21: =IFERROR(SUMIF($D$62:$D$997,"="&C21,$G$62:$G$997)/D21,0) -> 0 | K21: 0 | M21: =IFERROR(SUMIF($D$62:$D$997,"="&C21,$H$62:$H$997)/E21,0) -> 0 | N21: =IFERROR((M21*E21)+(F21*J21),0) -> 0 | O21: =IFERROR(N21/D21,0) -> 0
D22: =IF(C22="","",COUNTIF($D$62:$D$997,"="&C22)) | E22: =IF(C22="","",COUNTIF($I$62:$I$997,"="&C22)) | F22: =IFERROR(D22-E22,0) -> 0 | G22: =IFERROR(D22/$D$29,0) -> 0 | H22: =IFERROR(E22/D22,0) -> 0 | I22: =IFERROR(SUMIF($D$62:$D$997,"="&C22,$E$62:$E$997)/D22,0) -> 0 | J22: =IFERROR(SUMIF($D$62:$D$997,"="&C22,$G$62:$G$997)/D22,0) -> 0 | K22: 0 | M22: =IFERROR(SUMIF($D$62:$D$997,"="&C22,$H$62:$H$997)/E22,0) -> 0 | N22: =IFERROR((M22*E22)+(F22*J22),0) -> 0 | O22: =IFERROR(N22/D22,0) -> 0
D23: =IF(C23="","",COUNTIF($D$62:$D$997,"="&C23)) | E23: =IF(C23="","",COUNTIF($I$62:$I$997,"="&C23)) | F23: =IFERROR(D23-E23,0) -> 0 | G23: =IFERROR(D23/$D$29,0) -> 0 | H23: =IFERROR(E23/D23,0) -> 0 | I23: =IFERROR(SUMIF($D$62:$D$997,"="&C23,$E$62:$E$997)/D23,0) -> 0 | J23: =IFERROR(SUMIF($D$62:$D$997,"="&C23,$G$62:$G$997)/D23,0) -> 0 | K23: 0 | M23: =IFERROR(SUMIF($D$62:$D$997,"="&C23,$H$62:$H$997)/E23,0) -> 0 | N23: =IFERROR((M23*E23)+(F23*J23),0) -> 0 | O23: =IFERROR(N23/D23,0) -> 0
D24: =IF(C24="","",COUNTIF($D$62:$D$997,"="&C24)) | E24: =IF(C24="","",COUNTIF($I$62:$I$997,"="&C24)) | F24: =IFERROR(D24-E24,0) -> 0 | G24: =IFERROR(D24/$D$29,0) -> 0 | H24: =IFERROR(E24/D24,0) -> 0 | I24: =IFERROR(SUMIF($D$62:$D$997,"="&C24,$E$62:$E$997)/D24,0) -> 0 | J24: =IFERROR(SUMIF($D$62:$D$997,"="&C24,$G$62:$G$997)/D24,0) -> 0 | K24: 0 | M24: =IFERROR(SUMIF($D$62:$D$997,"="&C24,$H$62:$H$997)/E24,0) -> 0 | N24: =IFERROR((M24*E24)+(F24*J24),0) -> 0 | O24: =IFERROR(N24/D24,0) -> 0
D25: =IF(C25="","",COUNTIF($D$62:$D$997,"="&C25)) | E25: =IF(C25="","",COUNTIF($I$62:$I$997,"="&C25)) | F25: =IFERROR(D25-E25,0) -> 0 | G25: =IFERROR(D25/$D$29,0) -> 0 | H25: =IFERROR(E25/D25,0) -> 0 | I25: =IFERROR(SUMIF($D$62:$D$997,"="&C25,$E$62:$E$997)/D25,0) -> 0 | J25: =IFERROR(SUMIF($D$62:$D$997,"="&C25,$G$62:$G$997)/D25,0) -> 0 | K25: 0 | M25: =IFERROR(SUMIF($D$62:$D$997,"="&C25,$H$62:$H$997)/E25,0) -> 0 | N25: =IFERROR((M25*E25)+(F25*J25),0) -> 0 | O25: =IFERROR(N25/D25,0) -> 0
D26: =IF(C26="","",COUNTIF($D$62:$D$997,"="&C26)) | E26: =IF(C26="","",COUNTIF($I$62:$I$997,"="&C26)) | F26: =IFERROR(D26-E26,0) -> 0 | G26: =IFERROR(D26/$D$29,0) -> 0 | H26: =IFERROR(E26/D26,0) -> 0 | I26: =IFERROR(SUMIF($D$62:$D$997,"="&C26,$E$62:$E$997)/D26,0) -> 0 | J26: =IFERROR(SUMIF($D$62:$D$997,"="&C26,$G$62:$G$997)/D26,0) -> 0 | K26: 0 | M26: =IFERROR(SUMIF($D$62:$D$997,"="&C26,$H$62:$H$997)/E26,0) -> 0 | N26: =IFERROR((M26*E26)+(F26*J26),0) -> 0 | O26: =IFERROR(N26/D26,0) -> 0
D27: =IF(C27="","",COUNTIF($D$62:$D$997,"="&C27)) | E27: =IF(C27="","",COUNTIF($I$62:$I$997,"="&C27)) | F27: =IFERROR(D27-E27,0) -> 0 | G27: =IFERROR(D27/$D$29,0) -> 0 | H27: =IFERROR(E27/D27,0) -> 0 | I27: =IFERROR(SUMIF($D$62:$D$997,"="&C27,$E$62:$E$997)/D27,0) -> 0 | J27: =IFERROR(SUMIF($D$62:$D$997,"="&C27,$G$62:$G$997)/D27,0) -> 0 | K27: 0 | M27: =IFERROR(SUMIF($D$62:$D$997,"="&C27,$H$62:$H$997)/E27,0) -> 0 | N27: =IFERROR((M27*E27)+(F27*J27),0) -> 0 | O27: =IFERROR(N27/D27,0) -> 0
D28: =IF(C28="","",COUNTIF($D$62:$D$997,"="&C28)) | E28: =IF(C28="","",COUNTIF($I$62:$I$997,"="&C28)) | F28: =IFERROR(D28-E28,0) -> 0 | G28: =IFERROR(D28/$D$29,0) -> 0 | H28: =IFERROR(E28/D28,0) -> 0 | I28: =IFERROR(SUMIF($D$62:$D$997,"="&C28,$E$62:$E$997)/D28,0) -> 0 | J28: =IFERROR(SUMIF($D$62:$D$997,"="&C28,$G$62:$G$997)/D28,0) -> 0 | K28: 0 | M28: =IFERROR(SUMIF($D$62:$D$997,"="&C28,$H$62:$H$997)/E28,0) -> 0 | N28: =IFERROR((M28*E28)+(F28*J28),0) -> 0 | O28: =IFERROR(N28/D28,0) -> 0
C29: Total | D29: =SUM(D9:D28) -> 260 | E29: =SUM(E9:E28) -> 239 | F29: =SUM(F9:F28) -> 21 | G29: =SUM(G9:G28) -> 1 | H29: =E29/Units -> 0.91923077 | I29: =SUMPRODUCT($D$9:$D$28,I9:I28) -> 270332 | J29: =SUMPRODUCT($D$9:$D$28,J9:J28) -> 376456 | K29: =SUMPRODUCT($D$9:$D$28,K9:K28) -> 460406 | M29: =SUMPRODUCT(E9:E28,M9:M28) -> 338702 | N29: =SUM(N9:N28) -> 369116.37
G30: MRP | H30: =J29*12 -> 4517472 | I30: Rent per Unit | J30: =SUMPRODUCT(D9:D28,J9:J28)/D29 -> 1447.9077 | K30: =SUMPRODUCT(D9:D28,K9:K28)/D29 -> 1770.7923 | M30: =SUMPRODUCT(E9:E28,M9:M28)/E29 -> 1417.1632
G31: GRP | H31: =N29*12 -> 4429396.5 | I31: Rent per Sq ft | J31: =J30/J32 -> 1.3925691 | K31: =K30/K32 -> 1.7031132 | M31: =M30/(SUMPRODUCT(E9:E28,I9:I28)/E29) -> 1.361638
G32: Loss/(Gain) to lease | H32: =H30-H31 -> 88075.519 | I32: Average sq ft | J32: =SUMPRODUCT(D9:D28,I9:I28)/D29 -> 1039.7385 | K32: =SUMPRODUCT(D9:D28,I9:I28)/D29 -> 1039.7385 | M32: =SUMPRODUCT(E9:E28,I9:I28)/E29 -> 1040.7782
C35: Renovation Rent Premium and Cost Schdule
C36: Type | D36: Units | G36: Cost Per Unit | H36: Total Cost | I36: Premium Per Unit
C37: =IF(C9="","",C9) -> E1 | D37: =D9 -> 29 | G37: 0 | H37: =IFERROR(G37*D37,0) -> 0 | I37: 0
C38: =IF(C10="","",C10) -> E1-L2 | D38: =D10 -> 1 | G38: 0 | H38: =IFERROR(G38*D38,0) -> 0 | I38: 0
C39: =IF(C11="","",C11) -> A1 | D39: =D11 -> 26 | G39: 0 | H39: =IFERROR(G39*D39,0) -> 0 | I39: 0
C40: =IF(C12="","",C12) -> A1-L2 | D40: =D12 -> 42 | G40: 0 | H40: =IFERROR(G40*D40,0) -> 0 | I40: 0
C41: =IF(C13="","",C13) -> B1 | D41: =D13 -> 26 | G41: 0 | H41: =IFERROR(G41*D41,0) -> 0 | I41: 0
C42: =IF(C14="","",C14) -> B1-L2 | D42: =D14 -> 80 | G42: 0 | H42: =IFERROR(G42*D42,0) -> 0 | I42: 0
C43: =IF(C15="","",C15) -> C1 | D43: =D15 -> 17 | G43: 0 | H43: =IFERROR(G43*D43,0) -> 0 | I43: 0
C44: =IF(C16="","",C16) -> C1-L2 | D44: =D16 -> 39 | G44: 0 | H44: =IFERROR(G44*D44,0) -> 0 | I44: 0
C45: =IF(C17="","",C17) | D45: =D17 | G45: 0 | H45: =IFERROR(G45*D45,0) -> 0 | I45: 0
C46: =IF(C18="","",C18) | D46: =D18 | G46: 0 | H46: =IFERROR(G46*D46,0) -> 0 | I46: 0
C47: =IF(C19="","",C19) | D47: =D19 | G47: 0 | H47: =IFERROR(G47*D47,0) -> 0 | I47: 0
C48: =IF(C20="","",C20) | D48: =D20 | G48: 0 | H48: =IFERROR(G48*D48,0) -> 0 | I48: 0
... C56: =IF(C28="","",C28) | D56: =D28 | G56: 0 | H56: =IFERROR(G56*D56,0) -> 0 | I56: 0
C57: Total | D57: =SUM(D37:D56) -> 260 | G57: =SUMPRODUCT(D37:D56,G37:G56)/D57 -> 0 | H57: =SUM(H37:H56) -> 0 | I57: =SUMPRODUCT(D37:D56,I37:I56) -> 0
B61: Unit type | C61: Unit | D61: Unit Type | E61: Sq Ft | F61: Tenant Name | G61: Market Rent | H61: Lease Rent | I61: Occupancy
B62: A1 | C62: 101 | D62: E1 | E62: 583 | F62: Frederick, Ishmael | G62: 1162 | H62: 1071 | I62: =IF(H62=0,"",D62) -> E1
B63: A1-L2 | C63: 102 | D63: B1 | E63: 1127 | F63: Ringfield, Unrecay | G63: 1326 | H63: 1452 | I63: =IF(H63=0,"",D63) -> B1
B64: B1 | C64: 103 | D64: E1 | E64: 583 | F64: Thomas, Dorothy | G64: 1162 | H64: 1060 | I64: =IF(H64=0,"",D64) -> E1
B65: B1-L2 | C65: 104 | D65: B1-L2 | E65: 1127 | F65: Jones, Fredericka | G65: 1650 | H65: 1715 | I65: =IF(H65=0,"",D65) -> B1-L2
B66: C1 | C66: 105 | D66: E1 | E66: 583 | F66: Lamar, Quentin | G66: 1152 | H66: 1091 | I66: =IF(H66=0,"",D66) -> E1
B67: C1-L2 | C67: 106 | D67: B1 | E67: 1127 | F67: Smith, Gewandra | G67: 1330 | H67: 1312 | I67: =IF(H67=0,"",D67) -> B1
B68: E1 | C68: 107 | D68: E1 | E68: 583 | G68: 1138 | H68: 0 | I68: =IF(H68=0,"",D68)
B69: E1-L2 | C69: 108 | D69: B1-L2 | E69: 1127 | F69: Dennis, Evelyn | G69: 1526 | H69: 1496 | I69: =IF(H69=0,"",D69) -> B1-L2
B70: (blank) | C70: 109 | D70: B1-L2 | E70: 1127 | G70: 1561 | H70: 0 | I70: =IF(H70=0,"",D70)
B71: Grand Total | C71: 110 | D71: E1 | E71: 583 | F71: Parks, Dale | G71: 1162 | H71: 1119 | I71: =IF(H71=0,"",D71) -> E1
C72: 111 | D72: B1-L2 | E72: 1127 | F72: Williams, Marcella | G72: 1636 | H72: 1519 | I72: =IF(H72=0,"",D72) -> B1-L2
C73: 112 | D73: E1 | E73: 583 | F73: Jerald, Mccray | G73: 1197 | H73: 1089 | I73: =IF(H73=0,"",D73) -> E1
C74: 113 | D74: B1-L2 | E74: 1127 | F74: Charles, Gregory | G74: 1550 | H74: 1467 | I74: =IF(H74=0,"",D74) -> B1-L2
C75: 114 | D75: E1 | E75: 583 | F75: Lipscomb, Darin | G75: 1152 | H75: 995 | I75: =IF(H75=0,"",D75) -> E1
C76: 115 | D76: B1-L2 | E76: 1127 | F76: Taylor, Terrence | G76: 1536 | H76: 1466 | I76: =IF(H76=0,"",D76) -> B1-L2
C77: 116 | D77: E1-L2 | E77: 583 | F77: Catron, Brittany | G77: 1134 | H77: 1242 | I77: =IF(H77=0,"",D77) -> E1-L2
C78: 201 | D78: A1-L2 | E78: 825 | F78: Fletcher, Alexis | G78: 1510 | H78: 1283 | I78: =IF(H78=0,"",D78) -> A1-L2
C79: 202 | D79: A1 | E79: 825 | F79: Ross, Jada | G79: 1252 | H79: 1230 | I79: =IF(H79=0,"",D79) -> A1
C80: 203 | D80: A1 | E80: 825 | F80: Soitis, Nesptah | G80: 1212 | H80: 1203 | I80: =IF(H80=0,"",D80) -> A1
C81: 204 | D81: A1-L2 | E81: 825 | F81: Gordon, Selena | G81: 1470 | H81: 1386 | I81: =IF(H81=0,"",D81) -> A1-L2
C82: 205 | D82: A1 | E82: 825 | F82: Walker, Zhane | G82: 1212 | H82: 1012 | I82: =IF(H82=0,"",D82) -> A1
C83: 206 | D83: A1-L2 | E83: 825 | F83: Lewis, Trakevia | G83: 1455 | H83: 1350 | I83: =IF(H83=0,"",D83) -> A1-L2
... C111: 314 | D111: A1 | E111: 825 | F111: Brock, John | G111: 1197 | H111: 1243 | I111: =IF(H111=0,"",D111) -> A1
C112: 315 | D112: A1-L2 | E112: 825 | G112: 1530 | H112: 0 | I112: =IF(H112=0,"",D112)
C113: 316 | D113: A1-L2 | E113: 825 | F113: Cook, Ebony | G113: 1516 | H113: 1557 | I113: =IF(H113=0,"",D113) -> A1-L2
C114: 317 | D114: A1 | E114: 825 | G114: 1186 | H114: 0 | I114: =IF(H114=0,"",D114)
C115: 318 | D115: A1-L2 | E115: 825 | F115: Hayes, Nyasia | G115: 1415 | H115: 1252 | I115: =IF(H115=0,"",D115) -> A1-L2
C116: 319 | D116: A1-L2 | E116: 825 | F116: Dortch, Desmond | G116: 1415 | H116: 1208 | I116: =IF(H116=0,"",D116) -> A1-L2
C117: 320 | D117: A1-L2 | E117: 825 | F117: Poszwa, Daniel | G117: 1415 | H117: 1266 | I117: =IF(H117=0,"",D117) -> A1-L2
C118: 321 | D118: A1-L2 | E118: 825 | F118: Akinniyi, Temidayo | G118: 1435 | H118: 1206 | I118: =IF(H118=0,"",D118) -> A1-L2
C119: 322 | D119: A1-L2 | E119: 825 | F119: Thomas, Phaedra | G119: 1435 | H119: 1472 | I119: =IF(H119=0,"",D119) -> A1-L2
C120: 323 | D120: A1 | E120: 825 | F120: Wooden, Rahman | G120: 1192 | H120: 1230 | I120: =IF(H120=0,"",D120) -> A1
C121: 324 | D121: A1 | E121: 825 | G121: 1192 | H121: 0 | I121: =IF(H121=0,"",D121)
C122: 401 | D122: C1 | E122: 1380 | F122: Clark, Keith | G122: 1585 | H122: 1591 | I122: =IF(H122=0,"",D122) -> C1
C123: 402 | D123: B1-L2 | E123: 1127 | F123: Trotman, Lori | G123: 1575 | H123: 1526 | I123: =IF(H123=0,"",D123) -> B1-L2
C124: 403 | D124: C1-L2 | E124: 1380 | F124: Pursley, Marcoah | G124: 1720 | H124: 1696 | I124: =IF(H124=0,"",D124) -> C1-L2
C125: 404 | D125: B1-L2 | E125: 1127 | F125: Ashley, Kionna | G125: 1550 | H125: 1377 | I125: =IF(H125=0,"",D125) -> B1-L2
C126: 405 | D126: C1 | E126: 1380 | F126: Powell, Jacqlyn | G126: 1481 | H126: 1585 | I126: =IF(H126=0,"",D126) -> C1
C127: 406 | D127: B1-L2 | E127: 1127 | F127: Wilson, Jonijah | G127: 1550 | H127: 1616 | I127: =IF(H127=0,"",D127) -> B1-L2
C128: 407 | D128: C1 | E128: 1380 | F128: Lewis, Anthony | G128: 1486 | H128: 1457 | I128: =IF(H128=0,"",D128) -> C1
C129: 408 | D129: B1-L2 | E129: 1127 | F129: Pernell, Ulrica | G129: 1540 | H129: 1337 | I129: =IF(H129=0,"",D129) -> B1-L2
C130: 409 | D130: C1-L2 | E130: 1380 | F130: Ha, Nadine | G130: 1710 | H130: 1606 | I130: =IF(H130=0,"",D130) -> C1-L2
C131: 410 | D131: B1 | E131: 1127 | F131: Williams, Shelia | G131: 1306 | H131: 1366 | I131: =IF(H131=0,"",D131) -> B1
C132: 411 | D132: B1-L2 | E132: 1127 | G132: 1590 | H132: 0 | I132: =IF(H132=0,"",D132)
C133: 412 | D133: C1-L2 | E133: 1380 | F133: Reid, Isaiah | G133: 1745 | H133: 1899 | I133: =IF(H133=0,"",D133) -> C1-L2
C134: 413 | D134: B1 | E134: 1127 | F134: Baker, Jaquitta | G134: 1315 | H134: 1323 | I134: =IF(H134=0,"",D134) -> B1
C135: 414 | D135: C1-L2 | E135: 1380 | F135: Shack, Shannon | G135: 1720 | H135: 1645 | I135: =IF(H135=0,"",D135) -> C1-L2
C136: 415 | D136: B1-L2 | E136: 1127 | F136: Johnson, Ebony | G136: 1536 | H136: 1321 | I136: =IF(H136=0,"",D136) -> B1-L2
C137: 416 | D137: C1-L2 | E137: 1380 | F137: Frazier, Patricia | G137: 1691 | H137: 1717 | I137: =IF(H137=0,"",D137) -> C1-L2
C138: 417 | D138: B1-L2 | E138: 1127 | F138: Driver, Tonya | G138: 1540 | H138: 1645 | I138: =IF(H138=0,"",D138) -> B1-L2
C139: 418 | D139: C1-L2 | E139: 1380 | F139: Lee, Vickie | G139: 1760 | H139: 1841 | I139: =IF(H139=0,"",D139) -> C1-L2
C140: 419 | D140: B1-L2 | E140: 1127 | F140: Bennett, Anthony | G140: 1555 | H140: 1659 | I140: =IF(H140=0,"",D140) -> B1-L2
C141: 420 | D141: C1-L2 | E141: 1380 | F141: Wright, Elizabeth | G141: 1710 | H141: 1895 | I141: =IF(H141=0,"",D141) -> C1-L2
...

Sheet Sources & Usage
B2: =Loan!B2 -> The Grove on Southlake | C2: ='CFS-Main Page'!C2 -> Address: | D2: ='CFS-Main Page'!D2 -> 7290 Southlake Parkway Morrow, GA, 30260
B3: Sources & Usage | C3: ='CFS-Main Page'!C3 -> Units | D3: ='CFS-Main Page'!D3 -> 260
B4: =Loan!B4 -> 0 | C4: ='CFS-Main Page'!C4 -> Year Built/Reno | D4: ='CFS-Main Page'!D4 -> 2001
B6: Source of Funding (Pre Refinance) | C6: Amount | D6: Per Unit
B7: Debt | C7: =IF(Loan!C9=0,Loan!C30,Loan!$C$9) -> 29890000 | D7: =C7/Units -> 114961.54 | E7: =C7/$C$9 -> 0.68829892
B8: Equity | C8: =C23-C7 -> 13535900 | D8: =C8/Units -> 52061.154 | E8: =C8/$C$9 -> 0.31170108
B9: Total | C9: =SUM(C7:C8) -> 43425900 | D9: =SUM(D7:D8) -> 167022.69 | E9: =SUM(E7:E8) -> 1
B11: Usage of Funding | C11: Amount | D11: Per Unit
B12: Purchase Price | C12: ='CFS-Main Page'!C7 -> 42700000 | D12: =C12/Units -> 164230.77 | E12: =C12/$C$23 -> 0.98328417
B13: Loan Processing Fees | C13: =C7*F13 -> 298900 | D13: =C13/Units -> 1149.6154 | E13: =C13/$C$23 -> 0.0068829892 | F13: 0.01
B14: Acquisition Fees | C14: =F14*C12 -> 427000 | D14: =C14/Units -> 1642.3077 | E14: =C14/$C$23 -> 0.0098328417 | F14: 0.01
B15: Renovation Cost | C15: =Rent!H57 -> 0 | D15: =C15/Units -> 0 | E15: =C15/$C$23 -> 0
B16: Additional Capex | C16: 0 | D16: =C16/Units -> 0 | E16: =C16/$C$23 -> 0
B17: Equity Fees | C17: 0 | D17: =C17/Units -> 0 | E17: =C17/$C$23 -> 0
B18: Legal | C18: 0 | D18: =C18/Units -> 0 | E18: =C18/$C$23 -> 0
B19: Other Closing Cost | C19: 0 | D19: =C19/Units -> 0 | E19: =C19/$C$23 -> 0
B20: Other Closing Cost | C20: 0 | D20: =C20/Units -> 0 | E20: =C20/$C$23 -> 0
B21: Other Closing Cost | C21: 0 | D21: =C21/Units -> 0 | E21: =C21/$C$23 -> 0
B22: Other Closing Cost | C22: =C12*F22 -> 0 | D22: =C22/Units -> 0 | E22: =C22/$C$23 -> 0 | F22: 0
B23: Total | C23: =SUM(C12:C22) -> 43425900 | D23: =SUM(D12:D22) -> 167022.69 | E23: 1

Sheet Loan
B2: =Rent!B2 -> The Grove on Southlake | C2: ='CFS-Main Page'!C2 -> Address: | D2: ='CFS-Main Page'!D2 -> 7290 Southlake Parkway Morrow, GA, 30260
B3: Loan Schedule | C3: ='CFS-Main Page'!C3 -> Units | D3: ='CFS-Main Page'!D3 -> 260
B4: =Rent!B4 -> 0 | C4: ='CFS-Main Page'!C4 -> Year Built/Reno | D4: ='CFS-Main Page'!D4 -> 2001
B6: Loan Assumptions - Acquisition Loan
B7: Project Cost | C7: ='Sources & Usage'!C23 -> 43425900
B8: LTV | C8: 0.7 | D8: =C9/C7 -> 0.68829892
B9: Loan Amount | C9: =IF(C12>0,ROUND('CFS-Main Page'!C7*C8,-4),0) -> 29890000
B10: Processing Fees | C10: =C9*D10 -> 298900 | D10: ='Sources & Usage'!F13 -> 0.01
B11: Amortization Period (Years) | C11: 30
B12: Loan Termination for Refinance | C12: ='CFS-Main Page'!C13 -> 5 | D12: ← Input 0 if not using
B13: Interest Rate | C13: =4.007%+1.4% -> 0.05407
B14: I/O Period | C14: 3
B15: Debt Service Constant | C15: =-PMT(C13/12,C11*12,1)*12 -> 0.067436139
B16: Annual Payment Constant | C16: =C15*C9 -> 2015666.2
B17: Loan Schedule (First) | D17: 0 | E17: 1 | F17: 2 | G17: 3 | H17: 4 | I17: 5 | J17: 6 | K17: 7 | L17: 8 | M17: 9 | N17: 10
B18: Loan Amount BB | E18: =D23 -> 29890000 | F18: =E23 -> 29890000 | G18: =F23 -> 29890000 | H18: =G23 -> 29890000 | I18: =H23 -> 29490486 | J18: =I23 -> 0 | K18: =J23 -> 0 | L18: =K23 -> 0 | ... N18: =M23 -> 0
B19: Interest Payment | E19: =IF(E17>$C$12,0,E18*$C$13) -> 1616152.3 | F19: =IF(F17>$C$12,0,F18*$C$13) -> 1616152.3 | G19: =IF(G17>$C$12,0,G18*$C$13) -> 1616152.3 | H19: =IF(H17>$C$12,0,H18*$C$13) -> 1616152.3 | I19: =IF(I17>$C$12,0,I18*$C$13) -> 1594550.6 | J19: =IF(J17>$C$12,0,J18*$C$13) -> 0 | K19: =IF(K17>$C$12,0,K18*$C$13) -> 0 | L19: =IF(L17>$C$12,0,L18*$C$13) -> 0 | ... N19: =IF(N17>$C$12,0,N18*$C$13) -> 0
B20: Principal Payment | E20: =IF(OR(E17<=$C$14,E17>$C$12),0,$C$16-E19) -> 0 | F20: =IF(OR(F17<=$C$14,F17>$C$12),0,$C$16-F19) -> 0 | G20: =IF(OR(G17<=$C$14,G17>$C$12),0,$C$16-G19) -> 0 | H20: =IF(OR(H17<=$C$14,H17>$C$12),0,$C$16-H19) -> 399513.9 | I20: =IF(OR(I17<=$C$14,I17>$C$12),0,$C$16-I19) -> 421115.62 | J20: =IF(OR(J17<=$C$14,J17>$C$12),0,$C$16-J19) -> 0 | K20: =IF(OR(K17<=$C$14,K17>$C$12),0,$C$16-K19) -> 0 | L20: =IF(OR(L17<=$C$14,L17>$C$12),0,$C$16-L19) -> 0 | ... N20: =IF(OR(N17<=$C$14,N17>$C$12),0,$C$16-N19) -> 0
B21: Loan Payoff | E21: =IF(E17=$C$12,E18-E20,0) -> 0 | F21: =IF(F17=$C$12,F18-F20,0) -> 0 | G21: =IF(G17=$C$12,G18-G20,0) -> 0 | H21: =IF(H17=$C$12,H18-H20,0) -> 0 | I21: =IF(I17=$C$12,I18-I20,0) -> 29069370 | J21: =IF(J17=$C$12,J18-J20,0) -> 0 | K21: =IF(K17=$C$12,K18-K20,0) -> 0 | L21: =IF(L17=$C$12,L18-L20,0) -> 0 | ... N21: =IF(N17=$C$12,N18-N20,0) -> 0
B22: Total Debt Payment | E22: =SUM(E19:E20) -> 1616152.3 | F22: =SUM(F19:F20) -> 1616152.3 | G22: =SUM(G19:G20) -> 1616152.3 | H22: =SUM(H19:H20) -> 2015666.2 | I22: =SUM(I19:I20) -> 2015666.2 | J22: =SUM(J19:J20) -> 0 | K22: =SUM(K19:K20) -> 0 | L22: =SUM(L19:L20) -> 0 | ... N22: =SUM(N19:N20) -> 0
B23: Loan Balance End of Year | D23: =C9 -> 29890000 | E23: =E18-E20-E21 -> 29890000 | F23: =F18-F20-F21 -> 29890000 | G23: =G18-G20-G21 -> 29890000 | H23: =H18-H20-H21 -> 29490486 | I23: =I18-I20-I21 -> 0 | J23: =J18-J20-J21 -> 0 | K23: =K18-K20-K21 -> 0 | L23: =L18-L20-L21 -> 0 | ... N23: =N18-N20-N21 -> 0
B25: Loan Assumptions - Refinance | G25: Refinancing assumptions
B26: Total cost | C26: ='Sources & Usage'!C23 -> 43425900 | G26: Year of Refinance | H26: =C12 -> 5
G27: =CONCATENATE("Year ", H26," NOI") -> Year 5 NOI | H27: {=IF(H26<1,0,INDEX('CFS-Main Page'!I63:S63,Loan!$H$26))} -> 2530775.9
B28: LTV | C28: 0.8 | G28: DCR Sizing | H28: 1.25
B29: LTC | C29: =C30/C26 -> 0
B30: Loan Amount | C30: 0 | D30: ← Input 0 if not using Refinance and Loan amount can be Hardcoded. =ROUND(IF(H26=0,C28*C26,H33),-4) | G30: Constant | H30: =-PMT(C33/12,C31*12,1)*12 -> 0.075848163
B31: Amortization Period (Years) | C31: 30 | G31: Debt Service | H31: =IF(H26=0,C30*H30,H27/H28) -> 2024620.7
B32: Loan Term (Years)_Holding | C32: =IF(H26>0,MIN('CFS-Main Page'!C13+$H$26,N35),'CFS-Main Page'!C13) -> 10 | G32: Max Proceed | H32: =ROUND(H31/H30,-4) -> 26690000
B33: Interest Rate | C33: 0.065 | G33: Bridge Loan payoff | H33: =SUM(E21:N21) -> 29069370
B34: I/O Period | C34: 10
B35: Loan Schedule (Refinance) | D35: 0 | E35: 1 | F35: 2 | G35: 3 | H35: 4 | I35: 5 | J35: 6 | K35: 7 | L35: 8 | M35: 9 | N35: 10
B36: Loan Amount BB | E36: =IF($H$26>0,IF(E$35=$H$26+1,$C$30,IF(E$35>=$H$26,D$41,0)),IF(E$35=1,$C$30,D$41)) -> 0 | F36: =IF($H$26>0,IF(F$35=$H$26+1,$C$30,IF(F$35>=$H$26,E$41,0)),IF(F$35=1,$C$30,E$41)) -> 0 | G36: =IF($H$26>0,IF(G$35=$H$26+1,$C$30,IF(G$35>=$H$26,F$41,0)),IF(G$35=1,$C$30,F$41)) -> 0 | H36: =IF($H$26>0,IF(H$35=$H$26+1,$C$30,IF(H$35>=$H$26,G$41,0)),IF(H$35=1,$C$30,G$41)) -> 0 | I36: =IF($H$26>0,IF(I$35=$H$26+1,$C$30,IF(I$35>=$H$26,H$41,0)),IF(I$35=1,$C$30,H$41)) -> 0 | J36: =IF($H$26>0,IF(J$35=$H$26+1,$C$30,IF(J$35>=$H$26,I$41,0)),IF(J$35=1,$C$30,I$41)) -> 0 | K36: =IF($H$26>0,IF(K$35=$H$26+1,$C$30,IF(K$35>=$H$26,J$41,0)),IF(K$35=1,$C$30,J$41)) -> 0 | L36: =IF($H$26>0,IF(L$35=$H$26+1,$C$30,IF(L$35>=$H$26,K$41,0)),IF(L$35=1,$C$30,K$41)) -> 0 | ... N36: =IF($H$26>0,IF(N$35=$H$26+1,$C$30,IF(N$35>=$H$26,M$41,0)),IF(N$35=1,$C$30,M$41)) -> 0
B37: Interest Payment | E37: =IF(E35>$C$32,0,E36*$C$33) -> 0 | F37: =IF(F35>$C$32,0,F36*$C$33) -> 0 | G37: =IF(G35>$C$32,0,G36*$C$33) -> 0 | H37: =IF(H35>$C$32,0,H36*$C$33) -> 0 | I37: =IF(I35>$C$32,0,I36*$C$33) -> 0 | J37: =IF(J35>$C$32,0,J36*$C$33) -> 0 | K37: =IF(K35>$C$32,0,K36*$C$33) -> 0 | L37: =IF(L35>$C$32,0,L36*$C$33) -> 0 | ... N37: =IF(N35>$C$32,0,N36*$C$33) -> 0
B38: Principal | E38: =IF(E36>0,IF(OR(E35<=$C$34,E35>$C$32),0,$H$31-E37),0) -> 0 | F38: =IF(F36>0,IF(OR(F35<=$C$34,F35>$C$32),0,$H$31-F37),0) -> 0 | G38: =IF(G36>0,IF(OR(G35<=$C$34,G35>$C$32),0,$H$31-G37),0) -> 0 | H38: =IF(H36>0,IF(OR(H35<=$C$34,H35>$C$32),0,$H$31-H37),0) -> 0 | I38: =IF(I36>0,IF(OR(I35<=$C$34,I35>$C$32),0,$H$31-I37),0) -> 0 | J38: =IF(J36>0,IF(OR(J35<=$C$34,J35>$C$32),0,$H$31-J37),0) -> 0 | K38: =IF(K36>0,IF(OR(K35<=$C$34,K35>$C$32),0,$H$31-K37),0) -> 0 | L38: =IF(L36>0,IF(OR(L35<=$C$34,L35>$C$32),0,$H$31-L37),0) -> 0 | ... N38: =IF(N36>0,IF(OR(N35<=$C$34,N35>$C$32),0,$H$31-N37),0) -> 0
B39: Loan Payoff | E39: =IF(E35=$C$32,E36-E38,0) -> 0 | F39: =IF(F35=$C$32,F36-F38,0) -> 0 | G39: =IF(G35=$C$32,G36-G38,0) -> 0 | H39: =IF(H35=$C$32,H36-H38,0) -> 0 | I39: =IF(I35=$C$32,I36-I38,0) -> 0 | J39: =IF(J35=$C$32,J36-J38,0) -> 0 | K39: =IF(K35=$C$32,K36-K38,0) -> 0 | L39: =IF(L35=$C$32,L36-L38,0) -> 0 | ... N39: =IF(N35=$C$32,N36-N38,0) -> 0
B40: Total Debt Payment | E40: =E37+E38 -> 0 | F40: =F37+F38 -> 0 | G40: =G37+G38 -> 0 | H40: =H37+H38 -> 0 | I40: =I37+I38 -> 0 | J40: =J37+J38 -> 0 | K40: =K37+K38 -> 0 | L40: =L37+L38 -> 0 | ... N40: =N37+N38 -> 0
B41: Loan Balance End of Year | D41: =IF(H26>0,0,C30) -> 0 | E41: =E$36-E$38-E$39 -> 0 | F41: =F$36-F$38-F$39 -> 0 | G41: =G$36-G$38-G$39 -> 0 | H41: =H$36-H$38-H$39 -> 0 | I41: =I$36-I$38-I$39 -> 0 | J41: =J$36-J$38-J$39 -> 0 | K41: =K$36-K$38-K$39 -> 0 | L41: =L$36-L$38-L$39 -> 0 | ... N41: =N$36-N$38-N$39 -> 0
B43: Total Principal Payment | E43: =E20+E38 -> 0 | F43: =F20+F38 -> 0 | G43: =G20+G38 -> 0 | H43: =H20+H38 -> 399513.9 | I43: =I20+I38 -> 421115.62 | J43: =J20+J38 -> 0 | K43: =K20+K38 -> 0 | L43: =L20+L38 -> 0 | ... N43: =N20+N38 -> 0
B44: Total Loan Payoff | E44: =E21+E39-(IF(E21>0,F36,0)) -> 0 | F44: =F21+F39-(IF(F21>0,G36,0)) -> 0 | G44: =G21+G39-(IF(G21>0,H36,0)) -> 0 | H44: =H21+H39-(IF(H21>0,I36,0)) -> 0 | I44: =I21+I39-(IF(I21>0,J36,0)) -> 29069370 | J44: =J21+J39-(IF(J21>0,K36,0)) -> 0 | K44: =K21+K39-(IF(K21>0,L36,0)) -> 0 | L44: =L21+L39-(IF(L21>0,M36,0)) -> 0 | ... N44: =N21+N39-(IF(N21>0,O36,0)) -> 0
B45: Total Interest Payment | D45: =D37+D19 -> 0 | E45: =E37+E19 -> 1616152.3 | F45: =F37+F19 -> 1616152.3 | G45: =G37+G19 -> 1616152.3 | H45: =H37+H19 -> 1616152.3 | I45: =I37+I19 -> 1594550.6 | J45: =J37+J19 -> 0 | K45: =K37+K19 -> 0 | ... N45: =N37+N19 -> 0
B46: Debt Service | D46: =D45 -> 0 | E46: =E45+E43 -> 1616152.3 | F46: =F45+F43 -> 1616152.3 | G46: =G45+G43 -> 1616152.3 | H46: =H45+H43 -> 2015666.2 | I46: =I45+I43 -> 2015666.2 | J46: =J45+J43 -> 0 | K46: =K45+K43 -> 0 | L46: =L45+L43 -> 0 | ... N46: =N45+N43 -> 0

Sheet Historical Analysis
B2: ='Sources & Usage'!B2 -> The Grove on Southlake
B3: Historical Analysis
B4: ='Sources & Usage'!B4 -> 0
D5: =1 -> 1 | E5: =D5+1 -> 2 | F5: =E5+1 -> 3 | G5: =F5+1 -> 4 | H5: =G5+1 -> 5 | I5: =H5+1 -> 6 | J5: =I5+1 -> 7 | K5: =J5+1 -> 8 | L5: =K5+1 -> 9 | ... O5: =N5+1 -> 12
C6: ="T12 ending "&TEXT(O6,"mmm-yy") -> T12 ending Feb-26 | D6: 45741 | E6: =EOMONTH(D6,1) -> 45777 | F6: =EOMONTH(E6,1) -> 45808 | G6: =EOMONTH(F6,1) -> 45838 | H6: =EOMONTH(G6,1) -> 45869 | I6: =EOMONTH(H6,1) -> 45900 | J6: =EOMONTH(I6,1) -> 45930 | K6: =EOMONTH(J6,1) -> 45961 | L6: =EOMONTH(K6,1) -> 45991 | ... O6: =EOMONTH(N6,1) -> 46081 | Q6: T12 | R6: T3 | T6: Category | V6: Summary
Q8: =SUM(D8:O8) -> 0 | R8: =SUM(M8:O8)*4 -> 0 | T8: 1 - Market Rent Potential | V8: Operating Incomes | W8: T12 | X8: T3
C9: NET RENTAL INCOME | Q9: =SUM(D9:O9) -> 0 | R9: =SUM(M9:O9)*4 -> 0 | T9: 2 - Increase in Rent from Renovation | U9: 1 | V9: Market Rent Potential | W9: =SUMIF($B$1:$B$495,U9,$Q$1:$Q$495) -> 3987608 | X9: =SUMIF($B$1:$B$495,U9,$R$1:$R$495) -> 4061152
C10: OPERATING INCOME | Q10: =SUM(D10:O10) -> 0 | R10: =SUM(M10:O10)*4 -> 0 | T10: 3 - Loss to Lease | U10: 2 | V10: Increase in Market Rent Potential from Renovation | W10: =SUMIF($B$1:$B$495,U10,$Q$1:$Q$495) -> 428760 | X10: =SUMIF($B$1:$B$495,U10,$R$1:$R$495) -> 428760
B11: 1 | C11: Gross Market Rent | D11: 312251 | E11: 321492 | F11: 334334 | G11: 328058 | H11: 318037 | I11: 342488 | J11: 353457 | K11: 332518 | L11: 329685 | M11: 338583 | N11: 337971 | O11: 338734 | Q11: =SUM(D11:O11) -> 3987608 | R11: =SUM(M11:O11)*4 -> 4061152 | T11: 4 - Vacancy | V11: Total Market Rent Potential | W11: =SUM(W9:W10) -> 4416368 | X11: =SUM(X9:X10) -> 4489912
B12: 2 | C12: Upgrade Premium | D12: 35730 | E12: 35730 | F12: 35730 | G12: 35730 | H12: 35730 | I12: 35730 | J12: 35730 | K12: 35730 | L12: 35730 | M12: 35730 | N12: 35730 | O12: 35730 | Q12: =SUM(D12:O12) -> 428760 | R12: =SUM(M12:O12)*4 -> 428760 | T12: 5 - Concession/Discount | U12: 3 | V12: Loss to Lease | W12: =SUMIF($B$1:$B$495,U12,$Q$1:$Q$495) -> -57758.52 | X12: =SUMIF($B$1:$B$495,U12,$R$1:$R$495) -> -99854.84 | Y12: =W12/W11 -> -0.013078285
B13: 3 | C13: Contract Gain(Loss) to Lease | D13: 10090.7 | E13: 2003.51 | F13: -7972.21 | G13: -708.97 | H13: 6320.44 | I13: -14318.55 | J13: -23464.62 | K13: -5737.09 | L13: 991.98 | M13: -8705.69 | N13: -6768.6 | O13: -9489.42 | Q13: =SUM(D13:O13) -> -57758.52 | R13: =SUM(M13:O13)*4 -> -99854.84 | T13: 6 - Bad Debt | V13: Gross Rent Potential | W13: =W11+W12 -> 4358609.5 | X13: =X11+X12 -> 4390057.2
C14: TOTAL GROSS POTENTIAL RENT | D14: 358071.7 | E14: 359225.51 | F14: 362091.79 | G14: 363079.03 | H14: 360087.44 | I14: 363899.45 | J14: 365722.38 | K14: 362510.91 | L14: 366406.98 | M14: 365607.31 | N14: 366932.4 | O14: 364974.58 | Q14: =SUM(D14:O14) -> 4358609.5 | R14: =SUM(M14:O14)*4 -> 4390057.2 | T14: 7 - Non Revenue Units | U14: 4 | V14: Vacancy | W14: =SUMIF($B$1:$B$495,U14,$Q$1:$Q$495) -> -284691.74 | X14: =SUMIF($B$1:$B$495,U14,$R$1:$R$495) -> -332706.12
C15: RENTAL INCOME | Q15: =SUM(D15:O15) -> 0 | R15: =SUM(M15:O15)*4 -> 0 | T15: 8 - Utility Reimbursements | U15: 5 | V15: Concession/Discount | W15: =SUMIF($B$1:$B$495,U15,$Q$1:$Q$495) -> -49856.93 | X15: =SUMIF($B$1:$B$495,U15,$R$1:$R$495) -> -80204.04
B16: 6 | C16: Bad Debt | D16: -296.42 | E16: 6249.18 | F16: -6877.02 | G16: -11615.73 | H16: -8123.55 | I16: -18144.7 | J16: -24348.84 | K16: -34087.66 | L16: -6803.95 | M16: -15375.68 | N16: -18411.01 | O16: -13287.59 | Q16: =SUM(D16:O16) -> -151122.97 | R16: =SUM(M16:O16)*4 -> -188297.12 | T16: 9 - Other Reimbursements | U16: 6 | V16: Bad Debt | W16: =SUMIF($B$1:$B$495,U16,$Q$1:$Q$495) -> -152393.61 | X16: =SUMIF($B$1:$B$495,U16,$R$1:$R$495) -> -178909.2
B17: 5 | C17: Conc - Miscellaneous | D17: -51.79 | E17: -3166.98 | F17: -300 | G17: 0 | H17: -150 | I17: -280 | J17: 0 | K17: 0 | L17: -624 | M17: -0.17 | N17: 0 | O17: -200 | Q17: =SUM(D17:O17) -> -4772.94 | R17: =SUM(M17:O17)*4 -> -800.68 | T17: 10 - Other Income | U17: 7 | V17: Non Revenue Units | W17: =SUMIF($B$1:$B$495,U17,$Q$1:$Q$495) -> -26888.73 | X17: =SUMIF($B$1:$B$495,U17,$R$1:$R$495) -> -23107.2
B18: 5 | C18: Conc - Move-in Special | D18: 0 | E18: -4650 | F18: -3500 | G18: -3000 | H18: -1150 | I18: 650.01 | J18: -500 | K18: -145.16 | L18: -500 | M18: -6704.84 | N18: -3250 | O18: -5750 | Q18: =SUM(D18:O18) -> -28499.99 | R18: =SUM(M18:O18)*4 -> -62819.36 | T18: 11 - Repair & Maintenance | V18: Gross Effective Income | W18: =SUM(W13:W17) -> 3844778.5 | X18: =SUM(X13:X17) -> 3775130.6
B19: 7 | C19: Down Units | D19: 973.29 | E19: -1394.02 | F19: -1443 | G19: -1408.35 | H19: -8759 | I19: 7445.15 | J19: 0 | K19: 0 | L19: 0 | M19: 0 | N19: 0 | O19: 0 | Q19: =SUM(D19:O19) -> -4585.93 | R19: =SUM(M19:O19)*4 -> 0 | T19: 12 - Cleaning & Decorating | U19: 8 | V19: Utility Reimbursements | W19: =SUMIF($B$1:$B$495,U19,$Q$1:$Q$495) -> 171918.41 | X19: =SUMIF($B$1:$B$495,U19,$R$1:$R$495) -> 178771.76
B20: 7 | C20: Employee Units | D20: -319.2 | E20: -331.6 | F20: -331.6 | G20: -331.6 | H20: -331.6 | I20: -331.6 | J20: -331.6 | K20: -331.6 | L20: -331.6 | M20: -331.6 | N20: -331.6 | O20: -331.6 | Q20: =SUM(D20:O20) -> -3966.8 | R20: =SUM(M20:O20)*4 -> -3979.2 | T20: 13 - Contract & Services | U20: 9 | V20: Other Reimbursements | W20: =SUMIF($B$1:$B$495,U20,$Q$1:$Q$495) -> 100364.46 | X20: =SUMIF($B$1:$B$495,U20,$R$1:$R$495) -> 106408.96
B21: 5 | C21: Courtesy Officer Discounts | D21: -1382 | E21: -1382 | F21: -1382 | G21: -1382 | H21: -1382 | I21: -1382 | J21: -1382 | K21: -1382 | L21: -1382 | M21: -1382 | N21: -1382 | O21: -1382 | Q21: =SUM(D21:O21) -> -16584 | R21: =SUM(M21:O21)*4 -> -16584 | T21: 14 - Utility- Electricity | U21: 10 | V21: Other Income | W21: =SUMIF($B$1:$B$495,U21,$Q$1:$Q$495) -> 199077.53 | X21: =SUMIF($B$1:$B$495,U21,$R$1:$R$495) -> 240180.48
B22: 7 | C22: Model Units/Admin | D22: -1439 | E22: -1465 | F22: -1486 | G22: -1453 | H22: -1363 | I22: -1514 | J22: -1663 | K22: -1588 | L22: -1583 | M22: -1626 | N22: -1594 | O22: -1562 | Q22: =SUM(D22:O22) -> -18336 | R22: =SUM(M22:O22)*4 -> -19128 | T22: 15 - Utility- Water | V22: Total Operating Revenue | W22: =SUM(W18:W21) -> 4316138.9 | X22: =SUM(X18:X21) -> 4300491.8
B23: 4 | C23: Vacancy Loss | D23: -32417.72 | E23: -16143.49 | F23: -15296.34 | G23: -12228.07 | H23: -12060.08 | I23: -25726.27 | J23: -25076.24 | K23: -31859.51 | L23: -30707.49 | M23: -29595.46 | N23: -28208.17 | O23: -25372.9 | Q23: =SUM(D23:O23) -> -284691.74 | R23: =SUM(M23:O23)*4 -> -332706.12 | T23: 16 - Utility- Others
C24: TOTAL RENTAL INCOME | D24: -34932.84 | E24: -22283.91 | F24: -30615.96 | G24: -31418.75 | H24: -33319.23 | I24: -39283.41 | J24: -53301.68 | K24: -69393.93 | L24: -41932.04 | M24: -55015.75 | N24: -53176.78 | O24: -47886.09 | Q24: =SUM(D24:O24) -> -512560.37 | R24: =SUM(M24:O24)*4 -> -624314.48 | T24: 17 - Marketing | V24: Operating Expenses | W24: T12 | X24: T3
C25: NET RENTAL INCOME | D25: 323138.86 | E25: 336941.6 | F25: 331475.83 | G25: 331660.28 | H25: 326768.21 | I25: 324616.04 | J25: 312420.7 | K25: 293116.98 | L25: 324474.94 | M25: 310591.56 | N25: 313755.62 | O25: 317088.49 | Q25: =SUM(D25:O25) -> 3846049.1 | R25: =SUM(M25:O25)*4 -> 3765742.7 | T25: 18 - Payroll | U25: 11 | V25: Repair & Maintenance | W25: =SUMIF($B$1:$B$495,U25,$Q$1:$Q$495) -> 106218.29 | X25: =SUMIF($B$1:$B$495,U25,$R$1:$R$495) -> 121923.72
C26: OTHER PROPERTY INCOME | Q26: =SUM(D26:O26) -> 0 | R26: =SUM(M26:O26)*4 -> 0 | T26: 19 - RE Taxes | U26: 12 | V26: Cleaning & Decorating | W26: =SUMIF($B$1:$B$495,U26,$Q$1:$Q$495) -> 68078.69 | X26: =SUMIF($B$1:$B$495,U26,$R$1:$R$495) -> 47325.28
B27: 6 | C27: Bad Debt - Other | D27: 108.27 | E27: 1693.9 | F27: -1050.23 | G27: -1926.41 | H27: -1168.72 | I27: -3644.99 | J27: -3686.14 | K27: 4637.34 | L27: 975.91 | M27: -1101.99 | N27: -2911.4 | O27: 6981.99 | Q27: =SUM(D27:O27) -> -1092.47 | R27: =SUM(M27:O27)*4 -> 11874.4 | T27: 20 - Insurance | U27: 13 | V27: Contract & Services | W27: =SUMIF($B$1:$B$495,U27,$Q$1:$Q$495) -> 324765.62 | X27: =SUMIF($B$1:$B$495,U27,$R$1:$R$495) -> 344526.68
B28: 10 | C28: Administrative Fees | D28: 1600 | E28: 1600 | F28: 1400 | G28: 600 | H28: 1000 | I28: 600 | J28: 400 | K28: 1200 | L28: 1800 | M28: 600 | N28: 1000 | O28: 1400 | Q28: =SUM(D28:O28) -> 13200 | R28: =SUM(M28:O28)*4 -> 12000 | T28: 21 - Property Mangement fees | U28: 14 | V28: Utility | W28: =SUMIF($B$1:$B$495,U28,$Q$1:$Q$495) -> 55412.34 | X28: =SUMIF($B$1:$B$495,U28,$R$1:$R$495) -> 64601.52
B29: 10 | C29: Amenity Fee Income | D29: 0 | E29: 0 | F29: 0 | G29: 0 | H29: 0 | I29: 30 | J29: 0 | K29: 0 | L29: 0 | M29: 0 | N29: 0 | O29: 0 | Q29: =SUM(D29:O29) -> 30 | R29: =SUM(M29:O29)*4 -> 0 | T29: 22 - General & Administrative Expenses | U29: 15 | V29: Utility- Water | W29: =SUMIF($B$1:$B$495,U29,$Q$1:$Q$495) -> 156412.9 | X29: =SUMIF($B$1:$B$495,U29,$R$1:$R$495) -> 177613.48
B30: 10 | C30: Application Fees | D30: 3700 | E30: 2200 | F30: 1100 | G30: 2100 | H30: 1900 | I30: 1400 | J30: 300 | K30: 1400 | L30: 1100 | M30: 1200 | N30: 900 | O30: 1200 | Q30: =SUM(D30:O30) -> 18500 | R30: =SUM(M30:O30)*4 -> 13200 | T30: 23 - Other taxes/Permit license fees | U30: 16 | V30: Utility- Others | W30: =SUMIF($B$1:$B$495,U30,$Q$1:$Q$495) -> 15004.14 | X30: =SUMIF($B$1:$B$495,U30,$R$1:$R$495) -> 14451.04
B31: 6 | C31: Bad Debt Recovery | D31: 2086.62 | E31: 0 | F31: 978.74 | G31: -379.17 | H31: 1047.6 | I31: -315.02 | J31: -1716.32 | K31: -794.2 | L31: -464.8 | M31: 0 | N31: -567.86 | O31: -53.76 | Q31: =SUM(D31:O31) -> -178.17 | R31: =SUM(M31:O31)*4 -> -2486.48 | T31: 24 - NOI | U31: 17 | V31: Marketing | W31: =SUMIF($B$1:$B$495,U31,$Q$1:$Q$495) -> 99450.99 | X31: =SUMIF($B$1:$B$495,U31,$R$1:$R$495) -> 110734.28
B32: 10 | C32: Carport/Garages/Parking Income | D32: 580 | E32: 580 | F32: 612.26 | G32: 683.22 | H32: 680 | I32: 847.74 | J32: 920 | K32: 980 | L32: 931.67 | M32: 1000.97 | N32: 910.64 | O32: 1030 | Q32: =SUM(D32:O32) -> 9756.5 | R32: =SUM(M32:O32)*4 -> 11766.44 | T32: 1 - Market Rent Potential | U32: 18 | V32: Payroll | W32: =SUMIF($B$1:$B$495,U32,$Q$1:$Q$495) -> 452335.06 | X32: =SUMIF($B$1:$B$495,U32,$R$1:$R$495) -> 478699.88
B33: 10 | C33: Damages Income | D33: 556.83 | E33: 80 | F33: 65 | G33: 1296 | H33: 2646.24 | I33: 937.38 | J33: 64.21 | K33: 3050.93 | L33: 2.93 | M33: 1260 | N33: 781.59 | O33: 640 | Q33: =SUM(D33:O33) -> 11381.11 | R33: =SUM(M33:O33)*4 -> 10726.36 | T33: 2 - Increase in Rent from Renovation | U33: 19 | V33: RE Taxes | W33: =SUMIF($B$1:$B$495,U33,$Q$1:$Q$495) -> 517420.94 | X33: =SUMIF($B$1:$B$495,U33,$R$1:$R$495) -> 515612.56
B34: 10 | C34: Interest Income | D34: 2.88 | E34: 4.13 | F34: 3.45 | G34: 6.18 | H34: 8.75 | I34: 5.67 | J34: 4.14 | K34: 4.97 | L34: 7.75 | M34: 8.44 | N34: 3.63 | O34: 2.69 | Q34: =SUM(D34:O34) -> 62.68 | R34: =SUM(M34:O34)*4 -> 59.04 | T34: 3 - Loss to Lease | U34: 20 | V34: Insurance | W34: =SUMIF($B$1:$B$495,U34,$Q$1:$Q$495) -> 287361.82 | X34: =SUMIF($B$1:$B$495,U34,$R$1:$R$495) -> 285043.88
B35: 10 | C35: Key & Access Card Income | D35: 385 | E35: 300 | F35: 150 | G35: 150 | H35: 30 | I35: 0 | J35: 60 | K35: 0 | L35: 30 | M35: 0 | N35: 60 | O35: 0 | Q35: =SUM(D35:O35) -> 1165 | R35: =SUM(M35:O35)*4 -> 240 | T35: 4 - Vacancy | U35: 21 | V35: Property Mangement fees | W35: =SUMIF($B$1:$B$495,U35,$Q$1:$Q$495) -> 108042.23 | X35: =SUMIF($B$1:$B$495,U35,$R$1:$R$495) -> 107512.8 | Y35: =W35/W18 -> 0.028101029
B36: 10 | C36: Late Charges | D36: 3581.7 | E36: 4964.95 | F36: 5837.64 | G36: 6769.3 | H36: 5249.24 | I36: 6326.63 | J36: 7986.49 | K36: 5945.33 | L36: 6359.74 | M36: 6228.59 | N36: 5930.84 | O36: 6711.39 | Q36: =SUM(D36:O36) -> 71891.84 | R36: =SUM(M36:O36)*4 -> 75483.28 | T36: 5 - Concession/Discount | U36: 22 | V36: General & Administrative Expenses | W36: =SUMIF($B$1:$B$495,U36,$Q$1:$Q$495) -> 95425.62 | X36: =SUMIF($B$1:$B$495,U36,$R$1:$R$495) -> 120435.84
B37: 10 | C37: Lease Violation Income | D37: 2804.02 | E37: 150 | F37: 25.01 | G37: 0 | H37: 194.52 | I37: 3382 | J37: 0 | K37: 5234.9 | L37: -626 | M37: 4867.38 | N37: 2754 | O37: 3277 | Q37: =SUM(D37:O37) -> 22062.83 | R37: =SUM(M37:O37)*4 -> 43593.52 | T37: 6 - Bad Debt | U37: 23 | V37: Other taxes/Permit license fees | W37: =SUMIF($B$1:$B$495,U37,$Q$1:$Q$495) -> 20020.2 | X37: =SUMIF($B$1:$B$495,U37,$R$1:$R$495) -> 36049.12
B38: 10 | C38: Legal & Collections | D38: 60 | E38: 367.81 | F38: 700 | G38: 400 | H38: 525 | I38: 935 | J38: 672.87 | K38: 1137.13 | L38: 2345 | M38: 2470 | N38: 2910 | O38: 3180.63 | Q38: =SUM(D38:O38) -> 15703.44 | R38: =SUM(M38:O38)*4 -> 34242.52 | T38: 7 - Non Revenue Units | V38: Operating Expenses | W38: =SUM(W25:W37) -> 2305948.8 | X38: =SUM(X25:X37) -> 2424530.1
B39: 10 | C39: Miscellaneous Income | D39: 297.58 | E39: -325.33 | F39: 200 | G39: 0 | H39: 878.02 | I39: 0 | J39: 0 | K39: 0 | L39: 0 | M39: 0 | N39: 0 | O39: 0 | Q39: =SUM(D39:O39) -> 1050.27 | R39: =SUM(M39:O39)*4 -> 0 | T39: 8 - Utility Reimbursements
B40: 10 | C40: NSF Check Fees | D40: -50 | E40: 0 | F40: 50 | G40: 100 | H40: 50 | I40: 100 | J40: 50 | K40: 0 | L40: 300 | M40: 250 | N40: 200 | O40: 0 | Q40: =SUM(D40:O40) -> 1050 | R40: =SUM(M40:O40)*4 -> 1800 | T40: 9 - Other Reimbursements | V40: Net Operating Income (NOI) | W40: =W22-W38 -> 2010190 | X40: =X22-X38 -> 1875961.7
B41: 10 | C41: Pet Fees | D41: 400 | E41: 400 | F41: 0 | G41: 0 | H41: 400 | I41: 400 | J41: 0 | K41: 0 | L41: 400 | M41: 800 | N41: 0 | O41: 0 | Q41: =SUM(D41:O41) -> 2800 | R41: =SUM(M41:O41)*4 -> 3200 | T41: 10 - Other Income | U41: 25 | V41: Replacement Reserve | W41: =SUMIF($B$1:$B$495,U41,$Q$1:$Q$495) -> 0 | X41: =SUMIF($B$1:$B$495,U41,$R$1:$R$495) -> 0
B42: 10 | C42: Pet Rent | D42: 405.18 | E42: 405 | F42: 420.33 | G42: 439.17 | H42: 463.06 | I42: 483.23 | J42: 499.17 | K42: 457.42 | L42: 355.81 | M42: 482.5 | N42: 492.9 | O42: 541.61 | Q42: =SUM(D42:O42) -> 5445.38 | R42: =SUM(M42:O42)*4 -> 6068.04 | T42: 11 - Repair & Maintenance | U42: 24 | V42: NOI as per T 12 | W42: =SUMIF($B$1:$B$495,U42,$Q$1:$Q$495) -> 2010190 | X42: =SUMIF($B$1:$B$495,U42,$R$1:$R$495) -> 1875961.7
B43: 10 | C43: Renter's Insurance Income | D43: 800 | E43: 1650 | F43: 1550 | G43: 1900 | H43: 2050 | I43: 2050 | J43: 1878.16 | K43: 1850 | L43: 2050 | M43: 1850 | N43: 1729.35 | O43: 2550 | Q43: =SUM(D43:O43) -> 21907.51 | R43: =SUM(M43:O43)*4 -> 24517.4 | T43: 12 - Cleaning & Decorating
B44: 8 | C44: Electricity - Reimbursement | D44: 1761.77 | E44: 2116.34 | F44: 2264.05 | G44: 2234.37 | H44: 2542.25 | I44: 2671.2 | J44: 2883.65 | K44: 2878.46 | L44: 2739.78 | M44: 3141.98 | N44: 2756.26 | O44: 3188.31 | Q44: =SUM(D44:O44) -> 31178.42 | R44: =SUM(M44:O44)*4 -> 36346.2 | T44: 13 - Contract & Services
B45: 8 | C45: Water - Reimbursement | D45: 9808 | E45: 13755.24 | F45: 10460.16 | G45: 10561.72 | H45: 10893.75 | I45: 12039.25 | J45: 12405.43 | K45: 13191.56 | L45: 12018.49 | M45: 12264.57 | N45: 10461.52 | O45: 12880.3 | Q45: =SUM(D45:O45) -> 140739.99 | R45: =SUM(M45:O45)*4 -> 142425.56 | T45: 14 - Utility- Electricity
B46: 9 | C46: Trash - Reimbursement | D46: 3853.6 | E46: 4030.46 | F46: 4156.01 | G46: 4372.9 | H46: 5020.71 | I46: 4615.66 | J46: 4710.06 | K46: 5399.55 | L46: 4655.8 | M46: 4759.46 | N46: 5217.44 | O46: 4847.41 | Q46: =SUM(D46:O46) -> 55639.06 | R46: =SUM(M46:O46)*4 -> 59297.24 | T46: 15 - Utility- Water
B47: 9 | C47: Pest - Reimbursement | D47: 1480.22 | E47: 1497.33 | F47: 1472.14 | G47: 1582.45 | H47: 1690.66 | I47: 1732.26 | J47: 1646.93 | K47: 1619.23 | L47: 1659.56 | M47: 1665.73 | N47: 1679.88 | O47: 1715.74 | Q47: =SUM(D47:O47) -> 19442.13 | R47: =SUM(M47:O47)*4 -> 20245.4 | T47: 16 - Utility- Others
B48: 9 | C48: VCR Fees - Reimbursement | D48: 0 | E48: 60 | F48: 0 | G48: 110 | H48: 110 | I48: 0 | J48: 0 | K48: 220 | L48: 170 | M48: 440 | N48: 220 | O48: 110 | Q48: =SUM(D48:O48) -> 1440 | R48: =SUM(M48:O48)*4 -> 3080 | T48: 17 - Marketing
B49: 9 | C49: Start Up Fee - Reimbursement | D49: 125 | E49: 175 | F49: 50 | G49: 270 | H49: 180 | I49: 240 | J49: 90 | K49: 90 | L49: 120 | M49: 120 | N49: 150 | O49: 360 | Q49: =SUM(D49:O49) -> 1970 | R49: =SUM(M49:O49)*4 -> 2520 | T49: 18 - Payroll
B50: 9 | C50: Monthly Statement Fee Reimb. | D50: 1717.05 | E50: 1835.1 | F50: 1834.29 | G50: 1839.28 | H50: 1857.66 | I50: 1895.93 | J50: 1826.24 | K50: 1898.21 | L50: 1852.93 | M50: 1837.09 | N50: 1684.68 | O50: 1794.81 | Q50: =SUM(D50:O50) -> 21873.27 | R50: =SUM(M50:O50)*4 -> 21266.32 | T50: 19 - RE Taxes
B51: 10 | C51: Storage Unit Income | D51: 0 | E51: 600 | F51: 0 | G51: 200 | H51: 250 | I51: 300 | J51: 300 | K51: 300 | L51: 300 | M51: 300 | N51: 270.97 | O51: 250 | Q51: =SUM(D51:O51) -> 3070.97 | R51: =SUM(M51:O51)*4 -> 3283.88 | T51: 20 - Insurance
C52: TOTAL OTHER PROPERTY INCOME | D52: 36063.72 | E52: 38139.93 | F52: 32278.85 | G52: 33309.01 | H52: 38498.74 | I52: 37031.94 | J52: 31294.89 | K52: 50700.83 | L52: 39084.57 | M52: 44444.72 | N52: 36634.44 | O52: 52608.12 | Q52: =SUM(D52:O52) -> 470089.76 | R52: =SUM(M52:O52)*4 -> 534749.12 | T52: 21 - Property Mangement fees
C53: TOTAL OPERATING INCOME | D53: 359202.58 | E53: 375081.53 | F53: 363754.68 | G53: 364969.29 | H53: 365266.95 | I53: 361647.98 | J53: 343715.59 | K53: 343817.81 | L53: 363559.51 | M53: 355036.28 | N53: 350390.06 | O53: 369696.61 | Q53: =SUM(D53:O53) -> 4316138.9 | R53: =SUM(M53:O53)*4 -> 4300491.8 | T53: 22 - General & Administrative Expenses
Q54: =SUM(D54:O54) -> 0 | R54: =SUM(M54:O54)*4 -> 0 | T54: 23 - Other taxes/Permit license fees
C55: EXPENSE | Q55: =SUM(D55:O55) -> 0 | R55: =SUM(M55:O55)*4 -> 0 | T55: 24 - NOI
C56: ADMINISTRATIVE EXPENSE | Q56: =SUM(D56:O56) -> 0 | R56: =SUM(M56:O56)*4 -> 0 | T56: 1 - Market Rent Potential
C57: MANAGEMENT FEE EXPENSE | Q57: =SUM(D57:O57) -> 0 | R57: =SUM(M57:O57)*4 -> 0 | T57: 2 - Increase in Rent from Renovation
B58: 21 | C58: Management Fee Expense | D58: 9023.02 | E58: 9083.45 | F58: 8764.81 | G58: 8920.53 | H58: 9097.93 | I58: 8714.92 | J58: 8301.42 | K58: 8595.32 | L58: 10662.63 | M58: 8875.89 | N58: 8759.87 | O58: 9242.44 | Q58: =SUM(D58:O58) -> 108042.23 | R58: =SUM(M58:O58)*4 -> 107512.8 | T58: 3 - Loss to Lease
C59: TOTAL MANAGEMENT FEE EXPENSE | D59: 9023.02 | E59: 9083.45 | F59: 8764.81 | G59: 8920.53 | H59: 9097.93 | I59: 8714.92 | J59: 8301.42 | K59: 8595.32 | L59: 10662.63 | M59: 8875.89 | N59: 8759.87 | O59: 9242.44 | Q59: =SUM(D59:O59) -> 108042.23 | R59: =SUM(M59:O59)*4 -> 107512.8 | T59: 4 - Vacancy
C60: OFFICE ADMINISTRATION | Q60: =SUM(D60:O60) -> 0 | R60: =SUM(M60:O60)*4 -> 0 | T60: 5 - Concession/Discount
B61: 22 | C61: Office Administration | D61: 0 | E61: 0 | F61: 0 | G61: 0 | H61: 0 | I61: 0 | J61: 0 | K61: 0 | L61: 0 | M61: 0 | N61: 0 | O61: 640 | Q61: =SUM(D61:O61) -> 640 | R61: =SUM(M61:O61)*4 -> 2560 | T61: 6 - Bad Debt
B62: 22 | C62: Bank Charge | D62: 1253.85 | E62: 374.84 | F62: 106.81 | G62: 410.47 | H62: 444.24 | I62: 403.9 | J62: 379.69 | K62: 287.18 | L62: 461.23 | M62: 501.19 | N62: 677.84 | O62: 689.93 | Q62: =SUM(D62:O62) -> 5991.17 | R62: =SUM(M62:O62)*4 -> 7475.84 | T62: 7 - Non Revenue Units
B63: 22 | C63: Technology - Software | D63: 2226.94 | E63: 2845.6 | F63: 2054.1 | G63: 2367.42 | H63: 2315.83 | I63: 2563.29 | J63: 1458.03 | K63: 3178.95 | L63: 2647.38 | M63: 2139.6 | N63: 2687.02 | O63: 2247.67 | Q63: =SUM(D63:O63) -> 28731.83 | R63: =SUM(M63:O63)*4 -> 28297.16 | T63: 8 - Utility Reimbursements
B64: 22 | C64: Technology - Repairs | D64: 364.18 | E64: 364.34 | F64: 364.34 | G64: 364.34 | H64: 448.11 | I64: 396.62 | J64: 395.85 | K64: 350 | L64: 14.86 | M64: 758.47 | N64: 364.21 | O64: 324.24 | Q64: =SUM(D64:O64) -> 4509.56 | R64: =SUM(M64:O64)*4 -> 5787.68 | T64: 9 - Other Reimbursements
B65: 22 | C65: CORP - IT Hardware | D65: 0 | E65: 376.92 | F65: 0 | G65: 0 | H65: 0 | I65: 0 | J65: 0 | K65: 0 | L65: 0 | M65: 0 | N65: 0 | O65: 0 | Q65: =SUM(D65:O65) -> 376.92 | R65: =SUM(M65:O65)*4 -> 0 | T65: 10 - Other Income
B66: 22 | C66: Corp - Dues & Subscriptions | D66: 0 | E66: 0 | F66: 0 | G66: 0 | H66: 0 | I66: 0 | J66: 0 | K66: 0 | L66: 481 | M66: 0 | N66: 0 | O66: 0 | Q66: =SUM(D66:O66) -> 481 | R66: =SUM(M66:O66)*4 -> 0 | T66: 11 - Repair & Maintenance
B67: 23 | C67: Licenses, Fees & Permits | D67: 10161.92 | E67: 481 | F67: 365 | G67: 0 | H67: 0 | I67: 149 | J67: 149 | K67: -298 | L67: 0 | M67: 991 | N67: 3808.14 | O67: 4213.14 | Q67: =SUM(D67:O67) -> 20020.2 | R67: =SUM(M67:O67)*4 -> 36049.12 | T67: 12 - Cleaning & Decorating
B68: 22 | C68: Office Supplies | D68: 200.54 | E68: 200.8 | F68: 72.46 | G68: 0 | H68: 795.73 | I68: 500 | J68: -500 | K68: 528.12 | L68: -500 | M68: 0 | N68: 8.64 | O68: 72 | Q68: =SUM(D68:O68) -> 1378.29 | R68: =SUM(M68:O68)*4 -> 322.56 | T68: 13 - Contract & Services
B69: 22 | C69: Postage & Delivery | D69: 0 | E69: 1.4 | F69: 8.28 | G69: 68.55 | H69: 17.45 | I69: 7.9 | J69: 10.32 | K69: 0 | L69: 2.05 | M69: 2.05 | N69: 49.14 | O69: 47.27 | Q69: =SUM(D69:O69) -> 214.41 | R69: =SUM(M69:O69)*4 -> 393.84 | T69: 14 - Utility- Electricity
B70: 22 | C70: Printing/Copies/Film | D70: 40.76 | E70: 25 | F70: 0 | G70: -13.79 | H70: 0 | I70: -25 | J70: 0 | K70: 0 | L70: 0 | M70: 0 | N70: 25 | O70: -25 | Q70: =SUM(D70:O70) -> 26.97 | R70: =SUM(M70:O70)*4 -> 0 | T70: 15 - Utility- Water
B71: 22 | C71: Telephone | D71: 1090.34 | E71: 761.92 | F71: 246.18 | G71: 776.26 | H71: 500 | I71: 1573.54 | J71: -328.16 | K71: 983.83 | L71: 974.34 | M71: 1257.38 | N71: 2039.79 | O71: 974.29 | Q71: =SUM(D71:O71) -> 10849.71 | R71: =SUM(M71:O71)*4 -> 17085.84 | T71: 16 - Utility- Others
B72: 22 | C72: Telephone - Cell Phones | D72: 250 | E72: 250 | F72: 200 | G72: 250 | H72: 309.29 | I72: 660.83 | J72: 685.83 | K72: 302.63 | L72: 252.19 | M72: 252.19 | N72: 385.59 | O72: 252.29 | Q72: =SUM(D72:O72) -> 4050.84 | R72: =SUM(M72:O72)*4 -> 3560.28 | T72: 17 - Marketing
... B74: 22 | C74: Internet | D74: 613.49 | E74: 613.49 | F74: 613.49 | G74: 613.49 | H74: 1194.04 | I74: 93.7 | J74: 608 | K74: 39.67 | L74: 626.18 | M74: 630.25 | N74: 1252.36 | O74: 626.18 | Q74: =SUM(D74:O74) -> 7524.34 | R74: =SUM(M74:O74)*4 -> 10035.16 | T74: 19 - RE Taxes
C75: TOTAL OFFICE ADMINISTRATION | D75: 16751.59 | E75: 6774.88 | F75: 4578.86 | G75: 5384.94 | H75: 6575.33 | I75: 6874.72 | J75: 2998.56 | K75: 5920.58 | L75: 5034.68 | M75: 7099.62 | N75: 11937.63 | O75: 9708.53 | Q75: =SUM(D75:O75) -> 89639.92 | R75: =SUM(M75:O75)*4 -> 114983.12 | T75: 20 - Insurance
C76: RESIDENT RELATED EXPENSES | Q76: =SUM(D76:O76) -> 0 | R76: =SUM(M76:O76)*4 -> 0 | T76: 21 - Property Mangement fees
B77: 22 | C77: Collection & Evictions | D77: 175 | E77: 2765 | F77: 215 | G77: 1440 | H77: 833.5 | I77: 2415 | J77: 532 | K77: 975 | L77: 1346 | M77: 3500 | N77: 3399 | O77: -967 | Q77: =SUM(D77:O77) -> 16628.5 | R77: =SUM(M77:O77)*4 -> 23728 | T77: 22 - General & Administrative Expenses
B78: 22 | C78: Resident Screening | D78: 786.6 | E78: 964.6 | F78: 989.8 | G78: 869.6 | H78: 1068.2 | I78: 647.8 | J78: 995 | K78: 612.2 | L78: 710 | M78: 931.2 | N78: 1510.2 | O78: 1205.2 | Q78: =SUM(D78:O78) -> 11290.4 | R78: =SUM(M78:O78)*4 -> 14586.4 | T78: 23 - Other taxes/Permit license fees
B79: 22 | C79: Resident Relations | D79: 0 | E79: 0 | F79: 258.41 | G79: 0 | H79: 0 | I79: 0 | J79: 0 | K79: 0 | L79: 165.06 | M79: 0 | N79: 675.33 | O79: 121.53 | Q79: =SUM(D79:O79) -> 1220.33 | R79: =SUM(M79:O79)*4 -> 3187.44 | T79: 24 - NOI
C80: TOTAL RESIDENT RELATED EXPENSES | D80: 961.6 | E80: 3729.6 | F80: 1463.21 | G80: 2309.6 | H80: 1901.7 | I80: 3062.8 | J80: 1527 | K80: 1587.2 | L80: 2221.06 | M80: 4431.2 | N80: 5584.53 | O80: 359.73 | Q80: =SUM(D80:O80) -> 29139.23 | R80: =SUM(M80:O80)*4 -> 41501.84 | T80: 1 - Market Rent Potential
C81: ADVERTISING | Q81: =SUM(D81:O81) -> 0 | R81: =SUM(M81:O81)*4 -> 0 | T81: 2 - Increase in Rent from Renovation
B82: 17 | C82: Internet Ads | D82: 5669.25 | E82: 5994.25 | F82: 5880.73 | G82: 5807.51 | H82: 5791.25 | I82: 4502.25 | J82: 4320.25 | K82: 5871.25 | L82: 7056.42 | M82: 9029.58 | N82: 3875.61 | O82: 6135 | Q82: =SUM(D82:O82) -> 69933.35 | R82: =SUM(M82:O82)*4 -> 76160.76 | T82: 3 - Loss to Lease
B83: 17 | C83: Signs | D83: 0 | E83: 0 | F83: 0 | G83: 0 | H83: 0 | I83: 21.49 | J83: 0 | K83: 321.86 | L83: 0 | M83: 0 | N83: 0 | O83: 0 | Q83: =SUM(D83:O83) -> 343.35 | R83: =SUM(M83:O83)*4 -> 0 | T83: 4 - Vacancy
B84: 17 | C84: Websites/Online Leasing | D84: 1541.25 | E84: 1541.25 | F84: 1541.25 | G84: 1541.25 | H84: 1541.25 | I84: 1541.25 | J84: 1541.25 | K84: 631.25 | L84: 1541.25 | M84: 1585.45 | N84: 1952.6 | O84: 1887.59 | Q84: =SUM(D84:O84) -> 18386.89 | R84: =SUM(M84:O84)*4 -> 21702.56 | T84: 5 - Concession/Discount
C85: TOTAL ADVERTISING | D85: 7210.5 | E85: 7535.5 | F85: 7421.98 | G85: 7348.76 | H85: 7332.5 | I85: 6064.99 | J85: 5861.5 | K85: 6824.36 | L85: 8597.67 | M85: 10615.03 | N85: 5828.21 | O85: 8022.59 | Q85: =SUM(D85:O85) -> 88663.59 | R85: =SUM(M85:O85)*4 -> 97863.32 | T85: 6 - Bad Debt
C86: MARKETING | Q86: =SUM(D86:O86) -> 0 | R86: =SUM(M86:O86)*4 -> 0 | T86: 7 - Non Revenue Units
B87: 17 | C87: Marketing | D87: 0 | E87: 0 | F87: 32.35 | G87: 0 | H87: 0 | I87: 745.13 | J87: 0 | K87: 0 | L87: 0 | M87: 281.41 | N87: 0 | O87: 0 | Q87: =SUM(D87:O87) -> 1058.89 | R87: =SUM(M87:O87)*4 -> 1125.64 | T87: 8 - Utility Reimbursements
B88: 17 | C88: Brochures / Branding | D88: 4.26 | E88: 4.26 | F88: 4.26 | G88: -12.78 | H88: 0 | I88: 0 | J88: 0 | K88: 0 | L88: 0 | M88: 0 | N88: 0 | O88: 0 | Q88: =SUM(D88:O88) -> 0 | R88: =SUM(M88:O88)*4 -> 0 | T88: 9 - Other Reimbursements
B89: 17 | C89: Corporate Outreach | D89: 0 | E89: 0 | F89: 0 | G89: 0 | H89: 0 | I89: 0 | J89: 0 | K89: 0 | L89: 0 | M89: 0 | N89: 0 | O89: 45.45 | Q89: =SUM(D89:O89) -> 45.45 | R89: =SUM(M89:O89)*4 -> 181.8 | T89: 10 - Other Income
B90: 17 | C90: Locator Fees | D90: 39 | E90: 711.5 | F90: 39 | G90: 458 | H90: 39 | I90: 0 | J90: 427 | K90: 39 | L90: 39 | M90: 39 | N90: 39 | O90: 30 | Q90: =SUM(D90:O90) -> 1899.5 | R90: =SUM(M90:O90)*4 -> 432 | T90: 11 - Repair & Maintenance
B91: 17 | C91: Model Apartment | D91: 0 | E91: 73.86 | F91: 0 | G91: 0 | H91: 0 | I91: 0 | J91: 0 | K91: 0 | L91: 0 | M91: 0 | N91: 0 | O91: 0 | Q91: =SUM(D91:O91) -> 73.86 | R91: =SUM(M91:O91)*4 -> 0 | T91: 12 - Cleaning & Decorating
B92: 17 | C92: Resident Referrals | D92: 0 | E92: 1000 | F92: 0 | G92: 0 | H92: 0 | I92: 0 | J92: 0 | K92: 0 | L92: 0 | M92: 0 | N92: 750 | O92: 1000 | Q92: =SUM(D92:O92) -> 2750 | R92: =SUM(M92:O92)*4 -> 7000 | T92: 13 - Contract & Services
B93: 17 | C93: Survey | D93: 200.26 | E93: 200.26 | F93: 200.26 | G93: 200.26 | H93: 200.26 | I93: 200.26 | J93: 200.26 | K93: 200.26 | L93: 200.26 | M93: 200.26 | N93: 200.26 | O93: 200.26 | Q93: =SUM(D93:O93) -> 2403.12 | R93: =SUM(M93:O93)*4 -> 2403.12 | T93: 14 - Utility- Electricity
B94: 17 | C94: Market Data | D94: 83.98 | E94: 83.98 | F94: 768.58 | G94: 750.54 | H94: 82.12 | I94: 88.82 | J94: 88.82 | K94: 88.82 | L94: 88.82 | M94: 88.82 | N94: 170.5 | O94: 172.78 | Q94: =SUM(D94:O94) -> 2556.58 | R94: =SUM(M94:O94)*4 -> 1728.4 | T94: 15 - Utility- Water
C95: TOTAL MARKETING | D95: 327.5 | E95: 2073.86 | F95: 1044.45 | G95: 1396.02 | H95: 321.38 | I95: 1034.21 | J95: 716.08 | K95: 328.08 | L95: 328.08 | M95: 609.49 | N95: 1159.76 | O95: 1448.49 | Q95: =SUM(D95:O95) -> 10787.4 | R95: =SUM(M95:O95)*4 -> 12870.96 | T95: 16 - Utility- Others
C96: TOTAL ADMINISTRATIVE EXPENSE | D96: 34274.21 | E96: 29197.29 | F96: 23273.31 | G96: 25359.85 | H96: 25228.84 | I96: 25751.64 | J96: 19404.56 | K96: 23255.54 | L96: 26844.12 | M96: 31631.23 | N96: 33270 | O96: 28781.78 | Q96: =SUM(D96:O96) -> 326272.37 | R96: =SUM(M96:O96)*4 -> 374732.04 | T96: 17 - Marketing
C97: PAYROLL & BENEFITS | Q97: =SUM(D97:O97) -> 0 | R97: =SUM(M97:O97)*4 -> 0 | T97: 18 - Payroll
C98: SALARIES & WAGES | Q98: =SUM(D98:O98) -> 0 | R98: =SUM(M98:O98)*4 -> 0 | T98: 19 - RE Taxes
B99: 18 | C99: Centralized Services | D99: 0 | E99: 0 | F99: 1341.94 | G99: 2600 | H99: 2600 | I99: 2600 | J99: 2600 | K99: 2600 | L99: 2600 | M99: 2600 | N99: 2600 | O99: 2600 | Q99: =SUM(D99:O99) -> 24741.94 | R99: =SUM(M99:O99)*4 -> 31200 | T99: 20 - Insurance
B100: 18 | C100: Office Salaries | D100: 13312.96 | E100: 13971.07 | F100: 13586.85 | G100: 8055.81 | H100: 11833.78 | I100: 8927.95 | J100: 9494.69 | K100: 12312.56 | L100: 7344.16 | M100: 9039.27 | N100: 12858.76 | O100: 10134.47 | Q100: =SUM(D100:O100) -> 130872.33 | R100: =SUM(M100:O100)*4 -> 128130 | T100: 21 - Property Mangement fees
B101: 18 | C101: Admin Overtime | D101: 38.25 | E101: 140.5 | F101: 227.9 | G101: 78.75 | H101: 324.9 | I101: 82.35 | J101: 35.55 | K101: 210.15 | L101: 502.99 | M101: 258.79 | N101: 148.2 | O101: 18.45 | Q101: =SUM(D101:O101) -> 2066.78 | R101: =SUM(M101:O101)*4 -> 1701.76 | T101: 22 - General & Administrative Expenses
B102: 18 | C102: Maintenance Salaries | D102: 8830.8 | E102: 9405.86 | F102: 9821.55 | G102: 9061.09 | H102: 14944.99 | I102: 10309.78 | J102: 12180.37 | K102: 14776.73 | L102: 9534.48 | M102: 10033.47 | N102: 19303.74 | O102: 6958.41 | Q102: =SUM(D102:O102) -> 135161.27 | R102: =SUM(M102:O102)*4 -> 145182.48 | T102: 23 - Other taxes/Permit license fees
B103: 18 | C103: Maintenance Overtime | D103: 73.06 | E103: 550.94 | F103: 115.87 | G103: 254.37 | H103: 194.56 | I103: 314.23 | J103: 294.88 | K103: 151.28 | L103: 18.15 | M103: 479.33 | N103: 433.55 | O103: 112.27 | Q103: =SUM(D103:O103) -> 2992.49 | R103: =SUM(M103:O103)*4 -> 4100.6 | T103: 24 - NOI
...

Sheet Rent Comp
A1: Property Id | B1: Map # | C1: Building Name | D1: Link to Website | E1: Address | F1: Rating | G1: Apartments.com Ad Level | H1: Common View Last 60 Days | I1: % Overlap with Subject Property | J1: Units | K1: Stories | L1: Yr Blt/Ren | M1: Avg SF | N1: mi Away | O1: Rent/SF | P1: Rent/Unit | Q1: Studio | R1: 1 bed | S1: SqFt | T1: Rent psf | U1: 2 Beds | V1: SqFt | W1: Rent psf | X1: 3 beds | Y1: SqFt | Z1: Rent psf | AA1: Occ % | AB1: Concess % | AE1: #3 Beds | AF1: Neighborhood
C6: Subject Property | O6: Actual rents from Rent Roll
C7: ='CFS-Main Page'!B2 -> The Grove on Southlake | D7: Link | E7: ='CFS-Main Page'!D2 -> 7290 Southlake Parkway Morrow, GA, 30260 | J7: =Units -> 260 | L7: ='CFS-Main Page'!D4 -> 2001 | O7: =Rent!J31 -> 1.3925691 | P7: =Rent!J30 -> 1447.9077 | R7: =Rent!G5 -> 1292.2824 | S7: =AVERAGE(Rent!I9:I10,Rent!I15:I16) -> 981.5 | T7: =R7/S7 -> 1.3166402 | U7: =Rent!I5 -> 1487.558 | V7: =AVERAGE(Rent!I11:I12) -> 825 | W7: =U7/V7 -> 1.8031006 | X7: =Rent!K5 -> 1643.8853 | Y7: =AVERAGE(Rent!I13:I14) -> 1127 | Z7: =X7/Y7 -> 1.4586383 | AA7: =Rent!H29 -> 0.91923077
C9: Comps
A10: 1 | C10: Fieldstone By Trion Living | D10: Link | E10: 2615 Mount Zion Parkway Jonesboro, GA 30236 | J10: 216 | L10: 2003 | N10: 1.75 | R10: 1288 | S10: 757 | T10: =R10/S10 -> 1.7014531 | U10: 1532 | V10: 1085 | W10: =U10/V10 -> 1.4119816 | X10: 1952 | Y10: 1341 | Z10: =X10/Y10 -> 1.4556301 | AA10: 0.958
A11: =A10+1 -> 2 | C11: Battle Creek Village Townhomes | D11: Link | E11: 1174 Battle Creek Road Jonesboro, GA 30236 | J11: 250 | L11: 2003 | N11: 1.07 | U11: 1715 | V11: 1216 | W11: =U11/V11 -> 1.4103618 | X11: 1850 | Y11: 1363 | Z11: =X11/Y11 -> 1.3573001 | AA11: 0.996
A12: =A11+1 -> 3 | C12: Novo Stockbridge | D12: Link | E12: 3151 Mount Zion Road Stockbridge, GA 30281 | J12: 294 | L12: 2023 | N12: 2.71 | R12: 1554 | S12: 756 | T12: =R12/S12 -> 2.0555556 | U12: 1790 | V12: 1176 | W12: =U12/V12 -> 1.5221088 | X12: 2160 | Y12: 1248 | Z12: =X12/Y12 -> 1.7307692 | AA12: 0.956
A13: =A12+1 -> 4 | C13: Rovena at Mt. Zion | D13: Link | E13: 7135 Mount Zion Circle Morrow, GA 30260 | J13: 384 | L13: 2025 | N13: 0.49 | R13: 1469 | S13: 693 | T13: =R13/S13 -> 2.1197691 | U13: 1774 | V13: 1024 | W13: =U13/V13 -> 1.7324219 | AA13: 0.904
A14: =A13+1 -> 5 | C14: Story Mt. Zion | D14: Link | E14: 2465 Richardson Parkway Morrow, GA 30260 | J14: 300 | L14: 2024 | N14: 1.35 | R14: 1503 | S14: 784 | T14: =R14/S14 -> 1.9170918 | U14: 1910 | V14: 1171 | W14: =U14/V14 -> 1.6310845 | X14: 2217 | Y14: 1248 | Z14: =X14/Y14 -> 1.7764423 | AA14: 0.957
Q28: Studio | R28: 1 Beds | S28: Sqft | T28: PSF | U28: 2 Beds | V28: Sqft | W28: PSF | X28: 3 Beds | Y28: Sqft | Z28: PSF
M29: A. | N29: Avg Rent of Comps | Q29: =AVERAGE(Q10:Q26) -> #DIV/0! | R29: =AVERAGE(R10:R26) -> 1453.5 | S29: =AVERAGE(S10:S26) -> 747.5 | T29: =AVERAGE(T10:T26) -> 1.9484674 | U29: =AVERAGE(U10:U26) -> 1744.2 | V29: =AVERAGE(V10:V26) -> 1134.4 | W29: =AVERAGE(W10:W26) -> 1.5415917 | X29: =AVERAGE(X10:X26) -> 2044.75 | ... Z29: =AVERAGE(Z10:Z26) -> 1.5800354
M30: B. | N30: Subject Prop Rent | Q30: =Q7 -> 0 | R30: =R7 -> 1292.2824 | S30: =S7 -> 981.5 | T30: =T7 -> 1.3166402 | U30: =U7 -> 1487.558 | V30: =V7 -> 825 | W30: =W7 -> 1.8031006 | X30: =X7 -> 1643.8853 | ... Z30: =Z7 -> 1.4586383
M32: C. | N32: C=A-B | Q32: =Q29-Q30 -> #DIV/0! | R32: =R29-R30 -> 161.21765 | T32: =T29-T30 -> 0.63182721 | U32: =U29-U30 -> 256.642 | W32: =W29-W30 -> -0.26150887 | X32: =X29-X30 -> 400.86466 | Z32: =Z29-Z30 -> 0.12139716
M33: *Source - Hello Data

Sheet Quick Comps
B1: Comp 1 | I1: Comp 2 | P1: Comp 3 | W1: Comp 4 | AD1: Comp 5 | AK1: Comp 6
B2: Units | D2: PIN/Parcel ID | I2: Units | K2: PIN/Parcel ID | P2: Units | R2: PIN/Parcel ID | W2: Units | Y2: PIN/Parcel ID | AD2: Units | AF2: PIN/Parcel ID | AK2: Units | AM2: PIN/Parcel ID
B3: Built in: | D3: Last Sales Date | I3: Built in: | K3: Last Sales Date | P3: Built in: | R3: Last Sales Date | W3: Built in: | Y3: Last Sales Date | AD3: Built in: | AF3: Last Sales Date | AK3: Built in: | AM3: Last Sales Date
B4: Managed By: | D4: Price / Unit | I4: Managed By: | K4: Price / Unit | P4: Managed By: | R4: Price / | W4: Managed By: | Y4: Price / | AD4: Managed By: | AF4: Price / | AK4: Managed By: | AM4: Price / Unit
B5: Rent Survey Date: | D5: Year Assessed | F5: Per Unit | I5: Rent Survey Date: | K5: Year Assessed | M5: Per Unit | P5: Rent Survey Date: | R5: Year Assessed | T5: Per Unit | W5: Rent Survey Date: | Y5: Year Assessed | AA5: Per Unit | AD5: Rent Survey Date: | AF5: Year Assessed | AH5: Per Unit | AK5: Rent Survey Date: | AM5: Year Assessed | AO5: Per Unit
B6: Occupancy: | D6: Land | F6: =E6/C2 -> #DIV/0! | I6: Occupancy: | K6: Land | M6: =L6/J2 -> #DIV/0! | P6: Occupancy: | R6: Land | T6: =S6/Q2 -> #DIV/0! | W6: Occupancy: | Y6: Land | AA6: =Z6/X2 -> #DIV/0! | AD6: Occupancy: | AF6: Land | AH6: =AG6/AE2 -> #DIV/0! | AK6: Occupancy: | AM6: Land | AO6: =AN6/AL2 -> #DIV/0!
B7: Last Rent Increase: | D7: Improvements | F7: =E7/C2 -> #DIV/0! | I7: Last Rent Increase: | K7: Improvements | M7: =L7/J2 -> #DIV/0! | P7: Last Rent Increase: | R7: Improvements | T7: =S7/Q2 -> #DIV/0! | W7: Last Rent Increase: | Y7: Improvements | AA7: =Z7/X2 -> #DIV/0! | AD7: Last Rent Increase: | AF7: Improvements | AH7: =AG7/AE2 -> #DIV/0! | AK7: Last Rent Increase: | AM7: Improvements | AO7: =AN7/AL2 -> #DIV/0!
B8: Concessions? | D8: Total | E8: =SUM(E6:E7) -> 0 | F8: =SUM(F6:F7) -> #DIV/0! | I8: Concessions? | K8: Total | L8: =SUM(L6:L7) -> 0 | M8: =SUM(M6:M7) -> #DIV/0! | P8: Concessions? | R8: Total | S8: =SUM(S6:S7) -> 0 | T8: =SUM(T6:T7) -> #DIV/0! | W8: Concessions? | Y8: Total | Z8: =SUM(Z6:Z7) -> 0 | AA8: =SUM(AA6:AA7) -> #DIV/0! | AD8: Concessions? | AF8: Total | AG8: =SUM(AG6:AG7) -> 0 | AH8: =SUM(AH6:AH7) -> #DIV/0! | AK8: Concessions? | AM8: Total | AN8: =SUM(AN6:AN7) -> 0 | AO8: =SUM(AO6:AO7) -> #DIV/0!
B9: Income Restricted? | D9: Tax District | I9: Income Restricted? | K9: Tax District | P9: Income Restricted? | R9: Tax District | W9: Income Restricted? | Y9: Tax District | AD9: Income Restricted? | AF9: Tax District | AK9: Income Restricted? | AM9: Tax District
B10: Tax Credit? | D10: Zoning | I10: Tax Credit? | K10: Zoning | P10: Tax Credit? | R10: Zoning | W10: Tax Credit? | Y10: Zoning | AD10: Tax Credit? | AF10: Zoning | AK10: Tax Credit? | AM10: Zoning
B11: Building Style | D11: Acres | I11: Building Style | K11: Acres | P11: Building Style | R11: Acres | W11: Building Style | Y11: Acres | AD11: Building Style | AF11: Acres | AK11: Building Style | AM11: Acres
B12: Distance from Subject | C12: 0 | D12: Density | E12: =IFERROR(C2/E11,0) -> 0 | I12: Distance from Subject | K12: Density | L12: =IFERROR(J2/L11,0) -> 0 | P12: Distance from Subject | R12: Density | S12: =IFERROR(Q2/S11,0) -> 0 | W12: Distance from Subject | Y12: Density | Z12: =IFERROR(X2/Z11,0) -> 0 | AD12: Distance from Subject | AF12: Density | AG12: =IFERROR(AE2/AG11,0) -> 0 | AK12: Distance from Subject | AM12: Density | AN12: =IFERROR(AL2/AN11,0) -> 0
B14: Studio | I14: Studio | P14: Studio | W14: Studio | AD14: Studio | AK14: Studio
B15: Unit Type | C15: Units | D15: Square Feet | E15: Base Rent | F15: PSF | G15: % of Mix | I15: Unit Type | J15: Units | K15: Square Feet | L15: Base Rent | M15: PSF | N15: % of Mix | P15: Unit Type | Q15: Units | R15: Square Feet | S15: Base Rent | T15: PSF | U15: % of Mix | W15: Unit Type | X15: Units | Y15: Square Feet | Z15: Base Rent | AA15: PSF | AB15: % of Mix | AD15: Unit Type | AE15: Units | AF15: Square Feet | AG15: Base Rent | AH15: PSF | AI15: % of Mix | AK15: Unit Type | AL15: Units | AM15: Square Feet | AN15: Base Rent | AO15: PSF | AP15: % of Mix
B16: 0x1 | F16: =IFERROR(E16/D16,0) -> 0 | G16: =C16/$C$2 -> #DIV/0! | M16: =IFERROR(L16/K16,0) -> 0 | N16: =J16/J$2 -> #DIV/0! | T16: =IFERROR(S16/R16,0) -> 0 | U16: =Q16/Q$2 -> #DIV/0! | AA16: =IFERROR(Z16/Y16,0) -> 0 | AB16: =X16/X$2 -> #DIV/0! | AH16: =IFERROR(AG16/AF16,0) -> 0 | AI16: =AE16/AE$2 -> #DIV/0! | AO16: =IFERROR(AN16/AM16,0) -> 0 | AP16: =AL16/AL$2 -> #DIV/0!
B17: 0x1 | F17: =IFERROR(E17/D17,0) -> 0 | G17: =C17/$C$2 -> #DIV/0! | M17: =IFERROR(L17/K17,0) -> 0 | N17: =J17/J$2 -> #DIV/0! | T17: =IFERROR(S17/R17,0) -> 0 | U17: =Q17/Q$2 -> #DIV/0! | AA17: =IFERROR(Z17/Y17,0) -> 0 | AB17: =X17/X$2 -> #DIV/0! | AH17: =IFERROR(AG17/AF17,0) -> 0 | AI17: =AE17/AE$2 -> #DIV/0! | AO17: =IFERROR(AN17/AM17,0) -> 0 | AP17: =AL17/AL$2 -> #DIV/0!
B18: 0x1 | F18: =IFERROR(E18/D18,0) -> 0 | G18: =C18/$C$2 -> #DIV/0! | M18: =IFERROR(L18/K18,0) -> 0 | N18: =J18/J$2 -> #DIV/0! | T18: =IFERROR(S18/R18,0) -> 0 | U18: =Q18/Q$2 -> #DIV/0! | AA18: =IFERROR(Z18/Y18,0) -> 0 | AB18: =X18/X$2 -> #DIV/0! | AH18: =IFERROR(AG18/AF18,0) -> 0 | AI18: =AE18/AE$2 -> #DIV/0! | AO18: =IFERROR(AN18/AM18,0) -> 0 | AP18: =AL18/AL$2 -> #DIV/0!
B19: 0x1 | F19: =IFERROR(E19/D19,0) -> 0 | G19: =C19/$C$2 -> #DIV/0! | M19: =IFERROR(L19/K19,0) -> 0 | N19: =J19/J$2 -> #DIV/0! | T19: =IFERROR(S19/R19,0) -> 0 | U19: =Q19/Q$2 -> #DIV/0! | AA19: =IFERROR(Z19/Y19,0) -> 0 | AB19: =X19/X$2 -> #DIV/0! | AH19: =IFERROR(AG19/AF19,0) -> 0 | AI19: =AE19/AE$2 -> #DIV/0! | AO19: =IFERROR(AN19/AM19,0) -> 0 | AP19: =AL19/AL$2 -> #DIV/0!
B20: 0x1 | F20: =IFERROR(E20/D20,0) -> 0 | G20: =C20/$C$2 -> #DIV/0! | M20: =IFERROR(L20/K20,0) -> 0 | N20: =J20/J$2 -> #DIV/0! | T20: =IFERROR(S20/R20,0) -> 0 | U20: =Q20/Q$2 -> #DIV/0! | AA20: =IFERROR(Z20/Y20,0) -> 0 | AB20: =X20/X$2 -> #DIV/0! | AH20: =IFERROR(AG20/AF20,0) -> 0 | AI20: =AE20/AE$2 -> #DIV/0! | AO20: =IFERROR(AN20/AM20,0) -> 0 | AP20: =AL20/AL$2 -> #DIV/0!
B21: 0x1 | F21: =IFERROR(E21/D21,0) -> 0 | G21: =C21/$C$2 -> #DIV/0! | M21: =IFERROR(L21/K21,0) -> 0 | N21: =J21/J$2 -> #DIV/0! | T21: =IFERROR(S21/R21,0) -> 0 | U21: =Q21/Q$2 -> #DIV/0! | AA21: =IFERROR(Z21/Y21,0) -> 0 | AB21: =X21/X$2 -> #DIV/0! | AH21: =IFERROR(AG21/AF21,0) -> 0 | AI21: =AE21/AE$2 -> #DIV/0! | AO21: =IFERROR(AN21/AM21,0) -> 0 | AP21: =AL21/AL$2 -> #DIV/0!
B22: 0x1 | F22: =IFERROR(E22/D22,0) -> 0 | G22: =C22/$C$2 -> #DIV/0! | M22: =IFERROR(L22/K22,0) -> 0 | N22: =J22/J$2 -> #DIV/0! | T22: =IFERROR(S22/R22,0) -> 0 | U22: =Q22/Q$2 -> #DIV/0! | AA22: =IFERROR(Z22/Y22,0) -> 0 | AB22: =X22/X$2 -> #DIV/0! | AH22: =IFERROR(AG22/AF22,0) -> 0 | AI22: =AE22/AE$2 -> #DIV/0! | AO22: =IFERROR(AN22/AM22,0) -> 0 | AP22: =AL22/AL$2 -> #DIV/0!
B23: 0x1 | F23: =IFERROR(E23/D23,0) -> 0 | G23: =C23/$C$2 -> #DIV/0! | M23: =IFERROR(L23/K23,0) -> 0 | N23: =J23/J$2 -> #DIV/0! | T23: =IFERROR(S23/R23,0) -> 0 | U23: =Q23/Q$2 -> #DIV/0! | AA23: =IFERROR(Z23/Y23,0) -> 0 | AB23: =X23/X$2 -> #DIV/0! | AH23: =IFERROR(AG23/AF23,0) -> 0 | AI23: =AE23/AE$2 -> #DIV/0! | AO23: =IFERROR(AN23/AM23,0) -> 0 | AP23: =AL23/AL$2 -> #DIV/0!
B24: 0x1 | F24: =IFERROR(E24/D24,0) -> 0 | G24: =C24/$C$2 -> #DIV/0! | M24: =IFERROR(L24/K24,0) -> 0 | N24: =J24/J$2 -> #DIV/0! | T24: =IFERROR(S24/R24,0) -> 0 | U24: =Q24/Q$2 -> #DIV/0! | AA24: =IFERROR(Z24/Y24,0) -> 0 | AB24: =X24/X$2 -> #DIV/0! | AH24: =IFERROR(AG24/AF24,0) -> 0 | AI24: =AE24/AE$2 -> #DIV/0! | AO24: =IFERROR(AN24/AM24,0) -> 0 | AP24: =AL24/AL$2 -> #DIV/0!
B25: 0x1 | F25: =IFERROR(E25/D25,0) -> 0 | G25: =C25/$C$2 -> #DIV/0! | M25: =IFERROR(L25/K25,0) -> 0 | N25: =J25/J$2 -> #DIV/0! | T25: =IFERROR(S25/R25,0) -> 0 | U25: =Q25/Q$2 -> #DIV/0! | AA25: =IFERROR(Z25/Y25,0) -> 0 | AB25: =X25/X$2 -> #DIV/0! | AH25: =IFERROR(AG25/AF25,0) -> 0 | AI25: =AE25/AE$2 -> #DIV/0! | AO25: =IFERROR(AN25/AM25,0) -> 0 | AP25: =AL25/AL$2 -> #DIV/0!
B26: 0x1 | F26: =IFERROR(E26/D26,0) -> 0 | G26: =C26/$C$2 -> #DIV/0! | M26: =IFERROR(L26/K26,0) -> 0 | N26: =J26/J$2 -> #DIV/0! | T26: =IFERROR(S26/R26,0) -> 0 | U26: =Q26/Q$2 -> #DIV/0! | AA26: =IFERROR(Z26/Y26,0) -> 0 | AB26: =X26/X$2 -> #DIV/0! | AH26: =IFERROR(AG26/AF26,0) -> 0 | AI26: =AE26/AE$2 -> #DIV/0! | AO26: =IFERROR(AN26/AM26,0) -> 0 | AP26: =AL26/AL$2 -> #DIV/0!
B27: 0x1 | F27: =IFERROR(E27/D27,0) -> 0 | G27: =C27/$C$2 -> #DIV/0! | M27: =IFERROR(L27/K27,0) -> 0 | N27: =J27/J$2 -> #DIV/0! | T27: =IFERROR(S27/R27,0) -> 0 | U27: =Q27/Q$2 -> #DIV/0! | AA27: =IFERROR(Z27/Y27,0) -> 0 | AB27: =X27/X$2 -> #DIV/0! | AH27: =IFERROR(AG27/AF27,0) -> 0 | AI27: =AE27/AE$2 -> #DIV/0! | AO27: =IFERROR(AN27/AM27,0) -> 0 | AP27: =AL27/AL$2 -> #DIV/0!
B28: Total | C28: =SUBTOTAL(9,C16:C27) -> 0 | D28: =SUMPRODUCT(D16:D27,C16:C27) -> 0 | E28: =SUMPRODUCT(E16:E27,C16:C27) -> 0 | F28: =IFERROR(E28/D28,0) -> 0 | I28: Total | J28: =SUBTOTAL(9,J16:J27) -> 0 | K28: =SUMPRODUCT(K16:K27,J16:J27) -> 0 | L28: =SUMPRODUCT(L16:L27,J16:J27) -> 0 | M28: =IFERROR(L28/K28,0) -> 0 | P28: Total | Q28: =SUBTOTAL(9,Q16:Q27) -> 0 | R28: =SUMPRODUCT(R16:R27,Q16:Q27) -> 0 | S28: =SUMPRODUCT(S16:S27,Q16:Q27) -> 0 | T28: =IFERROR(S28/R28,0) -> 0 | W28: Total | X28: =SUBTOTAL(9,X16:X27) -> 0 | Y28: =SUMPRODUCT(Y16:Y27,X16:X27) -> 0 | Z28: =SUMPRODUCT(Z16:Z27,X16:X27) -> 0 | AA28: =IFERROR(Z28/Y28,0) -> 0 | AD28: Total | AE28: =SUBTOTAL(9,AE16:AE27) -> 0 | AF28: =SUMPRODUCT(AF16:AF27,AE16:AE27) -> 0 | AG28: =SUMPRODUCT(AG16:AG27,AE16:AE27) -> 0 | AH28: =IFERROR(AG28/AF28,0) -> 0 | AK28: Total | AL28: =SUBTOTAL(9,AL16:AL27) -> 0 | AM28: =SUMPRODUCT(AM16:AM27,AL16:AL27) -> 0 | AN28: =SUMPRODUCT(AN16:AN27,AL16:AL27) -> 0 | AO28: =IFERROR(AN28/AM28,0) -> 0
B29: Average | D29: =IFERROR(D28/C28,0) -> 0 | E29: =IFERROR(E28/C28,0) -> 0 | F29: =IFERROR(E29/D29,0) -> 0 | I29: Average | K29: =IFERROR(K28/J28,0) -> 0 | L29: =IFERROR(L28/J28,0) -> 0 | M29: =IFERROR(L29/K29,0) -> 0 | P29: Average | R29: =IFERROR(R28/Q28,0) -> 0 | S29: =IFERROR(S28/Q28,0) -> 0 | T29: =IFERROR(S29/R29,0) -> 0 | W29: Average | Y29: =IFERROR(Y28/X28,0) -> 0 | Z29: =IFERROR(Z28/X28,0) -> 0 | AA29: =IFERROR(Z29/Y29,0) -> 0 | AD29: Average | AF29: =IFERROR(AF28/AE28,0) -> 0 | AG29: =IFERROR(AG28/AE28,0) -> 0 | AH29: =IFERROR(AG29/AF29,0) -> 0 | AK29: Average | AM29: =IFERROR(AM28/AL28,0) -> 0 | AN29: =IFERROR(AN28/AL28,0) -> 0 | AO29: =IFERROR(AN29/AM29,0) -> 0
A31: Proforma | B31: One Bedroom | I31: One Bedroom | P31: One Bedroom | W31: One Bedroom | AD31: One Bedroom | AK31: One Bedroom
B32: Unit Type | C32: Units | D32: Square Feet | E32: Base Rent | F32: PSF | G32: % of Mix | I32: Unit Type | J32: Units | K32: Square Feet | L32: Base Rent | M32: PSF | N32: % of Mix | P32: Unit Type | Q32: Units | R32: Square Feet | S32: Base Rent | T32: PSF | U32: % of Mix | W32: Unit Type | X32: Units | Y32: Square Feet | Z32: Base Rent | AA32: PSF | AB32: % of Mix | AD32: Unit Type | AE32: Units | AF32: Square Feet | AG32: Base Rent | AH32: PSF | AI32: % of Mix | AK32: Unit Type | AL32: Units | AM32: Square Feet | AN32: Base Rent | AO32: PSF | AP32: % of Mix
B33: 1x1 | F33: =IFERROR(E33/D33,0) -> 0 | G33: =C33/$C$2 -> #DIV/0! | M33: =IFERROR(L33/K33,0) -> 0 | N33: =J33/J$2 -> #DIV/0! | T33: =IFERROR(S33/R33,0) -> 0 | U33: =Q33/Q$2 -> #DIV/0! | AA33: =IFERROR(Z33/Y33,0) -> 0 | AB33: =X33/X$2 -> #DIV/0! | AH33: =IFERROR(AG33/AF33,0) -> 0 | AI33: =AE33/AE$2 -> #DIV/0! | AO33: =IFERROR(AN33/AM33,0) -> 0 | AP33: =AL33/AL$2 -> #DIV/0!
B34: 1x1 | F34: =IFERROR(E34/D34,0) -> 0 | G34: =C34/$C$2 -> #DIV/0! | M34: =IFERROR(L34/K34,0) -> 0 | N34: =J34/J$2 -> #DIV/0! | T34: =IFERROR(S34/R34,0) -> 0 | U34: =Q34/Q$2 -> #DIV/0! | AA34: =IFERROR(Z34/Y34,0) -> 0 | AB34: =X34/X$2 -> #DIV/0! | AH34: =IFERROR(AG34/AF34,0) -> 0 | AI34: =AE34/AE$2 -> #DIV/0! | AO34: =IFERROR(AN34/AM34,0) -> 0 | AP34: =AL34/AL$2 -> #DIV/0!
B35: 1x1 | F35: =IFERROR(E35/D35,0) -> 0 | G35: =C35/$C$2 -> #DIV/0! | M35: =IFERROR(L35/K35,0) -> 0 | N35: =J35/J$2 -> #DIV/0! | T35: =IFERROR(S35/R35,0) -> 0 | U35: =Q35/Q$2 -> #DIV/0! | AA35: =IFERROR(Z35/Y35,0) -> 0 | AB35: =X35/X$2 -> #DIV/0! | AH35: =IFERROR(AG35/AF35,0) -> 0 | AI35: =AE35/AE$2 -> #DIV/0! | AO35: =IFERROR(AN35/AM35,0) -> 0 | AP35: =AL35/AL$2 -> #DIV/0!
B36: 1x1 | F36: =IFERROR(E36/D36,0) -> 0 | G36: =C36/$C$2 -> #DIV/0! | M36: =IFERROR(L36/K36,0) -> 0 | N36: =J36/J$2 -> #DIV/0! | T36: =IFERROR(S36/R36,0) -> 0 | U36: =Q36/Q$2 -> #DIV/0! | AA36: =IFERROR(Z36/Y36,0) -> 0 | AB36: =X36/X$2 -> #DIV/0! | AH36: =IFERROR(AG36/AF36,0) -> 0 | AI36: =AE36/AE$2 -> #DIV/0! | AO36: =IFERROR(AN36/AM36,0) -> 0 | AP36: =AL36/AL$2 -> #DIV/0!
B37: 1x1 | F37: =IFERROR(E37/D37,0) -> 0 | G37: =C37/$C$2 -> #DIV/0! | M37: =IFERROR(L37/K37,0) -> 0 | N37: =J37/J$2 -> #DIV/0! | T37: =IFERROR(S37/R37,0) -> 0 | U37: =Q37/Q$2 -> #DIV/0! | AA37: =IFERROR(Z37/Y37,0) -> 0 | AB37: =X37/X$2 -> #DIV/0! | AH37: =IFERROR(AG37/AF37,0) -> 0 | AI37: =AE37/AE$2 -> #DIV/0! | AO37: =IFERROR(AN37/AM37,0) -> 0 | AP37: =AL37/AL$2 -> #DIV/0!
B38: 1x1 | F38: =IFERROR(E38/D38,0) -> 0 | G38: =C38/$C$2 -> #DIV/0! | M38: =IFERROR(L38/K38,0) -> 0 | N38: =J38/J$2 -> #DIV/0! | T38: =IFERROR(S38/R38,0) -> 0 | U38: =Q38/Q$2 -> #DIV/0! | AA38: =IFERROR(Z38/Y38,0) -> 0 | AB38: =X38/X$2 -> #DIV/0! | AH38: =IFERROR(AG38/AF38,0) -> 0 | AI38: =AE38/AE$2 -> #DIV/0! | AO38: =IFERROR(AN38/AM38,0) -> 0 | AP38: =AL38/AL$2 -> #DIV/0!
B39: 1x1 | F39: =IFERROR(E39/D39,0) -> 0 | G39: =C39/$C$2 -> #DIV/0! | M39: =IFERROR(L39/K39,0) -> 0 | N39: =J39/J$2 -> #DIV/0! | T39: =IFERROR(S39/R39,0) -> 0 | U39: =Q39/Q$2 -> #DIV/0! | AA39: =IFERROR(Z39/Y39,0) -> 0 | AB39: =X39/X$2 -> #DIV/0! | AH39: =IFERROR(AG39/AF39,0) -> 0 | AI39: =AE39/AE$2 -> #DIV/0! | AO39: =IFERROR(AN39/AM39,0) -> 0 | AP39: =AL39/AL$2 -> #DIV/0!
B40: 1x1 | F40: =IFERROR(E40/D40,0) -> 0 | G40: =C40/$C$2 -> #DIV/0! | M40: =IFERROR(L40/K40,0) -> 0 | N40: =J40/J$2 -> #DIV/0! | T40: =IFERROR(S40/R40,0) -> 0 | U40: =Q40/Q$2 -> #DIV/0! | AA40: =IFERROR(Z40/Y40,0) -> 0 | AB40: =X40/X$2 -> #DIV/0! | AH40: =IFERROR(AG40/AF40,0) -> 0 | AI40: =AE40/AE$2 -> #DIV/0! | AO40: =IFERROR(AN40/AM40,0) -> 0 | AP40: =AL40/AL$2 -> #DIV/0!
B41: 1x1 | F41: =IFERROR(E41/D41,0) -> 0 | G41: =C41/$C$2 -> #DIV/0! | M41: =IFERROR(L41/K41,0) -> 0 | N41: =J41/J$2 -> #DIV/0! | T41: =IFERROR(S41/R41,0) -> 0 | U41: =Q41/Q$2 -> #DIV/0! | AA41: =IFERROR(Z41/Y41,0) -> 0 | AB41: =X41/X$2 -> #DIV/0! | AH41: =IFERROR(AG41/AF41,0) -> 0 | AI41: =AE41/AE$2 -> #DIV/0! | AO41: =IFERROR(AN41/AM41,0) -> 0 | AP41: =AL41/AL$2 -> #DIV/0!
B42: 1x1 | F42: =IFERROR(E42/D42,0) -> 0 | G42: =C42/$C$2 -> #DIV/0! | M42: =IFERROR(L42/K42,0) -> 0 | N42: =J42/J$2 -> #DIV/0! | T42: =IFERROR(S42/R42,0) -> 0 | U42: =Q42/Q$2 -> #DIV/0! | AA42: =IFERROR(Z42/Y42,0) -> 0 | AB42: =X42/X$2 -> #DIV/0! | AH42: =IFERROR(AG42/AF42,0) -> 0 | AI42: =AE42/AE$2 -> #DIV/0! | AO42: =IFERROR(AN42/AM42,0) -> 0 | AP42: =AL42/AL$2 -> #DIV/0!
B43: 1x1 | F43: =IFERROR(E43/D43,0) -> 0 | G43: =C43/$C$2 -> #DIV/0! | M43: =IFERROR(L43/K43,0) -> 0 | N43: =J43/J$2 -> #DIV/0! | T43: =IFERROR(S43/R43,0) -> 0 | U43: =Q43/Q$2 -> #DIV/0! | AA43: =IFERROR(Z43/Y43,0) -> 0 | AB43: =X43/X$2 -> #DIV/0! | AH43: =IFERROR(AG43/AF43,0) -> 0 | AI43: =AE43/AE$2 -> #DIV/0! | AO43: =IFERROR(AN43/AM43,0) -> 0 | AP43: =AL43/AL$2 -> #DIV/0!
B44: 1x1 | F44: =IFERROR(E44/D44,0) -> 0 | G44: =C44/$C$2 -> #DIV/0! | M44: =IFERROR(L44/K44,0) -> 0 | N44: =J44/J$2 -> #DIV/0! | T44: =IFERROR(S44/R44,0) -> 0 | U44: =Q44/Q$2 -> #DIV/0! | AA44: =IFERROR(Z44/Y44,0) -> 0 | AB44: =X44/X$2 -> #DIV/0! | AH44: =IFERROR(AG44/AF44,0) -> 0 | AI44: =AE44/AE$2 -> #DIV/0! | AO44: =IFERROR(AN44/AM44,0) -> 0 | AP44: =AL44/AL$2 -> #DIV/0!
B45: 1x1 | F45: =IFERROR(E45/D45,0) -> 0 | G45: =C45/C$2 -> #DIV/0! | M45: =IFERROR(L45/K45,0) -> 0 | N45: =J45/J$2 -> #DIV/0! | T45: =IFERROR(S45/R45,0) -> 0 | U45: =Q45/Q$2 -> #DIV/0! | AA45: =IFERROR(Z45/Y45,0) -> 0 | AB45: =X45/X$2 -> #DIV/0! | AH45: =IFERROR(AG45/AF45,0) -> 0 | AI45: =AE45/AE$2 -> #DIV/0! | AO45: =IFERROR(AN45/AM45,0) -> 0 | AP45: =AL45/AL$2 -> #DIV/0!
B46: 1x1 | F46: =IFERROR(E46/D46,0) -> 0 | G46: =C46/C$2 -> #DIV/0! | M46: =IFERROR(L46/K46,0) -> 0 | N46: =J46/J$2 -> #DIV/0! | T46: =IFERROR(S46/R46,0) -> 0 | U46: =Q46/Q$2 -> #DIV/0! | AA46: =IFERROR(Z46/Y46,0) -> 0 | AB46: =X46/X$2 -> #DIV/0! | AH46: =IFERROR(AG46/AF46,0) -> 0 | AI46: =AE46/AE$2 -> #DIV/0! | AO46: =IFERROR(AN46/AM46,0) -> 0 | AP46: =AL46/AL$2 -> #DIV/0!
B47: 1x1 | F47: =IFERROR(E47/D47,0) -> 0 | G47: =C47/C$2 -> #DIV/0! | M47: =IFERROR(L47/K47,0) -> 0 | N47: =J47/J$2 -> #DIV/0! | T47: =IFERROR(S47/R47,0) -> 0 | U47: =Q47/Q$2 -> #DIV/0! | AA47: =IFERROR(Z47/Y47,0) -> 0 | AB47: =X47/X$2 -> #DIV/0! | AH47: =IFERROR(AG47/AF47,0) -> 0 | AI47: =AE47/AE$2 -> #DIV/0! | AO47: =IFERROR(AN47/AM47,0) -> 0 | AP47: =AL47/AL$2 -> #DIV/0!
B48: 1x1 | F48: =IFERROR(E48/D48,0) -> 0 | G48: =C48/C$2 -> #DIV/0! | M48: =IFERROR(L48/K48,0) -> 0 | N48: =J48/J$2 -> #DIV/0! | T48: =IFERROR(S48/R48,0) -> 0 | U48: =Q48/Q$2 -> #DIV/0! | AA48: =IFERROR(Z48/Y48,0) -> 0 | AB48: =X48/X$2 -> #DIV/0! | AH48: =IFERROR(AG48/AF48,0) -> 0 | AI48: =AE48/AE$2 -> #DIV/0! | AO48: =IFERROR(AN48/AM48,0) -> 0 | AP48: =AL48/AL$2 -> #DIV/0!
B49: 1x1 | F49: =IFERROR(E49/D49,0) -> 0 | G49: =C49/C$2 -> #DIV/0! | M49: =IFERROR(L49/K49,0) -> 0 | N49: =J49/J$2 -> #DIV/0! | T49: =IFERROR(S49/R49,0) -> 0 | U49: =Q49/Q$2 -> #DIV/0! | AA49: =IFERROR(Z49/Y49,0) -> 0 | AB49: =X49/X$2 -> #DIV/0! | AH49: =IFERROR(AG49/AF49,0) -> 0 | AI49: =AE49/AE$2 -> #DIV/0! | AO49: =IFERROR(AN49/AM49,0) -> 0 | AP49: =AL49/AL$2 -> #DIV/0!
B50: 1x1 | F50: =IFERROR(E50/D50,0) -> 0 | G50: =C50/C$2 -> #DIV/0! | M50: =IFERROR(L50/K50,0) -> 0 | N50: =J50/J$2 -> #DIV/0! | T50: =IFERROR(S50/R50,0) -> 0 | U50: =Q50/Q$2 -> #DIV/0! | AA50: =IFERROR(Z50/Y50,0) -> 0 | AB50: =X50/X$2 -> #DIV/0! | AH50: =IFERROR(AG50/AF50,0) -> 0 | AI50: =AE50/AE$2 -> #DIV/0! | AO50: =IFERROR(AN50/AM50,0) -> 0 | AP50: =AL50/AL$2 -> #DIV/0!
B51: 1x1 | F51: =IFERROR(E51/D51,0) -> 0 | G51: =C51/C$2 -> #DIV/0! | M51: =IFERROR(L51/K51,0) -> 0 | N51: =J51/J$2 -> #DIV/0! | T51: =IFERROR(S51/R51,0) -> 0 | U51: =Q51/Q$2 -> #DIV/0! | AA51: =IFERROR(Z51/Y51,0) -> 0 | AB51: =X51/X$2 -> #DIV/0! | AH51: =IFERROR(AG51/AF51,0) -> 0 | AI51: =AE51/AE$2 -> #DIV/0! | AO51: =IFERROR(AN51/AM51,0) -> 0 | AP51: =AL51/AL$2 -> #DIV/0!
B52: 1x1 | F52: =IFERROR(E52/D52,0) -> 0 | G52: =C52/C$2 -> #DIV/0! | M52: =IFERROR(L52/K52,0) -> 0 | N52: =J52/J$2 -> #DIV/0! | T52: =IFERROR(S52/R52,0) -> 0 | U52: =Q52/Q$2 -> #DIV/0! | AA52: =IFERROR(Z52/Y52,0) -> 0 | AB52: =X52/X$2 -> #DIV/0! | AH52: =IFERROR(AG52/AF52,0) -> 0 | AI52: =AE52/AE$2 -> #DIV/0! | AO52: =IFERROR(AN52/AM52,0) -> 0 | AP52: =AL52/AL$2 -> #DIV/0!
B53: 1x1 | F53: =IFERROR(E53/D53,0) -> 0 | G53: =C53/C$2 -> #DIV/0! | M53: =IFERROR(L53/K53,0) -> 0 | N53: =J53/J$2 -> #DIV/0! | T53: =IFERROR(S53/R53,0) -> 0 | U53: =Q53/Q$2 -> #DIV/0! | AA53: =IFERROR(Z53/Y53,0) -> 0 | AB53: =X53/X$2 -> #DIV/0! | AH53: =IFERROR(AG53/AF53,0) -> 0 | AI53: =AE53/AE$2 -> #DIV/0! | AO53: =IFERROR(AN53/AM53,0) -> 0 | AP53: =AL53/AL$2 -> #DIV/0!
B54: 1x1 | F54: =IFERROR(E54/D54,0) -> 0 | G54: =C54/C$2 -> #DIV/0! | M54: =IFERROR(L54/K54,0) -> 0 | N54: =J54/J$2 -> #DIV/0! | T54: =IFERROR(S54/R54,0) -> 0 | U54: =Q54/Q$2 -> #DIV/0! | AA54: =IFERROR(Z54/Y54,0) -> 0 | AB54: =X54/X$2 -> #DIV/0! | AH54: =IFERROR(AG54/AF54,0) -> 0 | AI54: =AE54/AE$2 -> #DIV/0! | AO54: =IFERROR(AN54/AM54,0) -> 0 | AP54: =AL54/AL$2 -> #DIV/0!
B55: 1x1 | F55: =IFERROR(E55/D55,0) -> 0 | G55: =C55/C$2 -> #DIV/0! | M55: =IFERROR(L55/K55,0) -> 0 | N55: =J55/J$2 -> #DIV/0! | T55: =IFERROR(S55/R55,0) -> 0 | U55: =Q55/Q$2 -> #DIV/0! | AA55: =IFERROR(Z55/Y55,0) -> 0 | AB55: =X55/X$2 -> #DIV/0! | AH55: =IFERROR(AG55/AF55,0) -> 0 | AI55: =AE55/AE$2 -> #DIV/0! | AO55: =IFERROR(AN55/AM55,0) -> 0 | AP55: =AL55/AL$2 -> #DIV/0!
B56: 1x1 | F56: =IFERROR(E56/D56,0) -> 0 | G56: =C56/C$2 -> #DIV/0! | M56: =IFERROR(L56/K56,0) -> 0 | N56: =J56/J$2 -> #DIV/0! | T56: =IFERROR(S56/R56,0) -> 0 | U56: =Q56/Q$2 -> #DIV/0! | AA56: =IFERROR(Z56/Y56,0) -> 0 | AB56: =X56/X$2 -> #DIV/0! | AH56: =IFERROR(AG56/AF56,0) -> 0 | AI56: =AE56/AE$2 -> #DIV/0! | AO56: =IFERROR(AN56/AM56,0) -> 0 | AP56: =AL56/AL$2 -> #DIV/0!
B57: Total | C57: =SUBTOTAL(9,C33:C56) -> 0 | D57: =SUMPRODUCT(D33:D56,C33:C56) -> 0 | E57: =SUMPRODUCT(E33:E56,C33:C56) -> 0 | F57: =IFERROR(E57/D57,0) -> 0 | I57: Total | J57: =SUBTOTAL(9,J33:J56) -> 0 | K57: =SUMPRODUCT(K33:K56,J33:J56) -> 0 | L57: =SUMPRODUCT(L33:L56,J33:J56) -> 0 | M57: =IFERROR(L57/K57,0) -> 0 | P57: Total | Q57: =SUBTOTAL(9,Q33:Q56) -> 0 | R57: =SUMPRODUCT(R33:R56,Q33:Q56) -> 0 | S57: =SUMPRODUCT(S33:S56,Q33:Q56) -> 0 | T57: =IFERROR(S57/R57,0) -> 0 | W57: Total | X57: =SUBTOTAL(9,X33:X56) -> 0 | Y57: =SUMPRODUCT(Y33:Y56,X33:X56) -> 0 | Z57: =SUMPRODUCT(Z33:Z56,X33:X56) -> 0 | AA57: =IFERROR(Z57/Y57,0) -> 0 | AD57: Total | AE57: =SUBTOTAL(9,AE33:AE56) -> 0 | AF57: =SUMPRODUCT(AF33:AF56,AE33:AE56) -> 0 | AG57: =SUMPRODUCT(AG33:AG56,AE33:AE56) -> 0 | AH57: =IFERROR(AG57/AF57,0) -> 0 | AK57: Total | AL57: =SUBTOTAL(9,AL33:AL56) -> 0 | AM57: =SUMPRODUCT(AM33:AM56,AL33:AL56) -> 0 | AN57: =SUMPRODUCT(AN33:AN56,AL33:AL56) -> 0 | AO57: =IFERROR(AN57/AM57,0) -> 0
B58: Average | D58: =IFERROR(D57/C57,0) -> 0 | E58: =IFERROR(E57/C57,0) -> 0 | F58: =IFERROR(E58/D58,0) -> 0 | I58: Average | K58: =IFERROR(K57/J57,0) -> 0 | L58: =IFERROR(L57/J57,0) -> 0 | M58: =IFERROR(L58/K58,0) -> 0 | P58: Average | R58: =IFERROR(R57/Q57,0) -> 0 | S58: =IFERROR(S57/Q57,0) -> 0 | T58: =IFERROR(S58/R58,0) -> 0 | W58: Average | Y58: =IFERROR(Y57/X57,0) -> 0 | Z58: =IFERROR(Z57/X57,0) -> 0 | AA58: =IFERROR(Z58/Y58,0) -> 0 | AD58: Average | AF58: =IFERROR(AF57/AE57,0) -> 0 | AG58: =IFERROR(AG57/AE57,0) -> 0 | AH58: =IFERROR(AG58/AF58,0) -> 0 | AK58: Average | AM58: =IFERROR(AM57/AL57,0) -> 0 | AN58: =IFERROR(AN57/AL57,0) -> 0 | AO58: =IFERROR(AN58/AM58,0) -> 0
A59: =+A58-E58 -> 0 | B59: Two Bedroom | I59: Two Bedroom | P59: Two Bedroom | W59: Two Bedroom | AD59: Two Bedroom | AK59: Two Bedroom
B60: Unit Type | C60: Units | D60: Square Feet | E60: Base Rent | F60: PSF | G60: % of Mix | I60: Unit Type | J60: Units | K60: Square Feet | L60: Base Rent | M60: PSF | N60: % of Mix | P60: Unit Type | Q60: Units | R60: Square Feet | S60: Base Rent | T60: PSF | U60: % of Mix | W60: Unit Type | X60: Units | Y60: Square Feet | Z60: Base Rent | AA60: PSF | AB60: % of Mix | AD60: Unit Type | AE60: Units | AF60: Square Feet | AG60: Base Rent | AH60: PSF | AI60: % of Mix | AK60: Unit Type | AL60: Units | AM60: Square Feet | AN60: Base Rent | AO60: PSF | AP60: % of Mix
B61: 2x2 | F61: =IFERROR(E61/D61,0) -> 0 | G61: =C61/$C$2 -> #DIV/0! | M61: =IFERROR(L61/K61,0) -> 0 | N61: =J61/J$2 -> #DIV/0! | T61: =IFERROR(S61/R61,0) -> 0 | U61: =Q61/Q$2 -> #DIV/0! | AA61: =IFERROR(Z61/Y61,0) -> 0 | AB61: =X61/X$2 -> #DIV/0! | AH61: =IFERROR(AG61/AF61,0) -> 0 | AI61: =AE61/AE$2 -> #DIV/0! | AO61: =IFERROR(AN61/AM61,0) -> 0 | AP61: =AL61/AL$2 -> #DIV/0!
B62: 2x2 | F62: =IFERROR(E62/D62,0) -> 0 | G62: =C62/$C$2 -> #DIV/0! | M62: =IFERROR(L62/K62,0) -> 0 | N62: =J62/J$2 -> #DIV/0! | T62: =IFERROR(S62/R62,0) -> 0 | U62: =Q62/Q$2 -> #DIV/0! | AA62: =IFERROR(Z62/Y62,0) -> 0 | AB62: =X62/X$2 -> #DIV/0! | AH62: =IFERROR(AG62/AF62,0) -> 0 | AI62: =AE62/AE$2 -> #DIV/0! | AO62: =IFERROR(AN62/AM62,0) -> 0 | AP62: =AL62/AL$2 -> #DIV/0!
B63: 2x2 | F63: =IFERROR(E63/D63,0) -> 0 | G63: =C63/$C$2 -> #DIV/0! | M63: =IFERROR(L63/K63,0) -> 0 | N63: =J63/J$2 -> #DIV/0! | T63: =IFERROR(S63/R63,0) -> 0 | U63: =Q63/Q$2 -> #DIV/0! | AA63: =IFERROR(Z63/Y63,0) -> 0 | AB63: =X63/X$2 -> #DIV/0! | AH63: =IFERROR(AG63/AF63,0) -> 0 | AI63: =AE63/AE$2 -> #DIV/0! | AO63: =IFERROR(AN63/AM63,0) -> 0 | AP63: =AL63/AL$2 -> #DIV/0!
B64: 2x2 | F64: =IFERROR(E64/D64,0) -> 0 | G64: =C64/$C$2 -> #DIV/0! | M64: =IFERROR(L64/K64,0) -> 0 | N64: =J64/J$2 -> #DIV/0! | T64: =IFERROR(S64/R64,0) -> 0 | U64: =Q64/Q$2 -> #DIV/0! | AA64: =IFERROR(Z64/Y64,0) -> 0 | AB64: =X64/X$2 -> #DIV/0! | AH64: =IFERROR(AG64/AF64,0) -> 0 | AI64: =AE64/AE$2 -> #DIV/0! | AO64: =IFERROR(AN64/AM64,0) -> 0 | AP64: =AL64/AL$2 -> #DIV/0!
B65: 2x2 | F65: =IFERROR(E65/D65,0) -> 0 | G65: =C65/$C$2 -> #DIV/0! | M65: =IFERROR(L65/K65,0) -> 0 | N65: =J65/J$2 -> #DIV/0! | T65: =IFERROR(S65/R65,0) -> 0 | U65: =Q65/Q$2 -> #DIV/0! | AA65: =IFERROR(Z65/Y65,0) -> 0 | AB65: =X65/X$2 -> #DIV/0! | AH65: =IFERROR(AG65/AF65,0) -> 0 | AI65: =AE65/AE$2 -> #DIV/0! | AO65: =IFERROR(AN65/AM65,0) -> 0 | AP65: =AL65/AL$2 -> #DIV/0!
B66: 2x2 | F66: =IFERROR(E66/D66,0) -> 0 | G66: =C66/$C$2 -> #DIV/0! | M66: =IFERROR(L66/K66,0) -> 0 | N66: =J66/J$2 -> #DIV/0! | T66: =IFERROR(S66/R66,0) -> 0 | U66: =Q66/Q$2 -> #DIV/0! | AA66: =IFERROR(Z66/Y66,0) -> 0 | AB66: =X66/X$2 -> #DIV/0! | AH66: =IFERROR(AG66/AF66,0) -> 0 | AI66: =AE66/AE$2 -> #DIV/0! | AO66: =IFERROR(AN66/AM66,0) -> 0 | AP66: =AL66/AL$2 -> #DIV/0!
B67: 2x2 | F67: =IFERROR(E67/D67,0) -> 0 | G67: =C67/$C$2 -> #DIV/0! | M67: =IFERROR(L67/K67,0) -> 0 | N67: =J67/J$2 -> #DIV/0! | T67: =IFERROR(S67/R67,0) -> 0 | U67: =Q67/Q$2 -> #DIV/0! | AA67: =IFERROR(Z67/Y67,0) -> 0 | AB67: =X67/X$2 -> #DIV/0! | AH67: =IFERROR(AG67/AF67,0) -> 0 | AI67: =AE67/AE$2 -> #DIV/0! | AO67: =IFERROR(AN67/AM67,0) -> 0 | AP67: =AL67/AL$2 -> #DIV/0!
B68: 2x2 | F68: =IFERROR(E68/D68,0) -> 0 | G68: =C68/$C$2 -> #DIV/0! | M68: =IFERROR(L68/K68,0) -> 0 | N68: =J68/J$2 -> #DIV/0! | T68: =IFERROR(S68/R68,0) -> 0 | U68: =Q68/Q$2 -> #DIV/0! | AA68: =IFERROR(Z68/Y68,0) -> 0 | AB68: =X68/X$2 -> #DIV/0! | AH68: =IFERROR(AG68/AF68,0) -> 0 | AI68: =AE68/AE$2 -> #DIV/0! | AO68: =IFERROR(AN68/AM68,0) -> 0 | AP68: =AL68/AL$2 -> #DIV/0!
B69: 2x2 | F69: =IFERROR(E69/D69,0) -> 0 | G69: =C69/$C$2 -> #DIV/0! | M69: =IFERROR(L69/K69,0) -> 0 | N69: =J69/J$2 -> #DIV/0! | T69: =IFERROR(S69/R69,0) -> 0 | U69: =Q69/Q$2 -> #DIV/0! | AA69: =IFERROR(Z69/Y69,0) -> 0 | AB69: =X69/X$2 -> #DIV/0! | AH69: =IFERROR(AG69/AF69,0) -> 0 | AI69: =AE69/AE$2 -> #DIV/0! | AO69: =IFERROR(AN69/AM69,0) -> 0 | AP69: =AL69/AL$2 -> #DIV/0!
B70: 2x2 | F70: =IFERROR(E70/D70,0) -> 0 | G70: =C70/$C$2 -> #DIV/0! | M70: =IFERROR(L70/K70,0) -> 0 | N70: =J70/J$2 -> #DIV/0! | T70: =IFERROR(S70/R70,0) -> 0 | U70: =Q70/Q$2 -> #DIV/0! | AA70: =IFERROR(Z70/Y70,0) -> 0 | AB70: =X70/X$2 -> #DIV/0! | AH70: =IFERROR(AG70/AF70,0) -> 0 | AI70: =AE70/AE$2 -> #DIV/0! | AO70: =IFERROR(AN70/AM70,0) -> 0 | AP70: =AL70/AL$2 -> #DIV/0!
B71: 2x2 | F71: =IFERROR(E71/D71,0) -> 0 | G71: =C71/$C$2 -> #DIV/0! | M71: =IFERROR(L71/K71,0) -> 0 | N71: =J71/J$2 -> #DIV/0! | T71: =IFERROR(S71/R71,0) -> 0 | U71: =Q71/Q$2 -> #DIV/0! | AA71: =IFERROR(Z71/Y71,0) -> 0 | AB71: =X71/X$2 -> #DIV/0! | AH71: =IFERROR(AG71/AF71,0) -> 0 | AI71: =AE71/AE$2 -> #DIV/0! | AO71: =IFERROR(AN71/AM71,0) -> 0 | AP71: =AL71/AL$2 -> #DIV/0!
B72: 2x2 | F72: =IFERROR(E72/D72,0) -> 0 | G72: =C72/$C$2 -> #DIV/0! | M72: =IFERROR(L72/K72,0) -> 0 | N72: =J72/J$2 -> #DIV/0! | T72: =IFERROR(S72/R72,0) -> 0 | U72: =Q72/Q$2 -> #DIV/0! | AA72: =IFERROR(Z72/Y72,0) -> 0 | AB72: =X72/X$2 -> #DIV/0! | AH72: =IFERROR(AG72/AF72,0) -> 0 | AI72: =AE72/AE$2 -> #DIV/0! | AO72: =IFERROR(AN72/AM72,0) -> 0 | AP72: =AL72/AL$2 -> #DIV/0!
... B84: 2x2 | F84: =IFERROR(E84/D84,0) -> 0 | G84: =C84/$C$2 -> #DIV/0! | M84: =IFERROR(L84/K84,0) -> 0 | N84: =J84/J$2 -> #DIV/0! | T84: =IFERROR(S84/R84,0) -> 0 | U84: =Q84/Q$2 -> #DIV/0! | AA84: =IFERROR(Z84/Y84,0) -> 0 | AB84: =X84/X$2 -> #DIV/0! | AH84: =IFERROR(AG84/AF84,0) -> 0 | AI84: =AE84/AE$2 -> #DIV/0! | AO84: =IFERROR(AN84/AM84,0) -> 0 | AP84: =AL84/AL$2 -> #DIV/0!
B85: Total | C85: =SUBTOTAL(9,C61:C84) -> 0 | D85: =SUMPRODUCT(D61:D84,C61:C84) -> 0 | E85: =SUMPRODUCT(E61:E84,C61:C84) -> 0 | F85: =IFERROR(E85/D85,0) -> 0 | I85: Total | J85: =SUBTOTAL(9,J61:J84) -> 0 | K85: =SUMPRODUCT(K61:K84,J61:J84) -> 0 | L85: =SUMPRODUCT(L61:L84,J61:J84) -> 0 | M85: =IFERROR(L85/K85,0) -> 0 | P85: Total | Q85: =SUBTOTAL(9,Q61:Q84) -> 0 | R85: =SUMPRODUCT(R61:R84,Q61:Q84) -> 0 | S85: =SUMPRODUCT(S61:S84,Q61:Q84) -> 0 | T85: =IFERROR(S85/R85,0) -> 0 | W85: Total | X85: =SUBTOTAL(9,X61:X84) -> 0 | Y85: =SUMPRODUCT(Y61:Y84,X61:X84) -> 0 | Z85: =SUMPRODUCT(Z61:Z84,X61:X84) -> 0 | AA85: =IFERROR(Z85/Y85,0) -> 0 | AD85: Total | AE85: =SUBTOTAL(9,AE61:AE84) -> 0 | AF85: =SUMPRODUCT(AF61:AF84,AE61:AE84) -> 0 | AG85: =SUMPRODUCT(AG61:AG84,AE61:AE84) -> 0 | AH85: =IFERROR(AG85/AF85,0) -> 0 | AK85: Total | AL85: =SUBTOTAL(9,AL61:AL84) -> 0 | AM85: =SUMPRODUCT(AM61:AM84,AL61:AL84) -> 0 | AN85: =SUMPRODUCT(AN61:AN84,AL61:AL84) -> 0 | AO85: =IFERROR(AN85/AM85,0) -> 0
B86: Average | D86: =IFERROR(D85/C85,0) -> 0 | E86: =IFERROR(E85/C85,0) -> 0 | F86: =IFERROR(E86/D86,0) -> 0 | I86: Average | K86: =IFERROR(K85/J85,0) -> 0 | L86: =IFERROR(L85/J85,0) -> 0 | M86: =IFERROR(L86/K86,0) -> 0 | P86: Average | R86: =IFERROR(R85/Q85,0) -> 0 | S86: =IFERROR(S85/Q85,0) -> 0 | T86: =IFERROR(S86/R86,0) -> 0 | W86: Average | Y86: =IFERROR(Y85/X85,0) -> 0 | Z86: =IFERROR(Z85/X85,0) -> 0 | AA86: =IFERROR(Z86/Y86,0) -> 0 | AD86: Average | AF86: =IFERROR(AF85/AE85,0) -> 0 | AG86: =IFERROR(AG85/AE85,0) -> 0 | AH86: =IFERROR(AG86/AF86,0) -> 0 | AK86: Average | AM86: =IFERROR(AM85/AL85,0) -> 0 | AN86: =IFERROR(AN85/AL85,0) -> 0 | AO86: =IFERROR(AN86/AM86,0) -> 0
A87: =+A86-E86 -> 0 | B87: Three Bedroom | I87: Three Bedroom | P87: Three Bedroom | W87: Three Bedroom | AD87: Three Bedroom | AK87: Three Bedroom
B88: Unit Type | C88: Units | D88: Square Feet | E88: Base Rent | F88: PSF | G88: % of Mix | I88: Unit Type | J88: Units | K88: Square Feet | L88: Base Rent | M88: PSF | N88: % of Mix | P88: Unit Type | Q88: Units | R88: Square Feet | S88: Base Rent | T88: PSF | U88: % of Mix | W88: Unit Type | X88: Units | Y88: Square Feet | Z88: Base Rent | AA88: PSF | AB88: % of Mix | AD88: Unit Type | AE88: Units | AF88: Square Feet | AG88: Base Rent | AH88: PSF | AI88: % of Mix | AK88: Unit Type | AL88: Units | AM88: Square Feet | AN88: Base Rent | AO88: PSF | AP88: % of Mix
B89: 3x2 | F89: =IFERROR(E89/D89,0) -> 0 | G89: =C89/$C$2 -> #DIV/0! | M89: =IFERROR(L89/K89,0) -> 0 | N89: =J89/J$2 -> #DIV/0! | T89: =IFERROR(S89/R89,0) -> 0 | U89: =Q89/Q$2 -> #DIV/0! | AA89: =IFERROR(Z89/Y89,0) -> 0 | AB89: =X89/X$2 -> #DIV/0! | AH89: =IFERROR(AG89/AF89,0) -> 0 | AI89: =AE89/AE$2 -> #DIV/0! | AO89: =IFERROR(AN89/AM89,0) -> 0 | AP89: =AL89/AL$2 -> #DIV/0!
B90: 3x2 | F90: =IFERROR(E90/D90,0) -> 0 | G90: =C90/$C$2 -> #DIV/0! | M90: =IFERROR(L90/K90,0) -> 0 | N90: =J90/J$2 -> #DIV/0! | T90: =IFERROR(S90/R90,0) -> 0 | U90: =Q90/Q$2 -> #DIV/0! | AA90: =IFERROR(Z90/Y90,0) -> 0 | AB90: =X90/X$2 -> #DIV/0! | AH90: =IFERROR(AG90/AF90,0) -> 0 | AI90: =AE90/AE$2 -> #DIV/0! | AO90: =IFERROR(AN90/AM90,0) -> 0 | AP90: =AL90/AL$2 -> #DIV/0!
B91: 3x2 | F91: =IFERROR(E91/D91,0) -> 0 | G91: =C91/$C$2 -> #DIV/0! | M91: =IFERROR(L91/K91,0) -> 0 | N91: =J91/J$2 -> #DIV/0! | T91: =IFERROR(S91/R91,0) -> 0 | U91: =Q91/Q$2 -> #DIV/0! | AA91: =IFERROR(Z91/Y91,0) -> 0 | AB91: =X91/X$2 -> #DIV/0! | AH91: =IFERROR(AG91/AF91,0) -> 0 | AI91: =AE91/AE$2 -> #DIV/0! | AO91: =IFERROR(AN91/AM91,0) -> 0 | AP91: =AL91/AL$2 -> #DIV/0!
B92: 3x2 | F92: =IFERROR(E92/D92,0) -> 0 | G92: =C92/$C$2 -> #DIV/0! | M92: =IFERROR(L92/K92,0) -> 0 | N92: =J92/J$2 -> #DIV/0! | T92: =IFERROR(S92/R92,0) -> 0 | U92: =Q92/Q$2 -> #DIV/0! | AA92: =IFERROR(Z92/Y92,0) -> 0 | AB92: =X92/X$2 -> #DIV/0! | AH92: =IFERROR(AG92/AF92,0) -> 0 | AI92: =AE92/AE$2 -> #DIV/0! | AO92: =IFERROR(AN92/AM92,0) -> 0 | AP92: =AL92/AL$2 -> #DIV/0!
B93: 3x2 | F93: =IFERROR(E93/D93,0) -> 0 | G93: =C93/$C$2 -> #DIV/0! | M93: =IFERROR(L93/K93,0) -> 0 | N93: =J93/J$2 -> #DIV/0! | T93: =IFERROR(S93/R93,0) -> 0 | U93: =Q93/Q$2 -> #DIV/0! | AA93: =IFERROR(Z93/Y93,0) -> 0 | AB93: =X93/X$2 -> #DIV/0! | AH93: =IFERROR(AG93/AF93,0) -> 0 | AI93: =AE93/AE$2 -> #DIV/0! | AO93: =IFERROR(AN93/AM93,0) -> 0 | AP93: =AL93/AL$2 -> #DIV/0!
B94: 3x2 | F94: =IFERROR(E94/D94,0) -> 0 | G94: =C94/$C$2 -> #DIV/0! | M94: =IFERROR(L94/K94,0) -> 0 | N94: =J94/J$2 -> #DIV/0! | T94: =IFERROR(S94/R94,0) -> 0 | U94: =Q94/Q$2 -> #DIV/0! | AA94: =IFERROR(Z94/Y94,0) -> 0 | AB94: =X94/X$2 -> #DIV/0! | AH94: =IFERROR(AG94/AF94,0) -> 0 | AI94: =AE94/AE$2 -> #DIV/0! | AO94: =IFERROR(AN94/AM94,0) -> 0 | AP94: =AL94/AL$2 -> #DIV/0!
B95: 3x2 | F95: =IFERROR(E95/D95,0) -> 0 | G95: =C95/$C$2 -> #DIV/0! | M95: =IFERROR(L95/K95,0) -> 0 | N95: =J95/J$2 -> #DIV/0! | T95: =IFERROR(S95/R95,0) -> 0 | U95: =Q95/Q$2 -> #DIV/0! | AA95: =IFERROR(Z95/Y95,0) -> 0 | AB95: =X95/X$2 -> #DIV/0! | AH95: =IFERROR(AG95/AF95,0) -> 0 | AI95: =AE95/AE$2 -> #DIV/0! | AO95: =IFERROR(AN95/AM95,0) -> 0 | AP95: =AL95/AL$2 -> #DIV/0!
B96: 3x2 | F96: =IFERROR(E96/D96,0) -> 0 | G96: =C96/$C$2 -> #DIV/0! | M96: =IFERROR(L96/K96,0) -> 0 | N96: =J96/J$2 -> #DIV/0! | T96: =IFERROR(S96/R96,0) -> 0 | U96: =Q96/Q$2 -> #DIV/0! | AA96: =IFERROR(Z96/Y96,0) -> 0 | AB96: =X96/X$2 -> #DIV/0! | AH96: =IFERROR(AG96/AF96,0) -> 0 | AI96: =AE96/AE$2 -> #DIV/0! | AO96: =IFERROR(AN96/AM96,0) -> 0 | AP96: =AL96/AL$2 -> #DIV/0!
B97: 3x2 | F97: =IFERROR(E97/D97,0) -> 0 | G97: =C97/$C$2 -> #DIV/0! | M97: =IFERROR(L97/K97,0) -> 0 | N97: =J97/J$2 -> #DIV/0! | T97: =IFERROR(S97/R97,0) -> 0 | U97: =Q97/Q$2 -> #DIV/0! | AA97: =IFERROR(Z97/Y97,0) -> 0 | AB97: =X97/X$2 -> #DIV/0! | AH97: =IFERROR(AG97/AF97,0) -> 0 | AI97: =AE97/AE$2 -> #DIV/0! | AO97: =IFERROR(AN97/AM97,0) -> 0 | AP97: =AL97/AL$2 -> #DIV/0!
B98: 3x2 | F98: =IFERROR(E98/D98,0) -> 0 | G98: =C98/$C$2 -> #DIV/0! | M98: =IFERROR(L98/K98,0) -> 0 | N98: =J98/J$2 -> #DIV/0! | T98: =IFERROR(S98/R98,0) -> 0 | U98: =Q98/Q$2 -> #DIV/0! | AA98: =IFERROR(Z98/Y98,0) -> 0 | AB98: =X98/X$2 -> #DIV/0! | AH98: =IFERROR(AG98/AF98,0) -> 0 | AI98: =AE98/AE$2 -> #DIV/0! | AO98: =IFERROR(AN98/AM98,0) -> 0 | AP98: =AL98/AL$2 -> #DIV/0!
B99: 3x2 | F99: =IFERROR(E99/D99,0) -> 0 | G99: =C99/$C$2 -> #DIV/0! | M99: =IFERROR(L99/K99,0) -> 0 | N99: =J99/J$2 -> #DIV/0! | T99: =IFERROR(S99/R99,0) -> 0 | U99: =Q99/Q$2 -> #DIV/0! | AA99: =IFERROR(Z99/Y99,0) -> 0 | AB99: =X99/X$2 -> #DIV/0! | AH99: =IFERROR(AG99/AF99,0) -> 0 | AI99: =AE99/AE$2 -> #DIV/0! | AO99: =IFERROR(AN99/AM99,0) -> 0 | AP99: =AL99/AL$2 -> #DIV/0!
B100: 3x2 | F100: =IFERROR(E100/D100,0) -> 0 | G100: =C100/$C$2 -> #DIV/0! | M100: =IFERROR(L100/K100,0) -> 0 | N100: =J100/J$2 -> #DIV/0! | T100: =IFERROR(S100/R100,0) -> 0 | U100: =Q100/Q$2 -> #DIV/0! | AA100: =IFERROR(Z100/Y100,0) -> 0 | AB100: =X100/X$2 -> #DIV/0! | AH100: =IFERROR(AG100/AF100,0) -> 0 | AI100: =AE100/AE$2 -> #DIV/0! | AO100: =IFERROR(AN100/AM100,0) -> 0 | AP100: =AL100/AL$2 -> #DIV/0!
B101: Total | C101: =SUBTOTAL(9,C89:C100) -> 0 | D101: =SUMPRODUCT(D89:D100,C89:C100) -> 0 | E101: =SUMPRODUCT(E89:E100,C89:C100) -> 0 | F101: =IFERROR(E101/D101,0) -> 0 | I101: Total | J101: =SUBTOTAL(9,J89:J100) -> 0 | K101: =SUMPRODUCT(K89:K100,J89:J100) -> 0 | L101: =SUMPRODUCT(L89:L100,J89:J100) -> 0 | M101: =IFERROR(L101/K101,0) -> 0 | P101: Total | Q101: =SUBTOTAL(9,Q89:Q100) -> 0 | R101: =SUMPRODUCT(R89:R100,Q89:Q100) -> 0 | S101: =SUMPRODUCT(S89:S100,Q89:Q100) -> 0 | T101: =IFERROR(S101/R101,0) -> 0 | W101: Total | X101: =SUBTOTAL(9,X89:X100) -> 0 | Y101: =SUMPRODUCT(Y89:Y100,X89:X100) -> 0 | Z101: =SUMPRODUCT(Z89:Z100,X89:X100) -> 0 | AA101: =IFERROR(Z101/Y101,0) -> 0 | AD101: Total | AE101: =SUBTOTAL(9,AE89:AE100) -> 0 | AF101: =SUMPRODUCT(AF89:AF100,AE89:AE100) -> 0 | AG101: =SUMPRODUCT(AG89:AG100,AE89:AE100) -> 0 | AH101: =IFERROR(AG101/AF101,0) -> 0 | AK101: Total | AL101: =SUBTOTAL(9,AL89:AL100) -> 0 | AM101: =SUMPRODUCT(AM89:AM100,AL89:AL100) -> 0 | AN101: =SUMPRODUCT(AN89:AN100,AL89:AL100) -> 0 | AO101: =IFERROR(AN101/AM101,0) -> 0
B102: Average | D102: =IFERROR(D101/C101,) -> 0 | E102: =IFERROR(E101/C101,0) -> 0 | F102: =IFERROR(E102/D102,0) -> 0 | I102: Average | K102: =IFERROR(K101/J101,) -> 0 | L102: =IFERROR(L101/J101,0) -> 0 | M102: =IFERROR(L102/K102,0) -> 0 | P102: Average | R102: =IFERROR(R101/Q101,) -> 0 | S102: =IFERROR(S101/Q101,0) -> 0 | T102: =IFERROR(S102/R102,0) -> 0 | W102: Average | Y102: =IFERROR(Y101/X101,) -> 0 | Z102: =IFERROR(Z101/X101,0) -> 0 | AA102: =IFERROR(Z102/Y102,0) -> 0 | AD102: Average | AF102: =IFERROR(AF101/AE101,) -> 0 | AG102: =IFERROR(AG101/AE101,0) -> 0 | AH102: =IFERROR(AG102/AF102,0) -> 0 | AK102: Average | AM102: =IFERROR(AM101/AL101,) -> 0 | AN102: =IFERROR(AN101/AL101,0) -> 0 | AO102: =IFERROR(AN102/AM102,0) -> 0
A103: =+A102-E102 -> 0
B104: Property Mix Total | C104: Units | D104: SF | E104: Rent | F104: PSF | G104: % of Mix | I104: Property Mix Total | J104: Units | K104: SF | L104: Rent | M104: PSF | N104: % of Mix | P104: Property Mix Total | Q104: Units | R104: SF | S104: Rent | T104: PSF | U104: % of Mix | W104: Property Mix Total | X104: Units | Y104: SF | Z104: Rent | AA104: PSF | AB104: % of Mix | AD104: Property Mix Total | AE104: Units | AF104: SF | AG104: Rent | AH104: PSF | AI104: % of Mix | AK104: Property Mix Total | AL104: Units | AM104: SF | AN104: Rent | AO104: PSF | AP104: % of Mix
B105: Efficiency | C105: =+C28 -> 0 | D105: =D29 -> 0 | E105: =E29 -> 0 | F105: =IFERROR(E105/D105,0) -> 0 | G105: =C105/C2 -> #DIV/0! | I105: Efficiency | J105: =+J28 -> 0 | K105: =K29 -> 0 | L105: =L29 -> 0 | M105: =IFERROR(L105/K105,0) -> 0 | N105: =J105/J2 -> #DIV/0! | P105: Efficiency | Q105: =+Q28 -> 0 | R105: =R29 -> 0 | S105: =S29 -> 0 | T105: =IFERROR(S105/R105,0) -> 0 | U105: =Q105/Q2 -> #DIV/0! | W105: Efficiency | X105: =+X28 -> 0 | Y105: =Y29 -> 0 | Z105: =Z29 -> 0 | AA105: =IFERROR(Z105/Y105,0) -> 0 | AB105: =X105/X2 -> #DIV/0! | AD105: Efficiency | AE105: =+AE28 -> 0 | AF105: =AF29 -> 0 | AG105: =AG29 -> 0 | AH105: =IFERROR(AG105/AF105,0) -> 0 | AI105: =AE105/AE2 -> #DIV/0! | AK105: Efficiency | AL105: =+AL28 -> 0 | AM105: =AM29 -> 0 | AN105: =AN29 -> 0 | AO105: =IFERROR(AN105/AM105,0) -> 0 | AP105: =AL105/AL2 -> #DIV/0!
B106: 1 Bedroom | C106: =C57 -> 0 | D106: =D58 -> 0 | E106: =E58 -> 0 | F106: =IFERROR(E106/D106,0) -> 0 | G106: =C106/C2 -> #DIV/0! | I106: 1 Bedroom | J106: =J57 -> 0 | K106: =K58 -> 0 | L106: =L58 -> 0 | M106: =IFERROR(L106/K106,0) -> 0 | N106: =J106/J2 -> #DIV/0! | P106: 1 Bedroom | Q106: =Q57 -> 0 | R106: =R58 -> 0 | S106: =S58 -> 0 | T106: =IFERROR(S106/R106,0) -> 0 | U106: =Q106/Q2 -> #DIV/0! | W106: 1 Bedroom | X106: =X57 -> 0 | Y106: =Y58 -> 0 | Z106: =Z58 -> 0 | AA106: =IFERROR(Z106/Y106,0) -> 0 | AB106: =X106/X2 -> #DIV/0! | AD106: 1 Bedroom | AE106: =AE57 -> 0 | AF106: =AF58 -> 0 | AG106: =AG58 -> 0 | AH106: =IFERROR(AG106/AF106,0) -> 0 | AI106: =AE106/AE2 -> #DIV/0! | AK106: 1 Bedroom | AL106: =AL57 -> 0 | AM106: =AM58 -> 0 | AN106: =AN58 -> 0 | AO106: =IFERROR(AN106/AM106,0) -> 0 | AP106: =AL106/AL2 -> #DIV/0!
B107: 2 Bedroom | C107: =C85 -> 0 | D107: =D86 -> 0 | E107: =E86 -> 0 | F107: =IFERROR(E107/D107,0) -> 0 | G107: =C107/C2 -> #DIV/0! | I107: 2 Bedroom | J107: =J85 -> 0 | K107: =K86 -> 0 | L107: =L86 -> 0 | M107: =IFERROR(L107/K107,0) -> 0 | N107: =J107/J2 -> #DIV/0! | P107: 2 Bedroom | Q107: =Q85 -> 0 | R107: =R86 -> 0 | S107: =S86 -> 0 | T107: =IFERROR(S107/R107,0) -> 0 | U107: =Q107/Q2 -> #DIV/0! | W107: 2 Bedroom | X107: =X85 -> 0 | Y107: =Y86 -> 0 | Z107: =Z86 -> 0 | AA107: =IFERROR(Z107/Y107,0) -> 0 | AB107: =X107/X2 -> #DIV/0! | AD107: 2 Bedroom | AE107: =AE85 -> 0 | AF107: =AF86 -> 0 | AG107: =AG86 -> 0 | AH107: =IFERROR(AG107/AF107,0) -> 0 | AI107: =AE107/AE2 -> #DIV/0! | AK107: 2 Bedroom | AL107: =AL85 -> 0 | AM107: =AM86 -> 0 | AN107: =AN86 -> 0 | AO107: =IFERROR(AN107/AM107,0) -> 0 | AP107: =AL107/AL2 -> #DIV/0!
B108: 3 Bedroom | C108: =C101 -> 0 | D108: =D102 -> 0 | E108: =E102 -> 0 | F108: =IFERROR(E108/D108,0) -> 0 | G108: =C108/C2 -> #DIV/0! | I108: 3 Bedroom | J108: =J101 -> 0 | K108: =K102 -> 0 | L108: =L102 -> 0 | M108: =IFERROR(L108/K108,0) -> 0 | N108: =J108/J2 -> #DIV/0! | P108: 3 Bedroom | Q108: =Q101 -> 0 | R108: =R102 -> 0 | S108: =S102 -> 0 | T108: =IFERROR(S108/R108,0) -> 0 | U108: =Q108/Q2 -> #DIV/0! | W108: 3 Bedroom | X108: =X101 -> 0 | Y108: =Y102 -> 0 | Z108: =Z102 -> 0 | AA108: =IFERROR(Z108/Y108,0) -> 0 | AB108: =X108/X2 -> #DIV/0! | AD108: 3 Bedroom | AE108: =AE101 -> 0 | AF108: =AF102 -> 0 | AG108: =AG102 -> 0 | AH108: =IFERROR(AG108/AF108,0) -> 0 | AI108: =AE108/AE2 -> #DIV/0! | AK108: 3 Bedroom | AL108: =AL101 -> 0 | AM108: =AM102 -> 0 | AN108: =AN102 -> 0 | AO108: =IFERROR(AN108/AM108,0) -> 0 | AP108: =AL108/AL2 -> #DIV/0!
B109: Total/Average | C109: =SUM(C105:C108) -> 0 | D109: =IFERROR(SUMPRODUCT(D105:D108,C105:C108)/C109,0) -> 0 | E109: =IFERROR(SUMPRODUCT(E105:E108,C105:C108)/C109,0) -> 0 | F109: =IFERROR(SUMPRODUCT(F105:F108,C105:C108)/C109,0) -> 0 | G109: =SUM(G105:G108) -> #DIV/0! | I109: Total/Average | J109: =SUM(J105:J108) -> 0 | K109: =IFERROR(SUMPRODUCT(K105:K108,J105:J108)/J109,0) -> 0 | L109: =IFERROR(SUMPRODUCT(L105:L108,J105:J108)/J109,0) -> 0 | M109: =IFERROR(SUMPRODUCT(M105:M108,J105:J108)/J109,0) -> 0 | N109: =SUM(N105:N108) -> #DIV/0! | P109: Total/Average | Q109: =SUM(Q105:Q108) -> 0 | R109: =IFERROR(SUMPRODUCT(R105:R108,Q105:Q108)/Q109,0) -> 0 | S109: =IFERROR(SUMPRODUCT(S105:S108,Q105:Q108)/Q109,0) -> 0 | T109: =IFERROR(SUMPRODUCT(T105:T108,Q105:Q108)/Q109,0) -> 0 | U109: =SUM(U105:U108) -> #DIV/0! | W109: Total/Average | X109: =SUM(X105:X108) -> 0 | Y109: =IFERROR(SUMPRODUCT(Y105:Y108,X105:X108)/X109,0) -> 0 | Z109: =IFERROR(SUMPRODUCT(Z105:Z108,X105:X108)/X109,0) -> 0 | AA109: =IFERROR(SUMPRODUCT(AA105:AA108,X105:X108)/X109,0) -> 0 | AB109: =SUM(AB105:AB108) -> #DIV/0! | AD109: Total/Average | AE109: =SUM(AE105:AE108) -> 0 | AF109: =IFERROR(SUMPRODUCT(AF105:AF108,AE105:AE108)/AE109,0) -> 0 | AG109: =IFERROR(SUMPRODUCT(AG105:AG108,AE105:AE108)/AE109,0) -> 0 | AH109: =IFERROR(SUMPRODUCT(AH105:AH108,AE105:AE108)/AE109,0) -> 0 | AI109: =SUM(AI105:AI108) -> #DIV/0! | AK109: Total/Average | AL109: =SUM(AL105:AL108) -> 0 | AM109: =IFERROR(SUMPRODUCT(AM105:AM108,AL105:AL108)/AL109,0) -> 0 | AN109: =IFERROR(SUMPRODUCT(AN105:AN108,AL105:AL108)/AL109,0) -> 0 | AO109: =IFERROR(SUMPRODUCT(AO105:AO108,AL105:AL108)/AL109,0) -> 0 | AP109: =SUM(AP105:AP108) -> #DIV/0!
B110: Notes: | I110: Notes: | P110: Notes: | W110: Notes: | AD110: Notes: | AK110: Notes:
