Workbook
Name units: [1]Rents!$C$51
Name Units: Rent!$D$29

Sheet CFS-Main Page
B2: Calabash Shores | C2: Address: | D2: 660 Aubrey Ln Calabash, NC, 28467
B3: Cashflow Statement - Main Page | C3: Units | D3: =Units -> 132
C4: Year Built/Reno | D4: 2024 | F4: Scenario | G4: 2 | M4: Tax rate info. | P4: County Link: | Q4: Link
B5: Analysis Start Date | C5: 46174 | G5: =10925000 -> 10925000 | M5: Districts | N5: Jurisdictions | Q5: 2025 Rate
B6: Investment Assumptions/Summary | D6: Per Unit | F6: Pro forma Assumptions | I6: Key Metrics | N6: Calabash | Q6: 0.342
B7: Purchase Price | C7: =IF(OR(G4=0,G4=1),J8,K8)*1000000 -> 35000000 | D7: =C7/$D$3 -> 265151.52 | F7: Rent Increase (Y2 Onwards) | H7: 0.03 | I7: =B2 -> Calabash Shores | J7: 1 | K7: 2 | L7: Broker's Numbers | N7: Brunswick County | Q7: 0.07
B8: NOI After Reserve | C8: =I66 -> 1871250.5 | D8: =C8/$D$3 -> 14176.14 | F8: Other Income Increase (Y2) | H8: =H7 -> 0.03 | I8: Asking Price | J8: =IF(G4=2,"",L8) | K8: 35 | L8: 0
B9: All in Cost | C9: ='Sources & Usage'!C9 -> 35595000 | D9: =C9/$D$3 -> 269659.09 | F9: Expense Increase (Year 2 Onwards) | H9: 0.0275 | I9: Y1 NOI | J9: =IF(G4=2,"",I63) | K9: =IF(G4=1,"",I63) -> 1871250.5 | L9: =H63 -> 2254500
B10: PP Cap Rate | C10: =C8/C7 -> 0.053464299 | F10: Property Management Fee | H10: 0.0275 | I10: Cap rate | J10: =IF(G4=2,"",J9/(J8*1000000)) | K10: =IF(G4=1,"",K9/(K8*1000000)) -> 0.053464299 | L10: 0
B11: Total Rentable Square Feet | C11: =Rent!I29 -> 131840 | D11: =C11/$D$3 -> 998.78788 | F11: Asset Management Fee | H11: 0 | I11: Levered COC | J11: =IF(G4=2,"",G76) | K11: =IF(G4=1,"",G76) -> 0.044291737 | L11: -
B12: Cash on Cash Return | C12: =I76 -> 0.051357409 | F12: Cost of Exit (Brokerage) | H12: 0.01 | I12: Levered IRR | J12: =IF(G4=2,"",G78) | K12: =IF(G4=1,"",G78) -> 0.038638988 | L12: -
B13: Exit Year | C13: 5 | F13: Replacement Reserve (Per Unit) | H13: 0 | I13: Y1 Yield on Cost | J13: =IF(G4=2,"",$I$63/(J8*1000000)) | K13: =IF(G4=1,"",$I$63/'Sources & Usage'!$C$23) -> 0.052570599 | L13: -
B14: Exit Cap Rate | C14: 0.06 | F14: Assesment Ratio | G14: 1 | H14: =G14*C7 -> 35000000 | I14: Reappraisal happens every 4 years in Brunswick County with the next assessment in 2027.
B15: Exit NOI (After Reserve) | C15: =HLOOKUP($C$13+1,$I$46:$S$66,ROWS($I$46:$I$66)) -> 2093870.7 | D15: =C15/$D$3 -> 15862.657 | F15: Y1 Tax Reassessed | G15: =Q16 -> 0.00412 | H15: =(G15*H14)+16000 -> 160200
B16: Exit Price | C16: =HLOOKUP($C$13,$I$46:$S$67,ROWS($I$46:$I$67)) -> 34548867 | D16: =C16/$D$3 -> 261733.84 | F16: Tax growth (Y2 Onwards) | H16: 0.03 | I16: Direct tax in last tax bill was $16000 which is included for Y1 Tax calculations. | N16: Millage Rate | Q16: =SUM(Q6:Q15)/100 -> 0.00412
B18: Rental Assumptions | D18: =Rent!D5 -> 46066 | F18: T3 | G18: T12 | H18: Broker Numbers | I18: 1 | J18: =IF(I18<$C$13+1,I18+1,"") -> 2 | K18: =IF(J18<$C$13+1,J18+1,"") -> 3 | L18: =IF(K18<$C$13+1,K18+1,"") -> 4 | M18: =IF(L18<$C$13+1,L18+1,"") -> 5 | N18: =IF(M18<$C$13+1,M18+1,"") -> 6 | O18: =IF(N18<$C$13+1,N18+1,"") | P18: =IF(O18<$C$13+1,O18+1,"") | Q18: =IF(P18<$C$13+1,P18+1,"") | ... AC18: =IF(AB18<$C$13+1,AB18+1,"")
B19: Loss to Lease | D19: =Rent!H32/Rent!H30 -> -0.016852082 | F19: =-F34/F33 -> 0 | G19: =-G34/G33 -> 0 | H19: =-H34/H33 -> 0 | I19: =-I34/I33 -> -0.016852082 | J19: 0.01 | K19: 0.01 | L19: 0.01 | M19: 0.01 | N19: =M19 -> 0.01 | O19: =N19 -> 0.01 | P19: =O19 -> 0.01 | Q19: =P19 -> 0.01 | R19: =Q19 -> 0.01 | S19: =R19 -> 0.01 | T19: =S19 -> 0.01 | U19: =T19 -> 0.01 | ... AB19: =AA19 -> 0.01
B20: Vacancy | D20: =1-Rent!H29 -> 0.71969697 | F20: =-F36/$G$35 -> 0.56319934 | G20: =-G36/$G$35 -> 0.84663328 | H20: =-H36/$H$35 -> 0.05 | I20: 0.05 | J20: 0.05 | K20: 0.05 | L20: 0.05 | M20: =L20 -> 0.05 | N20: =M20 -> 0.05 | O20: =N20 -> 0.05 | P20: =O20 -> 0.05 | Q20: =P20 -> 0.05 | R20: =Q20 -> 0.05 | S20: =R20 -> 0.05 | T20: =S20 -> 0.05 | ... AB20: =AA20 -> 0.05
B21: Concession/Discount | F21: =-F37/$G$35 -> 0.063974054 | G21: =-G37/$G$35 -> 0.032579475 | H21: =-H37/$H$35 -> 0.03 | I21: 0.01 | J21: 0.01 | K21: 0.01 | L21: 0.01 | M21: =L21 -> 0.01 | N21: =M21 -> 0.01 | O21: =N21 -> 0.01 | P21: =O21 -> 0.01 | Q21: =P21 -> 0.01 | R21: =Q21 -> 0.01 | S21: =R21 -> 0.01 | T21: =S21 -> 0.01 | ... AB21: =AA21 -> 0.01
B22: Bad Debt | F22: =-F38/$G$35 -> 0 | G22: =-G38/$G$35 -> 0 | H22: =-H38/$H$35 -> 0 | I22: 0 | J22: 0 | K22: =J22 -> 0 | L22: =K22 -> 0 | M22: =L22 -> 0 | N22: =M22 -> 0 | O22: =N22 -> 0 | P22: =O22 -> 0 | Q22: =P22 -> 0 | R22: =Q22 -> 0 | ... AB22: =AA22 -> 0
B23: Non Revenue Units | F23: =-F39/$G$35 -> 0 | G23: =-G39/$G$35 -> 0.0029700022 | H23: =-H39/$H$35 -> 0 | I23: =G23 -> 0.0029700022 | J23: =I23 -> 0.0029700022 | K23: =J23 -> 0.0029700022 | L23: =K23 -> 0.0029700022 | M23: =L23 -> 0.0029700022 | N23: =M23 -> 0.0029700022 | O23: =N23 -> 0.0029700022 | P23: =O23 -> 0.0029700022 | Q23: =P23 -> 0.0029700022 | ... AB23: =AA23 -> 0.0029700022
D24: =Rent!H29 -> 0.28030303
B25: Average Rent (GRP) | F25: =F35/Units/12 -> 1970.4798 | G25: =G35/Units/12 -> 2440.2254 | H25: =H35/Units/12 -> 1959.8485 | I25: =I35/Units/12 -> 1996.6892 | J25: =IF(J$18="","",J35/Units/12) -> 2002.2814 | K25: =IF(K$18="","",K35/Units/12) -> 2062.3498 | L25: =IF(L$18="","",L35/Units/12) -> 2124.2203 | M25: =IF(M$18="","",M35/Units/12) -> 2187.9469 | N25: =IF(N$18="","",N35/Units/12) -> 2253.5853 | O25: =IF(O$18="","",O35/Units/12) | P25: =IF(P$18="","",P35/Units/12) | Q25: =IF(Q$18="","",Q35/Units/12) | ... AC25: =IF(AC$18="","",AC35/Units/12)
B26: GRP Increases | I26: =IF(I$18="","",I35/G35-1) -> -0.18176033 | J26: =IF(J$18="","",J35/I35-1) -> 0.0028007199 | K26: =IF(K$18="","",K35/J35-1) -> 0.03 | L26: =IF(L$18="","",L35/K35-1) -> 0.03 | M26: =IF(M$18="","",M35/L35-1) -> 0.03 | N26: =IF(N$18="","",N35/M35-1) -> 0.03 | O26: =IF(O$18="","",O35/N35-1) | P26: =IF(P$18="","",P35/O35-1) | Q26: =IF(Q$18="","",Q35/P35-1) | ... AC26: =IF(AC$18="","",AC35/AB35-1)
B27: Economic Occupancy | F27: =IF(F$18="","",F40/F35) -> 0.22331381 | G27: =IF(G$18="","",G40/G35) -> 0.11781725 | H27: =IF(H$18="","",H40/H35) -> 0.92 | I27: =IF(I$18="","",I40/I35) -> 0.93703 | J27: =IF(J$18="","",J40/J35) -> 0.93703 | K27: =IF(K$18="","",K40/K35) -> 0.93703 | L27: =IF(L$18="","",L40/L35) -> 0.93703 | M27: =IF(M$18="","",M40/M35) -> 0.93703 | ... AC27: =IF(AC$18="","",AC40/AC35)
B28: GEI Increases | I28: =IF(I$18="","",I40/G40-1) -> 5.5076646 | J28: =IF(J$18="","",J40/I40-1) -> 0.0028007199 | K28: =IF(K$18="","",K40/J40-1) -> 0.03 | L28: =IF(L$18="","",L40/K40-1) -> 0.03 | M28: =IF(M$18="","",M40/L40-1) -> 0.03 | N28: =IF(N$18="","",N40/M40-1) -> 0.03 | O28: =IF(O$18="","",O40/N40-1) | P28: =IF(P$18="","",P40/O40-1) | Q28: =IF(Q$18="","",Q40/P40-1) | ... AC28: =IF(AC$18="","",AC40/AB40-1)
B30: Income | D30: Per Unit (T12) | E30: Per Unit Y1 | F30: =F18 -> T3 | G30: T12 | H30: Broker's Numbers | I30: 1 | J30: =IF(I30<$C$13+1,I30+1,"") -> 2 | K30: =IF(J30<$C$13+1,J30+1,"") -> 3 | L30: =IF(K30<$C$13+1,K30+1,"") -> 4 | M30: =IF(L30<$C$13+1,L30+1,"") -> 5 | N30: =IF(M30<$C$13+1,M30+1,"") -> 6 | O30: =IF(N30<$C$13+1,N30+1,"") | P30: =IF(O30<$C$13+1,O30+1,"") | Q30: =IF(P30<$C$13+1,P30+1,"") | ... AC30: =IF(AB30<$C$13+1,AB30+1,"")
B31: Market Rent Potential | D31: =G31/Units -> 29282.705 | E31: =I31/Units -> 23563.182 | F31: ='Historical Analysis'!X9 -> 3121240 | G31: ='Historical Analysis'!W9 -> 3865317 | H31: 3104400 | I31: {=(SUMPRODUCT(Rent!$K$9:$K$28*(Rent!$L$9:$L$28=Rent!$K$8),Rent!$D$9:$D$28)+SUMPRODUCT(Rent!$J$9:$J$28*(Rent!$L$9:$L$28=Rent!$J$8),Rent!$D$9:$D$28))*12} -> 3110340 | J31: =IF(J$30>$C$13+1,"",I$31*(1+$H$7)) -> 3203650.2 | K31: =IF(K$30>$C$13+1,"",J$31*(1+$H$7)) -> 3299759.7 | L31: =IF(L$30>$C$13+1,"",K$31*(1+$H$7)) -> 3398752.5 | M31: =IF(M$30>$C$13+1,"",L$31*(1+$H$7)) -> 3500715.1 | N31: =IF(N$30>$C$13+1,"",M$31*(1+$H$7)) -> 3605736.5 | O31: =IF(O$30>$C$13+1,"",N$31*(1+$H$7)) | P31: =IF(P$30>$C$13+1,"",O$31*(1+$H$7)) | Q31: =IF(Q$30>$C$13+1,"",P$31*(1+$H$7)) | ... AC31: =IF(AC$30>$C$13+1,"",AB$31*(1+$H$7))
B32: Renovation Premium | D32: =G32/Units -> 0 | E32: =I32/Units -> 0 | F32: ='Historical Analysis'!X10 -> 0 | G32: ='Historical Analysis'!W10 -> 0 | H32: 0 | I32: =Rent!I57*12/3 -> 0 | J32: =IF(J30<=$C$13+1,(Rent!I57*12/3)+I32*(1+$H$7),"") -> 0 | K32: =IF(K30<=$C$13+1,(Rent!I57*12/3)+J32*(1+$H$7),"") -> 0 | L32: =IF(L30<=$C$13+1,K32*(1+$H$7),"") -> 0 | M32: =IF(M30<=$C$13+1,L32*(1+$H$7),"") -> 0 | N32: =IF(N30<=$C$13+1,M32*(1+$H$7),"") -> 0 | O32: =IF(O30<=$C$13+1,N32*(1+$H$7),"") | P32: =IF(P30<=$C$13+1,O32*(1+$H$7),"") | Q32: =IF(Q30<=$C$13+1,P32*(1+$H$7),"") | R32: =IF(R30<=$C$13+1,Q32*(1+$H$7),"") | S32: =IF(S30<=$C$13+1,R32*(1+$H$7),"") | ... AC32: =IF(AC30<=$C$13+1,AB32*(1+$H$7),"")
B33: Total Market Rent Potential | D33: =G33/Units -> 29282.705 | E33: =I33/Units -> 23563.182 | F33: =F31+F32 -> 3121240 | G33: =G31+G32 -> 3865317 | H33: =SUM(H31:H32) -> 3104400 | I33: =IF(I$30<=$C$13+1,I31+I32,"") -> 3110340 | J33: =IF(J$30<=$C$13+1,J31+J32,"") -> 3203650.2 | K33: =IF(K$30<=$C$13+1,K31+K32,"") -> 3299759.7 | L33: =IF(L$30<=$C$13+1,L31+L32,"") -> 3398752.5 | M33: =IF(M$30<=$C$13+1,M31+M32,"") -> 3500715.1 | N33: =IF(N$30<=$C$13+1,N31+N32,"") -> 3605736.5 | O33: =IF(O$30<=$C$13+1,O31+O32,"") | P33: =IF(P$30<=$C$13+1,P31+P32,"") | ... AC33: =IF(AC$30<=$C$13+1,AC31+AC32,"")
B34: Loss to Lease | D34: =G34/Units -> 0 | E34: =I34/Units -> 397.08868 | F34: ='Historical Analysis'!X12 -> 0 | G34: ='Historical Analysis'!W12 -> 0 | H34: 0 | I34: =IF(I$30<=$C$13+1,I35-I33,"") -> 52415.705 | J34: =IF(J$30<=$C$13+1,-J19*J33,"") -> -32036.502 | K34: =IF(K$30<=$C$13+1,-K19*K33,"") -> -32997.597 | L34: =IF(L$30<=$C$13+1,-L19*L33,"") -> -33987.525 | M34: =IF(M$30<=$C$13+1,-M19*M33,"") -> -35007.151 | N34: =IF(N$30<=$C$13+1,-N19*N33,"") -> -36057.365 | O34: =IF(O$30<=$C$13+1,-O19*O33,"") | P34: =IF(P$30<=$C$13+1,-P19*P33,"") | Q34: =IF(Q$30<=$C$13+1,-Q19*Q33,"") | ... AC34: =IF(AC$30<=$C$13+1,-AC19*AC33,"")
B35: Scheduled Rental Income | D35: =G35/Units -> 29282.705 | E35: =I35/Units -> 23960.27 | F35: =F33+F34 -> 3121240 | G35: =G33+G34 -> 3865317 | H35: =SUM(H33:H34) -> 3104400 | I35: =IF(I$30<=$C$13+1,Rent!N29*12,"") -> 3162755.7 | J35: =IF(J$30<=$C$13+1,J33+J34,"") -> 3171613.7 | K35: =IF(K$30<=$C$13+1,K33+K34,"") -> 3266762.1 | L35: =IF(L$30<=$C$13+1,L33+L34,"") -> 3364765 | M35: =IF(M$30<=$C$13+1,M33+M34,"") -> 3465707.9 | N35: =IF(N$30<=$C$13+1,N33+N34,"") -> 3569679.2 | O35: =IF(O$30<=$C$13+1,O33+O34,"") | P35: =IF(P$30<=$C$13+1,P33+P34,"") | Q35: =IF(Q$30<=$C$13+1,Q33+Q34,"") | ... AC35: =IF(AC$30<=$C$13+1,AC33+AC34,"")
B36: Vacancy | D36: =G36/Units -> -24791.712 | E36: =I36/Units -> -1198.0135 | F36: ='Historical Analysis'!X14 -> -2176944 | G36: ='Historical Analysis'!W14 -> -3272506 | H36: -155220 | I36: =IF(I$30<=$C$13+1,-I$35*I20,"") -> -158137.79 | J36: =IF(J$30<=$C$13+1,-J$35*J20,"") -> -158580.68 | K36: =IF(K$30<=$C$13+1,-K$35*K20,"") -> -163338.11 | L36: =IF(L$30<=$C$13+1,-L$35*L20,"") -> -168238.25 | M36: =IF(M$30<=$C$13+1,-M$35*M20,"") -> -173285.4 | N36: =IF(N$30<=$C$13+1,-N$35*N20,"") -> -178483.96 | O36: =IF(O$30<=$C$13+1,-O$35*O20,"") | P36: =IF(P$30<=$C$13+1,-P$35*P20,"") | ... AC36: =IF(AC$30<=$C$13+1,-AC$35*AC20,"")
B37: Concession/Discount | D37: =G37/Units -> -954.01515 | E37: =I37/Units -> -239.6027 | F37: ='Historical Analysis'!X15 -> -247280 | G37: ='Historical Analysis'!W15 -> -125930 | H37: -93132 | I37: =IF(I$30<=$C$13+1,-I$35*I21,"") -> -31627.557 | J37: =IF(J$30<=$C$13+1,-J$35*J21,"") -> -31716.137 | K37: =IF(K$30<=$C$13+1,-K$35*K21,"") -> -32667.621 | L37: =IF(L$30<=$C$13+1,-L$35*L21,"") -> -33647.65 | M37: =IF(M$30<=$C$13+1,-M$35*M21,"") -> -34657.079 | N37: =IF(N$30<=$C$13+1,-N$35*N21,"") -> -35696.792 | O37: =IF(O$30<=$C$13+1,-O$35*O21,"") | P37: =IF(P$30<=$C$13+1,-P$35*P21,"") | ... AC37: =IF(AC$30<=$C$13+1,-AC$35*AC21,"")
B38: Bad Debt | D38: =G38/Units -> 0 | E38: =I38/Units -> 0 | F38: ='Historical Analysis'!X16 -> 0 | G38: ='Historical Analysis'!W16 -> 0 | H38: 0 | I38: =IF(I$30<=$C$13+1,-I$35*I22,"") -> 0 | J38: =IF(J$30<=$C$13+1,-J$35*J22,"") -> 0 | K38: =IF(K$30<=$C$13+1,-K$35*K22,"") -> 0 | L38: =IF(L$30<=$C$13+1,-L$35*L22,"") -> 0 | M38: =IF(M$30<=$C$13+1,-M$35*M22,"") -> 0 | N38: =IF(N$30<=$C$13+1,-N$35*N22,"") -> 0 | O38: =IF(O$30<=$C$13+1,-O$35*O22,"") | P38: =IF(P$30<=$C$13+1,-P$35*P22,"") | ... AC38: =IF(AC$30<=$C$13+1,-AC$35*AC22,"")
B39: Non Revenue Units | D39: =G39/Units -> -86.969697 | E39: =I39/Units -> -71.162056 | F39: ='Historical Analysis'!X17 -> 0 | G39: ='Historical Analysis'!W17 -> -11480 | H39: 0 | I39: =IF(I$30<=$C$13+1,-I$35*I23,"") -> -9393.3914 | J39: =IF(J$30<=$C$13+1,-J$35*J23,"") -> -9419.6997 | K39: =IF(K$30<=$C$13+1,-K$35*K23,"") -> -9702.2907 | L39: =IF(L$30<=$C$13+1,-L$35*L23,"") -> -9993.3594 | M39: =IF(M$30<=$C$13+1,-M$35*M23,"") -> -10293.16 | N39: =IF(N$30<=$C$13+1,-N$35*N23,"") -> -10601.955 | O39: =IF(O$30<=$C$13+1,-O$35*O23,"") | P39: =IF(P$30<=$C$13+1,-P$35*P23,"") | ... Z39: =IF(Z$30<=$C$13+1,-Z$35*Z23,"") | AA39: =IF(AA$30<=$C$13+1,Z39*(1+$H$7),"") | AB39: =IF(AB$30<=$C$13+1,AA39*(1+$H$7),"") | AC39: =IF(AC$30<=$C$13+1,AB39*(1+$H$7),"")
B40: Gross Effective Income | D40: =G40/Units -> 3450.0076 | E40: =I40/Units -> 22451.492 | F40: =F35+SUM(F36:F39) -> 697016 | G40: =G35+SUM(G36:G39) -> 455401 | H40: =SUM(H35:H39) -> 2856048 | I40: =IF(I$30<=$C$13+1,SUM(I35:I39),"") -> 2963597 | J40: =IF(J$30<=$C$13+1,SUM(J35:J39),"") -> 2971897.2 | K40: =IF(K$30<=$C$13+1,SUM(K35:K39),"") -> 3061054.1 | L40: =IF(L$30<=$C$13+1,SUM(L35:L39),"") -> 3152885.7 | M40: =IF(M$30<=$C$13+1,SUM(M35:M39),"") -> 3247472.3 | N40: =IF(N$30<=$C$13+1,SUM(N35:N39),"") -> 3344896.5 | O40: =IF(O$30<=$C$13+1,SUM(O35:O39),"") | P40: =IF(P$30<=$C$13+1,SUM(P35:P39),"") | ... AC40: =IF(AC$30<=$C$13+1,SUM(AC35:AC39),"")
B41: Utility Reimbursements | D41: =G41/Units -> 4.4318182 | E41: 15 | F41: ='Historical Analysis'!X19 -> 2340 | G41: ='Historical Analysis'!W19 -> 585 | H41: =173052+72230 -> 245282 | I41: =IF(I$46="","",E41*Units) -> 1980 | J41: =IF(J$46="","",I41*(1+$H$9)) -> 2034.45 | K41: =IF(K$46="","",J41*(1+$H$9)) -> 2090.3974 | L41: =IF(L$46="","",K41*(1+$H$9)) -> 2147.8833 | M41: =IF(M$46="","",L41*(1+$H$9)) -> 2206.9501 | N41: =IF(N$46="","",M41*(1+$H$9)) -> 2267.6412 | O41: =IF(O$46="","",N41*(1+$H$9)) | P41: =IF(P$46="","",O41*(1+$H$9)) | Q41: =IF(Q$46="","",P41*(1+$H$9)) | ... AC41: =IF(AC$46="","",AB41*(1+$H$9))
B42: Other Reimbursements | D42: =G42/Units -> 0.93939394 | E42: 5 | F42: ='Historical Analysis'!X20 -> 496 | G42: ='Historical Analysis'!W20 -> 124 | H42: 60192 | I42: =IF(I$46="","",E42*Units) -> 660 | J42: =IF(J$30="","",(I42*(1+$H$9))) -> 678.15 | K42: =IF(K$46="","",J42*(1+$H$9)) -> 696.79913 | L42: =IF(L$46="","",K42*(1+$H$9)) -> 715.9611 | M42: =IF(M$46="","",L42*(1+$H$9)) -> 735.65003 | N42: =IF(N$46="","",M42*(1+$H$9)) -> 755.88041 | O42: =IF(O$46="","",N42*(1+$H$9)) | P42: =IF(P$46="","",O42*(1+$H$9)) | Q42: =IF(Q$46="","",P42*(1+$H$9)) | R42: =IF(R$46="","",Q42*(1+$H$9)) | ... AC42: =IF(AC$46="","",AB42*(1+$H$9))
B43: Other Income | D43: =G43/Units -> 215.21023 | E43: 500 | F43: ='Historical Analysis'!X21 -> 45501 | G43: ='Historical Analysis'!W21 -> 28407.75 | H43: =5000+37620+3400+19320 -> 65340 | I43: =IF(I$46="","",E43*Units) -> 66000 | J43: =IF(J$46="","",I43*(1+$H$8)) -> 67980 | K43: =IF(K$46="","",J43*(1+$H$8)) -> 70019.4 | L43: =IF(L$46="","",K43*(1+$H$8)) -> 72119.982 | M43: =IF(M$46="","",L43*(1+$H$8)) -> 74283.581 | N43: =IF(N$46="","",M43*(1+$H$8)) -> 76512.089 | O43: =IF(O$46="","",N43*(1+$H$8)) | P43: =IF(P$46="","",O43*(1+$H$8)) | Q43: =IF(Q$46="","",P43*(1+$H$8)) | ... AC43: =IF(AC$46="","",AB43*(1+$H$8))
B44: Total Operating Revenue | D44: =G44/Units -> 3670.589 | E44: =J44/Units -> 23049.923 | F44: =SUM(F40:F43) -> 745353 | G44: =SUM(G40:G43) -> 484517.75 | H44: =SUM(H40:H43) -> 3226862 | I44: =IF(I$30="","",SUM(I40:I43)) -> 3032237 | J44: =IF(J$30="","",SUM(J40:J43)) -> 3042589.8 | K44: =IF(K$30="","",SUM(K40:K43)) -> 3133860.7 | L44: =IF(L$30="","",SUM(L40:L43)) -> 3227869.5 | M44: =IF(M$30="","",SUM(M40:M43)) -> 3324698.5 | N44: =IF(N$30="","",SUM(N40:N43)) -> 3424432.1 | O44: =IF(O$30="","",SUM(O40:O43)) | P44: =IF(P$30="","",SUM(P40:P43)) | ... AC44: =IF(AC$30="","",SUM(AC40:AC43))
R45: =IF(R30<=$C$13+1,R44-Q44,"") | S45: =IF(S30<=$C$13+1,S44-R44,"") | T45: =IF(T30<=$C$13+1,T44-S44,"") | U45: =IF(U30<=$C$13+1,U44-T44,"") | V45: =IF(V30<=$C$13+1,V44-U44,"") | W45: =IF(W30<=$C$13+1,W44-V44,"") | X45: =IF(X30<=$C$13+1,X44-W44,"") | Y45: =IF(Y30<=$C$13+1,Y44-X44,"") | ... AC45: =IF(AC30<=$C$13+1,AC44-AB44,"")
B46: Operating Expenses | D46: Per Unit (T12) | E46: Per Unit Y1 | F46: =F30 -> T3 | G46: T12 | H46: Broker's Numbers | I46: 1 | J46: =IF(I46<$C$13+1,I46+1,"") -> 2 | K46: =IF(J46<$C$13+1,J46+1,"") -> 3 | L46: =IF(K46<$C$13+1,K46+1,"") -> 4 | M46: =IF(L46<$C$13+1,L46+1,"") -> 5 | N46: =IF(M46<$C$13+1,M46+1,"") -> 6 | O46: =IF(N46<$C$13+1,N46+1,"") | P46: =IF(O46<$C$13+1,O46+1,"") | Q46: =IF(P46<$C$13+1,P46+1,"") | ... AC46: =IF(AB46<$C$13+1,AB46+1,"")
B47: Repair & Maintenance | D47: =G47/Units -> 1390.6609 | E47: 1450 | F47: ='Historical Analysis'!X25 -> 172429.24 | G47: ='Historical Analysis'!W25 -> 183567.24 | H47: =20500+4500+6360+3500+8500+4500+600+600+7500+65000 -> 121560 | I47: =IF(I$46="","",E47*Units) -> 191400 | J47: =IF(J$46="","",I47*(1+$H$9)) -> 196663.5 | K47: =IF(K$46="","",J47*(1+$H$9)) -> 202071.75 | L47: =IF(L$46="","",K47*(1+$H$9)) -> 207628.72 | M47: =IF(M$46="","",L47*(1+$H$9)) -> 213338.51 | N47: =IF(N$46="","",M47*(1+$H$9)) -> 219205.32 | O47: =IF(O$46="","",N47*(1+$H$9)) | P47: =IF(P$46="","",O47*(1+$H$9)) | Q47: =IF(Q$46="","",P47*(1+$H$9)) | ... AC47: =IF(AC$46="","",AB47*(1+$H$9))
B48: Cleaning & Decorating | D48: =G48/Units -> 106.01947 | E48: 150 | F48: ='Historical Analysis'!X26 -> 27232.76 | G48: ='Historical Analysis'!W26 -> 13994.57 | H48: 21500 | I48: =IF(I$46="","",E48*Units) -> 19800 | J48: =IF(J$46="","",I48*(1+$H$9)) -> 20344.5 | K48: =IF(K$46="","",J48*(1+$H$9)) -> 20903.974 | L48: =IF(L$46="","",K48*(1+$H$9)) -> 21478.833 | M48: =IF(M$46="","",L48*(1+$H$9)) -> 22069.501 | N48: =IF(N$46="","",M48*(1+$H$9)) -> 22676.412 | O48: =IF(O$46="","",N48*(1+$H$9)) | P48: =IF(P$46="","",O48*(1+$H$9)) | Q48: =IF(Q$46="","",P48*(1+$H$9)) | ... AC48: =IF(AC$46="","",AB48*(1+$H$9))
B49: Contract & Services | D49: =G49/Units -> 112.61765 | E49: 150 | F49: ='Historical Analysis'!X27 -> 11974 | G49: ='Historical Analysis'!W27 -> 14865.53 | H49: =11088+8844 -> 19932 | I49: =IF(I$46="","",E49*Units) -> 19800 | J49: =IF(J$46="","",I49*(1+$H$9)) -> 20344.5 | K49: =IF(K$46="","",J49*(1+$H$9)) -> 20903.974 | L49: =IF(L$46="","",K49*(1+$H$9)) -> 21478.833 | M49: =IF(M$46="","",L49*(1+$H$9)) -> 22069.501 | N49: =IF(N$46="","",M49*(1+$H$9)) -> 22676.412 | O49: =IF(O$46="","",N49*(1+$H$9)) | P49: =IF(P$46="","",O49*(1+$H$9)) | Q49: =IF(Q$46="","",P49*(1+$H$9)) | ... AC49: =IF(AC$46="","",AB49*(1+$H$9))
B50: Utility | D50: =G50/Units -> 558.62826 | E50: 625 | F50: ='Historical Analysis'!X28 -> 75831.68 | G50: ='Historical Analysis'!W28 -> 73738.93 | H50: =97500+5040+11274 -> 113814 | I50: =IF(I$46="","",E50*Units) -> 82500 | J50: =IF(J$46="","",I50*(1+$H$9)) -> 84768.75 | K50: =IF(K$46="","",J50*(1+$H$9)) -> 87099.891 | L50: =IF(L$46="","",K50*(1+$H$9)) -> 89495.138 | M50: =IF(M$46="","",L50*(1+$H$9)) -> 91956.254 | N50: =IF(N$46="","",M50*(1+$H$9)) -> 94485.051 | O50: =IF(O$46="","",N50*(1+$H$9)) | P50: =IF(P$46="","",O50*(1+$H$9)) | Q50: =IF(Q$46="","",P50*(1+$H$9)) | ... AC50: =IF(AC$46="","",AB50*(1+$H$9))
B51: Utility- Water/Sewage | D51: =G51/Units -> 606.04265 | E51: 650 | F51: ='Historical Analysis'!X29 -> 89185 | G51: ='Historical Analysis'!W29 -> 79997.63 | H51: =37500+7200 -> 44700 | I51: =IF(I$46="","",E51*Units) -> 85800 | J51: =IF(J$46="","",I51*(1+$H$9)) -> 88159.5 | K51: =IF(K$46="","",J51*(1+$H$9)) -> 90583.886 | L51: =IF(L$46="","",K51*(1+$H$9)) -> 93074.943 | M51: =IF(M$46="","",L51*(1+$H$9)) -> 95634.504 | N51: =IF(N$46="","",M51*(1+$H$9)) -> 98264.453 | O51: =IF(O$46="","",N51*(1+$H$9)) | P51: =IF(P$46="","",O51*(1+$H$9)) | Q51: =IF(Q$46="","",P51*(1+$H$9)) | ... AC51: =IF(AC$46="","",AB51*(1+$H$9))
B52: Utility- Gas, Telephone & Others | D52: =G52/Units -> 55.402197 | E52: 100 | F52: ='Historical Analysis'!X30 -> 23186.4 | G52: ='Historical Analysis'!W30 -> 7313.09 | H52: =22500+2700+2300 -> 27500 | I52: =IF(I$46="","",E52*Units) -> 13200 | J52: =IF(J$46="","",I52*(1+$H$9)) -> 13563 | K52: =IF(K$46="","",J52*(1+$H$9)) -> 13935.983 | L52: =IF(L$46="","",K52*(1+$H$9)) -> 14319.222 | M52: =IF(M$46="","",L52*(1+$H$9)) -> 14713.001 | N52: =IF(N$46="","",M52*(1+$H$9)) -> 15117.608 | O52: =IF(O$46="","",N52*(1+$H$9)) | P52: =IF(P$46="","",O52*(1+$H$9)) | Q52: =IF(Q$46="","",P52*(1+$H$9)) | ... AC52: =IF(AC$46="","",AB52*(1+$H$9))
B53: RE Taxes | D53: =G53/Units -> 898.09561 | E53: =I53/Units -> 1213.6364 | F53: ='Historical Analysis'!X33 -> 118548.6 | G53: ='Historical Analysis'!W33 -> 118548.62 | H53: 130000 | I53: =IF(I$46="","",IF($F$15="Y1 Tax T12 Based",$G$53,$H$15)) -> 160200 | J53: =IF(J$46="","",I53*(1+$H$16)) -> 165006 | K53: =IF(K$46="","",J53*(1+$H$16)) -> 169956.18 | L53: =IF(L$46="","",K53*(1+$H$16)) -> 175054.87 | M53: =IF(M$46="","",L53*(1+$H$16)) -> 180306.51 | N53: =IF(N$46="","",M53*(1+$H$16)) -> 185715.71 | O53: =IF(O$46="","",N53*(1+$H$16)) | P53: =IF(P$46="","",O53*(1+$H$16)) | Q53: =IF(Q$46="","",P53*(1+$H$16)) | ... AC53: =IF(AC$46="","",AB53*(1+$H$16))
B54: Property Mangement fees | D54: =G54/Units -> 229.64129 | E54: =I54/Units -> 631.71604 | F54: ='Historical Analysis'!X35 -> 30000 | G54: ='Historical Analysis'!W35 -> 30312.65 | H54: =96806 -> 96806 | I54: =IF(I$46="","",I44*$H$10) -> 83386.517 | J54: =IF(J$46="","",J44*$H$10) -> 83671.219 | K54: =IF(K$46="","",K44*$H$10) -> 86181.169 | L54: =IF(L$46="","",L44*$H$10) -> 88766.412 | M54: =IF(M$46="","",M44*$H$10) -> 91429.208 | N54: =IF(N$46="","",N44*$H$10) -> 94171.882 | O54: =IF(O$46="","",O44*$H$10) | P54: =IF(P$46="","",P44*$H$10) | ... AC54: =IF(AC$46="","",AC44*$H$10)
B55: Marketing | D55: =G55/Units -> 1170.702 | E55: 1750 | F55: ='Historical Analysis'!X31 -> 147922.44 | G55: ='Historical Analysis'!W31 -> 154532.67 | H55: 34750 | I55: =IF(I$46="","",E55*Units) -> 231000 | J55: =IF(J$46="","",I55*(1+$H$9)) -> 237352.5 | K55: =IF(K$46="","",J55*(1+$H$9)) -> 243879.69 | L55: =IF(L$46="","",K55*(1+$H$9)) -> 250586.39 | M55: =IF(M$46="","",L55*(1+$H$9)) -> 257477.51 | N55: =IF(N$46="","",M55*(1+$H$9)) -> 264558.14 | O55: =IF(O$46="","",N55*(1+$H$9)) | P55: =IF(P$46="","",O55*(1+$H$9)) | Q55: =IF(Q$46="","",P55*(1+$H$9)) | ... AC55: =IF(AC$46="","",AB55*(1+$H$9))
B56: Payroll | D56: =G56/Units -> 726.37038 | E56: 875 | F56: ='Historical Analysis'!X32 -> 98123.52 | G56: ='Historical Analysis'!W32 -> 95880.89 | H56: =85000+92000 -> 177000 | I56: =IF(I$46="","",E56*Units) -> 115500 | J56: =IF(J$46="","",I56*(1+$H$9)) -> 118676.25 | K56: =IF(K$46="","",J56*(1+$H$9)) -> 121939.85 | L56: =IF(L$46="","",K56*(1+$H$9)) -> 125293.19 | M56: =IF(M$46="","",L56*(1+$H$9)) -> 128738.76 | N56: =IF(N$46="","",M56*(1+$H$9)) -> 132279.07 | O56: =IF(O$46="","",N56*(1+$H$9)) | P56: =IF(P$46="","",O56*(1+$H$9)) | Q56: =IF(Q$46="","",P56*(1+$H$9)) | ... AC56: =IF(AC$46="","",AB56*(1+$H$9))
B57: Insurance | D57: =G57/Units -> 2655.0898 | E57: 750 | F57: ='Historical Analysis'!X34 -> 819039.28 | G57: ='Historical Analysis'!W34 -> 350471.86 | H57: 165000 | I57: =IF(I$46="","",E57*Units) -> 99000 | J57: =IF(J$46="","",I57*(1+$H$9)) -> 101722.5 | K57: =IF(K$46="","",J57*(1+$H$9)) -> 104519.87 | L57: =IF(L$46="","",K57*(1+$H$9)) -> 107394.17 | M57: =IF(M$46="","",L57*(1+$H$9)) -> 110347.5 | N57: =IF(N$46="","",M57*(1+$H$9)) -> 113382.06 | O57: =IF(O$46="","",N57*(1+$H$9)) | P57: =IF(P$46="","",O57*(1+$H$9)) | Q57: =IF(Q$46="","",P57*(1+$H$9)) | ... AC57: =IF(AC$46="","",AB57*(1+$H$9))
B58: General & Administrative | D58: =G58/Units -> 336.09788 | E58: 450 | F58: ='Historical Analysis'!X36 -> 85518.4 | G58: ='Historical Analysis'!W36 -> 44364.92 | H58: =350+350+6500+2000+2000+1500+2112+2876+612 -> 18300 | I58: =IF(I$46="","",E58*Units) -> 59400 | J58: =IF(J$46="","",I58*(1+$H$9)) -> 61033.5 | K58: =IF(K$46="","",J58*(1+$H$9)) -> 62711.921 | L58: =IF(L$46="","",K58*(1+$H$9)) -> 64436.499 | M58: =IF(M$46="","",L58*(1+$H$9)) -> 66208.503 | N58: =IF(N$46="","",M58*(1+$H$9)) -> 68029.237 | O58: =IF(O$46="","",N58*(1+$H$9)) | P58: =IF(P$46="","",O58*(1+$H$9)) | Q58: =IF(Q$46="","",P58*(1+$H$9)) | ... AC58: =IF(AC$46="","",AB58*(1+$H$9))
B59: Other taxes/Permit license | D59: =G59/Units -> 13.886136 | E59: 0 | F59: ='Historical Analysis'!X37 -> 0 | G59: ='Historical Analysis'!W37 -> 1832.97 | H59: =1500 -> 1500 | I59: =IF(I$46="","",E59*Units) -> 0 | J59: =IF(J$46="","",I59*(1+$H$9)) -> 0 | K59: =IF(K$46="","",J59*(1+$H$9)) -> 0 | L59: =IF(L$46="","",K59*(1+$H$9)) -> 0 | M59: =IF(M$46="","",L59*(1+$H$9)) -> 0 | N59: =IF(N$46="","",M59*(1+$H$9)) -> 0 | O59: =IF(O$46="","",N59*(1+$H$9)) | P59: =IF(P$46="","",O59*(1+$H$9)) | Q59: =IF(Q$46="","",P59*(1+$H$9)) | ... AC59: =IF(AC$46="","",AB59*(1+$H$9))
B60: Total Operating Expenses | D60: =SUM(D47:D59) -> 8859.2543 | E60: =SUM(E47:E59) -> 8795.3524 | F60: =SUM(F47:F59) -> 1698991.3 | G60: =SUM(G47:G59) -> 1169421.6 | H60: =SUM(H47:H59) -> 972362 | I60: =SUM(I47:I59) -> 1160986.5 | J60: =SUM(J47:J59) -> 1191305.7 | K60: =SUM(K47:K59) -> 1224688.1 | ... N60: =SUM(N47:N59) -> 1330561.4 | O60: =IF(O$46="","",SUM(O47:O59)) | P60: =IF(P$46="","",SUM(P47:P59)) | Q60: =IF(Q$46="","",SUM(Q47:Q59)) | R60: =IF(R$46="","",SUM(R47:R59)) | S60: =IF(S$46="","",SUM(S47:S59)) | T60: =IF(T$46="","",SUM(T47:T59)) | U60: =IF(U$46="","",SUM(U47:U59)) | V60: =IF(V$46="","",SUM(V47:V59)) | ... AC60: =IF(AC$46="","",SUM(AC47:AC59))
B61: Expense Ratio | F61: =IF(F$46="","",F60/F44) -> 2.2794452 | G61: =IF(G$46="","",G60/G44) -> 2.4135784 | H61: =IF(H$46="","",H60/H44) -> 0.30133362 | I61: =IF(I$46="","",I60/I44) -> 0.3828812 | J61: =IF(J$46="","",J60/J44) -> 0.39154333 | K61: =IF(K$46="","",K60/K44) -> 0.39079214 | L61: =IF(L$46="","",L60/L44) -> 0.39004278 | M61: =IF(M$46="","",M60/M44) -> 0.38929523 | ... AC61: =IF(AC$46="","",AC60/AC44)
B63: Net Operating Income (NOI) before reserve | F63: =F44-F60 -> -953638.32 | G63: =G44-G60 -> -684903.82 | H63: =H44-H60 -> 2254500 | I63: =IF(I$46="","",I44-I60) -> 1871250.5 | J63: =IF(J$46="","",J44-J60) -> 1851284.1 | K63: =IF(K$46="","",K44-K60) -> 1909172.6 | L63: =IF(L$46="","",L44-L60) -> 1968862.3 | M63: =IF(M$46="","",M44-M60) -> 2030409.2 | N63: =IF(N$46="","",N44-N60) -> 2093870.7 | O63: =IF(O$46="","",O44-O60) | P63: =IF(P$46="","",P44-P60) | ... V63: =IF(V$46="","",V44-V60) | W63: =IF(W$46="","",W44+W60) | X63: =IF(X$46="","",X44+X60) | Y63: =IF(Y$46="","",Y44+Y60) | Z63: =IF(Z$46="","",Z44+Z60) | AA63: =IF(AA$46="","",AA44+AA60) | AB63: =IF(AB$46="","",AB44+AB60) | AC63: =IF(AC$46="","",AC44+AC60)
B64: % Increase in NOI | I64: =IF(I$46="","",I63/G63-1) -> -3.7321361 | J64: =IF(J$46="","",J63/I63-1) -> -0.010670083 | K64: =IF(K$46="","",K63/J63-1) -> 0.031269376 | L64: =IF(L$46="","",L63/K63-1) -> 0.031264737 | M64: =IF(M$46="","",M63/L63-1) -> 0.03126012 | N64: =IF(N$46="","",N63/M63-1) -> 0.031255525 | O64: =IF(O$46="","",O63/N63-1) | P64: =IF(P$46="","",P63/O63-1) | Q64: =IF(Q$46="","",Q63/P63-1) | ... AC64: =IF(AC$46="","",AC63/AB63-1)
B65: Replacement Reserves | D65: =G65/Units -> 0 | E65: =I65/Units -> 0 | F65: ='Historical Analysis'!X41 -> 0 | G65: ='Historical Analysis'!W41 -> 0 | H65: 0 | I65: =IF(I46="","",-$H$13*Units) -> 0 | J65: =IF(J46="","",I65*(1+$H$9)) -> 0 | K65: =IF(K46="","",J65*(1+$H$9)) -> 0 | L65: =IF(L46="","",K65*(1+$H$9)) -> 0 | M65: =IF(M46="","",L65*(1+$H$9)) -> 0 | N65: =IF(N46="","",M65*(1+$H$9)) -> 0 | O65: =IF(O46="","",N65*(1+$H$9)) | P65: =IF(P46="","",O65*(1+$H$9)) | Q65: =IF(Q46="","",-$H$13*Units) | R65: =IF(R46="","",-$H$13*Units) | S65: =IF(S46="","",-$H$13*Units) | T65: =IF(T46="","",-$H$13*Units) | U65: =IF(U46="","",-$H$13*Units) | V65: =IF(V46="","",-$H$13*Units) | W65: =IF(W46="","",-$H$13*Units) | X65: =IF(X46="","",-$H$13*Units) | ... AC65: =IF(AC46="","",-$H$13*Units)
B66: Net Operating Cash Flow | G66: =G63+G65 -> -684903.82 | H66: =H63+H65 -> 2254500 | I66: =IF(I46="","",I63+I65) -> 1871250.5 | J66: =IF(J46="","",J63+J65) -> 1851284.1 | K66: =IF(K46="","",K63+K65) -> 1909172.6 | L66: =IF(L46="","",L63+L65) -> 1968862.3 | M66: =IF(M46="","",M63+M65) -> 2030409.2 | N66: =IF(N46="","",N63+N65) -> 2093870.7 | O66: =IF(O46="","",O63+O65) | P66: =IF(P46="","",P63+P65) | ... AC66: =IF(AC46="","",AC63+AC65)
B67: Sale Proceed | I67: =IF(I46="","",IF(I46=$C$13,(J66/$C$14*(1-$H$12)),0)) -> 0 | J67: =IF(J46="","",IF(J46=$C$13,(K66/$C$14*(1-$H$12)),0)) -> 0 | K67: =IF(K46="","",IF(K46=$C$13,(L66/$C$14*(1-$H$12)),0)) -> 0 | L67: =IF(L46="","",IF(L46=$C$13,(M66/$C$14*(1-$H$12)),0)) -> 0 | M67: =IF(M46="","",IF(M46=$C$13,(N66/$C$14*(1-$H$12)),0)) -> 34548867 | N67: =IF(N46="","",IF(N46=$C$13,(O66/$C$14*(1-$H$12)),0)) -> 0 | O67: =IF(O46="","",IF(O46=$C$13,(P66/$C$14*(1-$H$12)),0)) | P67: =IF(P46="","",IF(P46=$C$13,(Q66/$C$14*(1-$H$12)),0)) | ... AC67: =IF(AC46="","",IF(AC46=$C$13,(AD66/$C$14*(1-$H$12)),0))
B68: Debt Service | I68: =-Loan!E46 -> -1301440 | J68: =-Loan!F46 -> -1301440 | K68: =-Loan!G46 -> -1301440 | L68: =-Loan!H46 -> -1634787.3 | M68: =-Loan!I46 -> -1634787.3 | N68: =-Loan!J46 -> 0 | O68: =-Loan!K46 -> 0 | P68: =-Loan!L46 -> 0 | ... AC68: =-Loan!Y46 -> 0
B69: DSCR | I69: =IF(I46<=$C$13,-(I67+I66)/(I70+I68),"") -> 1.4378308 | J69: =IF(J46<=$C$13,-(J67+J66)/(J70+J68),"") -> 1.422489 | K69: =IF(K46<=$C$13,-(K67+K66)/(K70+K68),"") -> 1.4669693 | L69: =IF(L46<=$C$13,-(L67+L66)/(L70+L68),"") -> 1.2043539 | M69: =IF(M46<=$C$13,-(M67+M66)/(M70+M68),"") -> 1.4372779 | N69: =IF(N46<=$C$13,-(N67+N66)/(N70+N68),"") | O69: =IF(O46<=$C$13,-(O67+O66)/(O70+O68),"") | P69: =IF(P46<=$C$13,-(P67+P66)/(P70+P68),"") | ... AC69: =IF(AC46<=$C$13,-(AC67+AC66)/(AC70+AC68),"")
B70: Loan Payoff | I70: =-Loan!E44 -> 0 | J70: =-Loan!F44 -> 0 | K70: =-Loan!G44 -> 0 | L70: =-Loan!H44 -> 0 | M70: =-Loan!I44 -> -23815598 | N70: =-Loan!J44 -> 0 | O70: =-Loan!K44 -> 0 | P70: =-Loan!L44 -> 0 | ... AC70: =-Loan!Y44 -> 0
B71: Asset Management Fee | I71: =-IF(I46="",0,IF(I46>$C$13,0,('Sources & Usage'!$C$8*$H$11))) -> 0 | J71: =-IF(J46="",0,IF(J46>$C$13,0,('Sources & Usage'!$C$8*$H$11))) -> 0 | K71: =-IF(K46="",0,IF(K46>$C$13,0,('Sources & Usage'!$C$8*$H$11))) -> 0 | L71: =-IF(L46="",0,IF(L46>$C$13,0,('Sources & Usage'!$C$8*$H$11))) -> 0 | M71: =-IF(M46="",0,IF(M46>$C$13,0,('Sources & Usage'!$C$8*$H$11))) -> 0 | N71: =-IF(N46="",0,IF(N46>$C$13,0,('Sources & Usage'!$C$8*$H$11))) -> 0 | O71: =-IF(O46="",0,IF(O46>$C$13,0,('Sources & Usage'!$C$8*$H$11))) -> 0 | P71: =-IF(P46="",0,IF(P46>$C$13,0,('Sources & Usage'!$C$8*$H$11))) -> 0 | ... AC71: =-IF(AC46="",0,IF(AC46>$C$13,0,('Sources & Usage'!$C$8*$H$11))) -> 0
B72: Levered Cash Flow | I72: =IF(I46>$C$13,0,I66+I67+I68+I70+I71) -> 569810.45 | J72: =IF(J46>$C$13,0,J66+J67+J68+J70+J71) -> 549844.06 | K72: =IF(K46>$C$13,0,K66+K67+K68+K70+K71) -> 607732.56 | L72: =IF(L46>$C$13,0,L66+L67+L68+L70+L71) -> 334075.08 | M72: =IF(M46>$C$13,0,M66+M67+M68+M70+M71) -> 11128891 | N72: =IF(N46>$C$13,0,N66+N67+N68+N70+N71) -> 0 | O72: =IF(O46>$C$13,0,O66+O67+O68+O70+O71) -> 0 | P72: =IF(P46>$C$13,0,P66+P67+P68+P70+P71) -> 0 | ... AC72: =IF(AC46>$C$13,0,AC66+AC67+AC68+AC70+AC71) -> 0
B74: Return Metrics | G74: Avg return | H74: 0 | I74: =IF(H74<$C$13,H74+1,"") -> 1 | J74: =IF(I74<$C$13,I74+1,"") -> 2 | K74: =IF(J74<$C$13,J74+1,"") -> 3 | L74: =IF(K74<$C$13,K74+1,"") -> 4 | M74: =IF(L74<$C$13,L74+1,"") -> 5 | N74: =IF(M74<$C$13,M74+1,"") | O74: =IF(N74<$C$13,N74+1,"") | P74: =IF(O74<$C$13,O74+1,"") | ... AC74: =IF(AB74<$C$13,AB74+1,"")
B75: Cash on Cash Return (Unlevered) | G75: =AVERAGE(I75:AC75) -> 0.054114222 | I75: =IF(I46>$C$13,"",I66/'Sources & Usage'!$C$23) -> 0.052570599 | J75: =IF(J46>$C$13,"",J66/'Sources & Usage'!$C$23) -> 0.052009666 | K75: =IF(K46>$C$13,"",K66/'Sources & Usage'!$C$23) -> 0.053635976 | L75: =IF(L46>$C$13,"",L66/'Sources & Usage'!$C$23) -> 0.05531289 | M75: =IF(M46>$C$13,"",M66/'Sources & Usage'!$C$23) -> 0.057041978 | N75: =IF(N46>$C$13,"",N66/'Sources & Usage'!$C$23) | O75: =IF(O46>$C$13,"",O66/'Sources & Usage'!$C$23) | P75: =IF(P46>$C$13,"",P66/'Sources & Usage'!$C$23) | ... R75: =IF(R46>$C$13,"",R66/'Sources & Usage'!$C$23)
B76: Cash on Cash Return (levered) | G76: =AVERAGE(I76:AC76) -> 0.044291737 | I76: =IF(I46>$C$13,"",SUM(I66,I68,I71)/'Sources & Usage'!$C$8) -> 0.051357409 | J76: =IF(J46>$C$13,"",SUM(J66,J68,J71)/'Sources & Usage'!$C$8) -> 0.049557824 | K76: =IF(K46>$C$13,"",SUM(K66,K68,K71)/'Sources & Usage'!$C$8) -> 0.054775354 | L76: =IF(L46>$C$13,"",SUM(L66,L68,L71)/'Sources & Usage'!$C$8) -> 0.030110417 | M76: =IF(M46>$C$13,"",SUM(M66,M68,M71)/'Sources & Usage'!$C$8) -> 0.035657679 | N76: =IF(N46>$C$13,"",SUM(N66,N68,N71)/'Sources & Usage'!$C$8) | O76: =IF(O46>$C$13,"",SUM(O66,O68,O71)/'Sources & Usage'!$C$8) | P76: =IF(P46>$C$13,"",SUM(P66,P68,P71)/'Sources & Usage'!$C$8) | ... R76: =IF(R46>$C$13,"",SUM(R66,R68,R71)/'Sources & Usage'!$C$8)
B77: IRR-Unlevered | G77: =IRR(H79:AC79) -> 0.048665982
B78: IRR-levered | G78: =IRR(H80:AC80) -> 0.038638988
B79: Cashflow -Unlevered | H79: =IF(H74="","",-'Sources & Usage'!C9) -> -35595000 | I79: =IF(I74="","",I66+I67+I71) -> 1871250.5 | J79: =IF(J74="","",J66+J67+J71) -> 1851284.1 | K79: =IF(K74="","",K66+K67+K71) -> 1909172.6 | L79: =IF(L74="","",L66+L67+L71) -> 1968862.3 | M79: =IF(M74="","",M66+M67+M71) -> 36579276 | N79: =IF(N74="","",N66+N67+N71) | O79: =IF(O74="","",O66+O67+O71) | P79: =IF(P74="","",P66+P67+P71) | ... AC79: =IF(AC74="","",AC66+AC67+AC71)
B80: Cashflow -levered | H80: =-'Sources & Usage'!C8 -> -11095000 | I80: =I72 -> 569810.45 | J80: =J72 -> 549844.06 | K80: =K72 -> 607732.56 | L80: =L72 -> 334075.08 | M80: =M72 -> 11128891 | N80: =N72 -> 0 | O80: =O72 -> 0 | P80: =P72 -> 0 | ... AC80: =AC72 -> 0
B81: Equity Required | H81: ='Sources & Usage'!C8 -> 11095000
B86: Underwriting Notes & Assumptions
B88: General Modeling Notes
B89: 1. We have used the Rent comps from Hello Data and added the screenshot for the rent comps as well.
B90: 2. We made a change on Rent page to choose from either of Comps or RR market rent in Col L.
B91: 3. We have added a switch for the Taxes in the Pro Forma Assumptions to choose between T12 taxes and taxes on Reassessed value.
B93: Our Assumptions
B94: General Assumptions
B95: 1. General assumptions (including market rent growth, expense growth, tax growth, and property management fees) are consistent with those applied in the prior model.
B96: 2. For financing, we have a 3 year I/O period and all in rate of 5.31% (5 year Treasury Yield of 3.912% + 1.40% spread).
B97: 3. We have used the assumptions for Vacancy, Bad debts & Loss to Lease provided by AJ.
B98: Asking Price and Exit Assumptions
B99: 1. Exit year has been assumed to be 5 years and exit cap rate to be 6%.
... B116: Would you like to continue with the lease and service agreement or not? If not, then is the termination fee included in the Broker guidance of $35MM or not?

Sheet Rent
B2: ='CFS-Main Page'!B2 -> Calabash Shores | D2: ='CFS-Main Page'!C2 -> Address: | E2: ='CFS-Main Page'!D2 -> 660 Aubrey Ln Calabash, NC, 28467
B3: Rent Roll Analysis | D3: ='CFS-Main Page'!C3 -> Units | E3: ='CFS-Main Page'!D3 -> 132
B4: ='CFS-Main Page'!B4 -> 0 | D4: ='CFS-Main Page'!C4 -> Year Built/Reno | E4: ='CFS-Main Page'!D4 -> 2024
C5: Rent Roll as on | D5: 46066 | E5: Avg Rent | F5: 1x1 | G5: {=-SUMPRODUCT(-($B$9:$B$28=F5),$E$9:$E$28,$J$9:$J$28)/SUMIF($B$9:$B$28,"="&F5,$E$9:$E$28)} -> 1568.64 | H5: 2x2 | I5: {=-SUMPRODUCT(-($B$9:$B$28=H5),$E$9:$E$28,$J$9:$J$28)/SUMIF($B$9:$B$28,"="&H5,$E$9:$E$28)} -> 2441.5258
C6: Rent Schedule
B8: Beds X Baths | C8: Type | D8: Units | E8: Occupied | F8: Vacant/Model | G8: Unit Mix % | H8: Occupancy % | I8: Square Feet | J8: MR - Based on RR | K8: MR - Based on Comps | L8: RR/Comps | M8: Effective Rent | N8: GRP | O8: GRP/unit
B9: 1x1 | C9: Surfside - 1 | D9: =IF(C9="","",COUNTIF($D$62:$D$997,"="&C9)) -> 40 | E9: =IF(C9="","",COUNTIF($I$62:$I$997,"="&C9)) -> 4 | F9: =IFERROR(D9-E9,0) -> 36 | G9: =IFERROR(D9/$D$29,0) -> 0.3030303 | H9: =IFERROR(E9/D9,0) -> 0.1 | I9: =IFERROR(SUMIF($D$62:$D$997,"="&C9,$E$62:$E$997)/D9,0) -> 745 | J9: =IFERROR(SUMIF($D$62:$D$997,"="&C9,$G$62:$G$997)/D9,0) -> 1575.8 | K9: 1700 | L9: MR - Based on RR | M9: =IFERROR(SUMIF($D$62:$D$997,"="&C9,$H$62:$H$997)/E9,0) -> 1941.75 | N9: =IFERROR((M9*E9)+(F9*J9),0) -> 64495.8 | O9: =IFERROR(N9/D9,0) -> 1612.395
B10: 1x1 | C10: Surfside - 1ADA | D10: =IF(C10="","",COUNTIF($D$62:$D$997,"="&C10)) -> 3 | E10: =IF(C10="","",COUNTIF($I$62:$I$997,"="&C10)) -> 1 | F10: =IFERROR(D10-E10,0) -> 2 | G10: =IFERROR(D10/$D$29,0) -> 0.022727273 | H10: =IFERROR(E10/D10,0) -> 0.33333333 | I10: =IFERROR(SUMIF($D$62:$D$997,"="&C10,$E$62:$E$997)/D10,0) -> 745 | J10: =IFERROR(SUMIF($D$62:$D$997,"="&C10,$G$62:$G$997)/D10,0) -> 1540 | K10: 1700 | L10: MR - Based on RR | M10: =IFERROR(SUMIF($D$62:$D$997,"="&C10,$H$62:$H$997)/E10,0) -> 1540 | N10: =IFERROR((M10*E10)+(F10*J10),0) -> 4620 | O10: =IFERROR(N10/D10,0) -> 1540
B11: 2x1 | C11: Shoreline - 4 | D11: =IF(C11="","",COUNTIF($D$62:$D$997,"="&C11)) -> 4 | E11: =IF(C11="","",COUNTIF($I$62:$I$997,"="&C11)) -> 0 | F11: =IFERROR(D11-E11,0) -> 4 | G11: =IFERROR(D11/$D$29,0) -> 0.03030303 | H11: =IFERROR(E11/D11,0) -> 0 | I11: =IFERROR(SUMIF($D$62:$D$997,"="&C11,$E$62:$E$997)/D11,0) -> 936 | J11: =IFERROR(SUMIF($D$62:$D$997,"="&C11,$G$62:$G$997)/D11,0) -> 1650 | K11: 1935 | L11: MR - Based on RR | M11: =IFERROR(SUMIF($D$62:$D$997,"="&C11,$H$62:$H$997)/E11,0) -> 0 | N11: =IFERROR((M11*E11)+(F11*J11),0) -> 6600 | O11: =IFERROR(N11/D11,0) -> 1650
B12: 2x2 | C12: Driftwood - 2 | D12: =IF(C12="","",COUNTIF($D$62:$D$997,"="&C12)) -> 10 | E12: =IF(C12="","",COUNTIF($I$62:$I$997,"="&C12)) -> 7 | F12: =IFERROR(D12-E12,0) -> 3 | G12: =IFERROR(D12/$D$29,0) -> 0.075757576 | H12: =IFERROR(E12/D12,0) -> 0.7 | I12: =IFERROR(SUMIF($D$62:$D$997,"="&C12,$E$62:$E$997)/D12,0) -> 995 | J12: =IFERROR(SUMIF($D$62:$D$997,"="&C12,$G$62:$G$997)/D12,0) -> 1900 | K12: 1935 | L12: MR - Based on RR | M12: =IFERROR(SUMIF($D$62:$D$997,"="&C12,$H$62:$H$997)/E12,0) -> 1996.4286 | N12: =IFERROR((M12*E12)+(F12*J12),0) -> 19675 | O12: =IFERROR(N12/D12,0) -> 1967.5
B13: 2x2 | C13: Driftwood - 2ADA | D13: =IF(C13="","",COUNTIF($D$62:$D$997,"="&C13)) -> 1 | E13: =IF(C13="","",COUNTIF($I$62:$I$997,"="&C13)) -> 0 | F13: =IFERROR(D13-E13,0) -> 1 | G13: =IFERROR(D13/$D$29,0) -> 0.0075757576 | H13: =IFERROR(E13/D13,0) -> 0 | I13: =IFERROR(SUMIF($D$62:$D$997,"="&C13,$E$62:$E$997)/D13,0) -> 995 | J13: =IFERROR(SUMIF($D$62:$D$997,"="&C13,$G$62:$G$997)/D13,0) -> 1675 | K13: 1935 | L13: MR - Based on RR | M13: =IFERROR(SUMIF($D$62:$D$997,"="&C13,$H$62:$H$997)/E13,0) -> 0 | N13: =IFERROR((M13*E13)+(F13*J13),0) -> 1675 | O13: =IFERROR(N13/D13,0) -> 1675
B14: 2x2 | C14: Seaglass - 3 | D14: =IF(C14="","",COUNTIF($D$62:$D$997,"="&C14)) -> 12 | E14: =IF(C14="","",COUNTIF($I$62:$I$997,"="&C14)) -> 2 | F14: =IFERROR(D14-E14,0) -> 10 | G14: =IFERROR(D14/$D$29,0) -> 0.090909091 | H14: =IFERROR(E14/D14,0) -> 0.16666667 | I14: =IFERROR(SUMIF($D$62:$D$997,"="&C14,$E$62:$E$997)/D14,0) -> 1000 | J14: =IFERROR(SUMIF($D$62:$D$997,"="&C14,$G$62:$G$997)/D14,0) -> 1905.8333 | K14: 1935 | L14: MR - Based on RR | M14: =IFERROR(SUMIF($D$62:$D$997,"="&C14,$H$62:$H$997)/E14,0) -> 1860 | N14: =IFERROR((M14*E14)+(F14*J14),0) -> 22778.333 | O14: =IFERROR(N14/D14,0) -> 1898.1944
B15: 2x2 | C15: Beach Haven In-line Unit | D15: =IF(C15="","",COUNTIF($D$62:$D$997,"="&C15)) -> 38 | E15: =IF(C15="","",COUNTIF($I$62:$I$997,"="&C15)) -> 4 | F15: =IFERROR(D15-E15,0) -> 34 | G15: =IFERROR(D15/$D$29,0) -> 0.28787879 | H15: =IFERROR(E15/D15,0) -> 0.10526316 | I15: =IFERROR(SUMIF($D$62:$D$997,"="&C15,$E$62:$E$997)/D15,0) -> 1149 | J15: =IFERROR(SUMIF($D$62:$D$997,"="&C15,$G$62:$G$997)/D15,0) -> 1956.7895 | K15: 1935 | L15: MR - Based on RR | M15: =IFERROR(SUMIF($D$62:$D$997,"="&C15,$H$62:$H$997)/E15,0) -> 2312 | N15: =IFERROR((M15*E15)+(F15*J15),0) -> 75778.842 | O15: =IFERROR(N15/D15,0) -> 1994.1801
B16: 2x2 | C16: Ocean Breeze - End Unit | D16: =IF(C16="","",COUNTIF($D$62:$D$997,"="&C16)) -> 22 | E16: =IF(C16="","",COUNTIF($I$62:$I$997,"="&C16)) -> 18 | F16: =IFERROR(D16-E16,0) -> 4 | G16: =IFERROR(D16/$D$29,0) -> 0.16666667 | H16: =IFERROR(E16/D16,0) -> 0.81818182 | I16: =IFERROR(SUMIF($D$62:$D$997,"="&C16,$E$62:$E$997)/D16,0) -> 1210 | J16: =IFERROR(SUMIF($D$62:$D$997,"="&C16,$G$62:$G$997)/D16,0) -> 2810 | K16: 1935 | L16: MR - Based on RR | M16: =IFERROR(SUMIF($D$62:$D$997,"="&C16,$H$62:$H$997)/E16,0) -> 2845.5556 | N16: =IFERROR((M16*E16)+(F16*J16),0) -> 62460 | O16: =IFERROR(N16/D16,0) -> 2839.0909
B17: 2x2 | C17: Lighthouse - 5 | D17: =IF(C17="","",COUNTIF($D$62:$D$997,"="&C17)) -> 2 | E17: =IF(C17="","",COUNTIF($I$62:$I$997,"="&C17)) -> 1 | F17: =IFERROR(D17-E17,0) -> 1 | G17: =IFERROR(D17/$D$29,0) -> 0.015151515 | H17: =IFERROR(E17/D17,0) -> 0.5 | I17: =IFERROR(SUMIF($D$62:$D$997,"="&C17,$E$62:$E$997)/D17,0) -> 1417 | J17: =IFERROR(SUMIF($D$62:$D$997,"="&C17,$G$62:$G$997)/D17,0) -> 2610 | K17: 1935 | L17: MR - Based on RR | M17: =IFERROR(SUMIF($D$62:$D$997,"="&C17,$H$62:$H$997)/E17,0) -> 2870 | N17: =IFERROR((M17*E17)+(F17*J17),0) -> 5480 | O17: =IFERROR(N17/D17,0) -> 2740
D18: =IF(C18="","",COUNTIF($D$62:$D$997,"="&C18)) | E18: =IF(C18="","",COUNTIF($I$62:$I$997,"="&C18)) | F18: =IFERROR(D18-E18,0) -> 0 | G18: =IFERROR(D18/$D$29,0) -> 0 | H18: =IFERROR(E18/D18,0) -> 0 | I18: =IFERROR(SUMIF($D$62:$D$997,"="&C18,$E$62:$E$997)/D18,0) -> 0 | J18: =IFERROR(SUMIF($D$62:$D$997,"="&C18,$G$62:$G$997)/D18,0) -> 0 | K18: 0 | M18: =IFERROR(SUMIF($D$62:$D$997,"="&C18,$H$62:$H$997)/E18,0) -> 0 | N18: =IFERROR((M18*E18)+(F18*J18),0) -> 0 | O18: =IFERROR(N18/D18,0) -> 0
D19: =IF(C19="","",COUNTIF($D$62:$D$997,"="&C19)) | E19: =IF(C19="","",COUNTIF($I$62:$I$997,"="&C19)) | F19: =IFERROR(D19-E19,0) -> 0 | G19: =IFERROR(D19/$D$29,0) -> 0 | H19: =IFERROR(E19/D19,0) -> 0 | I19: =IFERROR(SUMIF($D$62:$D$997,"="&C19,$E$62:$E$997)/D19,0) -> 0 | J19: =IFERROR(SUMIF($D$62:$D$997,"="&C19,$G$62:$G$997)/D19,0) -> 0 | K19: 0 | M19: =IFERROR(SUMIF($D$62:$D$997,"="&C19,$H$62:$H$997)/E19,0) -> 0 | N19: =IFERROR((M19*E19)+(F19*J19),0) -> 0 | O19: =IFERROR(N19/D19,0) -> 0
D20: =IF(C20="","",COUNTIF($D$62:$D$997,"="&C20)) | E20: =IF(C20="","",COUNTIF($I$62:$I$997,"="&C20)) | F20: =IFERROR(D20-E20,0) -> 0 | G20: =IFERROR(D20/$D$29,0) -> 0 | H20: =IFERROR(E20/D20,0) -> 0 | I20: =IFERROR(SUMIF($D$62:$D$997,"="&C20,$E$62:$E$997)/D20,0) -> 0 | J20: =IFERROR(SUMIF($D$62:$D$997,"="&C20,$G$62:$G$997)/D20,0) -> 0 | K20: 0 | M20: =IFERROR(SUMIF($D$62:$D$997,"="&C20,$H$62:$H$997)/E20,0) -> 0 | N20: =IFERROR((M20*E20)+(F20*J20),0) -> 0 | O20: =IFERROR(N20/D20,0) -> 0
D21: =IF(C21="","",COUNTIF($D$62:$D$997,"="&C21)) | E21: =IF(C21="","",COUNTIF($I$62:$I$997,"="&C21)) | F21: =IFERROR(D21-E21,0) -> 0 | G21: =IFERROR(D21/$D$29,0) -> 0 | H21: =IFERROR(E21/D21,0) -> 0 | I21: =IFERROR(SUMIF($D$62:$D$997,"="&C21,$E$62:$E$997)/D21,0) -> 0 | J21: =IFERROR(SUMIF($D$62:$D$997,"="&C21,$G$62:$G$997)/D21,0) -> 0 | K21: 0 | M21: =IFERROR(SUMIF($D$62:$D$997,"="&C21,$H$62:$H$997)/E21,0) -> 0 | N21: =IFERROR((M21*E21)+(F21*J21),0) -> 0 | O21: =IFERROR(N21/D21,0) -> 0
D22: =IF(C22="","",COUNTIF($D$62:$D$997,"="&C22)) | E22: =IF(C22="","",COUNTIF($I$62:$I$997,"="&C22)) | F22: =IFERROR(D22-E22,0) -> 0 | G22: =IFERROR(D22/$D$29,0) -> 0 | H22: =IFERROR(E22/D22,0) -> 0 | I22: =IFERROR(SUMIF($D$62:$D$997,"="&C22,$E$62:$E$997)/D22,0) -> 0 | J22: =IFERROR(SUMIF($D$62:$D$997,"="&C22,$G$62:$G$997)/D22,0) -> 0 | K22: 0 | M22: =IFERROR(SUMIF($D$62:$D$997,"="&C22,$H$62:$H$997)/E22,0) -> 0 | N22: =IFERROR((M22*E22)+(F22*J22),0) -> 0 | O22: =IFERROR(N22/D22,0) -> 0
D23: =IF(C23="","",COUNTIF($D$62:$D$997,"="&C23)) | E23: =IF(C23="","",COUNTIF($I$62:$I$997,"="&C23)) | F23: =IFERROR(D23-E23,0) -> 0 | G23: =IFERROR(D23/$D$29,0) -> 0 | H23: =IFERROR(E23/D23,0) -> 0 | I23: =IFERROR(SUMIF($D$62:$D$997,"="&C23,$E$62:$E$997)/D23,0) -> 0 | J23: =IFERROR(SUMIF($D$62:$D$997,"="&C23,$G$62:$G$997)/D23,0) -> 0 | K23: 0 | M23: =IFERROR(SUMIF($D$62:$D$997,"="&C23,$H$62:$H$997)/E23,0) -> 0 | N23: =IFERROR((M23*E23)+(F23*J23),0) -> 0 | O23: =IFERROR(N23/D23,0) -> 0
D24: =IF(C24="","",COUNTIF($D$62:$D$997,"="&C24)) | E24: =IF(C24="","",COUNTIF($I$62:$I$997,"="&C24)) | F24: =IFERROR(D24-E24,0) -> 0 | G24: =IFERROR(D24/$D$29,0) -> 0 | H24: =IFERROR(E24/D24,0) -> 0 | I24: =IFERROR(SUMIF($D$62:$D$997,"="&C24,$E$62:$E$997)/D24,0) -> 0 | J24: =IFERROR(SUMIF($D$62:$D$997,"="&C24,$G$62:$G$997)/D24,0) -> 0 | K24: 0 | M24: =IFERROR(SUMIF($D$62:$D$997,"="&C24,$H$62:$H$997)/E24,0) -> 0 | N24: =IFERROR((M24*E24)+(F24*J24),0) -> 0 | O24: =IFERROR(N24/D24,0) -> 0
D25: =IF(C25="","",COUNTIF($D$62:$D$997,"="&C25)) | E25: =IF(C25="","",COUNTIF($I$62:$I$997,"="&C25)) | F25: =IFERROR(D25-E25,0) -> 0 | G25: =IFERROR(D25/$D$29,0) -> 0 | H25: =IFERROR(E25/D25,0) -> 0 | I25: =IFERROR(SUMIF($D$62:$D$997,"="&C25,$E$62:$E$997)/D25,0) -> 0 | J25: =IFERROR(SUMIF($D$62:$D$997,"="&C25,$G$62:$G$997)/D25,0) -> 0 | K25: 0 | M25: =IFERROR(SUMIF($D$62:$D$997,"="&C25,$H$62:$H$997)/E25,0) -> 0 | N25: =IFERROR((M25*E25)+(F25*J25),0) -> 0 | O25: =IFERROR(N25/D25,0) -> 0 | Q25: 2350
D26: =IF(C26="","",COUNTIF($D$62:$D$997,"="&C26)) | E26: =IF(C26="","",COUNTIF($I$62:$I$997,"="&C26)) | F26: =IFERROR(D26-E26,0) -> 0 | G26: =IFERROR(D26/$D$29,0) -> 0 | H26: =IFERROR(E26/D26,0) -> 0 | I26: =IFERROR(SUMIF($D$62:$D$997,"="&C26,$E$62:$E$997)/D26,0) -> 0 | J26: =IFERROR(SUMIF($D$62:$D$997,"="&C26,$G$62:$G$997)/D26,0) -> 0 | K26: 0 | M26: =IFERROR(SUMIF($D$62:$D$997,"="&C26,$H$62:$H$997)/E26,0) -> 0 | N26: =IFERROR((M26*E26)+(F26*J26),0) -> 0 | O26: =IFERROR(N26/D26,0) -> 0 | Q26: 2350
D27: =IF(C27="","",COUNTIF($D$62:$D$997,"="&C27)) | E27: =IF(C27="","",COUNTIF($I$62:$I$997,"="&C27)) | F27: =IFERROR(D27-E27,0) -> 0 | G27: =IFERROR(D27/$D$29,0) -> 0 | H27: =IFERROR(E27/D27,0) -> 0 | I27: =IFERROR(SUMIF($D$62:$D$997,"="&C27,$E$62:$E$997)/D27,0) -> 0 | J27: =IFERROR(SUMIF($D$62:$D$997,"="&C27,$G$62:$G$997)/D27,0) -> 0 | K27: 0 | M27: =IFERROR(SUMIF($D$62:$D$997,"="&C27,$H$62:$H$997)/E27,0) -> 0 | N27: =IFERROR((M27*E27)+(F27*J27),0) -> 0 | O27: =IFERROR(N27/D27,0) -> 0 | Q27: 2025
D28: =IF(C28="","",COUNTIF($D$62:$D$997,"="&C28)) | E28: =IF(C28="","",COUNTIF($I$62:$I$997,"="&C28)) | F28: =IFERROR(D28-E28,0) -> 0 | G28: =IFERROR(D28/$D$29,0) -> 0 | H28: =IFERROR(E28/D28,0) -> 0 | I28: =IFERROR(SUMIF($D$62:$D$997,"="&C28,$E$62:$E$997)/D28,0) -> 0 | J28: =IFERROR(SUMIF($D$62:$D$997,"="&C28,$G$62:$G$997)/D28,0) -> 0 | K28: 0 | M28: =IFERROR(SUMIF($D$62:$D$997,"="&C28,$H$62:$H$997)/E28,0) -> 0 | N28: =IFERROR((M28*E28)+(F28*J28),0) -> 0 | O28: =IFERROR(N28/D28,0) -> 0 | Q28: 1525
C29: Total | D29: =SUM(D9:D28) -> 132 | E29: =SUM(E9:E28) -> 37 | F29: =SUM(F9:F28) -> 95 | G29: =SUM(G9:G28) -> 1 | H29: =E29/Units -> 0.28030303 | I29: =SUMPRODUCT($D$9:$D$28,I9:I28) -> 131840 | J29: =SUMPRODUCT($D$9:$D$28,J9:J28) -> 259195 | K29: =SUMPRODUCT($D$9:$D$28,K9:K28) -> 245315 | M29: =SUMPRODUCT(E9:E28,M9:M28) -> 90340 | N29: =SUM(N9:N28) -> 263562.98 | Q29: 1525
G30: MRP | H30: =J29*12 -> 3110340 | I30: Rent per Unit | J30: =SUMPRODUCT(D9:D28,J9:J28)/D29 -> 1963.5985 | K30: =SUMPRODUCT(D9:D28,K9:K28)/D29 -> 1858.447 | M30: =SUMPRODUCT(E9:E28,M9:M28)/E29 -> 2441.6216 | Q30: 2350
G31: GRP | H31: =N29*12 -> 3162755.7 | I31: Rent per Sq ft | J31: =J30/J32 -> 1.9659815 | K31: =K30/K32 -> 1.8607024 | M31: =M30/(SUMPRODUCT(E9:E28,I9:I28)/E29) -> 2.231554 | Q31: 1525
G32: Loss/(Gain) to lease | H32: =H30-H31 -> -52415.705 | I32: Average sq ft | J32: =SUMPRODUCT(D9:D28,I9:I28)/D29 -> 998.78788 | K32: =SUMPRODUCT(D9:D28,I9:I28)/D29 -> 998.78788 | M32: =SUMPRODUCT(E9:E28,I9:I28)/E29 -> 1094.1351 | Q32: 2350
Q33: 2350
Q34: 1540
C35: Renovation Rent Premium and Cost Schdule | Q35: 1702
C36: Type | D36: Units | G36: Cost Per Unit | H36: Total Cost | I36: Premium Per Unit | Q36: 2350
C37: =IF(C9="","",C9) -> Surfside - 1 | D37: =D9 -> 40 | G37: 0 | H37: =IFERROR(G37*D37,0) -> 0 | I37: 0 | Q37: 2870
C38: =IF(C10="","",C10) -> Surfside - 1ADA | D38: =D10 -> 3 | G38: 0 | H38: =IFERROR(G38*D38,0) -> 0 | I38: 0 | Q38: 1365
C39: =IF(C11="","",C11) -> Shoreline - 4 | D39: =D11 -> 4 | G39: 0 | H39: =IFERROR(G39*D39,0) -> 0 | I39: 0 | Q39: 1695
C40: =IF(C12="","",C12) -> Driftwood - 2 | D40: =D12 -> 10 | G40: 0 | H40: =IFERROR(G40*D40,0) -> 0 | I40: 0 | Q40: 2870
C41: =IF(C13="","",C13) -> Driftwood - 2ADA | D41: =D13 -> 1 | G41: 0 | H41: =IFERROR(G41*D41,0) -> 0 | I41: 0 | Q41: 2870
C42: =IF(C14="","",C14) -> Seaglass - 3 | D42: =D14 -> 12 | G42: 0 | H42: =IFERROR(G42*D42,0) -> 0 | I42: 0 | Q42: 2870
C43: =IF(C15="","",C15) -> Beach Haven In-line Unit | D43: =D15 -> 38 | G43: 0 | H43: =IFERROR(G43*D43,0) -> 0 | I43: 0 | Q43: 2650
C44: =IF(C16="","",C16) -> Ocean Breeze - End Unit | D44: =D16 -> 22 | G44: 0 | H44: =IFERROR(G44*D44,0) -> 0 | I44: 0 | Q44: 2650
C45: =IF(C17="","",C17) -> Lighthouse - 5 | D45: =D17 -> 2 | G45: 0 | H45: =IFERROR(G45*D45,0) -> 0 | I45: 0 | Q45: 2870
C46: =IF(C18="","",C18) | D46: =D18 | G46: 0 | H46: =IFERROR(G46*D46,0) -> 0 | I46: 0 | Q46: 2650
C47: =IF(C19="","",C19) | D47: =D19 | G47: 0 | H47: =IFERROR(G47*D47,0) -> 0 | I47: 0 | Q47: 2870
C48: =IF(C20="","",C20) | D48: =D20 | G48: 0 | H48: =IFERROR(G48*D48,0) -> 0 | I48: 0 | Q48: 2870
... C56: =IF(C28="","",C28) | D56: =D28 | G56: 0 | H56: =IFERROR(G56*D56,0) -> 0 | I56: 0 | Q56: 2870
C57: Total | D57: =SUM(D37:D56) -> 132 | G57: =SUMPRODUCT(D37:D56,G37:G56)/D57 -> 0 | H57: =SUM(H37:H56) -> 0 | I57: =SUMPRODUCT(D37:D56,I37:I56) -> 0 | Q57: 2870
Q58: 2870
Q59: 2870
Q60: 1795
B61: Unit type | C61: Unit | D61: Unit Type | E61: Sq Ft | F61: Tenant Name | G61: Market Rent | H61: Lease Rent | I61: Occupancy | Q61: 2870
B62: Beach Haven In-line Unit | C62: 100 | D62: Seaglass - 3 | E62: 1000 | F62: Vacant Unit | G62: 1895 | H62: 0 | I62: =IF(H62=0,"",D62)
B63: Driftwood - 2 | C63: 101 | D63: Seaglass - 3 | E63: 1000 | F63: Vacant Unit | G63: 1895 | H63: 0 | I63: =IF(H63=0,"",D63)
B64: Driftwood - 2ADA | C64: 102 | D64: Surfside - 1 | E64: 745 | F64: Vacant Unit | G64: 1540 | H64: 0 | I64: =IF(H64=0,"",D64)
B65: Lighthouse - 5 | C65: 103 | D65: Surfside - 1 | E65: 745 | F65: Vacant Unit | G65: 1540 | H65: 0 | I65: =IF(H65=0,"",D65)
B66: Ocean Breeze - End Unit | C66: 104 | D66: Surfside - 1 | E66: 745 | F66: Vacant Unit | G66: 1540 | H66: 0 | I66: =IF(H66=0,"",D66)
B67: Seaglass - 3 | C67: 105 | D67: Surfside - 1 | E67: 745 | F67: Vacant Unit | G67: 1540 | H67: 0 | I67: =IF(H67=0,"",D67)
B68: Shoreline - 4 | C68: 106 | D68: Surfside - 1 | E68: 745 | F68: Vacant Unit | G68: 1540 | H68: 0 | I68: =IF(H68=0,"",D68)
B69: Surfside - 1 | C69: 107 | D69: Surfside - 1 | E69: 745 | F69: Vacant Unit | G69: 1540 | H69: 0 | I69: =IF(H69=0,"",D69)
B70: Surfside - 1ADA | C70: 108 | D70: Driftwood - 2 | E70: 995 | F70: Vacant Unit | G70: 1675 | H70: 0 | I70: =IF(H70=0,"",D70)
B71: (blank) | C71: 109 | D71: Driftwood - 2ADA | E71: 995 | F71: Vacant Unit | G71: 1675 | H71: 0 | I71: =IF(H71=0,"",D71)
B72: Grand Total | C72: 110 | D72: Surfside - 1ADA | E72: 745 | F72: Vacant Unit | G72: 1540 | H72: 0 | I72: =IF(H72=0,"",D72)
C73: 111 | D73: Surfside - 1 | E73: 745 | F73: Vacant Unit | G73: 1540 | H73: 0 | I73: =IF(H73=0,"",D73)
C74: 116 | D74: Driftwood - 2 | E74: 995 | F74: Brunswick Resources | G74: 2350 | H74: 2350 | I74: =IF(H74=0,"",D74) -> Driftwood - 2
C75: 117 | D75: Surfside - 1 | E75: 745 | F75: Vacant Unit | G75: 1540 | H75: 0 | I75: =IF(H75=0,"",D75)
C76: 118 | D76: Surfside - 1 | E76: 745 | F76: Vacant Unit | G76: 1540 | H76: 0 | I76: =IF(H76=0,"",D76)
C77: 119 | D77: Surfside - 1 | E77: 745 | F77: Vacant Unit | G77: 1540 | H77: 0 | I77: =IF(H77=0,"",D77)
C78: 120 | D78: Surfside - 1 | E78: 745 | F78: Vacant Unit | G78: 1540 | H78: 0 | I78: =IF(H78=0,"",D78)
C79: 121 | D79: Surfside - 1 | E79: 745 | F79: Vacant Unit | G79: 1540 | H79: 0 | I79: =IF(H79=0,"",D79)
C80: 122 | D80: Surfside - 1 | E80: 745 | F80: Grace Batchelor | G80: 2350 | H80: 2350 | I80: =IF(H80=0,"",D80) -> Surfside - 1
C81: 123 | D81: Surfside - 1 | E81: 745 | F81: Vacant Unit | G81: 1540 | H81: 0 | I81: =IF(H81=0,"",D81)
C82: 124 | D82: Seaglass - 3 | E82: 1000 | F82: Vacant Unit | G82: 1895 | H82: 0 | I82: =IF(H82=0,"",D82)
C83: 125 | D83: Seaglass - 3 | E83: 1000 | F83: Vacant Unit | G83: 1895 | H83: 0 | I83: =IF(H83=0,"",D83)
C84: 200 | D84: Seaglass - 3 | E84: 1000 | F84: James Marchak | G84: 2025 | H84: 2025 | I84: =IF(H84=0,"",D84) -> Seaglass - 3
... C193: 767-H | D193: Ocean Breeze - End Unit | E193: 1210 | F193: Doug Cunha | G193: 2870 | H193: 2870 | I193: =IF(H193=0,"",D193) -> Ocean Breeze - End Unit
I194: =IF(H194=0,"",D194)
I195: =IF(H195=0,"",D195)
I196: =IF(H196=0,"",D196)
I197: =IF(H197=0,"",D197)
I198: =IF(H198=0,"",D198)
I199: =IF(H199=0,"",D199)
I200: =IF(H200=0,"",D200)
I201: =IF(H201=0,"",D201)
I202: =IF(H202=0,"",D202)
I203: =IF(H203=0,"",D203)
I204: =IF(H204=0,"",D204)
I205: =IF(H205=0,"",D205)
... I1061: =IF(H1061=0,"",D1061)

Sheet Sources & Usage
B2: =Loan!B2 -> Calabash Shores | C2: ='CFS-Main Page'!C2 -> Address: | D2: ='CFS-Main Page'!D2 -> 660 Aubrey Ln Calabash, NC, 28467
B3: Sources & Usage | C3: ='CFS-Main Page'!C3 -> Units | D3: ='CFS-Main Page'!D3 -> 132
B4: =Loan!B4 -> 0 | C4: ='CFS-Main Page'!C4 -> Year Built/Reno | D4: ='CFS-Main Page'!D4 -> 2024
B6: Source of Funding (Pre Refinance) | C6: Amount | D6: Per Unit
B7: Debt | C7: =IF(Loan!C9=0,Loan!C30,Loan!$C$9) -> 24500000 | D7: =C7/Units -> 185606.06 | E7: =C7/$C$9 -> 0.68829892
B8: Equity | C8: =C23-C7 -> 11095000 | D8: =C8/Units -> 84053.03 | E8: =C8/$C$9 -> 0.31170108
B9: Total | C9: =SUM(C7:C8) -> 35595000 | D9: =SUM(D7:D8) -> 269659.09 | E9: =SUM(E7:E8) -> 1
B11: Usage of Funding | C11: Amount | D11: Per Unit
B12: Purchase Price | C12: ='CFS-Main Page'!C7 -> 35000000 | D12: =C12/Units -> 265151.52 | E12: =C12/$C$23 -> 0.98328417
B13: Loan Processing Fees | C13: =C7*F13 -> 245000 | D13: =C13/Units -> 1856.0606 | E13: =C13/$C$23 -> 0.0068829892 | F13: 0.01
B14: Acquisition Fees | C14: =F14*C12 -> 350000 | D14: =C14/Units -> 2651.5152 | E14: =C14/$C$23 -> 0.0098328417 | F14: 0.01
B15: Renovation Cost | C15: =Rent!H57 -> 0 | D15: =C15/Units -> 0 | E15: =C15/$C$23 -> 0
B16: Additional Capex | C16: 0 | D16: =C16/Units -> 0 | E16: =C16/$C$23 -> 0
B17: Equity Fees | C17: 0 | D17: =C17/Units -> 0 | E17: =C17/$C$23 -> 0
B18: Legal | C18: 0 | D18: =C18/Units -> 0 | E18: =C18/$C$23 -> 0
B19: Other Closing Cost | C19: 0 | D19: =C19/Units -> 0 | E19: =C19/$C$23 -> 0
B20: Other Closing Cost | C20: 0 | D20: =C20/Units -> 0 | E20: =C20/$C$23 -> 0
B21: Other Closing Cost | C21: 0 | D21: =C21/Units -> 0 | E21: =C21/$C$23 -> 0
B22: Other Closing Cost | C22: =C12*F22 -> 0 | D22: =C22/Units -> 0 | E22: =C22/$C$23 -> 0 | F22: 0
B23: Total | C23: =SUM(C12:C22) -> 35595000 | D23: =SUM(D12:D22) -> 269659.09 | E23: 1

Sheet Loan
B2: =Rent!B2 -> Calabash Shores | C2: ='CFS-Main Page'!C2 -> Address: | D2: ='CFS-Main Page'!D2 -> 660 Aubrey Ln Calabash, NC, 28467
B3: Loan Schedule | C3: ='CFS-Main Page'!C3 -> Units | D3: ='CFS-Main Page'!D3 -> 132
B4: =Rent!B4 -> 0 | C4: ='CFS-Main Page'!C4 -> Year Built/Reno | D4: ='CFS-Main Page'!D4 -> 2024
B6: Loan Assumptions - Acquisition Loan
B7: Project Cost | C7: ='Sources & Usage'!C23 -> 35595000
B8: LTV | C8: 0.7 | D8: =C9/C7 -> 0.68829892
B9: Loan Amount | C9: =IF(C12>0,ROUND('CFS-Main Page'!C7*C8,-4),0) -> 24500000
B10: Processing Fees | C10: =C9*D10 -> 245000 | D10: ='Sources & Usage'!F13 -> 0.01
B11: Amortization Period (Years) | C11: 30
B12: Loan Termination for Refinance | C12: ='CFS-Main Page'!C13 -> 5 | D12: ← Input 0 if not using
B13: Interest Rate | C13: =3.912%+1.4% -> 0.05312
B14: I/O Period | C14: 3
B15: Debt Service Constant | C15: =-PMT(C13/12,C11*12,1)*12 -> 0.06672601
B16: Annual Payment Constant | C16: =C15*C9 -> 1634787.3
B17: Loan Schedule (First) | D17: 0 | E17: 1 | F17: 2 | G17: 3 | H17: 4 | I17: 5 | J17: 6 | K17: 7 | L17: 8 | M17: 9 | N17: 10
B18: Loan Amount BB | E18: =D23 -> 24500000 | F18: =E23 -> 24500000 | G18: =F23 -> 24500000 | H18: =G23 -> 24500000 | I18: =H23 -> 24166653 | J18: =I23 -> 0 | K18: =J23 -> 0 | L18: =K23 -> 0 | ... N18: =M23 -> 0
B19: Interest Payment | E19: =IF(E17>$C$12,0,E18*$C$13) -> 1301440 | F19: =IF(F17>$C$12,0,F18*$C$13) -> 1301440 | G19: =IF(G17>$C$12,0,G18*$C$13) -> 1301440 | H19: =IF(H17>$C$12,0,H18*$C$13) -> 1301440 | I19: =IF(I17>$C$12,0,I18*$C$13) -> 1283732.6 | J19: =IF(J17>$C$12,0,J18*$C$13) -> 0 | K19: =IF(K17>$C$12,0,K18*$C$13) -> 0 | L19: =IF(L17>$C$12,0,L18*$C$13) -> 0 | ... N19: =IF(N17>$C$12,0,N18*$C$13) -> 0
B20: Principal Payment | E20: =IF(OR(E17<=$C$14,E17>$C$12),0,$C$16-E19) -> 0 | F20: =IF(OR(F17<=$C$14,F17>$C$12),0,$C$16-F19) -> 0 | G20: =IF(OR(G17<=$C$14,G17>$C$12),0,$C$16-G19) -> 0 | H20: =IF(OR(H17<=$C$14,H17>$C$12),0,$C$16-H19) -> 333347.25 | I20: =IF(OR(I17<=$C$14,I17>$C$12),0,$C$16-I19) -> 351054.66 | J20: =IF(OR(J17<=$C$14,J17>$C$12),0,$C$16-J19) -> 0 | K20: =IF(OR(K17<=$C$14,K17>$C$12),0,$C$16-K19) -> 0 | L20: =IF(OR(L17<=$C$14,L17>$C$12),0,$C$16-L19) -> 0 | ... N20: =IF(OR(N17<=$C$14,N17>$C$12),0,$C$16-N19) -> 0
B21: Loan Payoff | E21: =IF(E17=$C$12,E18-E20,0) -> 0 | F21: =IF(F17=$C$12,F18-F20,0) -> 0 | G21: =IF(G17=$C$12,G18-G20,0) -> 0 | H21: =IF(H17=$C$12,H18-H20,0) -> 0 | I21: =IF(I17=$C$12,I18-I20,0) -> 23815598 | J21: =IF(J17=$C$12,J18-J20,0) -> 0 | K21: =IF(K17=$C$12,K18-K20,0) -> 0 | L21: =IF(L17=$C$12,L18-L20,0) -> 0 | ... N21: =IF(N17=$C$12,N18-N20,0) -> 0
B22: Total Debt Payment | E22: =SUM(E19:E20) -> 1301440 | F22: =SUM(F19:F20) -> 1301440 | G22: =SUM(G19:G20) -> 1301440 | H22: =SUM(H19:H20) -> 1634787.3 | I22: =SUM(I19:I20) -> 1634787.3 | J22: =SUM(J19:J20) -> 0 | K22: =SUM(K19:K20) -> 0 | L22: =SUM(L19:L20) -> 0 | ... N22: =SUM(N19:N20) -> 0
B23: Loan Balance End of Year | D23: =C9 -> 24500000 | E23: =E18-E20-E21 -> 24500000 | F23: =F18-F20-F21 -> 24500000 | G23: =G18-G20-G21 -> 24500000 | H23: =H18-H20-H21 -> 24166653 | I23: =I18-I20-I21 -> 0 | J23: =J18-J20-J21 -> 0 | K23: =K18-K20-K21 -> 0 | L23: =L18-L20-L21 -> 0 | ... N23: =N18-N20-N21 -> 0
B25: Loan Assumptions - Refinance | G25: Refinancing assumptions
B26: Total cost | C26: ='Sources & Usage'!C23 -> 35595000 | G26: Year of Refinance | H26: =C12 -> 5
G27: =CONCATENATE("Year ", H26," NOI") -> Year 5 NOI | H27: {=IF(H26<1,0,INDEX('CFS-Main Page'!I63:S63,Loan!$H$26))} -> 2030409.2
B28: LTV | C28: 0.8 | G28: DCR Sizing | H28: 1.25
B29: LTC | C29: =C30/C26 -> 0
B30: Loan Amount | C30: 0 | D30: ← Input 0 if not using Refinance and Loan amount can be Hardcoded. =ROUND(IF(H26=0,C28*C26,H33),-4) | G30: Constant | H30: =-PMT(C33/12,C31*12,1)*12 -> 0.075848163
B31: Amortization Period (Years) | C31: 30 | G31: Debt Service | H31: =IF(H26=0,C30*H30,H27/H28) -> 1624327.4
B32: Loan Term (Years)_Holding | C32: =IF(H26>0,MIN('CFS-Main Page'!C13+$H$26,N35),'CFS-Main Page'!C13) -> 10 | G32: Max Proceed | H32: =ROUND(H31/H30,-4) -> 21420000
B33: Interest Rate | C33: 0.065 | G33: Bridge Loan payoff | H33: =SUM(E21:N21) -> 23815598
B34: I/O Period | C34: 10
B35: Loan Schedule (Refinance) | D35: 0 | E35: 1 | F35: 2 | G35: 3 | H35: 4 | I35: 5 | J35: 6 | K35: 7 | L35: 8 | M35: 9 | N35: 10
B36: Loan Amount BB | E36: =IF($H$26>0,IF(E$35=$H$26+1,$C$30,IF(E$35>=$H$26,D$41,0)),IF(E$35=1,$C$30,D$41)) -> 0 | F36: =IF($H$26>0,IF(F$35=$H$26+1,$C$30,IF(F$35>=$H$26,E$41,0)),IF(F$35=1,$C$30,E$41)) -> 0 | G36: =IF($H$26>0,IF(G$35=$H$26+1,$C$30,IF(G$35>=$H$26,F$41,0)),IF(G$35=1,$C$30,F$41)) -> 0 | H36: =IF($H$26>0,IF(H$35=$H$26+1,$C$30,IF(H$35>=$H$26,G$41,0)),IF(H$35=1,$C$30,G$41)) -> 0 | I36: =IF($H$26>0,IF(I$35=$H$26+1,$C$30,IF(I$35>=$H$26,H$41,0)),IF(I$35=1,$C$30,H$41)) -> 0 | J36: =IF($H$26>0,IF(J$35=$H$26+1,$C$30,IF(J$35>=$H$26,I$41,0)),IF(J$35=1,$C$30,I$41)) -> 0 | K36: =IF($H$26>0,IF(K$35=$H$26+1,$C$30,IF(K$35>=$H$26,J$41,0)),IF(K$35=1,$C$30,J$41)) -> 0 | L36: =IF($H$26>0,IF(L$35=$H$26+1,$C$30,IF(L$35>=$H$26,K$41,0)),IF(L$35=1,$C$30,K$41)) -> 0 | ... N36: =IF($H$26>0,IF(N$35=$H$26+1,$C$30,IF(N$35>=$H$26,M$41,0)),IF(N$35=1,$C$30,M$41)) -> 0
B37: Interest Payment | E37: =IF(E35>$C$32,0,E36*$C$33) -> 0 | F37: =IF(F35>$C$32,0,F36*$C$33) -> 0 | G37: =IF(G35>$C$32,0,G36*$C$33) -> 0 | H37: =IF(H35>$C$32,0,H36*$C$33) -> 0 | I37: =IF(I35>$C$32,0,I36*$C$33) -> 0 | J37: =IF(J35>$C$32,0,J36*$C$33) -> 0 | K37: =IF(K35>$C$32,0,K36*$C$33) -> 0 | L37: =IF(L35>$C$32,0,L36*$C$33) -> 0 | ... N37: =IF(N35>$C$32,0,N36*$C$33) -> 0
B38: Principal | E38: =IF(E36>0,IF(OR(E35<=$C$34,E35>$C$32),0,$H$31-E37),0) -> 0 | F38: =IF(F36>0,IF(OR(F35<=$C$34,F35>$C$32),0,$H$31-F37),0) -> 0 | G38: =IF(G36>0,IF(OR(G35<=$C$34,G35>$C$32),0,$H$31-G37),0) -> 0 | H38: =IF(H36>0,IF(OR(H35<=$C$34,H35>$C$32),0,$H$31-H37),0) -> 0 | I38: =IF(I36>0,IF(OR(I35<=$C$34,I35>$C$32),0,$H$31-I37),0) -> 0 | J38: =IF(J36>0,IF(OR(J35<=$C$34,J35>$C$32),0,$H$31-J37),0) -> 0 | K38: =IF(K36>0,IF(OR(K35<=$C$34,K35>$C$32),0,$H$31-K37),0) -> 0 | L38: =IF(L36>0,IF(OR(L35<=$C$34,L35>$C$32),0,$H$31-L37),0) -> 0 | ... N38: =IF(N36>0,IF(OR(N35<=$C$34,N35>$C$32),0,$H$31-N37),0) -> 0
B39: Loan Payoff | E39: =IF(E35=$C$32,E36-E38,0) -> 0 | F39: =IF(F35=$C$32,F36-F38,0) -> 0 | G39: =IF(G35=$C$32,G36-G38,0) -> 0 | H39: =IF(H35=$C$32,H36-H38,0) -> 0 | I39: =IF(I35=$C$32,I36-I38,0) -> 0 | J39: =IF(J35=$C$32,J36-J38,0) -> 0 | K39: =IF(K35=$C$32,K36-K38,0) -> 0 | L39: =IF(L35=$C$32,L36-L38,0) -> 0 | ... N39: =IF(N35=$C$32,N36-N38,0) -> 0
B40: Total Debt Payment | E40: =E37+E38 -> 0 | F40: =F37+F38 -> 0 | G40: =G37+G38 -> 0 | H40: =H37+H38 -> 0 | I40: =I37+I38 -> 0 | J40: =J37+J38 -> 0 | K40: =K37+K38 -> 0 | L40: =L37+L38 -> 0 | ... N40: =N37+N38 -> 0
B41: Loan Balance End of Year | D41: =IF(H26>0,0,C30) -> 0 | E41: =E$36-E$38-E$39 -> 0 | F41: =F$36-F$38-F$39 -> 0 | G41: =G$36-G$38-G$39 -> 0 | H41: =H$36-H$38-H$39 -> 0 | I41: =I$36-I$38-I$39 -> 0 | J41: =J$36-J$38-J$39 -> 0 | K41: =K$36-K$38-K$39 -> 0 | L41: =L$36-L$38-L$39 -> 0 | ... N41: =N$36-N$38-N$39 -> 0
B43: Total Principal Payment | E43: =E20+E38 -> 0 | F43: =F20+F38 -> 0 | G43: =G20+G38 -> 0 | H43: =H20+H38 -> 333347.25 | I43: =I20+I38 -> 351054.66 | J43: =J20+J38 -> 0 | K43: =K20+K38 -> 0 | L43: =L20+L38 -> 0 | ... N43: =N20+N38 -> 0
B44: Total Loan Payoff | E44: =E21+E39-(IF(E21>0,F36,0)) -> 0 | F44: =F21+F39-(IF(F21>0,G36,0)) -> 0 | G44: =G21+G39-(IF(G21>0,H36,0)) -> 0 | H44: =H21+H39-(IF(H21>0,I36,0)) -> 0 | I44: =I21+I39-(IF(I21>0,J36,0)) -> 23815598 | J44: =J21+J39-(IF(J21>0,K36,0)) -> 0 | K44: =K21+K39-(IF(K21>0,L36,0)) -> 0 | L44: =L21+L39-(IF(L21>0,M36,0)) -> 0 | ... N44: =N21+N39-(IF(N21>0,O36,0)) -> 0
B45: Total Interest Payment | D45: =D37+D19 -> 0 | E45: =E37+E19 -> 1301440 | F45: =F37+F19 -> 1301440 | G45: =G37+G19 -> 1301440 | H45: =H37+H19 -> 1301440 | I45: =I37+I19 -> 1283732.6 | J45: =J37+J19 -> 0 | K45: =K37+K19 -> 0 | ... N45: =N37+N19 -> 0
B46: Debt Service | D46: =D45 -> 0 | E46: =E45+E43 -> 1301440 | F46: =F45+F43 -> 1301440 | G46: =G45+G43 -> 1301440 | H46: =H45+H43 -> 1634787.3 | I46: =I45+I43 -> 1634787.3 | J46: =J45+J43 -> 0 | K46: =K45+K43 -> 0 | L46: =L45+L43 -> 0 | ... N46: =N45+N43 -> 0

Sheet Historical Analysis
B2: ='Sources & Usage'!B2 -> Calabash Shores
B3: Historical Analysis
B4: ='Sources & Usage'!B4 -> 0
D5: =1 -> 1 | E5: =D5+1 -> 2 | F5: =E5+1 -> 3 | G5: =F5+1 -> 4 | H5: =G5+1 -> 5 | I5: =H5+1 -> 6 | J5: =I5+1 -> 7 | K5: =J5+1 -> 8 | L5: =K5+1 -> 9 | ... O5: =N5+1 -> 12
C6: ="T12 ending "&TEXT(O6,"mmm-yy") -> T12 ending Dec-25 | D6: 45658 | E6: =EOMONTH(D6,1) -> 45716 | F6: =EOMONTH(E6,1) -> 45747 | G6: =EOMONTH(F6,1) -> 45777 | H6: =EOMONTH(G6,1) -> 45808 | I6: =EOMONTH(H6,1) -> 45838 | J6: =EOMONTH(I6,1) -> 45869 | K6: =EOMONTH(J6,1) -> 45900 | L6: =EOMONTH(K6,1) -> 45930 | ... O6: =EOMONTH(N6,1) -> 46022 | Q6: T12 | R6: T3 | T6: Category | V6: Summary
Q8: =SUM(D8:O8) -> 0 | R8: =SUM(M8:O8)*4 -> 0 | T8: 1 - Market Rent Potential | V8: Operating Incomes | W8: T12 | X8: T3
C9: Net Rental Income | Q9: =SUM(D9:O9) -> 0 | R9: =SUM(M9:O9)*4 -> 0 | T9: 2 - Increase in Rent from Renovation | U9: 1 | V9: Market Rent Potential | W9: =SUMIF($B$1:$B$495,U9,$Q$1:$Q$495) -> 3865317 | X9: =SUMIF($B$1:$B$495,U9,$R$1:$R$495) -> 3121240
B10: 1 | C10: Gross Possible Rent | D10: 342198 | E10: 347296 | F10: 346450 | G10: 344142 | H10: 337405 | I10: 341284 | J10: 342324 | K10: 341704 | L10: 342204 | M10: 260655 | N10: 260225 | O10: 259430 | Q10: =SUM(D10:O10) -> 3865317 | R10: =SUM(M10:O10)*4 -> 3121240 | T10: 3 - Loss to Lease | U10: 2 | V10: Increase in Market Rent Potential from Renovation | W10: =SUMIF($B$1:$B$495,U10,$Q$1:$Q$495) -> 0 | X10: =SUMIF($B$1:$B$495,U10,$R$1:$R$495) -> 0
C11: Gross Potential Rent | D11: 342198 | E11: 347296 | F11: 346450 | G11: 344142 | H11: 337405 | I11: 341284 | J11: 342324 | K11: 341704 | L11: 342204 | M11: 260655 | N11: 260225 | O11: 259430 | Q11: =SUM(D11:O11) -> 3865317 | R11: =SUM(M11:O11)*4 -> 3121240 | T11: 4 - Vacancy | V11: Total Market Rent Potential | W11: =SUM(W9:W10) -> 3865317 | X11: =SUM(X9:X10) -> 3121240
C12: Deductions | Q12: =SUM(D12:O12) -> 0 | R12: =SUM(M12:O12)*4 -> 0 | T12: 5 - Concession/Discount | U12: 3 | V12: Loss to Lease | W12: =SUMIF($B$1:$B$495,U12,$Q$1:$Q$495) -> 0 | X12: =SUMIF($B$1:$B$495,U12,$R$1:$R$495) -> 0 | Y12: =W12/W11 -> 0
B13: 4 | C13: Vacancy Loss | D13: -336374 | E13: -319718 | F13: -318688 | G13: -311160 | H13: -295563 | I13: -288482 | J13: -292912 | K13: -284302 | L13: -281071 | M13: -187981 | N13: -180049 | O13: -176206 | Q13: =SUM(D13:O13) -> -3272506 | R13: =SUM(M13:O13)*4 -> -2176944 | T13: 6 - Bad Debt | V13: Gross Rent Potential | W13: =W11+W12 -> 3865317 | X13: =X11+X12 -> 3121240
B14: 7 | C14: Vacancy Loss - Model Units | D14: -2870 | E14: -2870 | F14: -2870 | G14: -2870 | H14: 0 | I14: 0 | J14: 0 | K14: 0 | L14: 0 | M14: 0 | N14: 0 | O14: 0 | Q14: =SUM(D14:O14) -> -11480 | R14: =SUM(M14:O14)*4 -> 0 | T14: 7 - Non Revenue Units | U14: 4 | V14: Vacancy | W14: =SUMIF($B$1:$B$495,U14,$Q$1:$Q$495) -> -3272506 | X14: =SUMIF($B$1:$B$495,U14,$R$1:$R$495) -> -2176944
B15: 5 | C15: Rent Concessions | D15: 0 | E15: 0 | F15: 0 | G15: 0 | H15: -10440 | I15: -17220 | J15: -13310 | K15: -16530 | L15: -6090 | M15: -17570 | N15: -20440 | O15: -23310 | Q15: =SUM(D15:O15) -> -124910 | R15: =SUM(M15:O15)*4 -> -245280 | T15: 8 - Utility Reimbursements | U15: 5 | V15: Concession/Discount | W15: =SUMIF($B$1:$B$495,U15,$Q$1:$Q$495) -> -125930 | X15: =SUMIF($B$1:$B$495,U15,$R$1:$R$495) -> -247280
B16: 5 | C16: Referral Discount | D16: 0 | E16: 0 | F16: 0 | G16: 0 | H16: 0 | I16: 0 | J16: 0 | K16: 0 | L16: 0 | M16: 0 | N16: 0 | O16: -500 | Q16: =SUM(D16:O16) -> -500 | R16: =SUM(M16:O16)*4 -> -2000 | T16: 9 - Other Reimbursements | U16: 6 | V16: Bad Debt | W16: =SUMIF($B$1:$B$495,U16,$Q$1:$Q$495) -> 0 | X16: =SUMIF($B$1:$B$495,U16,$R$1:$R$495) -> 0
B17: 5 | C17: Miscellaneous Credit | D17: 0 | E17: 0 | F17: 0 | G17: 0 | H17: 0 | I17: 0 | J17: -520 | K17: 0 | L17: 0 | M17: 0 | N17: 0 | O17: 0 | Q17: =SUM(D17:O17) -> -520 | R17: =SUM(M17:O17)*4 -> 0 | T17: 10 - Other Income | U17: 7 | V17: Non Revenue Units | W17: =SUMIF($B$1:$B$495,U17,$Q$1:$Q$495) -> -11480 | X17: =SUMIF($B$1:$B$495,U17,$R$1:$R$495) -> 0
C18: Total Deductions | D18: -339244 | E18: -322588 | F18: -321558 | G18: -314030 | H18: -306003 | I18: -305702 | J18: -306742 | K18: -300832 | L18: -287161 | M18: -205551 | N18: -200489 | O18: -200016 | Q18: =SUM(D18:O18) -> -3409916 | R18: =SUM(M18:O18)*4 -> -2424224 | T18: 11 - Repair & Maintenance | V18: Gross Effective Income | W18: =SUM(W13:W17) -> 455401 | X18: =SUM(X13:X17) -> 697016
C19: Total Net Rental Income | D19: 2954 | E19: 24708 | F19: 24892 | G19: 30112 | H19: 31402 | I19: 35582 | J19: 35582 | K19: 40872 | L19: 55043 | M19: 55104 | N19: 59736 | O19: 59414 | Q19: =SUM(D19:O19) -> 455401 | R19: =SUM(M19:O19)*4 -> 697016 | T19: 12 - Cleaning & Decorating | U19: 8 | V19: Utility Reimbursements | W19: =SUMIF($B$1:$B$495,U19,$Q$1:$Q$495) -> 585 | X19: =SUMIF($B$1:$B$495,U19,$R$1:$R$495) -> 2340
C20: Other Income | Q20: =SUM(D20:O20) -> 0 | R20: =SUM(M20:O20)*4 -> 0 | T20: 13 - Contract & Services | U20: 9 | V20: Other Reimbursements | W20: =SUMIF($B$1:$B$495,U20,$Q$1:$Q$495) -> 124 | X20: =SUMIF($B$1:$B$495,U20,$R$1:$R$495) -> 496
B21: 8 | C21: Electric Income | D21: 0 | E21: 0 | F21: 0 | G21: 0 | H21: 0 | I21: 0 | J21: 0 | K21: 0 | L21: 0 | M21: 0 | N21: 76 | O21: 282 | Q21: =SUM(D21:O21) -> 358 | R21: =SUM(M21:O21)*4 -> 1432 | T21: 14 - Utility- Electricity | U21: 10 | V21: Other Income | W21: =SUMIF($B$1:$B$495,U21,$Q$1:$Q$495) -> 28407.75 | X21: =SUMIF($B$1:$B$495,U21,$R$1:$R$495) -> 45501
B22: 8 | C22: Water Income | D22: 0 | E22: 0 | F22: 0 | G22: 0 | H22: 0 | I22: 0 | J22: 0 | K22: 0 | L22: 0 | M22: 0 | N22: 32 | O22: 118 | Q22: =SUM(D22:O22) -> 150 | R22: =SUM(M22:O22)*4 -> 600 | T22: 15 - Utility- Water | V22: Total Operating Revenue | W22: =SUM(W18:W21) -> 484517.75 | X22: =SUM(X18:X21) -> 745353
B23: 9 | C23: Broadband Income | D23: 0 | E23: 0 | F23: 0 | G23: 0 | H23: 0 | I23: 0 | J23: 0 | K23: 0 | L23: 0 | M23: 0 | N23: 26 | O23: 98 | Q23: =SUM(D23:O23) -> 124 | R23: =SUM(M23:O23)*4 -> 496 | T23: 16 - Utility- Others
B24: 10 | C24: Insurance Income | D24: 0 | E24: 0 | F24: 0 | G24: 40 | H24: 70 | I24: -90 | J24: -20 | K24: 0 | L24: 0 | M24: 0 | N24: 0 | O24: 0 | Q24: =SUM(D24:O24) -> 0 | R24: =SUM(M24:O24)*4 -> 0 | T24: 17 - Marketing | V24: Operating Expenses | W24: T12 | X24: T3
B25: 10 | C25: Tenant Service Request Income | D25: 0 | E25: 0 | F25: 0 | G25: 0 | H25: 0 | I25: 0 | J25: 0 | K25: 0 | L25: 0 | M25: 0 | N25: 0 | O25: 0 | Q25: =SUM(D25:O25) -> 0 | R25: =SUM(M25:O25)*4 -> 0 | T25: 18 - Payroll | U25: 11 | V25: Repair & Maintenance | W25: =SUMIF($B$1:$B$495,U25,$Q$1:$Q$495) -> 183567.24 | X25: =SUMIF($B$1:$B$495,U25,$R$1:$R$495) -> 172429.24
B26: 10 | C26: Late Fees | D26: 0 | E26: 0 | F26: 0 | G26: 287 | H26: 111.5 | I26: -398.5 | J26: 0 | K26: 143.5 | L26: 0 | M26: 224 | N26: 468.75 | O26: -382.5 | Q26: =SUM(D26:O26) -> 453.75 | R26: =SUM(M26:O26)*4 -> 1241 | T26: 19 - RE Taxes | U26: 12 | V26: Cleaning & Decorating | W26: =SUMIF($B$1:$B$495,U26,$Q$1:$Q$495) -> 13994.57 | X26: =SUMIF($B$1:$B$495,U26,$R$1:$R$495) -> 27232.76
B27: 10 | C27: Valet Tips | D27: 300 | E27: 300 | F27: 600 | G27: 0 | H27: 300 | I27: -300 | J27: 0 | K27: 100 | L27: 300 | M27: 100 | N27: 100 | O27: 100 | Q27: =SUM(D27:O27) -> 1900 | R27: =SUM(M27:O27)*4 -> 1200 | T27: 20 - Insurance | U27: 13 | V27: Contract & Services | W27: =SUMIF($B$1:$B$495,U27,$Q$1:$Q$495) -> 14865.53 | X27: =SUMIF($B$1:$B$495,U27,$R$1:$R$495) -> 11974
B28: 10 | C28: Application Fee | D28: 85 | E28: 85 | F28: 425 | G28: 0 | H28: 854 | I28: -170 | J28: 810 | K28: 255 | L28: 525 | M28: 170 | N28: 425 | O28: 255 | Q28: =SUM(D28:O28) -> 3719 | R28: =SUM(M28:O28)*4 -> 3400 | T28: 21 - Property Mangement fees | U28: 14 | V28: Utility | W28: =SUMIF($B$1:$B$495,U28,$Q$1:$Q$495) -> 73738.93 | X28: =SUMIF($B$1:$B$495,U28,$R$1:$R$495) -> 75831.68
B29: 10 | C29: Pet Fee | D29: 0 | E29: 0 | F29: 0 | G29: 0 | H29: 0 | I29: 0 | J29: 0 | K29: 35 | L29: 385 | M29: 35 | N29: 490 | O29: 70 | Q29: =SUM(D29:O29) -> 1015 | R29: =SUM(M29:O29)*4 -> 2380 | T29: 22 - General & Administrative Expenses | U29: 15 | V29: Utility- Water | W29: =SUMIF($B$1:$B$495,U29,$Q$1:$Q$495) -> 79997.63 | X29: =SUMIF($B$1:$B$495,U29,$R$1:$R$495) -> 89185
B30: 8 | C30: Utility Administration Fee | D30: 0 | E30: 0 | F30: 0 | G30: 0 | H30: 0 | I30: 0 | J30: 0 | K30: 0 | L30: 0 | M30: 0 | N30: 16 | O30: 61 | Q30: =SUM(D30:O30) -> 77 | R30: =SUM(M30:O30)*4 -> 308 | T30: 23 - Other taxes/Permit license fees | U30: 16 | V30: Utility- Others | W30: =SUMIF($B$1:$B$495,U30,$Q$1:$Q$495) -> 7313.09 | X30: =SUMIF($B$1:$B$495,U30,$R$1:$R$495) -> 23186.4
B31: 10 | C31: Miscellaneous Income | D31: 0 | E31: 0 | F31: 0 | G31: 0 | H31: 0 | I31: 0 | J31: 0 | K31: 0 | L31: 0 | M31: 0 | N31: 160 | O31: 160 | Q31: =SUM(D31:O31) -> 320 | R31: =SUM(M31:O31)*4 -> 1280 | T31: 24 - NOI | U31: 17 | V31: Marketing | W31: =SUMIF($B$1:$B$495,U31,$Q$1:$Q$495) -> 154532.67 | X31: =SUMIF($B$1:$B$495,U31,$R$1:$R$495) -> 147922.44
B32: 10 | C32: Other Income - Other | D32: 0 | E32: 0 | F32: 0 | G32: 0 | H32: 0 | I32: 0 | J32: 0 | K32: 12000 | L32: 0 | M32: 9000 | N32: 0 | O32: 0 | Q32: =SUM(D32:O32) -> 21000 | R32: =SUM(M32:O32)*4 -> 36000 | T32: 1 - Market Rent Potential | U32: 18 | V32: Payroll | W32: =SUMIF($B$1:$B$495,U32,$Q$1:$Q$495) -> 95880.89 | X32: =SUMIF($B$1:$B$495,U32,$R$1:$R$495) -> 98123.52
C33: Total Other Income | D33: 385 | E33: 385 | F33: 1025 | G33: 327 | H33: 1335.5 | I33: -958.5 | J33: 790 | K33: 12533.5 | L33: 1210 | M33: 9529 | N33: 1793.75 | O33: 761.5 | Q33: =SUM(D33:O33) -> 29116.75 | R33: =SUM(M33:O33)*4 -> 48337 | T33: 2 - Increase in Rent from Renovation | U33: 19 | V33: RE Taxes | W33: =SUMIF($B$1:$B$495,U33,$Q$1:$Q$495) -> 118548.62 | X33: =SUMIF($B$1:$B$495,U33,$R$1:$R$495) -> 118548.6
C34: TOTAL INCOME | D34: 3339 | E34: 25093 | F34: 25917 | G34: 30439 | H34: 32737.5 | I34: 34623.5 | J34: 36372 | K34: 53405.5 | L34: 56253 | M34: 64633 | N34: 61529.75 | O34: 60175.5 | Q34: =SUM(D34:O34) -> 484517.75 | R34: =SUM(M34:O34)*4 -> 745353 | T34: 3 - Loss to Lease | U34: 20 | V34: Insurance | W34: =SUMIF($B$1:$B$495,U34,$Q$1:$Q$495) -> 350471.86 | X34: =SUMIF($B$1:$B$495,U34,$R$1:$R$495) -> 819039.28
C35: EXPENSE | Q35: =SUM(D35:O35) -> 0 | R35: =SUM(M35:O35)*4 -> 0 | T35: 4 - Vacancy | U35: 21 | V35: Property Mangement fees | W35: =SUMIF($B$1:$B$495,U35,$Q$1:$Q$495) -> 30312.65 | X35: =SUMIF($B$1:$B$495,U35,$R$1:$R$495) -> 30000 | Y35: =W35/W18 -> 0.066562546
C36: Administrative Expense | Q36: =SUM(D36:O36) -> 0 | R36: =SUM(M36:O36)*4 -> 0 | T36: 5 - Concession/Discount | U36: 22 | V36: General & Administrative Expenses | W36: =SUMIF($B$1:$B$495,U36,$Q$1:$Q$495) -> 44364.92 | X36: =SUMIF($B$1:$B$495,U36,$R$1:$R$495) -> 85518.4
B37: 22 | C37: Administrative Expense - Other | D37: 0 | E37: 0 | F37: 51.39 | G37: 0 | H37: 0 | I37: 0 | J37: 0 | K37: 0 | L37: 0 | M37: 56 | N37: 203 | O37: 0 | Q37: =SUM(D37:O37) -> 310.39 | R37: =SUM(M37:O37)*4 -> 1036 | T37: 6 - Bad Debt | U37: 23 | V37: Other taxes/Permit license fees | W37: =SUMIF($B$1:$B$495,U37,$Q$1:$Q$495) -> 1832.97 | X37: =SUMIF($B$1:$B$495,U37,$R$1:$R$495) -> 0
B38: 22 | C38: Office Supplies | D38: 150.64 | E38: 936.09 | F38: 288.48 | G38: 98.46 | H38: 0 | I38: 1253.31 | J38: 0 | K38: 0 | L38: 202.82 | M38: 171.75 | N38: 248.98 | O38: 276.02 | Q38: =SUM(D38:O38) -> 3626.55 | R38: =SUM(M38:O38)*4 -> 2787 | T38: 7 - Non Revenue Units | V38: Operating Expenses | W38: =SUM(W25:W37) -> 1169421.6 | X38: =SUM(X25:X37) -> 1698991.3
B39: 22 | C39: Copier Expense | D39: 0 | E39: 0 | F39: 0 | G39: 0 | H39: 0 | I39: 0 | J39: 0 | K39: 0 | L39: 0 | M39: 0 | N39: 0 | O39: 0 | Q39: =SUM(D39:O39) -> 0 | R39: =SUM(M39:O39)*4 -> 0 | T39: 8 - Utility Reimbursements
B40: 22 | C40: Postage | D40: 0 | E40: 0 | F40: 0 | G40: 0 | H40: 0 | I40: 0 | J40: 0 | K40: 0 | L40: 0 | M40: 0 | N40: 5927.81 | O40: 0 | Q40: =SUM(D40:O40) -> 5927.81 | R40: =SUM(M40:O40)*4 -> 23711.24 | T40: 9 - Other Reimbursements | V40: Net Operating Income (NOI) | W40: =W22-W38 -> -684903.82 | X40: =X22-X38 -> -953638.32
B41: 22 | C41: Internet & Phone | D41: 0 | E41: 0 | F41: 1324.22 | G41: 270.45 | H41: 2021.23 | I41: 561.3 | J41: 859.75 | K41: 930.34 | L41: 0 | M41: 124.37 | N41: 124.83 | O41: 1052.96 | Q41: =SUM(D41:O41) -> 7269.45 | R41: =SUM(M41:O41)*4 -> 5208.64 | T41: 10 - Other Income | U41: 25 | V41: Replacement Reserve | W41: =SUMIF($B$1:$B$495,U41,$Q$1:$Q$495) -> 0 | X41: =SUMIF($B$1:$B$495,U41,$R$1:$R$495) -> 0
B42: 22 | C42: Reimbursable Travel | D42: 0 | E42: 0 | F42: 0 | G42: 0 | H42: 0 | I42: 27.6 | J42: 14.05 | K42: 14.5 | L42: 13.25 | M42: 0 | N42: 35.25 | O42: 0 | Q42: =SUM(D42:O42) -> 104.65 | R42: =SUM(M42:O42)*4 -> 141 | T42: 11 - Repair & Maintenance | U42: 24 | V42: NOI as per T 12 | W42: =SUMIF($B$1:$B$495,U42,$Q$1:$Q$495) -> -684903.82 | X42: =SUMIF($B$1:$B$495,U42,$R$1:$R$495) -> -953638.32
B43: 18 | C43: Administrative Salaries | D43: 2897.06 | E43: 8675.79 | F43: 10308.78 | G43: 5761.72 | H43: 5761.72 | I43: 5761.72 | J43: 5738.91 | K43: 14267.02 | L43: 84.14 | M43: 5800 | N43: 12000 | O43: 5171.16 | Q43: =SUM(D43:O43) -> 82228.02 | R43: =SUM(M43:O43)*4 -> 91884.64 | T43: 12 - Cleaning & Decorating
B44: 20 | C44: Insurance Expense - All Risk; G/L | D44: 53714.27 | E44: 99932.85 | F44: -31450.88 | G44: 19243.1 | H44: 14123.18 | I44: 14123.18 | J44: 14123.18 | K44: 14123.16 | L44: -52220 | M44: 159619 | N44: 22570.41 | O44: 22570.41 | Q44: =SUM(D44:O44) -> 350471.86 | R44: =SUM(M44:O44)*4 -> 819039.28 | T44: 13 - Contract & Services
C45: Total Administrative Expense | D45: 56761.97 | E45: 109544.73 | F45: -19478.01 | G45: 25373.73 | H45: 21906.13 | I45: 21727.11 | J45: 20735.89 | K45: 29335.02 | L45: -51919.79 | M45: 165771.12 | N45: 41110.28 | O45: 29070.55 | Q45: =SUM(D45:O45) -> 449938.73 | R45: =SUM(M45:O45)*4 -> 943807.8 | T45: 14 - Utility- Electricity
C46: Advertising & Selling | Q46: =SUM(D46:O46) -> 0 | R46: =SUM(M46:O46)*4 -> 0 | T46: 15 - Utility- Water
B47: 17 | C47: Advertising & Selling - Other | D47: 5678 | E47: 6823 | F47: 17089 | G47: 13519.69 | H47: 7732 | I47: 10761.5 | J47: 15634.96 | K47: 8660.5 | L47: 11421.5 | M47: 13732 | N47: 11154.39 | O47: 11997.66 | Q47: =SUM(D47:O47) -> 134204.2 | R47: =SUM(M47:O47)*4 -> 147536.2 | T47: 16 - Utility- Others
B48: 17 | C48: Advertising | D48: 0 | E48: 0 | F48: 0 | G48: 0 | H48: 0 | I48: 0 | J48: 0 | K48: 0 | L48: 0 | M48: 0 | N48: 0 | O48: 0 | Q48: =SUM(D48:O48) -> 0 | R48: =SUM(M48:O48)*4 -> 0 | T48: 17 - Marketing
B49: 17 | C49: Tenant Relations | D49: 0 | E49: 0 | F49: 0 | G49: 0 | H49: 0 | I49: 5267.55 | J49: 464.36 | K49: 0 | L49: 14500 | M49: 0 | N49: 40 | O49: 56.56 | Q49: =SUM(D49:O49) -> 20328.47 | R49: =SUM(M49:O49)*4 -> 386.24 | T49: 18 - Payroll
C50: Total Advertising & Selling | D50: 5678 | E50: 6823 | F50: 17089 | G50: 13519.69 | H50: 7732 | I50: 16029.05 | J50: 16099.32 | K50: 8660.5 | L50: 25921.5 | M50: 13732 | N50: 11194.39 | O50: 12054.22 | Q50: =SUM(D50:O50) -> 154532.67 | R50: =SUM(M50:O50)*4 -> 147922.44 | T50: 19 - RE Taxes
C51: Professional Fees | Q51: =SUM(D51:O51) -> 0 | R51: =SUM(M51:O51)*4 -> 0 | T51: 20 - Insurance
B52: 21 | C52: Management Fees | D52: 2500 | E52: 2500 | F52: 2500 | G52: 2500 | H52: 2500 | I52: 2500 | J52: 2500 | K52: 2500 | L52: 2812.65 | M52: 2500 | N52: 2500 | O52: 2500 | Q52: =SUM(D52:O52) -> 30312.65 | R52: =SUM(M52:O52)*4 -> 30000 | T52: 21 - Property Mangement fees
B53: 22 | C53: Accounting Fees | D53: 0 | E53: 250.56 | F53: 5886.91 | G53: 133.53 | H53: 623.55 | I53: 125 | J53: 104.57 | K53: 490 | L53: -4192.4 | M53: 6875.12 | N53: 125 | O53: 366.7 | Q53: =SUM(D53:O53) -> 10788.54 | R53: =SUM(M53:O53)*4 -> 29467.28 | T53: 22 - General & Administrative Expenses
B54: 22 | C54: Legal Fees | D54: 0 | E54: 1877 | F54: 727.17 | G54: 0 | H54: 0 | I54: 0 | J54: 2400 | K54: 0 | L54: 0 | M54: 2600 | N54: 375 | O54: 1028 | Q54: =SUM(D54:O54) -> 9007.17 | R54: =SUM(M54:O54)*4 -> 16012 | T54: 23 - Other taxes/Permit license fees
B55: 22 | C55: Applicant Credit Check | D55: 73.79 | E55: 21.96 | F55: 142.33 | G55: 53.3 | H55: 39.77 | I55: 95.13 | J55: 159.1 | K55: 22.64 | L55: 215.49 | M55: 276.76 | N55: 35.1 | O55: 96.37 | Q55: =SUM(D55:O55) -> 1231.74 | R55: =SUM(M55:O55)*4 -> 1632.92 | T55: 24 - NOI
B56: 22 | C56: Bank Fees | D56: 42.59 | E56: 0 | F56: 0 | G56: 0 | H56: 0 | I56: 24.37 | J56: 0 | K56: 80.18 | L56: 15.18 | M56: 93.92 | N56: 55.22 | O56: 46.29 | Q56: =SUM(D56:O56) -> 357.75 | R56: =SUM(M56:O56)*4 -> 781.72 | T56: 1 - Market Rent Potential
B57: 22 | C57: Other Professional Fees | D57: 135 | E57: 0 | F57: 0 | G57: 0 | H57: 0 | I57: 0 | J57: 0 | K57: 0 | L57: 0 | M57: 0 | N57: 0 | O57: 0 | Q57: =SUM(D57:O57) -> 135 | R57: =SUM(M57:O57)*4 -> 0 | T57: 2 - Increase in Rent from Renovation
B58: 23 | C58: Licenses/Inspections/Certificates | D58: 0 | E58: 0 | F58: 1850 | G58: -231.25 | H58: 103.25 | I58: 110.97 | J58: 0 | K58: 0 | L58: 0 | M58: 0 | N58: 0 | O58: 0 | Q58: =SUM(D58:O58) -> 1832.97 | R58: =SUM(M58:O58)*4 -> 0 | T58: 3 - Loss to Lease
B59: 22 | C59: Angus Anywhere | D59: 0 | E59: 0 | F59: 0 | G59: 0 | H59: 0 | I59: 1813.93 | J59: 175.93 | K59: 175.93 | L59: 175.93 | M59: 175.93 | N59: 175.93 | O59: 175.93 | Q59: =SUM(D59:O59) -> 2869.51 | R59: =SUM(M59:O59)*4 -> 2111.16 | T59: 4 - Vacancy
B60: 22 | C60: ResMan | D60: 176.88 | E60: 176.88 | F60: 176.88 | G60: 176.88 | H60: 176.88 | I60: 176.88 | J60: 184.8 | K60: 184.8 | L60: 184.8 | M60: 184.8 | N60: 184.8 | O60: 184.8 | Q60: =SUM(D60:O60) -> 2170.08 | R60: =SUM(M60:O60)*4 -> 2217.6 | T60: 5 - Concession/Discount
B61: 22 | C61: Aptexx | D61: 51.48 | E61: 51.48 | F61: 51.48 | G61: 51.48 | H61: 102.96 | I61: 0 | J61: 51.48 | K61: 51.48 | L61: 51.48 | M61: 0 | N61: 51.48 | O61: 51.48 | Q61: =SUM(D61:O61) -> 566.28 | R61: =SUM(M61:O61)*4 -> 411.84 | T61: 6 - Bad Debt
C62: Total Professional Fees | D62: 2979.74 | E62: 4877.88 | F62: 11334.77 | G62: 2683.94 | H62: 3546.41 | I62: 4846.28 | J62: 5575.88 | K62: 3505.03 | L62: -736.87 | M62: 12706.53 | N62: 3502.53 | O62: 4449.57 | Q62: =SUM(D62:O62) -> 59271.69 | R62: =SUM(M62:O62)*4 -> 82634.52 | T62: 7 - Non Revenue Units
C63: Security & Life Safety | Q63: =SUM(D63:O63) -> 0 | R63: =SUM(M63:O63)*4 -> 0 | T63: 8 - Utility Reimbursements
B64: 13 | C64: Security & Life Safety - Other | D64: 0 | E64: 0 | F64: 255 | G64: 1815.64 | H64: 0 | I64: 810.41 | J64: 0 | K64: 0 | L64: 335.98 | M64: 0 | N64: 700 | O64: 0 | Q64: =SUM(D64:O64) -> 3917.03 | R64: =SUM(M64:O64)*4 -> 2800 | T64: 9 - Other Reimbursements
C65: Phone/Alarm Monitoring | D65: 0 | E65: 0 | F65: 0 | G65: 0 | H65: 0 | I65: 0 | J65: 0 | K65: 0 | L65: 0 | M65: 0 | N65: 0 | O65: 0 | Q65: =SUM(D65:O65) -> 0 | R65: =SUM(M65:O65)*4 -> 0 | T65: 10 - Other Income
C66: Fire Suppression | D66: 0 | E66: 0 | F66: 0 | G66: 0 | H66: 0 | I66: 0 | J66: 0 | K66: 0 | L66: 0 | M66: 0 | N66: 0 | O66: 0 | Q66: =SUM(D66:O66) -> 0 | R66: =SUM(M66:O66)*4 -> 0 | T66: 11 - Repair & Maintenance
B67: 13 | C67: Contract Security | D67: 0 | E67: 0 | F67: 1243.5 | G67: 0 | H67: 0 | I67: 0 | J67: 1237.5 | K67: 0 | L67: 0 | M67: 1237.5 | N67: 0 | O67: 0 | Q67: =SUM(D67:O67) -> 3718.5 | R67: =SUM(M67:O67)*4 -> 4950 | T67: 12 - Cleaning & Decorating
C68: Total Security & Life Safety | D68: 0 | E68: 0 | F68: 1498.5 | G68: 1815.64 | H68: 0 | I68: 810.41 | J68: 1237.5 | K68: 0 | L68: 335.98 | M68: 1237.5 | N68: 700 | O68: 0 | Q68: =SUM(D68:O68) -> 7635.53 | R68: =SUM(M68:O68)*4 -> 7750 | T68: 13 - Contract & Services
C69: Taxes | Q69: =SUM(D69:O69) -> 0 | R69: =SUM(M69:O69)*4 -> 0 | T69: 14 - Utility- Electricity
C70: Taxes - Other | D70: 0 | E70: 0 | F70: 0 | G70: 0 | H70: 0 | I70: 0 | J70: 0 | K70: 0 | L70: 0 | M70: 0 | N70: 0 | O70: 0 | Q70: =SUM(D70:O70) -> 0 | R70: =SUM(M70:O70)*4 -> 0 | T70: 15 - Utility- Water
C71: Total Taxes | D71: 0 | E71: 0 | F71: 0 | G71: 0 | H71: 0 | I71: 0 | J71: 0 | K71: 0 | L71: 0 | M71: 0 | N71: 0 | O71: 0 | Q71: =SUM(D71:O71) -> 0 | R71: =SUM(M71:O71)*4 -> 0 | T71: 16 - Utility- Others
C72: Building Maintenance | Q72: =SUM(D72:O72) -> 0 | R72: =SUM(M72:O72)*4 -> 0 | T72: 17 - Marketing
B73: 18 | C73: Labor - Employee Paymaster | D73: 0 | E73: 0 | F73: 0 | G73: 0 | H73: 0 | I73: 0 | J73: 0 | K73: 0 | L73: 0 | M73: 0 | N73: 0 | O73: 0 | Q73: =SUM(D73:O73) -> 0 | R73: =SUM(M73:O73)*4 -> 0 | T73: 18 - Payroll
B74: 18 | C74: Labor - Burden & Fringes | D74: 1650 | E74: 1391.44 | F74: 1860.83 | G74: 1449.86 | H74: 1449.86 | I74: 1449.86 | J74: 1449.86 | K74: 737.79 | L74: 653.65 | M74: 737.79 | N74: 737.79 | O74: 84.14 | Q74: =SUM(D74:O74) -> 13652.87 | R74: =SUM(M74:O74)*4 -> 6238.88 | T74: 19 - RE Taxes
B75: 11 | C75: Maintenance - Chargeback Exp. | D75: 2329.19 | E75: 6975.91 | F75: 6779.73 | G75: 4519.82 | H75: 4519.82 | I75: 4519.82 | J75: 4519.82 | K75: 6779.73 | L75: 4519.82 | M75: 4519.82 | N75: 4530.38 | O75: 4540.94 | Q75: =SUM(D75:O75) -> 59054.8 | R75: =SUM(M75:O75)*4 -> 54364.56 | T75: 20 - Insurance
B76: 11 | C76: Grounds Maintenance | D76: 0 | E76: 0 | F76: 0 | G76: 0 | H76: 20700 | I76: 6025 | J76: 6525 | K76: 6525 | L76: 6525 | M76: 6525 | N76: 6525 | O76: 2175 | Q76: =SUM(D76:O76) -> 61525 | R76: =SUM(M76:O76)*4 -> 60900 | T76: 21 - Property Mangement fees
B77: 11 | C77: Building Maintenance | D77: 1377.23 | E77: 1102.98 | F77: 10477.09 | G77: 5448.09 | H77: 6000 | I77: 10704.5 | J77: 461.24 | K77: 681.61 | L77: 5764.7 | M77: 0 | N77: 0 | O77: 10491.06 | Q77: =SUM(D77:O77) -> 52508.5 | R77: =SUM(M77:O77)*4 -> 41964.24 | T77: 22 - General & Administrative Expenses
B78: 11 | C78: Window Cleaning | D78: 0 | E78: 0 | F78: 0 | G78: 0 | H78: 0 | I78: 0 | J78: 0 | K78: 0 | L78: 0 | M78: 0 | N78: 0 | O78: 0 | Q78: =SUM(D78:O78) -> 0 | R78: =SUM(M78:O78)*4 -> 0 | T78: 23 - Other taxes/Permit license fees
B79: 11 | C79: Rubbish / Recycling | D79: 0 | E79: 0 | F79: 807.93 | G79: 872.37 | H79: 680.37 | I79: 703.64 | J79: 679.05 | K79: 1295.88 | L79: 520.58 | M79: 520.58 | N79: 520.58 | O79: 520.58 | Q79: =SUM(D79:O79) -> 7121.56 | R79: =SUM(M79:O79)*4 -> 6246.96 | T79: 24 - NOI
B80: 11 | C80: Plumbing Maintenance | D80: 0 | E80: 0 | F80: 0 | G80: 0 | H80: 0 | I80: 280 | J80: 0 | K80: 0 | L80: 0 | M80: 0 | N80: 6.43 | O80: 0 | Q80: =SUM(D80:O80) -> 286.43 | R80: =SUM(M80:O80)*4 -> 25.72 | T80: 1 - Market Rent Potential
B81: 11 | C81: Elevator Maintenance | D81: 0 | E81: 0 | F81: 0 | G81: 0 | H81: 0 | I81: 0 | J81: 0 | K81: 0 | L81: 0 | M81: 0 | N81: 0 | O81: 0 | Q81: =SUM(D81:O81) -> 0 | R81: =SUM(M81:O81)*4 -> 0 | T81: 2 - Increase in Rent from Renovation
B82: 11 | C82: HVAC Maintenance | D82: 0 | E82: 0 | F82: 0 | G82: 0 | H82: 0 | I82: 0 | J82: 0 | K82: 0 | L82: 0 | M82: 0 | N82: 0 | O82: 0 | Q82: =SUM(D82:O82) -> 0 | R82: =SUM(M82:O82)*4 -> 0 | T82: 3 - Loss to Lease
B83: 11 | C83: Door Expenses | D83: 0 | E83: 0 | F83: 0 | G83: 0 | H83: 0 | I83: 0 | J83: 0 | K83: 0 | L83: 0 | M83: 0 | N83: 0 | O83: 0 | Q83: =SUM(D83:O83) -> 0 | R83: =SUM(M83:O83)*4 -> 0 | T83: 4 - Vacancy
B84: 12 | C84: Interior Landscaping | D84: 0 | E84: 0 | F84: 3300 | G84: 0 | H84: -3300 | I84: 0 | J84: 0 | K84: 0 | L84: 0 | M84: 0 | N84: 0 | O84: 0 | Q84: =SUM(D84:O84) -> 0 | R84: =SUM(M84:O84)*4 -> 0 | T84: 5 - Concession/Discount
... B89: 13 | C89: Pest Control | D89: 0 | E89: 0 | F89: 1056 | G89: 1056 | H89: 0 | I89: 0 | J89: 3006 | K89: 0 | L89: 1056 | M89: 1056 | N89: 1056 | O89: -1056 | Q89: =SUM(D89:O89) -> 7230 | R89: =SUM(M89:O89)*4 -> 4224 | T89: 10 - Other Income
C90: Total Building Maintenance | D90: 5356.42 | E90: 11300.33 | F90: 24838.89 | G90: 13346.14 | H90: 30050.05 | I90: 24692.82 | J90: 16745.97 | K90: 17420.01 | L90: 22162.83 | M90: 17664.23 | N90: 14863.65 | O90: 20003.34 | Q90: =SUM(D90:O90) -> 218444.68 | R90: =SUM(M90:O90)*4 -> 210124.88 | T90: 11 - Repair & Maintenance
C91: Utilties Expense | Q91: =SUM(D91:O91) -> 0 | R91: =SUM(M91:O91)*4 -> 0 | T91: 12 - Cleaning & Decorating
B92: 14 | C92: Tenant Electric Expense | D92: 0 | E92: 0 | F92: 487 | G92: 0 | H92: 516.02 | I92: 547.07 | J92: 1721.34 | K92: 694.92 | L92: 1447.77 | M92: 1375.91 | N92: 1479.45 | O92: 1688.7 | Q92: =SUM(D92:O92) -> 9958.18 | R92: =SUM(M92:O92)*4 -> 18176.24 | T92: 13 - Contract & Services
B93: 15 | C93: Tenant Water/Sewer Expense | D93: 0 | E93: 0 | F93: 0 | G93: 0 | H93: 0 | I93: 0 | J93: 0 | K93: 2445 | L93: 5424.84 | M93: 9596.66 | N93: 5564.26 | O93: 7086.9 | Q93: =SUM(D93:O93) -> 30117.66 | R93: =SUM(M93:O93)*4 -> 88991.28 | T93: 14 - Utility- Electricity
B94: 16 | C94: Tenant Broadband Expense | D94: 0 | E94: 0 | F94: 468.27 | G94: 205.87 | H94: -674.14 | I94: 0 | J94: 0 | K94: 0 | L94: 0 | M94: 945.81 | N94: 0 | O94: 1308.04 | Q94: =SUM(D94:O94) -> 2253.85 | R94: =SUM(M94:O94)*4 -> 9015.4 | T94: 15 - Utility- Water
B95: 16 | C95: Utilities - Nonbillable/Vacant | D95: 38693.33 | E95: 0 | F95: 0 | G95: -38693.33 | H95: 0 | I95: 0 | J95: 0 | K95: 0 | L95: 0 | M95: 0 | N95: 0 | O95: 0 | Q95: =SUM(D95:O95) -> 0 | R95: =SUM(M95:O95)*4 -> 0 | T95: 16 - Utility- Others
B96: 14 | C96: Electric Expense NB - Vacant | D96: 3712.54 | E96: 5183.81 | F96: 4239.4 | G96: 4607.17 | H96: 2283.05 | I96: 2073.71 | J96: 3038.55 | K96: 2630.56 | L96: 2894.99 | M96: 2502.36 | N96: 1927.82 | O96: 694.79 | Q96: =SUM(D96:O96) -> 35788.75 | R96: =SUM(M96:O96)*4 -> 20499.88 | T96: 17 - Marketing
B97: 15 | C97: Water/Sewer NB - Vacant | D97: 0 | E97: 0 | F97: 0 | G97: 0 | H97: 0 | I97: 0 | J97: 632.87 | K97: 48296.64 | L97: 0 | M97: 0 | N97: 0 | O97: 0 | Q97: =SUM(D97:O97) -> 48929.51 | R97: =SUM(M97:O97)*4 -> 0 | T97: 18 - Payroll
B98: 14 | C98: Electric - Common Area | D98: 0 | E98: 0 | F98: 0 | G98: 0 | H98: 6195.94 | I98: 2401.85 | J98: 4045.03 | K98: 3878.44 | L98: 2181.85 | M98: 2893.34 | N98: 5089.48 | O98: 1306.07 | Q98: =SUM(D98:O98) -> 27992 | R98: =SUM(M98:O98)*4 -> 37155.56 | T98: 19 - RE Taxes
B99: 15 | C99: Water/Sewer Common Area | D99: 16.83 | E99: 0 | F99: 0 | G99: 0 | H99: 285.42 | I99: 359.63 | J99: 225 | K99: 0 | L99: 15.15 | M99: 0 | N99: 0 | O99: 48.43 | Q99: =SUM(D99:O99) -> 950.46 | R99: =SUM(M99:O99)*4 -> 193.72 | T99: 20 - Insurance
B100: 16 | C100: Broadband/Phone Common Area | D100: 0 | E100: 0 | F100: 0 | G100: 528.18 | H100: -528.18 | I100: 248.98 | J100: 249 | K100: 772 | L100: 246.51 | M100: 1544.26 | N100: 1072.26 | O100: 926.23 | Q100: =SUM(D100:O100) -> 5059.24 | R100: =SUM(M100:O100)*4 -> 14171 | T100: 21 - Property Mangement fees
C101: Total Utilties Expense | D101: 42422.7 | E101: 5183.81 | F101: 5194.67 | G101: -33352.11 | H101: 8078.11 | I101: 5631.24 | J101: 9911.79 | K101: 58717.56 | L101: 12211.11 | M101: 18858.34 | N101: 15133.27 | O101: 13059.16 | Q101: =SUM(D101:O101) -> 161049.65 | R101: =SUM(M101:O101)*4 -> 188203.08 | T101: 22 - General & Administrative Expenses
C102: TOTAL EXPENSE | D102: 113198.83 | E102: 137729.75 | F102: 40477.82 | G102: 23387.03 | H102: 71312.7 | I102: 73736.91 | J102: 70306.35 | K102: 117638.12 | L102: 7974.76 | M102: 229969.72 | N102: 86504.12 | O102: 78636.84 | Q102: =SUM(D102:O102) -> 1050872.9 | R102: =SUM(M102:O102)*4 -> 1580442.7 | T102: 23 - Other taxes/Permit license fees
C103: NET OPERATING INCOME | D103: -109859.83 | E103: -112636.75 | F103: -14560.82 | G103: 7051.97 | H103: -38575.2 | I103: -39113.41 | J103: -33934.35 | K103: -64232.62 | L103: 48278.24 | M103: -165336.72 | N103: -24974.37 | O103: -18461.34 | Q103: =SUM(D103:O103) -> -566355.2 | R103: =SUM(M103:O103)*4 -> -835089.72 | T103: 24 - NOI
Q104: =SUM(D104:O104) -> 0 | R104: =SUM(M104:O104)*4 -> 0 | T104: 1 - Market Rent Potential
B105: 19 | C105: Real Estate Tax Expense | D105: 3601.29 | E105: 3601.29 | F105: 3601.29 | G105: 3601.29 | H105: 3601.29 | I105: 3601.29 | J105: 47545.63 | K105: 9879.05 | L105: 9879.05 | M105: 9879.05 | N105: 9879.05 | O105: 9879.05 | Q105: =SUM(D105:O105) -> 118548.62 | R105: =SUM(M105:O105)*4 -> 118548.6 | T105: 2 - Increase in Rent from Renovation
Q106: =SUM(D106:O106) -> 0 | R106: =SUM(M106:O106)*4 -> 0 | T106: 3 - Loss to Lease
...

Sheet Rent Comp
A1: Property Id | B1: Map # | C1: Building Name | D1: Link to Website | E1: Address | F1: Rating | G1: Apartments.com Ad Level | H1: Common View Last 60 Days | I1: % Overlap with Subject Property | J1: Units | K1: Stories | L1: Yr Blt/Ren | M1: Avg SF | N1: mi Away | O1: Rent/SF | P1: Rent/Unit | Q1: Studio | R1: 1 bed | S1: SqFt | T1: Rent psf | U1: 2 Beds | V1: SqFt | W1: Rent psf | X1: 2 Beds-Ranch | Y1: SqFt | Z1: Rent psf | AA1: Occ % | AB1: Concess % | AE1: #3 Beds | AF1: Neighborhood
C6: Subject Property | O6: Actual rents from Rent Roll
C7: ='CFS-Main Page'!B2 -> Calabash Shores | D7: Link | E7: ='CFS-Main Page'!D2 -> 660 Aubrey Ln Calabash, NC, 28467 | J7: =Units -> 132 | L7: ='CFS-Main Page'!D4 -> 2024 | O7: =Rent!J31 -> 1.9659815 | P7: =Rent!J30 -> 1963.5985 | R7: =Rent!G5 -> 1568.64 | S7: =AVERAGE(Rent!I9:I10) -> 745 | T7: =R7/S7 -> 2.105557 | U7: =Rent!I5 -> 2441.5258 | V7: =AVERAGE(Rent!I11:I14,Rent!I17) -> 1068.6 | W7: =U7/V7 -> 2.2847892 | X7: =Rent!K5 -> 0 | Y7: =AVERAGE(Rent!I15:I16) -> 1179.5 | Z7: =X7/Y7 -> 0 | AA7: =Rent!H29 -> 0.28030303
C9: Comps
A10: 1 | C10: River Rock at Shingletree | D10: Link | E10: 31 Quaker Ridge Drive Carolina Shores, NC 28467 | J10: 136 | L10: 2024 | N10: 2.14 | T10: =R10/S10 -> #DIV/0! | U10: 1954 | V10: 1376 | W10: =U10/V10 -> 1.4200581 | X10: 1990 | Y10: 1376 | Z10: =X10/Y10 -> 1.4462209 | AA10: 0.632
A11: =A10+1 -> 2 | C11: Egret Landing | D11: Link | E11: 3021 Siskin Drive Northwest Calabash, NC 28467 | J11: 198 | L11: 2024 | N11: 2.24 | T11: =R11/S11 -> #DIV/0! | U11: 2223 | V11: 1311 | W11: =U11/V11 -> 1.6956522 | X11: 1850 | Y11: 1310 | Z11: =X11/Y11 -> 1.4122137 | AA11: 0.732
A12: =A11+1 -> 3 | C12: River Oaks | D12: Link | E12: 119 River Village Drive Little River, SC 29566 | J12: 190 | L12: 2018 | N12: 2.44 | T12: =R12/S12 -> #DIV/0! | U12: 1733 | V12: 1147 | W12: =U12/V12 -> 1.510898 | X12: 2238 | Y12: 1140 | Z12: =X12/Y12 -> 1.9631579 | AA12: 0.958
A13: =A12+1 -> 4 | C13: Heartsease at Calabash | D13: Link | E13: 1035 Brightwater Way Calabash, NC 28467 | J13: 158 | L13: 2024 | N13: 0.73 | R13: 1762 | S13: 1161 | T13: =R13/S13 -> 1.5176572 | U13: 1850 | V13: 1366 | W13: =U13/V13 -> 1.3543192 | X13: 2175 | Y13: 1440 | Z13: =X13/Y13 -> 1.5104167 | AA13: 0.956
A14: 5 | C14: Heartsease at Ocean Isle Beach | D14: Link | E14: 1956 Sparrowstar Way Ocean Isle Beach, NC 28469 | J14: 136 | L14: 2025 | N14: 4.93 | R14: 1530 | S14: 929 | T14: =R14/S14 -> 1.6469322 | U14: 1672 | V14: 1343 | W14: =U14/V14 -> 1.2449739 | AA14: 0.868
Q28: Studio | R28: 1 Beds | S28: Sqft | T28: PSF | U28: 2 Beds | V28: Sqft | W28: PSF | X28: 3 Beds | Y28: Sqft | Z28: PSF
M29: A. | N29: Avg Rent of Comps | Q29: =AVERAGE(Q10:Q26) -> #DIV/0! | R29: =AVERAGE(R10:R26) -> 1646 | S29: =AVERAGE(S10:S26) -> 1045 | T29: =AVERAGE(T10:T26) -> #DIV/0! | U29: =AVERAGE(U10:U26) -> 1886.4 | V29: =AVERAGE(V10:V26) -> 1308.6 | W29: =AVERAGE(W10:W26) -> 1.4451803 | X29: =AVERAGE(X10:X26) -> 2063.25 | ... Z29: =AVERAGE(Z10:Z26) -> 1.5830023
M30: B. | N30: Subject Prop Rent | Q30: =Q7 -> 0 | R30: =R7 -> 1568.64 | S30: =S7 -> 745 | T30: =T7 -> 2.105557 | U30: =U7 -> 2441.5258 | V30: =V7 -> 1068.6 | W30: =W7 -> 2.2847892 | X30: =X7 -> 0 | ... Z30: =Z7 -> 0
M32: C. | N32: C=A-B | Q32: =Q29-Q30 -> #DIV/0! | R32: =R29-R30 -> 77.36 | T32: =T29-T30 -> #DIV/0! | U32: =U29-U30 -> -555.12577 | W32: =W29-W30 -> -0.83960894 | X32: =X29-X30 -> 2063.25 | Z32: =Z29-Z30 -> 1.5830023
M33: *Source - Hello Data

Sheet Quick Comps
B1: Comp 1 | I1: Comp 2 | P1: Comp 3 | W1: Comp 4 | AD1: Comp 5 | AK1: Comp 6
B2: Units | D2: PIN/Parcel ID | I2: Units | K2: PIN/Parcel ID | P2: Units | R2: PIN/Parcel ID | W2: Units | Y2: PIN/Parcel ID | AD2: Units | AF2: PIN/Parcel ID | AK2: Units | AM2: PIN/Parcel ID
B3: Built in: | D3: Last Sales Date | I3: Built in: | K3: Last Sales Date | P3: Built in: | R3: Last Sales Date | W3: Built in: | Y3: Last Sales Date | AD3: Built in: | AF3: Last Sales Date | AK3: Built in: | AM3: Last Sales Date
B4: Managed By: | D4: Price / Unit | I4: Managed By: | K4: Price / Unit | P4: Managed By: | R4: Price / | W4: Managed By: | Y4: Price / | AD4: Managed By: | AF4: Price / | AK4: Managed By: | AM4: Price / Unit
B5: Rent Survey Date: | D5: Year Assessed | F5: Per Unit | I5: Rent Survey Date: | K5: Year Assessed | M5: Per Unit | P5: Rent Survey Date: | R5: Year Assessed | T5: Per Unit | W5: Rent Survey Date: | Y5: Year Assessed | AA5: Per Unit | AD5: Rent Survey Date: | AF5: Year Assessed | AH5: Per Unit | AK5: Rent Survey Date: | AM5: Year Assessed | AO5: Per Unit
B6: Occupancy: | D6: Land | F6: =E6/C2 -> #DIV/0! | I6: Occupancy: | K6: Land | M6: =L6/J2 -> #DIV/0! | P6: Occupancy: | R6: Land | T6: =S6/Q2 -> #DIV/0! | W6: Occupancy: | Y6: Land | AA6: =Z6/X2 -> #DIV/0! | AD6: Occupancy: | AF6: Land | AH6: =AG6/AE2 -> #DIV/0! | AK6: Occupancy: | AM6: Land | AO6: =AN6/AL2 -> #DIV/0!
B7: Last Rent Increase: | D7: Improvements | F7: =E7/C2 -> #DIV/0! | I7: Last Rent Increase: | K7: Improvements | M7: =L7/J2 -> #DIV/0! | P7: Last Rent Increase: | R7: Improvements | T7: =S7/Q2 -> #DIV/0! | W7: Last Rent Increase: | Y7: Improvements | AA7: =Z7/X2 -> #DIV/0! | AD7: Last Rent Increase: | AF7: Improvements | AH7: =AG7/AE2 -> #DIV/0! | AK7: Last Rent Increase: | AM7: Improvements | AO7: =AN7/AL2 -> #DIV/0!
B8: Concessions? | D8: Total | E8: =SUM(E6:E7) -> 0 | F8: =SUM(F6:F7) -> #DIV/0! | I8: Concessions? | K8: Total | L8: =SUM(L6:L7) -> 0 | M8: =SUM(M6:M7) -> #DIV/0! | P8: Concessions? | R8: Total | S8: =SUM(S6:S7) -> 0 | T8: =SUM(T6:T7) -> #DIV/0! | W8: Concessions? | Y8: Total | Z8: =SUM(Z6:Z7) -> 0 | AA8: =SUM(AA6:AA7) -> #DIV/0! | AD8: Concessions? | AF8: Total | AG8: =SUM(AG6:AG7) -> 0 | AH8: =SUM(AH6:AH7) -> #DIV/0! | AK8: Concessions? | AM8: Total | AN8: =SUM(AN6:AN7) -> 0 | AO8: =SUM(AO6:AO7) -> #DIV/0!
B9: Income Restricted? | D9: Tax District | I9: Income Restricted? | K9: Tax District | P9: Income Restricted? | R9: Tax District | W9: Income Restricted? | Y9: Tax District | AD9: Income Restricted? | AF9: Tax District | AK9: Income Restricted? | AM9: Tax District
B10: Tax Credit? | D10: Zoning | I10: Tax Credit? | K10: Zoning | P10: Tax Credit? | R10: Zoning | W10: Tax Credit? | Y10: Zoning | AD10: Tax Credit? | AF10: Zoning | AK10: Tax Credit? | AM10: Zoning
B11: Building Style | D11: Acres | I11: Building Style | K11: Acres | P11: Building Style | R11: Acres | W11: Building Style | Y11: Acres | AD11: Building Style | AF11: Acres | AK11: Building Style | AM11: Acres
B12: Distance from Subject | C12: 0 | D12: Density | E12: =IFERROR(C2/E11,0) -> 0 | I12: Distance from Subject | K12: Density | L12: =IFERROR(J2/L11,0) -> 0 | P12: Distance from Subject | R12: Density | S12: =IFERROR(Q2/S11,0) -> 0 | W12: Distance from Subject | Y12: Density | Z12: =IFERROR(X2/Z11,0) -> 0 | AD12: Distance from Subject | AF12: Density | AG12: =IFERROR(AE2/AG11,0) -> 0 | AK12: Distance from Subject | AM12: Density | AN12: =IFERROR(AL2/AN11,0) -> 0
B14: Studio | I14: Studio | P14: Studio | W14: Studio | AD14: Studio | AK14: Studio
B15: Unit Type | C15: Units | D15: Square Feet | E15: Base Rent | F15: PSF | G15: % of Mix | I15: Unit Type | J15: Units | K15: Square Feet | L15: Base Rent | M15: PSF | N15: % of Mix | P15: Unit Type | Q15: Units | R15: Square Feet | S15: Base Rent | T15: PSF | U15: % of Mix | W15: Unit Type | X15: Units | Y15: Square Feet | Z15: Base Rent | AA15: PSF | AB15: % of Mix | AD15: Unit Type | AE15: Units | AF15: Square Feet | AG15: Base Rent | AH15: PSF | AI15: % of Mix | AK15: Unit Type | AL15: Units | AM15: Square Feet | AN15: Base Rent | AO15: PSF | AP15: % of Mix
B16: 0x1 | F16: =IFERROR(E16/D16,0) -> 0 | G16: =C16/$C$2 -> #DIV/0! | M16: =IFERROR(L16/K16,0) -> 0 | N16: =J16/J$2 -> #DIV/0! | T16: =IFERROR(S16/R16,0) -> 0 | U16: =Q16/Q$2 -> #DIV/0! | AA16: =IFERROR(Z16/Y16,0) -> 0 | AB16: =X16/X$2 -> #DIV/0! | AH16: =IFERROR(AG16/AF16,0) -> 0 | AI16: =AE16/AE$2 -> #DIV/0! | AO16: =IFERROR(AN16/AM16,0) -> 0 | AP16: =AL16/AL$2 -> #DIV/0!
B17: 0x1 | F17: =IFERROR(E17/D17,0) -> 0 | G17: =C17/$C$2 -> #DIV/0! | M17: =IFERROR(L17/K17,0) -> 0 | N17: =J17/J$2 -> #DIV/0! | T17: =IFERROR(S17/R17,0) -> 0 | U17: =Q17/Q$2 -> #DIV/0! | AA17: =IFERROR(Z17/Y17,0) -> 0 | AB17: =X17/X$2 -> #DIV/0! | AH17: =IFERROR(AG17/AF17,0) -> 0 | AI17: =AE17/AE$2 -> #DIV/0! | AO17: =IFERROR(AN17/AM17,0) -> 0 | AP17: =AL17/AL$2 -> #DIV/0!
B18: 0x1 | F18: =IFERROR(E18/D18,0) -> 0 | G18: =C18/$C$2 -> #DIV/0! | M18: =IFERROR(L18/K18,0) -> 0 | N18: =J18/J$2 -> #DIV/0! | T18: =IFERROR(S18/R18,0) -> 0 | U18: =Q18/Q$2 -> #DIV/0! | AA18: =IFERROR(Z18/Y18,0) -> 0 | AB18: =X18/X$2 -> #DIV/0! | AH18: =IFERROR(AG18/AF18,0) -> 0 | AI18: =AE18/AE$2 -> #DIV/0! | AO18: =IFERROR(AN18/AM18,0) -> 0 | AP18: =AL18/AL$2 -> #DIV/0!
B19: 0x1 | F19: =IFERROR(E19/D19,0) -> 0 | G19: =C19/$C$2 -> #DIV/0! | M19: =IFERROR(L19/K19,0) -> 0 | N19: =J19/J$2 -> #DIV/0! | T19: =IFERROR(S19/R19,0) -> 0 | U19: =Q19/Q$2 -> #DIV/0! | AA19: =IFERROR(Z19/Y19,0) -> 0 | AB19: =X19/X$2 -> #DIV/0! | AH19: =IFERROR(AG19/AF19,0) -> 0 | AI19: =AE19/AE$2 -> #DIV/0! | AO19: =IFERROR(AN19/AM19,0) -> 0 | AP19: =AL19/AL$2 -> #DIV/0!
B20: 0x1 | F20: =IFERROR(E20/D20,0) -> 0 | G20: =C20/$C$2 -> #DIV/0! | M20: =IFERROR(L20/K20,0) -> 0 | N20: =J20/J$2 -> #DIV/0! | T20: =IFERROR(S20/R20,0) -> 0 | U20: =Q20/Q$2 -> #DIV/0! | AA20: =IFERROR(Z20/Y20,0) -> 0 | AB20: =X20/X$2 -> #DIV/0! | AH20: =IFERROR(AG20/AF20,0) -> 0 | AI20: =AE20/AE$2 -> #DIV/0! | AO20: =IFERROR(AN20/AM20,0) -> 0 | AP20: =AL20/AL$2 -> #DIV/0!
B21: 0x1 | F21: =IFERROR(E21/D21,0) -> 0 | G21: =C21/$C$2 -> #DIV/0! | M21: =IFERROR(L21/K21,0) -> 0 | N21: =J21/J$2 -> #DIV/0! | T21: =IFERROR(S21/R21,0) -> 0 | U21: =Q21/Q$2 -> #DIV/0! | AA21: =IFERROR(Z21/Y21,0) -> 0 | AB21: =X21/X$2 -> #DIV/0! | AH21: =IFERROR(AG21/AF21,0) -> 0 | AI21: =AE21/AE$2 -> #DIV/0! | AO21: =IFERROR(AN21/AM21,0) -> 0 | AP21: =AL21/AL$2 -> #DIV/0!
B22: 0x1 | F22: =IFERROR(E22/D22,0) -> 0 | G22: =C22/$C$2 -> #DIV/0! | M22: =IFERROR(L22/K22,0) -> 0 | N22: =J22/J$2 -> #DIV/0! | T22: =IFERROR(S22/R22,0) -> 0 | U22: =Q22/Q$2 -> #DIV/0! | AA22: =IFERROR(Z22/Y22,0) -> 0 | AB22: =X22/X$2 -> #DIV/0! | AH22: =IFERROR(AG22/AF22,0) -> 0 | AI22: =AE22/AE$2 -> #DIV/0! | AO22: =IFERROR(AN22/AM22,0) -> 0 | AP22: =AL22/AL$2 -> #DIV/0!
B23: 0x1 | F23: =IFERROR(E23/D23,0) -> 0 | G23: =C23/$C$2 -> #DIV/0! | M23: =IFERROR(L23/K23,0) -> 0 | N23: =J23/J$2 -> #DIV/0! | T23: =IFERROR(S23/R23,0) -> 0 | U23: =Q23/Q$2 -> #DIV/0! | AA23: =IFERROR(Z23/Y23,0) -> 0 | AB23: =X23/X$2 -> #DIV/0! | AH23: =IFERROR(AG23/AF23,0) -> 0 | AI23: =AE23/AE$2 -> #DIV/0! | AO23: =IFERROR(AN23/AM23,0) -> 0 | AP23: =AL23/AL$2 -> #DIV/0!
B24: 0x1 | F24: =IFERROR(E24/D24,0) -> 0 | G24: =C24/$C$2 -> #DIV/0! | M24: =IFERROR(L24/K24,0) -> 0 | N24: =J24/J$2 -> #DIV/0! | T24: =IFERROR(S24/R24,0) -> 0 | U24: =Q24/Q$2 -> #DIV/0! | AA24: =IFERROR(Z24/Y24,0) -> 0 | AB24: =X24/X$2 -> #DIV/0! | AH24: =IFERROR(AG24/AF24,0) -> 0 | AI24: =AE24/AE$2 -> #DIV/0! | AO24: =IFERROR(AN24/AM24,0) -> 0 | AP24: =AL24/AL$2 -> #DIV/0!
B25: 0x1 | F25: =IFERROR(E25/D25,0) -> 0 | G25: =C25/$C$2 -> #DIV/0! | M25: =IFERROR(L25/K25,0) -> 0 | N25: =J25/J$2 -> #DIV/0! | T25: =IFERROR(S25/R25,0) -> 0 | U25: =Q25/Q$2 -> #DIV/0! | AA25: =IFERROR(Z25/Y25,0) -> 0 | AB25: =X25/X$2 -> #DIV/0! | AH25: =IFERROR(AG25/AF25,0) -> 0 | AI25: =AE25/AE$2 -> #DIV/0! | AO25: =IFERROR(AN25/AM25,0) -> 0 | AP25: =AL25/AL$2 -> #DIV/0!
B26: 0x1 | F26: =IFERROR(E26/D26,0) -> 0 | G26: =C26/$C$2 -> #DIV/0! | M26: =IFERROR(L26/K26,0) -> 0 | N26: =J26/J$2 -> #DIV/0! | T26: =IFERROR(S26/R26,0) -> 0 | U26: =Q26/Q$2 -> #DIV/0! | AA26: =IFERROR(Z26/Y26,0) -> 0 | AB26: =X26/X$2 -> #DIV/0! | AH26: =IFERROR(AG26/AF26,0) -> 0 | AI26: =AE26/AE$2 -> #DIV/0! | AO26: =IFERROR(AN26/AM26,0) -> 0 | AP26: =AL26/AL$2 -> #DIV/0!
B27: 0x1 | F27: =IFERROR(E27/D27,0) -> 0 | G27: =C27/$C$2 -> #DIV/0! | M27: =IFERROR(L27/K27,0) -> 0 | N27: =J27/J$2 -> #DIV/0! | T27: =IFERROR(S27/R27,0) -> 0 | U27: =Q27/Q$2 -> #DIV/0! | AA27: =IFERROR(Z27/Y27,0) -> 0 | AB27: =X27/X$2 -> #DIV/0! | AH27: =IFERROR(AG27/AF27,0) -> 0 | AI27: =AE27/AE$2 -> #DIV/0! | AO27: =IFERROR(AN27/AM27,0) -> 0 | AP27: =AL27/AL$2 -> #DIV/0!
B28: Total | C28: =SUBTOTAL(9,C16:C27) -> 0 | D28: =SUMPRODUCT(D16:D27,C16:C27) -> 0 | E28: =SUMPRODUCT(E16:E27,C16:C27) -> 0 | F28: =IFERROR(E28/D28,0) -> 0 | I28: Total | J28: =SUBTOTAL(9,J16:J27) -> 0 | K28: =SUMPRODUCT(K16:K27,J16:J27) -> 0 | L28: =SUMPRODUCT(L16:L27,J16:J27) -> 0 | M28: =IFERROR(L28/K28,0) -> 0 | P28: Total | Q28: =SUBTOTAL(9,Q16:Q27) -> 0 | R28: =SUMPRODUCT(R16:R27,Q16:Q27) -> 0 | S28: =SUMPRODUCT(S16:S27,Q16:Q27) -> 0 | T28: =IFERROR(S28/R28,0) -> 0 | W28: Total | X28: =SUBTOTAL(9,X16:X27) -> 0 | Y28: =SUMPRODUCT(Y16:Y27,X16:X27) -> 0 | Z28: =SUMPRODUCT(Z16:Z27,X16:X27) -> 0 | AA28: =IFERROR(Z28/Y28,0) -> 0 | AD28: Total | AE28: =SUBTOTAL(9,AE16:AE27) -> 0 | AF28: =SUMPRODUCT(AF16:AF27,AE16:AE27) -> 0 | AG28: =SUMPRODUCT(AG16:AG27,AE16:AE27) -> 0 | AH28: =IFERROR(AG28/AF28,0) -> 0 | AK28: Total | AL28: =SUBTOTAL(9,AL16:AL27) -> 0 | AM28: =SUMPRODUCT(AM16:AM27,AL16:AL27) -> 0 | AN28: =SUMPRODUCT(AN16:AN27,AL16:AL27) -> 0 | AO28: =IFERROR(AN28/AM28,0) -> 0
B29: Average | D29: =IFERROR(D28/C28,0) -> 0 | E29: =IFERROR(E28/C28,0) -> 0 | F29: =IFERROR(E29/D29,0) -> 0 | I29: Average | K29: =IFERROR(K28/J28,0) -> 0 | L29: =IFERROR(L28/J28,0) -> 0 | M29: =IFERROR(L29/K29,0) -> 0 | P29: Average | R29: =IFERROR(R28/Q28,0) -> 0 | S29: =IFERROR(S28/Q28,0) -> 0 | T29: =IFERROR(S29/R29,0) -> 0 | W29: Average | Y29: =IFERROR(Y28/X28,0) -> 0 | Z29: =IFERROR(Z28/X28,0) -> 0 | AA29: =IFERROR(Z29/Y29,0) -> 0 | AD29: Average | AF29: =IFERROR(AF28/AE28,0) -> 0 | AG29: =IFERROR(AG28/AE28,0) -> 0 | AH29: =IFERROR(AG29/AF29,0) -> 0 | AK29: Average | AM29: =IFERROR(AM28/AL28,0) -> 0 | AN29: =IFERROR(AN28/AL28,0) -> 0 | AO29: =IFERROR(AN29/AM29,0) -> 0
A31: Proforma | B31: One Bedroom | I31: One Bedroom | P31: One Bedroom | W31: One Bedroom | AD31: One Bedroom | AK31: One Bedroom
B32: Unit Type | C32: Units | D32: Square Feet | E32: Base Rent | F32: PSF | G32: % of Mix | I32: Unit Type | J32: Units | K32: Square Feet | L32: Base Rent | M32: PSF | N32: % of Mix | P32: Unit Type | Q32: Units | R32: Square Feet | S32: Base Rent | T32: PSF | U32: % of Mix | W32: Unit Type | X32: Units | Y32: Square Feet | Z32: Base Rent | AA32: PSF | AB32: % of Mix | AD32: Unit Type | AE32: Units | AF32: Square Feet | AG32: Base Rent | AH32: PSF | AI32: % of Mix | AK32: Unit Type | AL32: Units | AM32: Square Feet | AN32: Base Rent | AO32: PSF | AP32: % of Mix
B33: 1x1 | F33: =IFERROR(E33/D33,0) -> 0 | G33: =C33/$C$2 -> #DIV/0! | M33: =IFERROR(L33/K33,0) -> 0 | N33: =J33/J$2 -> #DIV/0! | T33: =IFERROR(S33/R33,0) -> 0 | U33: =Q33/Q$2 -> #DIV/0! | AA33: =IFERROR(Z33/Y33,0) -> 0 | AB33: =X33/X$2 -> #DIV/0! | AH33: =IFERROR(AG33/AF33,0) -> 0 | AI33: =AE33/AE$2 -> #DIV/0! | AO33: =IFERROR(AN33/AM33,0) -> 0 | AP33: =AL33/AL$2 -> #DIV/0!
B34: 1x1 | F34: =IFERROR(E34/D34,0) -> 0 | G34: =C34/$C$2 -> #DIV/0! | M34: =IFERROR(L34/K34,0) -> 0 | N34: =J34/J$2 -> #DIV/0! | T34: =IFERROR(S34/R34,0) -> 0 | U34: =Q34/Q$2 -> #DIV/0! | AA34: =IFERROR(Z34/Y34,0) -> 0 | AB34: =X34/X$2 -> #DIV/0! | AH34: =IFERROR(AG34/AF34,0) -> 0 | AI34: =AE34/AE$2 -> #DIV/0! | AO34: =IFERROR(AN34/AM34,0) -> 0 | AP34: =AL34/AL$2 -> #DIV/0!
B35: 1x1 | F35: =IFERROR(E35/D35,0) -> 0 | G35: =C35/$C$2 -> #DIV/0! | M35: =IFERROR(L35/K35,0) -> 0 | N35: =J35/J$2 -> #DIV/0! | T35: =IFERROR(S35/R35,0) -> 0 | U35: =Q35/Q$2 -> #DIV/0! | AA35: =IFERROR(Z35/Y35,0) -> 0 | AB35: =X35/X$2 -> #DIV/0! | AH35: =IFERROR(AG35/AF35,0) -> 0 | AI35: =AE35/AE$2 -> #DIV/0! | AO35: =IFERROR(AN35/AM35,0) -> 0 | AP35: =AL35/AL$2 -> #DIV/0!
B36: 1x1 | F36: =IFERROR(E36/D36,0) -> 0 | G36: =C36/$C$2 -> #DIV/0! | M36: =IFERROR(L36/K36,0) -> 0 | N36: =J36/J$2 -> #DIV/0! | T36: =IFERROR(S36/R36,0) -> 0 | U36: =Q36/Q$2 -> #DIV/0! | AA36: =IFERROR(Z36/Y36,0) -> 0 | AB36: =X36/X$2 -> #DIV/0! | AH36: =IFERROR(AG36/AF36,0) -> 0 | AI36: =AE36/AE$2 -> #DIV/0! | AO36: =IFERROR(AN36/AM36,0) -> 0 | AP36: =AL36/AL$2 -> #DIV/0!
B37: 1x1 | F37: =IFERROR(E37/D37,0) -> 0 | G37: =C37/$C$2 -> #DIV/0! | M37: =IFERROR(L37/K37,0) -> 0 | N37: =J37/J$2 -> #DIV/0! | T37: =IFERROR(S37/R37,0) -> 0 | U37: =Q37/Q$2 -> #DIV/0! | AA37: =IFERROR(Z37/Y37,0) -> 0 | AB37: =X37/X$2 -> #DIV/0! | AH37: =IFERROR(AG37/AF37,0) -> 0 | AI37: =AE37/AE$2 -> #DIV/0! | AO37: =IFERROR(AN37/AM37,0) -> 0 | AP37: =AL37/AL$2 -> #DIV/0!
B38: 1x1 | F38: =IFERROR(E38/D38,0) -> 0 | G38: =C38/$C$2 -> #DIV/0! | M38: =IFERROR(L38/K38,0) -> 0 | N38: =J38/J$2 -> #DIV/0! | T38: =IFERROR(S38/R38,0) -> 0 | U38: =Q38/Q$2 -> #DIV/0! | AA38: =IFERROR(Z38/Y38,0) -> 0 | AB38: =X38/X$2 -> #DIV/0! | AH38: =IFERROR(AG38/AF38,0) -> 0 | AI38: =AE38/AE$2 -> #DIV/0! | AO38: =IFERROR(AN38/AM38,0) -> 0 | AP38: =AL38/AL$2 -> #DIV/0!
B39: 1x1 | F39: =IFERROR(E39/D39,0) -> 0 | G39: =C39/$C$2 -> #DIV/0! | M39: =IFERROR(L39/K39,0) -> 0 | N39: =J39/J$2 -> #DIV/0! | T39: =IFERROR(S39/R39,0) -> 0 | U39: =Q39/Q$2 -> #DIV/0! | AA39: =IFERROR(Z39/Y39,0) -> 0 | AB39: =X39/X$2 -> #DIV/0! | AH39: =IFERROR(AG39/AF39,0) -> 0 | AI39: =AE39/AE$2 -> #DIV/0! | AO39: =IFERROR(AN39/AM39,0) -> 0 | AP39: =AL39/AL$2 -> #DIV/0!
B40: 1x1 | F40: =IFERROR(E40/D40,0) -> 0 | G40: =C40/$C$2 -> #DIV/0! | M40: =IFERROR(L40/K40,0) -> 0 | N40: =J40/J$2 -> #DIV/0! | T40: =IFERROR(S40/R40,0) -> 0 | U40: =Q40/Q$2 -> #DIV/0! | AA40: =IFERROR(Z40/Y40,0) -> 0 | AB40: =X40/X$2 -> #DIV/0! | AH40: =IFERROR(AG40/AF40,0) -> 0 | AI40: =AE40/AE$2 -> #DIV/0! | AO40: =IFERROR(AN40/AM40,0) -> 0 | AP40: =AL40/AL$2 -> #DIV/0!
B41: 1x1 | F41: =IFERROR(E41/D41,0) -> 0 | G41: =C41/$C$2 -> #DIV/0! | M41: =IFERROR(L41/K41,0) -> 0 | N41: =J41/J$2 -> #DIV/0! | T41: =IFERROR(S41/R41,0) -> 0 | U41: =Q41/Q$2 -> #DIV/0! | AA41: =IFERROR(Z41/Y41,0) -> 0 | AB41: =X41/X$2 -> #DIV/0! | AH41: =IFERROR(AG41/AF41,0) -> 0 | AI41: =AE41/AE$2 -> #DIV/0! | AO41: =IFERROR(AN41/AM41,0) -> 0 | AP41: =AL41/AL$2 -> #DIV/0!
B42: 1x1 | F42: =IFERROR(E42/D42,0) -> 0 | G42: =C42/$C$2 -> #DIV/0! | M42: =IFERROR(L42/K42,0) -> 0 | N42: =J42/J$2 -> #DIV/0! | T42: =IFERROR(S42/R42,0) -> 0 | U42: =Q42/Q$2 -> #DIV/0! | AA42: =IFERROR(Z42/Y42,0) -> 0 | AB42: =X42/X$2 -> #DIV/0! | AH42: =IFERROR(AG42/AF42,0) -> 0 | AI42: =AE42/AE$2 -> #DIV/0! | AO42: =IFERROR(AN42/AM42,0) -> 0 | AP42: =AL42/AL$2 -> #DIV/0!
B43: 1x1 | F43: =IFERROR(E43/D43,0) -> 0 | G43: =C43/$C$2 -> #DIV/0! | M43: =IFERROR(L43/K43,0) -> 0 | N43: =J43/J$2 -> #DIV/0! | T43: =IFERROR(S43/R43,0) -> 0 | U43: =Q43/Q$2 -> #DIV/0! | AA43: =IFERROR(Z43/Y43,0) -> 0 | AB43: =X43/X$2 -> #DIV/0! | AH43: =IFERROR(AG43/AF43,0) -> 0 | AI43: =AE43/AE$2 -> #DIV/0! | AO43: =IFERROR(AN43/AM43,0) -> 0 | AP43: =AL43/AL$2 -> #DIV/0!
B44: 1x1 | F44: =IFERROR(E44/D44,0) -> 0 | G44: =C44/$C$2 -> #DIV/0! | M44: =IFERROR(L44/K44,0) -> 0 | N44: =J44/J$2 -> #DIV/0! | T44: =IFERROR(S44/R44,0) -> 0 | U44: =Q44/Q$2 -> #DIV/0! | AA44: =IFERROR(Z44/Y44,0) -> 0 | AB44: =X44/X$2 -> #DIV/0! | AH44: =IFERROR(AG44/AF44,0) -> 0 | AI44: =AE44/AE$2 -> #DIV/0! | AO44: =IFERROR(AN44/AM44,0) -> 0 | AP44: =AL44/AL$2 -> #DIV/0!
B45: 1x1 | F45: =IFERROR(E45/D45,0) -> 0 | G45: =C45/C$2 -> #DIV/0! | M45: =IFERROR(L45/K45,0) -> 0 | N45: =J45/J$2 -> #DIV/0! | T45: =IFERROR(S45/R45,0) -> 0 | U45: =Q45/Q$2 -> #DIV/0! | AA45: =IFERROR(Z45/Y45,0) -> 0 | AB45: =X45/X$2 -> #DIV/0! | AH45: =IFERROR(AG45/AF45,0) -> 0 | AI45: =AE45/AE$2 -> #DIV/0! | AO45: =IFERROR(AN45/AM45,0) -> 0 | AP45: =AL45/AL$2 -> #DIV/0!
B46: 1x1 | F46: =IFERROR(E46/D46,0) -> 0 | G46: =C46/C$2 -> #DIV/0! | M46: =IFERROR(L46/K46,0) -> 0 | N46: =J46/J$2 -> #DIV/0! | T46: =IFERROR(S46/R46,0) -> 0 | U46: =Q46/Q$2 -> #DIV/0! | AA46: =IFERROR(Z46/Y46,0) -> 0 | AB46: =X46/X$2 -> #DIV/0! | AH46: =IFERROR(AG46/AF46,0) -> 0 | AI46: =AE46/AE$2 -> #DIV/0! | AO46: =IFERROR(AN46/AM46,0) -> 0 | AP46: =AL46/AL$2 -> #DIV/0!
B47: 1x1 | F47: =IFERROR(E47/D47,0) -> 0 | G47: =C47/C$2 -> #DIV/0! | M47: =IFERROR(L47/K47,0) -> 0 | N47: =J47/J$2 -> #DIV/0! | T47: =IFERROR(S47/R47,0) -> 0 | U47: =Q47/Q$2 -> #DIV/0! | AA47: =IFERROR(Z47/Y47,0) -> 0 | AB47: =X47/X$2 -> #DIV/0! | AH47: =IFERROR(AG47/AF47,0) -> 0 | AI47: =AE47/AE$2 -> #DIV/0! | AO47: =IFERROR(AN47/AM47,0) -> 0 | AP47: =AL47/AL$2 -> #DIV/0!
B48: 1x1 | F48: =IFERROR(E48/D48,0) -> 0 | G48: =C48/C$2 -> #DIV/0! | M48: =IFERROR(L48/K48,0) -> 0 | N48: =J48/J$2 -> #DIV/0! | T48: =IFERROR(S48/R48,0) -> 0 | U48: =Q48/Q$2 -> #DIV/0! | AA48: =IFERROR(Z48/Y48,0) -> 0 | AB48: =X48/X$2 -> #DIV/0! | AH48: =IFERROR(AG48/AF48,0) -> 0 | AI48: =AE48/AE$2 -> #DIV/0! | AO48: =IFERROR(AN48/AM48,0) -> 0 | AP48: =AL48/AL$2 -> #DIV/0!
B49: 1x1 | F49: =IFERROR(E49/D49,0) -> 0 | G49: =C49/C$2 -> #DIV/0! | M49: =IFERROR(L49/K49,0) -> 0 | N49: =J49/J$2 -> #DIV/0! | T49: =IFERROR(S49/R49,0) -> 0 | U49: =Q49/Q$2 -> #DIV/0! | AA49: =IFERROR(Z49/Y49,0) -> 0 | AB49: =X49/X$2 -> #DIV/0! | AH49: =IFERROR(AG49/AF49,0) -> 0 | AI49: =AE49/AE$2 -> #DIV/0! | AO49: =IFERROR(AN49/AM49,0) -> 0 | AP49: =AL49/AL$2 -> #DIV/0!
B50: 1x1 | F50: =IFERROR(E50/D50,0) -> 0 | G50: =C50/C$2 -> #DIV/0! | M50: =IFERROR(L50/K50,0) -> 0 | N50: =J50/J$2 -> #DIV/0! | T50: =IFERROR(S50/R50,0) -> 0 | U50: =Q50/Q$2 -> #DIV/0! | AA50: =IFERROR(Z50/Y50,0) -> 0 | AB50: =X50/X$2 -> #DIV/0! | AH50: =IFERROR(AG50/AF50,0) -> 0 | AI50: =AE50/AE$2 -> #DIV/0! | AO50: =IFERROR(AN50/AM50,0) -> 0 | AP50: =AL50/AL$2 -> #DIV/0!
B51: 1x1 | F51: =IFERROR(E51/D51,0) -> 0 | G51: =C51/C$2 -> #DIV/0! | M51: =IFERROR(L51/K51,0) -> 0 | N51: =J51/J$2 -> #DIV/0! | T51: =IFERROR(S51/R51,0) -> 0 | U51: =Q51/Q$2 -> #DIV/0! | AA51: =IFERROR(Z51/Y51,0) -> 0 | AB51: =X51/X$2 -> #DIV/0! | AH51: =IFERROR(AG51/AF51,0) -> 0 | AI51: =AE51/AE$2 -> #DIV/0! | AO51: =IFERROR(AN51/AM51,0) -> 0 | AP51: =AL51/AL$2 -> #DIV/0!
B52: 1x1 | F52: =IFERROR(E52/D52,0) -> 0 | G52: =C52/C$2 -> #DIV/0! | M52: =IFERROR(L52/K52,0) -> 0 | N52: =J52/J$2 -> #DIV/0! | T52: =IFERROR(S52/R52,0) -> 0 | U52: =Q52/Q$2 -> #DIV/0! | AA52: =IFERROR(Z52/Y52,0) -> 0 | AB52: =X52/X$2 -> #DIV/0! | AH52: =IFERROR(AG52/AF52,0) -> 0 | AI52: =AE52/AE$2 -> #DIV/0! | AO52: =IFERROR(AN52/AM52,0) -> 0 | AP52: =AL52/AL$2 -> #DIV/0!
B53: 1x1 | F53: =IFERROR(E53/D53,0) -> 0 | G53: =C53/C$2 -> #DIV/0! | M53: =IFERROR(L53/K53,0) -> 0 | N53: =J53/J$2 -> #DIV/0! | T53: =IFERROR(S53/R53,0) -> 0 | U53: =Q53/Q$2 -> #DIV/0! | AA53: =IFERROR(Z53/Y53,0) -> 0 | AB53: =X53/X$2 -> #DIV/0! | AH53: =IFERROR(AG53/AF53,0) -> 0 | AI53: =AE53/AE$2 -> #DIV/0! | AO53: =IFERROR(AN53/AM53,0) -> 0 | AP53: =AL53/AL$2 -> #DIV/0!
B54: 1x1 | F54: =IFERROR(E54/D54,0) -> 0 | G54: =C54/C$2 -> #DIV/0! | M54: =IFERROR(L54/K54,0) -> 0 | N54: =J54/J$2 -> #DIV/0! | T54: =IFERROR(S54/R54,0) -> 0 | U54: =Q54/Q$2 -> #DIV/0! | AA54: =IFERROR(Z54/Y54,0) -> 0 | AB54: =X54/X$2 -> #DIV/0! | AH54: =IFERROR(AG54/AF54,0) -> 0 | AI54: =AE54/AE$2 -> #DIV/0! | AO54: =IFERROR(AN54/AM54,0) -> 0 | AP54: =AL54/AL$2 -> #DIV/0!
B55: 1x1 | F55: =IFERROR(E55/D55,0) -> 0 | G55: =C55/C$2 -> #DIV/0! | M55: =IFERROR(L55/K55,0) -> 0 | N55: =J55/J$2 -> #DIV/0! | T55: =IFERROR(S55/R55,0) -> 0 | U55: =Q55/Q$2 -> #DIV/0! | AA55: =IFERROR(Z55/Y55,0) -> 0 | AB55: =X55/X$2 -> #DIV/0! | AH55: =IFERROR(AG55/AF55,0) -> 0 | AI55: =AE55/AE$2 -> #DIV/0! | AO55: =IFERROR(AN55/AM55,0) -> 0 | AP55: =AL55/AL$2 -> #DIV/0!
B56: 1x1 | F56: =IFERROR(E56/D56,0) -> 0 | G56: =C56/C$2 -> #DIV/0! | M56: =IFERROR(L56/K56,0) -> 0 | N56: =J56/J$2 -> #DIV/0! | T56: =IFERROR(S56/R56,0) -> 0 | U56: =Q56/Q$2 -> #DIV/0! | AA56: =IFERROR(Z56/Y56,0) -> 0 | AB56: =X56/X$2 -> #DIV/0! | AH56: =IFERROR(AG56/AF56,0) -> 0 | AI56: =AE56/AE$2 -> #DIV/0! | AO56: =IFERROR(AN56/AM56,0) -> 0 | AP56: =AL56/AL$2 -> #DIV/0!
B57: Total | C57: =SUBTOTAL(9,C33:C56) -> 0 | D57: =SUMPRODUCT(D33:D56,C33:C56) -> 0 | E57: =SUMPRODUCT(E33:E56,C33:C56) -> 0 | F57: =IFERROR(E57/D57,0) -> 0 | I57: Total | J57: =SUBTOTAL(9,J33:J56) -> 0 | K57: =SUMPRODUCT(K33:K56,J33:J56) -> 0 | L57: =SUMPRODUCT(L33:L56,J33:J56) -> 0 | M57: =IFERROR(L57/K57,0) -> 0 | P57: Total | Q57: =SUBTOTAL(9,Q33:Q56) -> 0 | R57: =SUMPRODUCT(R33:R56,Q33:Q56) -> 0 | S57: =SUMPRODUCT(S33:S56,Q33:Q56) -> 0 | T57: =IFERROR(S57/R57,0) -> 0 | W57: Total | X57: =SUBTOTAL(9,X33:X56) -> 0 | Y57: =SUMPRODUCT(Y33:Y56,X33:X56) -> 0 | Z57: =SUMPRODUCT(Z33:Z56,X33:X56) -> 0 | AA57: =IFERROR(Z57/Y57,0) -> 0 | AD57: Total | AE57: =SUBTOTAL(9,AE33:AE56) -> 0 | AF57: =SUMPRODUCT(AF33:AF56,AE33:AE56) -> 0 | AG57: =SUMPRODUCT(AG33:AG56,AE33:AE56) -> 0 | AH57: =IFERROR(AG57/AF57,0) -> 0 | AK57: Total | AL57: =SUBTOTAL(9,AL33:AL56) -> 0 | AM57: =SUMPRODUCT(AM33:AM56,AL33:AL56) -> 0 | AN57: =SUMPRODUCT(AN33:AN56,AL33:AL56) -> 0 | AO57: =IFERROR(AN57/AM57,0) -> 0
B58: Average | D58: =IFERROR(D57/C57,0) -> 0 | E58: =IFERROR(E57/C57,0) -> 0 | F58: =IFERROR(E58/D58,0) -> 0 | I58: Average | K58: =IFERROR(K57/J57,0) -> 0 | L58: =IFERROR(L57/J57,0) -> 0 | M58: =IFERROR(L58/K58,0) -> 0 | P58: Average | R58: =IFERROR(R57/Q57,0) -> 0 | S58: =IFERROR(S57/Q57,0) -> 0 | T58: =IFERROR(S58/R58,0) -> 0 | W58: Average | Y58: =IFERROR(Y57/X57,0) -> 0 | Z58: =IFERROR(Z57/X57,0) -> 0 | AA58: =IFERROR(Z58/Y58,0) -> 0 | AD58: Average | AF58: =IFERROR(AF57/AE57,0) -> 0 | AG58: =IFERROR(AG57/AE57,0) -> 0 | AH58: =IFERROR(AG58/AF58,0) -> 0 | AK58: Average | AM58: =IFERROR(AM57/AL57,0) -> 0 | AN58: =IFERROR(AN57/AL57,0) -> 0 | AO58: =IFERROR(AN58/AM58,0) -> 0
A59: =+A58-E58 -> 0 | B59: Two Bedroom | I59: Two Bedroom | P59: Two Bedroom | W59: Two Bedroom | AD59: Two Bedroom | AK59: Two Bedroom
B60: Unit Type | C60: Units | D60: Square Feet | E60: Base Rent | F60: PSF | G60: % of Mix | I60: Unit Type | J60: Units | K60: Square Feet | L60: Base Rent | M60: PSF | N60: % of Mix | P60: Unit Type | Q60: Units | R60: Square Feet | S60: Base Rent | T60: PSF | U60: % of Mix | W60: Unit Type | X60: Units | Y60: Square Feet | Z60: Base Rent | AA60: PSF | AB60: % of Mix | AD60: Unit Type | AE60: Units | AF60: Square Feet | AG60: Base Rent | AH60: PSF | AI60: % of Mix | AK60: Unit Type | AL60: Units | AM60: Square Feet | AN60: Base Rent | AO60: PSF | AP60: % of Mix
B61: 2x2 | F61: =IFERROR(E61/D61,0) -> 0 | G61: =C61/$C$2 -> #DIV/0! | M61: =IFERROR(L61/K61,0) -> 0 | N61: =J61/J$2 -> #DIV/0! | T61: =IFERROR(S61/R61,0) -> 0 | U61: =Q61/Q$2 -> #DIV/0! | AA61: =IFERROR(Z61/Y61,0) -> 0 | AB61: =X61/X$2 -> #DIV/0! | AH61: =IFERROR(AG61/AF61,0) -> 0 | AI61: =AE61/AE$2 -> #DIV/0! | AO61: =IFERROR(AN61/AM61,0) -> 0 | AP61: =AL61/AL$2 -> #DIV/0!
B62: 2x2 | F62: =IFERROR(E62/D62,0) -> 0 | G62: =C62/$C$2 -> #DIV/0! | M62: =IFERROR(L62/K62,0) -> 0 | N62: =J62/J$2 -> #DIV/0! | T62: =IFERROR(S62/R62,0) -> 0 | U62: =Q62/Q$2 -> #DIV/0! | AA62: =IFERROR(Z62/Y62,0) -> 0 | AB62: =X62/X$2 -> #DIV/0! | AH62: =IFERROR(AG62/AF62,0) -> 0 | AI62: =AE62/AE$2 -> #DIV/0! | AO62: =IFERROR(AN62/AM62,0) -> 0 | AP62: =AL62/AL$2 -> #DIV/0!
B63: 2x2 | F63: =IFERROR(E63/D63,0) -> 0 | G63: =C63/$C$2 -> #DIV/0! | M63: =IFERROR(L63/K63,0) -> 0 | N63: =J63/J$2 -> #DIV/0! | T63: =IFERROR(S63/R63,0) -> 0 | U63: =Q63/Q$2 -> #DIV/0! | AA63: =IFERROR(Z63/Y63,0) -> 0 | AB63: =X63/X$2 -> #DIV/0! | AH63: =IFERROR(AG63/AF63,0) -> 0 | AI63: =AE63/AE$2 -> #DIV/0! | AO63: =IFERROR(AN63/AM63,0) -> 0 | AP63: =AL63/AL$2 -> #DIV/0!
B64: 2x2 | F64: =IFERROR(E64/D64,0) -> 0 | G64: =C64/$C$2 -> #DIV/0! | M64: =IFERROR(L64/K64,0) -> 0 | N64: =J64/J$2 -> #DIV/0! | T64: =IFERROR(S64/R64,0) -> 0 | U64: =Q64/Q$2 -> #DIV/0! | AA64: =IFERROR(Z64/Y64,0) -> 0 | AB64: =X64/X$2 -> #DIV/0! | AH64: =IFERROR(AG64/AF64,0) -> 0 | AI64: =AE64/AE$2 -> #DIV/0! | AO64: =IFERROR(AN64/AM64,0) -> 0 | AP64: =AL64/AL$2 -> #DIV/0!
B65: 2x2 | F65: =IFERROR(E65/D65,0) -> 0 | G65: =C65/$C$2 -> #DIV/0! | M65: =IFERROR(L65/K65,0) -> 0 | N65: =J65/J$2 -> #DIV/0! | T65: =IFERROR(S65/R65,0) -> 0 | U65: =Q65/Q$2 -> #DIV/0! | AA65: =IFERROR(Z65/Y65,0) -> 0 | AB65: =X65/X$2 -> #DIV/0! | AH65: =IFERROR(AG65/AF65,0) -> 0 | AI65: =AE65/AE$2 -> #DIV/0! | AO65: =IFERROR(AN65/AM65,0) -> 0 | AP65: =AL65/AL$2 -> #DIV/0!
B66: 2x2 | F66: =IFERROR(E66/D66,0) -> 0 | G66: =C66/$C$2 -> #DIV/0! | M66: =IFERROR(L66/K66,0) -> 0 | N66: =J66/J$2 -> #DIV/0! | T66: =IFERROR(S66/R66,0) -> 0 | U66: =Q66/Q$2 -> #DIV/0! | AA66: =IFERROR(Z66/Y66,0) -> 0 | AB66: =X66/X$2 -> #DIV/0! | AH66: =IFERROR(AG66/AF66,0) -> 0 | AI66: =AE66/AE$2 -> #DIV/0! | AO66: =IFERROR(AN66/AM66,0) -> 0 | AP66: =AL66/AL$2 -> #DIV/0!
B67: 2x2 | F67: =IFERROR(E67/D67,0) -> 0 | G67: =C67/$C$2 -> #DIV/0! | M67: =IFERROR(L67/K67,0) -> 0 | N67: =J67/J$2 -> #DIV/0! | T67: =IFERROR(S67/R67,0) -> 0 | U67: =Q67/Q$2 -> #DIV/0! | AA67: =IFERROR(Z67/Y67,0) -> 0 | AB67: =X67/X$2 -> #DIV/0! | AH67: =IFERROR(AG67/AF67,0) -> 0 | AI67: =AE67/AE$2 -> #DIV/0! | AO67: =IFERROR(AN67/AM67,0) -> 0 | AP67: =AL67/AL$2 -> #DIV/0!
B68: 2x2 | F68: =IFERROR(E68/D68,0) -> 0 | G68: =C68/$C$2 -> #DIV/0! | M68: =IFERROR(L68/K68,0) -> 0 | N68: =J68/J$2 -> #DIV/0! | T68: =IFERROR(S68/R68,0) -> 0 | U68: =Q68/Q$2 -> #DIV/0! | AA68: =IFERROR(Z68/Y68,0) -> 0 | AB68: =X68/X$2 -> #DIV/0! | AH68: =IFERROR(AG68/AF68,0) -> 0 | AI68: =AE68/AE$2 -> #DIV/0! | AO68: =IFERROR(AN68/AM68,0) -> 0 | AP68: =AL68/AL$2 -> #DIV/0!
B69: 2x2 | F69: =IFERROR(E69/D69,0) -> 0 | G69: =C69/$C$2 -> #DIV/0! | M69: =IFERROR(L69/K69,0) -> 0 | N69: =J69/J$2 -> #DIV/0! | T69: =IFERROR(S69/R69,0) -> 0 | U69: =Q69/Q$2 -> #DIV/0! | AA69: =IFERROR(Z69/Y69,0) -> 0 | AB69: =X69/X$2 -> #DIV/0! | AH69: =IFERROR(AG69/AF69,0) -> 0 | AI69: =AE69/AE$2 -> #DIV/0! | AO69: =IFERROR(AN69/AM69,0) -> 0 | AP69: =AL69/AL$2 -> #DIV/0!
B70: 2x2 | F70: =IFERROR(E70/D70,0) -> 0 | G70: =C70/$C$2 -> #DIV/0! | M70: =IFERROR(L70/K70,0) -> 0 | N70: =J70/J$2 -> #DIV/0! | T70: =IFERROR(S70/R70,0) -> 0 | U70: =Q70/Q$2 -> #DIV/0! | AA70: =IFERROR(Z70/Y70,0) -> 0 | AB70: =X70/X$2 -> #DIV/0! | AH70: =IFERROR(AG70/AF70,0) -> 0 | AI70: =AE70/AE$2 -> #DIV/0! | AO70: =IFERROR(AN70/AM70,0) -> 0 | AP70: =AL70/AL$2 -> #DIV/0!
B71: 2x2 | F71: =IFERROR(E71/D71,0) -> 0 | G71: =C71/$C$2 -> #DIV/0! | M71: =IFERROR(L71/K71,0) -> 0 | N71: =J71/J$2 -> #DIV/0! | T71: =IFERROR(S71/R71,0) -> 0 | U71: =Q71/Q$2 -> #DIV/0! | AA71: =IFERROR(Z71/Y71,0) -> 0 | AB71: =X71/X$2 -> #DIV/0! | AH71: =IFERROR(AG71/AF71,0) -> 0 | AI71: =AE71/AE$2 -> #DIV/0! | AO71: =IFERROR(AN71/AM71,0) -> 0 | AP71: =AL71/AL$2 -> #DIV/0!
B72: 2x2 | F72: =IFERROR(E72/D72,0) -> 0 | G72: =C72/$C$2 -> #DIV/0! | M72: =IFERROR(L72/K72,0) -> 0 | N72: =J72/J$2 -> #DIV/0! | T72: =IFERROR(S72/R72,0) -> 0 | U72: =Q72/Q$2 -> #DIV/0! | AA72: =IFERROR(Z72/Y72,0) -> 0 | AB72: =X72/X$2 -> #DIV/0! | AH72: =IFERROR(AG72/AF72,0) -> 0 | AI72: =AE72/AE$2 -> #DIV/0! | AO72: =IFERROR(AN72/AM72,0) -> 0 | AP72: =AL72/AL$2 -> #DIV/0!
... B84: 2x2 | F84: =IFERROR(E84/D84,0) -> 0 | G84: =C84/$C$2 -> #DIV/0! | M84: =IFERROR(L84/K84,0) -> 0 | N84: =J84/J$2 -> #DIV/0! | T84: =IFERROR(S84/R84,0) -> 0 | U84: =Q84/Q$2 -> #DIV/0! | AA84: =IFERROR(Z84/Y84,0) -> 0 | AB84: =X84/X$2 -> #DIV/0! | AH84: =IFERROR(AG84/AF84,0) -> 0 | AI84: =AE84/AE$2 -> #DIV/0! | AO84: =IFERROR(AN84/AM84,0) -> 0 | AP84: =AL84/AL$2 -> #DIV/0!
B85: Total | C85: =SUBTOTAL(9,C61:C84) -> 0 | D85: =SUMPRODUCT(D61:D84,C61:C84) -> 0 | E85: =SUMPRODUCT(E61:E84,C61:C84) -> 0 | F85: =IFERROR(E85/D85,0) -> 0 | I85: Total | J85: =SUBTOTAL(9,J61:J84) -> 0 | K85: =SUMPRODUCT(K61:K84,J61:J84) -> 0 | L85: =SUMPRODUCT(L61:L84,J61:J84) -> 0 | M85: =IFERROR(L85/K85,0) -> 0 | P85: Total | Q85: =SUBTOTAL(9,Q61:Q84) -> 0 | R85: =SUMPRODUCT(R61:R84,Q61:Q84) -> 0 | S85: =SUMPRODUCT(S61:S84,Q61:Q84) -> 0 | T85: =IFERROR(S85/R85,0) -> 0 | W85: Total | X85: =SUBTOTAL(9,X61:X84) -> 0 | Y85: =SUMPRODUCT(Y61:Y84,X61:X84) -> 0 | Z85: =SUMPRODUCT(Z61:Z84,X61:X84) -> 0 | AA85: =IFERROR(Z85/Y85,0) -> 0 | AD85: Total | AE85: =SUBTOTAL(9,AE61:AE84) -> 0 | AF85: =SUMPRODUCT(AF61:AF84,AE61:AE84) -> 0 | AG85: =SUMPRODUCT(AG61:AG84,AE61:AE84) -> 0 | AH85: =IFERROR(AG85/AF85,0) -> 0 | AK85: Total | AL85: =SUBTOTAL(9,AL61:AL84) -> 0 | AM85: =SUMPRODUCT(AM61:AM84,AL61:AL84) -> 0 | AN85: =SUMPRODUCT(AN61:AN84,AL61:AL84) -> 0 | AO85: =IFERROR(AN85/AM85,0) -> 0
B86: Average | D86: =IFERROR(D85/C85,0) -> 0 | E86: =IFERROR(E85/C85,0) -> 0 | F86: =IFERROR(E86/D86,0) -> 0 | I86: Average | K86: =IFERROR(K85/J85,0) -> 0 | L86: =IFERROR(L85/J85,0) -> 0 | M86: =IFERROR(L86/K86,0) -> 0 | P86: Average | R86: =IFERROR(R85/Q85,0) -> 0 | S86: =IFERROR(S85/Q85,0) -> 0 | T86: =IFERROR(S86/R86,0) -> 0 | W86: Average | Y86: =IFERROR(Y85/X85,0) -> 0 | Z86: =IFERROR(Z85/X85,0) -> 0 | AA86: =IFERROR(Z86/Y86,0) -> 0 | AD86: Average | AF86: =IFERROR(AF85/AE85,0) -> 0 | AG86: =IFERROR(AG85/AE85,0) -> 0 | AH86: =IFERROR(AG86/AF86,0) -> 0 | AK86: Average | AM86: =IFERROR(AM85/AL85,0) -> 0 | AN86: =IFERROR(AN85/AL85,0) -> 0 | AO86: =IFERROR(AN86/AM86,0) -> 0
A87: =+A86-E86 -> 0 | B87: Three Bedroom | I87: Three Bedroom | P87: Three Bedroom | W87: Three Bedroom | AD87: Three Bedroom | AK87: Three Bedroom
B88: Unit Type | C88: Units | D88: Square Feet | E88: Base Rent | F88: PSF | G88: % of Mix | I88: Unit Type | J88: Units | K88: Square Feet | L88: Base Rent | M88: PSF | N88: % of Mix | P88: Unit Type | Q88: Units | R88: Square Feet | S88: Base Rent | T88: PSF | U88: % of Mix | W88: Unit Type | X88: Units | Y88: Square Feet | Z88: Base Rent | AA88: PSF | AB88: % of Mix | AD88: Unit Type | AE88: Units | AF88: Square Feet | AG88: Base Rent | AH88: PSF | AI88: % of Mix | AK88: Unit Type | AL88: Units | AM88: Square Feet | AN88: Base Rent | AO88: PSF | AP88: % of Mix
B89: 3x2 | F89: =IFERROR(E89/D89,0) -> 0 | G89: =C89/$C$2 -> #DIV/0! | M89: =IFERROR(L89/K89,0) -> 0 | N89: =J89/J$2 -> #DIV/0! | T89: =IFERROR(S89/R89,0) -> 0 | U89: =Q89/Q$2 -> #DIV/0! | AA89: =IFERROR(Z89/Y89,0) -> 0 | AB89: =X89/X$2 -> #DIV/0! | AH89: =IFERROR(AG89/AF89,0) -> 0 | AI89: =AE89/AE$2 -> #DIV/0! | AO89: =IFERROR(AN89/AM89,0) -> 0 | AP89: =AL89/AL$2 -> #DIV/0!
B90: 3x2 | F90: =IFERROR(E90/D90,0) -> 0 | G90: =C90/$C$2 -> #DIV/0! | M90: =IFERROR(L90/K90,0) -> 0 | N90: =J90/J$2 -> #DIV/0! | T90: =IFERROR(S90/R90,0) -> 0 | U90: =Q90/Q$2 -> #DIV/0! | AA90: =IFERROR(Z90/Y90,0) -> 0 | AB90: =X90/X$2 -> #DIV/0! | AH90: =IFERROR(AG90/AF90,0) -> 0 | AI90: =AE90/AE$2 -> #DIV/0! | AO90: =IFERROR(AN90/AM90,0) -> 0 | AP90: =AL90/AL$2 -> #DIV/0!
B91: 3x2 | F91: =IFERROR(E91/D91,0) -> 0 | G91: =C91/$C$2 -> #DIV/0! | M91: =IFERROR(L91/K91,0) -> 0 | N91: =J91/J$2 -> #DIV/0! | T91: =IFERROR(S91/R91,0) -> 0 | U91: =Q91/Q$2 -> #DIV/0! | AA91: =IFERROR(Z91/Y91,0) -> 0 | AB91: =X91/X$2 -> #DIV/0! | AH91: =IFERROR(AG91/AF91,0) -> 0 | AI91: =AE91/AE$2 -> #DIV/0! | AO91: =IFERROR(AN91/AM91,0) -> 0 | AP91: =AL91/AL$2 -> #DIV/0!
B92: 3x2 | F92: =IFERROR(E92/D92,0) -> 0 | G92: =C92/$C$2 -> #DIV/0! | M92: =IFERROR(L92/K92,0) -> 0 | N92: =J92/J$2 -> #DIV/0! | T92: =IFERROR(S92/R92,0) -> 0 | U92: =Q92/Q$2 -> #DIV/0! | AA92: =IFERROR(Z92/Y92,0) -> 0 | AB92: =X92/X$2 -> #DIV/0! | AH92: =IFERROR(AG92/AF92,0) -> 0 | AI92: =AE92/AE$2 -> #DIV/0! | AO92: =IFERROR(AN92/AM92,0) -> 0 | AP92: =AL92/AL$2 -> #DIV/0!
B93: 3x2 | F93: =IFERROR(E93/D93,0) -> 0 | G93: =C93/$C$2 -> #DIV/0! | M93: =IFERROR(L93/K93,0) -> 0 | N93: =J93/J$2 -> #DIV/0! | T93: =IFERROR(S93/R93,0) -> 0 | U93: =Q93/Q$2 -> #DIV/0! | AA93: =IFERROR(Z93/Y93,0) -> 0 | AB93: =X93/X$2 -> #DIV/0! | AH93: =IFERROR(AG93/AF93,0) -> 0 | AI93: =AE93/AE$2 -> #DIV/0! | AO93: =IFERROR(AN93/AM93,0) -> 0 | AP93: =AL93/AL$2 -> #DIV/0!
B94: 3x2 | F94: =IFERROR(E94/D94,0) -> 0 | G94: =C94/$C$2 -> #DIV/0! | M94: =IFERROR(L94/K94,0) -> 0 | N94: =J94/J$2 -> #DIV/0! | T94: =IFERROR(S94/R94,0) -> 0 | U94: =Q94/Q$2 -> #DIV/0! | AA94: =IFERROR(Z94/Y94,0) -> 0 | AB94: =X94/X$2 -> #DIV/0! | AH94: =IFERROR(AG94/AF94,0) -> 0 | AI94: =AE94/AE$2 -> #DIV/0! | AO94: =IFERROR(AN94/AM94,0) -> 0 | AP94: =AL94/AL$2 -> #DIV/0!
B95: 3x2 | F95: =IFERROR(E95/D95,0) -> 0 | G95: =C95/$C$2 -> #DIV/0! | M95: =IFERROR(L95/K95,0) -> 0 | N95: =J95/J$2 -> #DIV/0! | T95: =IFERROR(S95/R95,0) -> 0 | U95: =Q95/Q$2 -> #DIV/0! | AA95: =IFERROR(Z95/Y95,0) -> 0 | AB95: =X95/X$2 -> #DIV/0! | AH95: =IFERROR(AG95/AF95,0) -> 0 | AI95: =AE95/AE$2 -> #DIV/0! | AO95: =IFERROR(AN95/AM95,0) -> 0 | AP95: =AL95/AL$2 -> #DIV/0!
B96: 3x2 | F96: =IFERROR(E96/D96,0) -> 0 | G96: =C96/$C$2 -> #DIV/0! | M96: =IFERROR(L96/K96,0) -> 0 | N96: =J96/J$2 -> #DIV/0! | T96: =IFERROR(S96/R96,0) -> 0 | U96: =Q96/Q$2 -> #DIV/0! | AA96: =IFERROR(Z96/Y96,0) -> 0 | AB96: =X96/X$2 -> #DIV/0! | AH96: =IFERROR(AG96/AF96,0) -> 0 | AI96: =AE96/AE$2 -> #DIV/0! | AO96: =IFERROR(AN96/AM96,0) -> 0 | AP96: =AL96/AL$2 -> #DIV/0!
B97: 3x2 | F97: =IFERROR(E97/D97,0) -> 0 | G97: =C97/$C$2 -> #DIV/0! | M97: =IFERROR(L97/K97,0) -> 0 | N97: =J97/J$2 -> #DIV/0! | T97: =IFERROR(S97/R97,0) -> 0 | U97: =Q97/Q$2 -> #DIV/0! | AA97: =IFERROR(Z97/Y97,0) -> 0 | AB97: =X97/X$2 -> #DIV/0! | AH97: =IFERROR(AG97/AF97,0) -> 0 | AI97: =AE97/AE$2 -> #DIV/0! | AO97: =IFERROR(AN97/AM97,0) -> 0 | AP97: =AL97/AL$2 -> #DIV/0!
B98: 3x2 | F98: =IFERROR(E98/D98,0) -> 0 | G98: =C98/$C$2 -> #DIV/0! | M98: =IFERROR(L98/K98,0) -> 0 | N98: =J98/J$2 -> #DIV/0! | T98: =IFERROR(S98/R98,0) -> 0 | U98: =Q98/Q$2 -> #DIV/0! | AA98: =IFERROR(Z98/Y98,0) -> 0 | AB98: =X98/X$2 -> #DIV/0! | AH98: =IFERROR(AG98/AF98,0) -> 0 | AI98: =AE98/AE$2 -> #DIV/0! | AO98: =IFERROR(AN98/AM98,0) -> 0 | AP98: =AL98/AL$2 -> #DIV/0!
B99: 3x2 | F99: =IFERROR(E99/D99,0) -> 0 | G99: =C99/$C$2 -> #DIV/0! | M99: =IFERROR(L99/K99,0) -> 0 | N99: =J99/J$2 -> #DIV/0! | T99: =IFERROR(S99/R99,0) -> 0 | U99: =Q99/Q$2 -> #DIV/0! | AA99: =IFERROR(Z99/Y99,0) -> 0 | AB99: =X99/X$2 -> #DIV/0! | AH99: =IFERROR(AG99/AF99,0) -> 0 | AI99: =AE99/AE$2 -> #DIV/0! | AO99: =IFERROR(AN99/AM99,0) -> 0 | AP99: =AL99/AL$2 -> #DIV/0!
B100: 3x2 | F100: =IFERROR(E100/D100,0) -> 0 | G100: =C100/$C$2 -> #DIV/0! | M100: =IFERROR(L100/K100,0) -> 0 | N100: =J100/J$2 -> #DIV/0! | T100: =IFERROR(S100/R100,0) -> 0 | U100: =Q100/Q$2 -> #DIV/0! | AA100: =IFERROR(Z100/Y100,0) -> 0 | AB100: =X100/X$2 -> #DIV/0! | AH100: =IFERROR(AG100/AF100,0) -> 0 | AI100: =AE100/AE$2 -> #DIV/0! | AO100: =IFERROR(AN100/AM100,0) -> 0 | AP100: =AL100/AL$2 -> #DIV/0!
B101: Total | C101: =SUBTOTAL(9,C89:C100) -> 0 | D101: =SUMPRODUCT(D89:D100,C89:C100) -> 0 | E101: =SUMPRODUCT(E89:E100,C89:C100) -> 0 | F101: =IFERROR(E101/D101,0) -> 0 | I101: Total | J101: =SUBTOTAL(9,J89:J100) -> 0 | K101: =SUMPRODUCT(K89:K100,J89:J100) -> 0 | L101: =SUMPRODUCT(L89:L100,J89:J100) -> 0 | M101: =IFERROR(L101/K101,0) -> 0 | P101: Total | Q101: =SUBTOTAL(9,Q89:Q100) -> 0 | R101: =SUMPRODUCT(R89:R100,Q89:Q100) -> 0 | S101: =SUMPRODUCT(S89:S100,Q89:Q100) -> 0 | T101: =IFERROR(S101/R101,0) -> 0 | W101: Total | X101: =SUBTOTAL(9,X89:X100) -> 0 | Y101: =SUMPRODUCT(Y89:Y100,X89:X100) -> 0 | Z101: =SUMPRODUCT(Z89:Z100,X89:X100) -> 0 | AA101: =IFERROR(Z101/Y101,0) -> 0 | AD101: Total | AE101: =SUBTOTAL(9,AE89:AE100) -> 0 | AF101: =SUMPRODUCT(AF89:AF100,AE89:AE100) -> 0 | AG101: =SUMPRODUCT(AG89:AG100,AE89:AE100) -> 0 | AH101: =IFERROR(AG101/AF101,0) -> 0 | AK101: Total | AL101: =SUBTOTAL(9,AL89:AL100) -> 0 | AM101: =SUMPRODUCT(AM89:AM100,AL89:AL100) -> 0 | AN101: =SUMPRODUCT(AN89:AN100,AL89:AL100) -> 0 | AO101: =IFERROR(AN101/AM101,0) -> 0
B102: Average | D102: =IFERROR(D101/C101,) -> 0 | E102: =IFERROR(E101/C101,0) -> 0 | F102: =IFERROR(E102/D102,0) -> 0 | I102: Average | K102: =IFERROR(K101/J101,) -> 0 | L102: =IFERROR(L101/J101,0) -> 0 | M102: =IFERROR(L102/K102,0) -> 0 | P102: Average | R102: =IFERROR(R101/Q101,) -> 0 | S102: =IFERROR(S101/Q101,0) -> 0 | T102: =IFERROR(S102/R102,0) -> 0 | W102: Average | Y102: =IFERROR(Y101/X101,) -> 0 | Z102: =IFERROR(Z101/X101,0) -> 0 | AA102: =IFERROR(Z102/Y102,0) -> 0 | AD102: Average | AF102: =IFERROR(AF101/AE101,) -> 0 | AG102: =IFERROR(AG101/AE101,0) -> 0 | AH102: =IFERROR(AG102/AF102,0) -> 0 | AK102: Average | AM102: =IFERROR(AM101/AL101,) -> 0 | AN102: =IFERROR(AN101/AL101,0) -> 0 | AO102: =IFERROR(AN102/AM102,0) -> 0
A103: =+A102-E102 -> 0
B104: Property Mix Total | C104: Units | D104: SF | E104: Rent | F104: PSF | G104: % of Mix | I104: Property Mix Total | J104: Units | K104: SF | L104: Rent | M104: PSF | N104: % of Mix | P104: Property Mix Total | Q104: Units | R104: SF | S104: Rent | T104: PSF | U104: % of Mix | W104: Property Mix Total | X104: Units | Y104: SF | Z104: Rent | AA104: PSF | AB104: % of Mix | AD104: Property Mix Total | AE104: Units | AF104: SF | AG104: Rent | AH104: PSF | AI104: % of Mix | AK104: Property Mix Total | AL104: Units | AM104: SF | AN104: Rent | AO104: PSF | AP104: % of Mix
B105: Efficiency | C105: =+C28 -> 0 | D105: =D29 -> 0 | E105: =E29 -> 0 | F105: =IFERROR(E105/D105,0) -> 0 | G105: =C105/C2 -> #DIV/0! | I105: Efficiency | J105: =+J28 -> 0 | K105: =K29 -> 0 | L105: =L29 -> 0 | M105: =IFERROR(L105/K105,0) -> 0 | N105: =J105/J2 -> #DIV/0! | P105: Efficiency | Q105: =+Q28 -> 0 | R105: =R29 -> 0 | S105: =S29 -> 0 | T105: =IFERROR(S105/R105,0) -> 0 | U105: =Q105/Q2 -> #DIV/0! | W105: Efficiency | X105: =+X28 -> 0 | Y105: =Y29 -> 0 | Z105: =Z29 -> 0 | AA105: =IFERROR(Z105/Y105,0) -> 0 | AB105: =X105/X2 -> #DIV/0! | AD105: Efficiency | AE105: =+AE28 -> 0 | AF105: =AF29 -> 0 | AG105: =AG29 -> 0 | AH105: =IFERROR(AG105/AF105,0) -> 0 | AI105: =AE105/AE2 -> #DIV/0! | AK105: Efficiency | AL105: =+AL28 -> 0 | AM105: =AM29 -> 0 | AN105: =AN29 -> 0 | AO105: =IFERROR(AN105/AM105,0) -> 0 | AP105: =AL105/AL2 -> #DIV/0!
B106: 1 Bedroom | C106: =C57 -> 0 | D106: =D58 -> 0 | E106: =E58 -> 0 | F106: =IFERROR(E106/D106,0) -> 0 | G106: =C106/C2 -> #DIV/0! | I106: 1 Bedroom | J106: =J57 -> 0 | K106: =K58 -> 0 | L106: =L58 -> 0 | M106: =IFERROR(L106/K106,0) -> 0 | N106: =J106/J2 -> #DIV/0! | P106: 1 Bedroom | Q106: =Q57 -> 0 | R106: =R58 -> 0 | S106: =S58 -> 0 | T106: =IFERROR(S106/R106,0) -> 0 | U106: =Q106/Q2 -> #DIV/0! | W106: 1 Bedroom | X106: =X57 -> 0 | Y106: =Y58 -> 0 | Z106: =Z58 -> 0 | AA106: =IFERROR(Z106/Y106,0) -> 0 | AB106: =X106/X2 -> #DIV/0! | AD106: 1 Bedroom | AE106: =AE57 -> 0 | AF106: =AF58 -> 0 | AG106: =AG58 -> 0 | AH106: =IFERROR(AG106/AF106,0) -> 0 | AI106: =AE106/AE2 -> #DIV/0! | AK106: 1 Bedroom | AL106: =AL57 -> 0 | AM106: =AM58 -> 0 | AN106: =AN58 -> 0 | AO106: =IFERROR(AN106/AM106,0) -> 0 | AP106: =AL106/AL2 -> #DIV/0!
B107: 2 Bedroom | C107: =C85 -> 0 | D107: =D86 -> 0 | E107: =E86 -> 0 | F107: =IFERROR(E107/D107,0) -> 0 | G107: =C107/C2 -> #DIV/0! | I107: 2 Bedroom | J107: =J85 -> 0 | K107: =K86 -> 0 | L107: =L86 -> 0 | M107: =IFERROR(L107/K107,0) -> 0 | N107: =J107/J2 -> #DIV/0! | P107: 2 Bedroom | Q107: =Q85 -> 0 | R107: =R86 -> 0 | S107: =S86 -> 0 | T107: =IFERROR(S107/R107,0) -> 0 | U107: =Q107/Q2 -> #DIV/0! | W107: 2 Bedroom | X107: =X85 -> 0 | Y107: =Y86 -> 0 | Z107: =Z86 -> 0 | AA107: =IFERROR(Z107/Y107,0) -> 0 | AB107: =X107/X2 -> #DIV/0! | AD107: 2 Bedroom | AE107: =AE85 -> 0 | AF107: =AF86 -> 0 | AG107: =AG86 -> 0 | AH107: =IFERROR(AG107/AF107,0) -> 0 | AI107: =AE107/AE2 -> #DIV/0! | AK107: 2 Bedroom | AL107: =AL85 -> 0 | AM107: =AM86 -> 0 | AN107: =AN86 -> 0 | AO107: =IFERROR(AN107/AM107,0) -> 0 | AP107: =AL107/AL2 -> #DIV/0!
B108: 3 Bedroom | C108: =C101 -> 0 | D108: =D102 -> 0 | E108: =E102 -> 0 | F108: =IFERROR(E108/D108,0) -> 0 | G108: =C108/C2 -> #DIV/0! | I108: 3 Bedroom | J108: =J101 -> 0 | K108: =K102 -> 0 | L108: =L102 -> 0 | M108: =IFERROR(L108/K108,0) -> 0 | N108: =J108/J2 -> #DIV/0! | P108: 3 Bedroom | Q108: =Q101 -> 0 | R108: =R102 -> 0 | S108: =S102 -> 0 | T108: =IFERROR(S108/R108,0) -> 0 | U108: =Q108/Q2 -> #DIV/0! | W108: 3 Bedroom | X108: =X101 -> 0 | Y108: =Y102 -> 0 | Z108: =Z102 -> 0 | AA108: =IFERROR(Z108/Y108,0) -> 0 | AB108: =X108/X2 -> #DIV/0! | AD108: 3 Bedroom | AE108: =AE101 -> 0 | AF108: =AF102 -> 0 | AG108: =AG102 -> 0 | AH108: =IFERROR(AG108/AF108,0) -> 0 | AI108: =AE108/AE2 -> #DIV/0! | AK108: 3 Bedroom | AL108: =AL101 -> 0 | AM108: =AM102 -> 0 | AN108: =AN102 -> 0 | AO108: =IFERROR(AN108/AM108,0) -> 0 | AP108: =AL108/AL2 -> #DIV/0!
B109: Total/Average | C109: =SUM(C105:C108) -> 0 | D109: =IFERROR(SUMPRODUCT(D105:D108,C105:C108)/C109,0) -> 0 | E109: =IFERROR(SUMPRODUCT(E105:E108,C105:C108)/C109,0) -> 0 | F109: =IFERROR(SUMPRODUCT(F105:F108,C105:C108)/C109,0) -> 0 | G109: =SUM(G105:G108) -> #DIV/0! | I109: Total/Average | J109: =SUM(J105:J108) -> 0 | K109: =IFERROR(SUMPRODUCT(K105:K108,J105:J108)/J109,0) -> 0 | L109: =IFERROR(SUMPRODUCT(L105:L108,J105:J108)/J109,0) -> 0 | M109: =IFERROR(SUMPRODUCT(M105:M108,J105:J108)/J109,0) -> 0 | N109: =SUM(N105:N108) -> #DIV/0! | P109: Total/Average | Q109: =SUM(Q105:Q108) -> 0 | R109: =IFERROR(SUMPRODUCT(R105:R108,Q105:Q108)/Q109,0) -> 0 | S109: =IFERROR(SUMPRODUCT(S105:S108,Q105:Q108)/Q109,0) -> 0 | T109: =IFERROR(SUMPRODUCT(T105:T108,Q105:Q108)/Q109,0) -> 0 | U109: =SUM(U105:U108) -> #DIV/0! | W109: Total/Average | X109: =SUM(X105:X108) -> 0 | Y109: =IFERROR(SUMPRODUCT(Y105:Y108,X105:X108)/X109,0) -> 0 | Z109: =IFERROR(SUMPRODUCT(Z105:Z108,X105:X108)/X109,0) -> 0 | AA109: =IFERROR(SUMPRODUCT(AA105:AA108,X105:X108)/X109,0) -> 0 | AB109: =SUM(AB105:AB108) -> #DIV/0! | AD109: Total/Average | AE109: =SUM(AE105:AE108) -> 0 | AF109: =IFERROR(SUMPRODUCT(AF105:AF108,AE105:AE108)/AE109,0) -> 0 | AG109: =IFERROR(SUMPRODUCT(AG105:AG108,AE105:AE108)/AE109,0) -> 0 | AH109: =IFERROR(SUMPRODUCT(AH105:AH108,AE105:AE108)/AE109,0) -> 0 | AI109: =SUM(AI105:AI108) -> #DIV/0! | AK109: Total/Average | AL109: =SUM(AL105:AL108) -> 0 | AM109: =IFERROR(SUMPRODUCT(AM105:AM108,AL105:AL108)/AL109,0) -> 0 | AN109: =IFERROR(SUMPRODUCT(AN105:AN108,AL105:AL108)/AL109,0) -> 0 | AO109: =IFERROR(SUMPRODUCT(AO105:AO108,AL105:AL108)/AL109,0) -> 0 | AP109: =SUM(AP105:AP108) -> #DIV/0!
B110: Notes: | I110: Notes: | P110: Notes: | W110: Notes: | AD110: Notes: | AK110: Notes:
